Workbook

Sheet Cover
H7: Scenario Switchboard
H9: Revenue & Operating Expenses
H10: Business Segment
D11: Valuation Date: | E11: =TODAY() -> 46005 | H11: Global industrial rev(US) | I11: 2
D12: Company Name: | E12: ECOLAB inc. | H12: Global inst& spec rev(US) | I12: 2
D13: Sector: | E13: Materials | H13: Global industrial COS(US) | I13: 2
D14: Industry: | E14: Chemicals | H14: Global inst& spec COS(US) | I14: 2
D15: Rating: | E15: =IF(E23>Ke!D38,"BUY","SELL") -> SELL | H15: Goodwill | I15: 2
H16: Global industrial rev(EU) | I16: 2
D17: Current Price | E17: =DCF!B6 -> 280.06 | H17: Scenario Key
D18: Valuation Price | E18: =DCF!B24 -> 135.22598 | H18: Bull | I18: 1
D19: 12-month Valuation Price | E19: =DCF!B46 -> 140.65169 | H19: Base | I19: 2
D20: Valuation Appreciation | E20: =E18/E17-1 -> -0.51715354 | H20: Bear | I20: 3
D21: 12-mo Valuation Appreciation | E21: =E19/E17-1 -> -0.49778015
D22: Dividend Yield | E22: 0.0093
D23: Total | E23: =E21+E22 -> -0.48848015

Sheet DCF
A1: #VALUE!
H2: Share count in Millions
A3: Cost of Equity | B3: =Ke!D38 -> 0.099113049 | G3: =TODAY() -> 46005 | H3: Today | I3: =Schedules!B21 -> 282
A4: Number of Shares in thousands: | B4: =I3 -> 282 | G4: =G3+365 -> 46370 | H4: One year | I4: =Schedules!C21 -> 281.23836
G5: =G4+366 -> 46736 | H5: Two year | I5: =Schedules!D21 -> 280.60262
A6: Actual Price: | B6: 280.06 | C6: At close oct 08, 2025
G7: Price Appreciation
A8: Model Valuation: | B8: =B24 -> 135.22598 | G8: Price Appreciation | I8: =B8/$B$6-1 -> -0.51715354
A9: Model 12 Month Price Target: | B9: =B46 -> 140.65169 | G9: Price Appreciation (12 month) | I9: =B9/B6-1 -> -0.49778015
A12: Model Current Valuation with Sensitivity of Ke
C14: 46022 | D14: 46387 | E14: 46752 | F14: 47118 | G14: 47483
A15: Time period (years) | C15: =MAX((C14-$G$3)/365,0) -> 0.046575342 | D15: =MAX((D14-$G$3)/365,0) -> 1.0465753 | E15: =MAX((E14-$G$3)/365,0) -> 2.0465753 | F15: =MAX((F14-$G$3)/365,0) -> 3.0493151 | G15: =MAX((G14-$G$3)/365,0) -> 4.0493151
A16: Nominal FCFE: | C16: ='Cash flow'!F49 -> 2706.2239 | D16: ='Cash flow'!G49 -> 2337.3471 | E16: ='Cash flow'!H49 -> 2579.8435 | F16: ='Cash flow'!I49 -> 2748.9918 | G16: ='Cash flow'!J49 -> 3134.4489
A17: PV FCFE: | C17: =(C16*C15)/((1+$B$3)^C15) -> 125.48974 | D17: =D16/((1+$B$3)^D15) -> 2117.2361 | E17: =E16/((1+$B$3)^E15) -> 2126.1655 | F17: =F16/((1+$B$3)^F15) -> 2060.7359 | G17: =G16/((1+$B$3)^G15) -> 2137.8032
A19: Terminal Growth Rate | B19: 0.025
A21: Terminal Value in 2029 | B21: =G16*(1+B19)/(B3-B19) -> 43350.128 | D21: <== Implied terminal value / net income (or P/E) multiple for terminal value
A22: PV of Terminal Value | B22: =B21/(1+B3)^(G15) -> 29566.296
A23: Total PV: | B23: =SUM(C17:G17)+B22 -> 38133.726
A24: Valuation per Share ($): | B24: =B23/B4 -> 135.22598
C25: Terminal Growth Rate
B26: =B24 -> 135.22598 | C26: =D26-L27 -> 0.01 | D26: =E26-L27 -> 0.015 | E26: =F26-L27 -> 0.02 | F26: 0.025 | G26: =F26+L27 -> 0.03 | H26: =G26+L27 -> 0.035 | I26: =H26+L27 -> 0.04 | L26: 0.005
B27: =B28+L27 -> 0.11411305 | C27: 98.981907 | D27: 102.85577 | E27: 107.14125 | F27: 111.90763 | G27: 117.24067 | H27: 123.24782 | I27: 130.06551 | L27: 0.005
B28: =B29+L27 -> 0.10911305 | C28: 104.16943 | D28: 108.51409 | E28: 113.3463 | F28: 118.75299 | G28: 124.8431 | H28: 131.75495 | I28: 139.66687
B29: =B30+L27 -> 0.10411305 | C29: 109.91159 | D29: 114.81083 | E29: 120.29254 | F29: 126.46714 | G29: 133.47487 | H29: 141.49655 | I29: 150.76941
A30: Cost Of Equity Ke | B30: =Ke!D38 -> 0.099113049 | C30: 116.30184 | D30: 121.85993 | E30: 128.12059 | F30: 135.22598 | G30: 143.35946 | H30: 152.76155 | I30: 163.75417
B31: =B30-L27 -> 0.094113049 | C31: 123.45582 | D31: 129.80412 | E31: 137.00899 | F31: 145.25634 | G31: 154.79007 | H31: 165.93659 | I31: 179.14297
B32: =B31-L27 -> 0.089113049 | C32: 131.51844 | D32: 138.82465 | E32: 147.188 | F32: 156.85581 | G32: 168.15911 | H32: 181.55124 | I32: 197.67016
B33: =B32-L27 -> 0.084113049 | C33: 140.67369 | D33: 149.15522 | E33: 158.95964 | F33: 170.42266 | G33: 184.00402 | H33: 200.35071 | I33: 220.40303
A36: Model 12 Month Price Target with Sensitivity of Ke
C38: =C14 -> 46022 | D38: =D14 -> 46387 | E38: =E14 -> 46752 | F38: =F14 -> 47118 | G38: =G14 -> 47483
A39: Time period | C39: =MAX((C38-$G$4)/365,0) -> 0 | D39: =MAX((D38-$G$4)/365,0) -> 0.046575342 | E39: =MAX((E38-$G$4)/365,0) -> 1.0465753 | F39: =MAX((F38-$G$4)/365,0) -> 2.0493151 | G39: =MAX((G38-$G$4)/365,0) -> 3.0493151
A40: Nominal FCFE: | C40: 0 | D40: =D16*D39 -> 108.86274 | E40: =E16 -> 2579.8435 | F40: =F16 -> 2748.9918 | G40: =G16 -> 3134.4489
A41: PV FCFE: | C41: =(C40*C39)/((1+$B$3)^C39) -> 0 | D41: =D40/((1+$B$3)^D39) -> 108.38463 | E41: =E40/((1+$B$3)^E39) -> 2336.8963 | F41: =F40/((1+$B$3)^F39) -> 2264.9818 | G41: =G40/((1+$B$3)^G39) -> 2349.6874
A43: Terminal Value in 2030 | B43: =G40*(1+B19)/(B3-B19) -> 43350.128
A44: PV of Terminal Value | B44: =B43/(1+B3)^G39 -> 32496.702
A45: Total PV: | B45: =SUM(D41:H41)+B44 -> 39556.652
A46: Valuation per Share ($): | B46: =B45/I4 -> 140.65169
C47: Terminal Growth Rate
B48: =B46 -> 140.65169 | C48: =D48-$L$26 -> 0.01 | D48: =E48-$L$26 -> 0.015 | E48: =F48-$L$26 -> 0.02 | F48: 0.025 | G48: =F48+$L$26 -> 0.03 | H48: =G48+$L$26 -> 0.035 | I48: =H48+$L$26 -> 0.04
B49: =B50+$L$27 -> 0.11411305 | C49: 102.19482 | D49: 106.52243 | E49: 111.30987 | F49: 116.63454 | G49: 122.59224 | H49: 129.30301 | I49: 136.91926
B50: =B51+$L$27 -> 0.10911305 | C50: 107.46818 | D50: 112.29995 | E50: 117.67393 | F50: 123.6868 | G50: 130.45972 | H50: 138.14649 | I50: 146.94547
B51: =B52+$L$27 -> 0.10411305 | C51: 113.30355 | D51: 118.72752 | E51: 124.79633 | F51: 131.63225 | G51: 139.39053 | H51: 148.27136 | I51: 158.53738
A52: Cost Of Equity Ke | B52: =Ke!D38 -> 0.099113049 | C52: 119.79559 | D52: 125.92111 | E52: 132.82091 | F52: 140.65169 | G52: 149.61551 | H52: 159.97746 | I52: 172.09231
B53: =B52-$L$27 -> 0.094113049 | C53: 127.06142 | D53: 134.02599 | E53: 141.93028 | F53: 150.97825 | G53: 161.43748 | H53: 173.66606 | I53: 188.15446
B54: =B53-$L$27 -> 0.089113049 | C54: 135.2478 | D54: 143.22663 | E54: 152.35993 | F54: 162.9178 | G54: 175.2617 | H54: 189.88675 | I54: 207.48962
B55: =B54-$L$27 -> 0.084113049 | C55: 144.54107 | D55: 153.76091 | E55: 164.4188 | F55: 176.87966 | G55: 191.64326 | H55: 209.41291 | I55: 231.21077

Sheet ZDFhZjliYjItMDQxYy00MW

Sheet Ke
A1: #VALUE! | D1: ECL | G1: Price = E*(1+g)/(ke-g)
A2: Cost of Equity | G2: P/E = (1+g)/(ke-g)
A3: (Blue = input, Black = calculation) | G3: ke = (1+g)/(P/E) + g
C4: Historic Beta | D4: 1.08
A5: S&P 500 data | F5: Source | G5: Reference
B6: S&P500 Forward P/E | D6: 22.05 | F6: WSJ | G6: 1-Year Forward P/E for S&P
B7: Projected EPS growth rate (g S&P) | D7: 0.1111 | F7: CapIQ/Bloomberg | G7: 5-Year Projected Earnings Growth Rate for S&P
B8: Risk-free rate (Rf) | D8: 0.0396 | F8: WSJ (5/8) | G8: 10 yr T-Note
B9: Implied required return on equity (Rs&p500) | D9: =((1+D7)/D6)+D7 -> 0.16149002 | G9: { (1+ gs&p500 ) / (P/Es&p500) } + gs&p500
B10: Implied equity risk premium (Rm) | D10: =(D8-D9)*-1 -> 0.12189002 | G10: Rs&p500-Rm
A13: Beta
A14: Fedex data
B15: Current Price (P) | D15: 280.11 | F15: WorkSpace
B16: Forward EPS (E) | D16: 7.53 | F16: WorkSpace | H16: 33.06
B17: P/E ratio | D17: 37.48 | F17: WorkSpace | G17: calc | J17: Book
B18: Projected EPS growth rate (g) | D18: ='Comps no formula'!Q19 -> 0.12345 | F18: WorkSpace + Calculation | G18: Took the average | I18: Market Cap | J18: D/E Ratio | K18: Tax Rate | L18: bU = bL / (1+ ((1-t)D/E)) | M18: bL = bu (1+ ((1-t)D/E))
B19: Implied required return on equity (Re) | D19: =((1+D18)/(D17))+D18 -> 0.15342465 | G19: { (1+g) / (P/E) } +g | I19: CLX | J19: 5.2365145 | K19: 0.24 | L19: =E23/(1+((1-K19)*J19)) -> 0.10442289 | M19: =L19*(1+((1-$K$26)*$J$26)) -> 0.17596514
B20: Forward (Bf) | D20: =(D19-D8)/D10 -> 0.93383077 | G20: (Re-Rf)/Rm | I20: CHD | J20: 0.5055494 | K20: 0.23 | L20: =E24/(1+((1-K20)*J20)) -> 0.29511837 | M20: =L20*(1+((1-$K$26)*$J$26)) -> 0.49730999
I21: DD | J21: 0.3013912 | K21: 0.23 | L21: =E25/(1+((1-K21)*J21)) -> 0.88468911 | M21: =L21*(1+((1-$K$26)*$J$26)) -> 1.4908077
A22: Comparable Beta | D22: Relevered | E22: Market Beta | I22: SHW | J22: 2.4875839 | K22: 0.222 | L22: =E26/(1+((1-K22)*J22)) -> 0.41221797 | M22: =L22*(1+((1-$K$26)*$J$26)) -> 0.6946369
B23: CLX | D23: =M19 -> 0.17596514 | E23: 0.52 | F23: Workspace
B24: CHD | D24: =M20 -> 0.49730999 | E24: 0.41 | F24: Workspace
B25: DD | D25: =M21 -> 1.4908077 | E25: 1.09 | F25: Workspace | J25: D/E Ratio | K25: Tax Rate | L25: Unlevered | M25: Relevered
B26: SHW | D26: =M22 -> 0.6946369 | E26: 1.21 | F26: Workspace | I26: ECL | J26: 0.860704 | K26: 0.204 | L26: =D30/(1+((1-K26)*J26)) -> 0.64090377 | M26: =L26*(1+((1-K26)*J26)) -> 1.08
B27: Mean | D27: =AVERAGE(D23:D26) -> 0.71467992 | E27: =AVERAGE(E23:E26) -> 0.8075
A29: Historical Beta
B30: Historic (Bh) - 5-year monthly | D30: =D4 -> 1.08 | F30: WorkSpace | G30: Five-year monthly beta
A32: Cost of Equity:
B33: Historic equity risk premium | D33: 0.065 | E33: Weight | G33: Based on long-term, historic, average risk premium (see class slides, source: Damodaran)
B34: Using Forward Beta | D34: =$D$8+D20*$D$33 -> 0.100299 | E34: 0.5 | G34: Rf+Rm*Bf
B35: Using Comparable Beta | D35: =$D$8+D27*$D$33 -> 0.086054195 | E35: 0.25
B36: Using Historic Beta | D36: =$D$8+D30*$D$33 -> 0.1098 | E36: 0.25 | G36: Rf+Rm*Bh
B38: Weighted COE | D38: =SUMPRODUCT(D34:D36,E34:E36) -> 0.099113049
B40: Market COE (beta = 1) | D40: =D33+D8 -> 0.1046 | G40: Assumes beta of 1.0

Sheet Revenue
A4: Segment | B4: 2020 | C4: 2021 | D4: 2022 | E4: 2023 | F4: 2024 | G4: 2025 | H4: 2026 | I4: 2027 | J4: 2028 | K4: 2029
A5: Global Industrial | N5: Industrial water treatment, AI data center cooling, sustainability
A6: Revenue | B6: =B49 -> 6205.78 | C6: =C49 -> 6237.8 | D6: =D49 -> 7199 | E6: =E49 -> 7626.5 | F6: =F49 -> 7777.2 | G6: =G49 -> 8062.243 | H6: =H49 -> 8357.9865 | I6: =I49 -> 8636.2583 | ... K6: =K49 -> 9222.5442
A8: Global Institutional & Specialty | N8: Hospitality rebound, digital dishwashing (DishIQ), food safety
A9: Revenue | B9: =B70 -> 3553.2 | C9: =C70 -> 4179.0161 | D9: =D70 -> 4432.1 | E9: =E70 -> 4999.2 | F9: =F70 -> 5382.6 | G9: =G70 -> 5649.228 | H9: =H70 -> 5929.1352 | I9: =I70 -> 6222.9866 | ... K9: =K70 -> 6855.3511
A11: Global Healthcare & Life Sciences | N11: Biopharma purification, infection prevention
A12: Revenue | B12: =B88 -> 1181.9 | C12: =C88 -> 1181.6 | D12: =D88 -> 1510.5 | E12: =E88 -> 1586 | F12: =F88 -> 1418.8 | G12: =G88 -> 1489.0625 | H12: =H88 -> 1562.8865 | I12: =I88 -> 1631.8982 | ... K12: =K88 -> 1779.4138 | N12: The segment’s 2024 drop was likely a one-off portfolio optimization.
A14: Global Pest Elimination / Other | N14: Predictive pest tech, commercial footprint expansion
A15: Revenue | B15: =B106 -> 1084.3 | C15: =C106 -> 1218.6 | D15: =D106 -> 1326.6 | E15: =E106 -> 1066 | F15: =F106 -> 1162.8 | G15: =G106 -> 1218.951 | H15: =H106 -> 1277.8364 | I15: =I106 -> 1339.5902 | ... K15: =K106 -> 1472.2738
A17: Corporate (ChampionX and other) | N17: Non-core
A18: Revenue | B18: =B124 -> 100 | C18: =C124 -> 139.2 | D18: =D124 -> 123.8 | E18: =E124 -> 89.1 | F18: =F124 -> 0 | G18: =G124 -> 0 | H18: =H124 -> 0 | I18: =I124 -> 0 | ... K18: =K124 -> 0 | N18: Sunset of ChampionX contract by 2024
A20: Total Net Sales
A21: Grand Total Net Sales | B21: =SUM(B6+B9+B12+B15+B18) -> 12125.18 | C21: =SUM(C6+C9+C12+C15+C18) -> 12956.216 | D21: =SUM(D6+D9+D12+D15+D18) -> 14592 | E21: =SUM(E6+E9+E12+E15+E18) -> 15366.8 | F21: =SUM(F6+F9+F12+F15+F18) -> 15741.4 | G21: =SUM(G6+G9+G12+G15+G18) -> 16419.485 | H21: =SUM(H6+H9+H12+H15+H18) -> 17127.844 | I21: =SUM(I6+I9+I12+I15+I18) -> 17830.733 | ... K21: =SUM(K6+K9+K12+K15+K18) -> 19329.583
C22: =(C21-B21)/B21 -> 0.068538046 | D22: =(D21-C21)/C21 -> 0.12625476 | E22: =(E21-D21)/D21 -> 0.053097588 | F22: =(F21-E21)/E21 -> 0.024377229 | G22: =(G21-F21)/F21 -> 0.043076505 | H22: =(H21-G21)/G21 -> 0.043141427 | I22: =(I21-H21)/H21 -> 0.041037787 | J22: =(J21-I21)/I21 -> 0.041134149 | K22: =(K21-J21)/J21 -> 0.041229793
A23: Total Product & Equipment | B23: 9466.67 | C23: 10153.3 | D23: 11446.2 | E23: 12316.8 | F23: 12473.6 | G23: =G21*0.8 -> 13135.588 | H23: =H21*0.8 -> 13702.276 | I23: =I21*0.8 -> 14264.587 | J23: =J21*0.8 -> 14851.348 | K23: =K21*0.8 -> 15463.666
A24: Total Service & Lease | B24: 2323.6 | C24: 2579.8 | D24: 2741.6 | E24: 3003.4 | F24: 3267.8 | G24: =G21*0.2 -> 3283.8969 | H24: =H21*0.2 -> 3425.5689 | I24: =I21*0.2 -> 3566.1467 | J24: =J21*0.2 -> 3712.8371 | K24: =K21*0.2 -> 3865.9166
A27: 🏭 Global Industrial
A28: Region | B28: 2020 | C28: 2021 | D28: 2022 | E28: 2023 | F28: 2024 | G28: 2025 | H28: 2026 | I28: 2027 | J28: 2028 | K28: 2029
A29: United States | B29: =2564.3*'change in segment '!I7 -> 2717.036 | C29: 2603 | D29: 3129.2 | E29: 3232.5 | F29: 3320.7 | G29: =F29*(1+G30) -> 3453.528 | H29: =G29*(1+H30) -> 3591.6691 | I29: =H29*(1+I30) -> 3735.3359 | J29: =I29*(1+J30) -> 3884.7493 | K29: =J29*(1+K30) -> 4040.1393
A30: YoY growth | C30: =(C29-B29)/B29 -> -0.041970718 | D30: =(D29-C29)/C29 -> 0.20215136 | E30: =(E29-D29)/D29 -> 0.033011632 | F30: =(F29-E29)/E29 -> 0.027285383 | G30: =+CHOOSE(Cover!$I$11,G31,G32,G33) -> 0.04 | H30: =+CHOOSE(Cover!$I$11,H31,H32,H33) -> 0.04 | I30: =+CHOOSE(Cover!$I$11,I31,I32,I33) -> 0.04 | J30: =+CHOOSE(Cover!$I$11,J31,J32,J33) -> 0.04 | K30: =+CHOOSE(Cover!$I$11,K31,K32,K33) -> 0.04 | N30: Supported by steady industrial output (~1–2%) and surging AI/data-center & sustainability investment (~20–25% CAGR) driving higher-margin water and energy-efficiency demand.
A31: bull | G31: 0.06 | H31: 0.06 | I31: 0.06 | J31: 0.06 | K31: 0.06
A32: base | G32: 0.04 | H32: 0.04 | I32: 0.04 | J32: 0.04 | K32: 0.04
A33: bear | G33: 0.03 | H33: 0.03 | I33: 0.025 | J33: 0.025 | K33: 0.025
A34: Europe | B34: =1262.6*'change in segment '!I9 -> 1322.5409 | C34: 1367.1 | D34: 1433.9 | E34: 1573 | F34: 1593.7 | G34: =F34*(1+G35) -> 1641.511 | H34: =G34*(1+H35) -> 1690.7563 | I34: =H34*(1+I35) -> 1733.0252 | J34: =I34*(1+J35) -> 1776.3509 | K34: =J34*(1+K35) -> 1820.7596
A35: YoY growth | C35: =(C34-B34)/B34 -> 0.033692075 | D35: =(D34-C34)/C34 -> 0.048862556 | E35: =(E34-D34)/D34 -> 0.09700816 | F35: =(F34-E34)/E34 -> 0.013159568 | G35: =+CHOOSE(Cover!$I$16,G36,G37,G38) -> 0.03 | H35: =+CHOOSE(Cover!$I$16,H36,H37,H38) -> 0.03 | I35: =+CHOOSE(Cover!$I$16,I36,I37,I38) -> 0.025 | J35: =+CHOOSE(Cover!$I$16,J36,J37,J38) -> 0.025 | K35: =+CHOOSE(Cover!$I$16,K36,K37,K38) -> 0.025 | N35: Modest industrial production (~1–2%) growth, lifted slightly by EU Green Deal water & sustainability infrastructure investments.
A36: bull | G36: 0.04 | H36: 0.04 | I36: 0.03 | J36: 0.03 | K36: 0.03
A37: base | G37: 0.03 | H37: 0.03 | I37: 0.025 | J37: 0.025 | K37: 0.025
A38: bear | G38: 0.02 | H38: 0.02 | I38: 0.015 | J38: 0.015 | K38: 0.015
A39: Asia Pacific | B39: =747.2*'change in segment '!I11 -> 802.23325 | C39: 802.5 | D39: 888.8 | E39: 947.4 | F39: 948.9 | G39: =F39*(1+G40) -> 986.856 | H39: =G39*(1+H40) -> 1026.3302 | I39: =H39*(1+I40) -> 1062.2518 | J39: =I39*(1+J40) -> 1099.4306 | K39: =J39*(1+K40) -> 1137.9107
A40: YoY growth | C40: =(C39-B39)/B39 -> 0.00033250563 | D40: =(D39-C39)/C39 -> 0.10753894 | E40: =(E39-D39)/D39 -> 0.065931593 | F40: =(F39-E39)/E39 -> 0.0015832806 | G40: 0.04 | H40: 0.04 | I40: 0.035 | J40: 0.035 | K40: 0.035 | N40: Industrial production and GDP in the region are modest (~4–4.5%) but are uplifted by high-growth tailwinds from data-center build-out (~13–21% CAGR) and water treatment/infrastructure (~6%+ CAGR).
A41: Latin America | B41: =491.7*'change in segment '!I13 -> 517.18512 | C41: 551.5 | D41: 656.2 | E41: 772.5 | F41: 810.5 | G41: =F41*(1+G42) -> 842.92 | H41: =G41*(1+H42) -> 876.6368 | I41: =H41*(1+I42) -> 907.31909 | J41: =I41*(1+J42) -> 939.07526 | K41: =J41*(1+K42) -> 971.94289
A42: YoY growth | C42: =(C41-B41)/B41 -> 0.06634932 | D42: =(D41-C41)/C41 -> 0.18984587 | E42: =(E41-D41)/D41 -> 0.17723255 | F42: =(F41-E41)/E41 -> 0.049190939 | G42: 0.04 | H42: 0.04 | I42: 0.035 | J42: 0.035 | K42: 0.035 | N42: Regional GDP around 2.2–2.3% and industrial water/wastewater markets expanding ~5–6% CAGR, yielding mid-single-digit potential.
A43: Greater China | B43: =333*'change in segment '!I17 -> 363.4609 | C43: 394.9 | D43: 435.8 | E43: 407 | F43: 400.4 | G43: =F43*(1+G44) -> 408.408 | H43: =G43*(1+H44) -> 416.57616 | I43: =H43*(1+I44) -> 420.74192 | J43: =I43*(1+J44) -> 424.94934 | K43: =J43*(1+K44) -> 429.19883
A44: YoY growth | C44: =(C43-B43)/B43 -> 0.086499268 | D44: =(D43-C43)/C43 -> 0.10357052 | E44: =(E43-D43)/D43 -> -0.06608536 | F44: =(F43-E43)/E43 -> -0.016216216 | G44: 0.02 | H44: 0.02 | I44: 0.01 | J44: 0.01 | K44: 0.01 | N44: Slowing macro (~4.5% GDP) offset by industrial water-treatment (~7% CAGR) and data-center build-outs (~8–9% CAGR) sustaining mid-single-digit Industrial growth.
A45: India, Middle East & Africa | B45: =314.1*'change in segment '!I15 -> 326.53965 | C45: 344.4 | D45: 459.3 | E45: 491.8 | F45: 493 | G45: =F45*(1+G46) -> 512.72 | H45: =G45*(1+H46) -> 533.2288 | I45: =H45*(1+I46) -> 549.22566 | J45: =I45*(1+J46) -> 565.70243 | K45: =J45*(1+K46) -> 582.67351
A46: YoY growth | C46: =(C45-B45)/B45 -> 0.054695803 | D46: =(D45-C45)/C45 -> 0.33362369 | E46: =(E45-D45)/D45 -> 0.070759852 | F46: =(F45-E45)/E45 -> 0.0024400163 | G46: 0.04 | H46: 0.04 | I46: 0.03 | J46: 0.03 | K46: 0.03 | N46: High-growth mix — India GDP 6.6%, MENA GDP ~3%, combined with regional water infrastructure (~4% CAGR) and digital/data-center CAPEX (~12–16% CAGR).
A47: Canada | B47: =157.9*'change in segment '!I19 -> 156.78423 | C47: 174.4 | D47: 195.8 | E47: 202.3 | F47: 210 | G47: =F47*(1+G48) -> 216.3 | H47: =G47*(1+H48) -> 222.789 | I47: =H47*(1+I48) -> 228.35872 | J47: =I47*(1+J48) -> 234.06769 | K47: =J47*(1+K48) -> 239.91939
A48: YoY growth | C48: =(C47-B47)/B47 -> 0.11235674 | D48: =(D47-C47)/C47 -> 0.12270642 | E48: =(E47-D47)/D47 -> 0.03319714 | F48: =(F47-E47)/E47 -> 0.038062284 | G48: 0.03 | H48: 0.03 | I48: 0.025 | J48: 0.025 | K48: 0.025 | N48: Stable economy (GDP ~1.5%) but boosted by data-center (~14% CAGR) and industrial water (~4–6% CAGR) growth, keeping revenue above national output.
A49: Total | B49: =B47+B45+B43+B41+B39+B34+B29 -> 6205.78 | C49: =C47+C45+C43+C41+C39+C34+C29 -> 6237.8 | D49: =D47+D45+D43+D41+D39+D34+D29 -> 7199 | E49: =E47+E45+E43+E41+E39+E34+E29 -> 7626.5 | F49: =F47+F45+F43+F41+F39+F34+F29 -> 7777.2 | G49: =G47+G45+G43+G41+G39+G34+G29 -> 8062.243 | H49: =H47+H45+H43+H41+H39+H34+H29 -> 8357.9865 | I49: =I47+I45+I43+I41+I39+I34+I29 -> 8636.2583 | ... K49: =K47+K45+K43+K41+K39+K34+K29 -> 9222.5442
A51: 🏨 Global Institutional & Specialty
A52: Region | B52: 2020 | C52: 2021 | D52: 2022 | E52: 2023 | F52: 2024 | G52: 2025 | H52: 2026 | I52: 2027 | J52: 2028 | K52: 2029
A53: United States | B53: 2400.4 | C53: =2721.8*'change in segment '!I7 -> 2883.917 | D53: 3008.1 | E53: 3410.5 | F53: 3713.5 | G53: =F53*(1+G54) -> 3899.175 | H53: =G53*(1+H54) -> 4094.1338 | I53: =H53*(1+I54) -> 4298.8404 | J53: =I53*(1+J54) -> 4513.7825 | K53: =J53*(1+K54) -> 4739.4716
A54: YoY growth | C54: =(C53-B53)/B53 -> 0.20143186 | D54: =(D53-C53)/C53 -> 0.04306052 | E54: =(E53-D53)/D53 -> 0.13377215 | F54: =(F53-E53)/E53 -> 0.088843278 | G54: =+CHOOSE(Cover!$I$12,G55,G56,G57) -> 0.05 | H54: =+CHOOSE(Cover!$I$12,H55,H56,H57) -> 0.05 | I54: =+CHOOSE(Cover!$I$12,I55,I56,I57) -> 0.05 | J54: =+CHOOSE(Cover!$I$12,J55,J56,J57) -> 0.05 | K54: =+CHOOSE(Cover!$I$12,K55,K56,K57) -> 0.05 | N54: Strong recovery and expansion in food service & hospitality (~7% CAGR) and institutional cleaning demand sustain mid-single-digit revenue growth.
A55: bull | G55: 0.06 | H55: 0.06 | I55: 0.06 | J55: 0.06 | K55: 0.06
A56: base | G56: 0.05 | H56: 0.05 | I56: 0.05 | J56: 0.05 | K56: 0.05
A57: bear | G57: 0.04 | H57: 0.04 | I57: 0.04 | J57: 0.04 | K57: 0.04
A58: Europe | B58: 510.3 | C58: =557.9*'change in segment '!I9 -> 584.38582 | D58: 624.4 | E58: 682.3 | F58: 706.4 | G58: =F58*(1+G59) -> 738.188 | H58: =G58*(1+H59) -> 771.40646 | I58: =H58*(1+I59) -> 806.11975 | J58: =I58*(1+J59) -> 842.39514 | K58: =J58*(1+K59) -> 880.30292
C59: =(C58-B58)/B58 -> 0.14518092 | D59: =(D58-C58)/C58 -> 0.068472187 | E59: =(E58-D58)/D58 -> 0.09272902 | F59: =(F58-E58)/E58 -> 0.035321706 | G59: 0.045 | H59: 0.045 | I59: 0.045 | J59: 0.045 | K59: 0.045 | N59: Moderate growth as hospitality and cleaning services (~5–7% CAGR) rebound under EU sustainability & hygiene mandates.
A60: Asia Pacific | B60: 203.9 | C60: =201.2*'change in segment '!I11 -> 216.01891 | D60: 220.9 | E60: 238.8 | F60: 249.7 | G60: =F60*(1+G61) -> 263.4335 | H60: =G60*(1+H61) -> 277.92234 | I60: =H60*(1+I61) -> 293.20807 | J60: =I60*(1+J61) -> 309.33452 | K60: =J60*(1+K61) -> 326.34791
C61: =(C60-B60)/B60 -> 0.059435563 | D61: =(D60-C60)/C60 -> 0.022595655 | E61: =(E60-D60)/D60 -> 0.081032141 | F61: =(F60-E60)/E60 -> 0.045644891 | G61: 0.055 | H61: 0.055 | I61: 0.055 | J61: 0.055 | K61: 0.055 | N61: Expanding food-service & hospitality sectors (~5–6% CAGR) plus rising hygiene infrastructure spending drive above-average growth.
A62: Latin America | B62: 128.3 | C62: =135*'change in segment '!I13 -> 141.99713 | D62: 169.2 | E62: 197.8 | F62: 201.6 | G62: =F62*(1+G63) -> 212.688 | H62: =G62*(1+H63) -> 224.38584 | I62: =H62*(1+I63) -> 236.72706 | J62: =I62*(1+J63) -> 249.74705 | K62: =J62*(1+K63) -> 263.48314
C63: =(C62-B62)/B62 -> 0.10675865 | D63: =(D62-C62)/C62 -> 0.19157334 | E63: =(E62-D62)/D62 -> 0.16903073 | F63: =(F62-E62)/E62 -> 0.019211325 | G63: 0.055 | H63: 0.055 | I63: 0.055 | J63: 0.055 | K63: 0.055 | N63: Institutional & cleaning service demand expanding ~6–7% CAGR across Mexico, Brazil, and Chile supports steady regional growth.
A64: Greater China | B64: 114.9 | C64: =132.3*'change in segment '!I17 -> 144.40203 | D64: 138.3 | E64: 161 | F64: 177.5 | G64: =F64*(1+G65) -> 186.375 | H64: =G64*(1+H65) -> 195.69375 | I64: =H64*(1+I65) -> 205.47844 | J64: =I64*(1+J65) -> 215.75236 | K64: =J64*(1+K65) -> 226.53998
C65: =(C64-B64)/B64 -> 0.25676269 | D65: =(D64-C64)/C64 -> -0.042257249 | E65: =(E64-D64)/D64 -> 0.16413594 | F65: =(F64-E64)/E64 -> 0.10248447 | G65: 0.05 | H65: 0.05 | I65: 0.05 | J65: 0.05 | K65: 0.05 | N65: Continued urban food-service expansion and government hygiene standards yield steady mid-single-digit growth.
A66: India, Middle East & Africa | B66: 39.8 | C66: =44.2*'change in segment '!I15 -> 45.950502 | D66: 66.2 | E66: 77.8 | F66: 84.5 | G66: =F66*(1+G67) -> 89.9925 | H66: =G66*(1+H67) -> 95.842012 | I66: =H66*(1+I67) -> 102.07174 | J66: =I66*(1+J67) -> 108.70641 | K66: =J66*(1+K67) -> 115.77232
C67: =(C66-B66)/B66 -> 0.15453522 | D67: =(D66-C66)/C66 -> 0.44068068 | E67: =(E66-D66)/D66 -> 0.17522659 | F67: =(F66-E66)/E66 -> 0.086118252 | G67: 0.065 | H67: 0.065 | I67: 0.065 | J67: 0.065 | K67: 0.065 | N67: Rapid hospitality and institutional cleaning growth (~8–9% CAGR) and new infrastructure investments deliver strong momentum.
A68: Canada | B68: 155.6 | C68: =163.5*'change in segment '!I19 -> 162.34466 | D68: 205 | E68: 231 | F68: 249.4 | G68: =F68*(1+G69) -> 259.376 | H68: =G68*(1+H69) -> 269.75104 | I68: =H68*(1+I69) -> 280.54108 | J68: =I68*(1+J69) -> 291.76272 | K68: =J68*(1+K69) -> 303.43323
C69: =(C68-B68)/B68 -> 0.043346168 | D69: =(D68-C68)/C68 -> 0.26274554 | E69: =(E68-D68)/D68 -> 0.12682927 | F69: =(F68-E68)/E68 -> 0.07965368 | G69: 0.04 | H69: 0.04 | I69: 0.04 | J69: 0.04 | K69: 0.04 | N69: Mature but stable hospitality and institutional services (~4–5% CAGR) with incremental sustainability adoption.
A70: Total | B70: =SUM(B53,B58,B60,B62,B64,B66,B68) -> 3553.2 | C70: =SUM(C53,C58,C60,C62,C64,C66,C68) -> 4179.0161 | D70: =SUM(D53,D58,D60,D62,D64,D66,D68) -> 4432.1 | E70: =SUM(E53,E58,E60,E62,E64,E66,E68) -> 4999.2 | F70: =SUM(F53,F58,F60,F62,F64,F66,F68) -> 5382.6 | G70: =SUM(G53,G58,G60,G62,G64,G66,G68) -> 5649.228 | H70: =SUM(H53,H58,H60,H62,H64,H66,H68) -> 5929.1352 | I70: =SUM(I53,I58,I60,I62,I64,I66,I68) -> 6222.9866 | ... K70: =SUM(K53,K58,K60,K62,K64,K66,K68) -> 6855.3511
A72: 🧬 Global Healthcare & Life Sciences
A73: Region | B73: 2020 | C73: 2021 | D73: 2022 | E73: 2023 | F73: 2024 | G73: 2025 | H73: 2026 | I73: 2027 | J73: 2028 | K73: 2029
A74: United States | B74: 432.6 | C74: 442.3 | D74: 600.7 | E74: 633.6 | F74: 465.8 | G74: =F74*(1+G75) -> 489.09 | H74: =G74*(1+H75) -> 513.5445 | I74: =H74*(1+I75) -> 536.654 | J74: =I74*(1+J75) -> 560.80343 | K74: =J74*(1+K75) -> 586.03959
C75: =(C74-B74)/B74 -> 0.022422561 | D75: =(D74-C74)/C74 -> 0.35812797 | E75: =(E74-D74)/D74 -> 0.054769436 | F75: =(F74-E74)/E74 -> -0.26483586 | G75: 0.05 | H75: 0.05 | I75: 0.045 | J75: 0.045 | K75: 0.045 | N75: Growth led by steady hospital spending (~5–6% CAGR) and strong demand in biopharma & life sciences purification (~6–7% CAGR).
A76: Europe | B76: 643.6 | C76: 647.2 | D76: 675.6 | E76: 719.2 | F76: 705.5 | G76: =F76*(1+G77) -> 737.2475 | H76: =G76*(1+H77) -> 770.42364 | I76: =H76*(1+I77) -> 801.24058 | J76: =I76*(1+J77) -> 833.29021 | K76: =J76*(1+K77) -> 866.62181
C77: =(C76-B76)/B76 -> 0.0055935364 | D77: =(D76-C76)/C76 -> 0.043881335 | E77: =(E76-D76)/D76 -> 0.064535228 | F77: =(F76-E76)/E76 -> -0.019048943 | G77: 0.045 | H77: 0.045 | I77: 0.04 | J77: 0.04 | K77: 0.04 | N77: Stable healthcare expenditure (~4–5%) and EU-funded biotech expansion sustain moderate growth.
A78: Asia Pacific | B78: 69.8 | C78: 59.6 | D78: 100.4 | E78: 103.9 | F78: 111.3 | G78: =F78*(1+G79) -> 117.978 | H78: =G78*(1+H79) -> 125.05668 | I78: =H78*(1+I79) -> 131.30951 | J78: =I78*(1+J79) -> 137.87499 | K78: =J78*(1+K79) -> 144.76874
C79: =(C78-B78)/B78 -> -0.14613181 | D79: =(D78-C78)/C78 -> 0.68456376 | E79: =(E78-D78)/D78 -> 0.034860558 | F79: =(F78-E78)/E78 -> 0.071222329 | G79: 0.06 | H79: 0.06 | I79: 0.05 | J79: 0.05 | K79: 0.05 | N79: Rapid hospital infrastructure buildout and biotech/pharma CAPEX (~7–8% CAGR) fuel above-average growth.
A80: Latin America | B80: 6.1 | C80: 1.8 | D80: 32.9 | E80: 35.5 | F80: 29.1 | G80: =F80*(1+G81) -> 30.264 | H80: =G80*(1+H81) -> 31.47456 | I80: =H80*(1+I81) -> 32.733542 | J80: =I80*(1+J81) -> 34.042884 | K80: =J80*(1+K81) -> 35.404599
C81: =(C80-B80)/B80 -> -0.70491803 | D81: =(D80-C80)/C80 -> 17.277778 | E81: =(E80-D80)/D80 -> 0.079027356 | F81: =(F80-E80)/E80 -> -0.18028169 | G81: 0.04 | H81: 0.04 | I81: 0.04 | J81: 0.04 | K81: 0.04 | N81: Healthcare investment recovery (~3–4%) supported by expanding private hospital chains and medical device imports.
A82: Greater China | B82: 3.6 | C82: 6.3 | D82: 65.6 | E82: 56.4 | F82: 59 | G82: =F82*(1+G83) -> 62.835 | H82: =G82*(1+H83) -> 66.919275 | I82: =H82*(1+I83) -> 70.934431 | J82: =I82*(1+J83) -> 75.190497 | K82: =J82*(1+K83) -> 79.701927
C83: =(C82-B82)/B82 -> 0.75 | D83: =(D82-C82)/C82 -> 9.4126984 | E83: =(E82-D82)/D82 -> -0.1402439 | F83: =(F82-E82)/E82 -> 0.046099291 | G83: 0.065 | H83: 0.065 | I83: 0.06 | J83: 0.06 | K83: 0.06 | N83: Strong biopharma manufacturing & life-sciences purification (~8–9% CAGR) offset by slower hospital spending (~5%).
A84: India, Middle East & Africa | B84: 19.8 | C84: 18.1 | D84: 29 | E84: 29.6 | F84: 40.6 | G84: =F84*(1+G85) -> 43.848 | H84: =G84*(1+H85) -> 47.35584 | I84: =H84*(1+I85) -> 50.670749 | J84: =I84*(1+J85) -> 54.217701 | K84: =J84*(1+K85) -> 58.01294
C85: =(C84-B84)/B84 -> -0.085858586 | D85: =(D84-C84)/C84 -> 0.60220994 | E85: =(E84-D84)/D84 -> 0.020689655 | F85: =(F84-E84)/E84 -> 0.37162162 | G85: 0.08 | H85: 0.08 | I85: 0.07 | J85: 0.07 | K85: 0.07 | N85: Fastest growth from India healthcare (~8–9%) and Gulf life-sciences infrastructure (~6–7%) investments.
A86: Canada | B86: 6.4 | C86: 6.3 | D86: 6.3 | E86: 7.8 | F86: 7.5 | G86: =F86*(1+G87) -> 7.8 | H86: =G86*(1+H87) -> 8.112 | I86: =H86*(1+I87) -> 8.35536 | J86: =I86*(1+J87) -> 8.6060208 | K86: =J86*(1+K87) -> 8.8642014
C87: =(C86-B86)/B86 -> -0.015625 | D87: =(D86-C86)/C86 -> 0 | E87: =(E86-D86)/D86 -> 0.23809524 | F87: =(F86-E86)/E86 -> -0.038461538 | G87: 0.04 | H87: 0.04 | I87: 0.03 | J87: 0.03 | K87: 0.03 | N87: Mature hospital systems (~3–4%) complemented by gradual life-sciences cluster expansion (~5%).
A88: Total | B88: =SUM(B74,B76,B78,B80,B82,B84,B86) -> 1181.9 | C88: =SUM(C74,C76,C78,C80,C82,C84,C86) -> 1181.6 | D88: =SUM(D74,D76,D78,D80,D82,D84,D86) -> 1510.5 | E88: =SUM(E74,E76,E78,E80,E82,E84,E86) -> 1586 | F88: =SUM(F74,F76,F78,F80,F82,F84,F86) -> 1418.8 | G88: =SUM(G74,G76,G78,G80,G82,G84,G86) -> 1489.0625 | H88: =SUM(H74,H76,H78,H80,H82,H84,H86) -> 1562.8865 | I88: =SUM(I74,I76,I78,I80,I82,I84,I86) -> 1631.8982 | ... K88: =SUM(K74,K76,K78,K80,K82,K84,K86) -> 1779.4138
A90: 🪳 Global Pest Elimination / Other
A91: Region | B91: 2020 | C91: 2021 | D91: 2022 | E91: 2023 | F91: 2024 | G91: 2025 | H91: 2026 | I91: 2027 | J91: 2028 | K91: 2029
A92: United States | B92: =645.7*'change in segment '!I26 -> 520.85949 | C92: =719.9*'change in segment '!I26 -> 580.71357 | D92: 650.3 | E92: 733.6 | F92: 805.6 | G92: =F92*(1+G93) -> 845.88 | H92: =G92*(1+H93) -> 888.174 | I92: =H92*(1+I93) -> 932.5827 | J92: =I92*(1+J93) -> 979.21184 | K92: =J92*(1+K93) -> 1028.1724
C93: =(C92-B92)/B92 -> 0.11491405 | D93: =(D92-C92)/C92 -> 0.11982919 | E93: =(E92-D92)/D92 -> 0.12809473 | F93: =(F92-E92)/E92 -> 0.098146129 | G93: 0.05 | H93: 0.05 | I93: 0.05 | J93: 0.05 | K93: 0.05 | N93: Commercial pest control and sanitation services growing steadily (~5% CAGR) driven by food safety compliance and hospitality reopening.
A94: Europe | B94: =228.8*'change in segment '!I28 -> 129.73855 | C94: =264.9*'change in segment '!I28 -> 150.20867 | D94: 154.7 | E94: 171 | F94: 187.5 | G94: =F94*(1+G95) -> 195 | H94: =G94*(1+H95) -> 202.8 | I94: =H94*(1+I95) -> 210.912 | J94: =I94*(1+J95) -> 219.34848 | K94: =J94*(1+K95) -> 228.12242
C95: =(C94-B94)/B94 -> 0.15777972 | D95: =(D94-C94)/C94 -> 0.029900633 | E95: =(E94-D94)/D94 -> 0.10536522 | F95: =(F94-E94)/E94 -> 0.096491228 | G95: 0.04 | H95: 0.04 | I95: 0.04 | J95: 0.04 | K95: 0.04 | N95: EU pest control and hygiene markets expand (~4–4.5%) aided by tightened food safety and sanitation regulations.
A96: Asia Pacific | B96: =64.8*'change in segment '!I30 -> 22.703726 | C96: =72.4*'change in segment '!I30 -> 25.366509 | D96: 27.9 | E96: 28.7 | F96: 32.1 | G96: =F96*(1+G97) -> 34.026 | H96: =G96*(1+H97) -> 36.06756 | I96: =H96*(1+I97) -> 38.231614 | J96: =I96*(1+J97) -> 40.52551 | K96: =J96*(1+K97) -> 42.957041
C97: =(C96-B96)/B96 -> 0.11728395 | D97: =(D96-C96)/C96 -> 0.099875428 | E97: =(E96-D96)/D96 -> 0.028673835 | F97: =(F96-E96)/E96 -> 0.1184669 | G97: 0.06 | H97: 0.06 | I97: 0.06 | J97: 0.06 | K97: 0.06 | N97: Strong structural growth from urbanization, food processing expansion, and pest management outsourcing (~6–7% CAGR).
A98: Latin America | B98: =50.3*'change in segment '!I32 -> 50.207878 | C98: =50.4*'change in segment '!I32 -> 50.307695 | D98: 51.8 | E98: 57.5 | F98: 58.7 | G98: =F98*(1+G99) -> 61.3415 | H98: =G98*(1+H99) -> 64.101867 | I98: =H98*(1+I99) -> 66.986452 | J98: =I98*(1+J99) -> 70.000842 | K98: =J98*(1+K99) -> 73.15088
C99: =(C98-B98)/B98 -> 0.0019880716 | D99: =(D98-C98)/C98 -> 0.029663552 | E99: =(E98-D98)/D98 -> 0.11003861 | F99: =(F98-E98)/E98 -> 0.020869565 | G99: 0.045 | H99: 0.045 | I99: 0.045 | J99: 0.045 | K99: 0.045 | N99: Rising pest control penetration in foodservice, agriculture, and manufacturing sectors (~4–5% CAGR).
A100: Greater China | B100: =63.4*'change in segment '!I36 -> 50.550564 | C100: =80*'change in segment '!I36 -> 63.7862 | D100: 56.8 | E100: 57.4 | F100: 60 | G100: =F100*(1+G101) -> 63 | H100: =G100*(1+H101) -> 66.15 | I100: =H100*(1+I101) -> 69.4575 | J100: =I100*(1+J101) -> 72.930375 | K100: =J100*(1+K101) -> 76.576894
C101: =(C100-B100)/B100 -> 0.26182965 | D101: =(D100-C100)/C100 -> -0.10952526 | E101: =(E100-D100)/D100 -> 0.01056338 | F101: =(F100-E100)/E100 -> 0.045296167 | G101: 0.05 | H101: 0.05 | I101: 0.05 | J101: 0.05 | K101: 0.05 | N101: Expanding urban food chains and hygiene regulations (~5% CAGR) drive steady pest elimination service growth.
A102: India, Middle East & Africa | B102: =14.4*'change in segment '!I34 -> 11.63439 | C102: =11.6*'change in segment '!I34 -> 9.3721477 | D102: 8.1 | E102: 6.9 | F102: 7.1 | G102: =F102*(1+G103) -> 7.4905 | H102: =G102*(1+H103) -> 7.9024775 | I102: =H102*(1+I103) -> 8.3371138 | J102: =I102*(1+J103) -> 8.795655 | K102: =J102*(1+K103) -> 9.279416
C103: =(C102-B102)/B102 -> -0.19444444 | D103: =(D102-C102)/C102 -> -0.13573705 | E103: =(E102-D102)/D102 -> -0.14814815 | F103: =(F102-E102)/E102 -> 0.028985507 | G103: 0.055 | H103: 0.055 | I103: 0.055 | J103: 0.055 | K103: 0.055 | N103: Growth led by India pest management (~6.2% CAGR) and Gulf hygiene infrastructure expansion in hospitality & logistics.
A104: Canada | B104: =16.9*'change in segment '!I38 -> 7.9676239 | C104: =19.4*'change in segment '!I38 -> 9.1462665 | D104: 9.4 | E104: 10.9 | F104: 11.8 | G104: =F104*(1+G105) -> 12.213 | H104: =G104*(1+H105) -> 12.640455 | I104: =H104*(1+I105) -> 13.082871 | J104: =I104*(1+J105) -> 13.540771 | K104: =J104*(1+K105) -> 14.014698
C105: =(C104-B104)/B104 -> 0.14792899 | D105: =(D104-C104)/C104 -> 0.027741761 | E105: =(E104-D104)/D104 -> 0.15957447 | F105: =(F104-E104)/E104 -> 0.082568807 | G105: 0.035 | H105: 0.035 | I105: 0.035 | J105: 0.035 | K105: 0.035 | N105: Mature, regulated pest-control market (~3–4%) aligned with food safety and retail hygiene compliance.
A106: Total | B106: 1084.3 | C106: 1218.6 | D106: 1326.6 | E106: 1066 | F106: 1162.8 | G106: =SUM(G92,G94,G96,G98,G100,G102,G104) -> 1218.951 | H106: =SUM(H92,H94,H96,H98,H100,H102,H104) -> 1277.8364 | I106: =SUM(I92,I94,I96,I98,I100,I102,I104) -> 1339.5902 | J106: =SUM(J92,J94,J96,J98,J100,J102,J104) -> 1404.3535 | K106: =SUM(K92,K94,K96,K98,K100,K102,K104) -> 1472.2738
A108: 🏢 Corporate
A109: Region | B109: 2020 | C109: 2021 | D109: 2022 | E109: 2023 | F109: 2024 | G109: 2025 | H109: 2026 | I109: 2027 | J109: 2028 | K109: 2029
A110: United States | B110: 75.2 | C110: 98.2 | D110: 84 | E110: 38.4 | F110: 0 | G110: 0 | H110: 0 | I110: 0 | J110: 0 | K110: 0
N111: U.S. HQ eliminations and internal service charges likely remain flat or slightly negative, mirroring Ecolab’s historic corporate consolidation adjustments.
A112: Europe | B112: 4.8 | C112: 3.9 | D112: 2.7 | E112: 2.7 | F112: 0 | G112: 0 | H112: 0 | I112: 0 | J112: 0 | K112: 0
N113: Minimal growth as regional eliminations balance intra-segment allocations.
A114: Asia Pacific | B114: 2.8 | C114: 5.5 | D114: 0.3 | E114: 0.2 | F114: 0 | G114: 0 | H114: 0 | I114: 0 | J114: 0 | K114: 0
...

Sheet change in segment 
B3: changs in reportable segment
B4: 🏭 Global Industrial
C5: 2022 | D5: 2022 | F5: 2023 | G5: 2023 | I5: Avg percentage change
B7: United States | C7: 3129.2 | D7: 2945.1 | E7: =C7/D7 -> 1.0625106 | F7: 3232.5 | G7: 3059.3 | H7: =F7/G7 -> 1.0566143 | I7: =AVERAGE(E7,H7) -> 1.0595624
D8: =C7-D7 -> 184.1 | G8: =F7-G7 -> 173.2
B9: Europe | C9: 1433.9 | D9: 1373.6 | E9: =C9/D9 -> 1.0438992 | F9: 1573 | G9: 1496.6 | H9: =F9/G9 -> 1.051049 | I9: =AVERAGE(E9,H9) -> 1.0474741
D10: =C9-D9 -> 60.3 | G10: =F9-G9 -> 76.4
B11: Asia Pacific | C11: 888.8 | D11: 830.1 | E11: =C11/D11 -> 1.0707144 | F11: 947.4 | G11: 880 | H11: =F11/G11 -> 1.0765909 | I11: =AVERAGE(E11,H11) -> 1.0736526
D12: =C11-D11 -> 58.7 | G12: =F11-G11 -> 67.4
B13: Latin America | C13: 656.2 | D13: 621.7 | E13: =C13/D13 -> 1.055493 | F13: 772.5 | G13: 737 | H13: =F13/G13 -> 1.0481682 | I13: =AVERAGE(E13,H13) -> 1.0518306
D14: =C13-D13 -> 34.5 | G14: =F13-G13 -> 35.5
B15: India, Middle East & Africa | C15: 435.8 | D15: 419.3 | E15: =C15/D15 -> 1.0393513 | F15: 407 | G15: 391.4 | H15: =F15/G15 -> 1.0398569 | I15: =AVERAGE(E15,H15) -> 1.0396041
D16: =C15-D15 -> 16.5 | G16: =F15-G15 -> 15.6
B17: Greater China | C17: 459.3 | D17: 419.4 | E17: =C17/D17 -> 1.0951359 | F17: 491.8 | G17: 452.1 | H17: =F17/G17 -> 1.0878124 | I17: =AVERAGE(E17,H17) -> 1.0914742
D18: =C17-D17 -> 39.9 | G18: =F17-G17 -> 39.7
B19: Canada | C19: 195.8 | D19: 195.8 | E19: =C19/D19 -> 1 | F19: 202.3 | G19: 205.2 | H19: =F19/G19 -> 0.98586745 | I19: =AVERAGE(E19,H19) -> 0.99293372
D20: =C19-D19 -> 0
B21: Total | C21: =C9+C11+C13+C15+C17+C19+C7 -> 7199 | D21: =D9+D11+D13+D15+D17+D19+D7 -> 6805 | E21: =C21/D21 -> 1.0578986 | F21: =F9+F11+F13+F15+F17+F19+F7 -> 7626.5 | G21: =G9+G11+G13+G15+G17+G19+G7 -> 7221.6 | H21: =F21/G21 -> 1.0560679
B24: 🪳 Global Pest Elimination / Other
C25: 2022 | D25: 2022 | E25: % change | F25: 2023 | G25: 2023 | H25: %change | I25: avg % change
B26: United States | C26: 650.3 | D26: 816 | E26: =C26/D26 -> 0.79693627 | F26: 733.6 | G26: 898.6 | H26: =F26/G26 -> 0.81638104 | I26: =AVERAGE(E26,H26) -> 0.80665866
D27: =C26-D26 -> -165.7 | G27: =F26-G26 -> -165
B28: Europe | C28: 154.7 | D28: 272.7 | E28: =C28/D28 -> 0.56729006 | F28: 171 | G28: 301.7 | H28: =F28/G28 -> 0.5667882 | I28: =AVERAGE(E28,H28) -> 0.56703913
D29: =C28-D28 -> -118 | G29: =F28-G28 -> -130.7
B30: Asia Pacific | C30: 27.9 | D30: 76.1 | E30: =C30/D30 -> 0.36662286 | F30: 28.7 | G30: 85.9 | H30: =F30/G30 -> 0.33410943 | I30: =AVERAGE(E30,H30) -> 0.35036615
D31: =C30-D30 -> -48.2 | G31: =F30-G30 -> -57.2
B32: Latin America | C32: 51.8 | D32: 51.9 | E32: =C32/D32 -> 0.99807322 | F32: 57.5 | G32: 57.6 | H32: =F32/G32 -> 0.99826389 | I32: =AVERAGE(E32,H32) -> 0.99816855
D33: =C32-D32 -> -0.1 | G33: =F32-G32 -> -0.1
B34: India, Middle East & Africa | C34: 8.1 | D34: 10.3 | E34: =C34/D34 -> 0.78640777 | F34: 57.4 | G34: 69.2 | H34: =F34/G34 -> 0.82947977 | I34: =AVERAGE(E34,H34) -> 0.80794377
D35: =C34-D34 -> -2.2 | G35: =F34-G34 -> -11.8
B36: Greater China | C36: 56.8 | D36: 68.6 | E36: =C36/D36 -> 0.82798834 | F36: 6.9 | G36: 9 | H36: =F36/G36 -> 0.76666667 | I36: =AVERAGE(E36,H36) -> 0.7973275
D37: =C36-D36 -> -11.8 | G37: =F36-G36 -> -2.1
B38: Canada | C38: 9.4 | D38: 20.8 | E38: =C38/D38 -> 0.45192308 | F38: 10.9 | G38: 22.2 | H38: =F38/G38 -> 0.49099099 | I38: =AVERAGE(E38,H38) -> 0.47145703
D39: =C38-D38 -> -11.4
B40: Total | C40: =C26+C28+C30+C32+C34+C36+C38 -> 959 | D40: =D26+D28+D30+D32+D34+D36+D38 -> 1316.4 | E40: =C40/D40 -> 0.72850198 | F40: =F26+F28+F30+F32+F34+F36+F38 -> 1066 | G40: =G26+G28+G30+G32+G34+G36+G38 -> 1444.2 | H40: =F40/G40 -> 0.73812491

Sheet Cost of sales
A3: Segment | B3: 2020 | C3: 2021 | D3: 2022 | E3: 2023 | F3: 2024 | G3: 2025 | H3: 2026 | I3: 2027 | J3: 2028 | K3: 2029 | L3: 2029
A4: Global Industrial
A5: Revenue | B5: 5870.8 | C5: 6237.8 | D5: 6805 | E5: 7626.5 | F5: 7777.2 | G5: 8095.45 | H5: 8427.3891 | I5: 8726.7424 | J5: 9037.5581 | K5: 9360.296
A6: Op.income | B6: 1079.1 | C6: 985.7 | D6: 977
A7: Op.margin | B7: 0.105 | C7: 0.132 | D7: 0.119 | E7: 0.14 | F7: 0.166 | G7: =AVERAGE(D7:F7) -> 0.14166667 | H7: =AVERAGE(E7:G7) -> 0.14922222 | I7: =AVERAGE(F7:H7) -> 0.1522963 | J7: =AVERAGE(G7:I7) -> 0.1477284 | K7: =AVERAGE(H7:J7) -> 0.14974897 | M7: Numbers rounded from Ecolab’s Segment Results table in the Form 10-K; “Operating income ÷ Net sales.”
A8: SG&A | B8: ='Income statement'!$B$11/'Income statement'!$B$7 -> 0.28066363 | C8: ='Income statement'!$C$11/'Income statement'!$C$7 -> 0.26828502 | D8: ='Income statement'!$D$11/'Income statement'!$D$7 -> 0.25753112 | E8: ='Income statement'!$E$11/'Income statement'!$E$7 -> 0.26511403 | F8: ='Income statement'!$F$11/'Income statement'!$F$7 -> 0.26860381 | G8: 0.26 | H8: 0.26 | I8: 0.26 | J8: 0.26 | K8: 0.26
A9: cost of sales | B9: =B5*(1-B8-B7) -> 3606.6459 | C9: =C5*(1-C8-C7) -> 3740.9021 | D9: =D5*(1-D8-D7) -> 4242.7057 | E9: 4769.7 | F9: 4691.2 | G9: =G5*(1-G8-G7) -> 4843.7776 | H9: =H5*(1-H8-H7) -> 4978.7142 | I9: =I5*(1-I8-I7) -> 5128.7388 | J9: =J5*(1-J8-J7) -> 5352.689 | K9: =K5*(1-K8-K7) -> 5524.9243 | M9: cos=revenue-sga(26%)-operating margin
A10: Global Institutional & Specialty
A11: Revenue | B11: 3553.2 | C11: 3955.9 | D11: 4421.9 | E11: 4999.2 | F11: 5382.6 | G11: 5686.363 | H11: 6007.49 | I11: 6346.9841 | J11: 6705.9064 | K11: 7085.3802
A12: Op.income | B12: 316.3 | C12: 545.7 | D12: 634.5
A13: Op.margin | B13: =316.3/B11 -> 0.08901835 | C13: 0.102 | D13: 0.095 | E13: 0.12 | F13: 0.138 | G13: =AVERAGE(D13:F13) -> 0.11766667 | H13: =AVERAGE(E13:G13) -> 0.12522222 | I13: =AVERAGE(F13:H13) -> 0.12696296 | J13: =AVERAGE(G13:I13) -> 0.12328395 | K13: =AVERAGE(H13:J13) -> 0.12515638 | M13: Numbers rounded from Ecolab’s Segment Results table in the Form 10-K; “Operating income ÷ Net sales.”
A14: SG&A | B14: ='Income statement'!$B$11/'Income statement'!$B$7 -> 0.28066363 | C14: ='Income statement'!$C$11/'Income statement'!$C$7 -> 0.26828502 | D14: ='Income statement'!$D$11/'Income statement'!$D$7 -> 0.25753112 | E14: ='Income statement'!$E$11/'Income statement'!$E$7 -> 0.26511403 | F14: ='Income statement'!$F$11/'Income statement'!$F$7 -> 0.26860381 | G14: 0.26 | H14: 0.26 | I14: 0.26 | J14: 0.26 | K14: 0.26
A15: cost of sales | B15: =B11*(1-B14-B13) -> 2239.646 | C15: =C11*(1-C14-C13) -> 2491.0895 | D15: =D11*(1-D14-D13) -> 2863.0426 | E15: 2727.3 | F15: 2727 | G15: =G11*(1-G14-G13) -> 3538.8132 | H15: =H11*(1-H14-H13) -> 3693.2714 | I15: =I11*(1-I14-I13) -> 3890.9363 | J15: =J11*(1-J14-J13) -> 4135.6401 | K15: =K11*(1-K14-K13) -> 4356.4008 | M15: cos=revenue-sga(26%)-operating margin
A16: Global Healthcare & Life Sciences
A17: Revenue | B17: 1181.9 | C17: 1181.6 | D17: 1510.5 | E17: 1586 | F17: 1418.8 | G17: 1489.0625 | H17: 1562.8865 | I17: 1631.8982 | J17: 1704.0257 | K17: 1779.4138
A18: Op.income | B18: 207.6 | C18: 152.3 | D18: 205
A19: Op.margin | B19: 0.062 | C19: 0.07 | D19: 0.07 | E19: 0.085 | F19: 0.098 | G19: =AVERAGE(D19:F19) -> 0.084333333 | H19: =AVERAGE(E19:G19) -> 0.089111111 | I19: =AVERAGE(F19:H19) -> 0.090481481 | J19: =AVERAGE(G19:I19) -> 0.087975309 | K19: =AVERAGE(H19:J19) -> 0.0891893 | M19: Numbers rounded from Ecolab’s Segment Results table in the Form 10-K; “Operating income ÷ Net sales.”
A20: SG&A | B20: ='Income statement'!$B$11/'Income statement'!$B$7 -> 0.28066363 | C20: ='Income statement'!$C$11/'Income statement'!$C$7 -> 0.26828502 | D20: ='Income statement'!$D$11/'Income statement'!$D$7 -> 0.25753112 | E20: ='Income statement'!$E$11/'Income statement'!$E$7 -> 0.26511403 | F20: ='Income statement'!$F$11/'Income statement'!$F$7 -> 0.26860381 | G20: 0.26 | H20: 0.26 | I20: 0.26 | J20: 0.26 | K20: 0.26
A21: cost of sales | B21: =B17*(1-B20-B19) -> 776.90585 | C21: =C17*(1-C20-C19) -> 781.88242 | D21: =D17*(1-D20-D19) -> 1015.7642 | E21: 1026.9 | F21: 895 | G21: =G17*(1-G20-G19) -> 976.32865 | H21: =H17*(1-H20-H19) -> 1017.2655 | I21: =I17*(1-I20-I19) -> 1059.9481 | J21: =J17*(1-J20-J19) -> 1111.0669 | K21: =K17*(1-K20-K19) -> 1158.0615 | M21: cos=revenue-sga(26%)-operating margin
A22: Global Pest Elimination / Other
A23: Revenue | B23: 1084.3 | C23: 1218.6 | D23: 1326.6 | E23: 1066 | F23: 1162.8 | G23: 1218.951 | H23: 1277.8364 | I23: 1339.5902 | J23: 1404.3535 | K23: 1472.2738
A24: Op.income | B24: 130.6 | C24: 184 | D24: 212
A25: Op.margin | B25: 0.115 | C25: 0.118 | D25: 0.118 | E25: 0.126 | F25: 0.13 | G25: =AVERAGE(D25:F25) -> 0.12466667 | H25: =AVERAGE(E25:G25) -> 0.12688889 | I25: =AVERAGE(F25:H25) -> 0.12718519 | J25: =AVERAGE(G25:I25) -> 0.12624691 | K25: =AVERAGE(H25:J25) -> 0.12677366 | M25: Numbers rounded from Ecolab’s Segment Results table in the Form 10-K; “Operating income ÷ Net sales.”
A26: SG&A | B26: ='Income statement'!$B$11/'Income statement'!$B$7 -> 0.28066363 | C26: ='Income statement'!$C$11/'Income statement'!$C$7 -> 0.26828502 | D26: ='Income statement'!$D$11/'Income statement'!$D$7 -> 0.25753112 | E26: ='Income statement'!$E$11/'Income statement'!$E$7 -> 0.26511403 | F26: ='Income statement'!$F$11/'Income statement'!$F$7 -> 0.26860381 | G26: 0.26 | H26: 0.26 | I26: 0.26 | J26: 0.26 | K26: 0.26
A27: cost of sales | B27: =B23*(1-B26-B25) -> 655.28192 | C27: =C23*(1-C26-C25) -> 747.87307 | D27: =D23*(1-D26-D25) -> 828.42042 | E27: 595 | F27: 655 | G27: =G23*(1-G26-G25) -> 750.06118 | H27: =H23*(1-H26-H25) -> 783.45567 | I27: =I23*(1-I26-I25) -> 820.92075 | J27: =J23*(1-J26-J25) -> 861.92628 | K27: =K23*(1-K26-K25) -> 902.83705 | M27: cos=revenue-sga(26%)-operating margin
A28: Corporate (ChampionX and other)
A29: Revenue | B29: 100 | C29: 139.2 | D29: 123.8 | E29: 89.1 | F29: -42.5 | G29: 42.2 | H29: -42.2 | I29: 42.2 | J29: -42.2 | K29: 42.2
B30: -347.7 | C30: -316.6 | D30: -416.7 | E30: 63.3 | F30: 5.4
M32: cos=revenue-sga(26%)-operating margin
A33: Total Net Sales
A34: Grand Total Net Sales | B34: =B5+B11+B17+B23+B29 -> 11790.2 | C34: =C5+C11+C17+C23+C29 -> 12733.1 | D34: =D5+D11+D17+D23+D29 -> 14187.8 | E34: =E5+E11+E17+E23+E29 -> 15366.8 | F34: =F5+F11+F17+F23+F29 -> 15698.9 | G34: =G5+G11+G17+G23+G29 -> 16532.027 | H34: =H5+H11+H17+H23+H29 -> 17233.402 | I34: =I5+I11+I17+I23+I29 -> 18087.415 | ... K34: =K5+K11+K17+K23+K29 -> 19739.564
B37: =B9+B15+B21+B27 -> 7278.4797 | C37: =C9+C15+C21+C27 -> 7761.7471 | D37: =D9+D15+D21+D27 -> 8949.9331 | E37: =E9+E15+E21+E27 -> 9118.9 | F37: =F9+F15+F21+F27 -> 8968.2 | G37: =G9+G15+G21+G27 -> 10108.981 | H37: =H9+H15+H21+H27 -> 10472.707 | I37: =I9+I15+I21+I27 -> 10900.544 | ... K37: =K9+K15+K21+K27 -> 11942.224
B38: 9.8 | C38: 47.5 | D38: -50.1

Sheet COGS
A3: Segment / Line Item | B3: 2022 | C3: 2023 | D3: 2024 | E3: 2025 | F3: 2026 | G3: 2027 | H3: 2028 | I3: 2029
A4: 🏭 Global Industrial
A5: Net Sales | B5: 7172.6 | C5: 7640.5 | D5: 7857.2 | E5: =Revenue!G6 -> 8062.243 | F5: =Revenue!H6 -> 8357.9865 | G5: =Revenue!I6 -> 8636.2583 | H5: =Revenue!J6 -> 8924.3255 | I5: =Revenue!K6 -> 9222.5442
A6: Cost of Sales (COS) | B6: 4692.1 | C6: 4769.7 | D6: 4691.2 | E6: =E5*E7 -> 4837.3458 | F6: =F5*F7 -> 5014.7919 | G6: =G5*G7 -> 5181.755 | H6: =H5*H7 -> 5354.5953 | I6: =I5*I7 -> 5533.5265
B7: =B6/B5 -> 0.65417004 | C7: =C6/C5 -> 0.62426543 | D7: =D6/D5 -> 0.59705748 | E7: =+CHOOSE(Cover!$I$13,E8,E9,E10) -> 0.6 | F7: =+CHOOSE(Cover!$I$13,F8,F9,F10) -> 0.6 | G7: =+CHOOSE(Cover!$I$13,G8,G9,G10) -> 0.6 | H7: =+CHOOSE(Cover!$I$13,H8,H9,H10) -> 0.6 | I7: =+CHOOSE(Cover!$I$13,I8,I9,I10) -> 0.6 | L7: COS (% of sales): Held ~60% as 2024 price/cost tailwinds persist but are tempered by reinvestment, consistent with the company’s margin expansion drivers.
A8: bull | E8: 0.58 | F8: 0.58 | G8: 0.58 | H8: 0.58 | I8: 0.58
A9: base | E9: 0.6 | F9: 0.6 | G9: 0.6 | H9: 0.6 | I9: 0.6
A10: bear | E10: 0.62 | F10: 0.62 | G10: 0.62 | H10: 0.62 | I10: 0.62
A11: SG&A | B11: 1531.6 | C11: 1748.8 | D11: 1865.4 | E11: =E12*E5 -> 1934.9383 | F11: =F12*F5 -> 2005.9167 | G11: =G12*G5 -> 2072.702 | H11: =H12*H5 -> 2141.8381 | I11: =I12*I5 -> 2213.4106
B12: =B11/B5 -> 0.21353484 | C12: =C11/C5 -> 0.22888554 | D12: =D11/D5 -> 0.23741282 | E12: 0.24 | F12: 0.24 | G12: 0.24 | H12: 0.24 | I12: 0.24 | L12: SG&A (% of sales): ~24% (steady) to reflect ongoing growth investments vs. productivity (company SG&A ratio sat ~26.9% in 2024).
A13: Special (gains) & charges | B13: – | C13: – | D13: – | L13: Specials: None at the segment level because ECL does not allocate specials to reportable segments.
A14: 🏨 Global Institutional & Specialty
A15: Net Sales | B15: 4433.2 | C15: 5014.6 | D15: 5413.9 | E15: =Revenue!G9 -> 5649.228 | F15: =Revenue!H9 -> 5929.1352 | G15: =Revenue!I9 -> 6222.9866 | H15: =Revenue!J9 -> 6531.4807 | I15: =Revenue!K9 -> 6855.3511
A16: Cost of Sales (COS) | B16: 2491.3 | C16: 2727.3 | D16: 2727.5 | E16: =E15*E17 -> 2824.614 | F16: =F15*F17 -> 2964.5676 | G16: =G15*G17 -> 3111.4933 | H16: =H15*H17 -> 3265.7403 | I16: =I15*I17 -> 3427.6755
B17: =B16/B15 -> 0.56196427 | C17: =C16/C15 -> 0.54387189 | D17: =D16/D15 -> 0.50379578 | E17: =+CHOOSE(Cover!$I$14,E18,E19,E20) -> 0.5 | F17: =+CHOOSE(Cover!$I$14,F18,F19,F20) -> 0.5 | G17: =+CHOOSE(Cover!$I$14,G18,G19,G20) -> 0.5 | H17: =+CHOOSE(Cover!$I$14,H18,H19,H20) -> 0.5 | I17: =+CHOOSE(Cover!$I$14,I18,I19,I20) -> 0.5 | L17: Moves toward 50% as 2024 margin drivers (value pricing, lower delivered costs) carry forward.
A18: bull | E18: 0.48 | F18: 0.48 | G18: 0.48 | H18: 0.48 | I18: 0.48
A19: base | E19: 0.5 | F19: 0.5 | G19: 0.5 | H19: 0.5 | I19: 0.5
A20: bear | E20: 0.52 | F20: 0.52 | G20: 0.52 | H20: 0.52 | I20: 0.52
A21: SG&A | B21: 1310 | C21: 1445.5 | D21: 1503.7 | E21: =E22*E15 -> 1581.7838 | F21: =F22*F15 -> 1660.1579 | G21: =G22*G15 -> 1742.4362 | H21: =H22*H15 -> 1828.8146 | I21: =I22*I15 -> 1919.4983
B22: =B21/B15 -> 0.29549761 | C22: =C21/C15 -> 0.28825829 | D22: =D21/D15 -> 0.27774802 | E22: 0.28 | F22: 0.28 | G22: 0.28 | H22: 0.28 | I22: 0.28 | L22: ~28% (flat) reflecting scale benefits offset by continued commercial investment.
A23: Special (gains) & charges | B23: – | C23: – | D23: – | L23: Not allocated to segments.
A24: 🧬 Global Healthcare & Life Sciences
A25: Net Sales | B25: 1534.3 | C25: 1607.5 | D25: 1434.1 | E25: =Revenue!G12 -> 1489.0625 | F25: =Revenue!H12 -> 1562.8865 | G25: =Revenue!I12 -> 1631.8982 | H25: =Revenue!J12 -> 1704.0257 | I25: =Revenue!K12 -> 1779.4138
A26: Cost of Sales (COS) | B26: 956.2 | C26: 1026.9 | D26: 895.1 | E26: =E25*E27 -> 923.21875 | F26: =F25*F27 -> 968.98963 | G26: =G25*G27 -> 1011.7769 | H26: =H25*H27 -> 1056.496 | I26: =I25*I27 -> 1103.2366
B27: =B26/B25 -> 0.6232158 | C27: =C26/C25 -> 0.63881804 | D27: =D26/D25 -> 0.62415452 | E27: 0.62 | F27: 0.62 | G27: 0.62 | H27: 0.62 | I27: 0.62 | L27: Kept ~62% as mix/volume headwinds offset pricing—consistent with MD&A noting pricing gains partly offset by lower volumes.
A28: SG&A | B28: 384.7 | C28: 419.8 | D28: 391.8 | E28: =E29*E25 -> 387.15625 | F28: =F29*F25 -> 406.35049 | G28: =G29*G25 -> 424.29353 | H28: =H29*H25 -> 443.04669 | I28: =I29*I25 -> 462.64759
B29: =B28/B25 -> 0.25073323 | C29: =C28/C25 -> 0.26115086 | D29: =D28/D25 -> 0.27320271 | E29: 0.26 | F29: 0.26 | G29: 0.26 | H29: 0.26 | I29: 0.26 | L29: ~26–27% (steady) to reflect ongoing reinvestment while scaling Life Sciences.
A30: Special (gains) & charges | B30: – | C30: – | D30: – | L30: Not allocated to segments.
A31: 🪳 Global Pest Elimination
A32: Net Sales | B32: 963.5 | C32: 1070.2 | D32: 1167.8 | E32: ='Cost of sales'!G23 -> 1218.951 | F32: ='Cost of sales'!H23 -> 1277.8364 | G32: ='Cost of sales'!I23 -> 1339.5902 | H32: ='Cost of sales'!J23 -> 1404.3535 | I32: ='Cost of sales'!K23 -> 1472.2738
A33: Cost of Sales (COS) | B33: 537.8 | C33: 595 | D33: 655 | E33: =E32*E34 -> 683.68976 | F33: =F32*F34 -> 716.7176 | G33: =G32*G34 -> 751.35435 | H33: =H32*H34 -> 787.67899 | I33: =I32*I34 -> 825.77438
B34: =B33/B32 -> 0.55817333 | C34: =C33/C32 -> 0.55597085 | D34: =D33/D32 -> 0.56088371 | E34: =D34 -> 0.56088371 | F34: =E34 -> 0.56088371 | G34: =F34 -> 0.56088371 | H34: =G34 -> 0.56088371 | I34: =H34 -> 0.56088371 | L34: ~56% (service-heavy model; stable).
A35: SG&A | B35: 228.4 | C35: 264.8 | D35: 292.4 | E35: =E36*E32 -> 304.73775 | F35: =F36*F32 -> 319.45909 | G35: =G36*G32 -> 334.89756 | H35: =H36*H32 -> 351.08837 | I35: =I36*I32 -> 368.06844
B36: =B35/B32 -> 0.23705241 | C36: =C35/C32 -> 0.24743039 | D36: =D35/D32 -> 0.25038534 | E36: 0.25 | F36: 0.25 | G36: 0.25 | H36: 0.25 | I36: 0.25 | L36: ~25% (stable) as digital tools scale field productivity.
A37: Special (gains) & charges | B37: – | C37: – | D37: – | L37: Not allocated to segments.
A38: 🏢 Corporate / Other
A39: Net Sales | B39: 89.2 | C39: 42.7 | D39: -5.4 | E39: 0 | F39: 0 | G39: 0 | H39: 0 | I39: 0 | L39: Modeled to zero as transitional ChampionX product sales in Corporate wind down.
A40: Cost of Sales (COS) | B40: 159 | C40: 63.3 | D40: 199.3 | E40: 0 | F40: 0 | G40: 0 | H40: 0 | I40: 0 | L40: Modeled to zero as transitional ChampionX product sales in Corporate wind down.
A41: SG&A | B41: 204 | C41: 200.8 | D41: 188.9 | E41: 200 | F41: 200 | G41: 200 | H41: 200 | I41: 200 | L41: Flat ~$200mm proxy for HQ, shared services and unallocated amortization (Corporate includes Nalco/Purolite intangible amortization and specials).
A42: Special (gains) & charges | B42: 140.5 | C42: 111.4 | D42: -188.9 | E42: 100 | F42: 100 | G42: 100 | H42: 100 | I42: 100 | L42: Normalized at $100mm per year to reflect recurring restructuring/integration activity, informed by recent history and the multi-year One Ecolab program through 2027.
A43: Subtotal (fixed currency)
A44: Net Sales | B44: =B5+B15+B25+B32+B39 -> 14192.8 | C44: =C5+C15+C25+C32+C39 -> 15375.5 | D44: =D5+D15+D25+D32+D39 -> 15867.6 | E44: =E5+E15+E25+E32+E39 -> 16419.485 | F44: =F5+F15+F25+F32+F39 -> 17127.844 | G44: =G5+G15+G25+G32+G39 -> 17830.733 | H44: =H5+H15+H25+H32+H39 -> 18564.185 | I44: =I5+I15+I25+I32+I39 -> 19329.583
A45: Cost of Sales (COS) | B45: =B6+B16+B26+B33+B40 -> 8836.4 | C45: =C6+C16+C26+C33+C40 -> 9182.2 | D45: =D6+D16+D26+D33+D40 -> 9168.1 | E45: =E6+E16+E26+E33+E40 -> 9268.8683 | F45: =F6+F16+F26+F33+F40 -> 9665.0667 | G45: =G6+G16+G26+G33+G40 -> 10056.38 | H45: =H6+H16+H26+H33+H40 -> 10464.511 | I45: =I6+I16+I26+I33+I40 -> 10890.213
B46: =B45/B44 -> 0.62259737 | C46: =C45/C44 -> 0.59719684 | D46: =D45/D44 -> 0.57778744 | E46: =E45/E44 -> 0.56450422 | F46: =F45/F44 -> 0.56428973 | G46: =G45/G44 -> 0.56399136 | H46: =H45/H44 -> 0.5636935 | I46: =I45/I44 -> 0.56339617
A47: SG&A | B47: =B11+B21+B28+B35+B41 -> 3658.7 | C47: =C11+C21+C28+C35+C41 -> 4079.7 | D47: =D11+D21+D28+D35+D41 -> 4242.2 | E47: =E11+E21+E28+E35+E41 -> 4408.6162 | F47: =F11+F21+F28+F35+F41 -> 4591.8842 | G47: =G11+G21+G28+G35+G41 -> 4774.3293 | H47: =H11+H21+H28+H35+H41 -> 4964.7878 | I47: =I11+I21+I28+I35+I41 -> 5163.625
B48: =B47/B44 -> 0.25778564 | C48: =C47/C44 -> 0.26533771 | D48: =D47/D44 -> 0.26734982 | E48: =E47/E44 -> 0.26849906 | F48: =F47/F44 -> 0.26809469 | G48: =G47/G44 -> 0.26775844 | H48: =H47/H44 -> 0.26743903 | I48: =I47/I44 -> 0.26713587
A49: Special (gains) & charges | B49: =B42 -> 140.5 | C49: =C42 -> 111.4 | D49: =D42 -> -188.9 | E49: =E42 -> 100 | F49: =F42 -> 100 | G49: =G42 -> 100 | H49: =H42 -> 100 | I49: =I42 -> 100
A50: YoY growth | C50: =(C45-B45)/B45 -> 0.039133584 | D50: =(D45-C45)/C45 -> -0.0015355797 | E50: =(E45-D45)/D45 -> 0.010991188 | F50: =(F45-E45)/E45 -> 0.042745065 | G50: =(G45-F45)/F45 -> 0.040487337 | H50: =(H45-G45)/G45 -> 0.040584295 | I50: =(I45-H45)/H45 -> 0.040680588

Sheet Temporary
A3: Segment | B3: 2020 | C3: 2021 | D3: 2022 | E3: 2023 | F3: 2024 | G3: 2025 | H3: 2026 | I3: 2027 | J3: 2028 | K3: 2029
A4: Global Industrial | N4: Industrial water treatment, AI data center cooling, sustainability
A5: Product & Equipment Sales | B5: 5052.3 | C5: 5372 | D5: 6303.9 | E5: 6710.8 | F5: 6810.8 | G5: =F5*(1+G6) -> 7355.664 | H5: =G5*(1+H6) -> 7944.1171 | I5: =H5*(1+I6) -> 8579.6465 | J5: =I5*(1+J6) -> 9266.0182 | K5: =J5*(1+K6) -> 10007.3
C6: =(C5-B5)/B5 -> 0.063278111 | D6: =(D5-C5)/C5 -> 0.17347357 | E6: =(E5-D5)/D5 -> 0.064547344 | F6: =(F5-E5)/E5 -> 0.014901353 | G6: =8% -> 0.08 | H6: =8% -> 0.08 | I6: =8% -> 0.08 | J6: =8% -> 0.08 | K6: =8% -> 0.08
A7: Service & Lease Sales | B7: 818.5 | C7: 865.8 | D7: 893.2 | E7: 915.7 | F7: 966.4 | G7: =F7*(1+G8) -> 1007.4704 | H7: =G7*(1+H8) -> 1050.2863 | I7: =H7*(1+I8) -> 1094.9217 | J7: =I7*(1+J8) -> 1141.4541 | K7: =J7*(1+K8) -> 1189.9641
C8: =(C7-B7)/B7 -> 0.057788638 | D8: =(D7-C7)/C7 -> 0.031647032 | E8: =(E7-D7)/D7 -> 0.025190327 | F8: =(F7-E7)/E7 -> 0.055367478 | G8: =AVERAGE(C8:F8) -> 0.042498369 | H8: 0.042498369 | I8: 0.042498369 | J8: 0.042498369 | K8: 0.042498369
A9: Global Institutional & Specialty | N9: Hospitality rebound, digital dishwashing (DishIQ), food safety
A10: Product & Equipment Sales | B10: 2968.7 | C10: 3265.5 | D10: 3655.1 | E10: 4087.3 | F10: 4362.2 | G10: =F10*(1+G11) -> 4803.6407 | H10: =G10*(1+H11) -> 5289.7537 | I10: =H10*(1+I11) -> 5712.934 | J10: =I10*(1+J11) -> 6169.9687 | K10: =J10*(1+K11) -> 6663.5662
C11: =(C10-B10)/B10 -> 0.099976421 | D11: =(D10-C10)/C10 -> 0.11930792 | E11: =(E10-D10)/D10 -> 0.11824574 | F11: =(F10-E10)/E10 -> 0.067257113 | G11: =AVERAGE(C11:F11) -> 0.1011968 | H11: 0.1011968 | I11: 0.08 | J11: 0.08 | K11: 0.08
A12: Service & Lease Sales | B12: 584.5 | C12: 690.4 | D12: 777 | E12: 911.9 | F12: 1020.4 | G12: =F12*(1+G13) -> 1173.2595 | H12: =G12*(1+H13) -> 1337.5158 | I12: =H12*(1+I13) -> 1511.3928 | J12: =I12*(1+J13) -> 1692.76 | K12: =J12*(1+K13) -> 1878.9636
C13: =(C12-B12)/B12 -> 0.1811805 | D13: =(D12-C12)/C12 -> 0.12543453 | E13: =(E12-D12)/D12 -> 0.17361647 | F13: =(F12-E12)/E12 -> 0.11898234 | G13: =AVERAGE(C13:F13) -> 0.14980346 | H13: 0.14 | I13: 0.13 | J13: 0.12 | K13: 0.11
A14: Global Healthcare & Life Sciences | N14: Biopharma purification, infection prevention
A15: Product & Equipment Sales | B15: 1071.4 | C15: 1068.9 | D15: 1398.1 | E15: 1476.2 | F15: 1300.6 | G15: =F15*(1+G16) -> 1365.63 | H15: =G15*(1+H16) -> 1433.9115 | I15: =H15*(1+I16) -> 1505.6071 | J15: =I15*(1+J16) -> 1580.8874 | K15: =J15*(1+K16) -> 1659.9318 | N15: The segment’s 2024 drop was likely a one-off portfolio optimization.
C16: =(C15-B15)/B15 -> -0.0023333956 | D16: =(D15-C15)/C15 -> 0.30798017 | E16: =(E15-D15)/D15 -> 0.055861526 | F16: =(F15-E15)/E15 -> -0.11895407 | G16: 0.05 | H16: 0.05 | I16: 0.05 | J16: 0.05 | K16: 0.05
A17: Service & Lease Sales | B17: 110.5 | C17: 112.7 | D17: 112.4 | E17: 109.8 | F17: 118.2 | G17: =F17*(1+G18) -> 120.28678 | H17: =G17*(1+H18) -> 122.4104 | I17: =H17*(1+I18) -> 124.57152 | J17: =I17*(1+J18) -> 126.77078 | K17: =J17*(1+K18) -> 129.00888
C18: =(C17-B17)/B17 -> 0.019909502 | D18: =(D17-C17)/C17 -> -0.0026619343 | E18: =(E17-D17)/D17 -> -0.023131673 | F18: =(F17-E17)/E17 -> 0.076502732 | G18: =AVERAGE(C18:F18) -> 0.017654657 | H18: 0.017654657 | I18: 0.017654657 | J18: 0.017654657 | K18: 0.017654657
A19: Global Pest Elimination / Other | N19: Predictive pest tech, commercial footprint expansion
A20: Product & Equipment Sales | B20: 274.5 | C20: 308.9
A21: Service & Lease Sales | B21: 809.8 | C21: 909.7 | D21: 959 | E21: 1066 | F21: 1162.8 | G21: =F21*(1+G22) -> 1273.2482 | H21: =G21*(1+H22) -> 1394.1873 | I21: =H21*(1+I22) -> 1526.6138 | J21: =I21*(1+J22) -> 1671.6187 | K21: =J21*(1+K22) -> 1830.3969
C22: =(C21-B21)/B21 -> 0.12336379 | D22: =(D21-C21)/C21 -> 0.05419369 | E22: =(E21-D21)/D21 -> 0.11157456 | F22: =(F21-E21)/E21 -> 0.090806754 | G22: =AVERAGE(C22:F22) -> 0.094984699 | H22: 0.094984699 | I22: 0.094984699 | J22: 0.094984699 | K22: 0.094984699
A23: Corporate (ChampionX and other) | N23: Non-core
A24: Product & Equipment Sales | B24: 99.77 | C24: 138 | D24: 89.1 | E24: 42.5 | F24: 0 | G24: 0 | H24: 0 | I24: 0 | J24: 0 | K24: 0 | N24: Sunset of ChampionX contract by 2024
C25: =(C24-B24)/B24 -> 0.38318132 | D25: =(D24-C24)/C24 -> -0.35434783 | E25: =(E24-D24)/D24 -> -0.52300786 | F25: =(F24-E24)/E24 -> -1
A26: Service & Lease Sales | B26: 0.3 | C26: 1.2 | D26: – | E26: – | F26: –
A27: Total Net Sales
A28: Total Product & Equipment | B28: =B5+B10+B15+B20+B24 -> 9466.67 | C28: =C5+C10+C15+C20+C24 -> 10153.3 | D28: =D5+D10+D15+D24 -> 11446.2 | E28: =E5+E10+E15+E24 -> 12316.8 | F28: =F5+F10+F15+F24 -> 12473.6 | G28: =G5+G10+G15+G24 -> 13524.935 | H28: =H5+H10+H15+H24 -> 14667.782 | I28: =I5+I10+I15+I24 -> 15798.188 | J28: =J5+J10+J15+J24 -> 17016.874 | K28: =K5+K10+K15+K24 -> 18330.798
B29: =B28/B32 -> 0.80292224 | C29: =C28/C32 -> 0.79739419 | D29: =D28/D32 -> 0.80676356 | E29: =E28/E32 -> 0.80395817 | F29: =F28/F32 -> 0.79240728 | G29: =G28/G32 -> 0.79096888 | H29: =H28/H32 -> 0.78977162 | I29: =I28/I32 -> 0.78771609 | ... K29: =K28/K32 -> 0.78473799
A30: Total Service & Lease | B30: =B7+B12+B17+B21+B26 -> 2323.6 | C30: =C7+C12+C17+C21+C26 -> 2579.8 | D30: =D7+D12+D17+D21 -> 2741.6 | E30: =E7+E12+E17+E21 -> 3003.4 | F30: =F7+F12+F17+F21 -> 3267.8 | G30: =G7+G12+G17+G21 -> 3574.2649 | H30: =H7+H12+H17+H21 -> 3904.3998 | I30: =I7+I12+I17+I21 -> 4257.4998 | J30: =J7+J12+J17+J21 -> 4632.6036 | K30: =K7+K12+K17+K21 -> 5028.3334
B31: =B30/B32 -> 0.19707776 | C31: =C30/C32 -> 0.20260581 | D31: =D30/D32 -> 0.19323644 | E31: =E30/E32 -> 0.19604183 | F31: =F30/F32 -> 0.20759272 | G31: =G30/G32 -> 0.20903112 | H31: =H30/H32 -> 0.21022838 | I31: =I30/I32 -> 0.21228391 | ... K31: =K30/K32 -> 0.21526201
A32: Grand Total Net Sales | B32: =B28+B30 -> 11790.27 | C32: =C28+C30 -> 12733.1 | D32: =D28+D30 -> 14187.8 | E32: =E28+E30 -> 15320.2 | F32: =F28+F30 -> 15741.4 | G32: =G28+G30 -> 17099.2 | H32: =H28+H30 -> 18572.182 | I32: =I28+I30 -> 20055.687 | ... K32: =K28+K30 -> 23359.131

Sheet Income statement
A3: CONSOLIDATED STATEMENTS OF INCOME
B4: 2020 | C4: 2021 | D4: 2022 | E4: 2023 | F4: 2024 | G4: 2025 | H4: 2026 | I4: 2027 | J4: 2028 | K4: 2029
A5: Product and equipment sales | B5: =Revenue!B23 -> 9466.67 | C5: =Revenue!C23 -> 10153.3 | D5: =Revenue!D23 -> 11446.2 | E5: =Revenue!E23 -> 12316.8 | F5: =Revenue!F23 -> 12473.6 | G5: =Revenue!G23 -> 13135.588 | H5: =Revenue!H23 -> 13702.276 | I5: =Revenue!I23 -> 14264.587 | ... K5: =Revenue!K23 -> 15463.666
A6: Service and lease sales | B6: =Revenue!B24 -> 2323.6 | C6: =Revenue!C24 -> 2579.8 | D6: =Revenue!D24 -> 2741.6 | E6: =Revenue!E24 -> 3003.4 | F6: =Revenue!F24 -> 3267.8 | G6: =Revenue!G24 -> 3283.8969 | H6: =Revenue!H24 -> 3425.5689 | I6: =Revenue!I24 -> 3566.1467 | ... K6: =Revenue!K24 -> 3865.9166
A7: Net sales | B7: =B5+B6 -> 11790.27 | C7: =C5+C6 -> 12733.1 | D7: =D5+D6 -> 14187.8 | E7: =E5+E6 -> 15320.2 | F7: =Revenue!F21 -> 15741.4 | G7: =Revenue!G21 -> 16419.485 | H7: =Revenue!H21 -> 17127.844 | I7: =Revenue!I21 -> 17830.733 | J7: =Revenue!J21 -> 18564.185 | K7: =Revenue!K21 -> 19329.583
A8: Product and equipment cost of sales | B8: 5481.3 | C8: 6100.9 | D8: 7212.8 | E8: 7389.2 | F8: 6990
A9: Service and lease cost of sales | B9: 1424.5 | C9: 1514.9 | D9: 1618.2 | E9: 1765.7 | F9: 1909.7
A10: Cost of sales | B10: =B8+B9 -> 6905.8 | C10: =C8+C9 -> 7615.8 | D10: =D8+D9 -> 8831 | E10: =E8+E9 -> 9154.9 | F10: =F8+F9 -> 8899.7 | G10: =COGS!E45 -> 9268.8683 | H10: =COGS!F45 -> 9665.0667 | I10: =COGS!G45 -> 10056.38 | J10: =COGS!H45 -> 10464.511 | K10: =COGS!I45 -> 10890.213
A11: Selling, general and administrative expenses | B11: 3309.1 | C11: 3416.1 | D11: 3653.8 | E11: 4061.6 | F11: 4228.2 | G11: =COGS!E47 -> 4408.6162 | H11: =COGS!F47 -> 4591.8842 | I11: =COGS!G47 -> 4774.3293 | J11: =COGS!H47 -> 4964.7878 | K11: =COGS!I47 -> 5163.625
A12: Special (gains) and charges | B12: 179.6 | C12: 102.6 | D12: 140.5 | E12: 111.4 | F12: -188.9 | G12: =COGS!E49 -> 100 | H12: =COGS!F49 -> 100 | I12: =COGS!G49 -> 100 | J12: =COGS!H49 -> 100 | K12: =COGS!I49 -> 100
A13: Operating income | B13: =B7-B10-B11-B12 -> 1395.77 | C13: =C7-C10-C11-C12 -> 1598.6 | D13: =D7-D10-D11-D12 -> 1562.5 | E13: =E7-E10-E11-E12 -> 1992.3 | F13: =F7-F10-F11-F12 -> 2802.4 | G13: =G7-G10-G11-G12 -> 2642 | H13: =H7-H10-H11-H12 -> 2770.8936 | I13: =I7-I10-I11-I12 -> 2900.0245 | ... K13: =K7-K10-K11-K12 -> 3175.7449
A14: Other (income) expense | B14: -55.9 | C14: -33.9 | D14: -24.5 | E14: -59.9 | F14: -51.3 | G14: -50 | H14: -50 | I14: -50 | J14: -50 | K14: -50
A15: Interest expense, net | B15: 290.2 | C15: 218.3 | D15: 243.6 | E15: 296.7 | F15: 282.5 | G15: =Schedules!C51 -> 267.976 | H15: =Schedules!D51 -> 288.2 | I15: =Schedules!E51 -> 302.58 | J15: =Schedules!F51 -> 322.56 | K15: =Schedules!G51 -> 340.41
A16: Income before income taxes | B16: =B13-B14-B15 -> 1161.47 | C16: =C13-C14-C15 -> 1414.2 | D16: =D13-D14-D15 -> 1343.4 | E16: =E13-E14-E15 -> 1755.5 | F16: =F13-F14-F15 -> 2571.2 | G16: =G13-G14-G15 -> 2424.024 | H16: =H13-H14-H15 -> 2532.6936 | I16: =I13-I14-I15 -> 2647.4445 | ... K16: =K13-K14-K15 -> 2885.3349
A17: Provision for income taxes | B17: 176.6 | C17: 270.2 | D17: 234.5 | E17: 362.5 | F17: 439.3 | G17: =G16*G44 -> 472.68469 | H17: =H16*H44 -> 468.86428 | I17: =I16*I44 -> 490.10751 | J17: =J16*J44 -> 511.37511 | K17: =K16*K44 -> 534.14692
A18: Net income including noncontrolling interest | B18: =B16-B17 -> 984.87 | C18: =C16-C17 -> 1144 | D18: =D16-D17 -> 1108.9 | E18: =E16-E17 -> 1393 | F18: =F16-F17 -> 2131.9 | G18: =G16-G17 -> 1951.3393 | H18: =H16-H17 -> 2063.8293 | I18: =I16-I17 -> 2157.337 | ... K18: =K16-K17 -> 2351.188
A19: Net income attributable to noncontrolling interest | B19: 17.4 | C19: 14.1 | D19: 17.2 | E19: 20.7 | F19: 19.5 | G19: 20 | H19: 20 | I19: 20 | J19: 20 | K19: 20
A20: Net income attributable to Ecolab | B20: =B18-B19 -> 967.47 | C20: =C18-C19 -> 1129.9 | D20: =D18-D19 -> 1091.7 | E20: =E18-E19 -> 1372.3 | F20: =F18-F19 -> 2112.4 | G20: =G18-G19 -> 1931.3393 | H20: =H18-H19 -> 2043.8293 | I20: =I18-I19 -> 2137.337 | ... K20: =K18-K19 -> 2331.188
A21: Net loss from discontinued operations, net of tax | B21: -2172.5 | C21: 0 | D21: 0 | E21: 0 | F21: 0 | G21: 0 | H21: 0 | I21: 0 | J21: 0 | K21: 0
A22: Net income (loss) attributable to Ecolab (total) | B22: =B20+B21 -> -1205.03 | C22: =C20+C21 -> 1129.9 | D22: =D20+D21 -> 1091.7 | E22: =E20+E21 -> 1372.3 | F22: =F20+F21 -> 2112.4 | G22: =G20+G21 -> 1931.3393 | H22: =H20+H21 -> 2043.8293 | I22: =I20+I21 -> 2137.337 | ... K22: =K20+K21 -> 2331.188
A30: Assumptions
B31: 2020 | C31: 2021 | D31: 2022 | E31: 2023 | F31: 2024 | G31: 2025 | H31: 2026 | I31: 2027 | J31: 2028 | K31: 2029
A32: Product and equipment sales | O32: Revenue model
A33: Service and lease sales
A34: Net sales
A35: Product and equipment cost of sales
A36: Service and lease cost of sales
A37: Cost of sales | O37: COGS sheet
A38: Selling, general and administrative expenses
A39: Special (gains) and charges | O39: Normalized to ~$100mm/yr post-2024 to reflect ongoing restructuring/integration under the “One Ecolab” program (company disclosed expected restructuring/special charges cadence).
A40: Operating income | B40: =B13/B7 -> 0.11838321 | C40: =C13/C7 -> 0.1255468 | D40: =D13/D7 -> 0.11012983 | E40: =E13/E7 -> 0.13004399 | F40: =F13/F7 -> 0.17802737 | G40: =G13/G7 -> 0.16090639 | H40: =H13/H7 -> 0.16177714 | I40: =I13/I7 -> 0.16264191 | ... K40: =K13/K7 -> 0.16429454
A41: Other (income) expense | O41: Modeled at ~$(50)mm) (credit) as a clean, non-discrete run-rate around recent levels (Q4 note on pension/other).
A42: Interest expense, net | O42: Near-term step down from 2024 levels (benefit from rates) then slight upward normalization with refinancing/average debt costs.
A43: Income before income taxes
A44: Provision for income taxes | B44: =B17/B16 -> 0.1520487 | C44: =C17/C16 -> 0.19106208 | D44: =D17/D16 -> 0.17455709 | E44: =E17/E16 -> 0.20649388 | F44: =F17/F16 -> 0.17085408 | G44: 0.195 | H44: 0.18512475 | I44: 0.18512475 | J44: 0.18512475 | K44: 0.18512475 | O44: Forward ETR set ~19% anchored to Ecolab’s 2024 effective rate (~17%) and ~19% adjusted tax-rate range cited in company materials.
A45: Net income including noncontrolling interest
A46: Net income attributable to noncontrolling interest | O46: Flat ~$20mm consistent with the small, stable historical contribution of NCI.
A47: Net income attributable to Ecolab
A48: Net loss from discontinued operations, net of tax | O48: None assumed after 2020; no additional divestitures modeled beyond the 2024 surgical solutions sale already reflected in history.
A49: Net income (loss) attributable to Ecolab (total)
O50: Follows NI and share count; 2025 trajectory broadly in line with management’s +12–15% EPS growth outlook

Sheet Cash flow  2
B1: 2025 | C1: 2026 | D1: 2027 | E1: 2028 | F1: 2029
A2: Net income | B2: =+'Income statement'!G20 -> 1931.3393 | C2: =+'Income statement'!H20 -> 2043.8293 | D2: =+'Income statement'!I20 -> 2137.337 | E2: =+'Income statement'!J20 -> 2230.9519 | F2: =+'Income statement'!K20 -> 2331.188
A4: ASSETS
A5: Current assets
A6: Cash and cash equivalents
A7: Accounts receivable, net | B7: =+'Balance sheet'!F7-'Balance sheet'!G7 -> -104.00268 | C7: =+'Balance sheet'!G7-'Balance sheet'!H7 -> -81.161412 | D7: =+'Balance sheet'!H7-'Balance sheet'!I7 -> -125.17198 | E7: =+'Balance sheet'!I7-'Balance sheet'!J7 -> -130.61475 | F7: =+'Balance sheet'!J7-'Balance sheet'!K7 -> -136.30367
A8: Inventories | B8: =+'Balance sheet'!F8-'Balance sheet'!G8 -> -79.911385 | C8: =+'Balance sheet'!G8-'Balance sheet'!H8 -> -66.033064 | D8: =+'Balance sheet'!H8-'Balance sheet'!I8 -> -65.218802 | E8: =+'Balance sheet'!I8-'Balance sheet'!J8 -> -68.021846 | F8: =+'Balance sheet'!J8-'Balance sheet'!K8 -> -70.950407
A9: Other current assets | B9: =+'Balance sheet'!F9-'Balance sheet'!G9 -> -1.861616 | C9: =+'Balance sheet'!G9-'Balance sheet'!H9 -> -18.326802 | D9: =+'Balance sheet'!H9-'Balance sheet'!I9 -> -18.244515 | E9: =+'Balance sheet'!I9-'Balance sheet'!J9 -> -19.045844 | F9: =+'Balance sheet'!J9-'Balance sheet'!K9 -> -19.883719
A10: Total current assets
A11: Property, plant and equipment, net | B11: =+'Balance sheet'!F11-'Balance sheet'!G11 -> -280.07703 | C11: =+'Balance sheet'!G11-'Balance sheet'!H11 -> -269.95096 | D11: =+'Balance sheet'!H11-'Balance sheet'!I11 -> -261.39935 | E11: =+'Balance sheet'!I11-'Balance sheet'!J11 -> -256.28841 | F11: =+'Balance sheet'!J11-'Balance sheet'!K11 -> -254.05457
A12: Goodwill | B12: =+'Balance sheet'!F12-'Balance sheet'!G12 -> 0 | C12: =+'Balance sheet'!G12-'Balance sheet'!H12 -> 0 | D12: =+'Balance sheet'!H12-'Balance sheet'!I12 -> 0 | E12: =+'Balance sheet'!I12-'Balance sheet'!J12 -> 0 | F12: =+'Balance sheet'!J12-'Balance sheet'!K12 -> 0
A13: Other intangible assets, net | B13: =+'Balance sheet'!F13-'Balance sheet'!G13 -> 293 | C13: =+'Balance sheet'!G13-'Balance sheet'!H13 -> 287 | D13: =+'Balance sheet'!H13-'Balance sheet'!I13 -> 165 | E13: =+'Balance sheet'!I13-'Balance sheet'!J13 -> 157 | F13: =+'Balance sheet'!J13-'Balance sheet'!K13 -> 149
A14: Operating lease assets | B14: =+'Balance sheet'!F14-'Balance sheet'!G14 -> -210.55021 | C14: =+'Balance sheet'!G14-'Balance sheet'!H14 -> -194.70402 | D14: =+'Balance sheet'!H14-'Balance sheet'!I14 -> -180.80034 | E14: =+'Balance sheet'!I14-'Balance sheet'!J14 -> -169.42388 | F14: =+'Balance sheet'!J14-'Balance sheet'!K14 -> -160.24709
A15: Other assets | B15: =+'Balance sheet'!F15-'Balance sheet'!G15 -> 19.112732 | C15: =+'Balance sheet'!G15-'Balance sheet'!H15 -> -25.676405 | D15: =+'Balance sheet'!H15-'Balance sheet'!I15 -> -15.812366 | E15: =+'Balance sheet'!I15-'Balance sheet'!J15 -> -32.719797 | F15: =+'Balance sheet'!J15-'Balance sheet'!K15 -> -46.571499
A16: Total assets
A18: LIABILITIES AND EQUITY
A19: Current liabilities
A20: Short-term debt | B20: =+'Balance sheet'!G20-'Balance sheet'!F20 -> -43.3 | C20: ='Balance sheet'!H20-'Balance sheet'!G20 -> 8 | D20: ='Balance sheet'!I20-'Balance sheet'!H20 -> 20 | E20: ='Balance sheet'!J20-'Balance sheet'!I20 -> 28 | F20: ='Balance sheet'!K20-'Balance sheet'!J20 -> 40
A21: Accounts payable | B21: =+'Balance sheet'!G21-'Balance sheet'!F21 -> -172.49315 | C21: =+'Balance sheet'!H21-'Balance sheet'!G21 -> 67.925395 | D21: =+'Balance sheet'!I21-'Balance sheet'!H21 -> 72.898813 | E21: =+'Balance sheet'!J21-'Balance sheet'!I21 -> 71.999889 | F21: =+'Balance sheet'!K21-'Balance sheet'!J21 -> 75.094377
A22: Compensation and benefits | B22: =+'Balance sheet'!G22-'Balance sheet'!F22 -> -22.021414 | C22: =+'Balance sheet'!H22-'Balance sheet'!G22 -> 6.3634624 | D22: =+'Balance sheet'!I22-'Balance sheet'!H22 -> 28.278998 | E22: =+'Balance sheet'!J22-'Balance sheet'!I22 -> 4.6971189 | F22: =+'Balance sheet'!K22-'Balance sheet'!J22 -> 29.825578
A23: Income taxes | B23: =+'Balance sheet'!G23-'Balance sheet'!F23 -> 68.817592 | C23: =+'Balance sheet'!H23-'Balance sheet'!G23 -> -1.5826654 | D23: =+'Balance sheet'!I23-'Balance sheet'!H23 -> 8.8003647 | E23: =+'Balance sheet'!J23-'Balance sheet'!I23 -> 8.8104618 | F23: =+'Balance sheet'!K23-'Balance sheet'!J23 -> 9.4336042
A24: Other current liabilities | B24: =+'Balance sheet'!G24-'Balance sheet'!F24 -> 12.87411 | C24: =+'Balance sheet'!H24-'Balance sheet'!G24 -> 41.468191 | D24: =+'Balance sheet'!I24-'Balance sheet'!H24 -> 64.307948 | E24: =+'Balance sheet'!J24-'Balance sheet'!I24 -> 67.104205 | F24: =+'Balance sheet'!K24-'Balance sheet'!J24 -> 70.026926
A25: Total current liabilities
A26: Long-term debt | B26: =+'Balance sheet'!G26-'Balance sheet'!F26 -> 205.8 | C26: =+'Balance sheet'!H26-'Balance sheet'!G26 -> 100 | D26: =+'Balance sheet'!I26-'Balance sheet'!H26 -> 250 | E26: =+'Balance sheet'!J26-'Balance sheet'!I26 -> 350 | F26: =+'Balance sheet'!K26-'Balance sheet'!J26 -> 500
A27: Pension and post-retirement benefits | B27: =+'Balance sheet'!G27-'Balance sheet'!F27 -> 0 | C27: =+'Balance sheet'!H27-'Balance sheet'!G27 -> 0 | D27: =+'Balance sheet'!I27-'Balance sheet'!H27 -> 0 | E27: =+'Balance sheet'!J27-'Balance sheet'!I27 -> 0 | F27: =+'Balance sheet'!K27-'Balance sheet'!J27 -> 0
A28: Deferred income taxes | B28: =+'Balance sheet'!G28-'Balance sheet'!F28 -> 569.81131 | C28: =+'Balance sheet'!H28-'Balance sheet'!G28 -> -95.226024 | D28: =+'Balance sheet'!I28-'Balance sheet'!H28 -> -33.701942 | E28: =+'Balance sheet'!J28-'Balance sheet'!I28 -> -38.797935 | F28: =+'Balance sheet'!K28-'Balance sheet'!J28 -> 49.621163
A29: Operating lease liabilities | B29: =+'Balance sheet'!G29-'Balance sheet'!F29 -> 135.67616 | C29: =+'Balance sheet'!H29-'Balance sheet'!G29 -> 141.94324 | D29: =+'Balance sheet'!I29-'Balance sheet'!H29 -> 128.62715 | E29: =+'Balance sheet'!J29-'Balance sheet'!I29 -> 134.97562 | F29: =+'Balance sheet'!K29-'Balance sheet'!J29 -> 141.80966
A30: Other liabilities | B30: =+'Balance sheet'!G30-'Balance sheet'!F30 -> 38.620451 | C30: =+'Balance sheet'!H30-'Balance sheet'!G30 -> 17.421924 | D30: =+'Balance sheet'!I30-'Balance sheet'!H30 -> 17.327893 | E30: =+'Balance sheet'!J30-'Balance sheet'!I30 -> 18.081349 | F30: =+'Balance sheet'!K30-'Balance sheet'!J30 -> 18.868882
A31: Total liabilities
A33: Equity
A34: Common stock ($1 par value) | B34: =+'Balance sheet'!G34-'Balance sheet'!F34 -> 2 | C34: =+'Balance sheet'!H34-'Balance sheet'!G34 -> 1.5 | D34: =+'Balance sheet'!I34-'Balance sheet'!H34 -> 1 | E34: =+'Balance sheet'!J34-'Balance sheet'!I34 -> 1 | F34: =+'Balance sheet'!K34-'Balance sheet'!J34 -> 1
A35: Additional paid-in capital | B35: =+'Balance sheet'!G35-'Balance sheet'!F35 -> 328.38969 | C35: =+'Balance sheet'!H35-'Balance sheet'!G35 -> 342.55689 | D35: =+'Balance sheet'!I35-'Balance sheet'!H35 -> 356.61467 | E35: =+'Balance sheet'!J35-'Balance sheet'!I35 -> 371.28371 | F35: =+'Balance sheet'!K35-'Balance sheet'!J35 -> 386.59166
A36: Retained earnings
A37: Accumulated other comprehensive loss | B37: =+'Balance sheet'!G37-'Balance sheet'!F37 -> 0 | C37: =+'Balance sheet'!H37-'Balance sheet'!G37 -> 32 | D37: =+'Balance sheet'!I37-'Balance sheet'!H37 -> 30 | E37: =+'Balance sheet'!J37-'Balance sheet'!I37 -> 20 | F37: =+'Balance sheet'!K37-'Balance sheet'!J37 -> 20
A38: Treasury stock | B38: =+'Balance sheet'!G38-'Balance sheet'!F38 -> -499.8 | C38: =+'Balance sheet'!H38-'Balance sheet'!G38 -> -500 | D38: =+'Balance sheet'!I38-'Balance sheet'!H38 -> -500 | E38: =+'Balance sheet'!J38-'Balance sheet'!I38 -> -500 | F38: =+'Balance sheet'!K38-'Balance sheet'!J38 -> -500
A39: Total Ecolab shareholders’ equity
A40: Noncontrolling interest | B40: =+'Balance sheet'!G40-'Balance sheet'!F40 -> 0 | C40: =+'Balance sheet'!H40-'Balance sheet'!G40 -> 0 | D40: =+'Balance sheet'!I40-'Balance sheet'!H40 -> 0 | E40: =+'Balance sheet'!J40-'Balance sheet'!I40 -> 0 | F40: =+'Balance sheet'!K40-'Balance sheet'!J40 -> 0
A41: Total equity
A42: Total liabilities and equity
A43: Dividends | B43: =Schedules!G7 -> 690.1 | C43: =Schedules!H7 -> 703.902 | D43: =Schedules!I7 -> 725.01906 | E43: =Schedules!J7 -> 739.51944 | F43: =Schedules!K7 -> 761.70502
A45: Net cash generated | B45: =B2+B7+B8+B9+B11+B12+B13+B14+B15+B20+B21+B22+B23+B24+B26+B27+B28+B29+B30+B34+B35+B37+B38+B40-B43 -> 1501.3239 | C45: =C2+C7+C8+C9+C11+C12+C13+C14+C15+C20+C21+C22+C23+C24+C26+C27+C28+C29+C30+C34+C35+C37+C38+C40-C43 -> 1133.4451 | D45: =D2+D7+D8+D9+D11+D12+D13+D14+D15+D20+D21+D22+D23+D24+D26+D27+D28+D29+D30+D34+D35+D37+D38+D40-D43 -> 1354.8245 | E45: =E2+E7+E8+E9+E11+E12+E13+E14+E15+E20+E21+E22+E23+E24+E26+E27+E28+E29+E30+E34+E35+E37+E38+E40-E43 -> 1509.4724 | F45: =F2+F7+F8+F9+F11+F12+F13+F14+F15+F20+F21+F22+F23+F24+F26+F27+F28+F29+F30+F34+F35+F37+F38+F40-F43 -> 1872.7439
A47: cash starting | B47: ='Balance sheet'!F6 -> 1256.8 | C47: =B49 -> 2758.1239 | D47: =C49 -> 3891.569 | E47: =D49 -> 5246.3935 | F47: =E49 -> 6755.8658
A49: ending cash | B49: =B47+B45 -> 2758.1239 | C49: =C47+C45 -> 3891.569 | D49: =D47+D45 -> 5246.3935 | E49: =E47+E45 -> 6755.8658 | F49: =F47+F45 -> 8628.6097
A52: FCFE | B52: =B45+B43 -> 2191.4239 | C52: =C45+C43 -> 1837.3471 | D52: =D45+D43 -> 2079.8435 | E52: =E45+E43 -> 2248.9918 | F52: =F45+F43 -> 2634.4489
A54: Check | B54: =+'Balance sheet'!G16-'Balance sheet'!G42 -> 0.1 | C54: =+'Balance sheet'!H16-'Balance sheet'!H42 -> 0.1 | D54: =+'Balance sheet'!I16-'Balance sheet'!I42 -> 0.1 | E54: =+'Balance sheet'!J16-'Balance sheet'!J42 -> 0.1 | F54: =+'Balance sheet'!K16-'Balance sheet'!K42 -> 0.1

Sheet Cash flow
B1: 2021 | C1: 2022 | D1: 2023 | E1: 2024 | F1: 2025 | G1: 2026 | H1: 2027 | I1: 2028 | J1: 2029
A2: Net income | B2: ='Income statement'!C20 -> 1129.9 | C2: ='Income statement'!D20 -> 1091.7 | D2: ='Income statement'!E20 -> 1372.3 | E2: ='Income statement'!F20 -> 2112.4 | F2: ='Income statement'!G20 -> 1931.3393 | G2: ='Income statement'!H20 -> 2043.8293 | H2: ='Income statement'!I20 -> 2137.337 | I2: ='Income statement'!J20 -> 2230.9519 | J2: ='Income statement'!K20 -> 2331.188
A3: ASSETS
A4: Current assets
A5: Cash and cash equivalents
A6: Accounts receivable, net | B6: ='Balance sheet'!B7-'Balance sheet'!C7 -> -204.6 | C6: ='Balance sheet'!C7-'Balance sheet'!D7 -> -219.7 | D6: ='Balance sheet'!D7-'Balance sheet'!E7 -> -136.1 | E6: ='Balance sheet'!E7-'Balance sheet'!F7 -> -30.8 | F6: ='Balance sheet'!F7-'Balance sheet'!G7 -> -104.00268 | G6: ='Balance sheet'!G7-'Balance sheet'!H7 -> -81.161412 | H6: ='Balance sheet'!H7-'Balance sheet'!I7 -> -125.17198 | I6: ='Balance sheet'!I7-'Balance sheet'!J7 -> -130.61475 | J6: ='Balance sheet'!J7-'Balance sheet'!K7 -> -136.30367
A7: Inventories | B7: ='Balance sheet'!B8-'Balance sheet'!C8 -> -206.6 | C7: ='Balance sheet'!C8-'Balance sheet'!D8 -> -301 | D7: ='Balance sheet'!D8-'Balance sheet'!E8 -> 295.6 | E7: ='Balance sheet'!E8-'Balance sheet'!F8 -> 32.3 | F7: ='Balance sheet'!F8-'Balance sheet'!G8 -> -79.911385 | G7: ='Balance sheet'!G8-'Balance sheet'!H8 -> -66.033064 | H7: ='Balance sheet'!H8-'Balance sheet'!I8 -> -65.218802 | I7: ='Balance sheet'!I8-'Balance sheet'!J8 -> -68.021846 | J7: ='Balance sheet'!J8-'Balance sheet'!K8 -> -70.950407
A8: Other current assets | B8: ='Balance sheet'!B9-'Balance sheet'!C9 -> -58.8 | C8: ='Balance sheet'!C9-'Balance sheet'!D9 -> -47.7 | D8: ='Balance sheet'!D9-'Balance sheet'!E9 -> 11.5 | E8: ='Balance sheet'!E9-'Balance sheet'!F9 -> -45.8 | F8: ='Balance sheet'!F9-'Balance sheet'!G9 -> -1.861616 | G8: ='Balance sheet'!G9-'Balance sheet'!H9 -> -18.326802 | H8: ='Balance sheet'!H9-'Balance sheet'!I9 -> -18.244515 | I8: ='Balance sheet'!I9-'Balance sheet'!J9 -> -19.045844 | J8: ='Balance sheet'!J9-'Balance sheet'!K9 -> -19.883719
A9: Total current assets
A10: Property, plant and equipment, net | B10: ='Balance sheet'!B11-'Balance sheet'!C11 -> -163.6 | C10: ='Balance sheet'!C11-'Balance sheet'!D11 -> -4.9 | D10: ='Balance sheet'!D11-'Balance sheet'!E11 -> -181.2 | E10: ='Balance sheet'!E11-'Balance sheet'!F11 -> -277.8 | F10: ='Balance sheet'!F11-'Balance sheet'!G11 -> -280.07703 | G10: ='Balance sheet'!G11-'Balance sheet'!H11 -> -269.95096 | H10: ='Balance sheet'!H11-'Balance sheet'!I11 -> -261.39935 | I10: ='Balance sheet'!I11-'Balance sheet'!J11 -> -256.28841 | J10: ='Balance sheet'!J11-'Balance sheet'!K11 -> -254.05457
A11: Goodwill | B11: ='Balance sheet'!B12-'Balance sheet'!C12 -> -2057 | C11: ='Balance sheet'!C12-'Balance sheet'!D12 -> 51.2 | D11: ='Balance sheet'!D12-'Balance sheet'!E12 -> -135.5 | E11: ='Balance sheet'!E12-'Balance sheet'!F12 -> 240.9 | F11: ='Balance sheet'!F12-'Balance sheet'!G12 -> 0 | G11: ='Balance sheet'!G12-'Balance sheet'!H12 -> 0 | H11: ='Balance sheet'!H12-'Balance sheet'!I12 -> 0 | I11: ='Balance sheet'!I12-'Balance sheet'!J12 -> 0 | J11: ='Balance sheet'!J12-'Balance sheet'!K12 -> 0
A12: Other intangible assets, net | B12: ='Balance sheet'!B13-'Balance sheet'!C13 -> -1247.1 | C12: ='Balance sheet'!C13-'Balance sheet'!D13 -> 543.4 | D12: ='Balance sheet'!D13-'Balance sheet'!E13 -> 187.2 | E12: ='Balance sheet'!E13-'Balance sheet'!F13 -> 184.7 | F12: ='Balance sheet'!F13-'Balance sheet'!G13 -> 293 | G12: ='Balance sheet'!G13-'Balance sheet'!H13 -> 287 | H12: ='Balance sheet'!H13-'Balance sheet'!I13 -> 165 | I12: ='Balance sheet'!I13-'Balance sheet'!J13 -> 157 | J12: ='Balance sheet'!J13-'Balance sheet'!K13 -> 149
A13: Operating lease assets | B13: ='Balance sheet'!B14-'Balance sheet'!C14 -> 27 | C13: ='Balance sheet'!C14-'Balance sheet'!D14 -> -51.4 | D13: ='Balance sheet'!D14-'Balance sheet'!E14 -> -105.3 | E13: ='Balance sheet'!E14-'Balance sheet'!F14 -> -169.7 | F13: ='Balance sheet'!F14-'Balance sheet'!G14 -> -210.55021 | G13: ='Balance sheet'!G14-'Balance sheet'!H14 -> -194.70402 | H13: ='Balance sheet'!H14-'Balance sheet'!I14 -> -180.80034 | I13: ='Balance sheet'!I14-'Balance sheet'!J14 -> -169.42388 | J13: ='Balance sheet'!J14-'Balance sheet'!K14 -> -160.24709
A14: Other assets | B14: ='Balance sheet'!B15-'Balance sheet'!C15 -> -70 | C14: ='Balance sheet'!C15-'Balance sheet'!D15 -> 10.9 | D14: ='Balance sheet'!D15-'Balance sheet'!E15 -> 2.4 | E14: ='Balance sheet'!E15-'Balance sheet'!F15 -> -137.7 | F14: ='Balance sheet'!F15-'Balance sheet'!G15+15 -> 34.112732 | G14: ='Balance sheet'!G15-'Balance sheet'!H15 -> -25.676405 | H14: ='Balance sheet'!H15-'Balance sheet'!I15 -> -15.812366 | I14: ='Balance sheet'!I15-'Balance sheet'!J15 -> -32.719797 | J14: ='Balance sheet'!J15-'Balance sheet'!K15 -> -46.571499
A15: Total assets
A16: LIABILITIES AND EQUITY
A17: Current liabilities
A18: Short-term debt | B18: ='Balance sheet'!C20-'Balance sheet'!B20 -> 393.7 | C18: ='Balance sheet'!D20-'Balance sheet'!C20 -> 94.1 | D18: ='Balance sheet'!E20-'Balance sheet'!D20 -> 125.3 | E18: ='Balance sheet'!F20-'Balance sheet'!E20 -> -14.7 | F18: ='Balance sheet'!G20-'Balance sheet'!F20 -> -43.3 | G18: ='Balance sheet'!H20-'Balance sheet'!G20 -> 8 | H18: ='Balance sheet'!I20-'Balance sheet'!H20 -> 20 | I18: ='Balance sheet'!J20-'Balance sheet'!I20 -> 28 | J18: ='Balance sheet'!K20-'Balance sheet'!J20 -> 40
A19: Accounts payable | B19: ='Balance sheet'!C21-'Balance sheet'!B21 -> 223.6 | C19: ='Balance sheet'!D21-'Balance sheet'!C21 -> 344 | D19: ='Balance sheet'!E21-'Balance sheet'!D21 -> -161.9 | E19: ='Balance sheet'!F21-'Balance sheet'!E21 -> 243.7 | F19: ='Balance sheet'!G21-'Balance sheet'!F21 -> -172.49315 | G19: ='Balance sheet'!H21-'Balance sheet'!G21 -> 67.925395 | H19: ='Balance sheet'!I21-'Balance sheet'!H21 -> 72.898813 | I19: ='Balance sheet'!J21-'Balance sheet'!I21 -> 71.999889 | J19: ='Balance sheet'!K21-'Balance sheet'!J21 -> 75.094377
A20: Compensation and benefits | B20: ='Balance sheet'!C22-'Balance sheet'!B22 -> 40.2 | C20: ='Balance sheet'!D22-'Balance sheet'!C22 -> -15.9 | D20: ='Balance sheet'!E22-'Balance sheet'!D22 -> 161.9 | E20: ='Balance sheet'!F22-'Balance sheet'!E22 -> 71.9 | F20: ='Balance sheet'!G22-'Balance sheet'!F22 -> -22.021414 | G20: ='Balance sheet'!H22-'Balance sheet'!G22 -> 6.3634624 | H20: ='Balance sheet'!I22-'Balance sheet'!H22 -> 28.278998 | I20: ='Balance sheet'!J22-'Balance sheet'!I22 -> 4.6971189 | J20: ='Balance sheet'!K22-'Balance sheet'!J22 -> 29.825578
A21: Income taxes | B21: ='Balance sheet'!C23-'Balance sheet'!B23 -> 8.2 | C21: ='Balance sheet'!D23-'Balance sheet'!C23 -> 93.3 | D21: ='Balance sheet'!E23-'Balance sheet'!D23 -> -38.9 | E21: ='Balance sheet'!F23-'Balance sheet'!E23 -> -31.7 | F21: ='Balance sheet'!G23-'Balance sheet'!F23 -> 68.817592 | G21: ='Balance sheet'!H23-'Balance sheet'!G23 -> -1.5826654 | H21: ='Balance sheet'!I23-'Balance sheet'!H23 -> 8.8003647 | I21: ='Balance sheet'!J23-'Balance sheet'!I23 -> 8.8104618 | J21: ='Balance sheet'!K23-'Balance sheet'!J23 -> 9.4336042
A22: Other current liabilities | B22: ='Balance sheet'!C24-'Balance sheet'!B24 -> -44.7 | C22: ='Balance sheet'!D24-'Balance sheet'!C24 -> 141.7 | D22: ='Balance sheet'!E24-'Balance sheet'!D24 -> 49 | E22: ='Balance sheet'!F24-'Balance sheet'!E24 -> 177.8 | F22: ='Balance sheet'!G24-'Balance sheet'!F24 -> 12.87411 | G22: ='Balance sheet'!H24-'Balance sheet'!G24 -> 41.468191 | H22: ='Balance sheet'!I24-'Balance sheet'!H24 -> 64.307948 | I22: ='Balance sheet'!J24-'Balance sheet'!I24 -> 67.104205 | J22: ='Balance sheet'!K24-'Balance sheet'!J24 -> 70.026926
A23: Total current liabilities
A24: Long-term debt | B24: ='Balance sheet'!C26-'Balance sheet'!B26 -> 1677.9 | C24: ='Balance sheet'!D26-'Balance sheet'!C26 -> -271.9 | D24: ='Balance sheet'!E26-'Balance sheet'!D26 -> -523.9 | E24: ='Balance sheet'!F26-'Balance sheet'!E26 -> -602.2 | F24: ='Balance sheet'!G26-'Balance sheet'!F26 -> 205.8 | G24: ='Balance sheet'!H26-'Balance sheet'!G26 -> 100 | H24: ='Balance sheet'!I26-'Balance sheet'!H26 -> 250 | I24: ='Balance sheet'!J26-'Balance sheet'!I26 -> 350 | J24: ='Balance sheet'!K26-'Balance sheet'!J26 -> 500
A25: Pension and post-retirement benefits | B25: ='Balance sheet'!C27-'Balance sheet'!B27 -> -332 | C25: ='Balance sheet'!D27-'Balance sheet'!C27 -> -223.9 | D25: ='Balance sheet'!E27-'Balance sheet'!D27 -> -18.6 | E25: ='Balance sheet'!F27-'Balance sheet'!E27 -> -16.8 | F25: ='Balance sheet'!G27-'Balance sheet'!F27 -> 0 | G25: ='Balance sheet'!H27-'Balance sheet'!G27 -> 0 | H25: ='Balance sheet'!I27-'Balance sheet'!H27 -> 0 | I25: ='Balance sheet'!J27-'Balance sheet'!I27 -> 0 | J25: ='Balance sheet'!K27-'Balance sheet'!J27 -> 0
A26: Deferred income taxes | B26: ='Balance sheet'!C28-'Balance sheet'!B28 -> 138.1 | C26: ='Balance sheet'!D28-'Balance sheet'!C28 -> -116.4 | D26: ='Balance sheet'!E28-'Balance sheet'!D28 -> -87.4 | E26: ='Balance sheet'!F28-'Balance sheet'!E28 -> -138.2 | F26: ='Balance sheet'!G28-'Balance sheet'!F28 -> 569.81131 | G26: ='Balance sheet'!H28-'Balance sheet'!G28 -> -95.226024 | H26: ='Balance sheet'!I28-'Balance sheet'!H28 -> -33.701942 | I26: ='Balance sheet'!J28-'Balance sheet'!I28 -> -38.797935 | J26: ='Balance sheet'!K28-'Balance sheet'!J28 -> 49.621163
A27: Operating lease liabilities | B27: ='Balance sheet'!C29-'Balance sheet'!B29 -> -17.9 | C27: ='Balance sheet'!D29-'Balance sheet'!C29 -> 55.2 | D27: ='Balance sheet'!E29-'Balance sheet'!D29 -> 87.7 | E27: ='Balance sheet'!F29-'Balance sheet'!E29 -> 150 | F27: ='Balance sheet'!G29-'Balance sheet'!F29 -> 135.67616 | G27: ='Balance sheet'!H29-'Balance sheet'!G29 -> 141.94324 | H27: ='Balance sheet'!I29-'Balance sheet'!H29 -> 128.62715 | I27: ='Balance sheet'!J29-'Balance sheet'!I29 -> 134.97562 | J27: ='Balance sheet'!K29-'Balance sheet'!J29 -> 141.80966
A28: Other liabilities | B28: ='Balance sheet'!C30-'Balance sheet'!B30 -> -58.3 | C28: ='Balance sheet'!D30-'Balance sheet'!C30 -> 152.2 | D28: ='Balance sheet'!E30-'Balance sheet'!D30 -> -24.5 | E28: ='Balance sheet'!F30-'Balance sheet'!E30 -> -15.6 | F28: ='Balance sheet'!G30-'Balance sheet'!F30 -> 38.620451 | G28: ='Balance sheet'!H30-'Balance sheet'!G30 -> 17.421924 | H28: ='Balance sheet'!I30-'Balance sheet'!H30 -> 17.327893 | I28: ='Balance sheet'!J30-'Balance sheet'!I30 -> 18.081349 | J28: ='Balance sheet'!K30-'Balance sheet'!J30 -> 18.868882
A29: Total liabilities
A30: Equity
A31: Common stock ($1 par value) | B31: ='Balance sheet'!C34-'Balance sheet'!B34 -> 1.5 | C31: ='Balance sheet'!D34-'Balance sheet'!C34 -> 0.6 | D31: ='Balance sheet'!E34-'Balance sheet'!D34 -> 1 | E31: ='Balance sheet'!F34-'Balance sheet'!E34 -> 2.1 | F31: ='Balance sheet'!G34-'Balance sheet'!F34 -> 2 | G31: ='Balance sheet'!H34-'Balance sheet'!G34 -> 1.5 | H31: ='Balance sheet'!I34-'Balance sheet'!H34 -> 1 | I31: ='Balance sheet'!J34-'Balance sheet'!I34 -> 1 | J31: ='Balance sheet'!K34-'Balance sheet'!J34 -> 1
A32: Additional paid-in capital | B32: ='Balance sheet'!C35-'Balance sheet'!B35 -> 229.6 | C32: ='Balance sheet'!D35-'Balance sheet'!C35 -> 115.6 | D32: ='Balance sheet'!E35-'Balance sheet'!D35 -> 186.5 | E32: ='Balance sheet'!F35-'Balance sheet'!E35 -> 392.9 | F32: ='Balance sheet'!G35-'Balance sheet'!F35 -> 328.38969 | G32: ='Balance sheet'!H35-'Balance sheet'!G35 -> 342.55689 | H32: ='Balance sheet'!I35-'Balance sheet'!H35 -> 356.61467 | I32: ='Balance sheet'!J35-'Balance sheet'!I35 -> 371.28371 | J32: ='Balance sheet'!K35-'Balance sheet'!J35 -> 386.59166
A33: Retained earnings
A34: Accumulated other comprehensive loss | B34: ='Balance sheet'!C37-'Balance sheet'!B37 -> 359.6 | C34: ='Balance sheet'!D37-'Balance sheet'!C37 -> -91.8 | D34: ='Balance sheet'!E37-'Balance sheet'!D37 -> -123.8 | E34: ='Balance sheet'!F37-'Balance sheet'!E37 -> -131.6 | F34: ='Balance sheet'!G37-'Balance sheet'!F37 -> 0 | G34: ='Balance sheet'!H37-'Balance sheet'!G37 -> 32 | H34: ='Balance sheet'!I37-'Balance sheet'!H37 -> 30 | I34: ='Balance sheet'!J37-'Balance sheet'!I37 -> 20 | J34: ='Balance sheet'!K37-'Balance sheet'!J37 -> 20
A35: Treasury stock | B35: ='Balance sheet'!C38-'Balance sheet'!B38 -> -104.5 | C35: ='Balance sheet'!D38-'Balance sheet'!C38 -> -516.8 | D35: ='Balance sheet'!E38-'Balance sheet'!D38 -> -11.7 | E35: ='Balance sheet'!F38-'Balance sheet'!E38 -> -992.5 | F35: ='Balance sheet'!G38-'Balance sheet'!F38 -> -499.8 | G35: ='Balance sheet'!H38-'Balance sheet'!G38 -> -500 | H35: ='Balance sheet'!I38-'Balance sheet'!H38 -> -500 | I35: ='Balance sheet'!J38-'Balance sheet'!I38 -> -500 | J35: ='Balance sheet'!K38-'Balance sheet'!J38 -> -500
A36: Total Ecolab shareholders’ equity
A37: Noncontrolling interest | B37: ='Balance sheet'!C40-'Balance sheet'!B40 -> -6.1 | C37: ='Balance sheet'!D40-'Balance sheet'!C40 -> -6.4 | D37: ='Balance sheet'!E40-'Balance sheet'!D40 -> 5 | E37: ='Balance sheet'!F40-'Balance sheet'!E40 -> 4.4 | F37: ='Balance sheet'!G40-'Balance sheet'!F40 -> 0 | G37: ='Balance sheet'!H40-'Balance sheet'!G40 -> 0 | H37: ='Balance sheet'!I40-'Balance sheet'!H40 -> 0 | I37: ='Balance sheet'!J40-'Balance sheet'!I40 -> 0 | J37: ='Balance sheet'!K40-'Balance sheet'!J40 -> 0
A38: Total equity
A39: Total liabilities and equity
A40: Dividends | B40: =Schedules!B7 -> 549 | C40: =Schedules!C7 -> 559 | D40: =Schedules!D7 -> 576 | E40: =Schedules!E7 -> 616 | F40: =Schedules!G7 -> 690.1 | G40: =Schedules!H7 -> 703.902 | H40: =Schedules!I7 -> 725.01906 | I40: =Schedules!J7 -> 739.51944 | J40: =Schedules!K7 -> 761.70502
A41: Repurchases
A42: Net cash generated | B42: =B2+B6+B7+B8+B10+B11+B12+B13+B14+B18+B19+B20+B21+B22+B24+B25+B26+B27+B28+B31+B32+B34+B35+B37-B40 -> -890.9 | C42: =C2+C6+C7+C8+C10+C11+C12+C13+C14+C18+C19+C20+C21+C22+C24+C25+C26+C27+C28+C31+C32+C34+C35+C37-C40 -> 267.1 | D42: =D2+D6+D7+D8+D10+D11+D12+D13+D14+D18+D19+D20+D21+D22+D24+D25+D26+D27+D28+D31+D32+D34+D35+D37-D40 -> 360.6 | E42: =E2+E6+E7+E8+E10+E11+E12+E13+E14+E18+E19+E20+E21+E22+E24+E25+E26+E27+E28+E31+E32+E34+E35+E37-E40 -> 392 | F42: =F2+F6+F7+F8+F10+F11+F12+F13+F14+F18+F19+F20+F21+F22+F24+F25+F26+F27+F28+F31+F32+F34+F35+F37-F40 -> 1516.3239 | G42: =G2+G6+G7+G8+G10+G11+G12+G13+G14+G18+G19+G20+G21+G22+G24+G25+G26+G27+G28+G31+G32+G34+G35+G37-G40 -> 1133.4451 | H42: =H2+H6+H7+H8+H10+H11+H12+H13+H14+H18+H19+H20+H21+H22+H24+H25+H26+H27+H28+H31+H32+H34+H35+H37-H40 -> 1354.8245 | I42: =I2+I6+I7+I8+I10+I11+I12+I13+I14+I18+I19+I20+I21+I22+I24+I25+I26+I27+I28+I31+I32+I34+I35+I37-I40 -> 1509.4724 | J42: =J2+J6+J7+J8+J10+J11+J12+J13+J14+J18+J19+J20+J21+J22+J24+J25+J26+J27+J28+J31+J32+J34+J35+J37-J40 -> 1872.7439
A44: cash starting | F44: ='Balance sheet'!F6 -> 1256.8 | G44: =F46 -> 2773.1239 | H44: =G46 -> 3906.569 | I44: =H46 -> 5261.3935 | J44: =I46 -> 6770.8658
A46: ending cash | F46: =F44+F42 -> 2773.1239 | G46: =G44+G42 -> 3906.569 | H46: =H44+H42 -> 5261.3935 | I46: =I44+I42 -> 6770.8658 | J46: =J44+J42 -> 8643.6097
A49: FCFE | F49: =F42+F40-F35 -> 2706.2239 | G49: =G42+G40-G35 -> 2337.3471 | H49: =H42+H40-H35 -> 2579.8435 | I49: =I42+I40-I35 -> 2748.9918 | J49: =J42+J40-J35 -> 3134.4489

Sheet Balance sheet
A2: CONSOLIDATED BALANCE SHEETS
B3: 2020 | C3: 2021 | D3: 2022 | E3: 2023 | F3: 2024 | G3: 2025 | H3: 2026 | I3: 2027 | J3: 2028 | K3: 2029
A4: ASSETS
A5: Current assets
A6: Cash and cash equivalents | B6: 1260.2 | C6: 359.9 | D6: 598.6 | E6: 919.5 | F6: 1256.8 | G6: ='Cash flow'!F46 -> 2773.1239 | H6: ='Cash flow'!G46 -> 3906.569 | I6: ='Cash flow'!H46 -> 5261.3935 | J6: ='Cash flow'!I46 -> 6770.8658 | K6: ='Cash flow'!J46 -> 8643.6097
A7: Accounts receivable, net | B7: 2273.8 | C7: 2478.4 | D7: 2698.1 | E7: 2834.2 | F7: 2865 | G7: =G53 -> 2969.0027 | H7: =H53 -> 3050.1641 | I7: =I53 -> 3175.3361 | J7: =J53 -> 3305.9508 | K7: =K53 -> 3442.2545
A8: Inventories | B8: 1285.2 | C8: 1491.8 | D8: 1792.8 | E8: 1497.2 | F8: 1464.9 | G8: =G55 -> 1544.8114 | H8: =H55 -> 1610.8444 | I8: =I55 -> 1676.0633 | J8: =J55 -> 1744.0851 | K8: =K55 -> 1815.0355
A9: Other current assets | B9: 298.2 | C9: 357 | D9: 404.7 | E9: 393.2 | F9: 439 | G9: =G57*'Income statement'!G11 -> 440.86162 | H9: =H57*'Income statement'!H11 -> 459.18842 | I9: =I57*'Income statement'!I11 -> 477.43293 | J9: =J57*'Income statement'!J11 -> 496.47878 | K9: =K57*'Income statement'!K11 -> 516.3625
A10: Total current assets | B10: =SUM(B6:B9) -> 5117.4 | C10: =SUM(C6:C9) -> 4687.1 | D10: =SUM(D6:D9) -> 5494.2 | E10: =SUM(E6:E9) -> 5644.1 | F10: =SUM(F6:F9) -> 6025.7 | G10: =SUM(G6:G9) -> 7727.7996 | H10: =SUM(H6:H9) -> 9026.766 | I10: =SUM(I6:I9) -> 10590.226 | ... K10: =SUM(K6:K9) -> 14417.262
A11: Property, plant and equipment, net | B11: 3124.9 | C11: 3288.5 | D11: 3293.4 | E11: 3474.6 | F11: 3752.4 | G11: =G100 -> 4032.477 | H11: =H100 -> 4302.428 | I11: =I100 -> 4563.8273 | J11: =J100 -> 4820.1158 | K11: =K100 -> 5074.1703
A12: Goodwill | B12: 6006.9 | C12: 8063.9 | D12: 8012.7 | E12: 8148.2 | F12: 7907.3 | G12: =G60 -> 7907.3 | H12: =H60 -> 7907.3 | I12: =I60 -> 7907.3 | J12: =J60 -> 7907.3 | K12: =K60 -> 7907.3
A13: Other intangible assets, net | B13: 2977 | C13: 4224.1 | D13: 3680.7 | E13: 3493.5 | F13: 3308.8 | G13: =Schedules!F75 -> 3015.8 | H13: =Schedules!G75 -> 2728.8 | I13: =Schedules!H75 -> 2563.8 | J13: =Schedules!I75 -> 2406.8 | K13: =Schedules!J75 -> 2257.8
A14: Operating lease assets | B14: 423.8 | C14: 396.8 | D14: 448.2 | E14: 553.5 | F14: 723.2 | G14: =Schedules!G28 -> 933.75021 | H14: =Schedules!H28 -> 1128.4542 | I14: =Schedules!I28 -> 1309.2546 | J14: =Schedules!J28 -> 1478.6784 | K14: =Schedules!K28 -> 1638.9255
A15: Other assets | B15: 476 | C15: 546 | D15: 535.1 | E15: 532.7 | F15: 670.4 | G15: =G66*'Income statement'!G7 -> 651.28727 | H15: =H66*'Income statement'!H7 -> 676.96367 | I15: =I66*'Income statement'!I7 -> 692.77604 | J15: =J66*'Income statement'!J7 -> 725.49584 | K15: =K66*'Income statement'!K7 -> 772.06734
A16: Total assets | B16: =SUM(B10:B15) -> 18126 | C16: =SUM(C10:C15) -> 21206.4 | D16: =SUM(D10:D15) -> 21464.3 | E16: =SUM(E10:E15) -> 21846.6 | F16: =SUM(F10:F15) -> 22387.8 | G16: =SUM(G10:G15) -> 24268.414 | H16: =SUM(H10:H15) -> 25770.712 | I16: =SUM(I10:I15) -> 27627.184 | ... K16: =SUM(K10:K15) -> 32067.525
A18: LIABILITIES AND EQUITY
A19: Current liabilities
A20: Short-term debt | B20: 17.3 | C20: 411 | D20: 505.1 | E20: 630.4 | F20: 615.7 | G20: =G71*G26 -> 572.4 | H20: =H71*H26 -> 580.4 | I20: =I71*I26 -> 600.4 | J20: =J71*J26 -> 628.4 | K20: =K71*K26 -> 668.4
A21: Accounts payable | B21: 1160.6 | C21: 1384.2 | D21: 1728.2 | E21: 1566.3 | F21: 1810 | G21: =G72 -> 1637.5068 | H21: =H72 -> 1705.4322 | I21: =I72 -> 1778.3311 | J21: =J72 -> 1850.3309 | K21: =K72 -> 1925.4253
A22: Compensation and benefits | B22: 469.3 | C22: 509.5 | D22: 493.6 | E22: 655.5 | F22: 727.4 | G22: =G74*'Income statement'!G11 -> 705.37859 | H22: =H74*'Income statement'!H11 -> 711.74205 | I22: =I74*'Income statement'!I11 -> 740.02105 | J22: =J74*'Income statement'!J11 -> 744.71817 | K22: =K74*'Income statement'!K11 -> 774.54374
A23: Income taxes | B23: 96.1 | C23: 104.3 | D23: 197.6 | E23: 158.7 | F23: 127 | G23: =G75*'Income statement'!G17 -> 195.81759 | H23: =H75*'Income statement'!H17 -> 194.23493 | I23: =I75*'Income statement'!I17 -> 203.03529 | J23: =J75*'Income statement'!J17 -> 211.84575 | K23: =K75*'Income statement'!K17 -> 221.27936
A24: Other current liabilities | B24: 1188.9 | C24: 1144.2 | D24: 1285.9 | E24: 1334.9 | F24: 1512.7 | G24: =G76*'Income statement'!G7 -> 1525.5741 | H24: =H76*'Income statement'!H7 -> 1567.0423 | I24: =I76*'Income statement'!I7 -> 1631.3502 | J24: =J76*'Income statement'!J7 -> 1698.4545 | K24: =K76*'Income statement'!K7 -> 1768.4814
A25: Total current liabilities | B25: =SUM(B20:B24) -> 2932.2 | C25: =SUM(C20:C24) -> 3553.2 | D25: =SUM(D20:D24) -> 4210.4 | E25: =SUM(E20:E24) -> 4345.8 | F25: =SUM(F20:F24) -> 4792.8 | G25: =SUM(G20:G24) -> 4636.6771 | H25: =SUM(H20:H24) -> 4758.8515 | I25: =SUM(I20:I24) -> 4953.1376 | ... K25: =SUM(K20:K24) -> 5358.1298
A26: Long-term debt | B26: 6669.3 | C26: 8347.2 | D26: 8075.3 | E26: 7551.4 | F26: 6949.2 | G26: =Schedules!C48 -> 7155 | H26: =Schedules!D48 -> 7255 | I26: =Schedules!E48 -> 7505 | J26: =Schedules!F48 -> 7855 | K26: =Schedules!G48 -> 8355
A27: Pension and post-retirement benefits | B27: 1226.2 | C27: 894.2 | D27: 670.3 | E27: 651.7 | F27: 634.9 | G27: 634.9 | H27: 634.9 | I27: 634.9 | J27: 634.9 | K27: 634.9
A28: Deferred income taxes | B28: 483.9 | C28: 622 | D28: 505.6 | E28: 418.2 | F28: 280 | G28: =G80*'Income statement'!G17 -> 849.81131 | H28: =H80*'Income statement'!H17 -> 754.58529 | I28: =I80*'Income statement'!I17 -> 720.88335 | J28: =J80*'Income statement'!J17 -> 682.08541 | K28: =K80*'Income statement'!K17 -> 731.70657
A29: Operating lease liabilities | B29: 300.5 | C29: 282.6 | D29: 337.8 | E29: 425.5 | F29: 575.5 | G29: =Schedules!C39 -> 711.17616 | H29: =Schedules!D39 -> 853.1194 | I29: =Schedules!E39 -> 981.74655 | J29: =Schedules!F39 -> 1116.7222 | K29: =Schedules!G39 -> 1258.5318
A30: Other liabilities | B30: 312.4 | C30: 254.1 | D30: 406.3 | E30: 381.8 | F30: 366.2 | G30: =G82*'Income statement'!G7 -> 404.82045 | H30: =H82*'Income statement'!H7 -> 422.24238 | I30: =I82*'Income statement'!I7 -> 439.57027 | J30: =J82*'Income statement'!J7 -> 457.65162 | K30: =K82*'Income statement'!K7 -> 476.5205
A31: Total liabilities | B31: =SUM(B25:B30) -> 11924.5 | C31: =SUM(C25:C30) -> 13953.3 | D31: =SUM(D25:D30) -> 14205.7 | E31: =SUM(E25:E30) -> 13774.4 | F31: =SUM(F25:F30) -> 13598.6 | G31: =SUM(G25:G30) -> 14392.385 | H31: =SUM(H25:H30) -> 14678.699 | I31: =SUM(I25:I30) -> 15235.238 | ... K31: =SUM(K25:K30) -> 16814.789
A33: Equity
A34: Common stock ($1 par value) | B34: 362.6 | C34: 364.1 | D34: 364.7 | E34: 365.7 | F34: 367.8 | G34: =F34+G86 -> 369.8 | H34: =G34+H86 -> 371.3 | I34: =H34+I86 -> 372.3 | J34: =I34+J86 -> 373.3 | K34: =J34+K86 -> 374.3
A35: Additional paid-in capital | B35: 6235 | C35: 6464.6 | D35: 6580.2 | E35: 6766.7 | F35: 7159.6 | G35: =F35+G88 -> 7487.9897 | H35: =G35+H88 -> 7830.5466 | I35: =H35+I88 -> 8187.1612 | J35: =I35+J88 -> 8558.445 | K35: =J35+K88 -> 8945.0366
A36: Retained earnings | B36: 8243 | C36: 8814.5 | D36: 9318.8 | E36: 10075.4 | F36: 11532 | G36: =Schedules!G8 -> 12773.239 | H36: =Schedules!H8 -> 14113.167 | I36: =Schedules!I8 -> 15525.485 | J36: =Schedules!J8 -> 17016.917 | K36: =Schedules!K8 -> 18586.4
A37: Accumulated other comprehensive loss | B37: -1994.4 | C37: -1634.8 | D37: -1726.6 | E37: -1850.4 | F37: -1982 | G37: -1982 | H37: -1950 | I37: -1920 | J37: -1900 | K37: -1880
A38: Treasury stock | B38: -6679.7 | C38: -6784.2 | D38: -7301 | E38: -7312.7 | F38: -8305.2 | G38: =Schedules!C18 -> -8805 | H38: =Schedules!D18 -> -9305 | I38: =Schedules!E18 -> -9805 | J38: =Schedules!F18 -> -10305 | K38: =Schedules!G18 -> -10805
A39: Total Ecolab shareholders’ equity | B39: =SUM(B34:B38) -> 6166.5 | C39: =SUM(C34:C38) -> 7224.2 | D39: =SUM(D34:D38) -> 7236.1 | E39: =SUM(E34:E38) -> 8044.7 | F39: =SUM(F34:F38) -> 8772.2 | G39: =SUM(G34:G38) -> 9844.029 | H39: =SUM(H34:H38) -> 11060.013 | I39: =SUM(I34:I38) -> 12359.946 | ... K39: =SUM(K34:K38) -> 15220.737
A40: Noncontrolling interest | B40: 35 | C40: 28.9 | D40: 22.5 | E40: 27.5 | F40: 31.9 | G40: 31.9 | H40: 31.9 | I40: 31.9 | J40: 31.9 | K40: 31.9
A41: Total equity | B41: =SUM(B39:B40) -> 6201.5 | C41: =SUM(C39:C40) -> 7253.1 | D41: =SUM(D39:D40) -> 7258.6 | E41: =SUM(E39:E40) -> 8072.2 | F41: =SUM(F39:F40) -> 8804.1 | G41: =SUM(G39:G40) -> 9875.929 | H41: =SUM(H39:H40) -> 11091.913 | I41: =SUM(I39:I40) -> 12391.846 | ... K41: =SUM(K39:K40) -> 15252.637
A42: Total liabilities and equity | B42: =SUM(B41+B31) -> 18126 | C42: =SUM(C41+C31) -> 21206.4 | D42: =SUM(D41+D31) -> 21464.3 | E42: =SUM(E41+E31) -> 21846.6 | F42: =SUM(F41+F31) -> 22402.7 | G42: =SUM(G41+G31) -> 24268.314 | H42: =SUM(H41+H31) -> 25770.612 | I42: =SUM(I41+I31) -> 27627.084 | ... K42: =SUM(K41+K31) -> 32067.425
G44: =G42-G16 -> -0.1 | H44: =H42-H16 -> -0.1 | I44: =I42-I16 -> -0.1 | J44: =J42-J16 -> -0.1 | K44: =K42-K16 -> -0.1
B49: 2020 | C49: 2021 | D49: 2022 | E49: 2023 | F49: 2024 | G49: 2025 | H49: 2026 | I49: 2027 | J49: 2028 | K49: 2029
A50: ASSETS
A51: Current assets
A52: Cash and cash equivalents | N52: Modeled as the plug to balance forecasted FCFs, consistent with record free-cash-flow commentary and 2024 10-K liquidity trends.
A53: Accounts receivable, net | G53: ='Income statement'!G7/(365/'Balance sheet'!G54) -> 2969.0027 | H53: ='Income statement'!H7/(365/'Balance sheet'!H54) -> 3050.1641 | I53: ='Income statement'!I7/(365/'Balance sheet'!I54) -> 3175.3361 | J53: ='Income statement'!J7/(365/'Balance sheet'!J54) -> 3305.9508 | K53: ='Income statement'!K7/(365/'Balance sheet'!K54) -> 3442.2545
A54: DSO | C54: =(((B7+C7)/2)/'Income statement'!C7)*365 -> 68.111968 | D54: =(((C7+D7)/2)/'Income statement'!D7)*365 -> 66.586169 | E54: =(((D7+E7)/2)/'Income statement'!E7)*365 -> 65.902844 | F54: =(((E7+F7)/2)/'Income statement'!F7)*365 -> 66.074428 | G54: 66 | H54: 65 | I54: 65 | J54: 65 | K54: 65 | N54: Projected using a constant DSO ~65 days, aligning with Ecolab’s stable customer credit cycle and 2024 MD&A disclosure of “consistent collections performance.”
A55: Inventories | G55: ='Income statement'!G10/'Balance sheet'!G56 -> 1544.8114 | H55: ='Income statement'!H10/'Balance sheet'!H56 -> 1610.8444 | I55: ='Income statement'!I10/'Balance sheet'!I56 -> 1676.0633 | J55: ='Income statement'!J10/'Balance sheet'!J56 -> 1744.0851 | K55: ='Income statement'!K10/'Balance sheet'!K56 -> 1815.0355
A56: Inventory turnover | C56: ='Income statement'!C10/(('Balance sheet'!C8+'Balance sheet'!B8)/2) -> 5.4849118 | D56: ='Income statement'!D10/(('Balance sheet'!D8+'Balance sheet'!C8)/2) -> 5.3772149 | E56: ='Income statement'!E10/(('Balance sheet'!E8+'Balance sheet'!D8)/2) -> 5.5652888 | F56: ='Income statement'!F10/(('Balance sheet'!F8+'Balance sheet'!E8)/2) -> 6.0090476 | G56: 6 | H56: 6 | I56: 6 | J56: 6 | K56: 6 | N56: Forecasted with constant turnover ≈6×, reflecting supply-chain efficiency and normalized post-COVID inventory management mentioned in 2023–2024 filings.
A57: Other current assets | B57: =B9/'Income statement'!B11 -> 0.090115137 | C57: =C9/'Income statement'!C11 -> 0.10450514 | D57: =D9/'Income statement'!D11 -> 0.1107614 | E57: =E9/'Income statement'!E11 -> 0.096809139 | F57: =F9/'Income statement'!F11 -> 0.10382669 | G57: 0.1 | H57: 0.1 | I57: 0.1 | J57: 0.1 | K57: 0.1 | N57: Held at ~10 % of current assets based on historical averages and limited management guidance on “modest other current asset movement.”
A58: Total current assets
A59: Property, plant and equipment, net | N59: Built from depreciation (~19 % of gross PPE) and CapEx ≈ 6 % of sales, per management’s guidance on elevated capital investments in digital and manufacturing modernization
A60: Goodwill | B60: =B12 -> 6006.9 | C60: =C12 -> 8063.9 | D60: =D12 -> 8012.7 | E60: =E12 -> 8148.2 | F60: =F12 -> 7907.3 | G60: =+CHOOSE(Cover!$I$15,G61,G62,G63) -> 7907.3 | H60: =+CHOOSE(Cover!$I$15,H61,H62,H63) -> 7907.3 | I60: =+CHOOSE(Cover!$I$15,I61,I62,I63) -> 7907.3 | J60: =+CHOOSE(Cover!$I$15,J61,J62,J63) -> 7907.3 | K60: =+CHOOSE(Cover!$I$15,K61,K62,K63) -> 7907.3 | N60: Kept flat post-Purolite, matching 10-K note that no new large acquisitions or impairments are expected.
A61: Bull | F61: 7000 | G61: 7000 | H61: 7000 | I61: 7000 | J61: 7000 | K61: 7000
A62: base | B62: =B12 -> 6006.9 | C62: =C12 -> 8063.9 | D62: =D12 -> 8012.7 | E62: =E12 -> 8148.2 | F62: =F12 -> 7907.3 | G62: =F62 -> 7907.3 | H62: =G62 -> 7907.3 | I62: =H62 -> 7907.3 | J62: =I62 -> 7907.3 | K62: =J62 -> 7907.3
A63: Bear | F63: 8500 | G63: 8500 | H63: 8500 | I63: 8500 | J63: 8500 | K63: 8500
A64: Other intangible assets, net | B64: =B13/'Income statement'!B7 -> 0.25249634 | C64: =C13/'Income statement'!C7 -> 0.33174168 | D64: =D13/'Income statement'!D7 -> 0.25942711 | E64: =E13/'Income statement'!E7 -> 0.22803227 | F64: =F13/'Income statement'!F7 -> 0.21019731 | G64: =G13/'Income statement'!G7 -> 0.18367203 | H64: =H13/'Income statement'!H7 -> 0.15931952 | I64: =I13/'Income statement'!I7 -> 0.14378545 | ... K64: =K13/'Income statement'!K7 -> 0.11680542 | N64: Modeled at ~22–24 % of goodwill, declining slightly with amortization and modest reinvestment per 2024 report.
A65: Operating lease assets | N65: Grown in line with reported expansion of DishIQ™ and Pest Intelligence lease programs in the 2024 Annual Report.
A66: Other assets | B66: =B15/'Income statement'!B7 -> 0.040372273 | C66: =C15/'Income statement'!C7 -> 0.042880367 | D66: =D15/'Income statement'!D7 -> 0.037715502 | E66: =E15/'Income statement'!E7 -> 0.034771087 | F66: =F15/'Income statement'!F7 -> 0.042588334 | G66: =AVERAGE(B66:F66) -> 0.039665513 | H66: =AVERAGE(C66:G66) -> 0.03952416 | I66: =AVERAGE(D66:H66) -> 0.038852919 | J66: =AVERAGE(E66:I66) -> 0.039080402 | K66: =AVERAGE(F66:J66) -> 0.039942266 | N66: Set at 4 % of sales, consistent with historical ratio and limited incremental long-term investments.
A67: Total assets
A69: LIABILITIES AND EQUITY
A70: Current liabilities
A71: Short-term debt | B71: =B20/B26 -> 0.0025939754 | C71: =C20/C26 -> 0.049238068 | D71: =D20/D26 -> 0.06254876 | E71: =E20/E26 -> 0.083481209 | F71: =F20/F26 -> 0.088600127 | G71: 0.08 | H71: 0.08 | I71: 0.08 | J71: 0.08 | K71: 0.08 | N71: % of long term debt
A72: Accounts payable | G72: =G73*'Income statement'!F10/365 -> 1637.5068 | H72: =H73*'Income statement'!G10/365 -> 1705.4322 | I72: =I73*'Income statement'!H10/365 -> 1778.3311 | J72: =J73*'Income statement'!I10/365 -> 1850.3309 | K72: =K73*'Income statement'!J10/365 -> 1925.4253 | N72: Linked to COGS through DPO ≈ 67 days, reflecting normalized supplier-payment terms per management.
A73: DPO | B73: =(B21/'Income statement'!B10)*365 -> 61.342495 | C73: =(C21/'Income statement'!C10)*365 -> 66.340109 | D73: =(D21/'Income statement'!D10)*365 -> 71.429396 | E73: =(E21/'Income statement'!E10)*365 -> 62.447378 | F73: =(F21/'Income statement'!F10)*365 -> 74.232839 | G73: =AVERAGE(B73:F73) -> 67.158443 | H73: 67.158443 | I73: 67.158443 | J73: 67.158443 | K73: 67.158443
A74: Compensation and benefits | B74: =B22/'Income statement'!B11 -> 0.14182104 | C74: =C22/'Income statement'!C11 -> 0.14914669 | D74: =D22/'Income statement'!D11 -> 0.13509223 | E74: =E22/'Income statement'!E11 -> 0.1613896 | F74: =F22/'Income statement'!F11 -> 0.17203538 | G74: 0.16 | H74: 0.155 | I74: 0.155 | J74: 0.15 | K74: 0.15 | N74: Expressed as 15–17 % of SG&A, reflecting Ecolab’s heavy service-labor mix (≈25 k field staff).
A75: Income taxes | B75: =B23/'Income statement'!B17 -> 0.54416761 | C75: =C23/'Income statement'!C17 -> 0.38601036 | D75: =D23/'Income statement'!D17 -> 0.84264392 | E75: =E23/'Income statement'!E17 -> 0.4377931 | F75: =F23/'Income statement'!F17 -> 0.28909629 | G75: =AVERAGE(B75,C75,E75,F75) -> 0.41426684 | H75: 0.41426684 | I75: 0.41426684 | J75: 0.41426684 | K75: 0.41426684 | N75: Modeled at ~42 % of income tax, consistent with a 17 % effective rate disclosed in 2024 10-K.
A76: Other current liabilities | B76: =B24/'Income statement'!B7 -> 0.10083739 | C76: =C24/'Income statement'!C7 -> 0.089860285 | D76: =D24/'Income statement'!D7 -> 0.090634207 | E76: =E24/'Income statement'!E7 -> 0.087133327 | F76: =F24/'Income statement'!F7 -> 0.096096916 | G76: =AVERAGE(B76:F76) -> 0.092912424 | H76: 0.091490923 | I76: 0.091490923 | J76: 0.091490923 | K76: 0.091490923 | N76: 9 % of current sales, in line with historic pattern and absence of new accrual items.
A77: Total current liabilities
A78: Long-term debt
A79: Pension and post-retirement benefits | N79: Flat, per 2024 10-K statement of stable funded status.
A80: Deferred income taxes | B80: =B28/'Income statement'!B17 -> 2.7400906 | C80: =C28/'Income statement'!C17 -> 2.3019985 | D80: =D28/'Income statement'!D17 -> 2.1560768 | E80: =E28/'Income statement'!E17 -> 1.1536552 | F80: =F28/'Income statement'!F17 -> 0.63737765 | G80: =AVERAGE(B80:F80) -> 1.7978397 | H80: =AVERAGE(C80:G80) -> 1.6093896 | I80: =AVERAGE(D80:H80) -> 1.4708678 | J80: =AVERAGE(E80:I80) -> 1.333826 | K80: =AVERAGE(F80:J80) -> 1.3698601 | N80: 11–12 % of PPE, declining with utilization of deferred tax assets noted in filings.
A81: Operating lease liabilities | N81: Increase mirrors lease-asset growth and expanding equipment-placement programs.
A82: Other liabilities | B82: =B30/'Income statement'!B7 -> 0.026496425 | C82: =C30/'Income statement'!C7 -> 0.019955863 | D82: =D30/'Income statement'!D7 -> 0.02863728 | E82: =E30/'Income statement'!E7 -> 0.024921346 | F82: =F30/'Income statement'!F7 -> 0.023263496 | G82: =AVERAGE(B82:F82) -> 0.024654882 | H82: 0.024652394 | I82: 0.024652394 | J82: 0.024652394 | K82: 0.024652394 | N82: ~2.5 % of sales, reflecting steady environmental and restructuring accruals.
A83: Total liabilities
A85: Equity
A86: Common stock ($1 par value) | C86: =C34-B34 -> 1.5 | D86: =D34-C34 -> 0.6 | E86: =E34-D34 -> 1 | F86: =F34-E34 -> 2.1 | G86: 2 | H86: 1.5 | I86: 1 | J86: 1 | K86: 1 | N86: +1 share per year; driven by employee stock programs.
A87: Additional paid-in capital | N87: % of sales/revenue
A88: stock based compensation | B88: 229.6 | C88: 229.6 | D88: 115.6 | E88: 191 | F88: 392.9 | G88: =G89*'Income statement'!G7 -> 328.38969 | H88: =H89*'Income statement'!H7 -> 342.55689 | I88: =I89*'Income statement'!I7 -> 356.61467 | J88: =J89*'Income statement'!J7 -> 371.28371 | K88: =K89*'Income statement'!K7 -> 386.59166 | N88: *stock based omposition given in 10-k added to APIC.
A89: % sales | B89: =B88/'Income statement'!B7 -> 0.019473685 | C89: =C88/'Income statement'!C7 -> 0.018031744 | D89: =D88/'Income statement'!D7 -> 0.0081478453 | E89: =E88/'Income statement'!E7 -> 0.0124672 | F89: =F88/'Income statement'!F7 -> 0.024959661 | G89: 0.02 | H89: 0.02 | I89: 0.02 | J89: 0.02 | K89: 0.02 | N89: *stock based comp as % of revenue
A90: no of shares | F90: =F88/Schedules!B20 -> 1.9165854 | G90: =G88/Schedules!C20 -> 1.4574487 | H90: =H88/Schedules!D20 -> 1.3832291 | I90: =I88/Schedules!E20 -> 1.3101416 | J90: =J88/Schedules!F20 -> 1.2410308 | K90: =K88/Schedules!G20 -> 1.1756737
A91: Retained earnings | N91: Built from projected net income less dividends (payout ratio ≈ 35 %), aligned with 33-year dividend-increase streak noted in 2024 Annual Report.
A92: Accumulated other comprehensive loss | N92: Held near –$2 billion, assuming minor FX swings.
A93: Treasury stock | N93: Expands annually by expected employee stock (~$800 m per year), per Q2 2025 10-Q.
A94: Total Ecolab shareholders’ equity
A95: Noncontrolling interest | N95: Flat at ~$30 m, consistent with immaterial minority holdings.
A96: Total equity
A97: Total liabilities and equity
A99: PPE and capex schedule | B99: 2020 | C99: 2021 | D99: 2022 | E99: 2023 | F99: 2024 | G99: 2025 | H99: 2026 | I99: 2027 | J99: 2028 | K99: 2029
A100: PPE | B100: =B11 -> 3124.9 | C100: =C11 -> 3288.5 | D100: =D11 -> 3293.4 | E100: =E11 -> 3474.6 | F100: =F11 -> 3752.4 | G100: =F100+G104-G101 -> 4032.477 | H100: =G100+H104-H101 -> 4302.428 | I100: =H100+I104-I101 -> 4563.8273 | J100: =I100+J104-J101 -> 4820.1158 | K100: =J100+K104-K101 -> 5074.1703
A101: Depriciation | B101: 594 | C101: 604 | D101: 619 | E101: 617 | F101: 635 | G101: =G102*F100 -> 705.09204 | H101: =H102*G100 -> 757.71971 | I101: =I102*H100 -> 808.44465 | J101: =J102*I100 -> 857.56271 | K101: =K102*J100 -> 905.7204 | M101: *% of PPE
A102: % of PPE | C102: =C101/B100 -> 0.19328619 | D102: =D101/C100 -> 0.18823172 | E102: =E101/D100 -> 0.18734439 | F102: =F101/E100 -> 0.18275485 | G102: =AVERAGE(C102:F102) -> 0.18790428 | H102: 0.18790428 | I102: 0.18790428 | J102: 0.18790428 | K102: 0.18790428
A103: Capex as % of sales | C103: =(C100-B100+C101)/'Income statement'!C7 -> 0.060283827 | D103: =(D100-C100+D101)/'Income statement'!D7 -> 0.043974401 | E103: =(E100-D100+E101)/'Income statement'!E7 -> 0.052101148 | F103: =(F100-E100+F101)/'Income statement'!F7 -> 0.057987218 | G103: 0.06 | H103: 0.06 | I103: 0.06 | J103: 0.06 | K103: 0.06
A104: Capex | G104: =G103*'Income statement'!G7 -> 985.16907 | H104: =H103*'Income statement'!H7 -> 1027.6707 | I104: =I103*'Income statement'!I7 -> 1069.844 | J104: =J103*'Income statement'!J7 -> 1113.8511 | K104: =K103*'Income statement'!K7 -> 1159.775 | M104: *% of sales

Sheet Schedules
A3: Retained earnings
A4: Year | B4: 2020 | C4: 2021 | D4: 2022 | E4: 2023 | F4: 2024 | G4: 2025 | H4: 2026 | I4: 2027 | J4: 2028 | K4: 2029
A5: Beginning RE | C5: =B8 -> 8243 | D5: =C8 -> 8813.9 | E5: =D8 -> 9329.6 | F5: =E8 -> 10085.9 | G5: =+'Balance sheet'!F36 -> 11532 | H5: =G8 -> 12773.239 | I5: =H8 -> 14113.167 | J5: =I8 -> 15525.485 | K5: =J8 -> 17016.917
A6: Net Income to Ecolab ($ M) | B6: ='Income statement'!B20 -> 967.47 | C6: ='Income statement'!C20 -> 1129.9 | D6: ='Income statement'!D20 -> 1091.7 | E6: ='Income statement'!E20 -> 1372.3 | F6: ='Income statement'!F20 -> 2112.4 | G6: ='Income statement'!G20 -> 1931.3393 | H6: ='Income statement'!H20 -> 2043.8293 | I6: ='Income statement'!I20 -> 2137.337 | ... K6: ='Income statement'!K20 -> 2331.188
A7: Dividends ($ M) | B7: 549 | C7: 559 | D7: 576 | E7: 616 | F7: 670 | G7: =F7*(1+G11) -> 690.1 | H7: =G7*(1+H11) -> 703.902 | I7: =H7*(1+I11) -> 725.01906 | J7: =I7*(1+J11) -> 739.51944 | K7: =J7*(1+K11) -> 761.70502 | N7: 9 % YoY increase in 2024, then 2–3 %
A8: Ending RE ($ M) | B8: 8243 | C8: =C5+C6-C7 -> 8813.9 | D8: =D5+D6-D7 -> 9329.6 | E8: =E5+E6-E7 -> 10085.9 | F8: =F5+F6-F7 -> 11528.3 | G8: =G5+G6-G7 -> 12773.239 | H8: =H5+H6-H7 -> 14113.167 | I8: =I5+I6-I7 -> 15525.485 | J8: =J5+J6-J7 -> 17016.917 | K8: =K5+K6-K7 -> 18586.4
A9: NI YoY | C9: =(C6-B6)/B6 -> 0.16789151 | D9: =(D6-C6)/C6 -> -0.033808302 | E9: =(E6-D6)/D6 -> 0.25703032 | F9: =(F6-E6)/E6 -> 0.53931356 | G9: =(G6-F6)/F6 -> -0.085713245 | H9: =(H6-G6)/G6 -> 0.058244552 | I9: =(I6-H6)/H6 -> 0.045751201 | J9: =(J6-I6)/I6 -> 0.0437998 | K9: =(K6-J6)/J6 -> 0.044929739
N10: Used only for trend visualization; not a driver.
A11: Dividends YoY | C11: =(C7-B7)/B7 -> 0.018214936 | D11: =(D7-C7)/C7 -> 0.030411449 | E11: =(E7-D7)/D7 -> 0.069444444 | F11: =(F7-E7)/E7 -> 0.087662338 | G11: 0.03 | H11: 0.02 | I11: 0.03 | J11: 0.02 | K11: 0.03
A14: Treasury stock
A15: Year | B15: 2024A | C15: 2025E | D15: 2026E | E15: 2027E | F15: 2028E | G15: 2029E
A16: Beginning TS | B16: –8305 | C16: -8305 | D16: =C18 -> -8805 | E16: =D18 -> -9305 | F16: =E18 -> -9805 | G16: =F18 -> -10305
A17: Net Change | B17: 189.5 | C17: 500 | D17: 500 | E17: 500 | F17: 500 | G17: 500 | L17: *authorised buybacks | N17: Based on shares repurchased × avg price – shares reissued × avg price
A18: Ending TS | B18: –8305 | C18: =C16-C17 -> -8805 | D18: =D16-D17 -> -9305 | E18: =E16-E17 -> -9805 | F18: =F16-F17 -> -10305 | G18: =G16-G17 -> -10805
A19: No of shares | B19: =B17/B20 -> 0.92439024 | C19: =C17/C20 -> 2.2190842 | D19: =D17/D20 -> 2.0189772 | E19: =E17/E20 -> 1.836915 | F19: =F17/F20 -> 1.6712703 | G19: =G17/G20 -> 1.5205627 | L19: *expected share buyback
A20: Share price(avg repurchase) | B20: 205 | C20: =B20*(1+Ke!$D$38) -> 225.31817 | D20: =C20*(1+Ke!$D$38) -> 247.65015 | E20: =D20*(1+Ke!$D$38) -> 272.19551 | F20: =E20*(1+Ke!$D$38) -> 299.17363 | G20: =F20*(1+Ke!$D$38) -> 328.82564 | L20: *expected share value
A21: Total no of shares | B21: 282 | C21: =B21-C19+'Balance sheet'!G90 -> 281.23836 | D21: =C21-D19+'Balance sheet'!H90 -> 280.60262 | E21: =D21-E19+'Balance sheet'!I90 -> 280.07584 | F21: =E21-F19+'Balance sheet'!J90 -> 279.6456 | G21: =F21-G19+'Balance sheet'!K90 -> 279.30071 | L21: *share price grew by Ke
A23: operating lease assets
B24: 2020A | C24: 2021A | D24: 2022A | E24: 2023A | F24: 2024A | G24: 2025E | H24: 2026E | I24: 2027E | J24: 2028E | K24: 2029E
A25: Opening balance | B25: – | C25: 424 | D25: 397 | E25: 448 | F25: 554 | G25: =F28 -> 723 | H25: =G28 -> 933.75021 | I25: =H28 -> 1128.4542 | J25: =I28 -> 1309.2546 | K25: =J28 -> 1478.6784
A26: Additions (1.9 % of Sales) | B26: – | C26: – | D26: – | E26: – | F26: 336 | G26: =1.9%*'Income statement'!G7 -> 311.97021 | H26: =1.9%*'Income statement'!H7 -> 325.42905 | I26: =1.9%*'Income statement'!I7 -> 338.78393 | J26: =1.9%*'Income statement'!J7 -> 352.71952 | K26: =1.9%*'Income statement'!K7 -> 367.26208
A27: Amortization (≈14 % of Opening) | B27: – | C27: – | D27: – | E27: – | F27: -267 | G27: =-14%*G25 -> -101.22 | H27: =-14%*H25 -> -130.72503 | I27: =-14%*I25 -> -157.98359 | J27: =-14%*J25 -> -183.29564 | K27: =-14%*K25 -> -207.01498
A28: Closing balance | B28: 424 | C28: 397 | D28: 448 | E28: 554 | F28: 723 | G28: =G25+G26+G27 -> 933.75021 | H28: =H25+H26+H27 -> 1128.4542 | I28: =I25+I26+I27 -> 1309.2546 | J28: =J25+J26+J27 -> 1478.6784 | K28: =K25+K26+K27 -> 1638.9255
F29: =(F28-E28)/E28 -> 0.30505415 | G29: =(G28-F28)/F28 -> 0.29149406 | H29: =(H28-G28)/G28 -> 0.20851831 | I29: =(I28-H28)/H28 -> 0.16021947 | J29: =(J28-I28)/I28 -> 0.12940484 | K29: =(K28-J28)/J28 -> 0.10837183
A31: lease liabilities
B32: 2024A | C32: 2025E | D32: 2026E | E32: 2027E | F32: 2028E | G32: 2029E
A33: Opening balance | C33: =B37 -> 718 | D33: =C37 -> 888.97021 | E33: =D37 -> 1066.3993 | F33: =E37 -> 1227.1832 | G33: =F37 -> 1395.9027
A34: + Interest (4.8 %) | C34: =4.8%*F17 -> 24 | D34: =4.8%*G17 -> 24 | E34: =4.8%*H17 -> 0 | F34: =4.8%*I17 -> 0 | G34: =4.8%*J17 -> 0
A35: + New lease additions (1.9 % of Sales) | C35: =1.9%*'Income statement'!G7 -> 311.97021 | D35: =1.9%*'Income statement'!H7 -> 325.42905 | E35: =1.9%*'Income statement'!I7 -> 338.78393 | F35: =1.9%*'Income statement'!J7 -> 352.71952 | G35: =1.9%*'Income statement'!K7 -> 367.26208
A36: – Cash lease payments | B36: -208 | C36: -165 | D36: -172 | E36: -178 | F36: -184 | G36: -190
A37: Closing balance | B37: 718 | C37: =C33+C34+C35+C36 -> 888.97021 | D37: =D33+D34+D35+D36 -> 1066.3993 | E37: =E33+E34+E35+E36 -> 1227.1832 | F37: =F33+F34+F35+F36 -> 1395.9027 | G37: =G33+G34+G35+G36 -> 1573.1648
A38: of which Current (≈ 20 %) | B38: 143 | C38: =20%*C37 -> 177.79404 | D38: =20%*D37 -> 213.27985 | E38: =20%*E37 -> 245.43664 | F38: =20%*F37 -> 279.18054 | G38: =20%*G37 -> 314.63296
A39: Non-current (≈ 80 %) | B39: 575 | C39: =C37-C38 -> 711.17616 | D39: =D37-D38 -> 853.1194 | E39: =E37-E38 -> 981.74655 | F39: =F37-F38 -> 1116.7222 | G39: =G37-G38 -> 1258.5318
C40: =(C39-B39)/B39 -> 0.23682811 | D40: =(D39-C39)/C39 -> 0.19958942 | E40: =(E39-D39)/D39 -> 0.15077274 | F40: =(F39-E39)/E39 -> 0.1374852 | G40: =(G39-F39)/F39 -> 0.12698741
A43: Debt
B44: 2024A | C44: 2025E | D44: 2026E | E44: 2027E | F44: 2028E | G44: 2029E
A45: Opening balance (LT) | B45: 6949 | C45: =B48 -> 6949 | D45: =C48 -> 7155 | E45: =D48 -> 7255 | F45: =E48 -> 7505 | G45: =F48 -> 7855
A46: + New Issuances | B46: 0 | C46: 600 | D46: 1100 | E46: 850 | F46: 1100 | G46: 1000 | J46: *Modeled to keep constant debt to non cash assets ratio of 30-31%
A47: – Repayments (maturities) | B47: 0 | C47: -394 | D47: -1000 | E47: -600 | F47: -750 | G47: -500 | J47: *Maturity schedule from 10-k
A48: Closing LT Debt | B48: 6949 | C48: =C45+C46+C47 -> 7155 | D48: =D45+D46+D47 -> 7255 | E48: =E45+E46+E47 -> 7505 | F48: =F45+F46+F47 -> 7855 | G48: =G45+G46+G47 -> 8355
A49: Average Balance | B49: =AVERAGE(B48,B45) -> 6949 | C49: =AVERAGE(C48,C45) -> 7052 | D49: =AVERAGE(D48,D45) -> 7205 | E49: =AVERAGE(E48,E45) -> 7380 | F49: =AVERAGE(F48,F45) -> 7680 | G49: =AVERAGE(G48,G45) -> 8105
A50: Interest Rate (%) | B50: 0.037 | C50: 0.038 | D50: 0.04 | E50: 0.041 | F50: 0.042 | G50: 0.042
A51: Interest Expense | B51: =B49*B50 -> 257.113 | C51: =C49*C50 -> 267.976 | D51: =D49*D50 -> 288.2 | E51: =E49*E50 -> 302.58 | F51: =F49*F50 -> 322.56 | G51: =G49*G50 -> 340.41
B55: 2024 | C55: 2025 | D55: 2026 | E55: 2027 | F55: 2028 | G55: 2029
A56: Non cash assets | B56: 21131 | C56: 22266.627 | D56: 23268.221 | E56: 24194.187 | F56: 25249.32 | G56: 26235.864
A59: debt/non cash assets | B59: =B45/B56 -> 0.32885334 | C59: =C45/C56 -> 0.31208139 | D59: =D45/D56 -> 0.30750094 | E59: =E45/E56 -> 0.29986541 | F59: =F45/F56 -> 0.29723573 | G59: =G45/G56 -> 0.29939933 | I59: *Debt to Non cash assests ratio
A60: Intangible assets
A61: Year-End | B61: 2021 | C61: 2022 | D61: 2023 | E61: 2024 | F61: 2025 | G61: 2026 | H61: 2027 | I61: 2028 | J61: 2029
A62: Trade Names (Indefinite-Lived) | B62: 1230 | C62: 1230 | D62: 1230 | E62: 1230 | F62: 1230 | G62: 1230 | H62: 1230 | I62: 1230 | J62: 1230
A63: Customer Relationships | B63: 2530.9 | C63: 3444.6 | D63: 3385.1 | E63: 3279.8 | F63: 3279.8 | G63: 3279.8 | H63: 3279.8 | I63: 3279.8 | J63: 3279.8
C64: =(C63-B63)/B63 -> 0.36101782 | D64: =(D63-C63)/C63 -> -0.017273413 | E64: =(E63-D63)/D63 -> -0.03110691
A65: Patents | B65: 492.5 | C65: 496.3 | D65: 503.6 | E65: 504.6 | F65: 504.6 | G65: 504.6 | H65: 504.6 | I65: 504.6 | J65: 504.6 | M65: *Values are as per 10-k and foreword.
C66: =(C65-B65)/B65 -> 0.007715736 | D66: =(D65-C65)/C65 -> 0.014708845 | E66: =(E65-D65)/D65 -> 0.0019857029
A67: Trademarks | B67: 348 | C67: 561.1 | D67: 406.5 | E67: 371.9 | F67: 371.9 | G67: 371.9 | H67: 371.9 | I67: 371.9 | J67: 371.9 | M67: Possibility of increasing with increasing revenue but not possible to project without information onM&A activity.
C68: =(C67-B67)/B67 -> 0.61235632 | D68: =(D67-C67)/C67 -> -0.27553021 | E68: =(E67-D67)/D67 -> -0.085116851
A69: Other Technologies | B69: 240.1 | C69: 527.2 | D69: 551.2 | E69: 541.8 | F69: 541.8 | G69: 541.8 | H69: 541.8 | I69: 541.8 | J69: 541.8
C70: =(C69-B69)/B69 -> 1.1957518 | D70: =(D69-C69)/C69 -> 0.04552352 | E70: =(E69-D69)/D69 -> -0.017053701
A71: Total Finite-Lived Gross | B71: =B63+B65+B67+B69 -> 3611.5 | C71: =C63+C65+C67+C69 -> 5029.2 | D71: =D63+D65+D67+D69 -> 4846.4 | E71: =E63+E65+E67+E69 -> 4698.1 | F71: =F63+F65+F67+F69 -> 4698.1 | G71: =G63+G65+G67+G69 -> 4698.1 | H71: =H63+H65+H67+H69 -> 4698.1 | I71: =I63+I65+I67+I69 -> 4698.1 | J71: =J63+J65+J67+J69 -> 4698.1
C72: -320 | D72: -307 | E72: -301 | F72: -293 | G72: -287 | H72: -165 | I72: -157 | J72: -149
A73: Accum. Amort. (Finite-Lived) | B73: -1864.5 | C73: -2035.1 | D73: -2582.9 | E73: -2619.3 | F73: =E73+F72 -> -2912.3 | G73: =F73+G72 -> -3199.3 | H73: =G73+H72 -> -3364.3 | I73: =H73+I72 -> -3521.3 | J73: =I73+J72 -> -3670.3
A74: Net Finite-Lived | B74: =B71+B73 -> 1747 | C74: =C71+C73 -> 2994.1 | D74: =D71+D73 -> 2263.5 | E74: =E71+E73 -> 2078.8 | F74: =F71+F73 -> 1785.8 | G74: =G71+G73 -> 1498.8 | H74: =H71+H73 -> 1333.8 | I74: =I71+I73 -> 1176.8 | J74: =J71+J73 -> 1027.8
A75: Total Intangibles, Net | B75: =B74+B62 -> 2977 | C75: =C74+C62 -> 4224.1 | D75: =D74+D62 -> 3493.5 | E75: =E74+E62 -> 3308.8 | F75: =F74+F62 -> 3015.8 | G75: =G74+G62 -> 2728.8 | H75: =H74+H62 -> 2563.8 | I75: =I74+I62 -> 2406.8 | J75: =J74+J62 -> 2257.8

Sheet Comps
C1: USD
A2: COMPARABLE COMPANY ANALYSIS
A3: COMPANY DATA
A4: (in millions) | C4: Recent | D4: 52 week | E4: Shares | F4: Market | G4: Total | I4: Enterprise | J4: Book | L4: WS 12-mo
A5: Company Name | B5: Ticker | C5: Price | D5: High | E5: Out | F5: Cap | G5: Debt | H5: Cash | I5: Value | J5: Value | K5: Beta | L5: Price Target
A6: {=IF($B6="","",_xll.RDP.Data($B6,"TR.CompanyName"))} -> Clorox Co | B6: CLX | C6: =IF(B6="","",_xll.RDP.Data($B6,"TR.PriceClose","Curn=#1",,$C$1)) -> 104.01 | D6: =IF($B6="","",_xll.RDP.Data($B6,"MAX(TR.PriceHigh(SDate=0D,EDate=0D-364C))/*52 Week High*/","Curn=#1",,$C$1)) -> 166.35 | E6: =IF(B6="","",_xll.RDP.Data($B6,"TR.CompanySharesOutstanding(SDate=0)/*# Shares Outstanding*/")/1000000) -> 121.98038 | F6: =IF(B6="","",C6*E6) -> 12687.179 | G6: {=IF($B6="","",_xll.RDP.Data($B6,"TR.TotalDebtOutstanding","Curn=#1",,$C$1)/1000000)} -> 2524 | H6: =IF($B6="","",_xll.RDP.Data($B6,"TR.CashandEquivalents","Curn=#1",,$C$1)/1000000) -> 167 | I6: =IF(B6="","",F6+G6-H6) -> 15044.179 | J6: {=IF($B6="","",_xll.RDP.Data($B6,"TR.TotalEquity","Curn=#1",,$C$1)/1000000)} -> 321 | K6: =IF($B6="","",_xll.RDP.Data($B6,"TR.BetaFiveYear/*Beta 5 Year Monthly*//*Beta 5 Year Monthly*/")) -> 0.57248628 | L6: =IF(B6="","",_xll.RDP.Data($B6,"TR.PriceTargetMean","Curn=#1",,$C$1)) -> 128.66833
A7: {=IF($B7="","",_xll.RDP.Data($B7,"TR.CompanyName"))} -> Church & Dwight Co Inc | B7: CHD | C7: =IF(B7="","",_xll.RDP.Data($B7,"TR.PriceClose","Curn=#1",,$C$1)) -> 84.61 | D7: =IF($B7="","",_xll.RDP.Data($B7,"MAX(TR.PriceHigh(SDate=0D,EDate=0D-364C))/*52 Week High*/","Curn=#1",,$C$1)) -> 116.46 | E7: =IF(B7="","",_xll.RDP.Data($B7,"TR.CompanySharesOutstanding(SDate=0)/*# Shares Outstanding*/")/1000000) -> 240.13007 | F7: =IF(B7="","",C7*E7) -> 20317.405 | G7: {=IF($B7="","",_xll.RDP.Data($B7,"TR.TotalDebtOutstanding","Curn=#1",,$C$1)/1000000)} -> 2204.6 | H7: =IF($B7="","",_xll.RDP.Data($B7,"TR.CashandEquivalents","Curn=#1",,$C$1)/1000000) -> 964.1 | I7: =IF(B7="","",F7+G7-H7) -> 21557.905 | J7: {=IF($B7="","",_xll.RDP.Data($B7,"TR.TotalEquity","Curn=#1",,$C$1)/1000000)} -> 4360.8 | K7: =IF($B7="","",_xll.RDP.Data($B7,"TR.BetaFiveYear/*Beta 5 Year Monthly*//*Beta 5 Year Monthly*/")) -> 0.45869135 | L7: =IF(B7="","",_xll.RDP.Data($B7,"TR.PriceTargetMean","Curn=#1",,$C$1)) -> 97.655
A8: {=IF($B8="","",_xll.RDP.Data($B8,"TR.CompanyName"))} -> Dupont De Nemours Inc | B8: DD | C8: =IF(B8="","",_xll.RDP.Data($B8,"TR.PriceClose","Curn=#1",,$C$1)) -> 40.93 | D8: =IF($B8="","",_xll.RDP.Data($B8,"MAX(TR.PriceHigh(SDate=0D,EDate=0D-364C))/*52 Week High*/","Curn=#1",,$C$1)) -> 41.83 | E8: =IF(B8="","",_xll.RDP.Data($B8,"TR.CompanySharesOutstanding(SDate=0)/*# Shares Outstanding*/")/1000000) -> 418.97532 | F8: =IF(B8="","",C8*E8) -> 17148.66 | G8: {=IF($B8="","",_xll.RDP.Data($B8,"TR.TotalDebtOutstanding","Curn=#1",,$C$1)/1000000)} -> 7171 | H8: =IF($B8="","",_xll.RDP.Data($B8,"TR.CashandEquivalents","Curn=#1",,$C$1)/1000000) -> 1850 | I8: =IF(B8="","",F8+G8-H8) -> 22469.66 | J8: {=IF($B8="","",_xll.RDP.Data($B8,"TR.TotalEquity","Curn=#1",,$C$1)/1000000)} -> 23350 | K8: =IF($B8="","",_xll.RDP.Data($B8,"TR.BetaFiveYear/*Beta 5 Year Monthly*//*Beta 5 Year Monthly*/")) -> 1.0507269 | L8: =IF(B8="","",_xll.RDP.Data($B8,"TR.PriceTargetMean","Curn=#1",,$C$1)) -> 46.608
A9: {=IF($B9="","",_xll.RDP.Data($B9,"TR.CompanyName"))} -> Sherwin-Williams Co | B9: SHW | C9: =IF(B9="","",_xll.RDP.Data($B9,"TR.PriceClose","Curn=#1",,$C$1)) -> 328.69 | D9: =IF($B9="","",_xll.RDP.Data($B9,"MAX(TR.PriceHigh(SDate=0D,EDate=0D-364C))/*52 Week High*/","Curn=#1",,$C$1)) -> 379.65 | E9: =IF(B9="","",_xll.RDP.Data($B9,"TR.CompanySharesOutstanding(SDate=0)/*# Shares Outstanding*/")/1000000) -> 247.89351 | F9: =IF(B9="","",C9*E9) -> 81480.119 | G9: {=IF($B9="","",_xll.RDP.Data($B9,"TR.TotalDebtOutstanding","Curn=#1",,$C$1)/1000000)} -> 10077.7 | H9: =IF($B9="","",_xll.RDP.Data($B9,"TR.CashandEquivalents","Curn=#1",,$C$1)/1000000) -> 210.4 | I9: =IF(B9="","",F9+G9-H9) -> 91347.419 | J9: {=IF($B9="","",_xll.RDP.Data($B9,"TR.TotalEquity","Curn=#1",,$C$1)/1000000)} -> 4051.2 | K9: =IF($B9="","",_xll.RDP.Data($B9,"TR.BetaFiveYear/*Beta 5 Year Monthly*//*Beta 5 Year Monthly*/")) -> 1.2588298 | L9: =IF(B9="","",_xll.RDP.Data($B9,"TR.PriceTargetMean","Curn=#1",,$C$1)) -> 386.14591
A10: {=IF($B10="","",_xll.RDP.Data($B10,"TR.CompanyName"))} -> Ecolab Inc | B10: ECL | C10: =IF(B10="","",_xll.RDP.Data($B10,"TR.PriceClose","Curn=#1",,$C$1)) -> 263.6 | D10: =IF($B10="","",_xll.RDP.Data($B10,"MAX(TR.PriceHigh(SDate=0D,EDate=0D-364C))/*52 Week High*/","Curn=#1",,$C$1)) -> 286.04 | E10: =IF(B10="","",_xll.RDP.Data($B10,"TR.CompanySharesOutstanding(SDate=0)/*# Shares Outstanding*/")/1000000) -> 283.23565 | F10: =IF(B10="","",C10*E10) -> 74660.918 | G10: {=IF($B10="","",_xll.RDP.Data($B10,"TR.TotalDebtOutstanding","Curn=#1",,$C$1)/1000000)} -> 7564.9 | H10: =IF($B10="","",_xll.RDP.Data($B10,"TR.CashandEquivalents","Curn=#1",,$C$1)/1000000) -> 1256.8 | I10: =IF(B10="","",F10+G10-H10) -> 80969.018 | J10: {=IF($B10="","",_xll.RDP.Data($B10,"TR.TotalEquity","Curn=#1",,$C$1)/1000000)} -> 8757.3 | K10: =IF($B10="","",_xll.RDP.Data($B10,"TR.BetaFiveYear/*Beta 5 Year Monthly*//*Beta 5 Year Monthly*/")) -> 0.9990248 | L10: =IF(B10="","",_xll.RDP.Data($B10,"TR.PriceTargetMean","Curn=#1",,$C$1)) -> 291.8765
A12: I/B/E/S ESTIMATES
C13: SALES | G13: EPS | K13: EBIT | N13: EBITDA | Q13: EPS 5-yr
A14: Company Name | B14: Ticker | C14: Last FY | D14: FYR1 | E14: FYR2 | F14: FYR3 | G14: Last FY | H14: FYR1 | I14: FYR2 | J14: FYR3 | K14: Last FY | L14: FYR1 | M14: FYR2 | N14: Last FY | O14: FYR1 | P14: FYR2 | Q14: Growth %
A15: =A6 -> Clorox Co | B15: =IF(B6="","",B6) -> CLX | C15: {=IF($B15="","",_xll.RDP.Data($B15,"TR.Revenue","Curn=#1",,$C$1)/1000000)} -> 7104 | D15: {=IF($B15="","",_xll.RDP.Data($B15,"TR.RevenueMean","Period=FY1 Frq=D SDate=1D Curn=#1",,$C$1)/1000000)} -> 6495.4712 | E15: {=IF($B15="","",_xll.RDP.Data($B15,"TR.RevenueMean","Period=FY2 Frq=D SDate=1D Curn=#1",,$C$1)/1000000)} -> 6809.4967 | F15: {=IF($B15="","",_xll.RDP.Data($B15,"TR.RevenueMean","Period=FY3 Frq=D SDate=1D Curn=#1",,$C$1)/1000000)} -> 7005.8413 | G15: =IF($B15="","",_xll.RDP.Data($B15,"TR.EPSMean","Period=FY0 Frq=D SDate=1D Curn=#1",,$C$1)) -> 7.04971 | H15: =IF($B15="","",_xll.RDP.Data($B15,"TR.EPSMean","Period=FY1 Frq=D SDate=1D Curn=#1",,$C$1)) -> 5.93156 | I15: =IF($B15="","",_xll.RDP.Data($B15,"TR.EPSMean","Period=FY2 Frq=D SDate=1D Curn=#1",,$C$1)) -> 6.75739 | J15: =IF($B15="","",_xll.RDP.Data($B15,"TR.EPSMean","Period=FY3 Frq=D SDate=1D Curn=#1",,$C$1)) -> 7.16117 | K15: {=IF($B15="","",_xll.RDP.Data($B15,"TR.EBITMean","Period=FY0 Frq=D SDate=1D Curn=#1",,$C$1)/1000000)} -> 1196.5612 | L15: {=IF($B15="","",_xll.RDP.Data($B15,"TR.EBITMean","Period=FY1 Frq=D SDate=1D Curn=#1",,$C$1)/1000000)} -> 1052.1436 | M15: {=IF($B15="","",_xll.RDP.Data($B15,"TR.EBITMean","Period=FY2 Frq=D SDate=1D Curn=#1",,$C$1)/1000000)} -> 1187.8643 | N15: {=IF($B15="","",_xll.RDP.Data($B15,"TR.EBITDAMean","Period=FY0 Frq=D SDate=1D Curn=#1",,$C$1)/1000000)} -> 1417.1396 | O15: {=IF($B15="","",_xll.RDP.Data($B15,"TR.EBITDAMean","Period=FY1 Frq=D SDate=1D Curn=#1",,$C$1)/1000000)} -> 1267.5003 | P15: {=IF($B15="","",_xll.RDP.Data($B15,"TR.EBITDAMean","Period=FY2 Frq=D SDate=1D Curn=#1",,$C$1)/1000000)} -> 1401.8257 | Q15: {=IF($B15="","",_xll.RDP.Data($B15,"TR.LTGMean",,)/100)} -> -0.02895
A16: =A7 -> Church & Dwight Co Inc | B16: =IF(B7="","",B7) -> CHD | C16: {=IF($B16="","",_xll.RDP.Data($B16,"TR.Revenue","Curn=#1",,$C$1)/1000000)} -> 6107.1 | D16: {=IF($B16="","",_xll.RDP.Data($B16,"TR.RevenueMean","Period=FY1 Frq=D SDate=1D Curn=#1",,$C$1)/1000000)} -> 6199.006 | E16: {=IF($B16="","",_xll.RDP.Data($B16,"TR.RevenueMean","Period=FY2 Frq=D SDate=1D Curn=#1",,$C$1)/1000000)} -> 6434.6084 | F16: {=IF($B16="","",_xll.RDP.Data($B16,"TR.RevenueMean","Period=FY3 Frq=D SDate=1D Curn=#1",,$C$1)/1000000)} -> 6660.107 | G16: =IF($B16="","",_xll.RDP.Data($B16,"TR.EPSMean","Period=FY0 Frq=D SDate=1D Curn=#1",,$C$1)) -> 3.44016 | H16: =IF($B16="","",_xll.RDP.Data($B16,"TR.EPSMean","Period=FY1 Frq=D SDate=1D Curn=#1",,$C$1)) -> 3.49705 | I16: =IF($B16="","",_xll.RDP.Data($B16,"TR.EPSMean","Period=FY2 Frq=D SDate=1D Curn=#1",,$C$1)) -> 3.74781 | J16: =IF($B16="","",_xll.RDP.Data($B16,"TR.EPSMean","Period=FY3 Frq=D SDate=1D Curn=#1",,$C$1)) -> 4.00081 | K16: {=IF($B16="","",_xll.RDP.Data($B16,"TR.EBITMean","Period=FY0 Frq=D SDate=1D Curn=#1",,$C$1)/1000000)} -> 1145.8387 | L16: {=IF($B16="","",_xll.RDP.Data($B16,"TR.EBITMean","Period=FY1 Frq=D SDate=1D Curn=#1",,$C$1)/1000000)} -> 1164.9901 | M16: {=IF($B16="","",_xll.RDP.Data($B16,"TR.EBITMean","Period=FY2 Frq=D SDate=1D Curn=#1",,$C$1)/1000000)} -> 1240.4798 | N16: {=IF($B16="","",_xll.RDP.Data($B16,"TR.EBITDAMean","Period=FY0 Frq=D SDate=1D Curn=#1",,$C$1)/1000000)} -> 1375.5647 | O16: {=IF($B16="","",_xll.RDP.Data($B16,"TR.EBITDAMean","Period=FY1 Frq=D SDate=1D Curn=#1",,$C$1)/1000000)} -> 1399.6818 | P16: {=IF($B16="","",_xll.RDP.Data($B16,"TR.EBITDAMean","Period=FY2 Frq=D SDate=1D Curn=#1",,$C$1)/1000000)} -> 1478.5307 | Q16: {=IF($B16="","",_xll.RDP.Data($B16,"TR.LTGMean",,)/100)} -> 0.0498667
A17: =A8 -> Dupont De Nemours Inc | B17: =IF(B8="","",B8) -> DD | C17: {=IF($B17="","",_xll.RDP.Data($B17,"TR.Revenue","Curn=#1",,$C$1)/1000000)} -> 12386 | D17: {=IF($B17="","",_xll.RDP.Data($B17,"TR.RevenueMean","Period=FY1 Frq=D SDate=1D Curn=#1",,$C$1)/1000000)} -> 6847.6338 | E17: {=IF($B17="","",_xll.RDP.Data($B17,"TR.RevenueMean","Period=FY2 Frq=D SDate=1D Curn=#1",,$C$1)/1000000)} -> 7071.6311 | F17: {=IF($B17="","",_xll.RDP.Data($B17,"TR.RevenueMean","Period=FY3 Frq=D SDate=1D Curn=#1",,$C$1)/1000000)} -> 7353.6005 | G17: =IF($B17="","",_xll.RDP.Data($B17,"TR.EPSMean","Period=FY0 Frq=D SDate=1D Curn=#1",,$C$1)) -> 3.91061 | H17: =IF($B17="","",_xll.RDP.Data($B17,"TR.EPSMean","Period=FY1 Frq=D SDate=1D Curn=#1",,$C$1)) -> 1.76978 | I17: =IF($B17="","",_xll.RDP.Data($B17,"TR.EPSMean","Period=FY2 Frq=D SDate=1D Curn=#1",,$C$1)) -> 2.1564 | J17: =IF($B17="","",_xll.RDP.Data($B17,"TR.EPSMean","Period=FY3 Frq=D SDate=1D Curn=#1",,$C$1)) -> 2.3465 | K17: {=IF($B17="","",_xll.RDP.Data($B17,"TR.EBITMean","Period=FY0 Frq=D SDate=1D Curn=#1",,$C$1)/1000000)} -> 2535.1266 | L17: {=IF($B17="","",_xll.RDP.Data($B17,"TR.EBITMean","Period=FY1 Frq=D SDate=1D Curn=#1",,$C$1)/1000000)} -> 1360.8479 | M17: {=IF($B17="","",_xll.RDP.Data($B17,"TR.EBITMean","Period=FY2 Frq=D SDate=1D Curn=#1",,$C$1)/1000000)} -> 1349.3397 | N17: {=IF($B17="","",_xll.RDP.Data($B17,"TR.EBITDAMean","Period=FY0 Frq=D SDate=1D Curn=#1",,$C$1)/1000000)} -> 3131.6831 | O17: {=IF($B17="","",_xll.RDP.Data($B17,"TR.EBITDAMean","Period=FY1 Frq=D SDate=1D Curn=#1",,$C$1)/1000000)} -> 1610.3644 | P17: {=IF($B17="","",_xll.RDP.Data($B17,"TR.EBITDAMean","Period=FY2 Frq=D SDate=1D Curn=#1",,$C$1)/1000000)} -> 1703.1989 | Q17: {=IF($B17="","",_xll.RDP.Data($B17,"TR.LTGMean",,)/100)} -> #VALUE! | R17: Not available
A18: =A9 -> Sherwin-Williams Co | B18: =IF(B9="","",B9) -> SHW | C18: {=IF($B18="","",_xll.RDP.Data($B18,"TR.Revenue","Curn=#1",,$C$1)/1000000)} -> 23098.5 | D18: {=IF($B18="","",_xll.RDP.Data($B18,"TR.RevenueMean","Period=FY1 Frq=D SDate=1D Curn=#1",,$C$1)/1000000)} -> 23516.493 | E18: {=IF($B18="","",_xll.RDP.Data($B18,"TR.RevenueMean","Period=FY2 Frq=D SDate=1D Curn=#1",,$C$1)/1000000)} -> 24694.036 | F18: {=IF($B18="","",_xll.RDP.Data($B18,"TR.RevenueMean","Period=FY3 Frq=D SDate=1D Curn=#1",,$C$1)/1000000)} -> 25775.463 | G18: =IF($B18="","",_xll.RDP.Data($B18,"TR.EPSMean","Period=FY0 Frq=D SDate=1D Curn=#1",,$C$1)) -> 11.29786 | H18: =IF($B18="","",_xll.RDP.Data($B18,"TR.EPSMean","Period=FY1 Frq=D SDate=1D Curn=#1",,$C$1)) -> 11.3762 | I18: =IF($B18="","",_xll.RDP.Data($B18,"TR.EPSMean","Period=FY2 Frq=D SDate=1D Curn=#1",,$C$1)) -> 12.56396 | J18: =IF($B18="","",_xll.RDP.Data($B18,"TR.EPSMean","Period=FY3 Frq=D SDate=1D Curn=#1",,$C$1)) -> 14.117 | K18: {=IF($B18="","",_xll.RDP.Data($B18,"TR.EBITMean","Period=FY0 Frq=D SDate=1D Curn=#1",,$C$1)/1000000)} -> 3947.4394 | L18: {=IF($B18="","",_xll.RDP.Data($B18,"TR.EBITMean","Period=FY1 Frq=D SDate=1D Curn=#1",,$C$1)/1000000)} -> 3934.6579 | M18: {=IF($B18="","",_xll.RDP.Data($B18,"TR.EBITMean","Period=FY2 Frq=D SDate=1D Curn=#1",,$C$1)/1000000)} -> 4341.5446 | N18: {=IF($B18="","",_xll.RDP.Data($B18,"TR.EBITDAMean","Period=FY0 Frq=D SDate=1D Curn=#1",,$C$1)/1000000)} -> 4501.3397 | O18: {=IF($B18="","",_xll.RDP.Data($B18,"TR.EBITDAMean","Period=FY1 Frq=D SDate=1D Curn=#1",,$C$1)/1000000)} -> 4527.4936 | P18: {=IF($B18="","",_xll.RDP.Data($B18,"TR.EBITDAMean","Period=FY2 Frq=D SDate=1D Curn=#1",,$C$1)/1000000)} -> 4920.6077 | Q18: {=IF($B18="","",_xll.RDP.Data($B18,"TR.LTGMean",,)/100)} -> 0.07585 | R18: Not available
A19: =A10 -> Ecolab Inc | B19: =IF(B10="","",B10) -> ECL | C19: {=IF($B19="","",_xll.RDP.Data($B19,"TR.Revenue","Curn=#1",,$C$1)/1000000)} -> 15741.4 | D19: {=IF($B19="","",_xll.RDP.Data($B19,"TR.RevenueMean","Period=FY1 Frq=D SDate=1D Curn=#1",,$C$1)/1000000)} -> 16057.811 | E19: {=IF($B19="","",_xll.RDP.Data($B19,"TR.RevenueMean","Period=FY2 Frq=D SDate=1D Curn=#1",,$C$1)/1000000)} -> 16916.096 | F19: {=IF($B19="","",_xll.RDP.Data($B19,"TR.RevenueMean","Period=FY3 Frq=D SDate=1D Curn=#1",,$C$1)/1000000)} -> 17774.871 | G19: =IF($B19="","",_xll.RDP.Data($B19,"TR.EPSMean","Period=FY0 Frq=D SDate=1D Curn=#1",,$C$1)) -> 6.63082 | H19: =IF($B19="","",_xll.RDP.Data($B19,"TR.EPSMean","Period=FY1 Frq=D SDate=1D Curn=#1",,$C$1)) -> 7.52163 | I19: =IF($B19="","",_xll.RDP.Data($B19,"TR.EPSMean","Period=FY2 Frq=D SDate=1D Curn=#1",,$C$1)) -> 8.48167 | J19: =IF($B19="","",_xll.RDP.Data($B19,"TR.EPSMean","Period=FY3 Frq=D SDate=1D Curn=#1",,$C$1)) -> 9.64472 | K19: {=IF($B19="","",_xll.RDP.Data($B19,"TR.EBITMean","Period=FY0 Frq=D SDate=1D Curn=#1",,$C$1)/1000000)} -> 2630.6934 | L19: {=IF($B19="","",_xll.RDP.Data($B19,"TR.EBITMean","Period=FY1 Frq=D SDate=1D Curn=#1",,$C$1)/1000000)} -> 2891.0473 | M19: {=IF($B19="","",_xll.RDP.Data($B19,"TR.EBITMean","Period=FY2 Frq=D SDate=1D Curn=#1",,$C$1)/1000000)} -> 3217.3703 | N19: {=IF($B19="","",_xll.RDP.Data($B19,"TR.EBITDAMean","Period=FY0 Frq=D SDate=1D Curn=#1",,$C$1)/1000000)} -> 3599.2173 | O19: {=IF($B19="","",_xll.RDP.Data($B19,"TR.EBITDAMean","Period=FY1 Frq=D SDate=1D Curn=#1",,$C$1)/1000000)} -> 3847.8377 | P19: {=IF($B19="","",_xll.RDP.Data($B19,"TR.EBITDAMean","Period=FY2 Frq=D SDate=1D Curn=#1",,$C$1)/1000000)} -> 4213.7931 | Q19: {=IF($B19="","",_xll.RDP.Data($B19,"TR.LTGMean",,)/100)} -> 0.1271
A21: VALUATION MULTIPLES
C22: Recent | D22: Price / | E22: Price/Sales | H22: P/E | K22: PEG | N22: EV/EBITDA | Q22: SAME STORE SALES GROWTH
A23: Company Name | B23: Ticker | C23: Price | D23: Book | E23: FYR1 | F23: FYR2 | G23: FYR3 | H23: FYR1 | I23: FYR2 | J23: FYR3 | K23: FYR1 | L23: FYR2 | M23: FYR3 | N23: Last FY | O23: FYR1 | P23: FYR2
A24: =A6 -> Clorox Co | B24: =IF(B6="","",B6) -> CLX | C24: =IF(C6="","",C6) -> 104.01 | D24: =IF(OR(B24="",ISNUMBER(F6)=FALSE,ISNUMBER(J6)=FALSE),"",F6/J6) -> 39.523923 | E24: =IF(OR($B24="",ISNUMBER($F6)=FALSE,ISNUMBER(D15)=FALSE),"",$F6/D15) -> 1.9532346 | F24: =IF(OR($B24="",ISNUMBER($F6)=FALSE,ISNUMBER(E15)=FALSE),"",$F6/E15) -> 1.8631596 | G24: =IF(OR($B24="",ISNUMBER($F6)=FALSE,ISNUMBER(F15)=FALSE),"",$F6/F15) -> 1.810943 | H24: =IF(OR($B24="",ISNA(H15)=TRUE),"",$C6/H15) -> 17.535016 | I24: =IF(OR($B24="",ISNA(I15)=TRUE),"",$C6/I15) -> 15.392037 | J24: =IF(OR($B24="",ISNA(J15)=TRUE),"",$C6/J15) -> 14.524163 | K24: =IF(OR($B24="",H24="",ISNA($Q15)=TRUE),"",H24/$Q15/100) -> -6.0570004 | L24: =IF(OR($B24="",I24="",ISNA($Q15)=TRUE),"",I24/$Q15/100) -> -5.316766 | M24: =IF(OR($B24="",J24="",ISNA($Q15)=TRUE),"",J24/$Q15/100) -> -5.016982 | N24: =IF(OR($B24="",ISNA($I6)=TRUE,ISNA(N15)=TRUE),"",$I6/N15) -> 10.615877 | O24: =IF(OR($B24="",ISNA($I6)=TRUE,ISNA(O15)=TRUE),"",$I6/O15) -> 11.869172 | P24: =IF(OR($B24="",ISNA($I6)=TRUE,ISNA(P15)=TRUE),"",$I6/P15) -> 10.731847
A25: =A7 -> Church & Dwight Co Inc | B25: =IF(B7="","",B7) -> CHD | C25: =IF(C7="","",C7) -> 84.61 | D25: =IF(OR(B25="",ISNUMBER(F7)=FALSE,ISNUMBER(J7)=FALSE),"",F7/J7) -> 4.6591005 | E25: =IF(OR($B25="",ISNUMBER($F7)=FALSE,ISNUMBER(D16)=FALSE),"",$F7/D16) -> 3.2775263 | F25: =IF(OR($B25="",ISNUMBER($F7)=FALSE,ISNUMBER(E16)=FALSE),"",$F7/E16) -> 3.1575201 | G25: =IF(OR($B25="",ISNUMBER($F7)=FALSE,ISNUMBER(F16)=FALSE),"",$F7/F16) -> 3.0506124 | H25: =IF(OR($B25="",ISNA(H16)=TRUE),"",$C7/H16) -> 24.194678 | I25: =IF(OR($B25="",ISNA(I16)=TRUE),"",$C7/I16) -> 22.575851 | J25: =IF(OR($B25="",ISNA(J16)=TRUE),"",$C7/J16) -> 21.148217 | K25: =IF(OR($B25="",H25="",ISNA($Q16)=TRUE),"",H25/$Q16/100) -> 4.8518708 | L25: =IF(OR($B25="",I25="",ISNA($Q16)=TRUE),"",I25/$Q16/100) -> 4.5272398 | M25: =IF(OR($B25="",J25="",ISNA($Q16)=TRUE),"",J25/$Q16/100) -> 4.2409499 | N25: =IF(OR($B25="",ISNA($I7)=TRUE,ISNA(N16)=TRUE),"",$I7/N16) -> 15.672041 | O25: =IF(OR($B25="",ISNA($I7)=TRUE,ISNA(O16)=TRUE),"",$I7/O16) -> 15.402005 | P25: =IF(OR($B25="",ISNA($I7)=TRUE,ISNA(P16)=TRUE),"",$I7/P16) -> 14.580628
A26: =A8 -> Dupont De Nemours Inc | B26: =IF(B8="","",B8) -> DD | C26: =IF(C8="","",C8) -> 40.93 | D26: =IF(OR(B26="",ISNUMBER(F8)=FALSE,ISNUMBER(J8)=FALSE),"",F8/J8) -> 0.73441799 | E26: =IF(OR($B26="",ISNUMBER($F8)=FALSE,ISNUMBER(D17)=FALSE),"",$F8/D17) -> 2.5043191 | F26: =IF(OR($B26="",ISNUMBER($F8)=FALSE,ISNUMBER(E17)=FALSE),"",$F8/E17) -> 2.4249936 | G26: =IF(OR($B26="",ISNUMBER($F8)=FALSE,ISNUMBER(F17)=FALSE),"",$F8/F17) -> 2.3320087 | H26: =IF(OR($B26="",ISNA(H17)=TRUE),"",$C8/H17) -> 23.127168 | I26: =IF(OR($B26="",ISNA(I17)=TRUE),"",$C8/I17) -> 18.980709 | J26: =IF(OR($B26="",ISNA(J17)=TRUE),"",$C8/J17) -> 17.443 | K26: =IF(OR($B26="",H26="",ISNA($Q17)=TRUE),"",H26/$Q17/100) -> #VALUE! | L26: =IF(OR($B26="",I26="",ISNA($Q17)=TRUE),"",I26/$Q17/100) -> #VALUE! | M26: =IF(OR($B26="",J26="",ISNA($Q17)=TRUE),"",J26/$Q17/100) -> #VALUE! | N26: =IF(OR($B26="",ISNA($I8)=TRUE,ISNA(N17)=TRUE),"",$I8/N17) -> 7.1749469 | O26: =IF(OR($B26="",ISNA($I8)=TRUE,ISNA(O17)=TRUE),"",$I8/O17) -> 13.953153 | P26: =IF(OR($B26="",ISNA($I8)=TRUE,ISNA(P17)=TRUE),"",$I8/P17) -> 13.192622
A27: =A9 -> Sherwin-Williams Co | B27: =IF(B9="","",B9) -> SHW | C27: =IF(C9="","",C9) -> 328.69 | D27: =IF(OR(B27="",ISNUMBER(F9)=FALSE,ISNUMBER(J9)=FALSE),"",F9/J9) -> 20.112589 | E27: =IF(OR($B27="",ISNUMBER($F9)=FALSE,ISNUMBER(D18)=FALSE),"",$F9/D18) -> 3.4648074 | F27: =IF(OR($B27="",ISNUMBER($F9)=FALSE,ISNUMBER(E18)=FALSE),"",$F9/E18) -> 3.2995869 | G27: =IF(OR($B27="",ISNUMBER($F9)=FALSE,ISNUMBER(F18)=FALSE),"",$F9/F18) -> 3.1611506 | H27: =IF(OR($B27="",ISNA(H18)=TRUE),"",$C9/H18) -> 28.892776 | I27: =IF(OR($B27="",ISNA(I18)=TRUE),"",$C9/I18) -> 26.161338 | J27: =IF(OR($B27="",ISNA(J18)=TRUE),"",$C9/J18) -> 23.283275 | K27: =IF(OR($B27="",H27="",ISNA($Q18)=TRUE),"",H27/$Q18/100) -> 3.8091992 | L27: =IF(OR($B27="",I27="",ISNA($Q18)=TRUE),"",I27/$Q18/100) -> 3.4490887 | M27: =IF(OR($B27="",J27="",ISNA($Q18)=TRUE),"",J27/$Q18/100) -> 3.0696474 | N27: =IF(OR($B27="",ISNA($I9)=TRUE,ISNA(N18)=TRUE),"",$I9/N18) -> 20.293385 | O27: =IF(OR($B27="",ISNA($I9)=TRUE,ISNA(O18)=TRUE),"",$I9/O18) -> 20.176156 | P27: =IF(OR($B27="",ISNA($I9)=TRUE,ISNA(P18)=TRUE),"",$I9/P18) -> 18.564256
A28: =A10 -> Ecolab Inc | B28: =IF(B10="","",B10) -> ECL | C28: =IF(C10="","",C10) -> 263.6 | D28: =IF(OR(B28="",ISNUMBER(F10)=FALSE,ISNUMBER(J10)=FALSE),"",F10/J10) -> 8.5255636 | E28: =IF(OR($B28="",ISNUMBER($F10)=FALSE,ISNUMBER(D19)=FALSE),"",$F10/D19) -> 4.6495078 | F28: =IF(OR($B28="",ISNUMBER($F10)=FALSE,ISNUMBER(E19)=FALSE),"",$F10/E19) -> 4.4136023 | G28: =IF(OR($B28="",ISNUMBER($F10)=FALSE,ISNUMBER(F19)=FALSE),"",$F10/F19) -> 4.2003633 | H28: =IF(OR($B28="",ISNA(H19)=TRUE),"",$C10/H19) -> 35.045595 | I28: =IF(OR($B28="",ISNA(I19)=TRUE),"",$C10/I19) -> 31.078785 | J28: =IF(OR($B28="",ISNA(J19)=TRUE),"",$C10/J19) -> 27.331016 | K28: =IF(OR($B28="",H28="",ISNA($Q19)=TRUE),"",H28/$Q19/100) -> 2.7573246 | L28: =IF(OR($B28="",I28="",ISNA($Q19)=TRUE),"",I28/$Q19/100) -> 2.4452231 | M28: =IF(OR($B28="",J28="",ISNA($Q19)=TRUE),"",J28/$Q19/100) -> 2.1503553 | N28: =IF(OR($B28="",ISNA($I10)=TRUE,ISNA(N19)=TRUE),"",$I10/N19) -> 22.496285 | O28: =IF(OR($B28="",ISNA($I10)=TRUE,ISNA(O19)=TRUE),"",$I10/O19) -> 21.042732 | P28: =IF(OR($B28="",ISNA($I10)=TRUE,ISNA(P19)=TRUE),"",$I10/P19) -> 19.215233
C30: Average | D30: =AVERAGE(D24:D27) -> 16.257507 | E30: =AVERAGE(E24:E27) -> 2.7999719 | F30: =AVERAGE(F24:F27) -> 2.686315 | G30: =AVERAGE(G24:G27) -> 2.5886787 | H30: =AVERAGE(H24:H27) -> 23.43741 | I30: =AVERAGE(I24:I27) -> 20.777484 | J30: =AVERAGE(J24:J27) -> 19.099664 | K30: =AVERAGE(K24,K26:K26) -> #VALUE! | L30: =AVERAGE(L24,L26:L26) -> #VALUE! | M30: =AVERAGE(M24,M26:M26) -> #VALUE! | N30: =AVERAGE(N24:N27) -> 13.439062 | O30: =AVERAGE(O24:O27) -> 15.350122 | P30: =AVERAGE(P24:P27) -> 14.267338
C31: Median | D31: =MEDIAN(D24:D27) -> 12.385845 | E31: =MEDIAN(E24:E27) -> 2.8909227 | F31: =MEDIAN(F24:F27) -> 2.7912568 | G31: =MEDIAN(G24:G27) -> 2.6913106 | H31: =MEDIAN(H24:H27) -> 23.660923 | I31: =MEDIAN(I24:I27) -> 20.77828 | J31: =MEDIAN(J24:J27) -> 19.295609 | K31: =MEDIAN(K24,K26:K26) -> #VALUE! | L31: =MEDIAN(L24,L26:L26) -> #VALUE! | M31: =MEDIAN(M24,M26:M26) -> #VALUE! | N31: =MEDIAN(N24:N27) -> 13.143959 | O31: =MEDIAN(O24:O27) -> 14.677579 | P31: =MEDIAN(P24:P27) -> 13.886625
C33: Average | D33: =D30*$J$10/$E$10 -> 502.66225 | E33: =(E30*D$19)/$E$10 -> 158.74209 | F33: =(F30*E$19)/$E$10 -> 160.43871 | G33: =(G30*F$19)/$E$10 -> 162.45635 | H33: =H30*H$19 -> 176.28752 | I33: =I30*I$19 -> 176.22776 | J33: =J30*J$19 -> 184.21091 | K33: =K30*H$19*$Q$19*100 -> #VALUE! | L33: =L30*I$19*$Q$19*100 -> #VALUE! | M33: =M30*J$19*$Q$19*100 -> #VALUE! | N33: =(N30*N$19-($G$10-$H$10))/$E$10 -> 148.50533 | O33: =(O30*O$19-($G$10-$H$10))/$E$10 -> 186.26425 | P33: =(P30*P$19-($G$10-$H$10))/$E$10 -> 189.98848
C34: Median | D34: =D31*$J$10/$E$10 -> 382.95516 | E34: =(E31*D$19)/$E$10 -> 163.89847 | F34: =(F31*E$19)/$E$10 -> 166.7063 | G34: =(G31*F$19)/$E$10 -> 168.89717 | H34: =H31*H$19 -> 177.96871 | I34: =I31*I$19 -> 176.23451 | J34: =J31*J$19 -> 186.10074 | K34: =K31*H$19*$Q$19*100 -> #VALUE! | L34: =L31*I$19*$Q$19*100 -> #VALUE! | M34: =M31*J$19*$Q$19*100 -> #VALUE! | N34: =(N31*N$19-($G$10-$H$10))/$E$10 -> 144.7553 | O34: =(O31*O$19-($G$10-$H$10))/$E$10 -> 177.12756 | P34: =(P31*P$19-($G$10-$H$10))/$E$10 -> 184.32448
D35: ws.OperatingProfitMargin[ws.cpa] | H35: ws.AssetTurnover[ws.cpa] | I35: ws.InventoryTurnover[ws.cpa] | J35: ws.ReceivablesTurnover[ws.cpa] | K35: ws.TotalDebtPctCommonEquity[ws.cpa] | L35: ws.LTDebtPctCommonEquity[ws.cpa] | M35: ws.LTDebtPctTotalCapital[ws.cpa] | N35: ws.QuickRatio[ws.cpa] | O35: ws.CurrentRatio[ws.cpa]
A36: RATIO ANALYSIS
C37: Gross | D37: Operating | E37: Net | H37: Asset | I37: Inventory | J37: Receivables | M37: Quick | N37: Current | O37: Interest
A38: Company Name | B38: Ticker | C38: Margin | D38: Margin | E38: Margin | F38: ROA | G38: ROE | H38: Turnvover | I38: Turnvover | J38: Turnvover | K38: Debt/E | L38: LTD/TC | M38: Ratio | N38: Ratio | O38: Coverage
A39: =A6 -> Clorox Co | B39: =IF(B15="","",B24) -> CLX | C39: {=IF($B39="","",_xll.RDP.Data($B39,"TR.GrossMargin")/100)} -> 0.4515766 | D39: {=IF($B39="","",_xll.RDP.Data($B39,"TR.OperatingMarginPercent")/100)} -> 0.1517455 | E39: {=IF($B39="","",_xll.RDP.Data($B39,"TR.NetProfitMargin")/100)} -> 0.1140203 | F39: {=IF($B39="","",_xll.RDP.Data($B39,"TR.ROAActValue")/100)} -> 0.1696 | G39: {=IF($B39="","",_xll.RDP.Data($B39,"TR.ROEActValue")/100)} -> 2.9568 | H39: =IF($B39="","",_xll.RDP.Data($B39,"TR.AssetTurnover")) -> 1.2560113 | I39: =IF($B39="","",_xll.RDP.Data($B39,"TR.InventoryTurnover")) -> 6.7172414 | J39: {=IF($B39="","",_xll.RDP.Data($B39,"TR.Revenue")/_xll.RDP.Data($B39,"TR.TotalReceivablesNet"))} -> 8.6528624 | K39: =IF($B39="","",_xll.RDP.Data($B39,"TR.TtlDebtToTtlEquityPct")) -> 786.29283 | L39: =IF($B39="","",_xll.RDP.Data($B39,"TR.LTDebtToTtlCapitalPct")) -> 83.333333 | M39: =IF($B39="","",_xll.RDP.Data($B39,"TR.QuickRatio")) -> 0.5654 | N39: =IF($B39="","",_xll.RDP.Data($B39,"TR.CurrentRatio")) -> 0.83794 | O39: {=IF($B39="","",_xll.RDP.Data($B39,"TR.EBITDA")/_xll.RDP.Data($B39,"TR.InterestExpense"))} -> 17.386364
A40: =A7 -> Church & Dwight Co Inc | B40: =IF(B16="","",B25) -> CHD | C40: {=IF($B40="","",_xll.RDP.Data($B40,"TR.GrossMargin")/100)} -> 0.4568617 | D40: {=IF($B40="","",_xll.RDP.Data($B40,"TR.OperatingMarginPercent")/100)} -> 0.1321577 | E40: {=IF($B40="","",_xll.RDP.Data($B40,"TR.NetProfitMargin")/100)} -> 0.0958393 | F40: {=IF($B40="","",_xll.RDP.Data($B40,"TR.ROAActValue")/100)} -> 0.0973 | G40: {=IF($B40="","",_xll.RDP.Data($B40,"TR.ROEActValue")/100)} -> 0.2067 | H40: =IF($B40="","",_xll.RDP.Data($B40,"TR.AssetTurnover")) -> 0.69986191 | I40: =IF($B40="","",_xll.RDP.Data($B40,"TR.InventoryTurnover")) -> 5.4084461 | J40: {=IF($B40="","",_xll.RDP.Data($B40,"TR.Revenue")/_xll.RDP.Data($B40,"TR.TotalReceivablesNet"))} -> 10.164947 | K40: =IF($B40="","",_xll.RDP.Data($B40,"TR.TtlDebtToTtlEquityPct")) -> 50.554944 | L40: =IF($B40="","",_xll.RDP.Data($B40,"TR.LTDebtToTtlCapitalPct")) -> 33.579066 | M40: =IF($B40="","",_xll.RDP.Data($B40,"TR.QuickRatio")) -> 1.23664 | N40: =IF($B40="","",_xll.RDP.Data($B40,"TR.CurrentRatio")) -> 1.70271 | O40: {=IF($B40="","",_xll.RDP.Data($B40,"TR.EBITDA")/_xll.RDP.Data($B40,"TR.InterestExpense"))} -> 14.771579
A41: =A8 -> Dupont De Nemours Inc | B41: =IF(B17="","",B26) -> DD | C41: {=IF($B41="","",_xll.RDP.Data($B41,"TR.GrossMargin")/100)} -> 0.365897 | D41: {=IF($B41="","",_xll.RDP.Data($B41,"TR.OperatingMarginPercent")/100)} -> 0.1244954 | E41: {=IF($B41="","",_xll.RDP.Data($B41,"TR.NetProfitMargin")/100)} -> 0.0599871 | F41: {=IF($B41="","",_xll.RDP.Data($B41,"TR.ROAActValue")/100)} -> 0.0455 | G41: {=IF($B41="","",_xll.RDP.Data($B41,"TR.ROEActValue")/100)} -> 0.0718 | H41: =IF($B41="","",_xll.RDP.Data($B41,"TR.AssetTurnover")) -> 0.32946747 | I41: =IF($B41="","",_xll.RDP.Data($B41,"TR.InventoryTurnover")) -> 3.6726678 | J41: {=IF($B41="","",_xll.RDP.Data($B41,"TR.Revenue")/_xll.RDP.Data($B41,"TR.TotalReceivablesNet"))} -> 5.6325603 | K41: =IF($B41="","",_xll.RDP.Data($B41,"TR.TtlDebtToTtlEquityPct")) -> 30.710921 | L41: =IF($B41="","",_xll.RDP.Data($B41,"TR.LTDebtToTtlCapitalPct")) -> 17.190931 | M41: =IF($B41="","",_xll.RDP.Data($B41,"TR.QuickRatio")) -> 0.8819 | N41: =IF($B41="","",_xll.RDP.Data($B41,"TR.CurrentRatio")) -> 1.32556 | O41: {=IF($B41="","",_xll.RDP.Data($B41,"TR.EBITDA")/_xll.RDP.Data($B41,"TR.InterestExpense"))} -> 8.3879781
A42: =A9 -> Sherwin-Williams Co | B42: =IF(B18="","",B27) -> SHW | C42: {=IF($B42="","",_xll.RDP.Data($B42,"TR.GrossMargin")/100)} -> 0.4846678 | D42: {=IF($B42="","",_xll.RDP.Data($B42,"TR.OperatingMarginPercent")/100)} -> 0.1475031 | E42: {=IF($B42="","",_xll.RDP.Data($B42,"TR.NetProfitMargin")/100)} -> 0.1160855 | F42: {=IF($B42="","",_xll.RDP.Data($B42,"TR.ROAActValue")/100)} -> 0.12359 | G42: {=IF($B42="","",_xll.RDP.Data($B42,"TR.ROEActValue")/100)} -> 0.74159 | H42: =IF($B42="","",_xll.RDP.Data($B42,"TR.AssetTurnover")) -> 0.99162857 | I42: =IF($B42="","",_xll.RDP.Data($B42,"TR.InventoryTurnover")) -> 5.1553303 | J42: {=IF($B42="","",_xll.RDP.Data($B42,"TR.Revenue")/_xll.RDP.Data($B42,"TR.TotalReceivablesNet"))} -> 9.4518782 | K42: =IF($B42="","",_xll.RDP.Data($B42,"TR.TtlDebtToTtlEquityPct")) -> 248.75839 | L42: =IF($B42="","",_xll.RDP.Data($B42,"TR.LTDebtToTtlCapitalPct")) -> 59.18649 | M42: =IF($B42="","",_xll.RDP.Data($B42,"TR.QuickRatio")) -> 0.45717 | N42: =IF($B42="","",_xll.RDP.Data($B42,"TR.CurrentRatio")) -> 0.79322 | O42: {=IF($B42="","",_xll.RDP.Data($B42,"TR.EBITDA")/_xll.RDP.Data($B42,"TR.InterestExpense"))} -> 10.536503
A43: =A10 -> Ecolab Inc | B43: =IF(B19="","",B28) -> ECL | C43: {=IF($B43="","",_xll.RDP.Data($B43,"TR.GrossMargin")/100)} -> 0.4349677 | D43: {=IF($B43="","",_xll.RDP.Data($B43,"TR.OperatingMarginPercent")/100)} -> 0.1780274 | E43: {=IF($B43="","",_xll.RDP.Data($B43,"TR.NetProfitMargin")/100)} -> 0.1341939 | F43: {=IF($B43="","",_xll.RDP.Data($B43,"TR.ROAActValue")/100)} -> 0.08619 | G43: {=IF($B43="","",_xll.RDP.Data($B43,"TR.ROEActValue")/100)} -> 0.22699 | H43: =IF($B43="","",_xll.RDP.Data($B43,"TR.AssetTurnover")) -> 0.71172662 | I43: =IF($B43="","",_xll.RDP.Data($B43,"TR.InventoryTurnover")) -> 6.0054691 | J43: {=IF($B43="","",_xll.RDP.Data($B43,"TR.Revenue")/_xll.RDP.Data($B43,"TR.TotalReceivablesNet"))} -> 5.1980979 | K43: =IF($B43="","",_xll.RDP.Data($B43,"TR.TtlDebtToTtlEquityPct")) -> 86.383931 | L43: =IF($B43="","",_xll.RDP.Data($B43,"TR.LTDebtToTtlCapitalPct")) -> 42.492097 | M43: =IF($B43="","",_xll.RDP.Data($B43,"TR.QuickRatio")) -> 0.95159 | N43: =IF($B43="","",_xll.RDP.Data($B43,"TR.CurrentRatio")) -> 1.25724 | O43: {=IF($B43="","",_xll.RDP.Data($B43,"TR.EBITDA")/_xll.RDP.Data($B43,"TR.InterestExpense"))} -> 10.444608

Sheet Comps no formula
C1: USD
A2: COMPARABLE COMPANY ANALYSIS
A3: COMPANY DATA
A4: (in millions) | C4: Recent | D4: 52 week | E4: Shares | F4: Market | G4: Total | I4: Enterprise | J4: Book | L4: WS 12-mo
A5: Company Name | B5: Ticker | C5: Price | D5: High | E5: Out | F5: Cap | G5: Debt | H5: Cash | I5: Value | J5: Value | K5: Beta | L5: Price Target
A6: Clorox Co | B6: CLX | C6: 119.59 | D6: 171.37 | E6: 121.77358 | F6: 14562.902 | G6: 2524 | H6: 167 | I6: 16919.902 | J6: 321 | K6: 0.52029938 | L6: 133.895
A7: Church & Dwight Co Inc | B7: CHD | C7: 88.08 | D7: 116.46 | E7: 243.6087 | F7: 21457.054 | G7: 2204.6 | H7: 964.1 | I7: 22697.554 | J7: 4360.8 | K7: 0.4117981 | L7: 98.00632
A8: Dupont De Nemours Inc | B8: DD | C8: 80.95 | D8: 87.8 | E8: 418.86724 | F8: 33907.303 | G8: 7171 | H8: 1850 | I8: 39228.303 | J8: 23350 | K8: 1.0884169 | L8: 92.08067
A9: Sherwin-Williams Co | B9: SHW | C9: 331.24 | D9: 400.42 | E9: 249.33332 | F9: 82589.168 | G9: 10077.7 | H9: 210.4 | I9: 92456.468 | J9: 4051.2 | K9: 1.2136333 | L9: 378.54286
A10: Ecolab Inc | B10: ECL | C10: 280.17 | D10: 286.04 | E10: 283.62491 | F10: 79463.192 | G10: 7564.9 | H10: 1256.8 | I10: 85771.292 | J10: 8757.3 | K10: 1.0803688 | L10: 288.44368
A12: I/B/E/S ESTIMATES
C13: SALES | G13: EPS | K13: EBIT | N13: EBITDA | Q13: EPS 5-yr
A14: Company Name | B14: Ticker | C14: Last FY | D14: FYR1 | E14: FYR2 | F14: FYR3 | G14: Last FY | H14: FYR1 | I14: FYR2 | J14: FYR3 | K14: Last FY | L14: FYR1 | M14: FYR2 | N14: Last FY | O14: FYR1 | P14: FYR2 | Q14: Growth %
A15: Clorox Co | B15: CLX | C15: 7104 | D15: 6497.8198 | E15: 6784.8571 | F15: 6997.1822 | G15: 7.04971 | H15: 5.95833 | I15: 6.79433 | J15: 7.22325 | K15: 1196.5612 | L15: 1056.4671 | M15: 1194.8062 | N15: 1417.1396 | O15: 1261.085 | P15: 1407.2695 | Q15: -0.02445
A16: Church & Dwight Co Inc | B16: CHD | C16: 6107.1 | D16: 6144.3529 | E16: 6385.3027 | F16: 6625.2999 | G16: 3.44016 | H16: 3.474 | I16: 3.739 | J16: 3.98073 | K16: 1145.8387 | L16: 1165.2896 | M16: 1243.5027 | N16: 1375.5647 | O16: 1400.9216 | P16: 1478.2394 | Q16: 0.0499333
A17: Dupont De Nemours Inc | B17: DD | C17: 12386 | D17: 12840.031 | E17: 13161.369 | F17: 13766.274 | G17: 3.91061 | H17: 4.399 | I17: 4.70156 | J17: 5.197 | K17: 2535.1266 | L17: 2715.9714 | M17: 2868.1606 | N17: 3131.6831 | O17: 3359.817 | P17: 3516.2934 | Q17: 0.08015
A18: Sherwin-Williams Co | B18: SHW | C18: 23098.5 | D18: 23230.98 | E18: 24278.286 | F18: 25518.694 | G18: 11.29786 | H18: 11.31952 | I18: 12.64485 | J18: 14.32806 | K18: 3947.4394 | L18: 3985.8493 | M18: 4348.4852 | N18: 4501.3397 | O18: 4522.1499 | P18: 4898.6712 | Q18: 0.08105
A19: Ecolab Inc | B19: ECL | C19: 15741.4 | D19: 16052.349 | E19: 16967.52 | F19: 17844.86 | G19: 6.63082 | H19: 7.53068 | I19: 8.53532 | J19: 9.73024 | K19: 2630.6934 | L19: 2912.2141 | M19: 3240.6451 | N19: 3599.2173 | O19: 3873.5826 | P19: 4237.7645 | Q19: 0.12345
A21: VALUATION MULTIPLES
C22: Recent | D22: Price / | E22: Price/Sales | H22: P/E | K22: PEG | N22: EV/EBITDA | Q22: SAME STORE SALES GROWTH
A23: Company Name | B23: Ticker | C23: Price | D23: Book | E23: FYR1 | F23: FYR2 | G23: FYR3 | H23: FYR1 | I23: FYR2 | J23: FYR3 | K23: FYR1 | L23: FYR2 | M23: FYR3 | N23: Last FY | O23: FYR1 | P23: FYR2
A24: Clorox Co | B24: CLX | C24: 119.59 | D24: 45.367297 | E24: 2.2411983 | F24: 2.1463831 | G24: 2.0812524 | H24: 20.07106 | I24: 17.601441 | J24: 16.556259 | K24: -8.2090226 | L24: -7.1989535 | M24: -6.7714762 | N24: 11.939475 | O24: 13.41694 | P24: 12.023214
A25: Church & Dwight Co Inc | B25: CHD | C25: 88.08 | D25: 4.9204398 | E25: 3.4921584 | F25: 3.3603816 | G25: 3.238654 | H25: 25.354059 | I25: 23.557101 | J25: 22.126595 | K25: 5.0775852 | L25: 4.7177136 | M25: 4.4312302 | N25: 16.500536 | O25: 16.201873 | P25: 15.35445
A26: Dupont De Nemours Inc | B26: DD | C26: 80.95 | D26: 1.4521329 | E26: 2.6407492 | F26: 2.5762747 | G26: 2.4630704 | H26: 18.40191 | I26: 17.217689 | J26: 15.576294 | K26: 2.2959338 | L26: 2.1481833 | M26: 1.9433929 | N26: 12.526268 | O26: 11.675726 | P26: 11.156152
A27: Sherwin-Williams Co | B27: SHW | C27: 331.24 | D27: 20.386347 | E27: 3.5551305 | F27: 3.401771 | G27: 3.2364182 | H27: 29.262725 | I27: 26.195645 | J27: 23.118273 | K27: 3.6104534 | L27: 3.2320351 | M27: 2.852347 | N27: 20.539767 | O27: 20.445246 | P27: 18.873785
A28: Ecolab Inc | B28: ECL | C28: 280.17 | D28: 9.0739374 | E28: 4.9502531 | F28: 4.6832532 | G28: 4.4530017 | H28: 37.203812 | I28: 32.82478 | J28: 28.79374 | K28: 3.0136745 | L28: 2.6589534 | M28: 2.3324212 | N28: 23.83054 | O28: 22.142626 | P28: 20.239749
C30: Average | D30: 18.031554 | E30: 2.9823091 | F30: 2.8712026 | G30: 2.7548488 | H30: 23.272438 | I30: 21.142969 | J30: 19.344355 | K30: -2.9565444 | L30: -2.5253851 | M30: -2.4140417 | N30: 15.376511 | O30: 15.434946 | P30: 14.3519
C31: Median | D31: 12.653393 | E31: 3.0664538 | F31: 2.9683282 | G31: 2.8497443 | H31: 22.712559 | I31: 20.579271 | J31: 19.341427 | K31: -2.9565444 | L31: -2.5253851 | M31: -2.4140417 | N31: 14.513402 | O31: 14.809407 | P31: 13.688832
C33: Average | D33: 556.74844 | E33: 168.79007 | F33: 171.76625 | G33: 173.32712 | H33: 175.25729 | I33: 180.46201 | J33: 188.22522 | K33: -274.85883 | L33: -266.0961 | M33: -289.97423 | N33: 172.88786 | O33: 188.56045 | P33: 192.19706
C34: Median | D34: 390.69051 | E34: 173.55241 | F34: 177.57667 | G34: 179.29768 | H34: 171.04102 | I34: 175.65066 | J34: 188.19673 | K34: -274.85883 | L34: -266.0961 | M34: -289.97423 | N34: 161.93495 | O34: 180.01719 | P34: 182.28986
D35: ws.OperatingProfitMargin[ws.cpa] | H35: ws.AssetTurnover[ws.cpa] | I35: ws.InventoryTurnover[ws.cpa] | J35: ws.ReceivablesTurnover[ws.cpa] | K35: ws.TotalDebtPctCommonEquity[ws.cpa] | L35: ws.LTDebtPctCommonEquity[ws.cpa] | M35: ws.LTDebtPctTotalCapital[ws.cpa] | N35: ws.QuickRatio[ws.cpa] | O35: ws.CurrentRatio[ws.cpa]
A36: RATIO ANALYSIS
C37: Gross | D37: Operating | E37: Net | H37: Asset | I37: Inventory | J37: Receivables | M37: Quick | N37: Current | O37: Interest
A38: Company Name | B38: Ticker | C38: Margin | D38: Margin | E38: Margin | F38: ROA | G38: ROE | H38: Turnvover | I38: Turnvover | J38: Turnvover | K38: Debt/E | L38: LTD/TC | M38: Ratio | N38: Ratio | O38: Coverage
A39: Clorox Co | B39: CLX | C39: 0.4515766 | D39: 0.1517455 | E39: 0.1140203 | F39: 0.1696 | G39: 2.9568 | H39: 1.2560113 | I39: 6.7172414 | J39: 8.6528624 | K39: 786.29283 | L39: 83.333333 | M39: 0.5654 | N39: 0.83794 | O39: 17.386364
A40: Church & Dwight Co Inc | B40: CHD | C40: 0.4568617 | D40: 0.1321577 | E40: 0.0958393 | F40: 0.0973 | G40: 0.2067 | H40: 0.69986191 | I40: 5.4084461 | J40: 10.164947 | K40: 50.554944 | L40: 33.579066 | M40: 1.23664 | N40: 1.70271 | O40: 14.771579
A41: Dupont De Nemours Inc | B41: DD | C41: 0.365897 | D41: 0.1244954 | E41: 0.0599871 | F41: 0.0455 | G41: 0.0718 | H41: 0.32946747 | I41: 3.6726678 | J41: 5.6325603 | K41: 30.710921 | L41: 17.190931 | M41: 0.8819 | N41: 1.32556 | O41: 8.3879781
A42: Sherwin-Williams Co | B42: SHW | C42: 0.4846678 | D42: 0.1475031 | E42: 0.1160855 | F42: 0.12359 | G42: 0.74159 | H42: 0.99162857 | I42: 5.1553303 | J42: 9.4518782 | K42: 248.75839 | L42: 59.18649 | M42: 0.45717 | N42: 0.79322 | O42: 10.536503
A43: Ecolab Inc | B43: ECL | C43: 0.4349677 | D43: 0.1780274 | E43: 0.1341939 | F43: 0.08619 | G43: 0.22699 | H43: 0.71172662 | I43: 6.0054691 | J43: 5.1980979 | K43: 86.383931 | L43: 42.492097 | M43: 0.95159 | N43: 1.25724 | O43: 10.444608
