Workbook
Name AcquisitionsToggle: #REF!
Name CaseTable: #REF!
Name CaseToggle: #REF!
Name Company_Name: #REF!
Name date: #REF!
Name DeferredTaxUseRatio: #REF!
Name EarningsTable: #REF!
Name GVKey: ""
Name Scenario: #REF!
Name SPSet: "current"
Name SPWS_WBID: "5B7D581C-6777-4964-9E9E-E04793492FA2"
Name Stock_Name: #REF!
Name Stock_Name: #REF!
Name Stock_Ticker: #REF!
Name Stock_Ticker: #REF!
Name Ticker: #REF!
Name UseDeferredTaxAsset: #REF!

Sheet Cover
H7: Scenario Switchboard
H9: Revenue & Operating Expenses
H10: Business Segment
D11: Valuation Date: | E11: =TODAY() -> 45959 | H11: US Ground -no of Packages | I11: 2
D12: Company Name: | E12: Fedex corporation | H12: US Ground - Revenue Per Package | I12: 2
D13: Sector: | E13: Industrials | H13: International Export - no of Packages | I13: 2
D14: Industry: | E14: Logistics | H14: International Export - Revenue per package | I14: 2
D15: Rating: | E15: =IF(E23>=Ke!D38,"BUY","SELL") -> BUY | H15: Salaries & Employee Benefits-cogs | I15: 2
H16: Purchased Transportation-cogs | I16: 2
D17: Current Price | E17: =Ke!D15 -> 249.31 | H17: Scenario Key
D18: Valuation Price | E18: =DCF!B8 -> 272.0515 | H18: Bull | I18: 1
D19: 12-month Valuation Price | E19: =DCF!B9 -> 289.87884 | H19: Base | I19: 2
D20: Valuation Appreciation | E20: =E18/E17-1 -> 0.091217743 | H20: Bear | I20: 3
D21: 12-mo Valuation Appreciation | E21: =E19/E17-1 -> 0.16272449
D22: Dividend Yield | E22: 0.0239
D23: Total Valuation Appreciation | E23: =E21+E22 -> 0.18662449

Sheet DCF
A1: #VALUE!
H2: Share count in Millions
A3: Cost of Equity | B3: =Ke!D38 -> 0.11990275 | G3: =TODAY() -> 45959 | H3: Today | I3: ='Balance sheet'!F169 -> 235.95546
A4: Number of Shares in thousands: | B4: =I3 -> 235.95546 | G4: =G3+365 -> 46324 | H4: One year | I4: ='Balance sheet'!G169 -> 229.19789
G5: =G4+366 -> 46690 | H5: Two year | I5: ='Balance sheet'!H169 -> 223.241
A6: Actual Price: | B6: 242.84 | C6: At close oct 22, 2025
G7: Price Appreciation
A8: Model Valuation: | B8: =B24 -> 272.0515 | G8: Price Appreciation | I8: =B8/$B$6-1 -> 0.12029112
A9: Model 12 Month Price Target: | B9: =B46 -> 289.87884 | G9: Price Appreciation (12 month) | I9: =B9/B6-1 -> 0.19370303
A12: Model Current Valuation with Sensitivity of Ke
C14: 46173 | D14: 46538 | E14: 46904 | F14: 47269 | G14: 47634
A15: Time period (years) | C15: =MAX((C14-$G$3)/365,0) -> 0.58630137 | D15: =MAX((D14-$G$3)/365,0) -> 1.5863014 | E15: =MAX((E14-$G$3)/365,0) -> 2.5890411 | F15: =MAX((F14-$G$3)/365,0) -> 3.5890411 | G15: =MAX((G14-$G$3)/365,0) -> 4.5890411
A16: Nominal FCFE: | C16: =('Derived cash flow'!C59) -> 4634.6456 | D16: ='Derived cash flow'!D59 -> 6720.3146 | E16: ='Derived cash flow'!E59 -> 6901.7995 | F16: ='Derived cash flow'!F59 -> 6955.6837 | G16: ='Derived cash flow'!G59 -> 6382.3736
A17: PV FCFE: | C17: =(C16*C15)/((1+$B$3)^C15) -> 2542.7459 | D17: =D16/((1+$B$3)^D15) -> 5615.3239 | E17: =E16/((1+$B$3)^E15) -> 5147.9283 | F17: =F16/((1+$B$3)^F15) -> 4632.6518 | G17: =G16/((1+$B$3)^G15) -> 3795.6988
A19: Terminal Growth Rate | B19: 0.028
A21: Terminal Value in 2029 | B21: =G16*(1+B19)/(B3-B19) -> 71391.55 | D21: <== Implied terminal value / net income (or P/E) multiple for terminal value
A22: PV of Terminal Value | B22: =B21/(1+B3)^(G15) -> 42457.687
A23: Total PV: | B23: =SUM(C17:G17)+B22 -> 64192.036
A24: Valuation per Share ($): | B24: =B23/B4 -> 272.0515
C25: Terminal Growth Rate
B26: =B24 -> 272.0515 | C26: =D26-L27 -> 0.013 | D26: =E26-L27 -> 0.018 | E26: =F26-L27 -> 0.023 | F26: 0.028 | G26: =F26+L27 -> 0.033 | H26: =G26+L27 -> 0.038 | I26: =H26+L27 -> 0.043 | L26: 0.005
B27: =B28+L27 -> 0.13490275 | C27: 214.68367 | D27: 220.70975 | E27: 227.27435 | F27: 234.45301 | G27: 242.33614 | H27: 251.03277 | I27: 260.6757 | L27: 0.005
B28: =B29+L27 -> 0.12990275 | C28: 223.78936 | D28: 230.45881 | E28: 237.75215 | F28: 245.76119 | G28: 254.59674 | H28: 264.39369 | I28: 275.31799
B29: =B30+L27 -> 0.12490275 | C29: 233.70567 | D29: 241.11602 | E29: 249.25357 | F29: 258.23089 | G29: 268.18503 | H29: 279.2846 | I29: 291.73939
A30: Cost Of Equity Ke | B30: =Ke!D38 -> 0.11990275 | C30: 244.54623 | D30: 252.81493 | E30: 261.93693 | F30: 272.0515 | G30: 283.32996 | H30: 295.98548 | I30: 310.28665
B31: =B30-L27 -> 0.11490275 | C31: 256.44696 | D31: 265.71664 | E31: 275.99496 | F31: 287.45602 | G31: 300.31642 | H31: 314.84912 | I31: 331.40298
B32: =B31-L27 -> 0.10990275 | C32: 269.57186 | D32: 280.01733 | E32: 291.66477 | F32: 304.73432 | G32: 319.50337 | H32: 336.32644 | I32: 355.66407
B33: =B32-L27 -> 0.10490275 | C33: 284.12057 | D33: 295.9583 | E33: 309.24136 | F33: 324.25168 | G33: 341.34959 | H33: 361.00313 | I33: 383.83158
A36: Model 12 Month Price Target with Sensitivity of Ke
C38: =C14 -> 46173 | D38: =D14 -> 46538 | E38: =E14 -> 46904 | F38: =F14 -> 47269 | G38: =G14 -> 47634
A39: Time period | C39: =MAX((C38-$G$4)/365,0) -> 0 | D39: =MAX((D38-$G$4)/365,0) -> 0.58630137 | E39: =MAX((E38-$G$4)/365,0) -> 1.5890411 | F39: =MAX((F38-$G$4)/365,0) -> 2.5890411 | G39: =MAX((G38-$G$4)/365,0) -> 3.5890411
A40: Nominal FCFE: | C40: 0 | D40: =D16*D39 -> 3940.1297 | E40: =E16 -> 6901.7995 | F40: =F16 -> 6955.6837 | G40: =G16 -> 6382.3736
A41: PV FCFE: | C41: =(C40*C39)/((1+$B$3)^C39) -> 0 | D41: =D40/((1+$B$3)^D39) -> 3687.0246 | E41: =E40/((1+$B$3)^E39) -> 5765.179 | F41: =F40/((1+$B$3)^F39) -> 5188.1195 | G41: =G40/((1+$B$3)^G39) -> 4250.8136
A43: Terminal Value in 2030 | B43: =G40*(1+B19)/(B3-B19) -> 71391.55
A44: PV of Terminal Value | B44: =B43/(1+B3)^G39 -> 47548.481
A45: Total PV: | B45: =SUM(D41:H41)+B44 -> 66439.618
A46: Valuation per Share ($): | B46: =B45/I4 -> 289.87884
C47: Terminal Growth Rate
B48: =B46 -> 289.87884 | C48: =D48-$L$26 -> 0.013 | D48: =E48-$L$26 -> 0.018 | E48: =F48-$L$26 -> 0.023 | F48: 0.028 | G48: =F48+$L$26 -> 0.033 | H48: =G48+$L$26 -> 0.038 | I48: =H48+$L$26 -> 0.043
B49: =B50+$L$27 -> 0.13490275 | C49: 227.07307 | D49: 234.11373 | E49: 241.78356 | F49: 250.17085 | G49: 259.38121 | H49: 269.54204 | I49: 280.80849
B50: =B51+$L$27 -> 0.12990275 | C50: 236.5535 | D50: 244.31151 | E50: 252.79524 | F50: 262.11149 | G50: 272.38914 | H50: 283.78512 | I50: 296.49244
B51: =B52+$L$27 -> 0.12490275 | C51: 246.87879 | D51: 255.46049 | E51: 264.88433 | F51: 275.28068 | G51: 286.80826 | H51: 299.66233 | I51: 314.08583
A52: Cost Of Equity Ke | B52: =Ke!D38 -> 0.11990275 | C52: 258.16743 | D52: 267.70059 | E52: 278.21754 | F52: 289.87884 | G52: 302.88203 | H52: 317.47285 | I52: 333.96098
B53: =B52-$L$27 -> 0.11490275 | C53: 270.56116 | D53: 281.20066 | E53: 292.99785 | F53: 306.15255 | G53: 320.91339 | H53: 337.59365 | I53: 356.59374
B54: =B53-$L$27 -> 0.10990275 | C54: 284.23098 | D54: 296.16626 | E54: 309.47494 | F54: 324.40856 | G54: 341.28406 | H54: 360.50655 | I54: 382.60224
B55: =B54-$L$27 -> 0.10490275 | C55: 299.3851 | D55: 312.85026 | E55: 327.95948 | F55: 345.03341 | G55: 364.48192 | H55: 386.83742 | I55: 412.80431

Sheet Ke
A1: #VALUE! | D1: FDX.O | G1: Price = E*(1+g)/(ke-g)
A2: Cost of Equity | G2: P/E = (1+g)/(ke-g)
A3: (Blue = input, Black = calculation) | G3: ke = (1+g)/(P/E) + g
C4: Historic Beta | D4: 1.31
A5: S&P 500 data | F5: Source | G5: Reference
B6: S&P500 Forward P/E | D6: 22.17 | F6: WSJ | G6: 1-Year Forward P/E for S&P
B7: Projected EPS growth rate (g S&P) | D7: 0.1111 | F7: CapIQ/Bloomberg | G7: 5-Year Projected Earnings Growth Rate for S&P
B8: Risk-free rate (Rf) | D8: 0.0407 | F8: WSJ (5/8) | G8: 10 yr T-Note
B9: Implied required return on equity (Rs&p500) | D9: =((1+D7)/D6)+D7 -> 0.16121728 | G9: { (1+ gs&p500 ) / (P/Es&p500) } + gs&p500
B10: Implied equity risk premium (Rm) | D10: =(D8-D9)*-1 -> 0.12051728 | G10: Rs&p500-Rm
A13: Beta
A14: Fedex data
B15: Current Price (P) | D15: 249.31 | F15: WorkSpace
B16: Forward EPS (E) | D16: 18.03 | F16: WorkSpace | H16: 33.06
B17: P/E ratio | D17: =D15/D16 -> 13.82751 | F17: WorkSpace | G17: calc | J17: Book
B18: Projected EPS growth rate (g) | D18: ='Comps NF'!Q19 -> 0.104125 | F18: WorkSpace + Calculation | G18: Took the average | I18: Market Cap | J18: D/E Ratio | K18: Tax Rate | L18: bU = bL / (1+ ((1-t)D/E)) | M18: bL = bu (1+ ((1-t)D/E))
B19: Implied required return on equity (Re) | D19: =((1+D18)/(D17))+D18 -> 0.18397488 | G19: { (1+g) / (P/E) } +g | I19: UPS | J19: 1.5708 | K19: 0.23 | L19: =E23/(1+((1-K19)*J19)) -> 0.48426895 | M19: =L19*(1+((1-$K$26)*$J$26)) -> 0.7601025
B20: Forward (Bf) | D20: =(D19-D8)/D10 -> 1.1888327 | G20: (Re-Rf)/Rm | I20: JBHT.O | J20: 0.4485 | K20: 0.246 | L20: =E24/(1+((1-K20)*J20)) -> 0.91916641 | M20: =L20*(1+((1-$K$26)*$J$26)) -> 1.4427121
I21: GXO | J21: 0.9136 | K21: 0.368 | L21: =E25/(1+((1-K21)*J21)) -> 1.0840657 | M21: =L21*(1+((1-$K$26)*$J$26)) -> 1.7015359
A22: Comparable Beta | D22: Relevered | E22: Market Beta | I22: CHRW | J22: 0.7718 | K22: 0.192 | L22: =E26/(1+((1-K22)*J22)) -> 0.53584152 | M22: =L22*(1+((1-$K$26)*$J$26)) -> 0.84105014
B23: UPS | D23: =M19 -> 0.7601025 | E23: 1.07 | F23: Workspace
B24: JB hunt transport | D24: =M20 -> 1.4427121 | E24: 1.23 | F24: Workspace
B25: GXO logistics | D25: =M21 -> 1.7015359 | E25: 1.71 | F25: Workspace | J25: D/E Ratio | K25: Tax Rate | L25: Unlevered | M25: Relevered
B26: CHRW | D26: =M22 -> 0.84105014 | E26: 0.87 | F26: Workspace | I26: FDX | J26: 0.7625 | K26: 0.253 | L26: =D30/(1+((1-K26)*J26)) -> 0.83461419 | M26: =L26*(1+((1-K26)*J26)) -> 1.31
B27: Mean | D27: =AVERAGE(D23:D26) -> 1.1863502 | E27: =AVERAGE(E23:E26) -> 1.22
A29: Historical Beta
B30: Historic (Bh) - 5-year monthly | D30: =D4 -> 1.31 | F30: WorkSpace | G30: Five-year monthly beta
A32: Cost of Equity:
B33: Historic equity risk premium | D33: 0.065 | E33: Weight | G33: Based on long-term, historic, average risk premium (see class slides, source: Damodaran)
B34: Using Forward Beta | D34: =$D$8+D20*$D$33 -> 0.11797413 | E34: 0.5 | G34: Rf+Rm*Bf
B35: Using Comparable Beta | D35: =$D$8+D27*$D$33 -> 0.11781276 | E35: 0.25
B36: Using Historic Beta | D36: =$D$8+D30*$D$33 -> 0.12585 | E36: 0.25 | G36: Rf+Rm*Bh
B38: Weighted COE | D38: =SUMPRODUCT(D34:D36,E34:E36) -> 0.11990275
B40: Market COE (beta = 1) | D40: =D33+D8 -> 0.1057 | G40: Assumes beta of 1.0

Sheet Revenue
A1: FEDEX CORPORATION | C1: 2021 | D1: 2022 | E1: 2023 | F1: 2024 | G1: 2025 | J1: 2026E | K1: 2027E | L1: 2028E | M1: 2029E | N1: 2030E
A2: REVENUE STATEMENT
A4: Federal Express | C4: =42078+30496 -> 72574 | D4: =45814+33232 -> 79046 | E4: 75884 | F4: 74663 | G4: 75304 | J4: =J30 -> 77338.698 | K4: =K30 -> 78695.627 | L4: =L30 -> 80336.673 | M4: =M30 -> 81896.234 | N4: =N30 -> 83495.33
A5: FedEx Frieght | C5: 7833 | D5: 9532 | E5: 10084 | F5: 9429 | G5: 8892 | J5: =J32 -> 8962.7005 | K5: =K32 -> 9156.043 | L5: =L32 -> 9432.6225 | M5: =M32 -> 9717.5566 | N5: =N32 -> 10011.098
A6: Other(Print &Office) | C6: =3520+32 -> 3552 | D6: =4681+253 -> 4934 | E6: 4187 | F6: 3601 | G6: 3730 | J6: =J34 -> 3484 | K6: =K34 -> 3588.6619 | L6: =L34 -> 3696.4679 | M6: =M34 -> 3807.5125 | N6: =N34 -> 3921.8929
A7: Total | C7: =SUM(C4:C6) -> 83959 | D7: =SUM(D4:D6) -> 93512 | E7: =SUM(E4:E6) -> 90155 | F7: =SUM(F4:F6) -> 87693 | G7: =SUM(G4:G6) -> 87926 | J7: =SUM(J4:J6) -> 89785.399 | K7: =SUM(K4:K6) -> 91440.332 | L7: =SUM(L4:L6) -> 93465.763 | M7: =SUM(M4:M6) -> 95421.303 | N7: =SUM(N4:N6) -> 97428.321
A10: Federal Express segment
A11: Package:
A12: US priority revenue | C12: =8116+1791 -> 9907 | D12: =9084+1971 -> 11055 | E12: 10896 | F12: 10543 | G12: 10520 | J12: =J48*J43/1000 -> 10653.831 | K12: =K48*K43/1000 -> 10705.502 | L12: =L48*L43/1000 -> 10866.084 | M12: =M48*M43/1000 -> 11139.366 | N12: =N48*N43/1000 -> 11419.521
A13: US deferred revenue | C13: 4984 | D13: 5330 | E13: 5126 | F13: 4926 | G13: 5007 | J13: =J52*J43/1000 -> 5176.5974 | K13: =K52*K43/1000 -> 5332.9307 | L13: =L52*L43/1000 -> 5493.9852 | M13: =M52*M43/1000 -> 5659.9035 | N13: =N52*N43/1000 -> 5830.8326
A14: US ground revenue | C14: 30496 | D14: 33232 | E14: 32352 | F14: 32981 | G14: 33887 | J14: =J56*260/1000 -> 35373.279 | K14: =K56*260/1000 -> 36084.282 | L14: =L56*260/1000 -> 36809.576 | M14: =M56*260/1000 -> 37177.672 | N14: =N56*260/1000 -> 37549.449
A15: Total US domestic package revenue | C15: =SUM(C12:C14) -> 45387 | D15: =SUM(D12:D14) -> 49617 | E15: =SUM(E12:E14) -> 48374 | F15: =SUM(F12:F14) -> 48450 | G15: =SUM(G12:G14) -> 49414 | J15: =SUM(J12:J14) -> 51203.707 | K15: =SUM(K12:K14) -> 52122.714 | L15: =SUM(L12:L14) -> 53169.646 | M15: =SUM(M12:M14) -> 53976.942 | N15: =SUM(N12:N14) -> 54799.803
A16: International Priority | C16: 10317 | D16: 12130 | E16: 10938 | F16: 9454 | G16: 8737
A17: International economy | C17: 2632 | D17: 2838 | E17: 3307 | F17: 4653 | G17: 5861
A18: Total international export package revenue | C18: =SUM(C16:C17) -> 12949 | D18: =SUM(D16:D17) -> 14968 | E18: =SUM(E16:E17) -> 14245 | F18: =SUM(F16:F17) -> 14107 | G18: =SUM(G16:G17) -> 14598 | J18: =J60*J43/1000 -> 14857.884 | K18: =K60*K43/1000 -> 15003.491 | L18: =L60*L43/1000 -> 15303.561 | M18: =M60*M43/1000 -> 15765.728 | N18: =N60*N43/1000 -> 16241.853 | Q18: Calcualted as total due to the 10k reporting method
A19: International domestic | C19: 4640 | D19: 4340 | E19: 4552 | F19: 4659 | G19: 4495 | J19: =J64*J43/1000 -> 4576.3048 | K19: =K64*K43/1000 -> 4625.3603 | L19: =L64*L43/1000 -> 4674.9416 | M19: =M64*M43/1000 -> 4725.0544 | N19: =N64*N43/1000 -> 4775.7044
A20: Total package revenue | C20: =C19+C18+C15 -> 62976 | D20: =D19+D18+D15 -> 68925 | E20: =E19+E18+E15 -> 67171 | F20: =F19+F18+F15 -> 67216 | G20: =G19+G18+G15 -> 68507 | J20: =J19+J18+J15 -> 70637.896 | K20: =K19+K18+K15 -> 71751.566 | L20: =L19+L18+L15 -> 73148.148 | M20: =M19+M18+M15 -> 74467.724 | N20: =N19+N18+N15 -> 75817.36
A22: Freight:
A23: U.S. | C23: 3325 | D23: 3041 | E23: 2883 | F23: 2391 | G23: 1536 | J23: =J68*J43/1000 -> 1185.6574 | K23: =K68*K43/1000 -> 1244.9402 | L23: =L68*L43/1000 -> 1307.9342 | M23: =M68*M43/1000 -> 1374.1157 | N23: =N68*N43/1000 -> 1443.6459
A24: International priority | C24: 3030 | D24: 3840 | E24: 3059 | F24: 2205 | G24: 2320
A25: International economy | C25: =1582+245 -> 1827 | D25: =1653+177 -> 1830 | E25: 1719 | F25: 1874 | G25: 1975 | J25: =J72*J43/1000 -> 4565.1453 | K25: =K72*K43/1000 -> 4749.1206 | L25: =L72*L43/1000 -> 4930.5906 | M25: =M72*M43/1000 -> 5104.3939 | N25: =N72*N43/1000 -> 5284.3238 | Q25: Calcualted as total due to the 10k reporting method
A26: Total freight revenue | C26: =SUM(C23:C25) -> 8182 | D26: =SUM(D23:D25) -> 8711 | E26: =SUM(E23:E25) -> 7661 | F26: =SUM(F23:F25) -> 6470 | G26: =SUM(G23:G25) -> 5831 | J26: =SUM(J23:J25) -> 5750.8027 | K26: =SUM(K23:K25) -> 5994.0609 | L26: =SUM(L23:L25) -> 6238.5248 | M26: =SUM(M23:M25) -> 6478.5096 | N26: =SUM(N23:N25) -> 6727.9697
A28: Other | C28: 1416 | D28: 1410 | E28: 1052 | F28: 977 | G28: 966 | J28: 950 | K28: 950 | L28: 950 | M28: 950 | N28: 950
A30: Federal Express | C30: =C28+C26+C20 -> 72574 | D30: =D28+D26+D20 -> 79046 | E30: =E28+E26+E20 -> 75884 | F30: =F28+F26+F20 -> 74663 | G30: =G28+G26+G20 -> 75304 | J30: =J28+J26+J20 -> 77338.698 | K30: =K28+K26+K20 -> 78695.627 | L30: =L28+L26+L20 -> 80336.673 | M30: =M28+M26+M20 -> 81896.234 | N30: =N28+N26+N20 -> 83495.33
J31: =(J30-G30)/G30 -> 0.027019792 | K31: =(K30-J30)/J30 -> 0.017545268 | L31: =(L30-K30)/K30 -> 0.020853079 | M31: =(M30-L30)/L30 -> 0.019412819 | N31: =(N30-M30)/M30 -> 0.019525879
A32: Fedex freight segment | C32: 7833 | D32: 9532 | E32: 10084 | F32: 9429 | G32: 8892 | J32: =(J79+J83)*J43/1000 -> 8962.7005 | K32: =(K79+K83)*K43/1000 -> 9156.043 | L32: =(L79+L83)*L43/1000 -> 9432.6225 | M32: =(M79+M83)*M43/1000 -> 9717.5566 | N32: =(N79+N83)*N43/1000 -> 10011.098
J33: =(J32-G32)/G32 -> 0.0079510195 | K33: =(K32-J32)/J32 -> 0.021571909 | L33: =(L32-K32)/K32 -> 0.030207312 | M33: =(M32-L32)/L32 -> 0.030207312 | N33: =(N32-M32)/M32 -> 0.030207312
A34: Other and eliminations | C34: =3520+32 -> 3552 | D34: =4681+253 -> 4934 | E34: 4187 | F34: 3601 | G34: 3730 | J34: =J88 -> 3484 | K34: =K88 -> 3588.6619 | L34: =L88 -> 3696.4679 | M34: =M88 -> 3807.5125 | N34: =N88 -> 3921.8929
J35: =(J34-G34)/G34 -> -0.065951743 | K35: =(K34-J34)/J34 -> 0.030040728 | L35: =(L34-K34)/K34 -> 0.030040728 | M35: =(M34-L34)/L34 -> 0.030040728 | N35: =(N34-M34)/M34 -> 0.030040728
A36: Total revenue | C36: =SUM(C30:C34) -> 83959 | D36: =SUM(D30:D34) -> 93512 | E36: =SUM(E30:E34) -> 90155 | F36: =SUM(F30:F34) -> 87693 | G36: =SUM(G30:G34) -> 87926 | J36: =J89 -> 89241.195 | K36: =K89 -> 90885.189 | L36: =L89 -> 92899.462 | M36: =M89 -> 94849.339 | N36: =N89 -> 96850.637
E39: Package statistics
A41: Average daily package volume(ADV) | B41: in thousands
A42: Revenue/package | B42: dollars
A43: BusinessDays | C43: 256 | D43: 257 | E43: 255 | F43: 256 | G43: 254 | H43: 254 | J43: 256 | K43: 256 | L43: 256 | M43: 256 | N43: 256 | P43: calendar-neutral hold; no structural change expected.
A45: Federal Express | C45: 2021 | D45: 2022 | E45: 2023 | F45: 2024 | G45: 2025 | H45: Q1 2026 | J45: 2026E | K45: 2027E | L45: 2028E | M45: 2029E | N45: 2030E
A46: U.S. Priority(ADV) | C46: 1932 | D46: 1927 | E46: 1724 | F46: 1649 | G46: 1609 | H46: 1654 | J46: =G46*(1+J97) -> 1592.91 | K46: =J46*(1+K97) -> 1576.9809 | L46: =K46*(1+L97) -> 1576.9809 | M46: =L46*(1+M97) -> 1592.7507 | N46: =M46*(1+N97) -> 1608.6782
A47: Revenue/package | C47: 20.1117 | D47: 22.4993 | E47: 24.78 | F47: 24.98 | G47: 25.74 | H47: 26.13 | J47: =G47*(1+J98) -> 26.1261 | K47: =J47*(1+K98) -> 26.517991 | L47: =K47*(1+L98) -> 26.915761 | M47: =L47*(1+M98) -> 27.319498 | N47: =M47*(1+N98) -> 27.72929
A48: Revenue | C48: =C46*C47 -> 38855.804 | D48: =D46*D47 -> 43356.151 | E48: =E46*E47 -> 42720.72 | F48: =F46*F47 -> 41192.02 | G48: =G46*G47 -> 41415.66 | H48: =H46*H47 -> 43219.02 | J48: =J46*J47 -> 41616.526 | K48: =K46*K47 -> 41818.366 | L48: =L46*L47 -> 42445.642 | M48: =M46*M47 -> 43513.149 | N48: =N46*N47 -> 44607.505
A50: U.S. Deferred(ADV) | C50: 1351 | D50: 1262 | E50: 1064 | F50: 1015 | G50: 1052 | H50: 1061 | J50: =G50*(1+J101) -> 1067.78 | K50: =J50*(1+K101) -> 1089.1356 | L50: =K50*(1+L101) -> 1110.9183 | M50: =L50*(1+M101) -> 1133.1367 | N50: =M50*(1+N101) -> 1155.7994
A51: Revenue/package | C51: 14.46 | D51: 16.56 | E51: 18.91 | F51: 18.97 | G51: 18.75 | H51: 18.76 | J51: =G51*(1+J102) -> 18.9375 | K51: =J51*(1+K102) -> 19.126875 | L51: =K51*(1+L102) -> 19.318144 | M51: =L51*(1+M102) -> 19.511325 | N51: =M51*(1+N102) -> 19.706438
A52: Revenue | C52: =C51*C50 -> 19535.46 | D52: =D51*D50 -> 20898.72 | E52: =E51*E50 -> 20120.24 | F52: =F51*F50 -> 19254.55 | G52: =G51*G50 -> 19725 | H52: =H51*H50 -> 19904.36 | J52: =J51*J50 -> 20221.084 | K52: =K51*K50 -> 20831.76 | L52: =L51*L50 -> 21460.88 | M52: =M51*M50 -> 22108.998 | N52: =N51*N50 -> 22776.69
A54: U.S. Ground (total)(ADV) | C54: 12210 | D54: 12043 | E54: =6756+4194 -> 10950 | F54: =6678+4276 -> 10954 | G54: =7041+4252 -> 11293 | H54: =6915+4290 -> 11205 | J54: =G54*(1+J105) -> 11405.93 | K54: =J54*(1+K105) -> 11519.989 | L54: =K54*(1+L105) -> 11635.189 | M54: =L54*(1+M105) -> 11751.541 | N54: =M54*(1+N105) -> 11869.056
A55: Revenue/package | C55: 9.7 | D55: 10.64 | E55: 11.59 | F55: 11.76 | G55: 11.81 | H55: 12.07 | J55: =G55*(1+J110) -> 11.9281 | K55: =J55*(1+K110) -> 12.047381 | L55: =K55*(1+L110) -> 12.167855 | M55: =L55*(1+M110) -> 12.167855 | N55: =M55*(1+N110) -> 12.167855
A56: Revenue | C56: =C54*C55 -> 118437 | D56: =D54*D55 -> 128137.52 | E56: =E54*E55 -> 126910.5 | F56: =F54*F55 -> 128819.04 | G56: =G54*G55 -> 133370.33 | H56: =H54*H55 -> 135244.35 | J56: =J54*J55 -> 136051.07 | K56: =K54*K55 -> 138785.7 | L56: =L54*L55 -> 141575.29 | M56: =M54*M55 -> 142991.05 | N56: =N54*N55 -> 144420.96
A58: International Export(ADV) | C58: 1036 | D58: 1063 | E58: 1019 | F58: 1061 | G58: 1137 | H58: 1080 | J58: =G58*(1+J117) -> 1125.63 | K58: =J58*(1+K117) -> 1114.3737 | L58: =K58*(1+L117) -> 1114.3737 | M58: =L58*(1+M117) -> 1125.5174 | N58: =M58*(1+N117) -> 1136.7726
A59: Revenue/package | C59: 49.03 | D59: 55.21 | E59: 54.85 | F59: 51.94 | G59: 50.55 | H59: 52.27 | J59: =G59*(1+J121) -> 51.561 | K59: =J59*(1+K121) -> 52.59222 | L59: =K59*(1+L121) -> 53.644064 | M59: =L59*(1+M121) -> 54.716946 | N59: =M59*(1+N121) -> 55.811285
A60: Revenue | C60: =C59*C58 -> 50795.08 | D60: =D59*D58 -> 58688.23 | E60: =E59*E58 -> 55892.15 | F60: =F59*F58 -> 55108.34 | G60: =G59*G58 -> 57475.35 | H60: =H59*H58 -> 56451.6 | J60: =J59*J58 -> 58038.608 | K60: =K59*K58 -> 58607.387 | L60: =L59*L58 -> 59779.535 | M60: =M59*M58 -> 61584.876 | N60: =N59*N58 -> 63444.74
A62: International Domestic(ADV) | C62: 2362 | D62: 1954 | E62: 1967 | F62: 1936 | G62: 1910 | H62: 1806 | J62: =G62*(1+J128) -> 1873.2387 | K62: =J62*(1+K128) -> 1837.1849 | L62: =K62*(1+L128) -> 1801.8251 | M62: =L62*(1+M128) -> 1767.1458 | N62: =M62*(1+N128) -> 1733.1339
A63: Revenue/package | C63: 7.7 | D63: 8.71 | E63: 9.07 | F63: 9.4 | G63: 9.26 | H63: 9.81 | J63: =G63*(1+J129) -> 9.5429326 | K63: =J63*(1+K129) -> 9.8345101 | L63: =K63*(1+L129) -> 10.134996 | M63: =L63*(1+M129) -> 10.444664 | N63: =M63*(1+N129) -> 10.763793
A64: Revenue | C64: =C62*C63 -> 18187.4 | D64: =D62*D63 -> 17019.34 | E64: =E62*E63 -> 17840.69 | F64: =F62*F63 -> 18198.4 | G64: =G62*G63 -> 17686.6 | H64: =H62*H63 -> 17716.86 | J64: =J62*J63 -> 17876.191 | K64: =K62*K63 -> 18067.814 | L64: =L62*L63 -> 18261.491 | M64: =M62*M63 -> 18457.244 | N64: =N62*N63 -> 18655.095
A65: Freight statistics:
A66: U.S.(ADV-pounds) | C66: 9231 | D66: 7935 | E66: 6711 | F66: 5636 | G66: 3137 | H66: 2165 | J66: =G66*(1+J132) -> 2195.9 | K66: =J66*(1+K132) -> 2195.9 | L66: =K66*(1+L132) -> 2239.818 | M66: =L66*(1+M132) -> 2284.6144 | N66: =M66*(1+N132) -> 2330.3066
A67: Revenue/package | C67: 1.41 | D67: 1.5 | E67: 1.68 | F67: 1.66 | G67: 1.93 | H67: 2.18 | J67: =G67*(1+J133) -> 2.1091462 | K67: =J67*(1+K133) -> 2.2146035 | L67: =K67*(1+L133) -> 2.2810416 | M67: =L67*(1+M133) -> 2.3494729 | N67: =M67*(1+N133) -> 2.419957
A68: Revenue | C68: =C66*C67 -> 13015.71 | D68: =D66*D67 -> 11902.5 | E68: =E66*E67 -> 11274.48 | F68: =F66*F67 -> 9355.76 | G68: =G66*G67 -> 6054.41 | H68: =H66*H67 -> 4719.7 | J68: =J66*J67 -> 4631.4741 | K68: =K66*K67 -> 4863.0478 | L68: =L66*L67 -> 5109.1181 | M68: =M66*M67 -> 5367.6394 | N68: =N66*N67 -> 5639.242
A70: International Economy+priority(ADV-pounds) | C70: 18400 | D70: 18649 | E70: 17534 | F70: =11364+4444 -> 15808 | G70: =11365+4651 -> 16016 | H70: 15869 | J70: =G70*(1+J136) -> 16176.16 | K70: =J70*(1+K136) -> 16337.922 | L70: =K70*(1+L136) -> 16501.301 | M70: =L70*(1+M136) -> 16666.314 | N70: =M70*(1+N136) -> 16832.977
A71: Revenue/package | C71: 0.985 | D71: 1.1553 | E71: 1.07 | F71: 1.01 | G71: 1.06 | H71: 1.11 | J71: =G71*(1+J137) -> 1.1024 | K71: =J71*(1+K137) -> 1.135472 | L71: =K71*(1+L137) -> 1.1671879 | M71: =L71*(1+M137) -> 1.1963676 | N71: =M71*(1+N137) -> 1.2262768
A72: Revenue | C72: =C71*C70 -> 18124 | D72: =D71*D70 -> 21545.19 | E72: =E71*E70 -> 18761.38 | F72: =F71*F70 -> 15966.08 | G72: =G71*G70 -> 16976.96 | H72: =H71*H70 -> 17614.59 | J72: =J71*J70 -> 17832.599 | K72: =K71*K70 -> 18551.253 | L72: =L71*L70 -> 19260.119 | M72: =M71*M70 -> 19939.039 | N72: =N71*N70 -> 20641.89
A74: other | C74: =C28 -> 1416 | D74: =D28 -> 1410 | E74: =E28 -> 1052 | F74: =F28 -> 977 | G74: =G28 -> 966 | J74: 950 | K74: 950 | L74: 950 | M74: 950 | N74: 950 | P74: ~$950mm flat — non-transport services and eliminations stay stable.
A76: FedEx Freight segment (LTL revenue)
A77: Priority(ADV-pounds) | C77: 76.2 | D77: 79.1 | E77: 70.1 | F77: 64.9 | G77: 61.8 | H77: 62 | J77: =G77*(1+J143) -> 60.564 | K77: =J77*(1+K143) -> 61.16964 | L77: =K77*(1+L143) -> 62.393033 | M77: =L77*(1+M143) -> 63.640893 | N77: =M77*(1+N143) -> 64.913711
A78: revenue/ship | C78: 313.67 | D78: 368.08 | E78: 417.5 | F78: 411.25 | G78: 405.53 | H78: 408.05 | J78: =G78*(1+J144) -> 409.5853 | K78: =J78*(1+K144) -> 413.68115 | L78: =K78*(1+L144) -> 417.81796 | M78: =L78*(1+M144) -> 421.99614 | N78: =M78*(1+N144) -> 426.21611
A79: Revenue | C79: =C77*C78 -> 23901.654 | D79: =D77*D78 -> 29115.128 | E79: =E77*E78 -> 29266.75 | F79: =F77*F78 -> 26690.125 | G79: =G77*G78 -> 25061.754 | H79: =H77*H82 -> 22291.48 | J79: =J77*J78 -> 24806.124 | K79: =K77*K78 -> 25304.727 | L79: =L77*L78 -> 26068.93 | M79: =M77*M78 -> 26856.212 | N79: =N77*N78 -> 27667.269
A81: economy(ADV-pounds) | C81: 32.2 | D81: 32.6 | E81: 29.6 | F81: 29.1 | G81: 28.3 | H81: 28 | J81: =G81*(1+J147) -> 28.017 | K81: =J81*(1+K147) -> 28.29717 | L81: =K81*(1+L147) -> 28.721628 | M81: =L81*(1+M147) -> 29.152452 | N81: =M81*(1+N147) -> 29.589739
A82: revenue/ship | C82: 269.98 | D82: 320.76 | E82: 363.85 | F82: 361.38 | G82: 358.84 | H82: 359.54 | J82: =G82*(1+J148) -> 364.2226 | K82: =J82*(1+K148) -> 369.68594 | L82: =K82*(1+L148) -> 375.23123 | M82: =L82*(1+M148) -> 380.8597 | N82: =M82*(1+N148) -> 386.57259
A83: Revenue | C83: =C81*C82 -> 8693.356 | D83: =D81*D82 -> 10456.776 | E83: =E81*E82 -> 10769.96 | F83: =F81*F82 -> 10516.158 | G83: =G81*G82 -> 10155.172 | H83: =H82*H81 -> 10067.12 | J83: =J81*J82 -> 10204.425 | K83: =K81*K82 -> 10461.066 | L83: =L81*L82 -> 10777.252 | M83: =M81*M82 -> 11102.994 | N83: =N81*N82 -> 11438.582
A86: Consolidated Revenue/day | C86: =C83+C79+C72+C68+C64+C60+C56+C52+C48 -> 309545.46 | D86: =D83+D79+D72+D68+D64+D60+D56+D52+D48 -> 341119.55 | E86: =E83+E79+E72+E68+E64+E60+E56+E52+E48 -> 333556.87 | F86: =F83+F79+F72+F68+F64+F60+F56+F52+F48 -> 325100.47 | G86: =G83+G79+G72+G68+G64+G60+G56+G52+G48 -> 327921.24 | H86: =H83+H79+H72+H68+H64+H60+H56+H52+H48 -> 327229.08 | J86: =J83+J79+J72+J68+J64+J60+J56+J52+J48 -> 331278.1 | K86: =K83+K79+K72+K68+K64+K60+K56+K52+K48 -> 337291.12 | L86: =L83+L79+L72+L68+L64+L60+L56+L52+L48 -> 344738.26 | M86: =M83+M79+M72+M68+M64+M60+M56+M52+M48 -> 351921.2 | N86: =N83+N79+N72+N68+N64+N60+N56+N52+N48 -> 359291.97
A87: Revenue/annum in millions | C87: =C86*C43/1000 -> 79243.639 | D87: =D86*D43/1000 -> 87667.726 | E87: =E86*E43/1000 -> 85057.002 | F87: =F86*F43/1000 -> 83225.721 | G87: =G86*G43/1000 -> 83291.994 | H87: =H86*H43/1000 -> 83116.186 | J87: =J86*J43/1000 -> 84807.195 | K87: =K86*K43/1000 -> 86346.527 | L87: =L86*L43/1000 -> 88252.994 | M87: =M86*M43/1000 -> 90091.827 | N87: =N86*N43/1000 -> 91978.744
A88: Other & Eliminations | C88: 3520 | D88: 4681 | E88: =E34 -> 4187 | F88: =F34 -> 3601 | G88: =G34 -> 3730 | H88: 871 | J88: =871*4 -> 3484 | K88: =J88*(1+K154) -> 3588.6619 | L88: =K88*(1+L154) -> 3696.4679 | M88: =L88*(1+M154) -> 3807.5125 | N88: =M88*(1+N154) -> 3921.8929
A89: Total revenue | C89: =C87+C88+C74 -> 84179.639 | D89: =D87+D88+D74 -> 93758.726 | E89: =E87+E88+E74 -> 90296.002 | F89: =F87+F88+F74 -> 87803.721 | G89: =G87+G88+G74 -> 87987.994 | H89: =H87+H88+H74 -> 83987.186 | J89: =J87+J88+J74 -> 89241.195 | K89: =K87+K88+K74 -> 90885.189 | L89: =L87+L88+L74 -> 92899.462 | M89: =M87+M88+M74 -> 94849.339 | N89: =N87+N88+N74 -> 96850.637 | P89: Mechanical outputs of the above drivers and business-day assumption; no incremental top-down overlay
A94: YOY Growth
P95: Assumptions
A96: Federal Express | C96: 2021 | D96: 2022 | E96: 2023 | F96: 2024 | G96: 2025 | H96: Q1 2026 | J96: 2026E | K96: 2027E | L96: 2028E | M96: 2029E | N96: 2030E
A97: U.S. Priority | D97: =(D46-C46)/C46 -> -0.0025879917 | E97: =(E46-D46)/D46 -> -0.1053451 | F97: =(F46-E46)/E46 -> -0.04350348 | G97: =(G46-F46)/F46 -> -0.024257126 | H97: =(H46-G46)/G46 -> 0.027967682 | J97: -0.01 | K97: -0.01 | L97: 0 | M97: 0.01 | N97: 0.01 | P97: flat to +1–2%/yr — premium next-day demand stabilizes as on-time performance improves and commercial activity normalizes.
A98: Revenue/package | D98: =(D47-C47)/C47 -> 0.11871697 | E98: =(E47-D47)/D47 -> 0.1013676 | F98: =(F47-E47)/E47 -> 0.008071025 | G98: =(G47-F47)/F47 -> 0.030424339 | H98: =(H47-G47)/G47 -> 0.015151515 | J98: 0.015 | K98: 0.015 | L98: 0.015 | M98: 0.015 | N98: 0.015 | P98: ~+1.5%/yr — annual price increases and fuel surcharge pass-through offset mix pressure.
A99: Total revenue | D99: =(D48-C48)/C48 -> 0.11582174 | E99: =(E48-D48)/D48 -> -0.014656077 | F99: =(F48-E48)/E48 -> -0.035783573 | G99: =(G48-F48)/F48 -> 0.0054292069 | H99: =(H48-G48)/G48 -> 0.04354295
A101: U.S. Deferred | D101: =(D50-C50)/C50 -> -0.065877128 | E101: =(E50-D50)/D50 -> -0.15689382 | F101: =(F50-E50)/E50 -> -0.046052632 | G101: =(G50-F50)/F50 -> 0.036453202 | H101: =(H50-G50)/G50 -> 0.0085551331 | J101: 0.015 | K101: 0.02 | L101: 0.02 | M101: 0.02 | N101: 0.02 | P101: +1–2%/yr — steady e-commerce activity adds parcels without needing more air capacity.
A102: Revenue/package | D102: =(D51-C51)/C51 -> 0.14522822 | E102: =(E51-D51)/D51 -> 0.14190821 | F102: =(F51-E51)/E51 -> 0.0031729244 | G102: =(G51-F51)/F51 -> -0.011597259 | H102: =(H51-G51)/G51 -> 0.00053333333 | J102: 0.01 | K102: 0.01 | L102: 0.01 | M102: 0.01 | N102: 0.01 | P102: ~+1%/yr — competitive market limits pricing; GRIs mostly cover costs.
A103: Total revenue | D103: =(D52-C52)/C52 -> 0.06978387 | E103: =(E52-D52)/D52 -> -0.037250128 | F103: =(F52-E52)/E52 -> -0.043025829 | G103: =(G52-F52)/F52 -> 0.024433186 | H103: =(H52-G52)/G52 -> 0.0090930292
A105: U.S. Ground (total) | D105: =(D54-C54)/C54 -> -0.013677314 | E105: =(E54-D54)/D54 -> -0.090758117 | F105: =(F54-E54)/E54 -> 0.0003652968 | G105: =(G54-F54)/F54 -> 0.030947599 | H105: =(H54-G54)/G54 -> -0.0077924378 | J105: =+CHOOSE(Cover!$I$11,Revenue!J106,Revenue!J107,Revenue!J108) -> 0.01 | K105: =+CHOOSE(Cover!$I$11,Revenue!K106,Revenue!K107,Revenue!K108) -> 0.01 | L105: =+CHOOSE(Cover!$I$11,Revenue!L106,Revenue!L107,Revenue!L108) -> 0.01 | M105: =+CHOOSE(Cover!$I$11,Revenue!M106,Revenue!M107,Revenue!M108) -> 0.01 | N105: =+CHOOSE(Cover!$I$11,Revenue!N106,Revenue!N107,Revenue!N108) -> 0.01 | P105: base +3%/yr (bull 3–4%, bear 1–2%) — SMB and marketplace volumes add stops per route as the economy grows.
A106: Bull | J106: 0.02 | K106: 0.02 | L106: 0.02 | M106: 0.01 | N106: 0.01
A107: Base | J107: 0.01 | K107: 0.01 | L107: 0.01 | M107: 0.01 | N107: 0.01
A108: Bear | J108: -0.01 | K108: -0.01 | L108: -0.01 | M108: 0 | N108: 0
A110: Revenue/package | D110: =(D55-C55)/C55 -> 0.096907216 | E110: =(E55-D55)/D55 -> 0.089285714 | F110: =(F55-E55)/E55 -> 0.014667817 | G110: =(G55-F55)/F55 -> 0.0042517007 | H110: =(H55-G55)/G55 -> 0.022015241 | J110: =+CHOOSE(Cover!$I$12,Revenue!J111,Revenue!J112,Revenue!J113) -> 0.01 | K110: =+CHOOSE(Cover!$I$12,Revenue!K111,Revenue!K112,Revenue!K113) -> 0.01 | L110: =+CHOOSE(Cover!$I$12,Revenue!L111,Revenue!L112,Revenue!L113) -> 0.01 | M110: =+CHOOSE(Cover!$I$12,Revenue!M111,Revenue!M112,Revenue!M113) -> 0 | N110: =+CHOOSE(Cover!$I$12,Revenue!N111,Revenue!N112,Revenue!N113) -> 0 | P110: base +2%/yr (bands shown) — list price increases partially offset by contract resets and customer mix.
A111: Bull | J111: 0.025 | K111: 0.02 | L111: 0.018 | M111: 0.015 | N111: 0.015
A112: Base | J112: 0.01 | K112: 0.01 | L112: 0.01 | M112: 0 | N112: 0
A113: Bear | J113: 0.005 | K113: 0.01 | L113: 0.01 | M113: 0.008 | N113: 0.008
A115: Total revenue | D115: =(D56-C56)/C56 -> 0.081904472 | E115: =(E56-D56)/D56 -> -0.0095758057 | F115: =(F56-E56)/E56 -> 0.015038472 | G115: =(G56-F56)/F56 -> 0.03533088 | H115: =(H56-G56)/G56 -> 0.014051251
A117: International Export | D117: =(D58-C58)/C58 -> 0.026061776 | E117: =(E58-D58)/D58 -> -0.041392286 | F117: =(F58-E58)/E58 -> 0.041216879 | G117: =(G58-F58)/F58 -> 0.071630537 | H117: =(H58-G58)/G58 -> -0.050131926 | J117: =+CHOOSE(Cover!$I$13,Revenue!J118,Revenue!J119,Revenue!J120) -> -0.01 | K117: =+CHOOSE(Cover!$I$13,Revenue!K118,Revenue!K119,Revenue!K120) -> -0.01 | L117: =+CHOOSE(Cover!$I$13,Revenue!L118,Revenue!L119,Revenue!L120) -> 0 | M117: =+CHOOSE(Cover!$I$13,Revenue!M118,Revenue!M119,Revenue!M120) -> 0.01 | N117: =+CHOOSE(Cover!$I$13,Revenue!N118,Revenue!N119,Revenue!N120) -> 0.01 | P117: −1% in 2026, then +1–2%/yr — airfreight lanes recover slowly with global trade; China/EU cycles drive pace.
A118: Bull | J118: 0 | K118: 0.015 | L118: 0.025 | M118: 0.025 | N118: 0.025
A119: Base | J119: -0.01 | K119: -0.01 | L119: 0 | M119: 0.01 | N119: 0.01
A120: Bear | J120: -0.015 | K120: -0.015 | L120: -0.01 | M120: -0.01 | N120: 0
A121: Revenue/package | D121: =(D59-C59)/C59 -> 0.12604528 | E121: =(E59-D59)/D59 -> -0.0065205579 | F121: =(F59-E59)/E59 -> -0.053053783 | G121: =(G59-F59)/F59 -> -0.026761648 | H121: =(H59-G59)/G59 -> 0.034025717 | J121: =+CHOOSE(Cover!$I$14,Revenue!J122,Revenue!J123,Revenue!J124) -> 0.02 | K121: =+CHOOSE(Cover!$I$14,Revenue!K122,Revenue!K123,Revenue!K124) -> 0.02 | L121: =+CHOOSE(Cover!$I$14,Revenue!L122,Revenue!L123,Revenue!L124) -> 0.02 | M121: =+CHOOSE(Cover!$I$14,Revenue!M122,Revenue!M123,Revenue!M124) -> 0.02 | N121: =+CHOOSE(Cover!$I$14,Revenue!N122,Revenue!N123,Revenue!N124) -> 0.02 | P121: ~+2%/yr — disciplined pricing and fuel adders offset softer weight/mix.
A122: Bull | J122: 0.025 | K122: 0.025 | L122: 0.025 | M122: 0.025 | N122: 0.025
A123: Base | J123: 0.02 | K123: 0.02 | L123: 0.02 | M123: 0.02 | N123: 0.02
A124: Bear | J124: 0.015 | K124: 0.015 | L124: 0.015 | M124: 0.015 | N124: 0.015
A126: Total revenue | D126: =(D60-C60)/C60 -> 0.15539202 | E126: =(E60-D60)/D60 -> -0.047642943 | F126: =(F60-E60)/E60 -> -0.014023615 | G126: =(G60-F60)/F60 -> 0.042951938 | H126: =(H60-G60)/G60 -> -0.017811984
A128: International Domestic | D128: =(D62-C62)/C62 -> -0.17273497 | E128: =(E62-D62)/D62 -> 0.0066530194 | F128: =(F62-E62)/E62 -> -0.015760041 | G128: =(G62-F62)/F62 -> -0.013429752 | H128: =(H62-G62)/G62 -> -0.054450262 | J128: =AVERAGE(E128:H128) -> -0.019246759 | K128: -0.019246759 | L128: -0.019246759 | M128: -0.019246759 | N128: -0.019246759 | P128: ~−1.9%/yr — selective exits and portfolio pruning reduce lower-return in-country volume.
A129: Revenue/package | D129: =(D63-C63)/C63 -> 0.13116883 | E129: =(E63-D63)/D63 -> 0.041331803 | F129: =(F63-E63)/E63 -> 0.036383682 | G129: =(G63-F63)/F63 -> -0.014893617 | H129: =(H63-G63)/G63 -> 0.059395248 | J129: =AVERAGE(E129:H129) -> 0.030554279 | K129: 0.030554279 | L129: 0.030554279 | M129: 0.030554279 | N129: 0.030554279 | P129: ~+3.1%/yr — local inflation and annual price actions lift unit revenue.
A130: Total revenue | D130: =(D64-C64)/C64 -> -0.064223583 | E130: =(E64-D64)/D64 -> 0.048259803 | F130: =(F64-E64)/E64 -> 0.020050233 | G130: =(G64-F64)/F64 -> -0.028123352 | H130: =(H64-G64)/G64 -> 0.0017108998
A132: U.S. Frieght | D132: =(D66-C66)/C66 -> -0.14039649 | E132: =(E66-D66)/D66 -> -0.15425331 | F132: =(F66-E66)/E66 -> -0.16018477 | G132: =(G66-F66)/F66 -> -0.44339957 | H132: =(H66-G66)/G66 -> -0.30985018 | J132: -0.3 | K132: 0 | L132: 0.02 | M132: 0.02 | N132: 0.02 | P132: trough in 2025, then modest rebound — capacity and product mix reset; industrial activity steadies.
...

Sheet Income statement
A1: CONSOLIDATED STATEMENTS OF INCOME
A2: (IN MILLIONS, EXCEPT PER SHARE AMOUNTS)
B4: 2021 | C4: 2022 | D4: 2023 | E4: 2024 | F4: 2025 | G4: Q1 2026 | H4: 2026E | I4: 2027E | J4: 2028E | K4: 2029E | L4: 2030E
A5: REVENUE | B5: 83959 | C5: 93512 | D5: 90155 | E5: 87693 | F5: 87926 | G5: 22244 | H5: =Revenue!J36 -> 89241.195 | I5: =Revenue!K36 -> 90885.189 | J5: =Revenue!L36 -> 92899.462 | K5: =Revenue!M36 -> 94849.339 | L5: =Revenue!N36 -> 96850.637
A6: OPERATING EXPENSES
A7: Salaries and employee benefits | B7: 30173 | C7: 32058 | D7: ='Operating expenses'!B79 -> 31019 | E7: ='Operating expenses'!C79 -> 30961 | F7: ='Operating expenses'!D79 -> 31232 | G7: ='Operating expenses'!E79 -> 30770.008 | H7: ='Operating expenses'!E79 -> 30770.008 | I7: ='Operating expenses'!F79 -> 30565.171 | J7: ='Operating expenses'!G79 -> 31259.895 | K7: ='Operating expenses'!H79 -> 31934.966 | L7: ='Operating expenses'!I79 -> 32628.071
A8: Purchased transportation | B8: 21674 | C8: 24118 | D8: ='Operating expenses'!B80 -> 21790 | E8: ='Operating expenses'!C80 -> 20921 | F8: ='Operating expenses'!D80 -> 21768 | G8: 5488 | H8: ='Operating expenses'!E80 -> 21827.318 | I8: ='Operating expenses'!F80 -> 22224.878 | J8: ='Operating expenses'!G80 -> 22704.681 | K8: ='Operating expenses'!H80 -> 23164.898 | L8: ='Operating expenses'!I80 -> 23637.043
A9: Rentals and landing fees | B9: 4155 | C9: 4712 | D9: ='Operating expenses'!B81 -> 4738 | E9: ='Operating expenses'!C81 -> 4571 | F9: ='Operating expenses'!D81 -> 4647 | G9: 1192 | H9: ='Operating expenses'!E81 -> 4802.0229 | I9: ='Operating expenses'!F81 -> 5071.2757 | J9: ='Operating expenses'!G81 -> 5359.9383 | K9: ='Operating expenses'!H81 -> 5666.7948 | L9: ='Operating expenses'!I81 -> 5993.153
A10: Depreciation and amortization | B10: 3793 | C10: 3970 | D10: ='Operating expenses'!B82 -> 4176 | E10: ='Operating expenses'!C82 -> 4287 | F10: ='Operating expenses'!D82 -> 4264 | G10: 1092 | H10: ='Operating expenses'!E82 -> 4361.647 | I10: ='Operating expenses'!F82 -> 4333.2817 | J10: ='Operating expenses'!G82 -> 4349.0182 | K10: ='Operating expenses'!H82 -> 4430.443 | L10: ='Operating expenses'!I82 -> 4523.7068
A11: Fuel | B11: 2882 | C11: 5115 | D11: ='Operating expenses'!B83 -> 5909 | E11: ='Operating expenses'!C83 -> 4710 | F11: ='Operating expenses'!D83 -> 3775 | G11: 873 | H11: ='Operating expenses'!E83 -> 3868.2323 | I11: ='Operating expenses'!F83 -> 3937.9223 | J11: ='Operating expenses'!G83 -> 4024.4012 | K11: ='Operating expenses'!H83 -> 4107.7214 | L11: ='Operating expenses'!I83 -> 4193.2248
A12: Maintanence and repairs | B12: 3328 | C12: 3372 | D12: ='Operating expenses'!B84 -> 3357 | E12: ='Operating expenses'!C84 -> 3291 | F12: ='Operating expenses'!D84 -> 3245 | G12: 843 | H12: ='Operating expenses'!E84 -> 3236.3171 | I12: ='Operating expenses'!F84 -> 3205.0393 | J12: ='Operating expenses'!G84 -> 3276.1332 | K12: ='Operating expenses'!H84 -> 3253.1752 | L12: ='Operating expenses'!I84 -> 3321.7485
A13: Goodwill and other asset impairment charges | B13: 0 | C13: 0 | D13: ='Operating expenses'!B85 -> 117 | E13: ='Operating expenses'!C85 -> 157 | F13: ='Operating expenses'!D85 -> 21 | H13: ='Operating expenses'!E85 -> 21 | I13: ='Operating expenses'!F85 -> 21 | J13: ='Operating expenses'!G85 -> 21 | K13: ='Operating expenses'!H85 -> 21 | L13: ='Operating expenses'!I85 -> 21
A14: Business optimization and realignment costs | B14: 116 | C14: 278 | D14: ='Operating expenses'!B86 -> 309 | E14: ='Operating expenses'!C86 -> 582 | F14: ='Operating expenses'!D86 -> 756 | G14: 67 | H14: ='Operating expenses'!E86 -> 500 | I14: ='Operating expenses'!F86 -> 200 | J14: ='Operating expenses'!G86 -> 100 | K14: ='Operating expenses'!H86 -> 0 | L14: ='Operating expenses'!I86 -> 0
A15: Other | B15: 11981 | C15: 13644 | D15: ='Operating expenses'!B87 -> 13828 | E15: ='Operating expenses'!C87 -> 12654 | F15: ='Operating expenses'!D87 -> 13001 | G15: =3396+45 -> 3441 | H15: ='Operating expenses'!E87 -> 13354.807 | I15: ='Operating expenses'!F87 -> 13535.084 | J15: ='Operating expenses'!G87 -> 13924.897 | K15: ='Operating expenses'!H87 -> 14229.398 | L15: ='Operating expenses'!I87 -> 14544.992
A16: TOTAL OPERATING EXPENSES | B16: =SUM(B7:B15) -> 78102 | C16: =SUM(C7:C15) -> 87267 | D16: =SUM(D7:D15) -> 85243 | E16: =SUM(E7:E15) -> 82134 | F16: =SUM(F7:F15) -> 82709 | G16: =SUM(G7:G15) -> 43766.008 | H16: =SUM(H7:H15) -> 82741.353 | I16: =SUM(I7:I15) -> 83093.652 | ... L16: =SUM(L7:L15) -> 88862.938
A17: OPERATING INCOME | B17: =B5-B16 -> 5857 | C17: =C5-C16 -> 6245 | D17: =D5-D16 -> 4912 | E17: =E5-E16 -> 5559 | F17: =F5-F16 -> 5217 | G17: 1186 | H17: =H5-H16 -> 6499.842 | I17: =I5-I16 -> 7791.5372 | J17: =J5-J16 -> 7879.4977 | K17: =K5-K16 -> 8040.942 | L17: =L5-L16 -> 7987.6989
A18: OTHER INCOME(EXPENSE)
A19: Interest expense | B19: -793 | C19: -689 | D19: -694 | E19: -745 | F19: -789 | G19: -119 | H19: =-'Debt schedule'!G12 -> -859.551 | I19: =-'Debt schedule'!H12 -> -967.764 | J19: =-'Debt schedule'!I12 -> -1093.176 | K19: =-'Debt schedule'!J12 -> -1147.38 | L19: =-'Debt schedule'!K12 -> -1208.64
A20: Interest income | B20: 52 | C20: 53 | D20: 198 | E20: 370 | F20: 363 | H20: =H60*'Balance sheet'!G23 -> 211.13958 | I20: =I60*'Balance sheet'!H23 -> 215.02917 | J20: =J60*'Balance sheet'!I23 -> 219.79483 | K20: =K60*'Balance sheet'!J23 -> 224.40813 | L20: =L60*'Balance sheet'!K23 -> 229.14308
A21: Other retirement plans income | B21: 1983 | C21: -726 | D21: 1054 | E21: 722 | F21: 713 | G21: 60 | H21: =H61*H7 -> 758.18863 | I21: =I61*I7 -> 753.14133 | J21: =J61*J7 -> 770.25969 | K21: =K61*K7 -> 786.89379 | L21: =L61*L7 -> 803.97223
A22: Loss on debt extinguishment | B22: -393 | C22: 0 | D22: 0 | E22: 0 | F22: 0 | H22: =F22 -> 0 | I22: =G22 -> 0 | J22: =H22 -> 0 | K22: =I22 -> 0 | L22: =J22 -> 0
A23: Other,net | B23: -32 | C23: 13 | D23: -107 | E23: -70 | F23: -63 | G23: 7 | H23: =H63 -> -60 | I23: =I63 -> -60 | J23: =J63 -> -60 | K23: =K63 -> -60 | L23: =L63 -> -60
A24: TOTAL OTHER INCOME(EXPENSE) | B24: =SUM(B19:B23) -> 817 | C24: =SUM(C19:C23) -> -1349 | D24: =SUM(D19:D23) -> 451 | E24: =SUM(E19:E23) -> 277 | F24: =SUM(F19:F23) -> 224 | G24: =SUM(G19:G23) -> -52 | H24: =SUM(H19:H23) -> 49.777203 | I24: =SUM(I19:I23) -> -59.593501 | ... L24: =SUM(L19:L23) -> -235.52469
A25: INCOME BEFORE INCOME TAXES | B25: =B17+B24 -> 6674 | C25: =C17+C24 -> 4896 | D25: =D17+D24 -> 5363 | E25: =E17+E24 -> 5836 | F25: =F17+F24 -> 5441 | G25: =G17+G24 -> 1134 | H25: =H17+H24 -> 6549.6192 | I25: =I17+I24 -> 7731.9437 | ... L25: =L17+L24 -> 7752.1742
A26: PROVISION FOR INCOME TAXES | B26: 1443 | C26: 1070 | D26: 1391 | E26: 1505 | F26: 1349 | G26: 310 | H26: =H25*H66 -> 1637.4048 | I26: =I25*I66 -> 1932.9859 | J26: =J25*J66 -> 1929.0941 | K26: =K25*K66 -> 1961.216 | L26: =L25*L66 -> 1938.0436
A27: NET INCOME | B27: =B25-B26 -> 5231 | C27: =C25-C26 -> 3826 | D27: =D25-D26 -> 3972 | E27: =E25-E26 -> 4331 | F27: =F25-F26 -> 4092 | G27: =G25-G26 -> 824 | H27: =H25-H26 -> 4912.2144 | I27: =I25-I26 -> 5798.9578 | ... L27: =L25-L26 -> 5814.1307
A28: BASIC EARNINGS PER COMMON SHARE | B28: 19.79 | C28: 14.54 | D28: 15.6 | E28: 17.41 | F28: 16.96 | G28: 3.48 | H28: ='Debt schedule'!C32 -> 21.630182 | I28: ='Debt schedule'!D32 -> 26.68273 | J28: ='Debt schedule'!E32 -> 27.820797 | K28: ='Debt schedule'!F32 -> 29.542318 | L28: ='Debt schedule'!G32 -> 30.485165
A29: DILUTED EARNINGS PER COMMON SHARE | B29: 19.45 | C29: 14.33 | D29: 15.48 | E29: 17.21 | F29: 16.81 | G29: 3.46
A30: NET INCOME | B30: =B25-B26 -> 5231 | C30: =C25-C26 -> 3826 | D30: =D25-D26 -> 3972 | E30: =E25-E26 -> 4331 | F30: =F25-F26 -> 4092 | G30: =G25-G26 -> 824 | H30: =H25-H26 -> 4912.2144 | I30: =I25-I26 -> 5798.9578 | ... L30: =L25-L26 -> 5814.1307
A31: OTHER COMPREHENSIVE INCOME(LOSS)
A32: Foreign currency translation adhustments | B32: 422 | C32: -363 | D32: -214 | E32: -60 | F32: 2 | H32: 0 | I32: 0 | J32: 0 | K32: 0 | L32: 0
A33: prior service credit | E33: 36 | H33: 0 | I33: 0 | J33: 0 | K33: 0 | L33: 0
A34: Amortization of prior service credit and other | B34: -7 | C34: -8 | D34: -10 | E34: -8 | F34: -5 | H34: -5 | I34: -5 | J34: -5 | K34: -5 | L34: -5
A35: TOTAL OTHER COMP.INCOME(LOSS) | B35: =SUM(B32:B34) -> 415 | C35: =SUM(C32:C34) -> -371 | D35: =SUM(D32:D34) -> -224 | E35: =SUM(E32:E34) -> -32 | F35: =SUM(F32:F34) -> -3 | H35: =SUM(H32:H34) -> -5 | I35: =SUM(I32:I34) -> -5 | J35: =SUM(J32:J34) -> -5 | K35: =SUM(K32:K34) -> -5 | L35: =SUM(L32:L34) -> -5
B36: =B30+B35 -> 5646 | C36: =C30+C35 -> 3455 | D36: =D30+D35 -> 3748 | E36: =E30+E35 -> 4299 | F36: =F30+F35 -> 4089 | H36: =H30+H35 -> 4907.2144 | I36: =I30+I35 -> 5793.9578 | J36: =J30+J35 -> 5782.2822 | K36: =K30+K35 -> 5878.648 | L36: =L30+L35 -> 5809.1307
A39: Assumptions
B40: 2021 | C40: 2022 | D40: 2023 | E40: 2024 | F40: 2025 | G40: Q1 2026 | H40: 2026E | I40: 2027E | J40: 2028E | K40: 2029E | L40: 2020E
A41: REVENUE | C41: =(C5-B5)/B5 -> 0.11378173 | D41: =(D5-C5)/C5 -> -0.035899136 | E41: =(E5-D5)/D5 -> -0.027308524 | F41: =(F5-E5)/E5 -> 0.0026569966 | H41: =(H5-F5)/F5 -> 0.014957972 | I41: =(I5-H5)/H5 -> 0.01842192 | J41: =(J5-I5)/I5 -> 0.022162833 | K41: =(K5-J5)/J5 -> 0.02098911 | L41: =(L5-K5)/K5 -> 0.021099758 | O41: +3–4%/yr — modest parcel volume growth and small price increases after markets normalize.
A42: OPERATING EXPENSES
A43: Salaries and employee benefits | B43: =B7/B$5 -> 0.35937779 | C43: =C7/C$5 -> 0.34282231 | D43: =D7/D$5 -> 0.344063 | E43: =E7/E$5 -> 0.35306125 | F43: =F7/F$5 -> 0.35520779 | H43: 0.355 | I43: 0.355 | J43: 0.355 | K43: 0.355 | L43: 0.355 | O43: ~35.5% of revenue — wage inflation partly offset by DRIVE efficiencies and the Europe workforce reduction (~$150mm annualized savings from 2026).
A44: Purchased transportation | B44: =B8/B5 -> 0.25814981 | C44: =C8/C5 -> 0.25791342 | D44: =D8/D5 -> 0.24169486 | E44: =E8/E5 -> 0.23857092 | F44: =F8/F5 -> 0.24757182 | O44: ~25.0% of revenue (24.5–25.5% bands) — rates normalize; DRIVE and linehaul optimization temper costs after USPS contract roll-off effects.
A45: Bull | H45: 0.24 | I45: 0.24 | J45: 0.24 | K45: 0.24 | L45: 0.24 | O45: Falls to ~22% if FedEx insources more linehaul/airlift, Ground route density improves (fewer third-party miles per stop), freight & ACMI spot rates stay soft, and contract renewals lock in lower carrier costs.
A46: Base | H46: 0.25 | I46: 0.25 | J46: 0.25 | K46: 0.25 | L46: 0.25 | O46: Holds near the multi-year average if external capacity and rates are stable, mix between in-house vs. third-party is unchanged, and GRIs/fuel pass-throughs broadly offset carrier increases.
A47: Bear | H47: 0.26 | I47: 0.26 | J47: 0.26 | K47: 0.26 | L47: 0.26 | O47: Rises toward ~27% if trucking/air capacity tightens (spot rates up), FedEx needs more surge/charter lift in peaks or disruptions, ISP/linehaul contracts reprice higher, or fuel spikes aren’t fully recovered.
A49: Rentals and landing fees | B49: =B9/B5 -> 0.049488441 | C49: =C9/C5 -> 0.050389255 | D49: =D9/D5 -> 0.052553935 | E49: =E9/E5 -> 0.052125027 | F49: =F9/F5 -> 0.052851261 | H49: =AVERAGE(B49:F49) -> 0.051481584 | I49: =AVERAGE(C49:G49) -> 0.05197987 | J49: =AVERAGE(D49:H49) -> 0.052252952 | K49: =AVERAGE(E49:I49) -> 0.052109435 | L49: =AVERAGE(F49:J49) -> 0.052141417 | O49: ~5.1–5.2% of revenue — largely contractual airport/real estate expense; held near FY25 mix.
A50: Depreciation and amortization (% of Gross PP&E) | B50: =B10/'Balance sheet'!B17 -> 0.054126175 | C50: =C10/'Balance sheet'!C17 -> 0.052739954 | D50: =D10/'Balance sheet'!D17 -> 0.051795991 | E50: =E10/'Balance sheet'!E17 -> 0.050799256 | F50: =F10/'Balance sheet'!F17 -> 0.048663578 | H50: 0.052 | I50: 0.052 | J50: 0.052 | K50: 0.052 | L50: 0.052 | O50: ~5.2% of gross PP&E — steady run-rate; MD-11 retirement timeline extended to 2032 reduces near-term D&A volatility.
A51: Fuel | B51: =B11/B5 -> 0.034326278 | C51: =C11/C5 -> 0.054698862 | D51: =D11/D5 -> 0.065542677 | E51: =E11/E5 -> 0.053710102 | F51: =F11/F5 -> 0.042933831 | H51: =AVERAGE(B51:F51) -> 0.05024235 | I51: 0.05024235 | J51: 0.05024235 | K51: 0.05024235 | L51: 0.05024235 | O51: ~5.0% of revenue — indexed fuel surcharges mitigate price swings; aircraft fleet modernization improves burn (new 767F/777F/ATR/408 deliveries).
A52: Maintanence and repairs | B52: =B12/B$5 -> 0.039638395 | C52: =C12/C$5 -> 0.036059543 | D52: =D12/D$5 -> 0.037235872 | E52: =E12/E$5 -> 0.037528651 | F52: =F12/F$5 -> 0.036906035 | H52: 0.038 | I52: 0.038 | J52: 0.038 | K52: 0.038 | L52: 0.038 | O52: ~3.8% of revenue — preventive maintenance on a modernizing, younger fleet; temporary idles managed within network.
A53: Goodwill and other asset impairment charges | E53: =(E13-D13)/D13 -> 0.34188034 | F53: =(F13-E13)/E13 -> -0.86624204 | H53: 0 | I53: 0 | J53: 0 | K53: 0 | L53: 0 | O53: $0 from ’26 — aircraft impairment in FY25 tied to specific retirements; no planned write-downs thereafter.
A54: Business optimization and realignment costs | C54: =(C14-B14)/B14 -> 1.3965517 | D54: =(D14-C14)/C14 -> 0.11151079 | E54: =(E14-D14)/D14 -> 0.88349515 | F54: =(F14-E14)/E14 -> 0.29896907 | H54: 250 | I54: 0 | J54: 0 | K54: 0 | L54: 0 | O54: ~$250mm in ’26, $0 thereafter — tail of DRIVE program; Europe restructuring costs largely incurred, savings begin 2026.
A55: Other | B55: =B15/B5 -> 0.1427006 | C55: =C15/C5 -> 0.14590641 | D55: =D15/D5 -> 0.15338029 | E55: =E15/E5 -> 0.14429886 | F55: =F15/F5 -> 0.14786298 | H55: =AVERAGE(B55:F55) -> 0.14682983 | I55: 0.14682983 | J55: 0.14682983 | K55: 0.14682983 | L55: 0.14682983 | O55: ~14.7% of revenue — keep near multi-year run-rate for insurance, technology, and supplies embedded in “other.
A56: TOTAL OPERATING EXPENSES
A57: OPERATING INCOME | B57: =B17/B5 -> 0.06976024 | C57: =C17/C5 -> 0.066782873 | D57: =D17/D5 -> 0.054483944 | E57: =E17/E5 -> 0.063391605 | F57: =F17/F5 -> 0.059333985 | G57: =G17/G5 -> 0.053317749 | H57: =H17/H5 -> 0.072834547 | I57: =I17/I5 -> 0.08572945 | ... L57: =L17/L5 -> 0.082474407
A58: OTHER INCOME(EXPENSE)
A59: Interest expense | C59: =(C19-B19)/B19 -> -0.13114754 | D59: =(D19-C19)/C19 -> 0.007256894 | E59: =(E19-D19)/D19 -> 0.073487032 | F59: =(F19-E19)/E19 -> 0.059060403 | H59: 0.02 | I59: 0.02 | J59: 0.03 | K59: 0.03 | L59: 0.03 | O59: Down from ~$680mm to ~$515mm — predominantly fixed-rate debt; stable ratings and scheduled maturities lower interest burden.
A60: Interest income | B60: =B20/'Balance sheet'!B23 -> 0.012776413 | C60: =C20/'Balance sheet'!C23 -> 0.012097695 | D60: =D20/'Balance sheet'!D23 -> 0.048852702 | E60: =E20/'Balance sheet'!E23 -> 0.09811721 | F60: =F20/'Balance sheet'!F23 -> 0.079903148 | G60: =G20/'Balance sheet'!E23 -> 0 | H60: =AVERAGE(B60:F60) -> 0.050349433 | I60: 0.050349433 | J60: 0.050349433 | K60: 0.050349433 | L60: 0.050349433 | O60: Flat at ~$229mm — similar cash/liquidity posture and yield assumptions.
A61: Other retirement plans income | B61: =B21/B7 -> 0.065721009 | C61: =C21/C7 -> -0.022646453 | D61: =D21/D7 -> 0.033979174 | E61: =E21/E7 -> 0.02331966 | F61: =F21/F7 -> 0.02282915 | G61: =G21/G7 -> 0.0019499507 | H61: =AVERAGE(B61:F61) -> 0.024640508 | I61: 0.024640508 | J61: 0.024640508 | K61: 0.024640508 | L61: 0.024640508 | O61: (~+2.5%/yr) — MTM framework + normal EROA/discount rates; smooth growth versus FY23–25 path.
A62: Loss on debt extinguishment | H62: 0 | I62: 0 | J62: 0 | K62: 0 | L62: 0 | O62: No special refi events assumed; trend is non-recurring.
A63: Other,net | B63: =B23 -> -32 | C63: =C23 -> 13 | D63: =D23 -> -107 | E63: =E23 -> -70 | F63: =F23 -> -63 | H63: -60 | I63: -60 | J63: -60 | K63: -60 | L63: -60 | O63: Recurring non-operating items at steady state, consistent with FY23–25.
A64: TOTAL OTHER INCOME(EXPENSE)
A65: INCOME BEFORE INCOME TAXES
A66: PROVISION FOR INCOME TAXES | B66: =B26/B25 -> 0.21621217 | C66: =C26/C25 -> 0.21854575 | D66: =D26/D25 -> 0.25936976 | E66: =E26/E25 -> 0.25788211 | F66: =F26/F25 -> 0.24793237 | H66: 0.25 | I66: 0.25 | J66: 0.25 | K66: 0.25 | L66: 0.25 | O66: Normalized blended rate; aligned with the recent multi-year average.
A67: NET INCOME
A68: BASIC EARNINGS PER COMMON SHARE
A69: DILUTED EARNINGS PER COMMON SHARE
A70: NET INCOME
A71: OTHER COMPREHENSIVE INCOME(LOSS)
A72: Foreign currency translation adhustments
A73: prior service credit
A74: Amortization of prior service credit and other
A75: TOTAL OTHER COMP.INCOME(LOSS)
A83: Fleet modernization detail — scheduled deliveries: 7×767F (by 2026), 3×ATR-72-600F (2026), plus exercised options for 8×777F (2026–2027) and 10×ATR-72-600F (2027–2029); MD-11 fleet retired by 2032
A84: Fuel efficiency programs — Fuel Sense + aircraft modernization saved ~141M gallons in 2024; SAF procurement underway.

Sheet Operating expenses
A2: FedEx Express Segment
A3: Operating Expense | B3: 2023 | C3: 2024 | D3: 2025 | E3: 2026 | F3: 2027 | G3: 2028 | H3: 2029 | I3: 2030
A4: sales | B4: =Revenue!E4 -> 75884 | C4: =Revenue!F4 -> 74663 | D4: =Revenue!G4 -> 75304 | E4: =Revenue!J4 -> 77338.698 | F4: =Revenue!K4 -> 78695.627 | G4: =Revenue!L4 -> 80336.673 | H4: =Revenue!M4 -> 81896.234 | I4: =Revenue!N4 -> 83495.33
A5: Salaries & Employee Benefits | B5: 24523 | C5: 24606 | D5: 25091 | E5: =E4*E6 -> 24748.384 | F5: =F4*F6 -> 24395.644 | G5: =G4*G6 -> 24904.369 | H5: =H4*H6 -> 25387.833 | I5: =I4*I6 -> 25883.552
E6: =+CHOOSE(Cover!$I$15,E7,E8,E9) -> 0.32 | F6: =+CHOOSE(Cover!$I$15,F7,F8,F9) -> 0.31 | G6: =+CHOOSE(Cover!$I$15,G7,G8,G9) -> 0.31 | H6: =+CHOOSE(Cover!$I$15,H7,H8,H9) -> 0.31 | I6: =+CHOOSE(Cover!$I$15,I7,I8,I9) -> 0.31
A7: Bull | E7: 0.31 | F7: 0.31 | G7: 0.31 | H7: 0.31 | I7: 0.31 | N7: *operating expense decrese by Network 2.0 , which has already been shown in Q1 2026.
A8: Base | B8: =B5/B4 -> 0.3231643 | C8: =C5/C4 -> 0.32956083 | D8: =D5/D4 -> 0.33319611 | E8: 0.32 | F8: 0.31 | G8: 0.31 | H8: 0.31 | I8: 0.31 | N8: *expecting continued operational efficiency, saving 1B from 2026(management foreword)
A9: Bear | E9: 0.32 | F9: 0.32 | G9: 0.32 | H9: 0.32 | I9: 0.32
A10: Purchased Transportation | B10: 19677 | C10: 19330 | D10: 19974 | E10: =E4*E11 -> 20108.062 | F10: =F4*F11 -> 20460.863 | G10: =G4*G11 -> 20887.535 | H10: =H4*H11 -> 21293.021 | I10: =I4*I11 -> 21708.786
E11: =+CHOOSE(Cover!$I$16,E12,E13,E14) -> 0.26 | F11: =+CHOOSE(Cover!$I$16,F12,F13,F14) -> 0.26 | G11: =+CHOOSE(Cover!$I$16,G12,G13,G14) -> 0.26 | H11: =+CHOOSE(Cover!$I$16,H12,H13,H14) -> 0.26 | I11: =+CHOOSE(Cover!$I$16,I12,I13,I14) -> 0.26
A12: Bull | E12: 0.25 | F12: 0.24 | G12: 0.24 | H12: 0.24 | I12: 0.24
A13: Base | B13: =B10/B4 -> 0.25930367 | C13: =C10/C4 -> 0.25889664 | D13: =D10/D4 -> 0.26524487 | E13: 0.26 | F13: 0.26 | G13: 0.26 | H13: 0.26 | I13: 0.26 | N13: *expecting continued operational efficiency, saving 1B from 2026
A14: Bear | E14: 0.27 | F14: 0.27 | G14: 0.27 | H14: 0.27 | I14: 0.27
A15: Rentals & Landing Fees | B15: 4035 | C15: 3863 | D15: 3939 | E15: =E4*E16 -> 4045.431 | F15: =E15*(1+F16) -> 4257.0393 | G15: =F15*(1+G16) -> 4479.7164 | H15: =G15*(1+H16) -> 4714.0413 | I15: =H15*(1+I16) -> 4960.6233
B16: =B15/B4 -> 0.053173264 | C16: =C15/C4 -> 0.051739148 | D16: =D15/D4 -> 0.052307978 | E16: =D16 -> 0.052307978 | F16: =E16 -> 0.052307978 | G16: =F16 -> 0.052307978 | H16: =G16 -> 0.052307978 | I16: =H16 -> 0.052307978 | N16: *maintained at 2025 levels as no effect on landing fees
A17: Depreciation & Amortization | B17: 3655 | C17: 3754 | D17: 3722 | E17: =E4*E18 -> 3812.0554 | F17: =F4*F18 -> 3777.3901 | G17: =G4*G18 -> 3775.8236 | H17: =H4*H18 -> 3849.123 | I17: =I4*I18 -> 3924.2805
B18: =B17/B4 -> 0.048165621 | C18: =C17/C4 -> 0.050279255 | D18: =D17/D4 -> 0.049426325 | E18: =AVERAGE(B18:D18) -> 0.0492904 | F18: 0.048 | G18: 0.047 | H18: 0.047 | I18: 0.047 | N18: *tapered to 4.7 as new equipment will decrease dep.
A19: Fuel | B19: 5157 | C19: 4137 | D19: 3316 | E19: =E4*E20 -> 3405.5976 | F19: =F4*F20 -> 3465.3498 | G19: =G4*G20 -> 3537.613 | H19: =H4*H20 -> 3606.288 | I19: =I4*I20 -> 3676.704
B20: =B19/B4 -> 0.06795899 | C20: =C19/C4 -> 0.055408971 | D20: =D19/D4 -> 0.044034845 | E20: 0.044034845 | F20: 0.044034845 | G20: 0.044034845 | H20: 0.044034845 | I20: 0.044034845 | N20: *Kept at 2025 level
A21: Maintenance & Repairs | B21: 2910 | C21: 2848 | D21: 2799 | E21: =E4*E22 -> 2784.1931 | F21: =F4*F22 -> 2754.3469 | G21: =G4*G22 -> 2811.7835 | H21: =H4*H22 -> 2784.472 | I21: =I4*I22 -> 2838.8412
B22: =B21/B4 -> 0.038348005 | C22: =C21/C4 -> 0.03814473 | D22: =D21/D4 -> 0.03716934 | E22: 0.036 | F22: 0.035 | G22: 0.035 | H22: 0.034 | I22: 0.034 | N22: Tapered to 3.4 expecting less reapirs because of new equipmwnt
A23: Asset Impairment Charges | B23: 70 | C23: 157 | D23: 21 | E23: 21 | F23: 21 | G23: 21 | H23: 21 | I23: 21
A24: Business Optimization Costs | B24: 47 | C24: 251 | D24: 384 | E24: 250 | F24: 100 | G24: 0 | H24: 0 | I24: 0
A25: Intercompany Allocations (Charges) | B25: -689 | C25: -684 | D25: -791 | E25: =E4*E26 -> -812.37266 | F25: =F4*F26 -> -826.62595 | G25: =G4*G26 -> -843.86365 | H25: =H4*H26 -> -860.24542 | I25: =I4*I26 -> -877.04247 | N25: *maintaining same as 2025
B26: =B25/B4 -> -0.0090796479 | C26: =C25/C4 -> -0.0091611642 | D26: =D25/D4 -> -0.01050409 | E26: -0.01050409 | F26: -0.01050409 | G26: -0.01050409 | H26: -0.01050409 | I26: -0.01050409
A27: Other | B27: 12306 | C27: 11582 | D27: 11964 | E27: =E28*E4 -> 12275.412 | F27: =F28*F4 -> 12400.397 | G27: =G28*G4 -> 12724.604 | H27: =H28*H4 -> 12958.384 | I27: =I28*I4 -> 13197.674
B28: =B27/B4 -> 0.16216857 | C28: =C27/C4 -> 0.15512369 | D28: =D27/D4 -> 0.15887602 | E28: =AVERAGE(B28:D28) -> 0.15872276 | F28: =AVERAGE(C28:E28) -> 0.15757416 | G28: =AVERAGE(D28:F28) -> 0.15839098 | H28: =AVERAGE(E28:G28) -> 0.1582293 | I28: =AVERAGE(F28:H28) -> 0.15806481
A29: Total Operating Expenses | B29: =SUM(B5:B27) -> 71691.781 | C29: =SUM(C5:C27) -> 69844.775 | D29: =SUM(D5:D27) -> 70419.771 | E29: =SUM(E5:E27) -> 70640.243 | F29: =SUM(F5:F27) -> 70807.853 | G29: =SUM(G5:G27) -> 72301.029 | H29: =SUM(H5:H27) -> 73756.363 | I29: =SUM(I5:I27) -> 75336.865
A31: FedEx Freight Segment
A32: Operating Expense | B32: 2023 | C32: 2024 | D32: 2025 | E32: 2026 | F32: 2027 | G32: 2028 | H32: 2029 | I32: 2030
A33: sales YOY | B33: =Revenue!E5 -> 10084 | C33: =Revenue!F5 -> 9429 | D33: =Revenue!G5 -> 8892 | E33: =Revenue!J5 -> 8962.7005 | F33: =Revenue!K5 -> 9156.043 | G33: =Revenue!L5 -> 9432.6225 | H33: =Revenue!M5 -> 9717.5566 | I33: =Revenue!N5 -> 10011.098
A34: Salaries & Employee Benefits | B34: 4057 | C34: 3923 | D34: 3865 | E34: =E33*E35 -> 3895.7307 | F34: =F33*F35 -> 3979.769 | G34: =G33*G35 -> 4099.9872 | H34: =H33*H35 -> 4223.8368 | I34: =I33*I35 -> 4351.4275
B35: =B34/B33 -> 0.40232051 | C35: =C34/C33 -> 0.41605685 | D35: =D34/D33 -> 0.43466037 | E35: =D35 -> 0.43466037 | F35: =E35 -> 0.43466037 | G35: =F35 -> 0.43466037 | H35: =G35 -> 0.43466037 | I35: =H35 -> 0.43466037 | N35: *expected to decrease by optimisation and balanced by wage inflation
A36: Purchased Transportation | B36: 1078 | C36: 877 | D36: 807 | E36: =E33*E37 -> 813.41647 | F36: =F33*F37 -> 830.96342 | G36: =G33*G37 -> 856.06459 | H36: =H33*H37 -> 881.924 | I36: =I33*I37 -> 908.56455
B37: =B36/B33 -> 0.10690202 | C37: =C36/C33 -> 0.093010924 | D37: =D36/D33 -> 0.090755735 | E37: =D37 -> 0.090755735 | F37: =E37 -> 0.090755735 | G37: =F37 -> 0.090755735 | H37: =G37 -> 0.090755735 | I37: =H37 -> 0.090755735 | N37: *expeccted to be low as new equipment is being introduced
A38: Rentals & Landing Fees | B38: 269 | C38: 280 | D38: 287 | E38: =E39*E33 -> 289.28194 | F38: =F39*F33 -> 295.52231 | G38: =G39*G33 -> 304.44924 | H38: =H39*H33 -> 313.64583 | I38: =I39*I33 -> 323.12023
B39: =B38/B33 -> 0.026675922 | C39: =C38/C33 -> 0.02969562 | D39: =D38/D33 -> 0.032276203 | E39: =D39 -> 0.032276203 | F39: =E39 -> 0.032276203 | G39: =F39 -> 0.032276203 | H39: =G39 -> 0.032276203 | I39: =H39 -> 0.032276203 | N39: *similar or slightly higher than 2025 levels
A40: Depreciation & Amortization | B40: 387 | C40: 404 | D40: 416 | E40: =E41*E33 -> 419.30762 | F40: =F41*F33 -> 421.17798 | G40: =G41*G33 -> 433.90063 | H40: =H41*H33 -> 437.29005 | I40: =I41*I33 -> 450.49941
B41: =B40/B33 -> 0.038377628 | C41: =C40/C33 -> 0.042846537 | D41: =D40/D33 -> 0.046783626 | E41: =D41 -> 0.046783626 | F41: 0.046 | G41: 0.046 | H41: 0.045 | I41: 0.045 | N41: *Tapered down to 4.5 as expected to lower dep for newer vehicles
A42: Fuel | B42: 748 | C42: 571 | D42: 457 | E42: =E43*E33 -> 460.63362 | F42: =F43*F33 -> 470.57036 | G42: =G43*G33 -> 484.78503 | H42: =H43*H33 -> 499.42908 | I42: =I43*I33 -> 514.51549
B43: =B42/B33 -> 0.074176914 | C43: =C42/C33 -> 0.060557853 | D43: =D42/D33 -> 0.051394512 | E43: =D43 -> 0.051394512 | F43: =E43 -> 0.051394512 | G43: =F43 -> 0.051394512 | H43: =G43 -> 0.051394512 | I43: =H43 -> 0.051394512 | N43: *maintaine as same as 2025
A44: Maintenance & Repairs | B44: 320 | C44: 330 | D44: 332 | E44: =E45*E33 -> 334.63974 | F44: =F45*F33 -> 329.61755 | G44: =G45*G33 -> 339.57441 | H44: =H45*H33 -> 340.11448 | I44: =I45*I33 -> 350.38843
B45: =B44/B33 -> 0.031733439 | C45: =C44/C33 -> 0.034998409 | D45: =D44/D33 -> 0.037336932 | E45: =D45 -> 0.037336932 | F45: 0.036 | G45: 0.036 | H45: 0.035 | I45: 0.035 | N45: *Tapered to 3.5 expecting reduction in repairs
A46: Goodwill / Asset Impairment Charges | B46: 0 | C46: 0 | D46: 0
A47: Business Optimization Costs | B47: 0 | C47: 0 | D47: 0
A48: Intercompany Allocations (Charges) | B48: 542 | C48: 543 | D48: 573 | E48: =E49*E33 -> 573.61283 | F48: =F49*F33 -> 585.98675 | G48: =G49*G33 -> 603.68784 | H48: =H49*H33 -> 621.92363 | I48: =I49*I33 -> 640.71027
B49: =B48/B33 -> 0.053748512 | C49: =C48/C33 -> 0.057588291 | D49: =D48/D33 -> 0.064439946 | E49: 0.064 | F49: 0.064 | G49: 0.064 | H49: 0.064 | I49: 0.064 | N49: *Maintained at same as 2025
A50: Other | B50: 747 | C50: 680 | D50: 666 | E50: =E33*E51 -> 671.29538 | F50: =F33*F51 -> 685.7765 | G50: =G33*G51 -> 706.49197 | H50: =H33*H51 -> 727.83319 | I50: =I33*I51 -> 749.81907
B51: =B50/B33 -> 0.074077747 | C51: =C50/C33 -> 0.072117934 | D51: =D50/D33 -> 0.074898785 | E51: =D51 -> 0.074898785 | F51: =E51 -> 0.074898785 | G51: =F51 -> 0.074898785 | H51: =G51 -> 0.074898785 | I51: =H51 -> 0.074898785 | N51: *Manitianed as same as 2025 levels
A52: Total Operating Expenses | B52: =SUM(B34:B50) -> 8148.7339 | C52: =SUM(C34:C50) -> 7608.7348 | D52: =SUM(D34:D50) -> 7403.7576 | E52: =SUM(E34:E50) -> 7458.6755 | F52: =SUM(F34:F50) -> 7600.139 | G52: =SUM(G34:G50) -> 7829.696 | H52: =SUM(H34:H50) -> 8046.7501 | I52: =SUM(I34:I50) -> 8289.7981 | L52: =I52/$I$90 -> 0.09325264
A54: Corporate, Other & Eliminations
A55: Operating Expense | B55: 2023 | C55: 2024 | D55: 2025 | E55: 2026 | F55: 2027 | G55: 2028 | H55: 2029 | I55: 2030
A56: sales YOY | B56: =Revenue!E6 -> 4187 | C56: =Revenue!F6 -> 3601 | D56: =Revenue!G6 -> 3730 | E56: =Revenue!J6 -> 3484 | F56: =Revenue!K6 -> 3588.6619 | G56: =Revenue!L6 -> 3696.4679 | H56: =Revenue!M6 -> 3807.5125 | I56: =Revenue!N6 -> 3921.8929
A57: Salaries & Employee Benefits | B57: 2439 | C57: 2432 | D57: 2276 | E57: =E58*E56 -> 2125.8938 | F57: =F58*F56 -> 2189.7572 | G57: =G58*G56 -> 2255.5391 | H57: =H58*H56 -> 2323.2972 | I57: =I58*I56 -> 2393.0907
B58: =B57/B56 -> 0.58251732 | C58: =C57/C56 -> 0.67536795 | D58: =D57/D56 -> 0.61018767 | E58: =D58 -> 0.61018767 | F58: =E58 -> 0.61018767 | G58: =F58 -> 0.61018767 | H58: =G58 -> 0.61018767 | I58: =H58 -> 0.61018767 | L58: *Maintained at 2025 level
A59: Purchased Transportation | B59: 1035 | C59: 714 | D59: 987 | E59: =E56*E60 -> 905.84 | F59: =F56*F60 -> 933.05209 | G59: =G56*G60 -> 961.08166 | H59: =H56*H60 -> 989.95325 | I59: =I56*I60 -> 1019.6922
B60: =B59/B56 -> 0.24719369 | C60: =C59/C56 -> 0.19827826 | D60: =D59/D56 -> 0.26461126 | E60: 0.26 | F60: 0.26 | G60: 0.26 | H60: 0.26 | I60: 0.26 | L60: *Maintained at 2025 level
A61: Rentals & Landing Fees | B61: 434 | C61: 428 | D61: 421 | E61: =D61*(1+E62) -> 467.31 | F61: =E61*(1+F62) -> 518.7141 | G61: =F61*(1+G62) -> 575.77265 | H61: =G61*(1+H62) -> 639.10764 | I61: =H61*(1+I62) -> 709.40948
B62: =B61/B56 -> 0.10365417 | C62: =C61/C56 -> 0.11885587 | D62: =D61/D56 -> 0.11286863 | E62: 0.11 | F62: 0.11 | G62: 0.11 | H62: 0.11 | I62: 0.11 | L62: *Maintained at 2025 level
A63: Depreciation & Amortization | B63: 134 | C63: 129 | D63: 126 | E63: =D63*(1+E64) -> 130.284 | F63: =E63*(1+F64) -> 134.71366 | G63: =F63*(1+G64) -> 139.29392 | H63: =G63*(1+H64) -> 144.02991 | I63: =H63*(1+I64) -> 148.92693
B64: =B63/B56 -> 0.032003821 | C64: =C63/C56 -> 0.035823382 | D64: =D63/D56 -> 0.033780161 | E64: 0.034 | F64: 0.034 | G64: 0.034 | H64: 0.034 | I64: 0.034 | L64: *Maintained at 2025 level
A65: Fuel | B65: 4 | C65: 2 | D65: 2 | E65: =D65*(1+E66) -> 2.0010724 | F65: =E65*(1+F66) -> 2.0021453 | G65: =F65*(1+G66) -> 2.0032189 | H65: =G65*(1+H66) -> 2.004293 | I65: =H65*(1+I66) -> 2.0053677
B66: =B65/B56 -> 0.00095533795 | C66: =C65/C56 -> 0.00055540128 | D66: =D65/D56 -> 0.00053619303 | E66: 0.00053619303 | F66: 0.00053619303 | G66: 0.00053619303 | H66: 0.00053619303 | I66: 0.00053619303 | L66: *Maintained at 2025 level
A67: Maintenance & Repairs | B67: 127 | C67: 113 | D67: 114 | E67: =D67*(1+E68) -> 117.48418 | F67: =E67*(1+F68) -> 121.07485 | G67: =F67*(1+G68) -> 124.77526 | H67: =G67*(1+H68) -> 128.58877 | I67: =H67*(1+I68) -> 132.51883
B68: =B67/B56 -> 0.03033198 | C68: =C67/C56 -> 0.031380172 | D68: =D67/D56 -> 0.030563003 | E68: 0.030563003 | F68: 0.030563003 | G68: 0.030563003 | H68: 0.030563003 | I68: 0.030563003 | L68: *Maintained at 2025 level
A69: Goodwill / Asset Impairment Charges | B69: 47
A70: Business Optimization Costs | B70: 262 | C70: 331 | D70: 372 | E70: 250 | F70: 100 | G70: 100 | H70: 0 | I70: 0
A71: Intercompany Allocations (Charges) | B71: 147 | C71: 141 | D71: 218 | E71: =D71*(1+E72) -> 226.72 | F71: =E71*(1+F72) -> 235.7888 | G71: =F71*(1+G72) -> 245.22035 | H71: =G71*(1+H72) -> 255.02917 | I71: =H71*(1+I72) -> 265.23033
B72: =B71/B56 -> 0.03510867 | C72: =C71/C56 -> 0.03915579 | D72: =D71/D56 -> 0.05844504 | E72: 0.04 | F72: 0.04 | G72: 0.04 | H72: 0.04 | I72: 0.04 | L72: *normalsied over the years
A73: Other | B73: 775 | C73: 392 | D73: 371 | E73: =D73*(1+E74) -> 408.1 | F73: =E73*(1+F74) -> 448.91 | G73: =F73*(1+G74) -> 493.801 | H73: =G73*(1+H74) -> 543.1811 | I73: =H73*(1+I74) -> 597.49921
B74: =B73/B56 -> 0.18509673 | C74: =C73/C56 -> 0.10885865 | D74: =D73/D56 -> 0.099463807 | E74: 0.1 | F74: 0.1 | G74: 0.1 | H74: 0.1 | I74: 0.1 | L74: *Maintained at 2025 level
A75: Total Operating Expenses | B75: =SUM(B57:B73) -> 5405.0318 | C75: =SUM(C57:C73) -> 4683.0994 | D75: =SUM(D57:D73) -> 4888.111 | E75: =SUM(E57:E73) -> 4634.7184 | F75: =SUM(F57:F73) -> 4685.0982 | G75: =SUM(G57:G73) -> 4898.5725 | H75: =SUM(H57:H73) -> 5026.2766 | I75: =SUM(I57:I73) -> 5269.4583 | L75: =I75/$I$90 -> 0.059276583
A78: Operating Expense | B78: 2023 | C78: 2024 | D78: 2025 | E78: 2026 | F78: 2027 | G78: 2028 | H78: 2029 | I78: 2030
A79: Salaries and employee benefits | B79: =B5+B34+B57 -> 31019 | C79: =C5+C34+C57 -> 30961 | D79: =D5+D34+D57 -> 31232 | E79: =E5+E34+E57 -> 30770.008 | F79: =F5+F34+F57 -> 30565.171 | G79: =G5+G34+G57 -> 31259.895 | H79: =H5+H34+H57 -> 31934.966 | I79: =I5+I34+I57 -> 32628.071
A80: Purchased transportation | B80: =B10+B36+B59 -> 21790 | C80: =C10+C36+C59 -> 20921 | D80: =D10+D36+D59 -> 21768 | E80: =E10+E36+E59 -> 21827.318 | F80: =F10+F36+F59 -> 22224.878 | G80: =G10+G36+G59 -> 22704.681 | H80: =H10+H36+H59 -> 23164.898 | I80: =I10+I36+I59 -> 23637.043
A81: Rentals and landing fees | B81: =B15+B38+B61 -> 4738 | C81: =C15+C38+C61 -> 4571 | D81: =D15+D38+D61 -> 4647 | E81: =E15+E38+E61 -> 4802.0229 | F81: =F15+F38+F61 -> 5071.2757 | G81: =G15+G38+G61 -> 5359.9383 | H81: =H15+H38+H61 -> 5666.7948 | I81: =I15+I38+I61 -> 5993.153
A82: Depreciation and amortization | B82: =B17+B40+B63 -> 4176 | C82: =C17+C40+C63 -> 4287 | D82: =D17+D40+D63 -> 4264 | E82: =E17+E40+E63 -> 4361.647 | F82: =F17+F40+F63 -> 4333.2817 | G82: =G17+G40+G63 -> 4349.0182 | H82: =H17+H40+H63 -> 4430.443 | I82: =I17+I40+I63 -> 4523.7068
A83: Fuel | B83: =B19+B42+B65 -> 5909 | C83: =C19+C42+C65 -> 4710 | D83: =D19+D42+D65 -> 3775 | E83: =E19+E42+E65 -> 3868.2323 | F83: =F19+F42+F65 -> 3937.9223 | G83: =G19+G42+G65 -> 4024.4012 | H83: =H19+H42+H65 -> 4107.7214 | I83: =I19+I42+I65 -> 4193.2248
A84: Maintanence and repairs | B84: =B21+B44+B67 -> 3357 | C84: =C21+C44+C67 -> 3291 | D84: =D21+D44+D67 -> 3245 | E84: =E21+E44+E67 -> 3236.3171 | F84: =F21+F44+F67 -> 3205.0393 | G84: =G21+G44+G67 -> 3276.1332 | H84: =H21+H44+H67 -> 3253.1752 | I84: =I21+I44+I67 -> 3321.7485
A85: Goodwill and other asset impairment charges | B85: =B23+B46+B69 -> 117 | C85: =C23+C46+C69 -> 157 | D85: =D23+D46+D69 -> 21 | E85: =E23+E46+E69 -> 21 | F85: =F23+F46+F69 -> 21 | G85: =G23+G46+G69 -> 21 | H85: =H23+H46+H69 -> 21 | I85: =I23+I46+I69 -> 21
A86: Business optimization and realignment costs | B86: =B24+B47+B70 -> 309 | C86: =C24+C47+C70 -> 582 | D86: =D24+D47+D70 -> 756 | E86: =E24+E47+E70 -> 500 | F86: =F24+F47+F70 -> 200 | G86: =G24+G47+G70 -> 100 | H86: =H24+H47+H70 -> 0 | I86: =I24+I47+I70 -> 0
A87: Other | B87: =B73+B50+B27 -> 13828 | C87: =C73+C50+C27 -> 12654 | D87: =D73+D50+D27 -> 13001 | E87: =E73+E50+E27 -> 13354.807 | F87: =F73+F50+F27 -> 13535.084 | G87: =G73+G50+G27 -> 13924.897 | H87: =H73+H50+H27 -> 14229.398 | I87: =I73+I50+I27 -> 14544.992
A90: Total Operating Expenses | B90: =B29+B52+B75 -> 85245.547 | C90: =C29+C52+C75 -> 82136.609 | D90: =D29+D52+D75 -> 82711.64 | E90: =E29+E52+E75 -> 82733.636 | F90: =F29+F52+F75 -> 83093.09 | G90: =G29+G52+G75 -> 85029.297 | H90: =H29+H52+H75 -> 86829.39 | I90: =I29+I52+I75 -> 88896.122

Sheet Debt schedule
C3: Debt schedule | I3: Debt (10-K disclosures & management outlook)
A6: Year | B6: 2021 | C6: 2022 | D6: 2023 | E6: 2024 | F6: 2025 | G6: 2026 | H6: 2027 | I6: 2028 | J6: 2029 | K6: 2030
A7: Opening Debt Principal (mm) | C7: =B10 -> 20733 | D7: =C10 -> 20182 | E7: =D10 -> 20453 | F7: =E10 -> 20135 | G7: =F10 -> 19151 | H7: =G10 -> 21780 | I7: =H10 -> 24304 | J7: =I10 -> 27752 | K7: =J10 -> 29617
A8: Maturities (mm) | F8: 0 | G8: 1371 | H8: 1476 | I8: 552 | J8: 1135 | K8: 1802 | P8: Given in 10-K/10-Q — taken from the contractual debt maturity table by fiscal year.
A9: new debt | G9: 4000 | H9: 4000 | I9: 4000 | J9: 3000 | K9: 3000
A10: Closing Debt Principal (mm) | B10: ='Balance sheet'!B34 -> 20733 | C10: ='Balance sheet'!C34 -> 20182 | D10: ='Balance sheet'!D34 -> 20453 | E10: ='Balance sheet'!E34 -> 20135 | F10: ='Balance sheet'!F34 -> 19151 | G10: =G7-G8+G9 -> 21780 | H10: =H7-H8+H9 -> 24304 | I10: =I7-I8+I9 -> 27752 | J10: =J7-J8+J9 -> 29617 | K10: =K7-K8+K9 -> 30815
A11: Avg debt | B11: =AVERAGE(B10,B7) -> 20733 | C11: =AVERAGE(C10,C7) -> 20457.5 | D11: =AVERAGE(D10,D7) -> 20317.5 | E11: =AVERAGE(E10,E7) -> 20294 | F11: =AVERAGE(F10,F7) -> 19643 | G11: =AVERAGE(G10,G7) -> 20465.5 | H11: =AVERAGE(H10,H7) -> 23042 | I11: =AVERAGE(I10,I7) -> 26028 | ... K11: =AVERAGE(K10,K7) -> 30216
A12: Interest expense | B12: =-'Income statement'!B19 -> 793 | C12: =-'Income statement'!C19 -> 689 | D12: =-'Income statement'!D19 -> 694 | E12: =-'Income statement'!E19 -> 745 | F12: =-'Income statement'!F19 -> 789 | G12: =G11*0.042 -> 859.551 | H12: =H11*0.042 -> 967.764 | I12: =I11*0.042 -> 1093.176 | J12: =J11*0.04 -> 1147.38 | K12: =K11*0.04 -> 1208.64 | P12: Modeled — average debt × assumed blended coupon; reflects scheduled paydowns.
A13: Coupon rate | B13: =B12/B11 -> 0.038248203 | C13: =C12/C11 -> 0.03367958 | D13: =D12/D11 -> 0.034157746 | E13: =E12/E11 -> 0.036710358 | F13: =F12/F11 -> 0.040166981 | G13: =G12/G11 -> 0.042 | H13: =H12/H11 -> 0.042 | I13: =I12/I11 -> 0.042 | ... K13: =K12/K11 -> 0.04
A15: capex schedule | B15: FY 2025 | C15: FY 2026 | D15: 2026E | E15: 2027E | F15: 2028E | G15: 2029E | H15: 2030E
A16: By Asset Type | L16: Given in latest 10-Q — year-to-date capex by class (where disclosed).
A17: Aircraft and related equipment | B17: 1251 | C17: 60 | D17: 889 | E17: 1114 | F17: 989 | G17: 410 | H17: 204
A18: Package handling and ground support equipment | B18: 935 | C18: 205 | D18: 1200 | E18: 1250 | F18: 1300 | G18: 1200 | H18: 1100
A19: Information technology | B19: 504 | C19: 118 | D19: 600 | E19: 550 | F19: 525 | G19: 500 | H19: 475
A20: Vehicles and trailers | B20: 434 | C20: 47 | D20: 650 | E20: 600 | F20: 575 | G20: 550 | H20: 525
A21: Facilities and other | B21: 931 | C21: 193 | D21: 1161 | E21: 1000 | F21: 950 | G21: 900 | H21: 850
A22: Total | B22: 4055 | C22: 623 | D22: 4500 | E22: 4514 | F22: 4339 | G22: 3560 | H22: 3154 | L22: Modeled — forward plan based on fleet/ground automation program cadence and historical mix.
C23: Shares outstanding
A26: Year | B26: 2025 | C26: 2026 | D26: 2027 | E26: 2028 | F26: 2029 | G26: 2030
A27: Opening Diluted Shares (mm) | B27: 243 | C27: =B29 -> 232.1 | D27: =C29 -> 222.09 | E27: =D29 -> 212.56 | F27: =E29 -> 203.48 | G27: =F29 -> 194.83
A28: Buybacks (mm) | B28: 10.9 | C28: =C37 -> 10.007786 | D28: =D37 -> 9.5312248 | E28: =E37 -> 9.077357 | F28: =F37 -> 8.6451019 | G28: =G37 -> 8.2334304 | L28: Modeled — shares repurchased derived from assumed buyback dollars ÷ est. average price (authorizations disclosed but volumes not).
A29: Ending Diluted Shares (mm) | B29: =ROUND(B27-B28,2) -> 232.1 | C29: =ROUND(C27-C28,2) -> 222.09 | D29: =ROUND(D27-D28,2) -> 212.56 | E29: =ROUND(E27-E28,2) -> 203.48 | F29: =ROUND(F27-F28,2) -> 194.83 | G29: =ROUND(G27-G28,2) -> 186.6
A30: Avg Diluted Shares (mm) | B30: =(B27+B29)/2 -> 237.55 | C30: =ROUND(AVERAGE(C27,C29),2) -> 227.1 | D30: =ROUND(AVERAGE(D27,D29),2) -> 217.33 | E30: =ROUND(AVERAGE(E27,E29),2) -> 208.02 | F30: =ROUND(AVERAGE(F27,F29),2) -> 199.16 | G30: =ROUND(AVERAGE(G27,G29),2) -> 190.72
A31: Net income | B31: ='Income statement'!F27 -> 4092 | C31: ='Income statement'!H27 -> 4912.2144 | D31: ='Income statement'!I27 -> 5798.9578 | E31: ='Income statement'!J27 -> 5787.2822 | F31: ='Income statement'!K27 -> 5883.648 | G31: ='Income statement'!L27 -> 5814.1307
A32: Eps | B32: =B31/B30 -> 17.225847 | C32: =C31/C30 -> 21.630182 | D32: =D31/D30 -> 26.68273 | E32: =E31/E30 -> 27.820797 | F32: =F31/F30 -> 29.542318 | G32: =G31/G30 -> 30.485165
B35: 2500 | C35: 2500 | D35: 2500 | E35: 2500 | F35: 2500 | G35: 2500
B36: 237.91 | C36: =B36*(1+0.05) -> 249.8055 | D36: =C36*(1+0.05) -> 262.29577 | E36: =D36*(1+0.05) -> 275.41056 | F36: =E36*(1+0.05) -> 289.18109 | G36: =F36*(1+0.05) -> 303.64015
B37: =B35/B36 -> 10.508175 | C37: =C35/C36 -> 10.007786 | D37: =D35/D36 -> 9.5312248 | E37: =E35/E36 -> 9.077357 | F37: =F35/F36 -> 8.6451019 | G37: =G35/G36 -> 8.2334304

Sheet CapEx
A3: Capital Expenditures
A4: FY 2023 – FY 2026
A5: Years ended May 31
A6: In millions
E7: Q1 YTD
B8: FY 2023 | C8: FY 2024 | D8: FY 2025 | E8: FY 2026 | F8: 2026E | G8: 2027E | H8: 2028E | I8: 2029E | J8: 2030E
A9: By Asset Type
A10: Aircraft and related equipment | B10: 1684 | C10: 1627 | D10: 1251 | E10: 60 | F10: 889 | G10: 1114 | H10: 1114 | I10: 1114 | J10: 1114 | L10: Assumed to decline post-FY26 as major aircraft modernization under Network 2.0 concludes and fleet age profile stabilizes.
A11: Package handling and ground support equipment | B11: 1851 | C11: 974 | D11: 935 | E11: 205 | F11: 1200 | G11: 1250 | H11: 1300 | I11: 1250 | J11: 1250 | L11: Peaks through FY26 with automation and hub consolidation projects, then normalizes as Network 2.0 transitions from build-out to maintenance.
A12: Information technology | B12: 802 | C12: 656 | D12: 504 | E12: 118 | F12: 600 | G12: 550 | H12: 525 | I12: 500 | J12: 475 | L12: Gradually tapers after FY26 as key digital infrastructure and routing-optimization platforms are fully deployed, leaving steady maintenance spend.
A13: Vehicles and trailers | B13: 719 | C13: 709 | D13: 434 | E13: 47 | F13: 650 | G13: 600 | H13: 575 | I13: 550 | J13: 525 | L13: Moderate decline due to completion of large-scale Ground fleet refresh and increased reliance on leased or partner-supplied EV vehicles.
A14: Facilities and other | B14: 1118 | C14: 1210 | D14: 931 | E14: 193 | F14: 1161 | G14: 1000 | H14: 950 | I14: 950 | J14: 950 | L14: Decreases from FY26 onward as major hub expansions and building upgrades are completed, consistent with capital discipline and FCF priorities.
A15: Total | B15: 6174 | C15: 5176 | D15: 4055 | E15: 623 | F15: =SUM(F10:F14) -> 4500 | G15: =SUM(G10:G14) -> 4514 | H15: =SUM(H10:H14) -> 4464 | I15: =SUM(I10:I14) -> 4364 | J15: =SUM(J10:J14) -> 4314 | L15: FY26 ≈ $4.5 B per management guidance; decline through FY30 reflects completion of modernization cycle and focus on shareholder returns.
A17: By Segment
A18: Federal Express segment | B18: 5480 | C18: 4591 | D18: 3505 | E18: 568 | L18: Fore-word
A19: FedEx Freight segment | B19: 557 | C19: 461 | D19: 437 | E19: 32 | L19: “FY26 CapEx ≈ $4.5 B driven by aircraft and Network 2.0 investments.”
A20: Other | B20: 137 | C20: 124 | D20: 113 | E20: 23 | L20: “Investments in Network 2.0 and sort facility automation continue in FY26.”
A21: Total | B21: 6174 | C21: 5176 | D21: 4055 | E21: 623 | L21: “We expect lower incremental spend in subsequent years as platform deployments are completed.”
L22: “Vehicle purchases moderated as fleet modernization and electrification partnerships progress.”
L23: “Network 2.0 continues to focus on facility optimization, automation, and hub consolidation, which are expected to deliver efficiency and cost benefits in FY26 and beyond.”
D28: Moderate decline due to completion of large-scale Ground fleet refresh and increased reliance on leased or partner-supplied EV vehicles.

Sheet Balance sheet
A1: CONSOLIDATED BALANCE SHEETS
A2: (IN MILLIONS, EXCEPT SHARE DATA)
B3: 2021 | C3: 2022 | D3: 2023 | E3: 2024 | F3: 2025 | G3: 2026E | H3: 2027E | I3: 2028E | J3: 2029E | K3: 2030E
A4: ASSETS
A5: CURRENT ASSETS
A6: Cash and cash equivalents | B6: 7087 | C6: 6897 | D6: 6856 | E6: 6501 | F6: 5502 | G6: ='Derived cash flow'!C57 -> 6308.2147 | H6: ='Derived cash flow'!D57 -> 9169.9292 | I6: ='Derived cash flow'!E57 -> 12178.583 | J6: ='Derived cash flow'!F57 -> 15202.02 | K6: ='Derived cash flow'!G57 -> 17608.292
A7: Receivables | B7: 12069 | C7: 11863 | D7: 10188 | E7: 10087 | F7: 11368 | G7: =(G66*'Income statement'!H5)/365 -> 11207.474 | H7: =(H66*'Income statement'!I5)/365 -> 11413.938 | I7: =(I66*'Income statement'!J5)/365 -> 11666.903 | J7: =(J66*'Income statement'!K5)/365 -> 11911.781 | K7: =(K66*'Income statement'!L5)/365 -> 12163.116
A8: Spare parts | B8: 587 | C8: 637 | D8: 604 | E8: 614 | F8: 602 | G8: ='Income statement'!H12*'Balance sheet'!G67 -> 593.7341 | H8: ='Income statement'!I12*'Balance sheet'!H67 -> 587.9959 | I8: ='Income statement'!J12*'Balance sheet'!I67 -> 601.03877 | J8: ='Income statement'!K12*'Balance sheet'!J67 -> 596.82689 | K8: ='Income statement'!L12*'Balance sheet'!K67 -> 609.40733
A9: Prepaid expenses | B9: 837 | C9: 968 | D9: 962 | E9: 1005 | F9: 914 | G9: =G68*'Income statement'!H16 -> 933.01513 | H9: =H68*'Income statement'!I16 -> 936.98775 | I9: =I68*'Income statement'!J16 -> 958.7094 | J9: =J68*'Income statement'!K16 -> 978.87628 | K9: =K68*'Income statement'!L16 -> 1002.0439
A10: Total current assets | B10: =SUM(B6:B9) -> 20580 | C10: =SUM(C6:C9) -> 20365 | D10: =SUM(D6:D9) -> 18610 | E10: =SUM(E6:E9) -> 18207 | F10: =SUM(F6:F9) -> 18386 | G10: =SUM(G6:G9) -> 19042.438 | H10: =SUM(H6:H9) -> 22108.85 | I10: =SUM(I6:I9) -> 25405.234 | ... K10: =SUM(K6:K9) -> 31382.86
A11: PROPERTY AND EQUIPMENT
A12: Aircraft and related equipment | B12: 26268 | C12: 27874 | D12: 29108 | E12: 30525 | F12: 31584 | G12: =G71 -> 32473 | H12: =H71 -> 33587 | I12: =I71 -> 34701 | J12: =J71 -> 35815 | K12: =K71 -> 36929
A13: Package handling and ground support equipment | B13: 13012 | C13: 14930 | D13: 16839 | E13: 17880 | F13: 18878 | G13: =G72 -> 20078 | H13: =H72 -> 21328 | I13: =I72 -> 22628 | J13: =J72 -> 23878 | K13: =K72 -> 25128
A14: Information technology | B14: 7486 | C14: 8098 | D14: 8792 | E14: 9203 | F14: 9706 | G14: =G73 -> 10306 | H14: =H73 -> 10856 | I14: =I73 -> 11381 | J14: =J73 -> 11881 | K14: =K73 -> 12356
A15: Vehicles and trailers | B15: 9282 | C15: 9806 | D15: 10191 | E15: 10568 | F15: 10949 | G15: =G74 -> 11599 | H15: =H74 -> 12199 | I15: =I74 -> 12774 | J15: =J74 -> 13324 | K15: =K74 -> 13849
A16: Facilities and other | B16: 14029 | C16: 14567 | D16: 15694 | E16: 16215 | F16: 16505 | G16: =G75 -> 17666 | H16: =H75 -> 18666 | I16: =I75 -> 19616 | J16: =J75 -> 20566 | K16: =K75 -> 21516
A17: Total PP&E | B17: =SUM(B12:B16) -> 70077 | C17: =SUM(C12:C16) -> 75275 | D17: =SUM(D12:D16) -> 80624 | E17: =SUM(E12:E16) -> 84391 | F17: =SUM(F12:F16) -> 87622 | G17: =SUM(G12:G16) -> 92122 | H17: =SUM(H12:H16) -> 96636 | I17: =SUM(I12:I16) -> 101100 | ... K17: =SUM(K12:K16) -> 109778
A18: Depreciation and amortization, accumulated | B18: -34325 | C18: -37184 | D18: -39926 | E18: -42900 | F18: -45980 | G18: =G17*G77 -> -46284.087 | H18: =H17*H77 -> -48552.018 | I18: =I17*I77 -> -50794.828 | J18: =J17*J77 -> -52987.396 | K18: =K17*K77 -> -55154.843
A19: Net PP&E | B19: =B17+B18 -> 35752 | C19: =C17+C18 -> 38091 | D19: =D17+D18 -> 40698 | E19: =E17+E18 -> 41491 | F19: =F17+F18 -> 41642 | G19: =G17+G18 -> 45837.913 | H19: =H17+H18 -> 48083.982 | I19: =I17+I18 -> 50305.172 | ... K19: =K17+K18 -> 54623.157
A20: OTHER LONG-TERM ASSETS | E20: =E18-D18 -> -2974
A21: Operating lease right-of-use assets | B21: 15383 | C21: 16613 | D21: 17347 | E21: 17115 | F21: 16453 | G21: =G80 -> 15753 | H21: =H80 -> 15103 | I21: =I80 -> 14503 | J21: =J80 -> 14003 | K21: =K80 -> 13603
A22: Goodwill | B22: 6992 | C22: 6544 | D22: 6435 | E22: 6423 | F22: 6603 | G22: 6603 | H22: 6603 | I22: 6603 | J22: 6603 | K22: 6603
A23: Other assets | B23: 4070 | C23: 4381 | D23: 4053 | E23: 3771 | F23: 4543 | G23: =G82*'Income statement'!H5 -> 4193.4847 | H23: =H82*'Income statement'!I5 -> 4270.7367 | I23: =I82*'Income statement'!J5 -> 4365.3883 | J23: =J82*'Income statement'!K5 -> 4457.014 | K23: =K82*'Income statement'!L5 -> 4551.0559
A24: Total other long-term assets | B24: =SUM(B21:B23) -> 26445 | C24: =SUM(C21:C23) -> 27538 | D24: =SUM(D21:D23) -> 27835 | E24: =SUM(E21:E23) -> 27309 | F24: =SUM(F21:F23) -> 27599 | G24: =SUM(G21:G23) -> 26549.485 | H24: =SUM(H21:H23) -> 25976.737 | I24: =SUM(I21:I23) -> 25471.388 | ... K24: =SUM(K21:K23) -> 24757.056
A25: TOTAL ASSETS | B25: =B24+B19+B10 -> 82777 | C25: =C24+C19+C10 -> 85994 | D25: =D24+D19+D10 -> 87143 | E25: =E24+E19+E10 -> 87007 | F25: =F24+F19+F10 -> 87627 | G25: =G24+G19+G10 -> 91429.836 | H25: =H24+H19+H10 -> 96169.569 | I25: =I24+I19+I10 -> 101181.79 | ... K25: =K24+K19+K10 -> 110763.07
A26: LIABILITIES AND COMMON STOCKHOLDERS INVESTMENT
A27: CURRENT LIABILITIES
A28: Current portion of long-term debt | B28: 146 | C28: 82 | D28: 126 | E28: 68 | F28: 1428 | G28: ='Debt schedule'!G8 -> 1371 | H28: ='Debt schedule'!H8 -> 1476 | I28: ='Debt schedule'!I8 -> 552 | J28: ='Debt schedule'!J8 -> 1135 | K28: ='Debt schedule'!K8 -> 1802
A29: Accrued salaries and employee benefits | B29: 2903 | C29: 2531 | D29: 2475 | E29: 2673 | F29: 2731 | G29: ='Income statement'!H7*G88 -> 2638.3995 | H29: ='Income statement'!I7*H88 -> 2620.8356 | I29: ='Income statement'!J7*I88 -> 2680.4053 | J29: ='Income statement'!K7*J88 -> 2738.2898 | K29: ='Income statement'!L7*K88 -> 2797.7206
A30: Accounts payable | B30: 3841 | C30: 4030 | D30: 3848 | E30: 3189 | F30: 3692 | G30: =G89*'Income statement'!H16 -> 3723.3609 | H30: =H89*'Income statement'!I16 -> 3739.2143 | I30: =I89*'Income statement'!J16 -> 3825.8984 | J30: =J89*'Income statement'!K16 -> 3906.3779 | K30: =K89*'Income statement'!L16 -> 3998.8322
A31: Operating lease liabilities | B31: 2208 | C31: 2443 | D31: 2390 | E31: 2463 | F31: 2565 | G31: =G90*C147 -> 2362.95 | H31: =H90*D147 -> 2265.45 | I31: =I90*E147 -> 2175.45 | J31: =J90*F147 -> 2100.45 | K31: =K90*G147 -> 2040.45
A32: Accrued expenses | B32: 4562 | C32: 5188 | D32: 4747 | E32: 4962 | F32: 4995 | G32: =G91*'Income statement'!H16 -> 4871.0549 | H32: =H91*'Income statement'!I16 -> 4891.795 | I32: =I91*'Income statement'!J16 -> 5005.1987 | J32: =J91*'Income statement'!K16 -> 5110.4853 | K32: =K91*'Income statement'!L16 -> 5231.4379
A33: Total current liabilities | B33: =SUM(B28:B32) -> 13660 | C33: =SUM(C28:C32) -> 14274 | D33: =SUM(D28:D32) -> 13586 | E33: =SUM(E28:E32) -> 13355 | F33: =SUM(F28:F32) -> 15411 | G33: =SUM(G28:G32) -> 14966.765 | H33: =SUM(H28:H32) -> 14993.295 | I33: =SUM(I28:I32) -> 14238.952 | ... K33: =SUM(K28:K32) -> 15870.441
A34: Long term debt | B34: 20733 | C34: 20182 | D34: 20453 | E34: 20135 | F34: 19151 | G34: ='Debt schedule'!G10 -> 21780 | H34: ='Debt schedule'!H10 -> 24304 | I34: ='Debt schedule'!I10 -> 27752 | J34: ='Debt schedule'!J10 -> 29617 | K34: ='Debt schedule'!K10 -> 30815
A35: OTHER LONG-TERM LIABILITIES
A36: Deferred income taxes | B36: 3927 | C36: 4093 | D36: 4489 | E36: 4482 | F36: 4205 | G36: =G19*G95 -> 4919.2944 | H36: =H19*H95 -> 5136.1002 | I36: =I19*I95 -> 5366.9381 | J36: =J19*J95 -> 5560.687 | K36: =K19*K95 -> 5765.6598
A37: Pension | B37: 3501 | C37: 4448 | D37: 3130 | E37: 2010 | F37: 1698 | G37: =G96 -> 1897 | H37: =H96 -> 1939 | I37: =I96 -> 2000 | J37: =J96 -> 2063 | K37: =K96 -> 2137
A38: Self-insurance accruals | B38: 2430 | C38: 2889 | D38: 3339 | E38: 3701 | F38: 4033 | G38: =G97*'Income statement'!H16 -> 4340.7875 | H38: =H97*'Income statement'!I16 -> 4666.7836 | I38: =I97*'Income statement'!J16 -> 5089.6136 | J38: =J97*'Income statement'!K16 -> 5517.9372 | K38: =K97*'Income statement'!L16 -> 5977.3979
A39: Operating lease liabilities | B39: 13375 | C39: 14487 | D39: 15363 | E39: 15053 | F39: 14272 | G39: =G98*C147 -> 13390.05 | H39: =H98*D147 -> 12837.55 | I39: =I98*E147 -> 12327.55 | J39: =J98*F147 -> 11902.55 | K39: =K98*G147 -> 11562.55
A40: Other Liabilities | B40: 983 | C40: 682 | D40: 695 | E40: 689 | F40: 783 | G40: =G99*'Income statement'!H5 -> 775.90568 | H40: =H99*'Income statement'!I5 -> 790.19935 | I40: =I99*'Income statement'!J5 -> 807.71241 | J40: =J99*'Income statement'!K5 -> 824.66557 | K40: =K99*'Income statement'!L5 -> 842.06581
A41: Total other long-term liabilities | B41: =SUM(B36:B40) -> 24216 | C41: =SUM(C36:C40) -> 26599 | D41: =SUM(D36:D40) -> 27016 | E41: =SUM(E36:E40) -> 25935 | F41: =SUM(F36:F40) -> 24991 | G41: =SUM(G36:G40) -> 25323.038 | H41: =SUM(H36:H40) -> 25369.633 | I41: =SUM(I36:I40) -> 25591.814 | ... K41: =SUM(K36:K40) -> 26284.674
A42: COMMON STOCKHOLDERS INVESTMENT
A43: Common stock, 0.10 par value | B43: 32 | C43: 32 | D43: 32 | E43: 32 | F43: 32 | G43: 32 | H43: 32 | I43: 32 | J43: 32 | K43: 32
A44: Additional paid-in capital | B44: 3481 | C44: 3712 | D44: 3769 | E44: 3988 | F44: 4290 | G44: =F44+G103 -> 4492.25 | H44: =G44+H103 -> 4694.5 | I44: =H44+I103 -> 4896.75 | J44: =I44+J103 -> 5099 | K44: =J44+K103 -> 5301.25
A45: Retained earnings | B45: 29817 | C45: 32782 | D45: 35259 | E45: 38649 | F45: 41402 | G45: =G161 -> 44985.783 | H45: =H161 -> 49426.141 | I45: =I161 -> 53820.278 | J45: =J161 -> 58271.679 | K45: =K161 -> 62609.708
A46: Accumulated other comprehensive loss | B46: -732 | C46: -1103 | D46: -1327 | E46: -1359 | F46: -1362 | G46: -1362 | H46: -1362 | I46: -1362 | J46: -1362 | K46: -1362
A47: Treasury stock | B47: -8430 | C47: -10484 | D47: -11645 | E47: -13728 | F47: -16288 | G47: =F47-G165 -> -18788 | H47: =G47-H165 -> -21288 | I47: =H47-I165 -> -23788 | J47: =I47-J165 -> -26288 | K47: =J47-K165 -> -28788
A48: Total common stockholders investment | B48: 24168 | C48: 24939 | D48: 26088 | E48: =SUM(E43:E47) -> 27582 | F48: =SUM(F43:F47) -> 28074 | G48: =SUM(G43:G47) -> 29360.033 | H48: =SUM(H43:H47) -> 31502.641 | I48: =SUM(I43:I47) -> 33599.028 | J48: =SUM(J43:J47) -> 35752.679 | K48: =SUM(K43:K47) -> 37792.958
A49: TOTAL LIABILITIES AND COMMON STOCKHOLDERS INVESTMENT | B49: =B48+B41+B33+B34 -> 82777 | C49: =C48+C41+C33+C34 -> 85994 | D49: =D48+D41+D33+D34 -> 87143 | E49: =E48+E41+E33+E34 -> 87007 | F49: =F48+F41+F33+F34 -> 87627 | G49: =G48+G41+G33+G34 -> 91429.836 | H49: =H48+H41+H33+H34 -> 96169.569 | I49: =I48+I41+I33+I34 -> 101181.79 | ... K49: =K48+K41+K33+K34 -> 110763.07
A51: Check | G51: =G49-G25 -> 0 | H51: =H49-H25 -> 0 | I51: =I49-I25 -> 0 | J51: =J49-J25 -> 0 | K51: =K49-K25 -> 0
A57: Assumptions
B61: 2021 | C61: 2022 | D61: 2023 | E61: 2024 | F61: 2025 | G61: 2026E | H61: 2027E | I61: 2028E | J61: 2029E | K61: 2020E
A63: ASSETS
A64: CURRENT ASSETS
A65: Cash and cash equivalents
A66: Receivables | B66: =(B7/'Income statement'!B5)*365 -> 52.468288 | C66: =(C7/'Income statement'!C5)*365 -> 46.304164 | D66: =(D7/'Income statement'!D5)*365 -> 41.246964 | E66: =(E7/'Income statement'!E5)*365 -> 41.984594 | F66: =(F7/'Income statement'!F5)*365 -> 47.191047 | G66: =AVERAGE(B66:F66) -> 45.839011 | H66: 45.839011 | I66: 45.839011 | J66: 45.839011 | K66: 45.839011 | N66: Scale with revenue with DSO held near recent average (stable customer mix/terms per 10-K).”
A67: Spare parts | B67: =B8/'Income statement'!B12 -> 0.17638221 | C67: =C8/'Income statement'!C12 -> 0.18890866 | D67: =D8/'Income statement'!D12 -> 0.17992255 | E67: =E8/'Income statement'!E12 -> 0.18656943 | F67: =F8/'Income statement'!F12 -> 0.18551618 | G67: =AVERAGE(B67:F67) -> 0.18345981 | H67: 0.18345981 | I67: 0.18345981 | J67: 0.18345981 | K67: 0.18345981 | N67: Grow modestly with fleet/ground assets—kept near historical ratio to maintenance needs (trend-based)
A68: Prepaid expenses | B68: =B9/'Income statement'!B16 -> 0.010716755 | C68: =C9/'Income statement'!C16 -> 0.011092395 | D68: =D9/'Income statement'!D16 -> 0.011285384 | E68: =E9/'Income statement'!E16 -> 0.012236102 | F68: =F9/'Income statement'!F16 -> 0.011050793 | G68: =AVERAGE(B68:F68) -> 0.011276286 | H68: =+$G$68 -> 0.011276286 | I68: =+$G$68 -> 0.011276286 | J68: =+$G$68 -> 0.011276286 | K68: =+$G$68 -> 0.011276286 | N68: Held flat at FY25 run-rate; timing/contract items stable (trend-based).
A69: Total current assets
A70: PROPERTY AND EQUIPMENT
A71: Aircraft and related equipment | B71: =B12 -> 26268 | C71: =C12 -> 27874 | D71: =D12 -> 29108 | E71: =E12 -> 30525 | F71: =B119 -> 31584 | G71: =C119 -> 32473 | H71: =D119 -> 33587 | I71: =E119 -> 34701 | J71: =F119 -> 35815 | K71: =G119 -> 36929 | N71: Roll-forward = prior close + capex per fleet plan; retirements minimal (10-K fleet notes + trend).
A72: Package handling and ground support equipment | B72: =B13 -> 13012 | C72: =C13 -> 14930 | D72: =D13 -> 16839 | E72: =E13 -> 17880 | F72: =F13 -> 18878 | G72: =C125 -> 20078 | H72: =D125 -> 21328 | I72: =E125 -> 22628 | J72: =F125 -> 23878 | K72: =G125 -> 25128 | N72: Roll-forward = prior close + automation/handling capex; consistent with network upgrades (10-K + trend).
A73: Information technology | B73: =B14 -> 7486 | C73: =C14 -> 8098 | D73: =D14 -> 8792 | E73: =E14 -> 9203 | F73: =F14 -> 9706 | G73: =C131 -> 10306 | H73: =D131 -> 10856 | I73: =E131 -> 11381 | J73: =F131 -> 11881 | K73: =G131 -> 12356 | N73: Roll-forward = prior close + IT modernization capex; steady digital spend (10-K + trend)
A74: Vehicles and trailers | B74: =B15 -> 9282 | C74: =C15 -> 9806 | D74: =D15 -> 10191 | E74: =E15 -> 10568 | F74: =F15 -> 10949 | G74: =C136 -> 11599 | H74: =D136 -> 12199 | I74: =E136 -> 12774 | J74: =F136 -> 13324 | K74: =G136 -> 13849 | N74: Roll-forward = prior close + route/tractor refresh capex; tied to Ground density (trend-based).
A75: Facilities and other | B75: =B16 -> 14029 | C75: =C16 -> 14567 | D75: =D16 -> 15694 | E75: =E16 -> 16215 | F75: =F16 -> 16505 | G75: =C141 -> 17666 | H75: =D141 -> 18666 | I75: =E141 -> 19616 | J75: =F141 -> 20566 | K75: =G141 -> 21516 | N75: Roll-forward = prior close + real-estate/sortation capex; selective hub investments (10-K + trend).
A76: Total PP&E
A77: Depreciation and amortization, accumulated | B77: =B18/B17 -> -0.48981834 | C77: =C18/C17 -> -0.49397542 | D77: =D18/D17 -> -0.49521234 | E77: =E18/E17 -> -0.50834805 | F77: =F18/F17 -> -0.52475406 | G77: =AVERAGE(B77:F77) -> -0.50242164 | H77: -0.50242164 | I77: -0.50242164 | J77: -0.50242164 | K77: -0.50242164 | N77: Set at ~50% of gross PP&E to reflect mid-life asset mix; consistent with historical depreciation profile (trend-based).
A78: Net PP&E
A79: OTHER LONG-TERM ASSETS
A80: Operating lease right-of-use assets | B80: =B21 -> 15383 | C80: =C21 -> 16613 | D80: =D21 -> 17347 | E80: =E21 -> 17115 | F80: =F21 -> 16453 | G80: =C147 -> 15753 | H80: =D147 -> 15103 | I80: =E147 -> 14503 | J80: =F147 -> 14003 | K80: =G147 -> 13603 | N80: Down each year as amortization > new lease adds; mirrors lease liabilities schedule (10-K/10-Q mechanics).
A81: Goodwill | N81: Flat—no acquisitions or impairments modeled (10-K baseline).
A82: Other assets | B82: =B23/'Income statement'!B5 -> 0.048476042 | C82: =C23/'Income statement'!C5 -> 0.046849602 | D82: =D23/'Income statement'!D5 -> 0.044955909 | E82: =E23/'Income statement'!E5 -> 0.043002292 | F82: =F23/'Income statement'!F5 -> 0.051668448 | G82: =AVERAGE(B82:F82) -> 0.046990459 | H82: =$G$82 -> 0.046990459 | I82: =$G$82 -> 0.046990459 | J82: =$G$82 -> 0.046990459 | K82: =$G$82 -> 0.046990459 | N82: % of revenue
A83: Total other long-term assets
A84: TOTAL ASSETS
A85: LIABILITIES AND COMMON STOCKHOLDERS INVESTMENT
A86: CURRENT LIABILITIES
A87: Current portion of long-term debt | B87: 146 | C87: 82 | D87: 126 | E87: 68 | F87: 1428 | G87: ='Debt schedule'!G8 -> 1371 | H87: ='Debt schedule'!H8 -> 1476 | I87: ='Debt schedule'!I8 -> 552 | J87: ='Debt schedule'!J8 -> 1135 | K87: ='Debt schedule'!K8 -> 1802 | N87: From debt maturity table (10-K/10-Q).
A88: Accrued salaries and employee benefits | B88: =B29/'Income statement'!B7 -> 0.096211845 | C88: =C29/'Income statement'!C7 -> 0.078950652 | D88: =D29/'Income statement'!D7 -> 0.079789806 | E88: =E29/'Income statement'!E7 -> 0.086334421 | F88: =F29/'Income statement'!F7 -> 0.087442367 | G88: =AVERAGE(B88:F88) -> 0.085745818 | H88: =+$G$88 -> 0.085745818 | I88: =+$G$88 -> 0.085745818 | J88: =+$G$88 -> 0.085745818 | K88: =+$G$88 -> 0.085745818 | N88: Modeled at ~8½–9% of annual salary expense, matching multi-year average (trend-based).
A89: Accounts payable | B89: =B30/'Income statement'!B16 -> 0.049179278 | C89: =C30/'Income statement'!C16 -> 0.046180114 | D89: =D30/'Income statement'!D16 -> 0.045141537 | E89: =E30/'Income statement'!E16 -> 0.038826795 | F89: =F30/'Income statement'!F16 -> 0.044638431 | G89: 0.045 | H89: 0.045 | I89: 0.045 | J89: 0.045 | K89: 0.045 | N89: ~4½% of revenue—holds historical payables turnover (trend-based).
A90: Operating lease liabilities | B90: =B31/(B31+B39) -> 0.14169287 | C90: =C31/(C31+C39) -> 0.14430006 | D90: =D31/(D31+D39) -> 0.13462513 | E90: =E31/(E31+E39) -> 0.1406143 | F90: =F31/(F31+F39) -> 0.15234305 | G90: =0.15 -> 0.15 | H90: =0.15 -> 0.15 | I90: =0.15 -> 0.15 | J90: =0.15 -> 0.15 | K90: =0.15 -> 0.15 | N90: ~15% of total lease liabilities—consistent split of current vs. non-current (10-K mechanics).
A91: Accrued expenses | B91: =B32/'Income statement'!B16 -> 0.058410796 | C91: =C32/'Income statement'!C16 -> 0.059449735 | D91: =D32/'Income statement'!D16 -> 0.055687857 | E91: =E32/'Income statement'!E16 -> 0.060413471 | F91: =F32/'Income statement'!F16 -> 0.06039246 | G91: =AVERAGE(B91:F91) -> 0.058870864 | H91: 0.058870864 | I91: 0.058870864 | J91: 0.058870864 | K91: 0.058870864 | N91: ~5.9% of revenue—kept at multi-year run-rate (trend-based).
A92: Total current liabilities
A93: LONG-TERM DEBT | B93: =B34 -> 20733 | C93: =C34 -> 20182 | D93: =D34 -> 20453 | E93: =E34 -> 20135 | F93: =F34 -> 19151 | G93: =SUM(G7:G9,G19,G21:G23)*G175 -> 23834.054 | H93: =SUM(H7:H9,H19,H21:H23)*H175 -> 25229.896 | I93: =SUM(I7:I9,I19,I21:I23)*I175 -> 26700.963 | J93: =SUM(J7:J9,J19,J21:J23)*J175 -> 27308.13 | K93: =SUM(K7:K9,K19,K21:K23)*K175 -> 27946.434
A94: OTHER LONG-TERM LIABILITIES
A95: Deferred income taxes | B95: =B36/B19 -> 0.10984001 | C95: =C36/C19 -> 0.1074532 | D95: =D36/D19 -> 0.11030026 | E95: =E36/E19 -> 0.10802343 | F95: =F36/F19 -> 0.10097978 | G95: =AVERAGE(B95:F95) -> 0.10731934 | H95: =AVERAGE(C95:G95) -> 0.1068152 | I95: =AVERAGE(D95:H95) -> 0.1066876 | J95: =AVERAGE(E95:I95) -> 0.10596507 | K95: =AVERAGE(F95:J95) -> 0.1055534 | N95: Held near ~10–11% of other LT liabilities; grows with timing differences from capex/pensions (trend + 10-K mechanics).
A96: Pension | B96: =B37 -> 3501 | C96: =C37 -> 4448 | D96: =D37 -> 3130 | E96: =E37 -> 2010 | F96: =F37 -> 1698 | G96: =1897 -> 1897 | H96: 1939 | I96: 2000 | J96: 2063 | K96: 2137 | N96: Gradual increase with normal service cost/actuarial updates; no plan design change (10-K framework).
A97: Self-insurance accruals | B97: =B38/'Income statement'!B16 -> 0.03111316 | C97: =C38/'Income statement'!C16 -> 0.033105298 | D97: =D38/'Income statement'!D16 -> 0.039170372 | E97: =E38/'Income statement'!E16 -> 0.045060511 | F97: =F38/'Income statement'!F16 -> 0.04876132 | G97: =F97-E97+F97 -> 0.052462129 | H97: =G97-F97+G97 -> 0.056162938 | I97: =H97-G97+H97 -> 0.059863747 | J97: =I97-H97+I97 -> 0.063564556 | K97: =J97-I97+J97 -> 0.067265364 | N97: Step-up over time to reflect claims inflation and network scale; anchored to historical % of revenue (trend-based).
A98: Operating lease liabilities | B98: =B39/(B39+B31) -> 0.85830713 | C98: =C39/(C39+C31) -> 0.85569994 | D98: =D39/(D39+D31) -> 0.86537487 | E98: =E39/(E39+E31) -> 0.8593857 | F98: =F39/(F39+F31) -> 0.84765695 | G98: 0.85 | H98: 0.85 | I98: 0.85 | J98: 0.85 | K98: 0.85 | N98: ~85% of total lease liabilities—consistent amortization profile (10-K mechanics).”
A99: Other Liabilities | B99: =B40/'Income statement'!B5 -> 0.011708096 | C99: =C40/'Income statement'!C5 -> 0.0072931816 | D99: =D40/'Income statement'!D5 -> 0.0077089457 | E99: =E40/'Income statement'!E5 -> 0.0078569555 | F99: =F40/'Income statement'!F5 -> 0.0089052157 | G99: =AVERAGE(B99:F99) -> 0.0086944788 | H99: =$G$99 -> 0.0086944788 | I99: =$G$99 -> 0.0086944788 | J99: =$G$99 -> 0.0086944788 | K99: =$G$99 -> 0.0086944788 | N99: % of revenue
A100: Total other long-term liabilities
A101: COMMON STOCKHOLDERS INVESTMENT
A102: Common stock, 0.10 par value | N102: Constant—no change in authorized/issued structure (10-K baseline).
A103: Additional paid-in capital | C103: =C44-B44 -> 231 | D103: =D44-C44 -> 57 | E103: =E44-D44 -> 219 | F103: =F44-E44 -> 302 | G103: =AVERAGE(C103:F103) -> 202.25 | H103: =+$G$103 -> 202.25 | I103: =+$G$103 -> 202.25 | J103: =+$G$103 -> 202.25 | K103: =+$G$103 -> 202.25 | N103: Up modestly each year from stock-based compensation capitalization; ties to SBC schedule (10-K/10-Q + trend).
A104: Retained earnings
A105: Accumulated other comprehensive loss | N105: Held flat—no FX/actuarial shocks modeled (trend-based).
A106: Treasury stock | N106: Cumulative buybacks at modeled $ / avg price; authorization disclosed, volumes modeled (10-K + buyback plan).
A107: Total common stockholders investment
A108: TOTAL LIABILITIES AND COMMON STOCKHOLDERS INVESTMENT
A115: Aircraft and related equipment
A116: Year | B116: 2025A | C116: 2026E | D116: 2027E | E116: 2028E | F116: 2029E | G116: 2030E
...

Sheet Derived cash flow
A1: Free cash flow | B1: 2025 | C1: 2026 | D1: 2027 | E1: 2028 | F1: 2029 | G1: 2030
A2: Net Income | B2: ='Income statement'!F27 -> 4092 | C2: ='Income statement'!H27 -> 4912.2144 | D2: ='Income statement'!I27 -> 5798.9578 | E2: ='Income statement'!J27 -> 5787.2822 | F2: ='Income statement'!K27 -> 5883.648 | G2: ='Income statement'!L27 -> 5814.1307
A4: ASSETS
A5: CURRENT ASSETS
A6: Cash and cash equivalents
A7: Receivables | B7: ='Balance sheet'!E7-'Balance sheet'!F7 -> -1281 | C7: ='Balance sheet'!F7-'Balance sheet'!G7 -> 160.52566 | D7: ='Balance sheet'!G7-'Balance sheet'!H7 -> -206.46319 | E7: ='Balance sheet'!H7-'Balance sheet'!I7 -> -252.96519 | F7: ='Balance sheet'!I7-'Balance sheet'!J7 -> -244.8779 | G7: ='Balance sheet'!J7-'Balance sheet'!K7 -> -251.33568
A8: Spare parts | B8: ='Balance sheet'!E8-'Balance sheet'!F8 -> 12 | C8: ='Balance sheet'!F8-'Balance sheet'!G8 -> 8.2658981 | D8: ='Balance sheet'!G8-'Balance sheet'!H8 -> 5.7382067 | E8: ='Balance sheet'!H8-'Balance sheet'!I8 -> -13.042871 | F8: ='Balance sheet'!I8-'Balance sheet'!J8 -> 4.211872 | G8: ='Balance sheet'!J8-'Balance sheet'!K8 -> -12.580438
A9: Prepaid expenses | B9: ='Balance sheet'!E9-'Balance sheet'!F9 -> 91 | C9: ='Balance sheet'!F9-'Balance sheet'!G9 -> -19.015127 | D9: ='Balance sheet'!G9-'Balance sheet'!H9 -> -3.9726235 | E9: ='Balance sheet'!H9-'Balance sheet'!I9 -> -21.721653 | F9: ='Balance sheet'!I9-'Balance sheet'!J9 -> -20.166878 | G9: ='Balance sheet'!J9-'Balance sheet'!K9 -> -23.167593
A10: Total current assets
A11: PROPERTY AND EQUIPMENT
A12: Aircraft and related equipment
A13: Package handling and ground support equipment
A14: Information technology
A15: Vehicles and trailers
A16: Facilities and other
A17: Total PP&E
A18: Depreciation and amortization
A19: Net PP&E | B19: ='Balance sheet'!E19-'Balance sheet'!F19 -> -151 | C19: ='Balance sheet'!F19-'Balance sheet'!G19 -> -4195.9134 | D19: ='Balance sheet'!G19-'Balance sheet'!H19 -> -2246.0687 | E19: ='Balance sheet'!H19-'Balance sheet'!I19 -> -2221.1898 | F19: ='Balance sheet'!I19-'Balance sheet'!J19 -> -2171.432 | G19: ='Balance sheet'!J19-'Balance sheet'!K19 -> -2146.553
A20: OTHER LONG-TERM ASSETS | B20: ='Balance sheet'!E20-'Balance sheet'!F20 -> -2974 | C20: ='Balance sheet'!F20-'Balance sheet'!G20 -> 0 | D20: ='Balance sheet'!G20-'Balance sheet'!H20 -> 0 | E20: ='Balance sheet'!H20-'Balance sheet'!I20 -> 0 | F20: ='Balance sheet'!I20-'Balance sheet'!J20 -> 0 | G20: ='Balance sheet'!J20-'Balance sheet'!K20 -> 0
A21: Operating lease right-of-use assets | B21: ='Balance sheet'!E21-'Balance sheet'!F21 -> 662 | C21: ='Balance sheet'!F21-'Balance sheet'!G21 -> 700 | D21: ='Balance sheet'!G21-'Balance sheet'!H21 -> 650 | E21: ='Balance sheet'!H21-'Balance sheet'!I21 -> 600 | F21: ='Balance sheet'!I21-'Balance sheet'!J21 -> 500 | G21: ='Balance sheet'!J21-'Balance sheet'!K21 -> 400
A22: Goodwill | B22: ='Balance sheet'!E22-'Balance sheet'!F22 -> -180 | C22: ='Balance sheet'!F22-'Balance sheet'!G22 -> 0 | D22: ='Balance sheet'!G22-'Balance sheet'!H22 -> 0 | E22: ='Balance sheet'!H22-'Balance sheet'!I22 -> 0 | F22: ='Balance sheet'!I22-'Balance sheet'!J22 -> 0 | G22: ='Balance sheet'!J22-'Balance sheet'!K22 -> 0
A23: Other assets | B23: ='Balance sheet'!E23-'Balance sheet'!F23 -> -772 | C23: ='Balance sheet'!F23-'Balance sheet'!G23 -> 349.51532 | D23: ='Balance sheet'!G23-'Balance sheet'!H23 -> -77.252039 | E23: ='Balance sheet'!H23-'Balance sheet'!I23 -> -94.651624 | F23: ='Balance sheet'!I23-'Balance sheet'!J23 -> -91.625615 | G23: ='Balance sheet'!J23-'Balance sheet'!K23 -> -94.041914
A24: Total other long-term assets
A25: TOTAL ASSETS
A26: LIABILITIES AND COMMON STOCKHOLDERS INVESTMENT
A27: CURRENT LIABILITIES
A28: Current portion of long-term debt | B28: ='Balance sheet'!F28-'Balance sheet'!E28 -> 1360 | C28: ='Balance sheet'!G28-'Balance sheet'!F28 -> -57 | D28: ='Balance sheet'!H28-'Balance sheet'!G28 -> 105 | E28: ='Balance sheet'!I28-'Balance sheet'!H28 -> -924 | F28: ='Balance sheet'!J28-'Balance sheet'!I28 -> 583 | G28: ='Balance sheet'!K28-'Balance sheet'!J28 -> 667
A29: Accrued salaries and employee benefits | B29: ='Balance sheet'!F29-'Balance sheet'!E29 -> 58 | C29: ='Balance sheet'!G29-'Balance sheet'!F29 -> -92.600487 | D29: ='Balance sheet'!H29-'Balance sheet'!G29 -> -17.563959 | E29: ='Balance sheet'!I29-'Balance sheet'!H29 -> 59.569706 | F29: ='Balance sheet'!J29-'Balance sheet'!I29 -> 57.884568 | G29: ='Balance sheet'!K29-'Balance sheet'!J29 -> 59.430774
A30: Accounts payable | B30: ='Balance sheet'!F30-'Balance sheet'!E30 -> 503 | C30: ='Balance sheet'!G30-'Balance sheet'!F30 -> 31.360867 | D30: ='Balance sheet'!H30-'Balance sheet'!G30 -> 15.853452 | E30: ='Balance sheet'!I30-'Balance sheet'!H30 -> 86.684073 | F30: ='Balance sheet'!J30-'Balance sheet'!I30 -> 80.479472 | G30: ='Balance sheet'!K30-'Balance sheet'!J30 -> 92.454353
A31: Operating lease liabilities | B31: ='Balance sheet'!F31-'Balance sheet'!E31 -> 102 | C31: ='Balance sheet'!G31-'Balance sheet'!F31 -> -202.05 | D31: ='Balance sheet'!H31-'Balance sheet'!G31 -> -97.5 | E31: ='Balance sheet'!I31-'Balance sheet'!H31 -> -90 | F31: ='Balance sheet'!J31-'Balance sheet'!I31 -> -75 | G31: ='Balance sheet'!K31-'Balance sheet'!J31 -> -60
A32: Accrued expenses | B32: ='Balance sheet'!F32-'Balance sheet'!E32 -> 33 | C32: ='Balance sheet'!G32-'Balance sheet'!F32 -> -123.9451 | D32: ='Balance sheet'!H32-'Balance sheet'!G32 -> 20.740143 | E32: ='Balance sheet'!I32-'Balance sheet'!H32 -> 113.40369 | F32: ='Balance sheet'!J32-'Balance sheet'!I32 -> 105.28658 | G32: ='Balance sheet'!K32-'Balance sheet'!J32 -> 120.95261
A33: Total current liabilities
A34: LONG-TERM DEBT | B34: ='Balance sheet'!F34-'Balance sheet'!E34 -> -984 | C34: ='Balance sheet'!G34-'Balance sheet'!F34 -> 2629 | D34: ='Balance sheet'!H34-'Balance sheet'!G34 -> 2524 | E34: ='Balance sheet'!I34-'Balance sheet'!H34 -> 3448 | F34: ='Balance sheet'!J34-'Balance sheet'!I34 -> 1865 | G34: ='Balance sheet'!K34-'Balance sheet'!J34 -> 1198
A35: OTHER LONG-TERM LIABILITIES | B35: ='Balance sheet'!F35-'Balance sheet'!E35 -> 0 | C35: ='Balance sheet'!G35-'Balance sheet'!F35 -> 0 | D35: ='Balance sheet'!H35-'Balance sheet'!G35 -> 0 | E35: ='Balance sheet'!I35-'Balance sheet'!H35 -> 0 | F35: ='Balance sheet'!J35-'Balance sheet'!I35 -> 0 | G35: ='Balance sheet'!K35-'Balance sheet'!J35 -> 0
A36: Deferred income taxes | B36: ='Balance sheet'!F36-'Balance sheet'!E36 -> -277 | C36: ='Balance sheet'!G36-'Balance sheet'!F36 -> 714.29444 | D36: ='Balance sheet'!H36-'Balance sheet'!G36 -> 216.8058 | E36: ='Balance sheet'!I36-'Balance sheet'!H36 -> 230.83787 | F36: ='Balance sheet'!J36-'Balance sheet'!I36 -> 193.74885 | G36: ='Balance sheet'!K36-'Balance sheet'!J36 -> 204.97284
A37: Pension | B37: ='Balance sheet'!F37-'Balance sheet'!E37 -> -312 | C37: ='Balance sheet'!G37-'Balance sheet'!F37 -> 199 | D37: ='Balance sheet'!H37-'Balance sheet'!G37 -> 42 | E37: ='Balance sheet'!I37-'Balance sheet'!H37 -> 61 | F37: ='Balance sheet'!J37-'Balance sheet'!I37 -> 63 | G37: ='Balance sheet'!K37-'Balance sheet'!J37 -> 74
A38: Self-insurance accruals | B38: ='Balance sheet'!F38-'Balance sheet'!E38 -> 332 | C38: ='Balance sheet'!G38-'Balance sheet'!F38 -> 307.78749 | D38: ='Balance sheet'!H38-'Balance sheet'!G38 -> 325.99608 | E38: ='Balance sheet'!I38-'Balance sheet'!H38 -> 422.83003 | F38: ='Balance sheet'!J38-'Balance sheet'!I38 -> 428.32357 | G38: ='Balance sheet'!K38-'Balance sheet'!J38 -> 459.46075
A39: Operating lease liabilities | B39: ='Balance sheet'!F39-'Balance sheet'!E39 -> -781 | C39: ='Balance sheet'!G39-'Balance sheet'!F39 -> -881.95 | D39: ='Balance sheet'!H39-'Balance sheet'!G39 -> -552.5 | E39: ='Balance sheet'!I39-'Balance sheet'!H39 -> -510 | F39: ='Balance sheet'!J39-'Balance sheet'!I39 -> -425 | G39: ='Balance sheet'!K39-'Balance sheet'!J39 -> -340
A40: Other Liabilities | B40: ='Balance sheet'!F40-'Balance sheet'!E40 -> 94 | C40: ='Balance sheet'!G40-'Balance sheet'!F40 -> -7.0943215 | D40: ='Balance sheet'!H40-'Balance sheet'!G40 -> 14.293672 | E40: ='Balance sheet'!I40-'Balance sheet'!H40 -> 17.513056 | F40: ='Balance sheet'!J40-'Balance sheet'!I40 -> 16.953164 | G40: ='Balance sheet'!K40-'Balance sheet'!J40 -> 17.400244
A41: Total other long-term liabilities
A42: COMMON STOCKHOLDERS INVESTMENT | B42: ='Balance sheet'!F42-'Balance sheet'!E42 -> 0 | C42: ='Balance sheet'!G42-'Balance sheet'!F42 -> 0 | D42: ='Balance sheet'!H42-'Balance sheet'!G42 -> 0 | E42: ='Balance sheet'!I42-'Balance sheet'!H42 -> 0 | F42: ='Balance sheet'!J42-'Balance sheet'!I42 -> 0 | G42: ='Balance sheet'!K42-'Balance sheet'!J42 -> 0
A43: Common stock, 0.10 par value | B43: ='Balance sheet'!F43-'Balance sheet'!E43 -> 0 | C43: ='Balance sheet'!G43-'Balance sheet'!F43 -> 0 | D43: ='Balance sheet'!H43-'Balance sheet'!G43 -> 0 | E43: ='Balance sheet'!I43-'Balance sheet'!H43 -> 0 | F43: ='Balance sheet'!J43-'Balance sheet'!I43 -> 0 | G43: ='Balance sheet'!K43-'Balance sheet'!J43 -> 0
A44: Additional paid-in capital | B44: ='Balance sheet'!F44-'Balance sheet'!E44 -> 302 | C44: ='Balance sheet'!G44-'Balance sheet'!F44 -> 202.25 | D44: ='Balance sheet'!H44-'Balance sheet'!G44 -> 202.25 | E44: ='Balance sheet'!I44-'Balance sheet'!H44 -> 202.25 | F44: ='Balance sheet'!J44-'Balance sheet'!I44 -> 202.25 | G44: ='Balance sheet'!K44-'Balance sheet'!J44 -> 202.25
A45: Retained earnings
A46: Accumulated other comprehensive loss | B46: ='Balance sheet'!F46-'Balance sheet'!E46 -> -3 | C46: ='Balance sheet'!G46-'Balance sheet'!F46 -> 0 | D46: ='Balance sheet'!H46-'Balance sheet'!G46 -> 0 | E46: ='Balance sheet'!I46-'Balance sheet'!H46 -> 0 | F46: ='Balance sheet'!J46-'Balance sheet'!I46 -> 0 | G46: ='Balance sheet'!K46-'Balance sheet'!J46 -> 0
A47: Treasury stock | B47: ='Balance sheet'!F47-'Balance sheet'!E47 -> -2560 | C47: ='Balance sheet'!G47-'Balance sheet'!F47 -> -2500 | D47: ='Balance sheet'!H47-'Balance sheet'!G47 -> -2500 | E47: ='Balance sheet'!I47-'Balance sheet'!H47 -> -2500 | F47: ='Balance sheet'!J47-'Balance sheet'!I47 -> -2500 | G47: ='Balance sheet'!K47-'Balance sheet'!J47 -> -2500
A48: Total common stockholders investment
A49: TOTAL LIABILITIES AND COMMON STOCKHOLDERS INVESTMENT
A51: Repurchases | C51: =C47 -> -2500 | D51: =D47 -> -2500 | E51: =E47 -> -2500 | F51: =F47 -> -2500 | G51: =G47 -> -2500
A52: Dividends | C52: =-'Balance sheet'!G158 -> -1328.4309 | D52: =-'Balance sheet'!H158 -> -1358.6001 | E52: =-'Balance sheet'!I158 -> -1393.1454 | F52: =-'Balance sheet'!J158 -> -1432.2469 | G52: =-'Balance sheet'!K158 -> -1476.1014
A54: Net Cash Generated | C54: =SUM(C2:C47)+C52 -> 806.21468 | D54: =SUM(D2:D47)+D52 -> 2861.7146 | E54: =SUM(E2:E47)+E52 -> 3008.6541 | F54: =SUM(F2:F47)+F52 -> 3023.4368 | G54: =SUM(G2:G47)+G52 -> 2406.2721
A56: Cash at Starting of Year | C56: ='Balance sheet'!F6 -> 5502 | D56: =C57 -> 6308.2147 | E56: =D57 -> 9169.9292 | F56: =E57 -> 12178.583 | G56: =F57 -> 15202.02
A57: Cash at Ending of Year | C57: =C56+C54 -> 6308.2147 | D57: =D56+D54 -> 9169.9292 | E57: =E56+E54 -> 12178.583 | F57: =F56+F54 -> 15202.02 | G57: =G56+G54 -> 17608.292
A59: FCFE | C59: =C54-C52-C51 -> 4634.6456 | D59: =D54-D52-D51 -> 6720.3146 | E59: =E54-E52-E51 -> 6901.7995 | F59: =F54-F52-F51 -> 6955.6837 | G59: =G54-G52-G51 -> 6382.3736
C61: =C59-C2 -> -277.56879 | D61: =D59-D2 -> 921.35684 | E61: =E59-E2 -> 1114.5173 | F61: =F59-F2 -> 1072.0357 | G61: =G59-G2 -> 568.24292

Sheet Comps
C1: USD
A2: COMPARABLE COMPANY ANALYSIS
A3: COMPANY DATA
A4: (in millions) | C4: Recent | D4: 52 week | E4: Shares | F4: Market | G4: Total | I4: Enterprise | J4: Book | L4: WS 12-mo
A5: Company Name | B5: Ticker | C5: Price | D5: High | E5: Out | F5: Cap | G5: Debt | H5: Cash | I5: Value | J5: Value | K5: Beta | L5: Price Target
A6: {=IF($B6="","",_xll.RDP.Data($B6,"TR.CompanyName"))} -> United Parcel Service Inc | B6: UPS | C6: =IF(B6="","",_xll.RDP.Data($B6,"TR.PriceClose","Curn=#1",,$C$1)) -> 86.62 | D6: =IF($B6="","",_xll.RDP.Data($B6,"MAX(TR.PriceHigh(SDate=0D,EDate=0D-364C))/*52 Week High*/","Curn=#1",,$C$1)) -> 145.01 | E6: =IF(B6="","",_xll.RDP.Data($B6,"TR.CompanySharesOutstanding(SDate=0)/*# Shares Outstanding*/")/1000000) -> 847.56964 | F6: =IF(B6="","",C6*E6) -> 73416.482 | G6: {=IF($B6="","",_xll.RDP.Data($B6,"TR.TotalDebtOutstanding","Curn=#1",,$C$1)/1000000)} -> 21284 | H6: =IF($B6="","",_xll.RDP.Data($B6,"TR.CashandEquivalents","Curn=#1",,$C$1)/1000000) -> 6112 | I6: =IF(B6="","",F6+G6-H6) -> 88588.482 | J6: {=IF($B6="","",_xll.RDP.Data($B6,"TR.TotalEquity","Curn=#1",,$C$1)/1000000)} -> 16718 | K6: =IF($B6="","",_xll.RDP.Data($B6,"TR.BetaFiveYear/*Beta 5 Year Monthly*//*Beta 5 Year Monthly*/")) -> 1.0738736 | L6: =IF(B6="","",_xll.RDP.Data($B6,"TR.PriceTargetMean","Curn=#1",,$C$1)) -> 102.18464
A7: {=IF($B7="","",_xll.RDP.Data($B7,"TR.CompanyName"))} -> J B Hunt Transport Services Inc | B7: JBHT.O | C7: =IF(B7="","",_xll.RDP.Data($B7,"TR.PriceClose","Curn=#1",,$C$1)) -> 141.67 | D7: =IF($B7="","",_xll.RDP.Data($B7,"MAX(TR.PriceHigh(SDate=0D,EDate=0D-364C))/*52 Week High*/","Curn=#1",,$C$1)) -> 200.4 | E7: =IF(B7="","",_xll.RDP.Data($B7,"TR.CompanySharesOutstanding(SDate=0)/*# Shares Outstanding*/")/1000000) -> 96.799281 | F7: =IF(B7="","",C7*E7) -> 13713.554 | G7: {=IF($B7="","",_xll.RDP.Data($B7,"TR.TotalDebtOutstanding","Curn=#1",,$C$1)/1000000)} -> 1477.702 | H7: =IF($B7="","",_xll.RDP.Data($B7,"TR.CashandEquivalents","Curn=#1",,$C$1)/1000000) -> 46.983 | I7: =IF(B7="","",F7+G7-H7) -> 15144.273 | J7: {=IF($B7="","",_xll.RDP.Data($B7,"TR.TotalEquity","Curn=#1",,$C$1)/1000000)} -> 4014.505 | K7: =IF($B7="","",_xll.RDP.Data($B7,"TR.BetaFiveYear/*Beta 5 Year Monthly*//*Beta 5 Year Monthly*/")) -> 1.244103 | L7: =IF(B7="","",_xll.RDP.Data($B7,"TR.PriceTargetMean","Curn=#1",,$C$1)) -> 155.1787
A8: {=IF($B8="","",_xll.RDP.Data($B8,"TR.CompanyName"))} -> Deutsche Post AG | B8: DHLN.DE | C8: =IF(B8="","",_xll.RDP.Data($B8,"TR.PriceClose","Curn=#1",,$C$1)) -> 46.902851 | D8: =IF($B8="","",_xll.RDP.Data($B8,"MAX(TR.PriceHigh(SDate=0D,EDate=0D-364C))/*52 Week High*/","Curn=#1",,$C$1)) -> 49.431526 | E8: =IF(B8="","",_xll.RDP.Data($B8,"TR.CompanySharesOutstanding(SDate=0)/*# Shares Outstanding*/")/1000000) -> 1200 | F8: =IF(B8="","",C8*E8) -> 56283.421 | G8: {=IF($B8="","",_xll.RDP.Data($B8,"TR.TotalDebtOutstanding","Curn=#1",,$C$1)/1000000)} -> 25003.624 | H8: =IF($B8="","",_xll.RDP.Data($B8,"TR.CashandEquivalents","Curn=#1",,$C$1)/1000000) -> 1472.2021 | I8: =IF(B8="","",F8+G8-H8) -> 79814.842 | J8: {=IF($B8="","",_xll.RDP.Data($B8,"TR.TotalEquity","Curn=#1",,$C$1)/1000000)} -> 24632.985 | K8: =IF($B8="","",_xll.RDP.Data($B8,"TR.BetaFiveYear/*Beta 5 Year Monthly*//*Beta 5 Year Monthly*/")) -> 1.1003063 | L8: =IF(B8="","",_xll.RDP.Data($B8,"TR.PriceTargetMean","Curn=#1",,$C$1)) -> 50.583111
A9: {=IF($B9="","",_xll.RDP.Data($B9,"TR.CompanyName"))} -> CH Robinson Worldwide Inc | B9: CHRW.O | C9: =IF(B9="","",_xll.RDP.Data($B9,"TR.PriceClose","Curn=#1",,$C$1)) -> 134.36 | D9: =IF($B9="","",_xll.RDP.Data($B9,"MAX(TR.PriceHigh(SDate=0D,EDate=0D-364C))/*52 Week High*/","Curn=#1",,$C$1)) -> 137.996 | E9: =IF(B9="","",_xll.RDP.Data($B9,"TR.CompanySharesOutstanding(SDate=0)/*# Shares Outstanding*/")/1000000) -> 118.09116 | F9: =IF(B9="","",C9*E9) -> 15866.729 | G9: {=IF($B9="","",_xll.RDP.Data($B9,"TR.TotalDebtOutstanding","Curn=#1",,$C$1)/1000000)} -> 1411.446 | H9: =IF($B9="","",_xll.RDP.Data($B9,"TR.CashandEquivalents","Curn=#1",,$C$1)/1000000) -> 145.762 | I9: =IF(B9="","",F9+G9-H9) -> 17132.413 | J9: {=IF($B9="","",_xll.RDP.Data($B9,"TR.TotalEquity","Curn=#1",,$C$1)/1000000)} -> 1722.051 | K9: =IF($B9="","",_xll.RDP.Data($B9,"TR.BetaFiveYear/*Beta 5 Year Monthly*//*Beta 5 Year Monthly*/")) -> 0.86907517 | L9: =IF(B9="","",_xll.RDP.Data($B9,"TR.PriceTargetMean","Curn=#1",,$C$1)) -> 129.12958
A10: {=IF($B10="","",_xll.RDP.Data($B10,"TR.CompanyName"))} -> FedEx Corp | B10: FDX | C10: =IF(B10="","",_xll.RDP.Data($B10,"TR.PriceClose","Curn=#1",,$C$1)) -> 247.03 | D10: =IF($B10="","",_xll.RDP.Data($B10,"MAX(TR.PriceHigh(SDate=0D,EDate=0D-364C))/*52 Week High*/","Curn=#1",,$C$1)) -> 308.53 | E10: =IF(B10="","",_xll.RDP.Data($B10,"TR.CompanySharesOutstanding(SDate=0)/*# Shares Outstanding*/")/1000000) -> 235.95546 | F10: =IF(B10="","",C10*E10) -> 58288.078 | G10: {=IF($B10="","",_xll.RDP.Data($B10,"TR.TotalDebtOutstanding","Curn=#1",,$C$1)/1000000)} -> 20579 | H10: =IF($B10="","",_xll.RDP.Data($B10,"TR.CashandEquivalents","Curn=#1",,$C$1)/1000000) -> 5502 | I10: =IF(B10="","",F10+G10-H10) -> 73365.078 | J10: {=IF($B10="","",_xll.RDP.Data($B10,"TR.TotalEquity","Curn=#1",,$C$1)/1000000)} -> 28074 | K10: =IF($B10="","",_xll.RDP.Data($B10,"TR.BetaFiveYear/*Beta 5 Year Monthly*//*Beta 5 Year Monthly*/")) -> 1.3133555 | L10: =IF(B10="","",_xll.RDP.Data($B10,"TR.PriceTargetMean","Curn=#1",,$C$1)) -> 266.62
A12: I/B/E/S ESTIMATES
C13: SALES | G13: EPS | K13: EBIT | N13: EBITDA | Q13: EPS 5-yr
A14: Company Name | B14: Ticker | C14: Last FY | D14: FYR1 | E14: FYR2 | F14: FYR3 | G14: Last FY | H14: FYR1 | I14: FYR2 | J14: FYR3 | K14: Last FY | L14: FYR1 | M14: FYR2 | N14: Last FY | O14: FYR1 | P14: FYR2 | Q14: Growth %
A15: =A6 -> United Parcel Service Inc | B15: =IF(B6="","",B6) -> UPS | C15: {=IF($B15="","",_xll.RDP.Data($B15,"TR.Revenue","Curn=#1",,$C$1)/1000000)} -> 91070 | D15: {=IF($B15="","",_xll.RDP.Data($B15,"TR.RevenueMean","Period=FY1 Frq=D SDate=1D Curn=#1",,$C$1)/1000000)} -> 87558.921 | E15: {=IF($B15="","",_xll.RDP.Data($B15,"TR.RevenueMean","Period=FY2 Frq=D SDate=1D Curn=#1",,$C$1)/1000000)} -> 87803.754 | F15: {=IF($B15="","",_xll.RDP.Data($B15,"TR.RevenueMean","Period=FY3 Frq=D SDate=1D Curn=#1",,$C$1)/1000000)} -> 91023.347 | G15: =IF($B15="","",_xll.RDP.Data($B15,"TR.EPSMean","Period=FY0 Frq=D SDate=1D Curn=#1",,$C$1)) -> 7.49454 | H15: =IF($B15="","",_xll.RDP.Data($B15,"TR.EPSMean","Period=FY1 Frq=D SDate=1D Curn=#1",,$C$1)) -> 6.50727 | I15: =IF($B15="","",_xll.RDP.Data($B15,"TR.EPSMean","Period=FY2 Frq=D SDate=1D Curn=#1",,$C$1)) -> 7.19217 | J15: =IF($B15="","",_xll.RDP.Data($B15,"TR.EPSMean","Period=FY3 Frq=D SDate=1D Curn=#1",,$C$1)) -> 7.902 | K15: {=IF($B15="","",_xll.RDP.Data($B15,"TR.EBITMean","Period=FY0 Frq=D SDate=1D Curn=#1",,$C$1)/1000000)} -> 8684.2355 | L15: {=IF($B15="","",_xll.RDP.Data($B15,"TR.EBITMean","Period=FY1 Frq=D SDate=1D Curn=#1",,$C$1)/1000000)} -> 7787.0016 | M15: {=IF($B15="","",_xll.RDP.Data($B15,"TR.EBITMean","Period=FY2 Frq=D SDate=1D Curn=#1",,$C$1)/1000000)} -> 8548.4642 | N15: {=IF($B15="","",_xll.RDP.Data($B15,"TR.EBITDAMean","Period=FY0 Frq=D SDate=1D Curn=#1",,$C$1)/1000000)} -> 12286.924 | O15: {=IF($B15="","",_xll.RDP.Data($B15,"TR.EBITDAMean","Period=FY1 Frq=D SDate=1D Curn=#1",,$C$1)/1000000)} -> 11436.953 | P15: {=IF($B15="","",_xll.RDP.Data($B15,"TR.EBITDAMean","Period=FY2 Frq=D SDate=1D Curn=#1",,$C$1)/1000000)} -> 12250.186 | Q15: {=IF($B15="","",_xll.RDP.Data($B15,"TR.LTGMean",,)/100)} -> 0.01375
A16: =A7 -> J B Hunt Transport Services Inc | B16: =IF(B7="","",B7) -> JBHT.O | C16: {=IF($B16="","",_xll.RDP.Data($B16,"TR.Revenue","Curn=#1",,$C$1)/1000000)} -> 12087.204 | D16: {=IF($B16="","",_xll.RDP.Data($B16,"TR.RevenueMean","Period=FY1 Frq=D SDate=1D Curn=#1",,$C$1)/1000000)} -> 11993.223 | E16: {=IF($B16="","",_xll.RDP.Data($B16,"TR.RevenueMean","Period=FY2 Frq=D SDate=1D Curn=#1",,$C$1)/1000000)} -> 12586.922 | F16: {=IF($B16="","",_xll.RDP.Data($B16,"TR.RevenueMean","Period=FY3 Frq=D SDate=1D Curn=#1",,$C$1)/1000000)} -> 13258.713 | G16: =IF($B16="","",_xll.RDP.Data($B16,"TR.EPSMean","Period=FY0 Frq=D SDate=1D Curn=#1",,$C$1)) -> 5.6403 | H16: =IF($B16="","",_xll.RDP.Data($B16,"TR.EPSMean","Period=FY1 Frq=D SDate=1D Curn=#1",,$C$1)) -> 5.55527 | I16: =IF($B16="","",_xll.RDP.Data($B16,"TR.EPSMean","Period=FY2 Frq=D SDate=1D Curn=#1",,$C$1)) -> 6.79377 | J16: =IF($B16="","",_xll.RDP.Data($B16,"TR.EPSMean","Period=FY3 Frq=D SDate=1D Curn=#1",,$C$1)) -> 8.11991 | K16: {=IF($B16="","",_xll.RDP.Data($B16,"TR.EBITMean","Period=FY0 Frq=D SDate=1D Curn=#1",,$C$1)/1000000)} -> 847.83078 | L16: {=IF($B16="","",_xll.RDP.Data($B16,"TR.EBITMean","Period=FY1 Frq=D SDate=1D Curn=#1",,$C$1)/1000000)} -> 806.62633 | M16: {=IF($B16="","",_xll.RDP.Data($B16,"TR.EBITMean","Period=FY2 Frq=D SDate=1D Curn=#1",,$C$1)/1000000)} -> 941.17477 | N16: {=IF($B16="","",_xll.RDP.Data($B16,"TR.EBITDAMean","Period=FY0 Frq=D SDate=1D Curn=#1",,$C$1)/1000000)} -> 1599.2676 | O16: {=IF($B16="","",_xll.RDP.Data($B16,"TR.EBITDAMean","Period=FY1 Frq=D SDate=1D Curn=#1",,$C$1)/1000000)} -> 1532.4638 | P16: {=IF($B16="","",_xll.RDP.Data($B16,"TR.EBITDAMean","Period=FY2 Frq=D SDate=1D Curn=#1",,$C$1)/1000000)} -> 1703.5883 | Q16: {=IF($B16="","",_xll.RDP.Data($B16,"TR.LTGMean",,)/100)} -> 0.131
A17: =A8 -> Deutsche Post AG | B17: =IF(B8="","",B8) -> DHLN.DE | C17: {=IF($B17="","",_xll.RDP.Data($B17,"TR.Revenue","Curn=#1",,$C$1)/1000000)} -> 87158.091 | D17: {=IF($B17="","",_xll.RDP.Data($B17,"TR.RevenueMean","Period=FY1 Frq=D SDate=1D Curn=#1",,$C$1)/1000000)} -> 97142.373 | E17: {=IF($B17="","",_xll.RDP.Data($B17,"TR.RevenueMean","Period=FY2 Frq=D SDate=1D Curn=#1",,$C$1)/1000000)} -> 99609.137 | F17: {=IF($B17="","",_xll.RDP.Data($B17,"TR.RevenueMean","Period=FY3 Frq=D SDate=1D Curn=#1",,$C$1)/1000000)} -> 103373.08 | G17: =IF($B17="","",_xll.RDP.Data($B17,"TR.EPSMean","Period=FY0 Frq=D SDate=1D Curn=#1",,$C$1)) -> 3.0532176 | H17: =IF($B17="","",_xll.RDP.Data($B17,"TR.EPSMean","Period=FY1 Frq=D SDate=1D Curn=#1",,$C$1)) -> 3.4536545 | I17: =IF($B17="","",_xll.RDP.Data($B17,"TR.EPSMean","Period=FY2 Frq=D SDate=1D Curn=#1",,$C$1)) -> 3.8056297 | J17: =IF($B17="","",_xll.RDP.Data($B17,"TR.EPSMean","Period=FY3 Frq=D SDate=1D Curn=#1",,$C$1)) -> 4.2056088 | K17: {=IF($B17="","",_xll.RDP.Data($B17,"TR.EBITMean","Period=FY0 Frq=D SDate=1D Curn=#1",,$C$1)/1000000)} -> 6334.258 | L17: {=IF($B17="","",_xll.RDP.Data($B17,"TR.EBITMean","Period=FY1 Frq=D SDate=1D Curn=#1",,$C$1)/1000000)} -> 6940.4726 | M17: {=IF($B17="","",_xll.RDP.Data($B17,"TR.EBITMean","Period=FY2 Frq=D SDate=1D Curn=#1",,$C$1)/1000000)} -> 7387.9399 | N17: {=IF($B17="","",_xll.RDP.Data($B17,"TR.EBITDAMean","Period=FY0 Frq=D SDate=1D Curn=#1",,$C$1)/1000000)} -> 11462.678 | O17: {=IF($B17="","",_xll.RDP.Data($B17,"TR.EBITDAMean","Period=FY1 Frq=D SDate=1D Curn=#1",,$C$1)/1000000)} -> 12534.163 | P17: {=IF($B17="","",_xll.RDP.Data($B17,"TR.EBITDAMean","Period=FY2 Frq=D SDate=1D Curn=#1",,$C$1)/1000000)} -> 13111.967 | Q17: {=IF($B17="","",_xll.RDP.Data($B17,"TR.LTGMean",,)/100)} -> 0.073 | R17: Not available
A18: =A9 -> CH Robinson Worldwide Inc | B18: =IF(B9="","",B9) -> CHRW.O | C18: {=IF($B18="","",_xll.RDP.Data($B18,"TR.Revenue","Curn=#1",,$C$1)/1000000)} -> 17724.956 | D18: {=IF($B18="","",_xll.RDP.Data($B18,"TR.RevenueMean","Period=FY1 Frq=D SDate=1D Curn=#1",,$C$1)/1000000)} -> 16495.282 | E18: {=IF($B18="","",_xll.RDP.Data($B18,"TR.RevenueMean","Period=FY2 Frq=D SDate=1D Curn=#1",,$C$1)/1000000)} -> 17123.071 | F18: {=IF($B18="","",_xll.RDP.Data($B18,"TR.RevenueMean","Period=FY3 Frq=D SDate=1D Curn=#1",,$C$1)/1000000)} -> 18036.166 | G18: =IF($B18="","",_xll.RDP.Data($B18,"TR.EPSMean","Period=FY0 Frq=D SDate=1D Curn=#1",,$C$1)) -> 4.39652 | H18: =IF($B18="","",_xll.RDP.Data($B18,"TR.EPSMean","Period=FY1 Frq=D SDate=1D Curn=#1",,$C$1)) -> 4.92671 | I18: =IF($B18="","",_xll.RDP.Data($B18,"TR.EPSMean","Period=FY2 Frq=D SDate=1D Curn=#1",,$C$1)) -> 5.57556 | J18: =IF($B18="","",_xll.RDP.Data($B18,"TR.EPSMean","Period=FY3 Frq=D SDate=1D Curn=#1",,$C$1)) -> 5.98873 | K18: {=IF($B18="","",_xll.RDP.Data($B18,"TR.EBITMean","Period=FY0 Frq=D SDate=1D Curn=#1",,$C$1)/1000000)} -> 757.25444 | L18: {=IF($B18="","",_xll.RDP.Data($B18,"TR.EBITMean","Period=FY1 Frq=D SDate=1D Curn=#1",,$C$1)/1000000)} -> 811.79965 | M18: {=IF($B18="","",_xll.RDP.Data($B18,"TR.EBITMean","Period=FY2 Frq=D SDate=1D Curn=#1",,$C$1)/1000000)} -> 888.73405 | N18: {=IF($B18="","",_xll.RDP.Data($B18,"TR.EBITDAMean","Period=FY0 Frq=D SDate=1D Curn=#1",,$C$1)/1000000)} -> 839.5036 | O18: {=IF($B18="","",_xll.RDP.Data($B18,"TR.EBITDAMean","Period=FY1 Frq=D SDate=1D Curn=#1",,$C$1)/1000000)} -> 913.43505 | P18: {=IF($B18="","",_xll.RDP.Data($B18,"TR.EBITDAMean","Period=FY2 Frq=D SDate=1D Curn=#1",,$C$1)/1000000)} -> 993.22852 | Q18: {=IF($B18="","",_xll.RDP.Data($B18,"TR.LTGMean",,)/100)} -> 0.1291667 | R18: Not available
A19: =A10 -> FedEx Corp | B19: =IF(B10="","",B10) -> FDX | C19: {=IF($B19="","",_xll.RDP.Data($B19,"TR.Revenue","Curn=#1",,$C$1)/1000000)} -> 87926 | D19: {=IF($B19="","",_xll.RDP.Data($B19,"TR.RevenueMean","Period=FY1 Frq=D SDate=1D Curn=#1",,$C$1)/1000000)} -> 91412.886 | E19: {=IF($B19="","",_xll.RDP.Data($B19,"TR.RevenueMean","Period=FY2 Frq=D SDate=1D Curn=#1",,$C$1)/1000000)} -> 95149.829 | F19: {=IF($B19="","",_xll.RDP.Data($B19,"TR.RevenueMean","Period=FY3 Frq=D SDate=1D Curn=#1",,$C$1)/1000000)} -> 98971.009 | G19: =IF($B19="","",_xll.RDP.Data($B19,"TR.EPSMean","Period=FY0 Frq=D SDate=1D Curn=#1",,$C$1)) -> 18.008 | H19: =IF($B19="","",_xll.RDP.Data($B19,"TR.EPSMean","Period=FY1 Frq=D SDate=1D Curn=#1",,$C$1)) -> 18.02807 | I19: =IF($B19="","",_xll.RDP.Data($B19,"TR.EPSMean","Period=FY2 Frq=D SDate=1D Curn=#1",,$C$1)) -> 20.83456 | J19: =IF($B19="","",_xll.RDP.Data($B19,"TR.EPSMean","Period=FY3 Frq=D SDate=1D Curn=#1",,$C$1)) -> 23.31733 | K19: {=IF($B19="","",_xll.RDP.Data($B19,"TR.EBITMean","Period=FY0 Frq=D SDate=1D Curn=#1",,$C$1)/1000000)} -> 5982.1201 | L19: {=IF($B19="","",_xll.RDP.Data($B19,"TR.EBITMean","Period=FY1 Frq=D SDate=1D Curn=#1",,$C$1)/1000000)} -> 5905.2374 | M19: {=IF($B19="","",_xll.RDP.Data($B19,"TR.EBITMean","Period=FY2 Frq=D SDate=1D Curn=#1",,$C$1)/1000000)} -> 6613.2781 | N19: {=IF($B19="","",_xll.RDP.Data($B19,"TR.EBITDAMean","Period=FY0 Frq=D SDate=1D Curn=#1",,$C$1)/1000000)} -> 10287.836 | O19: {=IF($B19="","",_xll.RDP.Data($B19,"TR.EBITDAMean","Period=FY1 Frq=D SDate=1D Curn=#1",,$C$1)/1000000)} -> 10329.18 | P19: {=IF($B19="","",_xll.RDP.Data($B19,"TR.EBITDAMean","Period=FY2 Frq=D SDate=1D Curn=#1",,$C$1)/1000000)} -> 11202.511 | Q19: {=IF($B19="","",_xll.RDP.Data($B19,"TR.LTGMean",,)/100)} -> 0.104125
A21: VALUATION MULTIPLES
C22: Recent | D22: Price / | E22: Price/Sales | H22: P/E | K22: PEG | N22: EV/EBITDA | Q22: SAME STORE SALES GROWTH
A23: Company Name | B23: Ticker | C23: Price | D23: Book | E23: FYR1 | F23: FYR2 | G23: FYR3 | H23: FYR1 | I23: FYR2 | J23: FYR3 | K23: FYR1 | L23: FYR2 | M23: FYR3 | N23: Last FY | O23: FYR1 | P23: FYR2
A24: =A6 -> United Parcel Service Inc | B24: =IF(B6="","",B6) -> UPS | C24: =IF(C6="","",C6) -> 86.62 | D24: =IF(OR(B24="",ISNUMBER(F6)=FALSE,ISNUMBER(J6)=FALSE),"",F6/J6) -> 4.3914632 | E24: =IF(OR($B24="",ISNUMBER($F6)=FALSE,ISNUMBER(D15)=FALSE),"",$F6/D15) -> 0.8384809 | F24: =IF(OR($B24="",ISNUMBER($F6)=FALSE,ISNUMBER(E15)=FALSE),"",$F6/E15) -> 0.83614286 | G24: =IF(OR($B24="",ISNUMBER($F6)=FALSE,ISNUMBER(F15)=FALSE),"",$F6/F15) -> 0.8065676 | H24: =IF(OR($B24="",ISNA(H15)=TRUE),"",$C6/H15) -> 13.311266 | I24: =IF(OR($B24="",ISNA(I15)=TRUE),"",$C6/I15) -> 12.043653 | J24: =IF(OR($B24="",ISNA(J15)=TRUE),"",$C6/J15) -> 10.961782 | K24: =IF(OR($B24="",H24="",ISNA($Q15)=TRUE),"",H24/$Q15/100) -> 9.6809205 | L24: =IF(OR($B24="",I24="",ISNA($Q15)=TRUE),"",I24/$Q15/100) -> 8.7590204 | M24: =IF(OR($B24="",J24="",ISNA($Q15)=TRUE),"",J24/$Q15/100) -> 7.972205 | N24: =IF(OR($B24="",ISNA($I6)=TRUE,ISNA(N15)=TRUE),"",$I6/N15) -> 7.2099803 | O24: =IF(OR($B24="",ISNA($I6)=TRUE,ISNA(O15)=TRUE),"",$I6/O15) -> 7.7458114 | P24: =IF(OR($B24="",ISNA($I6)=TRUE,ISNA(P15)=TRUE),"",$I6/P15) -> 7.2316028
A25: =A7 -> J B Hunt Transport Services Inc | B25: =IF(B7="","",B7) -> JBHT.O | C25: =IF(C7="","",C7) -> 141.67 | D25: =IF(OR(B25="",ISNUMBER(F7)=FALSE,ISNUMBER(J7)=FALSE),"",F7/J7) -> 3.4160013 | E25: =IF(OR($B25="",ISNUMBER($F7)=FALSE,ISNUMBER(D16)=FALSE),"",$F7/D16) -> 1.1434419 | F25: =IF(OR($B25="",ISNUMBER($F7)=FALSE,ISNUMBER(E16)=FALSE),"",$F7/E16) -> 1.0895082 | G25: =IF(OR($B25="",ISNUMBER($F7)=FALSE,ISNUMBER(F16)=FALSE),"",$F7/F16) -> 1.0343051 | H25: =IF(OR($B25="",ISNA(H16)=TRUE),"",$C7/H16) -> 25.501911 | I25: =IF(OR($B25="",ISNA(I16)=TRUE),"",$C7/I16) -> 20.852928 | J25: =IF(OR($B25="",ISNA(J16)=TRUE),"",$C7/J16) -> 17.447238 | K25: =IF(OR($B25="",H25="",ISNA($Q16)=TRUE),"",H25/$Q16/100) -> 1.9467107 | L25: =IF(OR($B25="",I25="",ISNA($Q16)=TRUE),"",I25/$Q16/100) -> 1.5918266 | M25: =IF(OR($B25="",J25="",ISNA($Q16)=TRUE),"",J25/$Q16/100) -> 1.3318502 | N25: =IF(OR($B25="",ISNA($I7)=TRUE,ISNA(N16)=TRUE),"",$I7/N16) -> 9.4695054 | O25: =IF(OR($B25="",ISNA($I7)=TRUE,ISNA(O16)=TRUE),"",$I7/O16) -> 9.882304 | P25: =IF(OR($B25="",ISNA($I7)=TRUE,ISNA(P16)=TRUE),"",$I7/P16) -> 8.8896321
A26: =A8 -> Deutsche Post AG | B26: =IF(B8="","",B8) -> DHLN.DE | C26: =IF(C8="","",C8) -> 46.902851 | D26: =IF(OR(B26="",ISNUMBER(F8)=FALSE,ISNUMBER(J8)=FALSE),"",F8/J8) -> 2.2848803 | E26: =IF(OR($B26="",ISNUMBER($F8)=FALSE,ISNUMBER(D17)=FALSE),"",$F8/D17) -> 0.57939104 | F26: =IF(OR($B26="",ISNUMBER($F8)=FALSE,ISNUMBER(E17)=FALSE),"",$F8/E17) -> 0.56504275 | G26: =IF(OR($B26="",ISNUMBER($F8)=FALSE,ISNUMBER(F17)=FALSE),"",$F8/F17) -> 0.54446882 | H26: =IF(OR($B26="",ISNA(H17)=TRUE),"",$C8/H17) -> 13.580643 | I26: =IF(OR($B26="",ISNA(I17)=TRUE),"",$C8/I17) -> 12.324597 | J26: =IF(OR($B26="",ISNA(J17)=TRUE),"",$C8/J17) -> 11.152452 | K26: =IF(OR($B26="",H26="",ISNA($Q17)=TRUE),"",H26/$Q17/100) -> 1.8603621 | L26: =IF(OR($B26="",I26="",ISNA($Q17)=TRUE),"",I26/$Q17/100) -> 1.6883009 | M26: =IF(OR($B26="",J26="",ISNA($Q17)=TRUE),"",J26/$Q17/100) -> 1.5277332 | N26: =IF(OR($B26="",ISNA($I8)=TRUE,ISNA(N17)=TRUE),"",$I8/N17) -> 6.9630188 | O26: =IF(OR($B26="",ISNA($I8)=TRUE,ISNA(O17)=TRUE),"",$I8/O17) -> 6.3677839 | P26: =IF(OR($B26="",ISNA($I8)=TRUE,ISNA(P17)=TRUE),"",$I8/P17) -> 6.0871753
A27: =A9 -> CH Robinson Worldwide Inc | B27: =IF(B9="","",B9) -> CHRW.O | C27: =IF(C9="","",C9) -> 134.36 | D27: =IF(OR(B27="",ISNUMBER(F9)=FALSE,ISNUMBER(J9)=FALSE),"",F9/J9) -> 9.2138552 | E27: =IF(OR($B27="",ISNUMBER($F9)=FALSE,ISNUMBER(D18)=FALSE),"",$F9/D18) -> 0.96189498 | F27: =IF(OR($B27="",ISNUMBER($F9)=FALSE,ISNUMBER(E18)=FALSE),"",$F9/E18) -> 0.92662868 | G27: =IF(OR($B27="",ISNUMBER($F9)=FALSE,ISNUMBER(F18)=FALSE),"",$F9/F18) -> 0.87971737 | H27: =IF(OR($B27="",ISNA(H18)=TRUE),"",$C9/H18) -> 27.271749 | I27: =IF(OR($B27="",ISNA(I18)=TRUE),"",$C9/I18) -> 24.098028 | J27: =IF(OR($B27="",ISNA(J18)=TRUE),"",$C9/J18) -> 22.435475 | K27: =IF(OR($B27="",H27="",ISNA($Q18)=TRUE),"",H27/$Q18/100) -> 2.1113607 | L27: =IF(OR($B27="",I27="",ISNA($Q18)=TRUE),"",I27/$Q18/100) -> 1.8656533 | M27: =IF(OR($B27="",J27="",ISNA($Q18)=TRUE),"",J27/$Q18/100) -> 1.7369395 | N27: =IF(OR($B27="",ISNA($I9)=TRUE,ISNA(N18)=TRUE),"",$I9/N18) -> 20.407789 | O27: =IF(OR($B27="",ISNA($I9)=TRUE,ISNA(O18)=TRUE),"",$I9/O18) -> 18.756027 | P27: =IF(OR($B27="",ISNA($I9)=TRUE,ISNA(P18)=TRUE),"",$I9/P18) -> 17.249215
A28: =A10 -> FedEx Corp | B28: =IF(B10="","",B10) -> FDX | C28: =IF(C10="","",C10) -> 247.03 | D28: =IF(OR(B28="",ISNUMBER(F10)=FALSE,ISNUMBER(J10)=FALSE),"",F10/J10) -> 2.0762299 | E28: =IF(OR($B28="",ISNUMBER($F10)=FALSE,ISNUMBER(D19)=FALSE),"",$F10/D19) -> 0.63763524 | F28: =IF(OR($B28="",ISNUMBER($F10)=FALSE,ISNUMBER(E19)=FALSE),"",$F10/E19) -> 0.61259256 | G28: =IF(OR($B28="",ISNUMBER($F10)=FALSE,ISNUMBER(F19)=FALSE),"",$F10/F19) -> 0.58894092 | H28: =IF(OR($B28="",ISNA(H19)=TRUE),"",$C10/H19) -> 13.702521 | I28: =IF(OR($B28="",ISNA(I19)=TRUE),"",$C10/I19) -> 11.856742 | J28: =IF(OR($B28="",ISNA(J19)=TRUE),"",$C10/J19) -> 10.594266 | K28: =IF(OR($B28="",H28="",ISNA($Q19)=TRUE),"",H28/$Q19/100) -> 1.3159684 | L28: =IF(OR($B28="",I28="",ISNA($Q19)=TRUE),"",I28/$Q19/100) -> 1.1387027 | M28: =IF(OR($B28="",J28="",ISNA($Q19)=TRUE),"",J28/$Q19/100) -> 1.0174565 | N28: =IF(OR($B28="",ISNA($I10)=TRUE,ISNA(N19)=TRUE),"",$I10/N19) -> 7.1312445 | O28: =IF(OR($B28="",ISNA($I10)=TRUE,ISNA(O19)=TRUE),"",$I10/O19) -> 7.1027007 | P28: =IF(OR($B28="",ISNA($I10)=TRUE,ISNA(P19)=TRUE),"",$I10/P19) -> 6.5489852
C30: Average | D30: =AVERAGE(D24:D27) -> 4.82655 | E30: =AVERAGE(E24:E27) -> 0.88080221 | F30: =AVERAGE(F24:F27) -> 0.85433061 | G30: =AVERAGE(G24:G27) -> 0.81626472 | H30: =AVERAGE(H24:H27) -> 19.916392 | I30: =AVERAGE(I24:I27) -> 17.329802 | J30: =AVERAGE(J24:J27) -> 15.499237 | K30: =AVERAGE(K24,K26:K26) -> 5.7706413 | L30: =AVERAGE(L24,L26:L26) -> 5.2236607 | M30: =AVERAGE(M24,M26:M26) -> 4.7499691 | N30: =AVERAGE(N24:N27) -> 11.012573 | O30: =AVERAGE(O24:O27) -> 10.687982 | P30: =AVERAGE(P24:P27) -> 9.8644064
C31: Median | D31: =MEDIAN(D24:D27) -> 3.9037322 | E31: =MEDIAN(E24:E27) -> 0.90018794 | F31: =MEDIAN(F24:F27) -> 0.88138577 | G31: =MEDIAN(G24:G27) -> 0.84314249 | H31: =MEDIAN(H24:H27) -> 19.541277 | I31: =MEDIAN(I24:I27) -> 16.588763 | J31: =MEDIAN(J24:J27) -> 14.299845 | K31: =MEDIAN(K24,K26:K26) -> 5.7706413 | L31: =MEDIAN(L24,L26:L26) -> 5.2236607 | M31: =MEDIAN(M24,M26:M26) -> 4.7499691 | N31: =MEDIAN(N24:N27) -> 8.3397428 | O31: =MEDIAN(O24:O27) -> 8.8140577 | P31: =MEDIAN(P24:P27) -> 8.0606174
C33: Average | D33: =D30*$J$10/$E$10 -> 574.26331 | E33: =(E30*D$19)/$E$10 -> 341.23674 | F33: =(F30*E$19)/$E$10 -> 344.51168 | G33: =(G30*F$19)/$E$10 -> 342.38048 | H33: =H30*H$19 -> 359.05411 | I33: =I30*I$19 -> 361.05879 | J33: =J30*J$19 -> 361.40081 | K33: =K30*H$19*$Q$19*100 -> 1083.2491 | L33: =L30*I$19*$Q$19*100 -> 1133.2202 | M33: =M30*J$19*$Q$19*100 -> 1153.2531 | N33: =(N30*N$19-($G$10-$H$10))/$E$10 -> 416.25887 | O33: =(O30*O$19-($G$10-$H$10))/$E$10 -> 403.97917 | P33: =(P30*P$19-($G$10-$H$10))/$E$10 -> 404.437
C34: Median | D34: =D31*$J$10/$E$10 -> 464.46638 | E34: =(E31*D$19)/$E$10 -> 348.74708 | F34: =(F31*E$19)/$E$10 -> 355.42176 | G34: =(G31*F$19)/$E$10 -> 353.6543 | H34: =H31*H$19 -> 352.29151 | I34: =I31*I$19 -> 345.61957 | J34: =J31*J$19 -> 333.4342 | K34: =K31*H$19*$Q$19*100 -> 1083.2491 | L34: =L31*I$19*$Q$19*100 -> 1133.2202 | M34: =M31*J$19*$Q$19*100 -> 1153.2531 | N34: =(N31*N$19-($G$10-$H$10))/$E$10 -> 299.72144 | O34: =(O31*O$19-($G$10-$H$10))/$E$10 -> 321.94632 | P34: =(P31*P$19-($G$10-$H$10))/$E$10 -> 318.79811
D35: ws.OperatingProfitMargin[ws.cpa] | H35: ws.AssetTurnover[ws.cpa] | I35: ws.InventoryTurnover[ws.cpa] | J35: ws.ReceivablesTurnover[ws.cpa] | K35: ws.TotalDebtPctCommonEquity[ws.cpa] | L35: ws.LTDebtPctCommonEquity[ws.cpa] | M35: ws.LTDebtPctTotalCapital[ws.cpa] | N35: ws.QuickRatio[ws.cpa] | O35: ws.CurrentRatio[ws.cpa]
A36: RATIO ANALYSIS
C37: Gross | D37: Operating | E37: Net | H37: Asset | I37: Inventory | J37: Receivables | M37: Quick | N37: Current | O37: Interest
A38: Company Name | B38: Ticker | C38: Margin | D38: Margin | E38: Margin | F38: ROA | G38: ROE | H38: Turnvover | I38: Turnvover | J38: Turnvover | K38: Debt/E | L38: LTD/TC | M38: Ratio | N38: Ratio | O38: Coverage
A39: =A6 -> United Parcel Service Inc | B39: =IF(B15="","",B24) -> UPS | C39: {=IF($B39="","",_xll.RDP.Data($B39,"TR.GrossMargin")/100)} -> 0.802844 | D39: {=IF($B39="","",_xll.RDP.Data($B39,"TR.OperatingMarginPercent")/100)} -> 0.0929834 | E39: {=IF($B39="","",_xll.RDP.Data($B39,"TR.NetProfitMargin")/100)} -> 0.0634896 | F39: {=IF($B39="","",_xll.RDP.Data($B39,"TR.ROAActValue")/100)} -> 0.0939 | G39: {=IF($B39="","",_xll.RDP.Data($B39,"TR.ROEActValue")/100)} -> 0.3888 | H39: =IF($B39="","",_xll.RDP.Data($B39,"TR.AssetTurnover")) -> 1.2924422 | I39: =IF($B39="","",_xll.RDP.Data($B39,"TR.InventoryTurnover")) -> NULL | J39: {=IF($B39="","",_xll.RDP.Data($B39,"TR.Revenue")/_xll.RDP.Data($B39,"TR.TotalReceivablesNet"))} -> 8.3773342 | K39: =IF($B39="","",_xll.RDP.Data($B39,"TR.TtlDebtToTtlEquityPct")) -> 127.31188 | L39: =IF($B39="","",_xll.RDP.Data($B39,"TR.LTDebtToTtlCapitalPct")) -> 51.13735 | M39: =IF($B39="","",_xll.RDP.Data($B39,"TR.QuickRatio")) -> 1.1745 | N39: =IF($B39="","",_xll.RDP.Data($B39,"TR.CurrentRatio")) -> 1.1745 | O39: {=IF($B39="","",_xll.RDP.Data($B39,"TR.EBITDA")/_xll.RDP.Data($B39,"TR.InterestExpense"))} -> 14.385681
A40: =A7 -> J B Hunt Transport Services Inc | B40: =IF(B16="","",B25) -> JBHT.O | C40: {=IF($B40="","",_xll.RDP.Data($B40,"TR.GrossMargin")/100)} -> 0.1926768 | D40: {=IF($B40="","",_xll.RDP.Data($B40,"TR.OperatingMarginPercent")/100)} -> 0.068769 | E40: {=IF($B40="","",_xll.RDP.Data($B40,"TR.NetProfitMargin")/100)} -> 0.0472306 | F40: {=IF($B40="","",_xll.RDP.Data($B40,"TR.ROAActValue")/100)} -> 0.0679 | G40: {=IF($B40="","",_xll.RDP.Data($B40,"TR.ROEActValue")/100)} -> 0.1406 | H40: =IF($B40="","",_xll.RDP.Data($B40,"TR.AssetTurnover")) -> 1.4346378 | I40: =IF($B40="","",_xll.RDP.Data($B40,"TR.InventoryTurnover")) -> 232.76119 | J40: {=IF($B40="","",_xll.RDP.Data($B40,"TR.Revenue")/_xll.RDP.Data($B40,"TR.TotalReceivablesNet"))} -> 8.1563383 | K40: =IF($B40="","",_xll.RDP.Data($B40,"TR.TtlDebtToTtlEquityPct")) -> 36.809071 | L40: =IF($B40="","",_xll.RDP.Data($B40,"TR.LTDebtToTtlCapitalPct")) -> 17.801623 | M40: =IF($B40="","",_xll.RDP.Data($B40,"TR.QuickRatio")) -> 1.03056 | N40: =IF($B40="","",_xll.RDP.Data($B40,"TR.CurrentRatio")) -> 1.05539 | O40: {=IF($B40="","",_xll.RDP.Data($B40,"TR.EBITDA")/_xll.RDP.Data($B40,"TR.InterestExpense"))} -> 20.15143
A41: =A8 -> Deutsche Post AG | B41: =IF(B17="","",B26) -> DHLN.DE | C41: {=IF($B41="","",_xll.RDP.Data($B41,"TR.GrossMargin")/100)} -> 0.5141829 | D41: {=IF($B41="","",_xll.RDP.Data($B41,"TR.OperatingMarginPercent")/100)} -> 0.0699166 | E41: {=IF($B41="","",_xll.RDP.Data($B41,"TR.NetProfitMargin")/100)} -> 0.039579 | F41: {=IF($B41="","",_xll.RDP.Data($B41,"TR.ROAActValue")/100)} -> 0.04879 | G41: {=IF($B41="","",_xll.RDP.Data($B41,"TR.ROEActValue")/100)} -> 0.144 | H41: =IF($B41="","",_xll.RDP.Data($B41,"TR.AssetTurnover")) -> 1.231789 | I41: =IF($B41="","",_xll.RDP.Data($B41,"TR.InventoryTurnover")) -> 37.062981 | J41: {=IF($B41="","",_xll.RDP.Data($B41,"TR.Revenue")/_xll.RDP.Data($B41,"TR.TotalReceivablesNet"))} -> 6.5220019 | K41: =IF($B41="","",_xll.RDP.Data($B41,"TR.TtlDebtToTtlEquityPct")) -> 101.50464 | L41: =IF($B41="","",_xll.RDP.Data($B41,"TR.LTDebtToTtlCapitalPct")) -> 38.799859 | M41: =IF($B41="","",_xll.RDP.Data($B41,"TR.QuickRatio")) -> 0.8975 | N41: =IF($B41="","",_xll.RDP.Data($B41,"TR.CurrentRatio")) -> 0.95163 | O41: {=IF($B41="","",_xll.RDP.Data($B41,"TR.EBITDA")/_xll.RDP.Data($B41,"TR.InterestExpense"))} -> 11.31681
A42: =A9 -> CH Robinson Worldwide Inc | B42: =IF(B18="","",B27) -> CHRW.O | C42: {=IF($B42="","",_xll.RDP.Data($B42,"TR.GrossMargin")/100)} -> 0.1559955 | D42: {=IF($B42="","",_xll.RDP.Data($B42,"TR.OperatingMarginPercent")/100)} -> 0.0377513 | E42: {=IF($B42="","",_xll.RDP.Data($B42,"TR.NetProfitMargin")/100)} -> 0.0262731 | F42: {=IF($B42="","",_xll.RDP.Data($B42,"TR.ROAActValue")/100)} -> 0.1034 | G42: {=IF($B42="","",_xll.RDP.Data($B42,"TR.ROEActValue")/100)} -> 0.3464 | H42: =IF($B42="","",_xll.RDP.Data($B42,"TR.AssetTurnover")) -> 3.3687369 | I42: =IF($B42="","",_xll.RDP.Data($B42,"TR.InventoryTurnover")) -> NULL | J42: {=IF($B42="","",_xll.RDP.Data($B42,"TR.Revenue")/_xll.RDP.Data($B42,"TR.TotalReceivablesNet"))} -> 6.8593943 | K42: =IF($B42="","",_xll.RDP.Data($B42,"TR.TtlDebtToTtlEquityPct")) -> 81.963078 | L42: =IF($B42="","",_xll.RDP.Data($B42,"TR.LTDebtToTtlCapitalPct")) -> 29.419431 | M42: =IF($B42="","",_xll.RDP.Data($B42,"TR.QuickRatio")) -> 1.2773 | N42: =IF($B42="","",_xll.RDP.Data($B42,"TR.CurrentRatio")) -> 1.2773 | O42: {=IF($B42="","",_xll.RDP.Data($B42,"TR.EBITDA")/_xll.RDP.Data($B42,"TR.InterestExpense"))} -> 9.5232885
A43: =A10 -> FedEx Corp | B43: =IF(B19="","",B28) -> FDX | C43: {=IF($B43="","",_xll.RDP.Data($B43,"TR.GrossMargin")/100)} -> 0.7094943 | D43: {=IF($B43="","",_xll.RDP.Data($B43,"TR.OperatingMarginPercent")/100)} -> 0.059334 | E43: {=IF($B43="","",_xll.RDP.Data($B43,"TR.NetProfitMargin")/100)} -> 0.0464823 | F43: {=IF($B43="","",_xll.RDP.Data($B43,"TR.ROAActValue")/100)} -> 0.0507 | G43: {=IF($B43="","",_xll.RDP.Data($B43,"TR.ROEActValue")/100)} -> 0.15919 | H43: =IF($B43="","",_xll.RDP.Data($B43,"TR.AssetTurnover")) -> 1.0069746 | I43: =IF($B43="","",_xll.RDP.Data($B43,"TR.InventoryTurnover")) -> 42.011513 | J43: {=IF($B43="","",_xll.RDP.Data($B43,"TR.Revenue")/_xll.RDP.Data($B43,"TR.TotalReceivablesNet"))} -> 7.7345179 | K43: =IF($B43="","",_xll.RDP.Data($B43,"TR.TtlDebtToTtlEquityPct")) -> 73.3027 | L43: =IF($B43="","",_xll.RDP.Data($B43,"TR.LTDebtToTtlCapitalPct")) -> 39.362424 | M43: =IF($B43="","",_xll.RDP.Data($B43,"TR.QuickRatio")) -> 1.15398 | N43: =IF($B43="","",_xll.RDP.Data($B43,"TR.CurrentRatio")) -> 1.19304 | O43: {=IF($B43="","",_xll.RDP.Data($B43,"TR.EBITDA")/_xll.RDP.Data($B43,"TR.InterestExpense"))} -> 13.112801

Sheet Comps NF
C1: USD
A2: COMPARABLE COMPANY ANALYSIS
A3: COMPANY DATA
A4: (in millions) | C4: Recent | D4: 52 week | E4: Shares | F4: Market | G4: Total | I4: Enterprise | J4: Book | L4: WS 12-mo
A5: Company Name | B5: Ticker | C5: Price | D5: High | E5: Out | F5: Cap | G5: Debt | H5: Cash | I5: Value | J5: Value | K5: Beta | L5: Price Target
A6: United Parcel Service Inc | B6: UPS | C6: 86.78 | D6: 145.01 | E6: 847.56964 | F6: 73552.094 | G6: 21284 | H6: 6112 | I6: 88724.094 | J6: 16718 | K6: 1.0719394 | L6: 102.18464
A7: J B Hunt Transport Services Inc | B7: JBHT.O | C7: 137.95 | D7: 200.4 | E7: 96.799281 | F7: 13353.461 | G7: 1477.702 | H7: 46.983 | I7: 14784.18 | J7: 4014.505 | K7: 1.2440922 | L7: 156.43957
A8: GXO Logistics Inc | B8: GXO | C8: 53.73 | D8: 63.33 | E8: 114.47328 | F8: 6150.6493 | G8: 2631 | H8: 413 | I8: 8368.6493 | J8: 3003 | K8: 1.7073695 | L8: 61.64353
A9: CH Robinson Worldwide Inc | B9: CHRW.O | C9: 135.4 | D9: 137.996 | E9: 118.09116 | F9: 15989.543 | G9: 1411.446 | H9: 145.762 | I9: 17255.227 | J9: 1722.051 | K9: 0.86796169 | L9: 126.54625
A10: FedEx Corp | B10: FDX | C10: 244.61 | D10: 308.53 | E10: 235.95546 | F10: 57717.065 | G10: 20579 | H10: 5502 | I10: 72794.065 | J10: 28074 | K10: 1.3122156 | L10: 266.62
A12: I/B/E/S ESTIMATES
C13: SALES | G13: EPS | K13: EBIT | N13: EBITDA | Q13: EPS 5-yr
A14: Company Name | B14: Ticker | C14: Last FY | D14: FYR1 | E14: FYR2 | F14: FYR3 | G14: Last FY | H14: FYR1 | I14: FYR2 | J14: FYR3 | K14: Last FY | L14: FYR1 | M14: FYR2 | N14: Last FY | O14: FYR1 | P14: FYR2 | Q14: Growth %
A15: United Parcel Service Inc | B15: UPS | C15: 91070 | D15: 87579.885 | E15: 87840.28 | F15: 91088.424 | G15: 7.49454 | H15: 6.5096 | I15: 7.1955 | J15: 7.91333 | K15: 8684.2355 | L15: 7787.6362 | M15: 8554.1496 | N15: 12286.924 | O15: 11434.941 | P15: 12253.156 | Q15: 0.01375
A16: J B Hunt Transport Services Inc | B16: JBHT.O | C16: 12087.204 | D16: 12007.443 | E16: 12620.12 | F16: 13270.544 | G16: 5.6403 | H16: 5.56604 | I16: 6.84839 | J16: 8.13082 | K16: 847.83078 | L16: 807.62862 | M16: 944.5275 | N16: 1599.2676 | O16: 1532.4112 | P16: 1706.053 | Q16: 0.131
A17: GXO Logistics Inc | B17: GXO | C17: 11709 | D17: 13178.799 | E17: 14019.126 | F17: 14736.704 | G17: 2.73671 | H17: 2.529 | I17: 3.07393 | J17: 3.45456 | K17: 471.23511 | L17: 528.66625 | M17: 560.7551 | N17: 810.41781 | O17: 874.63994 | P17: 951.84069 | Q17: 0.0851333
A18: CH Robinson Worldwide Inc | B18: CHRW.O | C18: 17724.956 | D18: 16506.983 | E18: 17139.363 | F18: 18046.186 | G18: 4.39652 | H18: 4.92213 | I18: 5.57556 | J18: 5.95964 | K18: 757.25444 | L18: 810.98235 | M18: 888.86452 | N18: 839.5036 | O18: 914.21158 | P18: 994.32091 | Q18: 0.1291667
A19: FedEx Corp | B19: FDX | C19: 87926 | D19: 91412.886 | E19: 95149.829 | F19: 98971.009 | G19: 18.008 | H19: 18.02807 | I19: 20.83456 | J19: 23.31733 | K19: 5982.1201 | L19: 5905.2374 | M19: 6613.2781 | N19: 10287.836 | O19: 10329.18 | P19: 11202.511 | Q19: 0.104125
A21: VALUATION MULTIPLES
C22: Recent | D22: Price / | E22: Price/Sales | H22: P/E | K22: PEG | N22: EV/EBITDA
A23: Company Name | B23: Ticker | C23: Price | D23: Book | E23: FYR1 | F23: FYR2 | G23: FYR3 | H23: FYR1 | I23: FYR2 | J23: FYR3 | K23: FYR1 | L23: FYR2 | M23: FYR3 | N23: Last FY | O23: FYR1 | P23: FYR2
A24: United Parcel Service Inc | B24: UPS | C24: 86.78 | D24: 4.3995749 | E24: 0.83982862 | F24: 0.83733901 | G24: 0.80748014 | H24: 13.33108 | I24: 12.060315 | J24: 10.966306 | K24: 9.6953311 | L24: 8.7711385 | M24: 7.9754954 | N24: 7.2210173 | O24: 7.7590335 | P24: 7.2409176
A25: J B Hunt Transport Services Inc | B25: JBHT.O | C25: 137.95 | D25: 3.3263032 | E25: 1.1120987 | F25: 1.0581088 | G25: 1.0062482 | H25: 24.784227 | I25: 20.143421 | J25: 16.966308 | K25: 1.8919257 | L25: 1.5376657 | M25: 1.295138 | N25: 9.244344 | O25: 9.6476584 | P25: 8.665721
A26: GXO Logistics Inc | B26: GXO | C26: 53.73 | D26: 2.0481683 | E26: 0.46670788 | F26: 0.43873272 | G26: 0.4173694 | H26: 21.245552 | I26: 17.479253 | J26: 15.553356 | K26: 2.495563 | L26: 2.0531629 | M26: 1.8269415 | N26: 10.326339 | O26: 9.5681079 | P26: 8.7920693
A27: CH Robinson Worldwide Inc | B27: CHRW.O | C27: 135.4 | D27: 9.2851741 | E27: 0.9686533 | F27: 0.93291351 | G27: 0.88603451 | H27: 27.508416 | I27: 24.284556 | J27: 22.719493 | K27: 2.1296833 | L27: 1.8800942 | M27: 1.758928 | N27: 20.554084 | O27: 18.874435 | P27: 17.353781
A28: FedEx Corp | B28: FDX | C28: 244.61 | D28: 2.0558903 | E28: 0.63138872 | F28: 0.60659137 | G28: 0.58317143 | H28: 13.568285 | I28: 11.740589 | J28: 10.490481 | K28: 1.3030766 | L28: 1.1275475 | M28: 1.0074891 | N28: 7.0757409 | O28: 7.0474192 | P28: 6.4980133
C30: Average | D30: 4.7648051 | E30: 0.84682211 | F30: 0.81677352 | G30: 0.77928306 | H30: 21.717319 | I30: 18.491886 | J30: 16.551366 | K30: 6.0954471 | L30: 5.4121507 | M30: 4.9012184 | N30: 11.836446 | O30: 11.462309 | P30: 10.513122
C31: Median | D31: 3.8629391 | E31: 0.90424096 | F31: 0.88512626 | G31: 0.84675733 | H31: 23.014889 | I31: 18.811337 | J31: 16.259832 | K31: 6.0954471 | L31: 5.4121507 | M31: 4.9012184 | N31: 9.7853417 | O31: 9.6078831 | P31: 8.7288952
C33: Average | D33: 566.9169 | E33: 328.07231 | F33: 329.36666 | G33: 326.8686 | H33: 391.52134 | I33: 385.27031 | J33: 385.93366 | K33: 1144.2207 | L33: 1174.1112 | M33: 1189.9752 | N33: 452.18034 | O33: 437.8761 | P33: 435.23624
C34: Median | D34: 459.6128 | E34: 350.31728 | F34: 356.93013 | G34: 355.17054 | H34: 414.91404 | I34: 391.92592 | J34: 379.13587 | K34: 1144.2207 | L34: 1174.1112 | M34: 1189.9752 | N34: 362.75064 | O34: 356.6968 | P34: 350.52608
D35: ws.OperatingProfitMargin[ws.cpa] | H35: ws.AssetTurnover[ws.cpa] | I35: ws.InventoryTurnover[ws.cpa] | J35: ws.ReceivablesTurnover[ws.cpa] | K35: ws.TotalDebtPctCommonEquity[ws.cpa] | L35: ws.LTDebtPctCommonEquity[ws.cpa] | M35: ws.LTDebtPctTotalCapital[ws.cpa] | N35: ws.QuickRatio[ws.cpa] | O35: ws.CurrentRatio[ws.cpa]
A36: RATIO ANALYSIS
C37: Gross | D37: Operating | E37: Net | H37: Asset | I37: Inventory | J37: Receivables | M37: Quick | N37: Current | O37: Interest
A38: Company Name | B38: Ticker | C38: Margin | D38: Margin | E38: Margin | F38: ROA | G38: ROE | H38: Turnvover | I38: Turnvover | J38: Turnvover | K38: Debt/E | L38: LTD/TC | M38: Ratio | N38: Ratio | O38: Coverage
A39: United Parcel Service Inc | B39: UPS | C39: 0.802844 | D39: 0.0929834 | E39: 0.0634896 | F39: 0.0939 | G39: 0.3888 | H39: 1.2924422 | I39: NULL | J39: 8.3773342 | K39: 127.31188 | L39: 51.13735 | M39: 1.1745 | N39: 1.1745 | O39: 14.385681
A40: J B Hunt Transport Services Inc | B40: JBHT.O | C40: 0.1926768 | D40: 0.068769 | E40: 0.0472306 | F40: 0.0679 | G40: 0.1406 | H40: 1.4346378 | I40: 232.76119 | J40: 8.1563383 | K40: 36.809071 | L40: 17.801623 | M40: 1.03056 | N40: 1.05539 | O40: 20.15143
A41: GXO Logistics Inc | B41: GXO | C41: 0.1585105 | D41: 0.0186182 | E41: 0.0114442 | F41: 0.03229 | G41: 0.1133 | H41: 1.1273287 | I41: NULL | J41: 6.377451 | K41: 87.612388 | L41: 44.49347 | M41: 0.82816 | N41: 0.82816 | O41: 7.7184466
A42: CH Robinson Worldwide Inc | B42: CHRW.O | C42: 0.1559955 | D42: 0.0377513 | E42: 0.0262731 | F42: 0.1034 | G42: 0.3464 | H42: 3.3687369 | I42: NULL | J42: 6.8593943 | K42: 81.963078 | L42: 29.419431 | M42: 1.2773 | N42: 1.2773 | O42: 9.5232885
A43: FedEx Corp | B43: FDX | C43: 0.7094943 | D43: 0.059334 | E43: 0.0464823 | F43: 0.0507 | G43: 0.15919 | H43: 1.0069746 | I43: 42.011513 | J43: 7.7345179 | K43: 73.3027 | L43: 39.362424 | M43: 1.15398 | N43: 1.19304 | O43: 13.112801
