Workbook

Sheet Cover
E5: GENERAL DYNAMICS Corporation
E6: NYSE: GD
D11: Valuation Date: | E11: =TODAY() -> 46111 | H11: Scenario Switchboard
D12: Company Name: | E12: General Dynamics Corporation
D13: Sector: | E13: Industrials — Aerospace & Defense | H13: Revenue & Operating Expenses
D14: Industry: | E14: Aerospace & Defense | H14: Marine revenue | I14: 2
D15: Rating: | E15: =IF(E23>=Ke!D32,"BUY","SELL") -> BUY | H15: Marine op.margin | I15: 2
H16: Combat revenue | I16: 2
D17: Current Price | E17: =Ke!D17 -> 340.71 | H17: Combat op.margin | I17: 2
D18: Valuation Price | E18: =DCF!B8 -> 388.20096 | H18: IT revenue | I18: 2
D19: 12-month Valuation Price | E19: =DCF!B9 -> 408.20567 | H19: IT op .margin | I19: 2
D20: Valuation Appreciation | E20: =E18/E17-1 -> 0.13938823
D21: 12-mo Valuation Appreciation | E21: =E19/E17-1 -> 0.19810298 | H21: Scenario Key
D22: Dividend Yield | E22: 0.0182 | H22: Bull | I22: 1
D23: Total Valuation Appreciation | E23: =E21+E22 -> 0.21630298 | H23: Base | I23: 2
H24: Bear | I24: 3

Sheet DCF
G2: Share count in Millions
A3: Cost of Equity | B3: =Ke!D32 -> 0.075163557 | G3: =TODAY() -> 46111 | H3: Today | I3: 270.38976
A4: Number of Shares in thousands: | G4: =G3+365 -> 46476 | H4: One year | I4: =Equity!G21 -> 266.88682
G5: =G4+366 -> 46842 | H5: Two year | I5: =Equity!H21 -> 263.06703
A6: Actual Price: | B6: =Ke!D17 -> 340.71 | C6: At close oct 22, 2025
A8: Model Valuation: | B8: =B24 -> 388.20096
A9: Model 12 Month Price Target: | B9: =B46 -> 408.20567
A12: Model Current Valuation with Sensitivity of Ke
D14: 46387 | E14: 46752 | F14: 47118 | G14: 47483 | H14: 47848 | I14: 48213
A15: Time period (years) | D15: =MAX((D14-$G$3)/365,0) -> 0.75616438 | E15: =MAX((E14-$G$3)/365,0) -> 1.7561644 | F15: =MAX((F14-$G$3)/365,0) -> 2.7589041 | G15: =MAX((G14-$G$3)/365,0) -> 3.7589041 | H15: =MAX((H14-$G$3)/365,0) -> 4.7589041 | I15: =MAX((I14-$G$3)/365,0) -> 5.7589041
A16: Nominal FCFE: | D16: ='Cash flow'!G48 -> 3788.3468 | E16: ='Cash flow'!H48 -> 4309.4143 | F16: ='Cash flow'!I48 -> 4807.6934 | G16: ='Cash flow'!J48 -> 5300.9532 | H16: ='Cash flow'!K48 -> 5890.0695 | I16: ='Cash flow'!L48 -> 6112.9996
A17: PV FCFE: | D17: =D16*D15/((1+$B$3)^D15) -> 2711.8523 | E17: =E16/((1+$B$3)^E15) -> 3794.406 | F17: =F16/((1+$B$3)^F15) -> 3936.421 | G17: =G16/((1+$B$3)^G15) -> 4036.8649 | H17: =H16/((1+$B$3)^H15) -> 4171.9214 | I17: =I16/((1+$B$3)^I15) -> 4027.1289
A19: Terminal Growth Rate | B19: 0.025
A21: Terminal Value in 2030 | B21: =I16*(1+B19)/(B3-B19) -> 124907.9
A22: PV of Terminal Value | B22: =B21/(1+B3)^(I15) -> 82286.971
A23: Total PV: | B23: =SUM(D17:I17)+B22 -> 104965.57
A24: Valuation per Share ($): | B24: =B23/I3 -> 388.20096
C25: Terminal Growth Rate
B26: =B24 -> 388.20096 | C26: =D26-L27 -> 0.005 | D26: =E26-L27 -> 0.01 | E26: =F26-L27 -> 0.015 | F26: 0.02 | G26: =F26+L27 -> 0.025 | H26: =G26+L27 -> 0.03 | I26: =H26+L27 -> 0.035 | L26: 0.005
B27: =B28+L27 -> 0.090163557 | C27: 242.28174 | D27: 253.26128 | E27: 265.70158 | F27: 279.91491 | G27: 296.30943 | H27: 315.42893 | I27: 338.0144 | L27: 0.005
B28: =B29+L27 -> 0.085163557 | C28: 258.2885 | D28: 271.00394 | E28: 285.53164 | F28: 302.28877 | G28: 321.83115 | H28: 344.91617 | I28: 372.60313
B29: =B30+L27 -> 0.080163557 | C29: 276.44382 | D29: 291.29434 | E29: 308.42383 | F29: 328.40047 | G29: 351.99846 | H29: 380.30065 | I29: 414.86945
A30: Cost Of Equity Ke | B30: =Ke!D32 -> 0.075163557 | C30: 297.20756 | D30: 314.71947 | E30: 335.14209 | F30: 359.26691 | G30: 388.20096 | H30: 423.54152 | I30: 467.68123
B31: =B30-L27 -> 0.070163557 | C31: 321.18072 | D31: 342.06143 | E31: 366.72738 | F31: 396.31044 | G31: 432.44371 | H31: 477.5735 | I31: 535.53755
B32: =B31-L27 -> 0.065163557 | C32: 349.16409 | D32: 374.38593 | E32: 404.6357 | F32: 441.58329 | G32: 487.73016 | H32: 547.00053 | I32: 625.92056
B33: =B32-L27 -> 0.060163557 | C33: 382.24884 | D33: 413.18358 | E33: 450.96781 | F33: 498.15963 | G33: 558.77212 | H33: 639.47921 | I33: 752.25932
A36: Model 12 Month Price Target with Sensitivity of Ke
D38: =D14 -> 46387 | E38: =E14 -> 46752 | F38: =F14 -> 47118 | G38: =G14 -> 47483 | H38: =H14 -> 47848 | I38: =I14 -> 48213
A39: Time period | D39: =MAX((D38-$G$4)/365,0) -> 0 | E39: =MAX((E38-$G$4)/365,0) -> 0.75616438 | F39: =MAX((F38-$G$4)/365,0) -> 1.7589041 | G39: =MAX((G38-$G$4)/365,0) -> 2.7589041 | H39: =MAX((H38-$G$4)/365,0) -> 3.7589041 | I39: =MAX((I38-$G$4)/365,0) -> 4.7589041
A40: Nominal FCFE: | D40: ='Cash flow'!G48 -> 3788.3468 | E40: ='Cash flow'!H48 -> 4309.4143 | F40: ='Cash flow'!I48 -> 4807.6934 | G40: ='Cash flow'!J48 -> 5300.9532 | H40: ='Cash flow'!K48 -> 5890.0695 | I40: ='Cash flow'!L48 -> 6112.9996
A41: PV FCFE: | D41: =D40*D39/((1+$B$3)^D39) -> 0 | E41: =E40*E39/((1+$B$3)^E39) -> 3084.8535 | F41: =F40/((1+$B$3)^F39) -> 4232.2964 | G41: =G40/((1+$B$3)^G39) -> 4340.29 | H41: =H40/((1+$B$3)^H39) -> 4485.4979 | I41: =I40/((1+$B$3)^I39) -> 4329.8223
A43: Terminal Value in 2030 | B43: =I40*(1+B19)/(B3-B19) -> 124907.9
A44: PV of Terminal Value | B44: =B43/(1+B3)^I39 -> 88471.952
A45: Total PV: | B45: =SUM(D41:I41)+B44 -> 108944.71
A46: Valuation per Share ($): | B46: =B45/I4 -> 408.20567
C47: Terminal Growth Rate
B48: =B46 -> 408.20567 | C48: =D48-$L$26 -> 0.005 | D48: =E48-$L$26 -> 0.01 | E48: =F48-$L$26 -> 0.015 | F48: 0.02 | G48: =F48+$L$26 -> 0.025 | H48: =G48+$L$26 -> 0.03 | I48: =H48+$L$26 -> 0.035
B49: =B50+$L$27 -> 0.090163557 | C49: 252.94327 | D49: 265.06987 | E49: 278.80982 | F49: 294.50806 | G49: 312.61534 | H49: 333.7323 | I49: 358.67732
B50: =B51+$L$27 -> 0.085163557 | C50: 269.31332 | D50: 283.29277 | E50: 299.26462 | F50: 317.68751 | G50: 339.17254 | H50: 364.55235 | I50: 394.99158
B51: =B52+$L$27 -> 0.080163557 | C51: 287.87242 | D51: 304.12396 | E51: 322.86945 | F51: 344.73071 | G51: 370.55495 | H51: 401.5272 | I51: 439.35725
A52: Cost Of Equity Ke | B52: =Ke!D32 -> 0.075163557 | C52: 309.0888 | D52: 328.16409 | E52: 350.40995 | F52: 376.68852 | G52: 408.20567 | H52: 446.70126 | I52: 494.78156
B53: =B52-$L$27 -> 0.070163557 | C53: 333.57444 | D53: 356.21351 | E53: 382.95657 | F53: 415.03081 | G53: 454.20685 | H53: 503.137 | I53: 565.98218
B54: =B53-$L$27 -> 0.065163557 | C54: 362.14473 | D54: 389.36273 | E54: 422.00658 | F54: 461.87836 | G54: 511.67748 | H54: 575.63874 | I54: 660.80482
B55: =B54-$L$27 -> 0.060163557 | C55: 395.91073 | D55: 429.13706 | E55: 469.72029 | F55: 520.40801 | G55: 585.51057 | H55: 672.19632 | I55: 793.33099

Sheet Ke
B2: Company name | D2: Company ticker
B3: General dynamics corporation | D3: GD
B4: Cost of Equity
B5: (Blue = input, Black = calculation)
B7: S&P 500 data | F7: Source
C8: S&P500 Forward P/E | D8: 20.57 | F8: WSJ
C9: Projected EPS growth rate (g S&P) | D9: 0.122 | E9: Yahoo Finance | F9: CapIQ / Bloomberg | G9: (5 years)
C10: Risk-free rate (Rf) | D10: 0.043 | F10: Market quote
C11: Implied required return on equity (Rs&p500) | D11: =((1+D9)/D8)+D9 -> 0.17654545
C12: Implied equity risk premium (Rm) | D12: =+D11-D10 -> 0.13354545
B15: Beta
B16: General Dynamics
C17: Current Price (P) | D17: 340.71 | F17: Yahoo!Finance
C18: Forward EPS (E) | D18: 16.33 | F18: Yahoo!Finance | J18: Company | K18: D/E Ratio | L18: Tax Rate | M18: Beta | N18: bU = bL / (1+ ((1-t)D/E)) | O18: bL = bu (1+ ((1-t)D/E))
C19: P/E ratio | D19: =D17/D18 -> 20.864054 | J19: LMT | K19: ='Comps no formuals'!G6/'Comps no formuals'!F6 -> 0.14794266 | L19: 0.165 | M19: ='Comps no formuals'!K6 -> 0.21173258 | N19: =M19/(1+((1-L19)*K19)) -> 0.18845263 | O19: =N19*(1+((1-$L$26)*$K$26)) -> 0.20225864
C20: Projected EPS growth rate (g) | D20: 0.105 | F20: LSEG>Estmates>Recommendations & Target Price | G20: (5 years) | J20: RTX | K20: ='Comps no formuals'!G7/'Comps no formuals'!F7 -> 0.140293 | L20: 0.189 | M20: ='Comps no formuals'!K7 -> 0.40948776 | N20: =M20/(1+((1-L20)*K20)) -> 0.36765665 | O20: =N20*(1+((1-$L$26)*$K$26)) -> 0.39459112
C21: Implied required return on equity (Re) | D21: =+((1+D20)/D19)+D20 -> 0.1579619 | J21: NOC | K21: ='Comps no formuals'!G8/'Comps no formuals'!F8 -> 0.15486418 | L21: 0.163 | M21: ='Comps no formuals'!K8 -> 0.02049081 | N21: =M21/(1+((1-L21)*K21)) -> 0.018139539 | O21: =N21*(1+((1-$L$26)*$K$26)) -> 0.019468439
C22: Forward (Bf) | D22: =(D21-D10)/D12 -> 0.86084475 | J22: LHX | K22: ='Comps no formuals'!G9/'Comps no formuals'!F9 -> 0.16363777 | L22: 0.15 | M22: ='Comps no formuals'!K9 -> 0.59925533 | N22: =M22/(1+((1-L22)*K22)) -> 0.52608154 | O22: =N22*(1+((1-$L$26)*$K$26)) -> 0.56462219
C23: Historical (Bh) | D23: 0.37 | F23: Yahoo!Finance | M23: ='Comps no formuals'!K10 -> 0.37863835 | O23: =+AVERAGE(O19:O22) -> 0.2952351
C24: Average Beta | D24: =+(D22+D23)/2 -> 0.61542237
C25: Comperable Beta | D25: =+O23 -> 0.2952351 | F25: Calculation | K25: D/E Ratio | L25: Tax Rate | O25: Relevered
J26: GD | K26: ='Comps no formuals'!G10/'Comps no formuals'!F10 -> 0.08890758 | L26: 0.176 | M26: ='Comps no formuals'!K10 -> 0.37863835 | N26: =M26/(1+((1-L26)*K26)) -> 0.3527928 | O26: =N26*(1+((1-L26)*K26)) -> 0.37863835
B27: Cost of Equity:
C28: Historic equity risk premium | D28: 0.065
C29: Using Forward Beta | D29: =+$D$10+D22*($D$28) -> 0.098954909 | E29: 0.3
C30: Using Historic Beta | D30: =+$D$10+D23*($D$28) -> 0.06705 | E30: 0.4
C31: Comperable Beta | D31: =+$D$10+D25*($D$28) -> 0.062190281 | E31: 0.3
C32: Weighted COE | D32: =+SUMPRODUCT(D29:D31,E29:E31) -> 0.075163557
C34: Market COE (beta = 1) | D34: =+D10+1*D28 -> 0.108

Sheet Revenue model
A1: General Dynamics Corporation
A2: Bottom-Up Revenue Model
A3: (Dollars in millions, except units and per-unit amounts)
A5: Year Ended December 31 | B5: 2021 | C5: 2022 | D5: 2023 | E5: 2024 | F5: 2025 | G5: 2026E | H5: 2027E | I5: 2028E | J5: 2029E | K5: 2030E | L5: 2031E | N5: Projection Assumptions
A7: AEROSPACE | N7: AEROSPACE
A8: Aircraft manufacturing | B8: 5864 | C8: 5876 | D8: 5710 | E8: 7811 | F8: 9413 | G8: =G13*G15 -> 9722.7949 | H8: =H13*H15 -> 10041.216 | I8: =I13*I15 -> 10470.138 | J8: =J13*J15 -> 10915.757 | K8: =K13*K15 -> 11378.69 | L8: =L13*L15 -> 11859.575
A9: Aircraft services | B9: 2271 | C9: 2691 | D9: 2911 | E9: 3438 | F9: 3697 | G9: =F9*(1+G18) -> 3881.85 | H9: =G9*(1+H18) -> 4075.9425 | I9: =H9*(1+I18) -> 4279.7396 | J9: =I9*(1+J18) -> 4493.7266 | K9: =J9*(1+K18) -> 4718.4129 | L9: =K9*(1+L18) -> 4954.3336
A10: Total Aerospace Revenue | B10: =B8+B9 -> 8135 | C10: =C8+C9 -> 8567 | D10: =D8+D9 -> 8621 | E10: =E8+E9 -> 11249 | F10: =F8+F9 -> 13110 | G10: =G8+G9 -> 13604.645 | H10: =H8+H9 -> 14117.159 | I10: =I8+I9 -> 14749.877 | ... L10: =L8+L9 -> 16813.909
A12: Key Drivers:
A13: Gulfstream deliveries (units) | B13: 119 | C13: 120 | D13: 111 | E13: 136 | F13: 158 | G13: =ROUND(F13*(1+G14), 0) -> 160 | H13: =ROUND(G13*(1+H14), 0) -> 162 | I13: =ROUND(H13*(1+I14), 0) -> 164 | J13: =ROUND(I13*(1+J14), 0) -> 166 | K13: =ROUND(J13*(1+K14), 0) -> 168 | L13: =ROUND(K13*(1+L14), 0) -> 170
C14: =C13/B13-1 -> 0.0084033613 | D14: =D13/C13-1 -> -0.075 | E14: =E13/D13-1 -> 0.22522523 | F14: =F13/E13-1 -> 0.16176471 | G14: 0.01 | H14: 0.01 | I14: 0.01 | J14: 0.01 | K14: 0.01 | L14: 0.01 | N14: Gulfstream deliveries: 3% growth in 2026E tapering to 1% by 2030–31E. Supported by strong backlog ($21.8B in 2025) and management guidance for ~158 deliveries in 2025 with continued ramp. Growth decelerates as delivery ramp matures and approaches steady-state production capacity.
A15: Implied ASP per aircraft ($M) | B15: =B8/B13 -> 49.277311 | C15: =C8/C13 -> 48.966667 | D15: =D8/D13 -> 51.441441 | E15: =E8/E13 -> 57.433824 | F15: =F8/F13 -> 59.575949 | G15: =F15*(1+G16) -> 60.767468 | H15: =G15*(1+H16) -> 61.982818 | I15: =H15*(1+I16) -> 63.842302 | J15: =I15*(1+J16) -> 65.757571 | K15: =J15*(1+K16) -> 67.730298 | L15: =K15*(1+L16) -> 69.762207 | N15: ASP per aircraft: 3% annual price escalation in 2026E, stepping up to 4% from 2029E onward. Reflects Gulfstream's historical pricing power (2021–2025 implied ASP CAGR ~4.8%) and premium market positioning. Conservative vs. historical given mix normalization as new models ramp.
C16: =C15/B15-1 -> -0.0063040018 | D16: =D15/C15-1 -> 0.050539989 | E16: =E15/D15-1 -> 0.11648939 | F16: =F15/E15-1 -> 0.037297288 | G16: 0.02 | H16: =G16 -> 0.02 | I16: 0.03 | J16: 0.03 | K16: =J16 -> 0.03 | L16: =K16 -> 0.03
A17: Aircraft mfg. revenue growth | B17: n/a | C17: =C8/B8-1 -> 0.0020463847 | D17: =D8/C8-1 -> -0.028250511 | E17: =E8/D8-1 -> 0.36795096 | F17: =F8/E8-1 -> 0.20509538 | G17: =G8/F8-1 -> 0.032911392 | H17: =H8/G8-1 -> 0.03275 | I17: =I8/H8-1 -> 0.042716049 | J17: =J8/I8-1 -> 0.042560976 | ... L17: =L8/K8-1 -> 0.042261905 | N17: Aircraft mfg. revenue: Derived as deliveries × ASP. No independent assumption — flows from the unit and pricing drivers above.
A18: Aircraft services revenue growth | B18: n/a | C18: =C9/B9-1 -> 0.18494055 | D18: =D9/C9-1 -> 0.081753995 | E18: =E9/D9-1 -> 0.18103744 | F18: =F9/E9-1 -> 0.075334497 | G18: 0.05 | H18: =G18 -> 0.05 | I18: =H18 -> 0.05 | J18: =I18 -> 0.05 | K18: =J18 -> 0.05 | L18: =K18 -> 0.05 | N18: Aircraft services: 5% annual growth throughout projection. Historical growth volatile (8–18%) driven by expanding installed fleet and recurring aftermarket demand. 5% is a moderated steady-state assumption reflecting fleet growth net of cycle normalization.
A19: Operating Earnings | B19: 1031 | C19: 1130 | D19: 1182 | E19: 1464 | F19: 1746 | G19: =G20*G10 -> 1904.6503 | H19: =H20*H10 -> 1976.4023 | I19: =I20*I10 -> 2064.9828 | J19: =J20*J10 -> 2157.3277 | K19: =K20*K10 -> 2253.5944 | L19: =L20*L10 -> 2353.9472 | N19: Aerospace Operating Earnings: Derived from operating margin × total segment revenue.
A20: Operating Margin | B20: =B19/B10 -> 0.12673632 | C20: =C19/C10 -> 0.13190148 | D20: =D19/D10 -> 0.13710706 | E20: =E19/E10 -> 0.1301449 | F20: =F19/F10 -> 0.13318078 | G20: 0.14 | H20: 0.14 | I20: 0.14 | J20: 0.14 | K20: 0.14 | L20: 0.14 | N20: Aerospace Operating Margin: 13.5% in 2026E, rising to 14% by 2028E and held flat thereafter. 2026 management forward guidance is ~14% operating margin. Tapered entry from 13.0% actual in 2024 / 13.3% in 2025 reflects gradual margin expansion as Gulfstream production ramp yields operating leverage. Historical range: 12.7–13.7%.
A22: MARINE SYSTEMS | N22: MARINE SYSTEMS
A23: Nuclear-powered submarines | B23: 7117 | C23: 7310 | D23: 8631 | E23: 10392 | F23: 12608 | G23: =F23*(1+G29) -> 13490.56 | H23: =G23*(1+H29) -> 14434.899 | I23: =H23*(1+I29) -> 15445.342 | J23: =I23*(1+J29) -> 16526.516 | K23: =J23*(1+K29) -> 17683.372 | L23: =K23*(1+L29) -> 18921.208 | N23: Submarine revenue: 10% growth in 2026E, tapering to 5% by 2031E. Driven by Columbia-class SSBN production ramp and Virginia-class Block V orders. Backlog of $52.3B (2025) provides multi-year visibility. Growth decelerates as Columbia production stabilizes.
A24: Surface ships | B24: 2328 | C24: 2561 | D24: 2698 | E24: 2819 | F24: 2932 | G24: =F24*(1+G30) -> 3019.96 | H24: =G24*(1+H30) -> 3110.5588 | I24: =H24*(1+I30) -> 3203.8756 | J24: =I24*(1+J30) -> 3332.0306 | K24: =J24*(1+K30) -> 3465.3118 | L24: =K24*(1+L30) -> 3603.9243 | N24: Surface ships: 4% annual growth held flat. Reflects steady DDG-51 and DDG(X) program contributions. Historical growth volatile (4–10%); 4% is conservative given stable Navy shipbuilding budget expectations.
A25: Repair and other services | B25: 1081 | C25: 1169 | D25: 1132 | E25: 1132 | F25: 1183 | G25: =F25*(1+G32) -> 1206.66 | H25: =G25*(1+H32) -> 1230.7932 | I25: =H25*(1+I32) -> 1255.4091 | J25: =I25*(1+J32) -> 1280.5172 | K25: =J25*(1+K32) -> 1306.1276 | L25: =K25*(1+L32) -> 1332.2501 | N25: Repair & other services: 2% annual growth. Stable recurring maintenance and modernization work on the existing fleet. Historical range volatile (-3% to +8%); 2% reflects normalized sustainment demand.
A26: Total Marine Systems Revenue | B26: =B23+B24+B25 -> 10526 | C26: =C23+C24+C25 -> 11040 | D26: =D23+D24+D25 -> 12461 | E26: =E23+E24+E25 -> 14343 | F26: =F23+F24+F25 -> 16723 | G26: =G23+G24+G25 -> 17717.18 | H26: =H23+H24+H25 -> 18776.251 | I26: =I23+I24+I25 -> 19904.627 | ... L26: =L23+L24+L25 -> 23857.383
A28: Key Drivers:
A29: Submarine revenue growth | B29: n/a | C29: =C23/B23-1 -> 0.027118168 | D29: =D23/C23-1 -> 0.18071135 | E29: =E23/D23-1 -> 0.20403198 | F29: =F23/E23-1 -> 0.21324095 | G29: =CHOOSE(Cover!$I$14,'Revenue model'!G92,'Revenue model'!G93,'Revenue model'!G94) -> 0.07 | H29: =CHOOSE(Cover!$I$14,'Revenue model'!H92,'Revenue model'!H93,'Revenue model'!H94) -> 0.07 | I29: =CHOOSE(Cover!$I$14,'Revenue model'!I92,'Revenue model'!I93,'Revenue model'!I94) -> 0.07 | J29: =CHOOSE(Cover!$I$14,'Revenue model'!J92,'Revenue model'!J93,'Revenue model'!J94) -> 0.07 | K29: =CHOOSE(Cover!$I$14,'Revenue model'!K92,'Revenue model'!K93,'Revenue model'!K94) -> 0.07 | L29: =CHOOSE(Cover!$I$14,'Revenue model'!L92,'Revenue model'!L93,'Revenue model'!L94) -> 0.07 | N29: Marine submarine growth: 10% in 2026E tapering to 5% by 2031E. See row 23 for detail.
A30: Surface ships revenue growth | B30: n/a | C30: =C24/B24-1 -> 0.10008591 | D30: =D24/C24-1 -> 0.053494729 | E30: =E24/D24-1 -> 0.044848036 | F30: =F24/E24-1 -> 0.040085137 | G30: =CHOOSE(Cover!$I$14,'Revenue model'!G96,'Revenue model'!G97,'Revenue model'!G98) -> 0.03 | H30: =CHOOSE(Cover!$I$14,'Revenue model'!H96,'Revenue model'!H97,'Revenue model'!H98) -> 0.03 | I30: =CHOOSE(Cover!$I$14,'Revenue model'!I96,'Revenue model'!I97,'Revenue model'!I98) -> 0.03 | J30: =CHOOSE(Cover!$I$14,'Revenue model'!J96,'Revenue model'!J97,'Revenue model'!J98) -> 0.04 | K30: =CHOOSE(Cover!$I$14,'Revenue model'!K96,'Revenue model'!K97,'Revenue model'!K98) -> 0.04 | L30: =CHOOSE(Cover!$I$14,'Revenue model'!L96,'Revenue model'!L97,'Revenue model'!L98) -> 0.04 | N30: Marine surface ships growth: 4% annual. See row 24 for detail.
A31: Operating Earnings | B31: 874 | C31: 897 | D31: 874 | E31: 935 | F31: 1177 | G31: =G33*G26 -> 1293.3541 | H31: =H33*H26 -> 1370.6663 | I31: =I33*I26 -> 1472.9424 | J31: =J33*J26 -> 1564.2907 | K31: =K33*K26 -> 1684.1109 | L31: =L33*L26 -> 1789.3037 | N31: Marine Operating Earnings: Derived from operating margin × total segment revenue.
A32: Repair and other services growth | C32: =C25/B25-1 -> 0.081406105 | D32: =D25/C25-1 -> -0.031650984 | E32: =E25/D25-1 -> 0 | F32: =F25/E25-1 -> 0.045053004 | G32: 0.02 | H32: 0.02 | I32: 0.02 | J32: 0.02 | K32: 0.02 | L32: 0.02 | N32: Marine repair services growth: 2% annual. See row 25 for detail.
A33: Operating Margin | B33: =B31/B26 -> 0.083032491 | C33: =C31/C26 -> 0.08125 | D33: =D31/D26 -> 0.070138833 | E33: =E31/E26 -> 0.065188594 | F33: =F31/F26 -> 0.070382108 | G33: =CHOOSE(Cover!$I$15,'Revenue model'!G100,'Revenue model'!G101,'Revenue model'!G102) -> 0.073 | H33: =CHOOSE(Cover!$I$15,'Revenue model'!H100,'Revenue model'!H101,'Revenue model'!H102) -> 0.073 | I33: =CHOOSE(Cover!$I$15,'Revenue model'!I100,'Revenue model'!I101,'Revenue model'!I102) -> 0.074 | J33: =CHOOSE(Cover!$I$15,'Revenue model'!J100,'Revenue model'!J101,'Revenue model'!J102) -> 0.074 | K33: =CHOOSE(Cover!$I$15,'Revenue model'!K100,'Revenue model'!K101,'Revenue model'!K102) -> 0.075 | L33: =CHOOSE(Cover!$I$15,'Revenue model'!L100,'Revenue model'!L101,'Revenue model'!L102) -> 0.075 | N33: Marine Operating Margin: 7.3% in 2026E per management guidance (~7.3%), rising modestly to 7.4% in 2028E+. Historically compressed (7.0–8.3%) due to cost-plus contract mix in submarine programs. Limited margin expansion expected given program mix and Navy pricing dynamics.
A35: COMBAT SYSTEMS | N35: COMBAT SYSTEMS
A36: Military vehicles | B36: 4699 | C36: 4581 | D36: 5036 | E36: 5101 | F36: 4970 | G36: =F36*(1+G42) -> 5019.7 | H36: =G36*(1+H42) -> 5120.094 | I36: =H36*(1+I42) -> 5222.4959 | J36: =I36*(1+J42) -> 5326.9458 | K36: =J36*(1+K42) -> 5433.4847 | L36: =K36*(1+L42) -> 5542.1544 | N36: Military vehicles: 2% annual growth. Reflects steady Abrams tank and Stryker vehicle production. Historical growth volatile (-2.5% to +10%); 2% is a conservative steady-state reflecting stable but not accelerating Army procurement budgets.
A37: Weapons systems and munitions | B37: 2006 | C37: 2024 | D37: 2442 | E37: 2932 | F37: 3104 | G37: =F37*(1+G43) -> 3274.72 | H37: =G37*(1+H43) -> 3503.9504 | I37: =H37*(1+I43) -> 3749.2269 | J37: =I37*(1+J43) -> 4011.6728 | K37: =J37*(1+K43) -> 4292.4899 | L37: =K37*(1+L43) -> 4592.9642 | N37: Weapons systems & munitions: 7% annual growth (2027E+). Driven by sustained global ammunition restocking cycle post-Ukraine conflict and elevated allied nation replenishment orders. Multi-year demand cycle supported by historically low inventory levels. 2026E at 5.5% per guidance.
A38: Engineering and other services | B38: 646 | C38: 703 | D38: 790 | E38: 964 | F38: 1172 | G38: =F38*(1+G44) -> 1382.96 | H38: =G38*(1+H44) -> 1590.404 | I38: =H38*(1+I44) -> 1828.9646 | J38: =I38*(1+J44) -> 2103.3093 | K38: =J38*(1+K44) -> 2418.8057 | L38: =K38*(1+L44) -> 2781.6265 | N38: Engineering & other services: 15% annual growth (2027E+). Strong but moderated from 18% to reflect more sustainable long-term trajectory as European programs transition from engineering to production. Supported by Combat Systems book-to-bill of 2.1x and $27.2B backlog. 2026E at 18% per guidance.
A39: Total Combat Systems Revenue | B39: =B36+B37+B38 -> 7351 | C39: =C36+C37+C38 -> 7308 | D39: =D36+D37+D38 -> 8268 | E39: =E36+E37+E38 -> 8997 | F39: =F36+F37+F38 -> 9246 | G39: =G36+G37+G38 -> 9677.38 | H39: =H36+H37+H38 -> 10214.448 | I39: =I36+I37+I38 -> 10800.687 | ... L39: =L36+L37+L38 -> 12916.745
A41: Key Drivers:
A42: Military vehicles revenue growth | B42: n/a | C42: =C36/B36-1 -> -0.025111726 | D42: =D36/C36-1 -> 0.099323292 | E42: =E36/D36-1 -> 0.012907069 | F42: =F36/E36-1 -> -0.025681239 | G42: =CHOOSE(Cover!$I$16,'Revenue model'!G106,'Revenue model'!G107,'Revenue model'!G108) -> 0.01 | H42: =CHOOSE(Cover!$I$16,'Revenue model'!H106,'Revenue model'!H107,'Revenue model'!H108) -> 0.02 | I42: =CHOOSE(Cover!$I$16,'Revenue model'!I106,'Revenue model'!I107,'Revenue model'!I108) -> 0.02 | J42: =CHOOSE(Cover!$I$16,'Revenue model'!J106,'Revenue model'!J107,'Revenue model'!J108) -> 0.02 | K42: =CHOOSE(Cover!$I$16,'Revenue model'!K106,'Revenue model'!K107,'Revenue model'!K108) -> 0.02 | L42: =CHOOSE(Cover!$I$16,'Revenue model'!L106,'Revenue model'!L107,'Revenue model'!L108) -> 0.02
A43: Weapons systems revenue growth | B43: n/a | C43: =C37/B37-1 -> 0.0089730808 | D43: =D37/C37-1 -> 0.20652174 | E43: =E37/D37-1 -> 0.2006552 | F43: =F37/E37-1 -> 0.058663029 | G43: =CHOOSE(Cover!$I$16,'Revenue model'!G110,'Revenue model'!G111,'Revenue model'!G112) -> 0.055 | H43: =CHOOSE(Cover!$I$16,'Revenue model'!H110,'Revenue model'!H111,'Revenue model'!H112) -> 0.07 | I43: =CHOOSE(Cover!$I$16,'Revenue model'!I110,'Revenue model'!I111,'Revenue model'!I112) -> 0.07 | J43: =CHOOSE(Cover!$I$16,'Revenue model'!J110,'Revenue model'!J111,'Revenue model'!J112) -> 0.07 | K43: =CHOOSE(Cover!$I$16,'Revenue model'!K110,'Revenue model'!K111,'Revenue model'!K112) -> 0.07 | L43: =CHOOSE(Cover!$I$16,'Revenue model'!L110,'Revenue model'!L111,'Revenue model'!L112) -> 0.07
A44: Engineering and other services growth | C44: =C38/B38-1 -> 0.088235294 | D44: =D38/C38-1 -> 0.12375533 | E44: =E38/D38-1 -> 0.22025316 | F44: =F38/E38-1 -> 0.21576763 | G44: =CHOOSE(Cover!$I$16,'Revenue model'!G114,'Revenue model'!G115,'Revenue model'!G116) -> 0.18 | H44: =CHOOSE(Cover!$I$16,'Revenue model'!H114,'Revenue model'!H115,'Revenue model'!H116) -> 0.15 | I44: =CHOOSE(Cover!$I$16,'Revenue model'!I114,'Revenue model'!I115,'Revenue model'!I116) -> 0.15 | J44: =CHOOSE(Cover!$I$16,'Revenue model'!J114,'Revenue model'!J115,'Revenue model'!J116) -> 0.15 | K44: =CHOOSE(Cover!$I$16,'Revenue model'!K114,'Revenue model'!K115,'Revenue model'!K116) -> 0.15 | L44: =CHOOSE(Cover!$I$16,'Revenue model'!L114,'Revenue model'!L115,'Revenue model'!L116) -> 0.15
A45: Operating Earnings | B45: 1067 | C45: 1075 | D45: 1147 | E45: 1276 | F45: 1331 | G45: =G46*G39 -> 1364.5106 | H45: =H46*H39 -> 1440.2372 | I45: =I46*I39 -> 1533.6976 | J45: =J46*J39 -> 1624.7538 | K45: =K46*K39 -> 1736.7036 | L45: =L46*L39 -> 1847.0946
A46: Operating Margin | B46: =B45/B39 -> 0.14515032 | C46: =C45/C39 -> 0.14709907 | D46: =D45/D39 -> 0.13872762 | E46: =E45/E39 -> 0.14182505 | F46: =F45/F39 -> 0.14395414 | G46: =CHOOSE(Cover!$I$17,'Revenue model'!G118,'Revenue model'!G119,'Revenue model'!G120) -> 0.141 | H46: =CHOOSE(Cover!$I$17,'Revenue model'!H118,'Revenue model'!H119,'Revenue model'!H120) -> 0.141 | I46: =CHOOSE(Cover!$I$17,'Revenue model'!I118,'Revenue model'!I119,'Revenue model'!I120) -> 0.142 | J46: =CHOOSE(Cover!$I$17,'Revenue model'!J118,'Revenue model'!J119,'Revenue model'!J120) -> 0.142 | K46: =CHOOSE(Cover!$I$17,'Revenue model'!K118,'Revenue model'!K119,'Revenue model'!K120) -> 0.143 | L46: =CHOOSE(Cover!$I$17,'Revenue model'!L118,'Revenue model'!L119,'Revenue model'!L120) -> 0.143 | N46: Combat Operating Margin: 14.1% in 2026E per management guidance (~14.1%), rising to 14.2–14.3% by 2028–30E. Reflects strong mix shift toward higher-margin munitions and engineering services. Historical range: 13.9–14.8%. Modest expansion assumed as higher-margin revenue lines grow faster.
A48: TECHNOLOGIES | N48: TECHNOLOGIES
A49: Information technology (IT) services | B49: 8069 | C49: 8195 | D49: 8459 | E49: 8761 | F49: 9057 | G49: =F49*(1+G54) -> 9364.938 | H49: =G49*(1+H54) -> 9683.3459 | I49: =H49*(1+I54) -> 10012.58 | J49: =I49*(1+J54) -> 10353.007 | K49: =J49*(1+K54) -> 10705.01 | L49: =K49*(1+L54) -> 11068.98 | N49: IT services: 3.4% annual growth (held at 3-yr historical average of 2022–2025). Reflects steady federal IT modernization spend and GDIT contract wins. Formula uses =AVERAGE of prior 3 years’ growth rates. Conservative given large contract base and competitive rebid dynamics.
A50: C5ISR solutions | B50: 4388 | C50: 4297 | D50: 4463 | E50: 4366 | F50: 4414 | G50: =F50*(1+G55) -> 4458.14 | H50: =G50*(1+H55) -> 4502.7214 | I50: =H50*(1+I55) -> 4547.7486 | J50: =I50*(1+J55) -> 4593.2261 | K50: =J50*(1+K55) -> 4639.1584 | L50: =K50*(1+L55) -> 4685.5499 | N50: C5ISR solutions: 1% annual growth. Historical growth volatile (-2% to +4%); 1% reflects a maturing product cycle with stable but not expanding intelligence/surveillance programs. Below-average growth assumed due to potential program transitions.
A51: Total Technologies Revenue | B51: =B49+B50 -> 12457 | C51: =C49+C50 -> 12492 | D51: =D49+D50 -> 12922 | E51: =E49+E50 -> 13127 | F51: =F49+F50 -> 13471 | G51: =G49+G50 -> 13823.078 | H51: =H49+H50 -> 14186.067 | I51: =I49+I50 -> 14560.328 | ... L51: =L49+L50 -> 15754.53
A53: Key Drivers:
A54: IT services revenue growth | B54: n/a | C54: =C49/B49-1 -> 0.015615318 | D54: =D49/C49-1 -> 0.032214765 | E54: =E49/D49-1 -> 0.03570162 | F54: =F49/E49-1 -> 0.033786097 | G54: =CHOOSE(Cover!$I$18,'Revenue model'!G124,'Revenue model'!G125,'Revenue model'!G126) -> 0.034 | H54: =CHOOSE(Cover!$I$18,'Revenue model'!H124,'Revenue model'!H125,'Revenue model'!H126) -> 0.034 | I54: =CHOOSE(Cover!$I$18,'Revenue model'!I124,'Revenue model'!I125,'Revenue model'!I126) -> 0.034 | J54: =CHOOSE(Cover!$I$18,'Revenue model'!J124,'Revenue model'!J125,'Revenue model'!J126) -> 0.034 | K54: =CHOOSE(Cover!$I$18,'Revenue model'!K124,'Revenue model'!K125,'Revenue model'!K126) -> 0.034 | L54: =CHOOSE(Cover!$I$18,'Revenue model'!L124,'Revenue model'!L125,'Revenue model'!L126) -> 0.034
A55: C5ISR solutions revenue growth | B55: n/a | C55: =C50/B50-1 -> -0.020738377 | D55: =D50/C50-1 -> 0.038631603 | E55: =E50/D50-1 -> -0.021734259 | F55: =F50/E50-1 -> 0.010994045 | G55: =CHOOSE(Cover!$I$18,'Revenue model'!G128,'Revenue model'!G129,'Revenue model'!G130) -> 0.01 | H55: =CHOOSE(Cover!$I$18,'Revenue model'!H128,'Revenue model'!H129,'Revenue model'!H130) -> 0.01 | I55: =CHOOSE(Cover!$I$18,'Revenue model'!I128,'Revenue model'!I129,'Revenue model'!I130) -> 0.01 | J55: =CHOOSE(Cover!$I$18,'Revenue model'!J128,'Revenue model'!J129,'Revenue model'!J130) -> 0.01 | K55: =CHOOSE(Cover!$I$18,'Revenue model'!K128,'Revenue model'!K129,'Revenue model'!K130) -> 0.01 | L55: =CHOOSE(Cover!$I$18,'Revenue model'!L128,'Revenue model'!L129,'Revenue model'!L130) -> 0.01
A56: Operating Earnings | B56: 1275 | C56: 1227 | D56: 1202 | E56: 1260 | F56: 1277 | G56: =G57*G51 -> 1271.7232 | H56: =H57*H51 -> 1305.1182 | I56: =I57*I51 -> 1354.1105 | J56: =J57*J51 -> 1389.9997 | K56: =K57*K51 -> 1442.3518 | L56: =L57*L51 -> 1480.9258
A57: Operating Margin | B57: =B56/B51 -> 0.10235209 | C57: =C56/C51 -> 0.098222863 | D57: =D56/D51 -> 0.093019656 | E57: =E56/E51 -> 0.095985374 | F57: =F56/F51 -> 0.094796229 | G57: =CHOOSE(Cover!$I$19,'Revenue model'!G132,'Revenue model'!G133,'Revenue model'!G134) -> 0.092 | H57: =CHOOSE(Cover!$I$19,'Revenue model'!H132,'Revenue model'!H133,'Revenue model'!H134) -> 0.092 | I57: =CHOOSE(Cover!$I$19,'Revenue model'!I132,'Revenue model'!I133,'Revenue model'!I134) -> 0.093 | J57: =CHOOSE(Cover!$I$19,'Revenue model'!J132,'Revenue model'!J133,'Revenue model'!J134) -> 0.093 | K57: =CHOOSE(Cover!$I$19,'Revenue model'!K132,'Revenue model'!K133,'Revenue model'!K134) -> 0.094 | L57: =CHOOSE(Cover!$I$19,'Revenue model'!L132,'Revenue model'!L133,'Revenue model'!L134) -> 0.094 | N57: Technologies Operating Margin: 9.2% in 2026E per management guidance (~9.2%), rising to 9.3–9.4% by 2028–30E. Historical range: 9.3–10.2%. Near-term margin compression from GDIT integration costs and competitive pricing, with gradual recovery as contract mix improves.
A59: CONSOLIDATED REVENUE | N59: CONSOLIDATED REVENUE & EARNINGS
A60: Aerospace | B60: =B10 -> 8135 | C60: =C10 -> 8567 | D60: =D10 -> 8621 | E60: =E10 -> 11249 | F60: =F10 -> 13110 | G60: =G10 -> 13604.645 | H60: =H10 -> 14117.159 | I60: =I10 -> 14749.877 | ... L60: =L10 -> 16813.909 | N60: Aerospace revenue: Sum of aircraft manufacturing + services. Flows from bottom-up drivers above.
A61: Marine Systems | B61: =B26 -> 10526 | C61: =C26 -> 11040 | D61: =D26 -> 12461 | E61: =E26 -> 14343 | F61: =F26 -> 16723 | G61: =G26 -> 17717.18 | H61: =H26 -> 18776.251 | I61: =I26 -> 19904.627 | ... L61: =L26 -> 23857.383 | N61: Marine Systems revenue: Sum of submarines + surface ships + repair services. Flows from sub-segment growth rates above.
A62: Combat Systems | B62: =B39 -> 7351 | C62: =C39 -> 7308 | D62: =D39 -> 8268 | E62: =E39 -> 8997 | F62: =F39 -> 9246 | G62: =G39 -> 9677.38 | H62: =H39 -> 10214.448 | I62: =I39 -> 10800.687 | ... L62: =L39 -> 12916.745 | N62: Combat Systems revenue: Sum of military vehicles + weapons + engineering. Flows from sub-segment growth rates above.
A63: Technologies | B63: =B51 -> 12457 | C63: =C51 -> 12492 | D63: =D51 -> 12922 | E63: =E51 -> 13127 | F63: =F51 -> 13471 | G63: =G51 -> 13823.078 | H63: =H51 -> 14186.067 | I63: =I51 -> 14560.328 | ... L63: =L51 -> 15754.53 | N63: Technologies revenue: Sum of IT services + C5ISR. Flows from sub-segment growth rates above.
A64: Total Consolidated Revenue | B64: =B60+B61+B62+B63 -> 38469 | C64: =C60+C61+C62+C63 -> 39407 | D64: =D60+D61+D62+D63 -> 42272 | E64: =E60+E61+E62+E63 -> 47716 | F64: =F60+F61+F62+F63 -> 52550 | G64: =G60+G61+G62+G63 -> 54822.283 | H64: =H60+H61+H62+H63 -> 57293.926 | I64: =I60+I61+I62+I63 -> 60015.52 | ... L64: =L60+L61+L62+L63 -> 69342.567 | N64: Total consolidated revenue: Sum of four segments. No intercompany eliminations modeled (historically immaterial).
A66: YoY Revenue Growth | B66: n/a | C66: =C64/B64-1 -> 0.02438327 | D66: =D64/C64-1 -> 0.072702819 | E66: =E64/D64-1 -> 0.12878501 | F66: =F64/E64-1 -> 0.10130774 | G66: =G64/F64-1 -> 0.043240398 | H66: =H64/G64-1 -> 0.045084641 | I66: =I64/H64-1 -> 0.047502309 | J66: =J64/I64-1 -> 0.048673895 | ... L66: =L64/K64-1 -> 0.049994858
A68: CONSOLIDATED OPERATING EARNINGS
A69: Aerospace | B69: =B19 -> 1031 | C69: =C19 -> 1130 | D69: =D19 -> 1182 | E69: =E19 -> 1464 | F69: =F19 -> 1746 | G69: =G19 -> 1904.6503 | H69: =H19 -> 1976.4023 | I69: =I19 -> 2064.9828 | ... L69: =L19 -> 2353.9472
A70: Marine Systems | B70: =B31 -> 874 | C70: =C31 -> 897 | D70: =D31 -> 874 | E70: =E31 -> 935 | F70: =F31 -> 1177 | G70: =G31 -> 1293.3541 | H70: =H31 -> 1370.6663 | I70: =I31 -> 1472.9424 | ... L70: =L31 -> 1789.3037
A71: Combat Systems | B71: =B45 -> 1067 | C71: =C45 -> 1075 | D71: =D45 -> 1147 | E71: =E45 -> 1276 | F71: =F45 -> 1331 | G71: =G45 -> 1364.5106 | H71: =H45 -> 1440.2372 | I71: =I45 -> 1533.6976 | ... L71: =L45 -> 1847.0946
A72: Technologies | B72: =B56 -> 1275 | C72: =C56 -> 1227 | D72: =D56 -> 1202 | E72: =E56 -> 1260 | F72: =F56 -> 1277 | G72: =G56 -> 1271.7232 | H72: =H56 -> 1305.1182 | I72: =I56 -> 1354.1105 | ... L72: =L56 -> 1480.9258
A73: Corporate | B73: -84 | C73: -118 | D73: -160 | E73: -139 | F73: -175 | G73: -160 | H73: -160 | I73: -160 | J73: -160 | K73: -160 | L73: -160 | N73: Corporate expense: Held flat at -$160M for projection years. Historical range: -$84M to -$175M. Conservative flat assumption; no significant change in corporate overhead structure expected.
A74: Total Operating Earnings | B74: =B69+B70+B71+B72+B73 -> 4163 | C74: =C69+C70+C71+C72+C73 -> 4211 | D74: =D69+D70+D71+D72+D73 -> 4245 | E74: =E69+E70+E71+E72+E73 -> 4796 | F74: =F69+F70+F71+F72+F73 -> 5356 | G74: =G69+G70+G71+G72+G73 -> 5674.2382 | H74: =H69+H70+H71+H72+H73 -> 5932.424 | I74: =I69+I70+I71+I72+I73 -> 6265.7333 | ... L74: =L69+L70+L71+L72+L73 -> 7311.2713
A75: Consolidated Operating Margin | B75: =B74/B64 -> 0.10821701 | C75: =C74/C64 -> 0.10685919 | D75: =D74/D64 -> 0.10042108 | E75: =E74/E64 -> 0.10051136 | F75: =F74/F64 -> 0.10192198 | G75: =G74/G64 -> 0.10350241 | H75: =H74/H64 -> 0.10354368 | I75: =I74/I64 -> 0.10440188 | ... L75: =L74/L64 -> 0.10543699 | N75: Consolidated operating margin: Derived (total operating earnings / total revenue). Projects ~10.2–10.6% over forecast, gradually expanding from 10.2% (2025) as segment margins improve. Consistent with management’s stated goal of margin expansion.
A77: DoD Budget YoY Growth | C77: 0.057 | D77: 0.044 | E77: 0.018 | F77: 0.001 | G77: 0.01 | H77: 0.04 | I77: 0.04 | J77: 0.04 | K77: 0.04 | L77: 0.04 | N77: DoD budget YoY growth: FY2021–2026 based on enacted NDAA levels. FY2027–2031E estimated at ~4% nominal (CBO baseline: 0.9% real + ~3% inflation). Note: $1.5T FY2027 proposal, if enacted, would represent ~66% increase.
A78: GD Defense Revenue YoY Growth | C78: =(C26+C39+C51)/(B26+B39+B51)-1 -> 0.016680952 | D78: =(D26+D39+D51)/(C26+C39+C51)-1 -> 0.09114786 | E78: =(E26+E39+E51)/(D26+D39+D51)-1 -> 0.083682506 | F78: =(F26+F39+F51)/(E26+E39+E51)-1 -> 0.081525763 | G78: =(G26+G39+G51)/(F26+F39+F51)-1 -> 0.045071957 | H78: =(H26+H39+H51)/(G26+G39+G51)-1 -> 0.047531324 | I78: =(I26+I39+I51)/(H26+H39+H51)-1 -> 0.04837962 | J78: =(J26+J39+J51)/(I26+I39+I51)-1 -> 0.04996246 | ... L78: =(L26+L39+L51)/(K26+K39+K51)-1 -> 0.051756172 | N78: GD defense revenue growth: YoY growth of Marine + Combat + Technologies (excludes Aerospace, which is largely commercial Gulfstream). Comparable to DoD budget growth for assessing whether GD's defense segments are outpacing government spending.
A80: BACKLOG ANALYSIS
A81: Aerospace | B81: 16293 | C81: 19516 | D81: 20454 | E81: 19693 | F81: 21828
A82: Marine Systems | B82: 44855 | C82: 45699 | D82: 45896 | E82: 39818 | F82: 52340
A83: Combat Systems | B83: 13093 | C83: 13251 | D83: 14537 | E83: 16980 | F83: 27218
A84: Technologies | B84: 13353 | C84: 12671 | D84: 12740 | E84: 14106 | F84: 16660
A85: Total Backlog | B85: =SUM(B81:B84) -> 87594 | C85: =SUM(C81:C84) -> 91137 | D85: =SUM(D81:D84) -> 93627 | E85: =SUM(E81:E84) -> 90597 | F85: =SUM(F81:F84) -> 118046 | G85: =SUM(G81:G84) -> 0 | H85: =SUM(H81:H84) -> 0 | I85: =SUM(I81:I84) -> 0 | ... L85: =SUM(L81:L84) -> 0
A90: sensitivity
A91: Submarine revenue growth
A92: bull | G92: =G93+0.5% -> 0.075 | H92: =H93+0.5% -> 0.075 | I92: =I93+0.5% -> 0.075 | J92: =J93+0.5% -> 0.075 | K92: =K93+0.5% -> 0.075 | L92: =L93+0.5% -> 0.075
A93: base | G93: 0.07 | H93: 0.07 | I93: 0.07 | J93: 0.07 | K93: 0.07 | L93: 0.07
A94: bear | G94: =G93-0.5% -> 0.065 | H94: =H93-0.5% -> 0.065 | I94: =I93-0.5% -> 0.065 | J94: =J93-0.5% -> 0.065 | K94: =K93-0.5% -> 0.065 | L94: =L93-0.5% -> 0.065
A95: Surface ships revenue growth
A96: bull | G96: =G97+0.5% -> 0.035 | H96: =H97+0.5% -> 0.035 | I96: =I97+0.5% -> 0.035 | J96: =J97+0.5% -> 0.045 | K96: =K97+0.5% -> 0.045 | L96: =L97+0.5% -> 0.045
A97: base | G97: 0.03 | H97: 0.03 | I97: 0.03 | J97: 0.04 | K97: 0.04 | L97: 0.04
A98: bear | G98: =G97-0.5% -> 0.025 | H98: =H97-0.5% -> 0.025 | I98: =I97-0.5% -> 0.025 | J98: =J97-0.5% -> 0.035 | K98: =K97-0.5% -> 0.035 | L98: =L97-0.5% -> 0.035
A99: Operating Margin
A100: bull | G100: =G101+0.1% -> 0.074 | H100: =H101+0.1% -> 0.074 | I100: =I101+0.1% -> 0.075 | J100: =J101+0.1% -> 0.075 | K100: =K101+0.1% -> 0.076 | L100: =L101+0.1% -> 0.076
A101: base | G101: 0.073 | H101: 0.073 | I101: 0.074 | J101: 0.074 | K101: 0.075 | L101: 0.075
A102: bear | G102: =G101-0.1% -> 0.072 | H102: =H101-0.1% -> 0.072 | I102: =I101-0.1% -> 0.073 | J102: =J101-0.1% -> 0.073 | K102: =K101-0.1% -> 0.074 | L102: =L101-0.1% -> 0.074
A105: Military vehicles revenue growth
A106: bull | G106: =G107+0.5% -> 0.015 | H106: =H107+0.5% -> 0.025 | I106: =I107+0.5% -> 0.025 | J106: =J107+0.5% -> 0.025 | K106: =K107+0.5% -> 0.025 | L106: =L107+0.5% -> 0.025
A107: base | G107: 0.01 | H107: 0.02 | I107: 0.02 | J107: 0.02 | K107: 0.02 | L107: 0.02
A108: bear | G108: =G107-0.5% -> 0.005 | H108: =H107-0.5% -> 0.015 | I108: =I107-0.5% -> 0.015 | J108: =J107-0.5% -> 0.015 | K108: =K107-0.5% -> 0.015 | L108: =L107-0.5% -> 0.015
A109: Weapons systems revenue growth
A110: bull | G110: =G111+0.5% -> 0.06 | H110: =H111+0.5% -> 0.075 | I110: =I111+0.5% -> 0.075 | J110: =J111+0.5% -> 0.075 | K110: =K111+0.5% -> 0.075 | L110: =L111+0.5% -> 0.075
A111: base | G111: 0.055 | H111: 0.07 | I111: 0.07 | J111: 0.07 | K111: 0.07 | L111: 0.07
A112: bear | G112: =G111-0.5% -> 0.05 | H112: =H111-0.5% -> 0.065 | I112: =I111-0.5% -> 0.065 | J112: =J111-0.5% -> 0.065 | K112: =K111-0.5% -> 0.065 | L112: =L111-0.5% -> 0.065
A113: Engineering and other services growth
A114: bull | G114: =G115+0.5% -> 0.185 | H114: =H115+0.5% -> 0.155 | I114: =I115+0.5% -> 0.155 | J114: =J115+0.5% -> 0.155 | K114: =K115+0.5% -> 0.155 | L114: =L115+0.5% -> 0.155
A115: base | G115: 0.18 | H115: 0.15 | I115: 0.15 | J115: 0.15 | K115: 0.15 | L115: 0.15
A116: bear | G116: =G115-0.5% -> 0.175 | H116: =H115-0.5% -> 0.145 | I116: =I115-0.5% -> 0.145 | J116: =J115-0.5% -> 0.145 | K116: =K115-0.5% -> 0.145 | L116: =L115-0.5% -> 0.145
A117: Operating Margin
A118: bull | G118: =G119+0.1% -> 0.142 | H118: =H119+0.1% -> 0.142 | I118: =I119+0.1% -> 0.143 | J118: =J119+0.1% -> 0.143 | K118: =K119+0.1% -> 0.144 | L118: =L119+0.1% -> 0.144
A119: base | G119: 0.141 | H119: 0.141 | I119: 0.142 | J119: 0.142 | K119: 0.143 | L119: 0.143
A120: bear | G120: =G119-0.1% -> 0.14 | H120: =H119-0.1% -> 0.14 | I120: =I119-0.1% -> 0.141 | J120: =J119-0.1% -> 0.141 | K120: =K119-0.1% -> 0.142 | L120: =L119-0.1% -> 0.142
...

Sheet Income statement
A1: General Dynamics Corporation
A2: Consolidated Statement of Earnings
A3: (Dollars in millions, except per-share amounts)
A5: Year Ended December 31 | B5: 2021 | C5: 2022 | D5: 2023 | E5: 2024 | F5: 2025 | G5: 2026 | H5: 2027 | I5: 2028 | J5: 2029 | K5: 2030 | L5: 2031 | N5: Projection Assumptions
A6: Revenue:
A7: Products | B7: 22428 | C7: 23022 | D7: 24595 | E7: 28635 | F7: 33021 | G7: ='Revenue model'!G8+'Revenue model'!G23+'Revenue model'!G24+'Revenue model'!G36+'Revenue model'!G37 -> 34527.735 | H7: ='Revenue model'!H8+'Revenue model'!H23+'Revenue model'!H24+'Revenue model'!H36+'Revenue model'!H37 -> 36210.719 | I7: ='Revenue model'!I8+'Revenue model'!I23+'Revenue model'!I24+'Revenue model'!I36+'Revenue model'!I37 -> 38091.078 | J7: ='Revenue model'!J8+'Revenue model'!J23+'Revenue model'!J24+'Revenue model'!J36+'Revenue model'!J37 -> 40112.922 | K7: ='Revenue model'!K8+'Revenue model'!K23+'Revenue model'!K24+'Revenue model'!K36+'Revenue model'!K37 -> 42253.349 | L7: ='Revenue model'!L8+'Revenue model'!L23+'Revenue model'!L24+'Revenue model'!L36+'Revenue model'!L37 -> 44519.826 | N7: Product revenue: Linked from Revenue model. Sum of aircraft mfg, submarine, surface ships, military vehicles, and weapons systems revenue across all four segments.
A8: Services | B8: 16041 | C8: 16385 | D8: 17677 | E8: 19081 | F8: 19529 | G8: ='Revenue model'!G9+'Revenue model'!G25+'Revenue model'!G38+'Revenue model'!G49+'Revenue model'!G50 -> 20294.548 | H8: ='Revenue model'!H9+'Revenue model'!H25+'Revenue model'!H38+'Revenue model'!H49+'Revenue model'!H50 -> 21083.207 | I8: ='Revenue model'!I9+'Revenue model'!I25+'Revenue model'!I38+'Revenue model'!I49+'Revenue model'!I50 -> 21924.442 | J8: ='Revenue model'!J9+'Revenue model'!J25+'Revenue model'!J38+'Revenue model'!J49+'Revenue model'!J50 -> 22823.787 | K8: ='Revenue model'!K9+'Revenue model'!K25+'Revenue model'!K38+'Revenue model'!K49+'Revenue model'!K50 -> 23787.514 | L8: ='Revenue model'!L9+'Revenue model'!L25+'Revenue model'!L38+'Revenue model'!L49+'Revenue model'!L50 -> 24822.74 | N8: Service revenue: Linked from Revenue model. Sum of aircraft services, marine repair, combat engineering, IT services, and C5ISR across all four segments.
A9: Total Revenue | B9: =B7+B8 -> 38469 | C9: =C7+C8 -> 39407 | D9: =D7+D8 -> 42272 | E9: =E7+E8 -> 47716 | F9: =F7+F8 -> 52550 | G9: =G7+G8 -> 54822.283 | H9: =H7+H8 -> 57293.926 | I9: =I7+I8 -> 60015.52 | ... L9: =L7+L8 -> 69342.567
A11: Operating costs and expenses:
A12: Products | B12: -18524 | C12: -18981 | D12: -20591 | E12: -24332 | F12: -27965 | G12: =G7*($F$12/$F$7) -> -29241.032 | H12: =H7*($F$12/$F$7) -> -30666.326 | I12: =I7*($F$12/$F$7) -> -32258.775 | J12: =J7*($F$12/$F$7) -> -33971.045 | K12: =K7*($F$12/$F$7) -> -35783.741 | L12: =L7*($F$12/$F$7) -> -37703.187 | N12: Product COGS: Allocated as a share of total OpEx (excl. G&A) using the 2025 actual product-to-service COGS split ratio (~62.8%/37.2%). Assumes product vs. service cost mix remains stable. Historically stable at 48–53% of revenue.
A13: Services | B13: -13537 | C13: -13804 | D13: -15009 | E13: -16020 | F13: -16634 | G13: =G8*($F$13/$F$8) -> -17286.062 | H13: =H8*($F$13/$F$8) -> -17957.81 | I13: =I8*($F$13/$F$8) -> -18674.339 | J13: =J8*($F$13/$F$8) -> -19440.364 | K13: =K8*($F$13/$F$8) -> -20261.227 | L13: =L8*($F$13/$F$8) -> -21142.99 | N13: Service COGS: Remainder of total OpEx (excl. G&A) after product COGS allocation. Same split methodology as products. Historically stable at 31–35% of revenue.
A14: General and administrative (G&A) | B14: -2245 | C14: -2411 | D14: -2427 | E14: -2568 | F14: -2595 | G14: =G9*($F$14/$F$9) -> -2707.2088 | H14: =H9*($F$14/$F$9) -> -2829.2624 | I14: =I9*($F$14/$F$9) -> -2963.6589 | J14: =J9*($F$14/$F$9) -> -3107.9117 | K14: =K9*($F$14/$F$9) -> -3261.1996 | L14: =L9*($F$14/$F$9) -> -3424.2428 | N14: G&A expense: Projected as a % of revenue using the 2025 actual G&A-to-revenue ratio (~4.9%), rounded. Historical range: 4.9–5.8% of revenue. Declining trend reflects operating leverage as revenue scales faster than corporate overhead.
A15: Total Operating Costs and Expenses | B15: =B12+B13+B14 -> -34306 | C15: =C12+C13+C14 -> -35196 | D15: =D12+D13+D14 -> -38027 | E15: =E12+E13+E14 -> -42920 | F15: =F12+F13+F14 -> -47194 | G15: =G17-G9 -> -49148.045 | H15: =H17-H9 -> -51361.502 | I15: =I17-I9 -> -53749.786 | J15: =J17-J9 -> -56360.337 | K15: =K17-K9 -> -59084.102 | L15: =L17-L9 -> -62031.295
A17: Operating Earnings | B17: =B9+B15 -> 4163 | C17: =C9+C15 -> 4211 | D17: =D9+D15 -> 4245 | E17: =E9+E15 -> 4796 | F17: =F9+F15 -> 5356 | G17: ='Revenue model'!G74 -> 5674.2382 | H17: ='Revenue model'!H74 -> 5932.424 | I17: ='Revenue model'!I74 -> 6265.7333 | J17: ='Revenue model'!J74 -> 6576.3719 | K17: ='Revenue model'!K74 -> 6956.7607 | L17: ='Revenue model'!L74 -> 7311.2713
A19: Other, net | B19: 134 | C19: 189 | D19: 82 | E19: 68 | F19: 61 | G19: 50 | H19: 50 | I19: 50 | J19: 50 | K19: 50 | L19: 50 | N19: Other, net: Flat at $50M for all projection years. Historical range volatile ($61–$189M) including gains/losses on investments and other non-operating items. $50M is a conservative normalized estimate below the 2021–2025 average of ~$97M.
A20: Interest, net | B20: -424 | C20: -364 | D20: -343 | E20: -324 | F20: -314 | G20: =-(Schedules!G95) -> -339.20223 | H20: =-(Schedules!H95) -> -370.28125 | I20: =-(Schedules!I95) -> -411.705 | J20: =-(Schedules!J95) -> -454.12375 | K20: =-(Schedules!K95) -> -497.975 | L20: =-(Schedules!L95) -> -516.85 | N20: Interest expense, net: Linked from Schedules debt schedule. Calculated as weighted-average interest rate × average total debt balance. Rate held at ~4.1–4.25% reflecting blended coupon on existing fixed-rate notes plus new issuances.
A22: Earnings Before Income Tax | B22: =B17+B19+B20 -> 3873 | C22: =C17+C19+C20 -> 4036 | D22: =D17+D19+D20 -> 3984 | E22: =E17+E19+E20 -> 4540 | F22: =F17+F19+F20 -> 5103 | G22: =G17+G19+G20 -> 5385.036 | H22: =H17+H19+H20 -> 5612.1428 | I22: =I17+I19+I20 -> 5904.0283 | ... L22: =L17+L19+L20 -> 6844.4213
A24: Provision for income tax, net | B24: -616 | C24: -646 | D24: -669 | E24: -758 | F24: -893 | G24: =G22*G30 -> -942.35491 | H24: =H22*H30 -> -982.09749 | I24: =I22*I30 -> -1033.176 | J24: =J22*J30 -> -1080.1132 | K24: =K22*K30 -> -1139.0056 | L24: =L22*L30 -> -1197.7402 | N24: Income tax provision: Projected using 2025 effective tax rate (~17.5%) held constant. Historical range: 15.9–17.5%. The 2025 rate is used as the best current estimate; no significant tax law changes assumed. Applied as EBT × (tax provision / EBT from 2025).
A26: Net Earnings | B26: =B22+B24 -> 3257 | C26: =C22+C24 -> 3390 | D26: =D22+D24 -> 3315 | E26: =E22+E24 -> 3782 | F26: =F22+F24 -> 4210 | G26: =G22+G24 -> 4442.681 | H26: =H22+H24 -> 4630.0453 | I26: =I22+I24 -> 4870.8523 | ... L26: =L22+L24 -> 5646.6811
A28: Key Margins
A29: Operating Margin | B29: =B17/B9 -> 0.10821701 | C29: =C17/C9 -> 0.10685919 | D29: =D17/D9 -> 0.10042108 | E29: =E17/E9 -> 0.10051136 | F29: =F17/F9 -> 0.10192198 | G29: =G17/G9 -> 0.10350241 | H29: =H17/H9 -> 0.10354368 | I29: =I17/I9 -> 0.10440188 | ... L29: =L17/L9 -> 0.10543699
A30: Effective Tax Rate | B30: =B24/B22 -> -0.15904983 | C30: =C24/C22 -> -0.16005946 | D30: =D24/D22 -> -0.16792169 | E30: =E24/E22 -> -0.16696035 | F30: =F24/F22 -> -0.1749951 | G30: =F30 -> -0.1749951 | H30: =G30 -> -0.1749951 | I30: =H30 -> -0.1749951 | J30: =I30 -> -0.1749951 | K30: =J30 -> -0.1749951 | L30: =K30 -> -0.1749951
A31: Net Margin | B31: =B26/B9 -> 0.084665575 | C31: =C26/C9 -> 0.086025325 | D31: =D26/D9 -> 0.078420704 | E31: =E26/E9 -> 0.079260625 | F31: =F26/F9 -> 0.080114177 | G31: =G26/G9 -> 0.08103787 | H31: =H26/H9 -> 0.080812149 | I31: =I26/I9 -> 0.081159879 | ... L31: =L26/L9 -> 0.081431672
A36: Common size statement | B36: 2021 | C36: 2022 | D36: 2023 | E36: 2024 | F36: 2025 | G36: 2026 | H36: 2027 | I36: 2028 | J36: 2029 | K36: 2030 | L36: 2031
A37: Revenue:
A38: Products | B38: =B7/B9 -> 0.5830149 | C38: =C7/C9 -> 0.58421093 | D38: =D7/D9 -> 0.58182721 | E38: =E7/E9 -> 0.60011317 | F38: =F7/F9 -> 0.62837298 | G38: =G7/G9 -> 0.62981206 | H38: =H7/H9 -> 0.63201672 | I38: =I7/I9 -> 0.63468713 | ... L38: =L7/L9 -> 0.64202738
A39: Services | B39: =B8/B9 -> 0.4169851 | C39: =C8/C9 -> 0.41578907 | D39: =D8/D9 -> 0.41817279 | E39: =E8/E9 -> 0.39988683 | F39: =F8/F9 -> 0.37162702 | G39: =G8/G9 -> 0.37018794 | H39: =H8/H9 -> 0.36798328 | I39: =I8/I9 -> 0.36531287 | ... L39: =L8/L9 -> 0.35797262
A40: Total Revenue | B40: =B9/B9 -> 1 | C40: =C9/C9 -> 1 | D40: =D9/D9 -> 1 | E40: =E9/E9 -> 1 | F40: =F9/F9 -> 1 | G40: =G9/G9 -> 1 | H40: =H9/H9 -> 1 | I40: =I9/I9 -> 1 | ... L40: =L9/L9 -> 1
A42: Operating costs and expenses:
A43: Products | B43: =B12/B7 -> -0.82593187 | C43: =C12/C7 -> -0.82447224 | D43: =D12/D7 -> -0.83720268 | E43: =E12/E7 -> -0.84972935 | F43: =F12/F7 -> -0.84688532 | G43: =G12/G7 -> -0.84688532 | H43: =H12/H7 -> -0.84688532 | I43: =I12/I7 -> -0.84688532 | ... L43: =L12/L7 -> -0.84688532
A44: Services | B44: =B13/B8 -> -0.84390001 | C44: =C13/C8 -> -0.84247788 | D44: =D13/D8 -> -0.84906941 | E44: =E13/E8 -> -0.83957864 | F44: =F13/F8 -> -0.85175892 | G44: =G13/G8 -> -0.85175892 | H44: =H13/H8 -> -0.85175892 | I44: =I13/I8 -> -0.85175892 | ... L44: =L13/L8 -> -0.85175892
A45: General and administrative (G&A) | B45: =B14/B9 -> -0.058358678 | C45: =C14/C9 -> -0.061182023 | D45: =D14/D9 -> -0.057413891 | E45: =E14/E9 -> -0.053818426 | F45: =F14/F9 -> -0.049381541 | G45: =G14/G9 -> -0.049381541 | H45: =H14/H9 -> -0.049381541 | I45: =I14/I9 -> -0.049381541 | ... L45: =L14/L9 -> -0.049381541
A46: Total Operating Costs and Expenses | B46: =B15/B9 -> -0.89178299 | C46: =C15/C9 -> -0.89314081 | D46: =D15/D9 -> -0.89957892 | E46: =E15/E9 -> -0.89948864 | F46: =F15/F9 -> -0.89807802 | G46: =G15/G9 -> -0.89649759 | H46: =H15/H9 -> -0.89645632 | I46: =I15/I9 -> -0.89559812 | ... L46: =L15/L9 -> -0.89456301
A48: Operating Earnings | B48: =B17/B9 -> 0.10821701 | C48: =C17/C9 -> 0.10685919 | D48: =D17/D9 -> 0.10042108 | E48: =E17/E9 -> 0.10051136 | F48: =F17/F9 -> 0.10192198 | G48: =G17/G9 -> 0.10350241 | H48: =H17/H9 -> 0.10354368 | I48: =I17/I9 -> 0.10440188 | ... L48: =L17/L9 -> 0.10543699
A50: Other, net | B50: =B19/B9 -> 0.0034833242 | C50: =C19/C9 -> 0.0047961022 | D50: =D19/D9 -> 0.0019398183 | E50: =E19/E9 -> 0.0014250985 | F50: =F19/F9 -> 0.0011607992 | G50: =G19/G9 -> 0.0009120379 | H50: =H19/H9 -> 0.00087269286 | I50: =I19/I9 -> 0.00083311784 | ... L50: =L19/L9 -> 0.00072105782
A51: Interest, net | B51: =B20/B9 -> -0.011021862 | C51: =C20/C9 -> -0.0092369376 | D51: =D20/D9 -> -0.0081141181 | E51: =E20/E9 -> -0.0067901752 | F51: =F20/F9 -> -0.0059752617 | G51: =G20/G9 -> -0.0061873057 | H51: =H20/H9 -> -0.0064628361 | I51: =I20/I9 -> -0.0068599756 | ... L51: =L20/L9 -> -0.0074535747
A53: Earnings Before Income Tax | B53: =B22/B9 -> 0.10067847 | C53: =C22/C9 -> 0.10241835 | D53: =D22/D9 -> 0.094246783 | E53: =E22/E9 -> 0.095146282 | F53: =F22/F9 -> 0.097107517 | G53: =G22/G9 -> 0.098227138 | H53: =H22/H9 -> 0.097953538 | I53: =I22/I9 -> 0.098375026 | ... L53: =L22/L9 -> 0.09870447
A55: Provision for income tax, net | B55: =B24/B9 -> -0.016012893 | C55: =C24/C9 -> -0.016393027 | D55: =D24/D9 -> -0.015826079 | E55: =E24/E9 -> -0.015885657 | F55: =F24/F9 -> -0.01699334 | G55: =G24/G9 -> -0.017189268 | H55: =H24/H9 -> -0.017141389 | I55: =I24/I9 -> -0.017215148 | ... L55: =L24/L9 -> -0.017272799
A57: Net Earnings | B57: =B26/B9 -> 0.084665575 | C57: =C26/C9 -> 0.086025325 | D57: =D26/D9 -> 0.078420704 | E57: =E26/E9 -> 0.079260625 | F57: =F26/F9 -> 0.080114177 | G57: =G26/G9 -> 0.08103787 | H57: =H26/H9 -> 0.080812149 | I57: =I26/I9 -> 0.081159879 | ... L57: =L26/L9 -> 0.081431672

Sheet Balance sheet
A1: General Dynamics Corporation
A2: Consolidated Balance Sheet
A3: (Dollars in millions)
A5: 46387 | B5: 2021 | C5: 2022 | D5: 2023 | E5: 2024 | F5: 2025 | G5: 2026 | H5: 2027 | I5: 2028 | J5: 2029 | K5: 2030 | L5: 2031 | N5: Projection Assumptions
A6: ASSETS
A7: Current assets:
A8: Cash and equivalents | B8: 1603 | C8: 1242 | D8: 1913 | E8: 1697 | F8: 2333 | G8: ='Cash flow'!G56 -> 2844.2744 | H8: ='Cash flow'!H56 -> 3601.6706 | I8: ='Cash flow'!I56 -> 4561.0231 | J8: ='Cash flow'!J56 -> 5725.1223 | K8: ='Cash flow'!K56 -> 7167.2798 | L8: ='Cash flow'!L56 -> 8521.6069
A9: Accounts receivable | B9: 3041 | C9: 3008 | D9: 3004 | E9: 2977 | F9: 2406 | G9: =Schedules!G116 -> 2553.3666 | H9: =Schedules!H116 -> 2668.4842 | I9: =Schedules!I116 -> 2795.2434 | J9: =Schedules!J116 -> 2931.2988 | K9: =Schedules!K116 -> 3075.8758 | L9: =Schedules!L116 -> 3229.6538 | N9: Accounts receivable: Projected using DSO of 17 days (held flat). Historical DSO ranged 17–29 days; 17 days matches 2025 actual and reflects GD’s efficient collections on government contracts with predictable payment cycles.
A10: Unbilled receivables | B10: 8498 | C10: 8795 | D10: 7997 | E10: 8248 | F10: 8380 | G10: =G59*'Income statement'!G9 -> 8771.5653 | H10: =H59*'Income statement'!H9 -> 9167.0281 | I10: =I59*'Income statement'!I9 -> 9602.4831 | J10: =J59*'Income statement'!J9 -> 10069.873 | K10: =K59*'Income statement'!K9 -> 10566.538 | L10: =L59*'Income statement'!L9 -> 11094.811 | N10: Unbilled receivables: Projected at 16% of revenue (held flat). Historical range: 16–22% of revenue. 2025 actual of 15.9% used as baseline. Reflects contract revenue recognition timing on long-duration defense programs.
A11: Inventories | B11: 5340 | C11: 6322 | D11: 8578 | E11: 9724 | F11: 9232 | G11: =Schedules!G117 -> 9560.3618 | H11: =Schedules!H117 -> 9991.2608 | I11: =Schedules!I117 -> 10465.708 | J11: =Schedules!J117 -> 10974.947 | K11: =Schedules!K117 -> 11516.089 | L11: =Schedules!L117 -> 12091.68 | N11: Inventories: Projected using DSI of 75 days (held flat). Historical DSI ranged 61–88 days; 75 days reflects 2025 actual and normalized inventory levels after the 2023–2024 Gulfstream production ramp build-up.
A12: Other current assets | B12: 1505 | C12: 1696 | D12: 2123 | E12: 1740 | F12: 1897 | G12: =G61*'Income statement'!G9 -> 2192.8913 | H12: =H61*'Income statement'!H9 -> 2291.757 | I12: =I61*'Income statement'!I9 -> 2400.6208 | J12: =J61*'Income statement'!J9 -> 2517.4683 | K12: =K61*'Income statement'!K9 -> 2641.6345 | L12: =L61*'Income statement'!L9 -> 2773.7027 | N12: Other current assets: Projected at 4.0% of revenue (held flat). Historical range: 3.6–5.0%. Stable relationship to revenue; includes prepaid expenses and other miscellaneous current items.
A13: Total current assets | B13: =SUM(B8:B12) -> 19987 | C13: =SUM(C8:C12) -> 21063 | D13: =SUM(D8:D12) -> 23615 | E13: =SUM(E8:E12) -> 24386 | F13: =SUM(F8:F12) -> 24248 | G13: =SUM(G8:G12) -> 25922.459 | H13: =SUM(H8:H12) -> 27720.201 | I13: =SUM(I8:I12) -> 29825.079 | ... L13: =SUM(L8:L12) -> 37711.454
A15: Noncurrent assets:
A16: Property, plant and equipment, net | B16: 5417 | C16: 5900 | D16: 6198 | E16: 6467 | F16: 7525 | G16: =Schedules!G50 -> 8880 | H16: =Schedules!H50 -> 10065 | I16: =Schedules!I50 -> 10960 | J16: =Schedules!J50 -> 11552 | K16: =Schedules!K50 -> 11827 | L16: =Schedules!L50 -> 12107 | N16: PP&E, net: Linked from Schedules PP&E schedule. Driven by CapEx at 2.2% of revenue and D&A at 4.5% of average gross PP&E. See Schedules sheet for detailed rollforward.
A17: Intangible assets, net | B17: 1978 | C17: 1824 | D17: 1656 | E17: 1520 | F17: 1375 | G17: =F17+G66 -> 1225 | H17: =G17+H66 -> 1075 | I17: =H17+I66 -> 925 | J17: =I17+J66 -> 775 | K17: =J17+K66 -> 625 | L17: =K17+L66 -> 475 | N17: Intangible assets, net: Annual amortization of -$150M (held flat). Historical annual decline ranged -$136M to -$168M. Reflects steady amortization of acquired intangibles from CSRA acquisition with no significant new acquisitions assumed.
A18: Goodwill | B18: 20098 | C18: 20334 | D18: 20586 | E18: 20556 | F18: 21009 | G18: 21009 | H18: 21009 | I18: 21009 | J18: 21009 | K18: 21009 | L18: 21009 | N18: Goodwill: Held flat at $21,009M (2025 level). No impairments or acquisitions assumed. Goodwill primarily from 2018 CSRA acquisition ($9.7B) and historical deals. Would only change with M&A activity.
A19: Other assets | B19: 2593 | C19: 2464 | D19: 2755 | E19: 2951 | F19: 3092 | G19: ='Income statement'!G9*'Balance sheet'!G68 -> 3462.4584 | H19: ='Income statement'!H9*'Balance sheet'!H68 -> 3618.5621 | I19: ='Income statement'!I9*'Balance sheet'!I68 -> 3790.4522 | J19: ='Income statement'!J9*'Balance sheet'!J68 -> 3974.9483 | K19: ='Income statement'!K9*'Balance sheet'!K68 -> 4171 | L19: ='Income statement'!L9*'Balance sheet'!L68 -> 4379.5286 | N19: Other noncurrent assets: Held flat at $3,092M (2025 level). Includes operating lease ROU assets, deferred tax assets, and other long-term items. Stable historical trajectory with no specific growth driver identified.
A20: Total noncurrent assets | B20: =SUM(B16:B19) -> 30086 | C20: =SUM(C16:C19) -> 30522 | D20: =SUM(D16:D19) -> 31195 | E20: =SUM(E16:E19) -> 31494 | F20: =SUM(F16:F19) -> 33001 | G20: =SUM(G16:G19) -> 34576.458 | H20: =SUM(H16:H19) -> 35767.562 | I20: =SUM(I16:I19) -> 36684.452 | ... L20: =SUM(L16:L19) -> 37970.529
A22: Total assets | B22: =B13+B20 -> 50073 | C22: =C13+C20 -> 51585 | D22: =D13+D20 -> 54810 | E22: =E13+E20 -> 55880 | F22: =F13+F20 -> 57249 | G22: =G13+G20 -> 60498.918 | H22: =H13+H20 -> 63487.763 | I22: =I13+I20 -> 66509.531 | ... L22: =L13+L20 -> 75681.983
A24: LIABILITIES AND SHAREHOLDERS' EQUITY
A25: Current liabilities:
A26: Short-term debt and current portion of long-term debt | B26: 1005 | C26: 1253 | D26: 507 | E26: 1502 | F26: 1006 | G26: =Schedules!G88 -> 1257 | H26: =Schedules!H88 -> 1007 | I26: =Schedules!I88 -> 7 | J26: =Schedules!J88 -> 1007 | K26: =Schedules!K88 -> 500 | L26: =Schedules!L88 -> 0 | N26: Short-term debt: Current portion of LTD from debt maturity schedule. Equals notes maturing within 12 months per 2025 10-K Note K debt maturity detail. Linked from Schedules debt schedule.
A27: Accounts payable | B27: 3167 | C27: 3398 | D27: 3095 | E27: 3344 | F27: 2678 | G27: =Schedules!G118 -> 2804.3728 | H27: =Schedules!H118 -> 2930.7698 | I27: =Schedules!I118 -> 3069.9411 | J27: =Schedules!J118 -> 3219.3178 | K27: =Schedules!K118 -> 3378.0529 | L27: =Schedules!L118 -> 3546.8929 | N27: Accounts payable: Projected using DPO of 22 days (held flat). Historical DPO ranged 22–38 days; 22 days matches 2025 actual. Reflects GD’s disciplined payables management and shorter payment cycles typical of defense primes.
A28: Customer advances and deposits | B28: 6266 | C28: 7436 | D28: 9564 | E28: 9491 | F28: 9824 | G28: =G77*'Income statement'!G9 -> 10566.257 | H28: =H77*'Income statement'!H9 -> 11042.633 | I28: =I77*'Income statement'!I9 -> 11567.183 | J28: =J77*'Income statement'!J9 -> 12130.203 | K28: =K77*'Income statement'!K9 -> 12728.487 | L28: =L77*'Income statement'!L9 -> 13364.846 | N28: Customer advances & deposits: Projected at ~19.3% of revenue (5-yr historical average). Historical range: 16.3–22.6%. Reflects advance payments received on large defense contracts, particularly submarines and combat vehicles. Averaged to smooth volatility.
A29: Other current liabilities | B29: 3540 | C29: 3254 | D29: 3266 | E29: 3487 | F29: 3288 | G29: =G78*'Income statement'!G9 -> 3289.337 | H29: =H78*'Income statement'!H9 -> 3437.6356 | I29: =I78*'Income statement'!I9 -> 3600.9312 | J29: =J78*'Income statement'!J9 -> 3776.2025 | K29: =K78*'Income statement'!K9 -> 3962.4518 | L29: =L78*'Income statement'!L9 -> 4160.554 | N29: Other current liabilities: Projected at 6.0% of revenue (held flat). Historical range: 6.3–9.2%; 6.0% is slightly below historical average reflecting normalization of accrued compensation and other current obligations.
A30: Total current liabilities | B30: =SUM(B26:B29) -> 13978 | C30: =SUM(C26:C29) -> 15341 | D30: =SUM(D26:D29) -> 16432 | E30: =SUM(E26:E29) -> 17824 | F30: =SUM(F26:F29) -> 16796 | G30: =SUM(G26:G29) -> 17916.967 | H30: =SUM(H26:H29) -> 18418.038 | I30: =SUM(I26:I29) -> 18245.056 | ... L30: =SUM(L26:L29) -> 21072.293
A32: Noncurrent liabilities:
A33: Long-term debt | B33: 10490 | C33: 9243 | D33: 8754 | E33: 7260 | F33: 7007 | G33: =Schedules!G89 -> 7231 | H33: =Schedules!H89 -> 7930 | I33: =Schedules!I89 -> 9354 | J33: =Schedules!J89 -> 8753 | K33: =Schedules!K89 -> 9659 | L33: =Schedules!L89 -> 10515 | N33: Long-term debt: Linked from Schedules debt schedule. Reflects total debt book value less current portion. New issuances of $1,650M/yr in 2026–28E and $1,000–1,600M/yr thereafter to maintain target D/V ratio of ~24%.
A34: Other liabilities | B34: 7964 | C34: 8433 | D34: 8325 | E34: 8733 | F34: 7824 | G34: ='Income statement'!G9*'Balance sheet'!G83 -> 8223.3424 | H34: ='Income statement'!H9*'Balance sheet'!H83 -> 8594.0889 | I34: ='Income statement'!I9*'Balance sheet'!I83 -> 9002.3279 | J34: ='Income statement'!J9*'Balance sheet'!J83 -> 9440.5063 | K34: ='Income statement'!K9*'Balance sheet'!K83 -> 9906.1294 | L34: ='Income statement'!L9*'Balance sheet'!L83 -> 10401.385 | N34: Other noncurrent liabilities: Held flat at $7,824M (2025 level). Includes pension obligations, deferred revenue (noncurrent), and other long-term liabilities. Pension obligations expected to remain stable given GD’s funded status.
A35: Total noncurrent liabilities | B35: =SUM(B33:B34) -> 18454 | C35: =SUM(C33:C34) -> 17676 | D35: =SUM(D33:D34) -> 17079 | E35: =SUM(E33:E34) -> 15993 | F35: =SUM(F33:F34) -> 14831 | G35: =SUM(G33:G34) -> 15454.342 | H35: =SUM(H33:H34) -> 16524.089 | I35: =SUM(I33:I34) -> 18356.328 | ... L35: =SUM(L33:L34) -> 20916.385
A37: Total liabilities | B37: =B30+B35 -> 32432 | C37: =C30+C35 -> 33017 | D37: =D30+D35 -> 33511 | E37: =E30+E35 -> 33817 | F37: =F30+F35 -> 31627 | G37: =G30+G35 -> 33371.309 | H37: =H30+H35 -> 34942.127 | I37: =I30+I35 -> 36601.384 | ... L37: =L30+L35 -> 41988.678
A39: Shareholders' equity:
A40: Common stock | B40: 482 | C40: 482 | D40: 482 | E40: 482 | F40: 482 | G40: =Equity!G45 -> 482 | H40: =Equity!H45 -> 482 | I40: =Equity!I45 -> 482 | J40: =Equity!J45 -> 482 | K40: =Equity!K45 -> 482 | L40: =Equity!L45 -> 482 | N40: Common stock: Held flat at $482M. Par value of common shares; does not change with repurchases.
A41: Surplus | B41: 3278 | C41: 3556 | D41: 3760 | E41: 4062 | F41: 4403 | G41: =Equity!G32 -> 4743 | H41: =Equity!H32 -> 5083 | I41: =Equity!I32 -> 5423 | J41: =Equity!J32 -> 5763 | K41: =Equity!K32 -> 6103 | L41: =Equity!L32 -> 6443 | N41: Surplus (APIC): Grows by $340M/yr reflecting annual stock-based compensation expense. Historical SBC ranged $204–$341M; $340M is consistent with recent trend and reflects ongoing equity compensation programs.
A42: Retained earnings | B42: 35420 | C42: 37403 | D42: 39270 | E42: 41487 | F42: 44080 | G42: =Equity!G13 -> 46745.609 | H42: =Equity!H13 -> 49523.636 | I42: =Equity!I13 -> 52446.147 | J42: =Equity!J13 -> 55501.428 | K42: =Equity!K13 -> 58723.296 | L42: =Equity!L13 -> 62111.305 | N42: Retained earnings: Beginning balance + net earnings – dividends. Dividends grow 5% annually from 2025 base ($1,617M), reflecting GD’s consistent dividend growth track record (increased for 27+ consecutive years).
A43: Treasury stock | B43: -19619 | C43: -20721 | D43: -21054 | E43: -22450 | F43: -22860 | G43: =Equity!G22 -> -24360 | H43: =Equity!H22 -> -26060 | I43: =Equity!I22 -> -27960 | J43: =Equity!J22 -> -30060 | K43: =Equity!K22 -> -32360 | L43: =Equity!L22 -> -34860 | N43: Treasury stock: $1,500M annual share repurchases assumed. Historical buybacks volatile ($333M–$1,856M); $1,500M reflects management’s stated commitment to returning capital via repurchases. Share count declines ~1.7% annually at projected prices.
A44: Accumulated other comprehensive loss | B44: -1920 | C44: -2152 | D44: -1159 | E44: -1518 | F44: -483 | G44: =Equity!G41 -> -483 | H44: =Equity!H41 -> -483 | I44: =Equity!I41 -> -483 | J44: =Equity!J41 -> -483 | K44: =Equity!K41 -> -483 | L44: =Equity!L41 -> -483 | N44: AOCI: Gradual recovery toward zero. +$100M/yr in 2026–28E, then +$50M/yr. Reflects expected improvement in pension-related AOCI as interest rates normalize and pension funded status improves. Historical swings large ($+1,035M to -$359M).
A45: Total shareholders' equity | B45: =SUM(B40:B44) -> 17641 | C45: =SUM(C40:C44) -> 18568 | D45: =SUM(D40:D44) -> 21299 | E45: =SUM(E40:E44) -> 22063 | F45: =SUM(F40:F44) -> 25622 | G45: =SUM(G40:G44) -> 27127.609 | H45: =SUM(H40:H44) -> 28545.636 | I45: =SUM(I40:I44) -> 29908.147 | ... L45: =SUM(L40:L44) -> 33693.305
A47: Total liabilities and shareholders' equity | B47: =B37+B45 -> 50073 | C47: =C37+C45 -> 51585 | D47: =D37+D45 -> 54810 | E47: =E37+E45 -> 55880 | F47: =F37+F45 -> 57249 | G47: =G37+G45 -> 60498.918 | H47: =H37+H45 -> 63487.763 | I47: =I37+I45 -> 66509.531 | ... L47: =L37+L45 -> 75681.983
A49: Balance Check (Assets - L&E) | B49: =B22-B47 -> 0 | C49: =C22-C47 -> 0 | D49: =D22-D47 -> 0 | E49: =E22-E47 -> 0 | F49: =F22-F47 -> 0 | G49: =G22-G47 -> 0 | H49: =H22-H47 -> 0 | I49: =I22-I47 -> 0 | ... L49: =L22-L47 -> 0
A54: 46387 | B54: 2021 | C54: 2022 | D54: 2023 | E54: 2024 | F54: 2025 | G54: 2026 | H54: 2027 | I54: 2028 | J54: 2029 | K54: 2030 | L54: 2031
A55: ASSETS
A56: Current assets:
A57: Cash and equivalents
A58: Accounts receivable — DSO (days) | B58: =B9/'Income statement'!B9*365 -> 28.853492 | C58: =C9/'Income statement'!C9*365 -> 27.86104 | D58: =D9/'Income statement'!D9*365 -> 25.93821 | E58: =E9/'Income statement'!E9*365 -> 22.772341 | F58: =F9/'Income statement'!F9*365 -> 16.711513 | G58: =Schedules!G110 -> 17 | H58: =Schedules!H110 -> 17 | I58: =Schedules!I110 -> 17 | J58: =Schedules!J110 -> 17 | K58: =Schedules!K110 -> 17 | L58: =Schedules!L110 -> 17
A59: Unbilled receivables | B59: =B10/'Income statement'!B9 -> 0.22090514 | C59: =C10/'Income statement'!C9 -> 0.2231837 | D59: =D10/'Income statement'!D9 -> 0.1891796 | E59: =E10/'Income statement'!E9 -> 0.17285607 | F59: =F10/'Income statement'!F9 -> 0.15946717 | G59: 0.16 | H59: =G59 -> 0.16 | I59: =H59 -> 0.16 | J59: =I59 -> 0.16 | K59: =J59 -> 0.16 | L59: =K59 -> 0.16
A60: Inventories — DSI (days) | B60: =B11/(ABS('Income statement'!B12)+ABS('Income statement'!B13))*365 -> 60.793487 | C60: =C11/(ABS('Income statement'!C12)+ABS('Income statement'!C13))*365 -> 70.383712 | D60: =D11/(ABS('Income statement'!D12)+ABS('Income statement'!D13))*365 -> 87.948596 | E60: =E11/(ABS('Income statement'!E12)+ABS('Income statement'!E13))*365 -> 87.957474 | F60: =F11/(ABS('Income statement'!F12)+ABS('Income statement'!F13))*365 -> 75.555057 | G60: =Schedules!G111 -> 75 | H60: =Schedules!H111 -> 75 | I60: =Schedules!I111 -> 75 | J60: =Schedules!J111 -> 75 | K60: =Schedules!K111 -> 75 | L60: =Schedules!L111 -> 75
A61: Other current assets | B61: =B12/'Income statement'!B9 -> 0.03912241 | C61: =C12/'Income statement'!C9 -> 0.043038039 | D61: =D12/'Income statement'!D9 -> 0.050222369 | E61: =E12/'Income statement'!E9 -> 0.036465756 | F61: =F12/'Income statement'!F9 -> 0.036098953 | G61: 0.04 | H61: 0.04 | I61: 0.04 | J61: 0.04 | K61: 0.04 | L61: 0.04
A62: Total current assets
A64: Noncurrent assets:
A65: Property, plant and equipment, net
A66: Intangible assets, net | C66: =C17-B17 -> -154 | D66: =D17-C17 -> -168 | E66: =E17-D17 -> -136 | F66: =F17-E17 -> -145 | G66: -150 | H66: -150 | I66: -150 | J66: -150 | K66: -150 | L66: -150
A67: Goodwill
A68: Other assets | B68: =B19/'Income statement'!B9 -> 0.067404923 | C68: =C19/'Income statement'!C9 -> 0.062526962 | D68: =D19/'Income statement'!D9 -> 0.065173164 | E68: =E19/'Income statement'!E9 -> 0.061845083 | F68: =F19/'Income statement'!F9 -> 0.058839201 | G68: =AVERAGE(B68:F68) -> 0.063157867 | H68: =G68 -> 0.063157867 | I68: =H68 -> 0.063157867 | J68: =I68 -> 0.063157867 | K68: =J68 -> 0.063157867 | L68: =K68 -> 0.063157867
A69: Total noncurrent assets
A71: Total assets
A73: LIABILITIES AND SHAREHOLDERS' EQUITY
A74: Current liabilities:
A75: Short-term debt and current portion of long-term debt | G75: =Schedules!G88 -> 1257 | H75: =Schedules!H88 -> 1007 | I75: =Schedules!I88 -> 7 | J75: =Schedules!J88 -> 1007 | K75: =Schedules!K88 -> 500 | L75: =Schedules!L88 -> 0
A76: Accounts payable — DPO (days) | B76: =B27/(ABS('Income statement'!B12)+ABS('Income statement'!B13))*365 -> 36.054864 | C76: =C27/(ABS('Income statement'!C12)+ABS('Income statement'!C13))*365 -> 37.83041 | D76: =D27/(ABS('Income statement'!D12)+ABS('Income statement'!D13))*365 -> 31.732444 | E76: =E27/(ABS('Income statement'!E12)+ABS('Income statement'!E13))*365 -> 30.247819 | F76: =F27/(ABS('Income statement'!F12)+ABS('Income statement'!F13))*365 -> 21.916859 | G76: =Schedules!G112 -> 22 | H76: =Schedules!H112 -> 22 | I76: =Schedules!I112 -> 22 | J76: =Schedules!J112 -> 22 | K76: =Schedules!K112 -> 22 | L76: =Schedules!L112 -> 22
A77: Customer advances and deposits | B77: =B28/'Income statement'!B9 -> 0.1628844 | C77: =C28/'Income statement'!C9 -> 0.18869744 | D77: =D28/'Income statement'!D9 -> 0.22624905 | E77: =E28/'Income statement'!E9 -> 0.19890603 | F77: =F28/'Income statement'!F9 -> 0.18694577 | G77: =AVERAGE(B77:F77) -> 0.19273654 | H77: =G77 -> 0.19273654 | I77: =H77 -> 0.19273654 | J77: =I77 -> 0.19273654 | K77: =J77 -> 0.19273654 | L77: =K77 -> 0.19273654
A78: Other current liabilities | B78: =B29/'Income statement'!B9 -> 0.092022148 | C78: =C29/'Income statement'!C9 -> 0.082574162 | D78: =D29/'Income statement'!D9 -> 0.077261544 | E78: =E29/'Income statement'!E9 -> 0.073078213 | F78: =F29/'Income statement'!F9 -> 0.062568982 | G78: 0.06 | H78: 0.06 | I78: 0.06 | J78: 0.06 | K78: 0.06 | L78: 0.06
A79: Total current liabilities
A81: Noncurrent liabilities:
A82: Long-term debt
A83: Other liabilities | B83: =B34/'Income statement'!B9 -> 0.20702384 | C83: =C34/'Income statement'!C9 -> 0.21399751 | D83: =D34/'Income statement'!D9 -> 0.19693887 | E83: =E34/'Income statement'!E9 -> 0.18302037 | F83: =F34/'Income statement'!F9 -> 0.14888677 | G83: 0.15 | H83: =G83 -> 0.15 | I83: =H83 -> 0.15 | J83: =I83 -> 0.15 | K83: =J83 -> 0.15 | L83: =K83 -> 0.15
A84: Total noncurrent liabilities
A86: Total liabilities
A88: Shareholders' equity:
A89: Common stock
A90: Surplus
A91: Retained earnings
A92: Treasury stock
A93: Accumulated other comprehensive loss
A94: Total shareholders' equity
A96: Total liabilities and shareholders' equity

Sheet Cash flow
A3: NET INCOME | G3: ='Income statement'!G26 -> 4442.681 | H3: ='Income statement'!H26 -> 4630.0453 | I3: ='Income statement'!I26 -> 4870.8523 | J3: ='Income statement'!J26 -> 5092.135 | K3: ='Income statement'!K26 -> 5369.7801 | L3: ='Income statement'!L26 -> 5646.6811
A4: 46387 | G4: 2026 | H4: 2027 | I4: 2028 | J4: 2029 | K4: 2030 | L4: 2031
A5: ASSETS
A6: Current assets:
A7: Cash and equivalents
A8: Accounts receivable | G8: ='Balance sheet'!F9-'Balance sheet'!G9 -> -147.3666 | H8: ='Balance sheet'!G9-'Balance sheet'!H9 -> -115.11762 | I8: ='Balance sheet'!H9-'Balance sheet'!I9 -> -126.75916 | J8: ='Balance sheet'!I9-'Balance sheet'!J9 -> -136.05538 | K8: ='Balance sheet'!J9-'Balance sheet'!K9 -> -144.57705 | L8: ='Balance sheet'!K9-'Balance sheet'!L9 -> -153.77798
A9: Unbilled receivables | G9: ='Balance sheet'!F10-'Balance sheet'!G10 -> -391.56527 | H9: ='Balance sheet'!G10-'Balance sheet'!H10 -> -395.46287 | I9: ='Balance sheet'!H10-'Balance sheet'!I10 -> -435.455 | J9: ='Balance sheet'!I10-'Balance sheet'!J10 -> -467.39025 | K9: ='Balance sheet'!J10-'Balance sheet'!K10 -> -496.66468 | L9: ='Balance sheet'!K10-'Balance sheet'!L10 -> -528.27258
A10: Inventories | G10: ='Balance sheet'!F11-'Balance sheet'!G11 -> -328.36179 | H10: ='Balance sheet'!G11-'Balance sheet'!H11 -> -430.89898 | I10: ='Balance sheet'!H11-'Balance sheet'!I11 -> -474.44746 | J10: ='Balance sheet'!I11-'Balance sheet'!J11 -> -509.23874 | K10: ='Balance sheet'!J11-'Balance sheet'!K11 -> -541.14236 | L10: ='Balance sheet'!K11-'Balance sheet'!L11 -> -575.59101
A11: Other current assets | G11: ='Balance sheet'!F12-'Balance sheet'!G12 -> -295.89132 | H11: ='Balance sheet'!G12-'Balance sheet'!H12 -> -98.865717 | I11: ='Balance sheet'!H12-'Balance sheet'!I12 -> -108.86375 | J11: ='Balance sheet'!I12-'Balance sheet'!J12 -> -116.84756 | K11: ='Balance sheet'!J12-'Balance sheet'!K12 -> -124.16617 | L11: ='Balance sheet'!K12-'Balance sheet'!L12 -> -132.06814
A12: Total current assets
G13: ='Balance sheet'!F14-'Balance sheet'!G14 -> 0 | H13: ='Balance sheet'!G14-'Balance sheet'!H14 -> 0 | I13: ='Balance sheet'!H14-'Balance sheet'!I14 -> 0 | J13: ='Balance sheet'!I14-'Balance sheet'!J14 -> 0 | K13: ='Balance sheet'!J14-'Balance sheet'!K14 -> 0 | L13: ='Balance sheet'!K14-'Balance sheet'!L14 -> 0
A14: Noncurrent assets: | G14: ='Balance sheet'!F15-'Balance sheet'!G15 -> 0 | H14: ='Balance sheet'!G15-'Balance sheet'!H15 -> 0 | I14: ='Balance sheet'!H15-'Balance sheet'!I15 -> 0 | J14: ='Balance sheet'!I15-'Balance sheet'!J15 -> 0 | K14: ='Balance sheet'!J15-'Balance sheet'!K15 -> 0 | L14: ='Balance sheet'!K15-'Balance sheet'!L15 -> 0
A15: Property, plant and equipment, net | G15: ='Balance sheet'!F16-'Balance sheet'!G16 -> -1355 | H15: ='Balance sheet'!G16-'Balance sheet'!H16 -> -1185 | I15: ='Balance sheet'!H16-'Balance sheet'!I16 -> -895 | J15: ='Balance sheet'!I16-'Balance sheet'!J16 -> -592 | K15: ='Balance sheet'!J16-'Balance sheet'!K16 -> -275 | L15: ='Balance sheet'!K16-'Balance sheet'!L16 -> -280
A16: Intangible assets, net | G16: ='Balance sheet'!F17-'Balance sheet'!G17 -> 150 | H16: ='Balance sheet'!G17-'Balance sheet'!H17 -> 150 | I16: ='Balance sheet'!H17-'Balance sheet'!I17 -> 150 | J16: ='Balance sheet'!I17-'Balance sheet'!J17 -> 150 | K16: ='Balance sheet'!J17-'Balance sheet'!K17 -> 150 | L16: ='Balance sheet'!K17-'Balance sheet'!L17 -> 150
A17: Goodwill | G17: ='Balance sheet'!F18-'Balance sheet'!G18 -> 0 | H17: ='Balance sheet'!G18-'Balance sheet'!H18 -> 0 | I17: ='Balance sheet'!H18-'Balance sheet'!I18 -> 0 | J17: ='Balance sheet'!I18-'Balance sheet'!J18 -> 0 | K17: ='Balance sheet'!J18-'Balance sheet'!K18 -> 0 | L17: ='Balance sheet'!K18-'Balance sheet'!L18 -> 0
A18: Other assets | G18: ='Balance sheet'!F19-'Balance sheet'!G19 -> -370.45844 | H18: ='Balance sheet'!G19-'Balance sheet'!H19 -> -156.10369 | I18: ='Balance sheet'!H19-'Balance sheet'!I19 -> -171.89006 | J18: ='Balance sheet'!I19-'Balance sheet'!J19 -> -184.49607 | K18: ='Balance sheet'!J19-'Balance sheet'!K19 -> -196.05176 | L18: ='Balance sheet'!K19-'Balance sheet'!L19 -> -208.52856
A19: Total noncurrent assets
A21: Total assets
A23: LIABILITIES AND SHAREHOLDERS' EQUITY
A24: Current liabilities:
A25: Short-term debt and current portion of long-term debt | G25: ='Balance sheet'!G26-'Balance sheet'!F26 -> 251 | H25: ='Balance sheet'!H26-'Balance sheet'!G26 -> -250 | I25: ='Balance sheet'!I26-'Balance sheet'!H26 -> -1000 | J25: ='Balance sheet'!J26-'Balance sheet'!I26 -> 1000 | K25: ='Balance sheet'!K26-'Balance sheet'!J26 -> -507 | L25: ='Balance sheet'!L26-'Balance sheet'!K26 -> -500
A26: Accounts payable | G26: ='Balance sheet'!G27-'Balance sheet'!F27 -> 126.37279 | H26: ='Balance sheet'!H27-'Balance sheet'!G27 -> 126.39703 | I26: ='Balance sheet'!I27-'Balance sheet'!H27 -> 139.17126 | J26: ='Balance sheet'!J27-'Balance sheet'!I27 -> 149.3767 | K26: ='Balance sheet'!K27-'Balance sheet'!J27 -> 158.73509 | L26: ='Balance sheet'!L27-'Balance sheet'!K27 -> 168.84003
A27: Customer advances and deposits | G27: ='Balance sheet'!G28-'Balance sheet'!F28 -> 742.25699 | H27: ='Balance sheet'!H28-'Balance sheet'!G28 -> 476.3759 | I27: ='Balance sheet'!I28-'Balance sheet'!H28 -> 524.55056 | J27: ='Balance sheet'!J28-'Balance sheet'!I28 -> 563.01987 | K27: ='Balance sheet'!K28-'Balance sheet'!J28 -> 598.28394 | L27: ='Balance sheet'!L28-'Balance sheet'!K28 -> 636.35892
A28: Other current liabilities | G28: ='Balance sheet'!G29-'Balance sheet'!F29 -> 1.3369762 | H28: ='Balance sheet'!H29-'Balance sheet'!G29 -> 148.29858 | I28: ='Balance sheet'!I29-'Balance sheet'!H29 -> 163.29563 | J28: ='Balance sheet'!J29-'Balance sheet'!I29 -> 175.27135 | K28: ='Balance sheet'!K29-'Balance sheet'!J29 -> 186.24925 | L28: ='Balance sheet'!L29-'Balance sheet'!K29 -> 198.10222
A29: Total current liabilities
G30: ='Balance sheet'!G31-'Balance sheet'!F31 -> 0 | H30: ='Balance sheet'!H31-'Balance sheet'!G31 -> 0 | I30: ='Balance sheet'!I31-'Balance sheet'!H31 -> 0 | J30: ='Balance sheet'!J31-'Balance sheet'!I31 -> 0 | K30: ='Balance sheet'!K31-'Balance sheet'!J31 -> 0 | L30: ='Balance sheet'!L31-'Balance sheet'!K31 -> 0
A31: Noncurrent liabilities: | G31: ='Balance sheet'!G32-'Balance sheet'!F32 -> 0 | H31: ='Balance sheet'!H32-'Balance sheet'!G32 -> 0 | I31: ='Balance sheet'!I32-'Balance sheet'!H32 -> 0 | J31: ='Balance sheet'!J32-'Balance sheet'!I32 -> 0 | K31: ='Balance sheet'!K32-'Balance sheet'!J32 -> 0 | L31: ='Balance sheet'!L32-'Balance sheet'!K32 -> 0
A32: Long-term debt | G32: ='Balance sheet'!G33-'Balance sheet'!F33 -> 224 | H32: ='Balance sheet'!H33-'Balance sheet'!G33 -> 699 | I32: ='Balance sheet'!I33-'Balance sheet'!H33 -> 1424 | J32: ='Balance sheet'!J33-'Balance sheet'!I33 -> -601 | K32: ='Balance sheet'!K33-'Balance sheet'!J33 -> 906 | L32: ='Balance sheet'!L33-'Balance sheet'!K33 -> 856
A33: Other liabilities | G33: ='Balance sheet'!G34-'Balance sheet'!F34 -> 399.34244 | H33: ='Balance sheet'!H34-'Balance sheet'!G34 -> 370.74644 | I33: ='Balance sheet'!I34-'Balance sheet'!H34 -> 408.23907 | J33: ='Balance sheet'!J34-'Balance sheet'!I34 -> 438.17836 | K33: ='Balance sheet'!K34-'Balance sheet'!J34 -> 465.62314 | L33: ='Balance sheet'!L34-'Balance sheet'!K34 -> 495.25554
A34: Total noncurrent liabilities
G35: ='Balance sheet'!G36-'Balance sheet'!F36 -> 0 | H35: ='Balance sheet'!H36-'Balance sheet'!G36 -> 0 | I35: ='Balance sheet'!I36-'Balance sheet'!H36 -> 0 | J35: ='Balance sheet'!J36-'Balance sheet'!I36 -> 0 | K35: ='Balance sheet'!K36-'Balance sheet'!J36 -> 0 | L35: ='Balance sheet'!L36-'Balance sheet'!K36 -> 0
A36: Total liabilities
G37: ='Balance sheet'!G38-'Balance sheet'!F38 -> 0 | H37: ='Balance sheet'!H38-'Balance sheet'!G38 -> 0 | I37: ='Balance sheet'!I38-'Balance sheet'!H38 -> 0 | J37: ='Balance sheet'!J38-'Balance sheet'!I38 -> 0 | K37: ='Balance sheet'!K38-'Balance sheet'!J38 -> 0 | L37: ='Balance sheet'!L38-'Balance sheet'!K38 -> 0
A38: Shareholders' equity: | G38: ='Balance sheet'!G39-'Balance sheet'!F39 -> 0 | H38: ='Balance sheet'!H39-'Balance sheet'!G39 -> 0 | I38: ='Balance sheet'!I39-'Balance sheet'!H39 -> 0 | J38: ='Balance sheet'!J39-'Balance sheet'!I39 -> 0 | K38: ='Balance sheet'!K39-'Balance sheet'!J39 -> 0 | L38: ='Balance sheet'!L39-'Balance sheet'!K39 -> 0
A39: Common stock | G39: ='Balance sheet'!G40-'Balance sheet'!F40 -> 0 | H39: ='Balance sheet'!H40-'Balance sheet'!G40 -> 0 | I39: ='Balance sheet'!I40-'Balance sheet'!H40 -> 0 | J39: ='Balance sheet'!J40-'Balance sheet'!I40 -> 0 | K39: ='Balance sheet'!K40-'Balance sheet'!J40 -> 0 | L39: ='Balance sheet'!L40-'Balance sheet'!K40 -> 0
A40: Surplus | G40: ='Balance sheet'!G41-'Balance sheet'!F41 -> 340 | H40: ='Balance sheet'!H41-'Balance sheet'!G41 -> 340 | I40: ='Balance sheet'!I41-'Balance sheet'!H41 -> 340 | J40: ='Balance sheet'!J41-'Balance sheet'!I41 -> 340 | K40: ='Balance sheet'!K41-'Balance sheet'!J41 -> 340 | L40: ='Balance sheet'!L41-'Balance sheet'!K41 -> 340
A43: Accumulated other comprehensive loss | G43: ='Balance sheet'!G44-'Balance sheet'!F44 -> 0 | H43: ='Balance sheet'!H44-'Balance sheet'!G44 -> 0 | I43: ='Balance sheet'!I44-'Balance sheet'!H44 -> 0 | J43: ='Balance sheet'!J44-'Balance sheet'!I44 -> 0 | K43: ='Balance sheet'!K44-'Balance sheet'!J44 -> 0 | L43: ='Balance sheet'!L44-'Balance sheet'!K44 -> 0
A44: Total shareholders' equity
A46: Total liabilities and shareholders' equity
A48: FCFE | G48: =SUM(G8:G43)+G3 -> 3788.3468 | H48: =SUM(H8:H43)+H3 -> 4309.4143 | I48: =SUM(I8:I43)+I3 -> 4807.6934 | J48: =SUM(J8:J43)+J3 -> 5300.9532 | K48: =SUM(K8:K43)+K3 -> 5890.0695 | L48: =SUM(L8:L43)+L3 -> 6112.9996
A50: Dividends | G50: =Equity!G10 -> -1777.0724 | H50: =Equity!H10 -> -1852.0181 | I50: =Equity!I10 -> -1948.3409 | J50: =Equity!J10 -> -2036.854 | K50: =Equity!K10 -> -2147.912 | L50: =Equity!L10 -> -2258.6724
A51: Repurchases | G51: =Equity!G18 -> -1500 | H51: =Equity!H18 -> -1700 | I51: =Equity!I18 -> -1900 | J51: =Equity!J18 -> -2100 | K51: =Equity!K18 -> -2300 | L51: =Equity!L18 -> -2500
A53: Cash Generated | G53: =G48+G50+G51 -> 511.2744 | H53: =H48+H50+H51 -> 757.39623 | I53: =I48+I50+I51 -> 959.35245 | J53: =J48+J50+J51 -> 1164.0992 | K53: =K48+K50+K51 -> 1442.1575 | L53: =L48+L50+L51 -> 1354.3271
A55: Opening Cash | G55: ='Balance sheet'!F8 -> 2333 | H55: =G56 -> 2844.2744 | I55: =H56 -> 3601.6706 | J55: =I56 -> 4561.0231 | K55: =J56 -> 5725.1223 | L55: =K56 -> 7167.2798
A56: Closing Cash | G56: =G55+G53 -> 2844.2744 | H56: =H55+H53 -> 3601.6706 | I56: =I55+I53 -> 4561.0231 | J56: =J55+J53 -> 5725.1223 | K56: =K55+K53 -> 7167.2798 | L56: =L55+L53 -> 8521.6069

Sheet Equity
A1: General Dynamics Corporation
A2: Shareholders' Equity Schedule
A3: (Dollars in millions)
B5: 2021 | C5: 2022 | D5: 2023 | E5: 2024 | F5: 2025 | G5: 2026 | H5: 2027 | I5: 2028 | J5: 2029 | K5: 2030 | L5: 2031 | N5: Projection Assumptions
N6: SHAREHOLDERS' EQUITY SCHEDULE
A7: RETAINED EARNINGS ROLLFORWARD
A8: Beginning Balance | B8: 33512 | C8: =B13 -> 35420 | D8: =C13 -> 37403 | E8: =D13 -> 39270 | F8: =E13 -> 41487 | G8: =F13 -> 44080 | H8: =G13 -> 46745.609 | I8: =H13 -> 49523.636 | J8: =I13 -> 52446.147 | ... L8: =K13 -> 58723.296
A9: Net Earnings | B9: ='Income statement'!B26 -> 3257 | C9: ='Income statement'!C26 -> 3390 | D9: ='Income statement'!D26 -> 3315 | E9: ='Income statement'!E26 -> 3782 | F9: ='Income statement'!F26 -> 4210 | G9: ='Income statement'!G26 -> 4442.681 | H9: ='Income statement'!H26 -> 4630.0453 | I9: ='Income statement'!I26 -> 4870.8523 | ... L9: ='Income statement'!L26 -> 5646.6811
A10: Dividends Declared | B10: =-(B8+B9-B13) -> -1349 | C10: =-(C8+C9-C13) -> -1407 | D10: =-(D8+D9-D13) -> -1448 | E10: =-(E8+E9-E13) -> -1565 | F10: =-(F8+F9-F13) -> -1617 | G10: =-G9*0.4 -> -1777.0724 | H10: =-H9*0.4 -> -1852.0181 | I10: =-I9*0.4 -> -1948.3409 | J10: =-J9*0.4 -> -2036.854 | K10: =-K9*0.4 -> -2147.912 | L10: =-L9*0.4 -> -2258.6724 | N10: Dividends: 40% payout ratio of net income. Historical payout ratio ranged 38–44% (5-yr avg ~41%). Per professor feedback, payout ratio is a better assumption than fixed YoY growth since it ties dividends to earnings capacity rather than an arbitrary growth rate. GD has increased dividends for 27+ consecutive years.
A11: Other | B11: 0 | C11: 0 | D11: 0 | E11: 0 | F11: 0 | G11: 0 | H11: 0 | I11: 0 | J11: 0 | K11: 0 | L11: 0
A13: Ending Balance | B13: ='Balance sheet'!B42 -> 35420 | C13: ='Balance sheet'!C42 -> 37403 | D13: ='Balance sheet'!D42 -> 39270 | E13: ='Balance sheet'!E42 -> 41487 | F13: ='Balance sheet'!F42 -> 44080 | G13: =G8+G9+G10+G11 -> 46745.609 | H13: =H8+H9+H10+H11 -> 49523.636 | I13: =I8+I9+I10+I11 -> 52446.147 | J13: =J8+J9+J10+J11 -> 55501.428 | K13: =K8+K9+K10+K11 -> 58723.296 | L13: =L8+L9+L10+L11 -> 62111.305
A16: TREASURY STOCK / SHARE REPURCHASES
A17: Beginning Balance | B17: -17763 | C17: =B22 -> -19619 | D17: =C22 -> -20721 | E17: =D22 -> -21054 | F17: =E22 -> -22450 | G17: =F22 -> -22860 | H17: =G22 -> -24360 | I17: =H22 -> -26060 | J17: =I22 -> -27960 | ... L17: =K22 -> -32360
A18: Share Repurchases | B18: =B22-B17-B19 -> -1856 | C18: =C22-C17-C19 -> -1102 | D18: =D22-D17-D19 -> -333 | E18: =E22-E17-E19 -> -1396 | F18: =F22-F17-F19 -> -410 | G18: -1500 | H18: -1700 | I18: -1900 | J18: -2100 | K18: -2300 | L18: -2500 | N18: Share repurchases: Gradually increasing from $1,500M (2026) to $2,500M (2031) in $200M annual increments. Historical buybacks ranged $333M–$1,856M. Ramp reflects management's commitment to returning excess cash to shareholders as earnings and FCF grow, preventing excessive cash accumulation on the balance sheet.
A19: Other (exercise/vesting) | B19: 0 | C19: 0 | D19: 0 | E19: 0 | F19: 0 | G19: 0 | H19: 0 | I19: 0 | J19: 0 | K19: 0 | L19: 0
A20: share price | F20: 308 | G20: =F20*(1+Ke!$D$32) -> 331.15038 | H20: =G20*(1+Ke!$D$32) -> 356.04082 | I20: =H20*(1+Ke!$D$32) -> 382.80211 | J20: =I20*(1+Ke!$D$32) -> 411.57488 | K20: =J20*(1+Ke!$D$32) -> 442.51031 | L20: =K20*(1+Ke!$D$32) -> 475.77096 | N20: Share price: Grows annually at the cost of equity rate (from Ke sheet). Used to estimate shares retired from repurchases.
A21: total shares | F21: =DCF!I3 -> 270.38976 | G21: =F21+(G18/G20)+G29 -> 266.88682 | H21: =G21+(H18/H20)+H29 -> 263.06703 | I21: =H21+(I18/I20)+I29 -> 258.99182 | J21: =I21+(J18/J20)+J29 -> 254.71556 | K21: =J21+(K18/K20)+K29 -> 250.28629 | L21: =K21+(L18/L20)+L29 -> 245.74629 | N21: Shares outstanding: Derived from beginning shares plus shares repurchased (repurchase amount / share price). Declines ~1.7% annually.
A22: Ending Balance | B22: ='Balance sheet'!B43 -> -19619 | C22: ='Balance sheet'!C43 -> -20721 | D22: ='Balance sheet'!D43 -> -21054 | E22: ='Balance sheet'!E43 -> -22450 | F22: ='Balance sheet'!F43 -> -22860 | G22: =G17+G18+G19 -> -24360 | H22: =H17+H18+H19 -> -26060 | I22: =I17+I18+I19 -> -27960 | J22: =J17+J18+J19 -> -30060 | K22: =K17+K18+K19 -> -32360 | L22: =L17+L18+L19 -> -34860
A25: SURPLUS (APIC / SBC)
A26: Beginning Balance | B26: 3008 | C26: =B32 -> 3278 | D26: =C32 -> 3556 | E26: =D32 -> 3760 | F26: =E32 -> 4062 | G26: =F32 -> 4403 | H26: =G32 -> 4743 | I26: =H32 -> 5083 | J26: =I32 -> 5423 | ... L26: =K32 -> 6103
A27: Stock-Based Compensation | B27: =B32-B26-B28 -> 270 | C27: =C32-C26-C28 -> 278 | D27: =D32-D26-D28 -> 204 | E27: =E32-E26-E28 -> 302 | F27: =F32-F26-F28 -> 341 | G27: 340 | H27: 340 | I27: 340 | J27: 340 | K27: 340 | L27: 340 | N27: Stock-based compensation: $340M annually. Historical SBC ranged $204–$341M. $340M is at the top of historical range, reflecting GD's growing equity compensation programs and competitive hiring in the defense sector. Held flat as a simplification.
A28: Other (options/vesting) | B28: 0 | C28: 0 | D28: 0 | E28: 0 | F28: 0 | G28: 0 | H28: 0 | I28: 0 | J28: 0 | K28: 0 | L28: 0
A29: new shares | G29: =G27/G20 -> 1.0267239 | H29: =H27/H20 -> 0.95494669 | I29: =I27/I20 -> 0.88818737 | J29: =J27/J20 -> 0.82609512 | K29: =K27/K20 -> 0.76834368 | L29: =L27/L20 -> 0.71462958 | N29: added back to total shares
A32: Ending Balance | B32: ='Balance sheet'!B41 -> 3278 | C32: ='Balance sheet'!C41 -> 3556 | D32: ='Balance sheet'!D41 -> 3760 | E32: ='Balance sheet'!E41 -> 4062 | F32: ='Balance sheet'!F41 -> 4403 | G32: =G26+G27+G28 -> 4743 | H32: =H26+H27+H28 -> 5083 | I32: =I26+I27+I28 -> 5423 | J32: =J26+J27+J28 -> 5763 | K32: =K26+K27+K28 -> 6103 | L32: =L26+L27+L28 -> 6443
A35: ACCUMULATED OTHER COMPREHENSIVE INCOME (LOSS)
A36: Beginning Balance | B36: -2182 | C36: =B41 -> -1920 | D36: =C41 -> -2152 | E36: =D41 -> -1159 | F36: =E41 -> -1518 | G36: =F41 -> -483 | H36: =G41 -> -483 | I36: =H41 -> -483 | J36: =I41 -> -483 | ... L36: =K41 -> -483
A37: Other Comprehensive Income (Loss) | B37: =B41-B36 -> 262 | C37: =C41-C36 -> -232 | D37: =D41-D36 -> 993 | E37: =E41-E36 -> -359 | F37: =F41-F36 -> 1035 | G37: 0 | H37: 0 | I37: 0 | J37: 0 | K37: 0 | L37: 0 | N37: OCI: Held constant at 2025 level (-$483M) per professor feedback. Historical swings large and volatile (+$1,035M to -$359M); too unpredictable to forecast. No change assumed.
A41: Ending Balance | B41: ='Balance sheet'!B44 -> -1920 | C41: ='Balance sheet'!C44 -> -2152 | D41: ='Balance sheet'!D44 -> -1159 | E41: ='Balance sheet'!E44 -> -1518 | F41: ='Balance sheet'!F44 -> -483 | G41: =G36+G37 -> -483 | H41: =H36+H37 -> -483 | I41: =I36+I37 -> -483 | J41: =J36+J37 -> -483 | K41: =K36+K37 -> -483 | L41: =L36+L37 -> -483
A44: TOTAL SHAREHOLDERS' EQUITY
A45: Common Stock | B45: ='Balance sheet'!B40 -> 482 | C45: ='Balance sheet'!C40 -> 482 | D45: ='Balance sheet'!D40 -> 482 | E45: ='Balance sheet'!E40 -> 482 | F45: ='Balance sheet'!F40 -> 482 | G45: 482 | H45: 482 | I45: 482 | J45: 482 | K45: 482 | L45: 482
A46: Surplus (APIC) | B46: =B32 -> 3278 | C46: =C32 -> 3556 | D46: =D32 -> 3760 | E46: =E32 -> 4062 | F46: =F32 -> 4403 | G46: =G32 -> 4743 | H46: =H32 -> 5083 | I46: =I32 -> 5423 | ... L46: =L32 -> 6443
A47: Retained Earnings | B47: =B13 -> 35420 | C47: =C13 -> 37403 | D47: =D13 -> 39270 | E47: =E13 -> 41487 | F47: =F13 -> 44080 | G47: =G13 -> 46745.609 | H47: =H13 -> 49523.636 | I47: =I13 -> 52446.147 | ... L47: =L13 -> 62111.305
A48: Treasury Stock | B48: =B22 -> -19619 | C48: =C22 -> -20721 | D48: =D22 -> -21054 | E48: =E22 -> -22450 | F48: =F22 -> -22860 | G48: =G22 -> -24360 | H48: =H22 -> -26060 | I48: =I22 -> -27960 | ... L48: =L22 -> -34860
A49: AOCI | B49: =B41 -> -1920 | C49: =C41 -> -2152 | D49: =D41 -> -1159 | E49: =E41 -> -1518 | F49: =F41 -> -483 | G49: =G41 -> -483 | H49: =H41 -> -483 | I49: =I41 -> -483 | ... L49: =L41 -> -483
A52: Total Shareholders' Equity | B52: =SUM(B45:B49) -> 17641 | C52: =SUM(C45:C49) -> 18568 | D52: =SUM(D45:D49) -> 21299 | E52: =SUM(E45:E49) -> 22063 | F52: =SUM(F45:F49) -> 25622 | G52: =SUM(G45:G49) -> 27127.609 | H52: =SUM(H45:H49) -> 28545.636 | I52: =SUM(I45:I49) -> 29908.147 | ... L52: =SUM(L45:L49) -> 33693.305

Sheet Schedules
A1: General Dynamics Corporation | N1: Projection Assumptions
A2: Property, Plant & Equipment Schedule
A3: (Dollars in millions)
A5: Year Ended December 31 | B5: 2021 | C5: 2022 | D5: 2023 | E5: 2024 | F5: 2025 | G5: 2026 | H5: 2027 | I5: 2028 | J5: 2029 | K5: 2030 | L5: 2031
A7: GROSS PP&E BY ASSET CLASS
A8: Machinery and equipment | B8: 5908 | C8: 6195 | D8: 6540 | E8: 7067 | F8: 7383
A9: Buildings and improvements | B9: 3756 | C9: 4035 | D9: 4406 | E9: 4886 | F9: 5763
A10: Construction in process | B10: 1318 | C10: 1397 | D10: 1434 | E10: 1173 | F10: 1462
A11: Land and improvements | B11: 382 | C11: 397 | D11: 428 | E11: 438 | F11: 522
A13: Total Gross PP&E | B13: =SUM(B8:B11) -> 11364 | C13: =SUM(C8:C11) -> 12024 | D13: =SUM(D8:D11) -> 12808 | E13: =SUM(E8:E11) -> 13564 | F13: =SUM(F8:F11) -> 15130 | G13: =G33 -> 17213 | H13: =H33 -> 19218 | I13: =I33 -> 21018 | J13: =J33 -> 22591 | K13: =K33 -> 23912 | L13: =L33 -> 25298
A14: Accumulated depreciation | B14: -5947 | C14: -6124 | D14: -6610 | E14: -7097 | F14: -7605 | G14: =-G42 -> -8333 | H14: =-H42 -> -9153 | I14: =-I42 -> -10058 | J14: =-J42 -> -11039 | K14: =-K42 -> -12085 | L14: =-L42 -> -13191
A16: PP&E, net | B16: =B13+B14 -> 5417 | C16: =C13+C14 -> 5900 | D16: =D13+D14 -> 6198 | E16: =E13+E14 -> 6467 | F16: =F13+F14 -> 7525 | G16: =G13+G14 -> 8880 | H16: =H13+H14 -> 10065 | I16: =I13+I14 -> 10960 | ... L16: =L13+L14 -> 12107
A19: ASSUMPTIONS
A20: Capital Expenditures | B20: 697 | C20: 783 | D20: 878 | E20: 916 | F20: 1163 | G20: =ROUND(G24*'Income statement'!G9,0) -> 2083 | H20: =ROUND(H24*'Income statement'!H9,0) -> 2005 | I20: =ROUND(I24*'Income statement'!I9,0) -> 1800 | J20: =ROUND(J24*'Income statement'!J9,0) -> 1573 | K20: =ROUND(K24*'Income statement'!K9,0) -> 1321 | L20: =ROUND(L24*'Income statement'!L9,0) -> 1387
A21: Depreciation Expense | B21: 508 | C21: 543 | D21: 568 | E21: 599 | F21: 680 | G21: =ROUND(G25*(G29+G33)/2,0) -> 728 | H21: =ROUND(H25*(H29+H33)/2,0) -> 820 | I21: =ROUND(I25*(I29+I33)/2,0) -> 905 | J21: =ROUND(J25*(J29+J33)/2,0) -> 981 | K21: =ROUND(K25*(K29+K33)/2,0) -> 1046 | L21: =ROUND(L25*(L29+L33)/2,0) -> 1107 | N21: Depreciation: Projected at 4.5% of average gross PP&E (beginning + ending / 2). Historical range: 4.5–4.7%. Per professor feedback, depreciation is better estimated as % of PP&E rather than revenue since it's the PP&E that is depreciating. Implied useful life stabilizes at ~23 years.
A22: Disposals / Retirements | B22: 0 | C22: =B13+C20-C13 -> 123 | D22: =C13+D20-D13 -> 94 | E22: =D13+E20-E13 -> 160 | F22: =E13+F20-F13 -> -403 | G22: 0 | H22: 0 | I22: 0 | J22: 0 | K22: 0 | L22: 1 | N22: Disposals: Zero assumed for projection years (except $1 in 2031E as placeholder). Historical disposals small and irregular ($0–$160M); immaterial to the PP&E rollforward and conservatively excluded.
A24: CapEx as % of Revenue | B24: =B20/'Income statement'!B9 -> 0.018118485 | C24: =C20/'Income statement'!C9 -> 0.019869566 | D24: =D20/'Income statement'!D9 -> 0.02077025 | E24: =E20/'Income statement'!E9 -> 0.019196915 | F24: =F20/'Income statement'!F9 -> 0.022131304 | G24: 0.038 | H24: 0.035 | I24: 0.03 | J24: 0.025 | K24: 0.02 | L24: 0.02
A25: D&A as % of Avg Gross PP&E | B25: =B21/((B29+B33)/2) -> 0.046116835 | C25: =C21/((C29+C33)/2) -> 0.046434069 | D25: =D21/((D29+D33)/2) -> 0.045747423 | E25: =E21/((E29+E33)/2) -> 0.045426968 | F25: =F21/((F29+F33)/2) -> 0.047396668 | G25: 0.045 | H25: 0.045 | I25: 0.045 | J25: 0.045 | K25: 0.045 | L25: 0.045
A26: Implied Useful Life (years) | B26: =B13/B21 -> 22.370079 | C26: =C13/C21 -> 22.143646 | D26: =D13/D21 -> 22.549296 | E26: =E13/E21 -> 22.644407 | F26: =F13/F21 -> 22.25 | G26: =IF(G21=0,"",G13/G21) -> 23.644231 | H26: =IF(H21=0,"",H13/H21) -> 23.436585 | I26: =IF(I21=0,"",I13/I21) -> 23.224309 | J26: =IF(J21=0,"",J13/J21) -> 23.028542 | K26: =IF(K21=0,"",K13/K21) -> 22.860421 | L26: =IF(L21=0,"",L13/L21) -> 22.852755
N27: Implied useful life: Derived (gross PP&E / depreciation). Rises gradually from ~24.5 to ~27.4 years reflecting growing PP&E base relative to stable depreciation rates.
A28: GROSS PP&E ROLLFORWARD
A29: Beginning Gross PP&E | B29: 10667 | C29: =B33 -> 11364 | D29: =C33 -> 12024 | E29: =D33 -> 12808 | F29: =E33 -> 13564 | G29: =F33 -> 15130 | H29: =G33 -> 17213 | I29: =H33 -> 19218 | J29: =I33 -> 21018 | ... L29: =K33 -> 23912
A30: (+) Capital Expenditures | B30: =B20 -> 697 | C30: =C20 -> 783 | D30: =D20 -> 878 | E30: =E20 -> 916 | F30: =F20 -> 1163 | G30: =G20 -> 2083 | H30: =H20 -> 2005 | I30: =I20 -> 1800 | ... L30: =L20 -> 1387
A31: (-) Disposals / Retirements | B31: =B22 -> 0 | C31: =C22 -> 123 | D31: =D22 -> 94 | E31: =E22 -> 160 | F31: =F22 -> -403 | G31: =G22 -> 0 | H31: =H22 -> 0 | I31: =I22 -> 0 | ... L31: =L22 -> 1
A33: Ending Gross PP&E | B33: =B13 -> 11364 | C33: =C13 -> 12024 | D33: =D13 -> 12808 | E33: =E13 -> 13564 | F33: =F13 -> 15130 | G33: =G29+G30-G31 -> 17213 | H33: =H29+H30-H31 -> 19218 | I33: =I29+I30-I31 -> 21018 | J33: =J29+J30-J31 -> 22591 | K33: =K29+K30-K31 -> 23912 | L33: =L29+L30-L31 -> 25298
A35: YoY Change | B35: n/a | C35: =C33/B33-1 -> 0.058078141 | D35: =D33/C33-1 -> 0.065202927 | E35: =E33/D33-1 -> 0.059025609 | F35: =F33/E33-1 -> 0.11545267 | G35: =G33/F33-1 -> 0.1376735 | H35: =H33/G33-1 -> 0.11648173 | I35: =I33/H33-1 -> 0.093662192 | J35: =J33/I33-1 -> 0.074840613 | ... L35: =L33/K33-1 -> 0.057962529
A37: ACCUMULATED DEPRECIATION ROLLFORWARD
A38: Beginning Accumulated Depreciation | B38: 5468 | C38: =B42 -> 5947 | D38: =C42 -> 6124 | E38: =D42 -> 6610 | F38: =E42 -> 7097 | G38: =F42 -> 7605 | H38: =G42 -> 8333 | I38: =H42 -> 9153 | J38: =I42 -> 10058 | ... L38: =K42 -> 12085
A39: (+) Depreciation Expense | B39: =B21 -> 508 | C39: =C21 -> 543 | D39: =D21 -> 568 | E39: =E21 -> 599 | F39: =F21 -> 680 | G39: =G21 -> 728 | H39: =H21 -> 820 | I39: =I21 -> 905 | ... L39: =L21 -> 1107
A40: (-) Disposals removed | B40: =B42-B38-B39 -> -29 | C40: =C42-C38-C39 -> -366 | D40: =D42-D38-D39 -> -82 | E40: =E42-E38-E39 -> -112 | F40: =F42-F38-F39 -> -172 | G40: =G22 -> 0 | H40: =H22 -> 0 | I40: =I22 -> 0 | J40: =J22 -> 0 | K40: =K22 -> 0 | L40: =L22 -> 1
A42: Ending Accumulated Depreciation | B42: =-B14 -> 5947 | C42: =-C14 -> 6124 | D42: =-D14 -> 6610 | E42: =-E14 -> 7097 | F42: =-F14 -> 7605 | G42: =G38+G39-G40 -> 8333 | H42: =H38+H39-H40 -> 9153 | I42: =I38+I39-I40 -> 10058 | J42: =J38+J39-J40 -> 11039 | K42: =K38+K39-K40 -> 12085 | L42: =L38+L39-L40 -> 13191
A44: Accum. Dep as % of Gross PP&E | B44: =B42/B13 -> 0.52331925 | C44: =C42/C13 -> 0.5093147 | D44: =D42/D13 -> 0.5160837 | E44: =E42/E13 -> 0.52322324 | F44: =F42/F13 -> 0.50264375 | G44: =G42/G13 -> 0.48411085 | H44: =H42/H13 -> 0.47627224 | I44: =I42/I13 -> 0.4785422 | ... L44: =L42/L13 -> 0.52142462
A46: NET PP&E SUMMARY
A47: Gross PP&E | B47: =B13 -> 11364 | C47: =C13 -> 12024 | D47: =D13 -> 12808 | E47: =E13 -> 13564 | F47: =F13 -> 15130 | G47: =G13 -> 17213 | H47: =H13 -> 19218 | I47: =I13 -> 21018 | ... L47: =L13 -> 25298
A48: Accumulated Depreciation | B48: =-B42 -> -5947 | C48: =-C42 -> -6124 | D48: =-D42 -> -6610 | E48: =-E42 -> -7097 | F48: =-F42 -> -7605 | G48: =-G42 -> -8333 | H48: =-H42 -> -9153 | I48: =-I42 -> -10058 | ... L48: =-L42 -> -13191
A50: Net PP&E | B50: =B47+B48 -> 5417 | C50: =C47+C48 -> 5900 | D50: =D47+D48 -> 6198 | E50: =E47+E48 -> 6467 | F50: =F47+F48 -> 7525 | G50: =G47+G48 -> 8880 | H50: =H47+H48 -> 10065 | I50: =I47+I48 -> 10960 | ... L50: =L47+L48 -> 12107
A52: General Dynamics Corporation
A53: Debt Schedule
A54: (Dollars in millions)
A56: Year Ended December 31 | B56: 2021 | C56: 2022 | D56: 2023 | E56: 2024 | F56: 2025 | G56: 2026 | H56: 2027 | I56: 2028 | J56: 2029 | K56: 2030 | L56: 2031
A58: OUTSTANDING NOTES DETAIL | N58: Individual note balances: Based on actual outstanding notes from GD 2024/2025 10-K filings. Each note matures per its stated maturity date (balances go to zero in maturity year). 1.150% and 2.125% notes matured in 2026E; 3.500% and 2.625% notes mature in 2027E, etc.
A59: 1.150% Fixed-Rate Notes | B59: 500 | C59: 500 | D59: 500 | E59: 500 | F59: 500 | G59: 0 | H59: 0 | I59: 0 | J59: 0 | K59: 0 | L59: 0
A60: 2.125% Fixed-Rate Notes | B60: 500 | C60: 500 | D60: 500 | E60: 500 | F60: 500 | G60: 0 | H60: 0 | I60: 0 | J60: 0 | K60: 0 | L60: 0
A61: 3.500% Fixed-Rate Notes | B61: 750 | C61: 750 | D61: 750 | E61: 750 | F61: 750 | G61: 750 | H61: 0 | I61: 0 | J61: 0 | K61: 0 | L61: 0
A62: 2.625% Fixed-Rate Notes | B62: 500 | C62: 500 | D62: 500 | E62: 500 | F62: 500 | G62: 500 | H62: 0 | I62: 0 | J62: 0 | K62: 0 | L62: 0
A63: 3.750% Fixed-Rate Notes | B63: 1000 | C63: 1000 | D63: 1000 | E63: 1000 | F63: 1000 | G63: 1000 | H63: 1000 | I63: 0 | J63: 0 | K63: 0 | L63: 0
A64: 3.625% Fixed-Rate Notes | B64: 1000 | C64: 1000 | D64: 1000 | E64: 1000 | F64: 1000 | G64: 1000 | H64: 1000 | I64: 1000 | J64: 1000 | K64: 0 | L64: 0
A65: 2.250% Fixed-Rate Notes | B65: 500 | C65: 500 | D65: 500 | E65: 500 | F65: 500 | G65: 500 | H65: 500 | I65: 500 | J65: 500 | K65: 500 | L65: 0
A66: 4.950% Fixed-Rate Notes | B66: 0 | C66: 0 | D66: 0 | E66: 0 | F66: 750 | G66: 750 | H66: 750 | I66: 750 | J66: 750 | K66: 750 | L66: 750
A67: 4.250% Fixed-Rate Notes | B67: 750 | C67: 750 | D67: 750 | E67: 750 | F67: 750 | G67: 750 | H67: 750 | I67: 750 | J67: 750 | K67: 750 | L67: 750
A68: 2.850% Fixed-Rate Notes | B68: 500 | C68: 500 | D68: 500 | E68: 500 | F68: 500 | G68: 500 | H68: 500 | I68: 500 | J68: 500 | K68: 500 | L68: 500
A69: 3.600% Fixed-Rate Notes | B69: 500 | C69: 500 | D69: 500 | E69: 500 | F69: 500 | G69: 500 | H69: 500 | I69: 500 | J69: 500 | K69: 500 | L69: 500
A70: 4.250% Fixed-Rate Notes | B70: 750 | C70: 750 | D70: 750 | E70: 750 | F70: 750 | G70: 750 | H70: 750 | I70: 750 | J70: 750 | K70: 750 | L70: 750
A71: Other | B71: 74 | C71: 74 | D71: 74 | E71: 76 | F71: 74 | G71: 68 | H71: 61 | I71: 54 | J71: 47 | K71: 40 | L71: 40
A73: Total Debt Principal | B73: =SUM(B59:B71) -> 7324 | C73: =SUM(C59:C71) -> 7324 | D73: =SUM(D59:D71) -> 7324 | E73: =SUM(E59:E71) -> 7326 | F73: =SUM(F59:F71) -> 8074 | G73: =SUM(G59:G71) -> 7068 | H73: =SUM(H59:H71) -> 5811 | I73: =SUM(I59:I71) -> 4804 | ... L73: =SUM(L59:L71) -> 3290
A74: Less: Unamortized issuance costs & discounts | B74: -61 | C74: -61 | D74: -61 | E74: -64 | F74: -61 | G74: -55 | H74: -49 | I74: -43 | J74: -37 | K74: -31 | L74: -25 | N74: Unamortized costs: Gradually declining from -$55 to -$25 as older notes mature and issuance costs amortize. Approximated based on historical trend.
A75: Total Debt (Book Value) | B75: =B73+B74 -> 7263 | C75: =C73+C74 -> 7263 | D75: =D73+D74 -> 7263 | E75: =E73+E74 -> 7262 | F75: =F73+F74 -> 8013 | G75: =G81+G74 -> 8488 | H75: =H81+H74 -> 8937 | I75: =I81+I74 -> 9361 | J75: =J81+J74 -> 9760 | K75: =K81+K74 -> 10159 | L75: =L81+L74 -> 10515
A77: DEBT ROLLFORWARD
A78: Beginning Debt Principal | B78: 11672 | C78: =B73 -> 7324 | D78: =C73 -> 7324 | E78: =D73 -> 7324 | F78: =E73 -> 7326 | G78: =F73 -> 8074 | H78: =G81 -> 8543 | I78: =H81 -> 8986 | J78: =I81 -> 9404 | K78: =J81 -> 9797 | L78: =K81 -> 10190
A79: (+) New Issuances | B79: 1497 | C79: 0 | D79: 0 | E79: 0 | F79: 750 | G79: 1475 | H79: 1700 | I79: 1425 | J79: 400 | K79: 1400 | L79: 850 | N79: New issuances: $1,650M/yr in 2026–28E, stepping down to $1,000–1,600M/yr in 2029–31E. Sized to maintain target D/V ratio of ~24% as equity grows from retained earnings. Consistent with GD's historical pattern of periodic bond issuances to manage capital structure.
A80: (-) Repayments | B80: =B73-B78-B79 -> -5845 | C80: =C73-C78-C79 -> 0 | D80: =D73-D78-D79 -> 0 | E80: =E73-E78-E79 -> 2 | F80: =F73-F78-F79 -> -2 | G80: =G81-G78-G79 -> -1006 | H80: =H81-H78-H79 -> -1257 | I80: =I81-I78-I79 -> -1007 | J80: =J81-J78-J79 -> -7 | K80: =K81-K78-K79 -> -1007 | L80: =L81-L78-L79 -> -500 | N80: Repayments: Driven by maturing notes per the note detail above. No early repayments assumed.
A81: Ending Debt Principal | B81: =B78+B79+B80 -> 7324 | C81: =C78+C79+C80 -> 7324 | D81: =D78+D79+D80 -> 7324 | E81: =E78+E79+E80 -> 7326 | F81: =F78+F79+F80 -> 8074 | G81: =G73+G79 -> 8543 | H81: =H73+SUM(G79:H79) -> 8986 | I81: =I73+SUM(G79:I79) -> 9404 | J81: =J73+SUM(G79:J79) -> 9797 | K81: =K73+SUM(G79:K79) -> 10190 | L81: =L73+SUM(G79:L79) -> 10540
A82: Check (Ending = Total Principal) | B82: =B81-B73 -> 0 | C82: =C81-C73 -> 0 | D82: =D81-D73 -> 0 | E82: =E81-E73 -> 0 | F82: =F81-F73 -> 0 | G82: =G81-G73-G79 -> 0 | H82: =H81-H73-SUM(G79:H79) -> 0 | I82: =I81-I73-SUM(G79:I79) -> 0 | J82: =J81-J73-SUM(G79:J79) -> 0 | K82: =K81-K73-SUM(G79:K79) -> 0 | L82: =L81-L73-SUM(G79:L79) -> 0
A84: LEVERAGE ANALYSIS
A85: D/E Ratio (Total Debt / Equity) | C85: =C75/'Balance sheet'!C45 -> 0.39115683 | D85: =D75/'Balance sheet'!D45 -> 0.34100192 | E85: =E75/'Balance sheet'!E45 -> 0.32914835 | F85: =F75/'Balance sheet'!F45 -> 0.31273905 | G85: =G90/'Balance sheet'!G45 -> 0.31289157 | H85: =H90/'Balance sheet'!H45 -> 0.31307763 | I85: =I90/'Balance sheet'!I45 -> 0.31299164 | J85: =J90/'Balance sheet'!J45 -> 0.31278615 | K85: =K90/'Balance sheet'!K45 -> 0.31291875 | L85: =L90/'Balance sheet'!L45 -> 0.3120798 | N85: D/E ratio: Simple Debt / Equity. Historical and projected. Total Debt from balance sheet classification divided by Total Shareholders' Equity.
A87: BALANCE SHEET CLASSIFICATION
A88: Short-term Debt (Current Portion of LTD) | B88: ='Balance sheet'!B26 -> 1005 | C88: ='Balance sheet'!C26 -> 1253 | D88: ='Balance sheet'!D26 -> 507 | E88: ='Balance sheet'!E26 -> 1502 | F88: ='Balance sheet'!F26 -> 1006 | G88: =G73-H73 -> 1257 | H88: =H73-I73 -> 1007 | I88: =I73-J73 -> 7 | J88: =J73-K73 -> 1007 | K88: =K73-L73 -> 500 | L88: 0 | N88: Short-term debt (current portion): Equals sum of notes maturing within 12 months. Linked from the note maturity schedule above.
A89: Long-term Debt | B89: ='Balance sheet'!B33 -> 10490 | C89: ='Balance sheet'!C33 -> 9243 | D89: ='Balance sheet'!D33 -> 8754 | E89: ='Balance sheet'!E33 -> 7260 | F89: ='Balance sheet'!F33 -> 7007 | G89: =G75-G88 -> 7231 | H89: =H75-H88 -> 7930 | I89: =I75-I88 -> 9354 | J89: =J75-J88 -> 8753 | K89: =K75-K88 -> 9659 | L89: =L75-L88 -> 10515 | N89: Long-term debt: Total debt book value minus current portion.
A90: Total Debt | B90: =B88+B89 -> 11495 | C90: =C88+C89 -> 10496 | D90: =D88+D89 -> 9261 | E90: =E88+E89 -> 8762 | F90: =F88+F89 -> 8013 | G90: =G88+G89 -> 8488 | H90: =H88+H89 -> 8937 | I90: =I88+I89 -> 9361 | ... L90: =L88+L89 -> 10515
A92: INTEREST EXPENSE ESTIMATE
A93: Wtd. Avg. Interest Rate | C93: =ABS('Income statement'!C20)/((B75+C75)/2) -> 0.050117032 | D93: =ABS('Income statement'!D20)/((C75+D75)/2) -> 0.047225664 | E93: =ABS('Income statement'!E20)/((D75+E75)/2) -> 0.044612737 | F93: =ABS('Income statement'!F20)/((E75+F75)/2) -> 0.04111293 | G93: =F93 -> 0.04111293 | H93: 0.0425 | I93: 0.045 | J93: 0.0475 | K93: 0.05 | L93: 0.05 | N93: Weighted-avg interest rate: 4.11% in 2026E (carried from 2025 actual), stepping up to 4.25% from 2027E onward. Reflects blended coupon on existing fixed-rate notes (~3.0–4.95%) plus new issuances assumed at higher current market rates (~4.5–5.0%).
A94: Avg. Total Debt (Book Value) | C94: =(B75+C75)/2 -> 7263 | D94: =(C75+D75)/2 -> 7263 | E94: =(D75+E75)/2 -> 7262.5 | F94: =(E75+F75)/2 -> 7637.5 | G94: =(F75+G75)/2 -> 8250.5 | H94: =(G75+H75)/2 -> 8712.5 | I94: =(H75+I75)/2 -> 9149 | J94: =(I75+J75)/2 -> 9560.5 | ... L94: =(K75+L75)/2 -> 10337 | N94: Average total debt: Simple average of beginning and ending debt book values for each year.
A95: Interest Expense | C95: =ABS('Income statement'!C20) -> 364 | D95: =ABS('Income statement'!D20) -> 343 | E95: =ABS('Income statement'!E20) -> 324 | F95: =ABS('Income statement'!F20) -> 314 | G95: =G93*G94 -> 339.20223 | H95: =H93*H94 -> 370.28125 | I95: =I93*I94 -> 411.705 | J95: =J93*J94 -> 454.12375 | K95: =K93*K94 -> 497.975 | L95: =L93*L94 -> 516.85 | N95: Interest expense: Wtd. avg. rate × avg. total debt. Links to Income statement interest, net line. Historical interest ranged $314–$424M; rises over projection as total debt grows.
A97: General Dynamics Corporation
A98: Working Capital Schedule
A99: (Dollars in millions)
A101: Year Ended December 31 | B101: 2021 | C101: 2022 | D101: 2023 | E101: 2024 | F101: 2025 | G101: 2026 | H101: 2027 | I101: 2028 | J101: 2029 | K101: 2030 | L101: 2031
A103: REFERENCE DATA
A104: Total Revenue | B104: ='Income statement'!B9 -> 38469 | C104: ='Income statement'!C9 -> 39407 | D104: ='Income statement'!D9 -> 42272 | E104: ='Income statement'!E9 -> 47716 | F104: ='Income statement'!F9 -> 52550 | G104: ='Income statement'!G9 -> 54822.283 | H104: ='Income statement'!H9 -> 57293.926 | I104: ='Income statement'!I9 -> 60015.52 | ... L104: ='Income statement'!L9 -> 69342.567
A105: Product COGS | B105: =ABS('Income statement'!B12) -> 18524 | C105: =ABS('Income statement'!C12) -> 18981 | D105: =ABS('Income statement'!D12) -> 20591 | E105: =ABS('Income statement'!E12) -> 24332 | F105: =ABS('Income statement'!F12) -> 27965 | G105: =ABS('Income statement'!G12) -> 29241.032 | H105: =ABS('Income statement'!H12) -> 30666.326 | I105: =ABS('Income statement'!I12) -> 32258.775 | ... L105: =ABS('Income statement'!L12) -> 37703.187
A106: Service COGS | B106: =ABS('Income statement'!B13) -> 13537 | C106: =ABS('Income statement'!C13) -> 13804 | D106: =ABS('Income statement'!D13) -> 15009 | E106: =ABS('Income statement'!E13) -> 16020 | F106: =ABS('Income statement'!F13) -> 16634 | G106: =ABS('Income statement'!G13) -> 17286.062 | H106: =ABS('Income statement'!H13) -> 17957.81 | I106: =ABS('Income statement'!I13) -> 18674.339 | ... L106: =ABS('Income statement'!L13) -> 21142.99
A107: Total COGS | B107: =B105+B106 -> 32061 | C107: =C105+C106 -> 32785 | D107: =D105+D106 -> 35600 | E107: =E105+E106 -> 40352 | F107: =F105+F106 -> 44599 | G107: =G105+G106 -> 46527.094 | H107: =H105+H106 -> 48624.136 | I107: =I105+I106 -> 50933.113 | ... L107: =L105+L106 -> 58846.178
A109: EFFICIENCY RATIOS
A110: DSO (Days Sales Outstanding) | B110: ='Balance sheet'!B9/B104*365 -> 28.853492 | C110: ='Balance sheet'!C9/C104*365 -> 27.86104 | D110: ='Balance sheet'!D9/D104*365 -> 25.93821 | E110: ='Balance sheet'!E9/E104*365 -> 22.772341 | F110: ='Balance sheet'!F9/F104*365 -> 16.711513 | G110: 17 | H110: 17 | I110: 17 | J110: 17 | K110: 17 | L110: 17 | N110: DSO: 17 days (held flat). Historical range: 17–29 days. 2025 actual was 16.7 days, the lowest in the period. 17 days reflects GD's efficient collections on government contracts with predictable payment cycles. Conservative rounding up from 2025.
A111: DSI (Days Sales of Inventory) | B111: ='Balance sheet'!B11/B107*365 -> 60.793487 | C111: ='Balance sheet'!C11/C107*365 -> 70.383712 | D111: ='Balance sheet'!D11/D107*365 -> 87.948596 | E111: ='Balance sheet'!E11/E107*365 -> 87.957474 | F111: ='Balance sheet'!F11/F107*365 -> 75.555057 | G111: 75 | H111: 75 | I111: 75 | J111: 75 | K111: 75 | L111: 75 | N111: DSI: 75 days (held flat). Historical range: 61–88 days. 2025 actual was 75.6 days. Reflects normalized inventory levels after the Gulfstream production ramp build-up in 2023–24 (which peaked at 88 days).
A112: DPO (Days Payable Outstanding) | B112: ='Balance sheet'!B27/B107*365 -> 36.054864 | C112: ='Balance sheet'!C27/C107*365 -> 37.83041 | D112: ='Balance sheet'!D27/D107*365 -> 31.732444 | E112: ='Balance sheet'!E27/E107*365 -> 30.247819 | F112: ='Balance sheet'!F27/F107*365 -> 21.916859 | G112: 22 | H112: 22 | I112: 22 | J112: 22 | K112: 22 | L112: 22 | N112: DPO: 22 days (held flat). Historical range: 22–38 days. 2025 actual was 21.9 days, the lowest in the period. Reflects GD's disciplined payables management and shorter payment cycles typical of defense primes.
A113: CCC (Cash Conversion Cycle) | B113: =B110+B111-B112 -> 53.592116 | C113: =C110+C111-C112 -> 60.414342 | D113: =D110+D111-D112 -> 82.154361 | E113: =E110+E111-E112 -> 80.481996 | F113: =F110+F111-F112 -> 70.349711 | G113: =G110+G111-G112 -> 70 | H113: =H110+H111-H112 -> 70 | I113: =I110+I111-I112 -> 70 | ... L113: =L110+L111-L112 -> 70 | N113: CCC: 70 days (derived: DSO + DSI – DPO). Stable throughout projection reflecting flat efficiency ratios. Historical CCC ranged 54–82 days.
A115: PROJECTED WORKING CAPITAL BALANCES
A116: Accounts Receivable | B116: ='Balance sheet'!B9 -> 3041 | C116: ='Balance sheet'!C9 -> 3008 | D116: ='Balance sheet'!D9 -> 3004 | E116: ='Balance sheet'!E9 -> 2977 | F116: ='Balance sheet'!F9 -> 2406 | G116: =G110/365*G104 -> 2553.3666 | H116: =H110/365*H104 -> 2668.4842 | I116: =I110/365*I104 -> 2795.2434 | J116: =J110/365*J104 -> 2931.2988 | K116: =K110/365*K104 -> 3075.8758 | L116: =L110/365*L104 -> 3229.6538 | N116: Accounts receivable: = DSO / 365 × total revenue. Linked to Balance sheet.
A117: Inventories | B117: ='Balance sheet'!B11 -> 5340 | C117: ='Balance sheet'!C11 -> 6322 | D117: ='Balance sheet'!D11 -> 8578 | E117: ='Balance sheet'!E11 -> 9724 | F117: ='Balance sheet'!F11 -> 9232 | G117: =G111/365*G107 -> 9560.3618 | H117: =H111/365*H107 -> 9991.2608 | I117: =I111/365*I107 -> 10465.708 | J117: =J111/365*J107 -> 10974.947 | K117: =K111/365*K107 -> 11516.089 | L117: =L111/365*L107 -> 12091.68 | N117: Inventories: = DSI / 365 × total COGS. Linked to Balance sheet.
A118: Accounts Payable | B118: ='Balance sheet'!B27 -> 3167 | C118: ='Balance sheet'!C27 -> 3398 | D118: ='Balance sheet'!D27 -> 3095 | E118: ='Balance sheet'!E27 -> 3344 | F118: ='Balance sheet'!F27 -> 2678 | G118: =G112/365*G107 -> 2804.3728 | H118: =H112/365*H107 -> 2930.7698 | I118: =I112/365*I107 -> 3069.9411 | J118: =J112/365*J107 -> 3219.3178 | K118: =K112/365*K107 -> 3378.0529 | L118: =L112/365*L107 -> 3546.8929 | N118: Accounts payable: = DPO / 365 × total COGS. Linked to Balance sheet.
A120: Net Working Capital (AR + Inv - AP) | B120: =B116+B117-B118 -> 5214 | C120: =C116+C117-C118 -> 5932 | D120: =D116+D117-D118 -> 8487 | E120: =E116+E117-E118 -> 9357 | F120: =F116+F117-F118 -> 8960 | G120: =G116+G117-G118 -> 9309.3556 | H120: =H116+H117-H118 -> 9728.9752 | I120: =I116+I117-I118 -> 10191.011 | ... L120: =L116+L117-L118 -> 11774.441
A121: Change in Net Working Capital | C121: =C120-B120 -> 718 | D121: =D120-C120 -> 2555 | E121: =E120-D120 -> 870 | F121: =F120-E120 -> -397 | G121: =G120-F120 -> 349.3556 | H121: =H120-G120 -> 419.61956 | I121: =I120-H120 -> 462.03537 | J121: =J120-I120 -> 495.91743 | ... L121: =L120-K120 -> 560.52896
A122: NWC as % of Revenue | B122: =B120/B104 -> 0.13553771 | C122: =C120/C104 -> 0.15053163 | D122: =D120/D104 -> 0.2007712 | E122: =E120/E104 -> 0.19609774 | F122: =F120/F104 -> 0.17050428 | G122: =G120/G104 -> 0.1698097 | H122: =H120/H104 -> 0.16980814 | I122: =I120/I104 -> 0.16980625 | ... L122: =L120/L104 -> 0.16980106

Sheet Comps
C1: USD
A2: COMPARABLE COMPANY ANALYSIS
A3: COMPANY DATA
A4: (in millions) | C4: Recent | D4: 52 week | E4: Shares | F4: Market | G4: Total | I4: Enterprise | J4: Book | L4: WS 12-mo
A5: Company Name | B5: Ticker | C5: Price | D5: High | E5: Out | F5: Cap | G5: Debt | H5: Cash | I5: Value | J5: Value | K5: Beta | L5: Price Target
A6: {=IF($B6="","",_xll.RDP.Data($B6,"TR.CompanyName"))} -> Please sign in | B6: LMT | C6: =IF(B6="","",_xll.RDP.Data($B6,"TR.PriceClose","Curn=#1",,$C$1)) -> Please sign in | D6: =IF($B6="","",_xll.RDP.Data($B6,"MAX(TR.PriceHigh(SDate=0D,EDate=0D-364C))/*52 Week High*/","Curn=#1",,$C$1)) -> Please sign in | E6: =IF(B6="","",_xll.RDP.Data($B6,"TR.CompanySharesOutstanding(SDate=0)/*# Shares Outstanding*/")/1000000) -> #VALUE! | F6: =IF(B6="","",C6*E6) -> #VALUE! | G6: {=IF($B6="","",_xll.RDP.Data($B6,"TR.TotalDebtOutstanding","Curn=#1",,$C$1)/1000000)} -> #VALUE! | H6: =IF($B6="","",_xll.RDP.Data($B6,"TR.CashandEquivalents","Curn=#1",,$C$1)/1000000) -> #VALUE! | I6: =IF(B6="","",F6+G6-H6) -> #VALUE! | J6: {=IF($B6="","",_xll.RDP.Data($B6,"TR.TotalEquity","Curn=#1",,$C$1)/1000000)} -> #VALUE! | K6: =IF($B6="","",_xll.RDP.Data($B6,"TR.BetaFiveYear/*Beta 5 Year Monthly*//*Beta 5 Year Monthly*/")) -> Please sign in | L6: =IF(B6="","",_xll.RDP.Data($B6,"TR.PriceTargetMean","Curn=#1",,$C$1)) -> Please sign in
A7: {=IF($B7="","",_xll.RDP.Data($B7,"TR.CompanyName"))} -> Please sign in | B7: RTX | C7: =IF(B7="","",_xll.RDP.Data($B7,"TR.PriceClose","Curn=#1",,$C$1)) -> Please sign in | D7: =IF($B7="","",_xll.RDP.Data($B7,"MAX(TR.PriceHigh(SDate=0D,EDate=0D-364C))/*52 Week High*/","Curn=#1",,$C$1)) -> Please sign in | E7: =IF(B7="","",_xll.RDP.Data($B7,"TR.CompanySharesOutstanding(SDate=0)/*# Shares Outstanding*/")/1000000) -> #VALUE! | F7: =IF(B7="","",C7*E7) -> #VALUE! | G7: {=IF($B7="","",_xll.RDP.Data($B7,"TR.TotalDebtOutstanding","Curn=#1",,$C$1)/1000000)} -> #VALUE! | H7: =IF($B7="","",_xll.RDP.Data($B7,"TR.CashandEquivalents","Curn=#1",,$C$1)/1000000) -> #VALUE! | I7: =IF(B7="","",F7+G7-H7) -> #VALUE! | J7: {=IF($B7="","",_xll.RDP.Data($B7,"TR.TotalEquity","Curn=#1",,$C$1)/1000000)} -> #VALUE! | K7: =IF($B7="","",_xll.RDP.Data($B7,"TR.BetaFiveYear/*Beta 5 Year Monthly*//*Beta 5 Year Monthly*/")) -> Please sign in | L7: =IF(B7="","",_xll.RDP.Data($B7,"TR.PriceTargetMean","Curn=#1",,$C$1)) -> Please sign in
A8: {=IF($B8="","",_xll.RDP.Data($B8,"TR.CompanyName"))} -> Please sign in | B8: NOC | C8: =IF(B8="","",_xll.RDP.Data($B8,"TR.PriceClose","Curn=#1",,$C$1)) -> Please sign in | D8: =IF($B8="","",_xll.RDP.Data($B8,"MAX(TR.PriceHigh(SDate=0D,EDate=0D-364C))/*52 Week High*/","Curn=#1",,$C$1)) -> Please sign in | E8: =IF(B8="","",_xll.RDP.Data($B8,"TR.CompanySharesOutstanding(SDate=0)/*# Shares Outstanding*/")/1000000) -> #VALUE! | F8: =IF(B8="","",C8*E8) -> #VALUE! | G8: {=IF($B8="","",_xll.RDP.Data($B8,"TR.TotalDebtOutstanding","Curn=#1",,$C$1)/1000000)} -> #VALUE! | H8: =IF($B8="","",_xll.RDP.Data($B8,"TR.CashandEquivalents","Curn=#1",,$C$1)/1000000) -> #VALUE! | I8: =IF(B8="","",F8+G8-H8) -> #VALUE! | J8: {=IF($B8="","",_xll.RDP.Data($B8,"TR.TotalEquity","Curn=#1",,$C$1)/1000000)} -> #VALUE! | K8: =IF($B8="","",_xll.RDP.Data($B8,"TR.BetaFiveYear/*Beta 5 Year Monthly*//*Beta 5 Year Monthly*/")) -> Please sign in | L8: =IF(B8="","",_xll.RDP.Data($B8,"TR.PriceTargetMean","Curn=#1",,$C$1)) -> Please sign in
A9: {=IF($B9="","",_xll.RDP.Data($B9,"TR.CompanyName"))} -> Please sign in | B9: LHX | C9: =IF(B9="","",_xll.RDP.Data($B9,"TR.PriceClose","Curn=#1",,$C$1)) -> Please sign in | D9: =IF($B9="","",_xll.RDP.Data($B9,"MAX(TR.PriceHigh(SDate=0D,EDate=0D-364C))/*52 Week High*/","Curn=#1",,$C$1)) -> Please sign in | E9: =IF(B9="","",_xll.RDP.Data($B9,"TR.CompanySharesOutstanding(SDate=0)/*# Shares Outstanding*/")/1000000) -> #VALUE! | F9: =IF(B9="","",C9*E9) -> #VALUE! | G9: {=IF($B9="","",_xll.RDP.Data($B9,"TR.TotalDebtOutstanding","Curn=#1",,$C$1)/1000000)} -> #VALUE! | H9: 0 | I9: =IF(B9="","",F9+G9-H9) -> #VALUE! | J9: {=IF($B9="","",_xll.RDP.Data($B9,"TR.TotalEquity","Curn=#1",,$C$1)/1000000)} -> #VALUE! | K9: =IF($B9="","",_xll.RDP.Data($B9,"TR.BetaFiveYear/*Beta 5 Year Monthly*//*Beta 5 Year Monthly*/")) -> Please sign in | L9: =IF(B9="","",_xll.RDP.Data($B9,"TR.PriceTargetMean","Curn=#1",,$C$1)) -> Please sign in
A10: {=IF($B10="","",_xll.RDP.Data($B10,"TR.CompanyName"))} -> Please sign in | B10: GD | C10: =IF(B10="","",_xll.RDP.Data($B10,"TR.PriceClose","Curn=#1",,$C$1)) -> Please sign in | D10: =IF($B10="","",_xll.RDP.Data($B10,"MAX(TR.PriceHigh(SDate=0D,EDate=0D-364C))/*52 Week High*/","Curn=#1",,$C$1)) -> Please sign in | E10: =IF(B10="","",_xll.RDP.Data($B10,"TR.CompanySharesOutstanding(SDate=0)/*# Shares Outstanding*/")/1000000) -> #VALUE! | F10: =IF(B10="","",C10*E10) -> #VALUE! | G10: {=IF($B10="","",_xll.RDP.Data($B10,"TR.TotalDebtOutstanding","Curn=#1",,$C$1)/1000000)} -> #VALUE! | H10: =IF($B10="","",_xll.RDP.Data($B10,"TR.CashandEquivalents","Curn=#1",,$C$1)/1000000) -> #VALUE! | I10: =IF(B10="","",F10+G10-H10) -> #VALUE! | J10: {=IF($B10="","",_xll.RDP.Data($B10,"TR.TotalEquity","Curn=#1",,$C$1)/1000000)} -> #VALUE! | K10: =IF($B10="","",_xll.RDP.Data($B10,"TR.BetaFiveYear/*Beta 5 Year Monthly*//*Beta 5 Year Monthly*/")) -> Please sign in | L10: =IF(B10="","",_xll.RDP.Data($B10,"TR.PriceTargetMean","Curn=#1",,$C$1)) -> Please sign in
A12: I/B/E/S ESTIMATES
C13: SALES | G13: EPS | K13: EBIT | N13: EBITDA | Q13: EPS 5-yr
A14: Company Name | B14: Ticker | C14: Last FY | D14: FYR1 | E14: FYR2 | F14: FYR3 | G14: Last FY | H14: FYR1 | I14: FYR2 | J14: FYR3 | K14: Last FY | L14: FYR1 | M14: FYR2 | N14: Last FY | O14: FYR1 | P14: FYR2 | Q14: Growth %
A15: =A6 -> Please sign in | B15: =IF(B6="","",B6) -> LMT | C15: {=IF($B15="","",_xll.RDP.Data($B15,"TR.Revenue","Curn=#1",,$C$1)/1000000)} -> #VALUE! | D15: {=IF($B15="","",_xll.RDP.Data($B15,"TR.RevenueMean","Period=FY1 Frq=D SDate=1D Curn=#1",,$C$1)/1000000)} -> #VALUE! | E15: {=IF($B15="","",_xll.RDP.Data($B15,"TR.RevenueMean","Period=FY2 Frq=D SDate=1D Curn=#1",,$C$1)/1000000)} -> #VALUE! | F15: {=IF($B15="","",_xll.RDP.Data($B15,"TR.RevenueMean","Period=FY3 Frq=D SDate=1D Curn=#1",,$C$1)/1000000)} -> #VALUE! | G15: =IF($B15="","",_xll.RDP.Data($B15,"TR.EPSMean","Period=FY0 Frq=D SDate=1D Curn=#1",,$C$1)) -> Please sign in | H15: =IF($B15="","",_xll.RDP.Data($B15,"TR.EPSMean","Period=FY1 Frq=D SDate=1D Curn=#1",,$C$1)) -> Please sign in | I15: =IF($B15="","",_xll.RDP.Data($B15,"TR.EPSMean","Period=FY2 Frq=D SDate=1D Curn=#1",,$C$1)) -> Please sign in | J15: =IF($B15="","",_xll.RDP.Data($B15,"TR.EPSMean","Period=FY3 Frq=D SDate=1D Curn=#1",,$C$1)) -> Please sign in | K15: {=IF($B15="","",_xll.RDP.Data($B15,"TR.EBITMean","Period=FY0 Frq=D SDate=1D Curn=#1",,$C$1)/1000000)} -> #VALUE! | L15: {=IF($B15="","",_xll.RDP.Data($B15,"TR.EBITMean","Period=FY1 Frq=D SDate=1D Curn=#1",,$C$1)/1000000)} -> #VALUE! | M15: {=IF($B15="","",_xll.RDP.Data($B15,"TR.EBITMean","Period=FY2 Frq=D SDate=1D Curn=#1",,$C$1)/1000000)} -> #VALUE! | N15: {=IF($B15="","",_xll.RDP.Data($B15,"TR.EBITDAMean","Period=FY0 Frq=D SDate=1D Curn=#1",,$C$1)/1000000)} -> #VALUE! | O15: {=IF($B15="","",_xll.RDP.Data($B15,"TR.EBITDAMean","Period=FY1 Frq=D SDate=1D Curn=#1",,$C$1)/1000000)} -> #VALUE! | P15: {=IF($B15="","",_xll.RDP.Data($B15,"TR.EBITDAMean","Period=FY2 Frq=D SDate=1D Curn=#1",,$C$1)/1000000)} -> #VALUE! | Q15: {=IF($B15="","",_xll.RDP.Data($B15,"TR.LTGMean",,)/100)} -> #VALUE!
A16: =A7 -> Please sign in | B16: =IF(B7="","",B7) -> RTX | C16: {=IF($B16="","",_xll.RDP.Data($B16,"TR.Revenue","Curn=#1",,$C$1)/1000000)} -> #VALUE! | D16: {=IF($B16="","",_xll.RDP.Data($B16,"TR.RevenueMean","Period=FY1 Frq=D SDate=1D Curn=#1",,$C$1)/1000000)} -> #VALUE! | E16: {=IF($B16="","",_xll.RDP.Data($B16,"TR.RevenueMean","Period=FY2 Frq=D SDate=1D Curn=#1",,$C$1)/1000000)} -> #VALUE! | F16: {=IF($B16="","",_xll.RDP.Data($B16,"TR.RevenueMean","Period=FY3 Frq=D SDate=1D Curn=#1",,$C$1)/1000000)} -> #VALUE! | G16: =IF($B16="","",_xll.RDP.Data($B16,"TR.EPSMean","Period=FY0 Frq=D SDate=1D Curn=#1",,$C$1)) -> Please sign in | H16: =IF($B16="","",_xll.RDP.Data($B16,"TR.EPSMean","Period=FY1 Frq=D SDate=1D Curn=#1",,$C$1)) -> Please sign in | I16: =IF($B16="","",_xll.RDP.Data($B16,"TR.EPSMean","Period=FY2 Frq=D SDate=1D Curn=#1",,$C$1)) -> Please sign in | J16: =IF($B16="","",_xll.RDP.Data($B16,"TR.EPSMean","Period=FY3 Frq=D SDate=1D Curn=#1",,$C$1)) -> Please sign in | K16: {=IF($B16="","",_xll.RDP.Data($B16,"TR.EBITMean","Period=FY0 Frq=D SDate=1D Curn=#1",,$C$1)/1000000)} -> #VALUE! | L16: {=IF($B16="","",_xll.RDP.Data($B16,"TR.EBITMean","Period=FY1 Frq=D SDate=1D Curn=#1",,$C$1)/1000000)} -> #VALUE! | M16: {=IF($B16="","",_xll.RDP.Data($B16,"TR.EBITMean","Period=FY2 Frq=D SDate=1D Curn=#1",,$C$1)/1000000)} -> #VALUE! | N16: {=IF($B16="","",_xll.RDP.Data($B16,"TR.EBITDAMean","Period=FY0 Frq=D SDate=1D Curn=#1",,$C$1)/1000000)} -> #VALUE! | O16: {=IF($B16="","",_xll.RDP.Data($B16,"TR.EBITDAMean","Period=FY1 Frq=D SDate=1D Curn=#1",,$C$1)/1000000)} -> #VALUE! | P16: {=IF($B16="","",_xll.RDP.Data($B16,"TR.EBITDAMean","Period=FY2 Frq=D SDate=1D Curn=#1",,$C$1)/1000000)} -> #VALUE! | Q16: {=IF($B16="","",_xll.RDP.Data($B16,"TR.LTGMean",,)/100)} -> #VALUE!
A17: =A8 -> Please sign in | B17: =IF(B8="","",B8) -> NOC | C17: {=IF($B17="","",_xll.RDP.Data($B17,"TR.Revenue","Curn=#1",,$C$1)/1000000)} -> #VALUE! | D17: {=IF($B17="","",_xll.RDP.Data($B17,"TR.RevenueMean","Period=FY1 Frq=D SDate=1D Curn=#1",,$C$1)/1000000)} -> #VALUE! | E17: {=IF($B17="","",_xll.RDP.Data($B17,"TR.RevenueMean","Period=FY2 Frq=D SDate=1D Curn=#1",,$C$1)/1000000)} -> #VALUE! | F17: {=IF($B17="","",_xll.RDP.Data($B17,"TR.RevenueMean","Period=FY3 Frq=D SDate=1D Curn=#1",,$C$1)/1000000)} -> #VALUE! | G17: =IF($B17="","",_xll.RDP.Data($B17,"TR.EPSMean","Period=FY0 Frq=D SDate=1D Curn=#1",,$C$1)) -> Please sign in | H17: =IF($B17="","",_xll.RDP.Data($B17,"TR.EPSMean","Period=FY1 Frq=D SDate=1D Curn=#1",,$C$1)) -> Please sign in | I17: =IF($B17="","",_xll.RDP.Data($B17,"TR.EPSMean","Period=FY2 Frq=D SDate=1D Curn=#1",,$C$1)) -> Please sign in | J17: =IF($B17="","",_xll.RDP.Data($B17,"TR.EPSMean","Period=FY3 Frq=D SDate=1D Curn=#1",,$C$1)) -> Please sign in | K17: {=IF($B17="","",_xll.RDP.Data($B17,"TR.EBITMean","Period=FY0 Frq=D SDate=1D Curn=#1",,$C$1)/1000000)} -> #VALUE! | L17: {=IF($B17="","",_xll.RDP.Data($B17,"TR.EBITMean","Period=FY1 Frq=D SDate=1D Curn=#1",,$C$1)/1000000)} -> #VALUE! | M17: {=IF($B17="","",_xll.RDP.Data($B17,"TR.EBITMean","Period=FY2 Frq=D SDate=1D Curn=#1",,$C$1)/1000000)} -> #VALUE! | N17: {=IF($B17="","",_xll.RDP.Data($B17,"TR.EBITDAMean","Period=FY0 Frq=D SDate=1D Curn=#1",,$C$1)/1000000)} -> #VALUE! | O17: {=IF($B17="","",_xll.RDP.Data($B17,"TR.EBITDAMean","Period=FY1 Frq=D SDate=1D Curn=#1",,$C$1)/1000000)} -> #VALUE! | P17: {=IF($B17="","",_xll.RDP.Data($B17,"TR.EBITDAMean","Period=FY2 Frq=D SDate=1D Curn=#1",,$C$1)/1000000)} -> #VALUE! | Q17: {=IF($B17="","",_xll.RDP.Data($B17,"TR.LTGMean",,)/100)} -> #VALUE! | R17: Not available
A18: =A9 -> Please sign in | B18: =IF(B9="","",B9) -> LHX | C18: {=IF($B18="","",_xll.RDP.Data($B18,"TR.Revenue","Curn=#1",,$C$1)/1000000)} -> #VALUE! | D18: {=IF($B18="","",_xll.RDP.Data($B18,"TR.RevenueMean","Period=FY1 Frq=D SDate=1D Curn=#1",,$C$1)/1000000)} -> #VALUE! | E18: {=IF($B18="","",_xll.RDP.Data($B18,"TR.RevenueMean","Period=FY2 Frq=D SDate=1D Curn=#1",,$C$1)/1000000)} -> #VALUE! | F18: {=IF($B18="","",_xll.RDP.Data($B18,"TR.RevenueMean","Period=FY3 Frq=D SDate=1D Curn=#1",,$C$1)/1000000)} -> #VALUE! | G18: =IF($B18="","",_xll.RDP.Data($B18,"TR.EPSMean","Period=FY0 Frq=D SDate=1D Curn=#1",,$C$1)) -> Please sign in | H18: =IF($B18="","",_xll.RDP.Data($B18,"TR.EPSMean","Period=FY1 Frq=D SDate=1D Curn=#1",,$C$1)) -> Please sign in | I18: =IF($B18="","",_xll.RDP.Data($B18,"TR.EPSMean","Period=FY2 Frq=D SDate=1D Curn=#1",,$C$1)) -> Please sign in | J18: =IF($B18="","",_xll.RDP.Data($B18,"TR.EPSMean","Period=FY3 Frq=D SDate=1D Curn=#1",,$C$1)) -> Please sign in | K18: {=IF($B18="","",_xll.RDP.Data($B18,"TR.EBITMean","Period=FY0 Frq=D SDate=1D Curn=#1",,$C$1)/1000000)} -> #VALUE! | L18: {=IF($B18="","",_xll.RDP.Data($B18,"TR.EBITMean","Period=FY1 Frq=D SDate=1D Curn=#1",,$C$1)/1000000)} -> #VALUE! | M18: {=IF($B18="","",_xll.RDP.Data($B18,"TR.EBITMean","Period=FY2 Frq=D SDate=1D Curn=#1",,$C$1)/1000000)} -> #VALUE! | N18: {=IF($B18="","",_xll.RDP.Data($B18,"TR.EBITDAMean","Period=FY0 Frq=D SDate=1D Curn=#1",,$C$1)/1000000)} -> #VALUE! | O18: {=IF($B18="","",_xll.RDP.Data($B18,"TR.EBITDAMean","Period=FY1 Frq=D SDate=1D Curn=#1",,$C$1)/1000000)} -> #VALUE! | P18: {=IF($B18="","",_xll.RDP.Data($B18,"TR.EBITDAMean","Period=FY2 Frq=D SDate=1D Curn=#1",,$C$1)/1000000)} -> #VALUE! | Q18: {=IF($B18="","",_xll.RDP.Data($B18,"TR.LTGMean",,)/100)} -> #VALUE! | R18: Not available
A19: =A10 -> Please sign in | B19: =IF(B10="","",B10) -> GD | C19: {=IF($B19="","",_xll.RDP.Data($B19,"TR.Revenue","Curn=#1",,$C$1)/1000000)} -> #VALUE! | D19: {=IF($B19="","",_xll.RDP.Data($B19,"TR.RevenueMean","Period=FY1 Frq=D SDate=1D Curn=#1",,$C$1)/1000000)} -> #VALUE! | E19: {=IF($B19="","",_xll.RDP.Data($B19,"TR.RevenueMean","Period=FY2 Frq=D SDate=1D Curn=#1",,$C$1)/1000000)} -> #VALUE! | F19: {=IF($B19="","",_xll.RDP.Data($B19,"TR.RevenueMean","Period=FY3 Frq=D SDate=1D Curn=#1",,$C$1)/1000000)} -> #VALUE! | G19: =IF($B19="","",_xll.RDP.Data($B19,"TR.EPSMean","Period=FY0 Frq=D SDate=1D Curn=#1",,$C$1)) -> Please sign in | H19: =IF($B19="","",_xll.RDP.Data($B19,"TR.EPSMean","Period=FY1 Frq=D SDate=1D Curn=#1",,$C$1)) -> Please sign in | I19: =IF($B19="","",_xll.RDP.Data($B19,"TR.EPSMean","Period=FY2 Frq=D SDate=1D Curn=#1",,$C$1)) -> Please sign in | J19: =IF($B19="","",_xll.RDP.Data($B19,"TR.EPSMean","Period=FY3 Frq=D SDate=1D Curn=#1",,$C$1)) -> Please sign in | K19: {=IF($B19="","",_xll.RDP.Data($B19,"TR.EBITMean","Period=FY0 Frq=D SDate=1D Curn=#1",,$C$1)/1000000)} -> #VALUE! | L19: {=IF($B19="","",_xll.RDP.Data($B19,"TR.EBITMean","Period=FY1 Frq=D SDate=1D Curn=#1",,$C$1)/1000000)} -> #VALUE! | M19: {=IF($B19="","",_xll.RDP.Data($B19,"TR.EBITMean","Period=FY2 Frq=D SDate=1D Curn=#1",,$C$1)/1000000)} -> #VALUE! | N19: {=IF($B19="","",_xll.RDP.Data($B19,"TR.EBITDAMean","Period=FY0 Frq=D SDate=1D Curn=#1",,$C$1)/1000000)} -> #VALUE! | O19: {=IF($B19="","",_xll.RDP.Data($B19,"TR.EBITDAMean","Period=FY1 Frq=D SDate=1D Curn=#1",,$C$1)/1000000)} -> #VALUE! | P19: {=IF($B19="","",_xll.RDP.Data($B19,"TR.EBITDAMean","Period=FY2 Frq=D SDate=1D Curn=#1",,$C$1)/1000000)} -> #VALUE! | Q19: {=IF($B19="","",_xll.RDP.Data($B19,"TR.LTGMean",,)/100)} -> #VALUE!
A21: VALUATION MULTIPLES
C22: Recent | D22: Price / | E22: Price/Sales | H22: P/E | K22: PEG | N22: EV/EBITDA
A23: Company Name | B23: Ticker | C23: Price | D23: Book | E23: FYR1 | F23: FYR2 | G23: FYR3 | H23: FYR1 | I23: FYR2 | J23: FYR3 | K23: FYR1 | L23: FYR2 | M23: FYR3 | N23: Last FY | O23: FYR1 | P23: FYR2
A24: =A6 -> Please sign in | B24: =IF(B6="","",B6) -> LMT | C24: =IF(C6="","",C6) -> Please sign in | D24: =IF(OR(B24="",ISNUMBER(F6)=FALSE,ISNUMBER(J6)=FALSE),"",F6/J6) | E24: =IF(OR($B24="",ISNUMBER($F6)=FALSE,ISNUMBER(D15)=FALSE),"",$F6/D15) | F24: =IF(OR($B24="",ISNUMBER($F6)=FALSE,ISNUMBER(E15)=FALSE),"",$F6/E15) | G24: =IF(OR($B24="",ISNUMBER($F6)=FALSE,ISNUMBER(F15)=FALSE),"",$F6/F15) | H24: =IF(OR($B24="",ISNA(H15)=TRUE),"",$C6/H15) -> #VALUE! | I24: =IF(OR($B24="",ISNA(I15)=TRUE),"",$C6/I15) -> #VALUE! | J24: =IF(OR($B24="",ISNA(J15)=TRUE),"",$C6/J15) -> #VALUE! | K24: =IF(OR($B24="",H24="",ISNA($Q15)=TRUE),"",H24/$Q15/100) -> #VALUE! | L24: =IF(OR($B24="",I24="",ISNA($Q15)=TRUE),"",I24/$Q15/100) -> #VALUE! | M24: =IF(OR($B24="",J24="",ISNA($Q15)=TRUE),"",J24/$Q15/100) -> #VALUE! | N24: =IF(OR($B24="",ISNA($I6)=TRUE,ISNA(N15)=TRUE),"",$I6/N15) -> #VALUE! | O24: =IF(OR($B24="",ISNA($I6)=TRUE,ISNA(O15)=TRUE),"",$I6/O15) -> #VALUE! | P24: =IF(OR($B24="",ISNA($I6)=TRUE,ISNA(P15)=TRUE),"",$I6/P15) -> #VALUE!
A25: =A7 -> Please sign in | B25: =IF(B7="","",B7) -> RTX | C25: =IF(C7="","",C7) -> Please sign in | D25: =IF(OR(B25="",ISNUMBER(F7)=FALSE,ISNUMBER(J7)=FALSE),"",F7/J7) | E25: =IF(OR($B25="",ISNUMBER($F7)=FALSE,ISNUMBER(D16)=FALSE),"",$F7/D16) | F25: =IF(OR($B25="",ISNUMBER($F7)=FALSE,ISNUMBER(E16)=FALSE),"",$F7/E16) | G25: =IF(OR($B25="",ISNUMBER($F7)=FALSE,ISNUMBER(F16)=FALSE),"",$F7/F16) | H25: =IF(OR($B25="",ISNA(H16)=TRUE),"",$C7/H16) -> #VALUE! | I25: =IF(OR($B25="",ISNA(I16)=TRUE),"",$C7/I16) -> #VALUE! | J25: =IF(OR($B25="",ISNA(J16)=TRUE),"",$C7/J16) -> #VALUE! | K25: =IF(OR($B25="",H25="",ISNA($Q16)=TRUE),"",H25/$Q16/100) -> #VALUE! | L25: =IF(OR($B25="",I25="",ISNA($Q16)=TRUE),"",I25/$Q16/100) -> #VALUE! | M25: =IF(OR($B25="",J25="",ISNA($Q16)=TRUE),"",J25/$Q16/100) -> #VALUE! | N25: =IF(OR($B25="",ISNA($I7)=TRUE,ISNA(N16)=TRUE),"",$I7/N16) -> #VALUE! | O25: =IF(OR($B25="",ISNA($I7)=TRUE,ISNA(O16)=TRUE),"",$I7/O16) -> #VALUE! | P25: =IF(OR($B25="",ISNA($I7)=TRUE,ISNA(P16)=TRUE),"",$I7/P16) -> #VALUE!
A26: =A8 -> Please sign in | B26: =IF(B8="","",B8) -> NOC | C26: =IF(C8="","",C8) -> Please sign in | D26: =IF(OR(B26="",ISNUMBER(F8)=FALSE,ISNUMBER(J8)=FALSE),"",F8/J8) | E26: =IF(OR($B26="",ISNUMBER($F8)=FALSE,ISNUMBER(D17)=FALSE),"",$F8/D17) | F26: =IF(OR($B26="",ISNUMBER($F8)=FALSE,ISNUMBER(E17)=FALSE),"",$F8/E17) | G26: =IF(OR($B26="",ISNUMBER($F8)=FALSE,ISNUMBER(F17)=FALSE),"",$F8/F17) | H26: =IF(OR($B26="",ISNA(H17)=TRUE),"",$C8/H17) -> #VALUE! | I26: =IF(OR($B26="",ISNA(I17)=TRUE),"",$C8/I17) -> #VALUE! | J26: =IF(OR($B26="",ISNA(J17)=TRUE),"",$C8/J17) -> #VALUE! | K26: =IF(OR($B26="",H26="",ISNA($Q17)=TRUE),"",H26/$Q17/100) -> #VALUE! | L26: =IF(OR($B26="",I26="",ISNA($Q17)=TRUE),"",I26/$Q17/100) -> #VALUE! | M26: =IF(OR($B26="",J26="",ISNA($Q17)=TRUE),"",J26/$Q17/100) -> #VALUE! | N26: =IF(OR($B26="",ISNA($I8)=TRUE,ISNA(N17)=TRUE),"",$I8/N17) -> #VALUE! | O26: =IF(OR($B26="",ISNA($I8)=TRUE,ISNA(O17)=TRUE),"",$I8/O17) -> #VALUE! | P26: =IF(OR($B26="",ISNA($I8)=TRUE,ISNA(P17)=TRUE),"",$I8/P17) -> #VALUE!
A27: =A9 -> Please sign in | B27: =IF(B9="","",B9) -> LHX | C27: =IF(C9="","",C9) -> Please sign in | D27: =IF(OR(B27="",ISNUMBER(F9)=FALSE,ISNUMBER(J9)=FALSE),"",F9/J9) | E27: =IF(OR($B27="",ISNUMBER($F9)=FALSE,ISNUMBER(D18)=FALSE),"",$F9/D18) | F27: =IF(OR($B27="",ISNUMBER($F9)=FALSE,ISNUMBER(E18)=FALSE),"",$F9/E18) | G27: =IF(OR($B27="",ISNUMBER($F9)=FALSE,ISNUMBER(F18)=FALSE),"",$F9/F18) | H27: =IF(OR($B27="",ISNA(H18)=TRUE),"",$C9/H18) -> #VALUE! | I27: =IF(OR($B27="",ISNA(I18)=TRUE),"",$C9/I18) -> #VALUE! | J27: =IF(OR($B27="",ISNA(J18)=TRUE),"",$C9/J18) -> #VALUE! | K27: =IF(OR($B27="",H27="",ISNA($Q18)=TRUE),"",H27/$Q18/100) -> #VALUE! | L27: =IF(OR($B27="",I27="",ISNA($Q18)=TRUE),"",I27/$Q18/100) -> #VALUE! | M27: =IF(OR($B27="",J27="",ISNA($Q18)=TRUE),"",J27/$Q18/100) -> #VALUE! | N27: =IF(OR($B27="",ISNA($I9)=TRUE,ISNA(N18)=TRUE),"",$I9/N18) -> #VALUE! | O27: =IF(OR($B27="",ISNA($I9)=TRUE,ISNA(O18)=TRUE),"",$I9/O18) -> #VALUE! | P27: =IF(OR($B27="",ISNA($I9)=TRUE,ISNA(P18)=TRUE),"",$I9/P18) -> #VALUE!
A28: =A10 -> Please sign in | B28: =IF(B10="","",B10) -> GD | C28: =IF(C10="","",C10) -> Please sign in | D28: =IF(OR(B28="",ISNUMBER(F10)=FALSE,ISNUMBER(J10)=FALSE),"",F10/J10) | E28: =IF(OR($B28="",ISNUMBER($F10)=FALSE,ISNUMBER(D19)=FALSE),"",$F10/D19) | F28: =IF(OR($B28="",ISNUMBER($F10)=FALSE,ISNUMBER(E19)=FALSE),"",$F10/E19) | G28: =IF(OR($B28="",ISNUMBER($F10)=FALSE,ISNUMBER(F19)=FALSE),"",$F10/F19) | H28: =IF(OR($B28="",ISNA(H19)=TRUE),"",$C10/H19) -> #VALUE! | I28: =IF(OR($B28="",ISNA(I19)=TRUE),"",$C10/I19) -> #VALUE! | J28: =IF(OR($B28="",ISNA(J19)=TRUE),"",$C10/J19) -> #VALUE! | K28: =IF(OR($B28="",H28="",ISNA($Q19)=TRUE),"",H28/$Q19/100) -> #VALUE! | L28: =IF(OR($B28="",I28="",ISNA($Q19)=TRUE),"",I28/$Q19/100) -> #VALUE! | M28: =IF(OR($B28="",J28="",ISNA($Q19)=TRUE),"",J28/$Q19/100) -> #VALUE! | N28: =IF(OR($B28="",ISNA($I10)=TRUE,ISNA(N19)=TRUE),"",$I10/N19) -> #VALUE! | O28: =IF(OR($B28="",ISNA($I10)=TRUE,ISNA(O19)=TRUE),"",$I10/O19) -> #VALUE! | P28: =IF(OR($B28="",ISNA($I10)=TRUE,ISNA(P19)=TRUE),"",$I10/P19) -> #VALUE!
C30: Average | D30: =AVERAGE(D24:D27) -> #DIV/0! | E30: =AVERAGE(E24:E27) -> #DIV/0! | F30: =AVERAGE(F24:F27) -> #DIV/0! | G30: =AVERAGE(G24:G27) -> #DIV/0! | H30: =AVERAGE(H24:H27) -> #VALUE! | I30: =AVERAGE(I24:I27) -> #VALUE! | J30: =AVERAGE(J24:J27) -> #VALUE! | K30: =AVERAGE(K24,K26:K26) -> #VALUE! | L30: =AVERAGE(L24,L26:L26) -> #VALUE! | M30: =AVERAGE(M24,M26:M26) -> #VALUE! | N30: =AVERAGE(N24:N27) -> #VALUE! | O30: =AVERAGE(O24:O27) -> #VALUE! | P30: =AVERAGE(P24:P27) -> #VALUE!
C31: Median | D31: =MEDIAN(D24:D27) -> #NUM! | E31: =MEDIAN(E24:E27) -> #NUM! | F31: =MEDIAN(F24:F27) -> #NUM! | G31: =MEDIAN(G24:G27) -> #NUM! | H31: =MEDIAN(H24:H27) -> #VALUE! | I31: =MEDIAN(I24:I27) -> #VALUE! | J31: =MEDIAN(J24:J27) -> #VALUE! | K31: =MEDIAN(K24,K26:K26) -> #VALUE! | L31: =MEDIAN(L24,L26:L26) -> #VALUE! | M31: =MEDIAN(M24,M26:M26) -> #VALUE! | N31: =MEDIAN(N24:N27) -> #VALUE! | O31: =MEDIAN(O24:O27) -> #VALUE! | P31: =MEDIAN(P24:P27) -> #VALUE!
C33: Average | D33: =D30*$J$10/$E$10 -> #DIV/0! | E33: =(E30*D$19)/$E$10 -> #DIV/0! | F33: =(F30*E$19)/$E$10 -> #DIV/0! | G33: =(G30*F$19)/$E$10 -> #DIV/0! | H33: =H30*H$19 -> #VALUE! | I33: =I30*I$19 -> #VALUE! | J33: =J30*J$19 -> #VALUE! | K33: =K30*H$19*$Q$19*100 -> #VALUE! | L33: =L30*I$19*$Q$19*100 -> #VALUE! | M33: =M30*J$19*$Q$19*100 -> #VALUE! | N33: =(N30*N$19-($G$10-$H$10))/$E$10 -> #VALUE! | O33: =(O30*O$19-($G$10-$H$10))/$E$10 -> #VALUE! | P33: =(P30*P$19-($G$10-$H$10))/$E$10 -> #VALUE!
C34: Median | D34: =D31*$J$10/$E$10 -> #NUM! | E34: =(E31*D$19)/$E$10 -> #NUM! | F34: =(F31*E$19)/$E$10 -> #NUM! | G34: =(G31*F$19)/$E$10 -> #NUM! | H34: =H31*H$19 -> #VALUE! | I34: =I31*I$19 -> #VALUE! | J34: =J31*J$19 -> #VALUE! | K34: =K31*H$19*$Q$19*100 -> #VALUE! | L34: =L31*I$19*$Q$19*100 -> #VALUE! | M34: =M31*J$19*$Q$19*100 -> #VALUE! | N34: =(N31*N$19-($G$10-$H$10))/$E$10 -> #VALUE! | O34: =(O31*O$19-($G$10-$H$10))/$E$10 -> #VALUE! | P34: =(P31*P$19-($G$10-$H$10))/$E$10 -> #VALUE!
D35: ws.OperatingProfitMargin[ws.cpa] | H35: ws.AssetTurnover[ws.cpa] | I35: ws.InventoryTurnover[ws.cpa] | J35: ws.ReceivablesTurnover[ws.cpa] | K35: ws.TotalDebtPctCommonEquity[ws.cpa] | L35: ws.LTDebtPctCommonEquity[ws.cpa] | M35: ws.LTDebtPctTotalCapital[ws.cpa] | N35: ws.QuickRatio[ws.cpa] | O35: ws.CurrentRatio[ws.cpa]
A36: RATIO ANALYSIS
C37: Gross | D37: Operating | E37: Net | H37: Asset | I37: Inventory | J37: Receivables | M37: Quick | N37: Current | O37: Interest
A38: Company Name | B38: Ticker | C38: Margin | D38: Margin | E38: Margin | F38: ROA | G38: ROE | H38: Turnvover | I38: Turnvover | J38: Turnvover | K38: Debt/E | L38: LTD/TC | M38: Ratio | N38: Ratio | O38: Coverage
A39: =A6 -> Please sign in | B39: =IF(B15="","",B24) -> LMT | C39: {=IF($B39="","",_xll.RDP.Data($B39,"TR.GrossMargin")/100)} -> #VALUE! | D39: {=IF($B39="","",_xll.RDP.Data($B39,"TR.OperatingMarginPercent")/100)} -> #VALUE! | E39: {=IF($B39="","",_xll.RDP.Data($B39,"TR.NetProfitMargin")/100)} -> #VALUE! | F39: {=IF($B39="","",_xll.RDP.Data($B39,"TR.ROAActValue")/100)} -> #VALUE! | G39: {=IF($B39="","",_xll.RDP.Data($B39,"TR.ROEActValue")/100)} -> #VALUE! | H39: =IF($B39="","",_xll.RDP.Data($B39,"TR.AssetTurnover")) -> Please sign in | I39: =IF($B39="","",_xll.RDP.Data($B39,"TR.InventoryTurnover")) -> Please sign in | J39: {=IF($B39="","",_xll.RDP.Data($B39,"TR.Revenue")/_xll.RDP.Data($B39,"TR.TotalReceivablesNet"))} -> #VALUE! | K39: =IF($B39="","",_xll.RDP.Data($B39,"TR.TtlDebtToTtlEquityPct")) -> Please sign in | L39: =IF($B39="","",_xll.RDP.Data($B39,"TR.LTDebtToTtlCapitalPct")) -> Please sign in | M39: =IF($B39="","",_xll.RDP.Data($B39,"TR.QuickRatio")) -> Please sign in | N39: =IF($B39="","",_xll.RDP.Data($B39,"TR.CurrentRatio")) -> Please sign in | O39: {=IF($B39="","",_xll.RDP.Data($B39,"TR.EBITDA")/_xll.RDP.Data($B39,"TR.InterestExpense"))} -> #VALUE!
A40: =A7 -> Please sign in | B40: =IF(B16="","",B25) -> RTX | C40: {=IF($B40="","",_xll.RDP.Data($B40,"TR.GrossMargin")/100)} -> #VALUE! | D40: {=IF($B40="","",_xll.RDP.Data($B40,"TR.OperatingMarginPercent")/100)} -> #VALUE! | E40: {=IF($B40="","",_xll.RDP.Data($B40,"TR.NetProfitMargin")/100)} -> #VALUE! | F40: {=IF($B40="","",_xll.RDP.Data($B40,"TR.ROAActValue")/100)} -> #VALUE! | G40: {=IF($B40="","",_xll.RDP.Data($B40,"TR.ROEActValue")/100)} -> #VALUE! | H40: =IF($B40="","",_xll.RDP.Data($B40,"TR.AssetTurnover")) -> Please sign in | I40: =IF($B40="","",_xll.RDP.Data($B40,"TR.InventoryTurnover")) -> Please sign in | J40: {=IF($B40="","",_xll.RDP.Data($B40,"TR.Revenue")/_xll.RDP.Data($B40,"TR.TotalReceivablesNet"))} -> #VALUE! | K40: =IF($B40="","",_xll.RDP.Data($B40,"TR.TtlDebtToTtlEquityPct")) -> Please sign in | L40: =IF($B40="","",_xll.RDP.Data($B40,"TR.LTDebtToTtlCapitalPct")) -> Please sign in | M40: =IF($B40="","",_xll.RDP.Data($B40,"TR.QuickRatio")) -> Please sign in | N40: =IF($B40="","",_xll.RDP.Data($B40,"TR.CurrentRatio")) -> Please sign in | O40: {=IF($B40="","",_xll.RDP.Data($B40,"TR.EBITDA")/_xll.RDP.Data($B40,"TR.InterestExpense"))} -> #VALUE!
A41: =A8 -> Please sign in | B41: =IF(B17="","",B26) -> NOC | C41: {=IF($B41="","",_xll.RDP.Data($B41,"TR.GrossMargin")/100)} -> #VALUE! | D41: {=IF($B41="","",_xll.RDP.Data($B41,"TR.OperatingMarginPercent")/100)} -> #VALUE! | E41: {=IF($B41="","",_xll.RDP.Data($B41,"TR.NetProfitMargin")/100)} -> #VALUE! | F41: {=IF($B41="","",_xll.RDP.Data($B41,"TR.ROAActValue")/100)} -> #VALUE! | G41: {=IF($B41="","",_xll.RDP.Data($B41,"TR.ROEActValue")/100)} -> #VALUE! | H41: =IF($B41="","",_xll.RDP.Data($B41,"TR.AssetTurnover")) -> Please sign in | I41: =IF($B41="","",_xll.RDP.Data($B41,"TR.InventoryTurnover")) -> Please sign in | J41: {=IF($B41="","",_xll.RDP.Data($B41,"TR.Revenue")/_xll.RDP.Data($B41,"TR.TotalReceivablesNet"))} -> #VALUE! | K41: =IF($B41="","",_xll.RDP.Data($B41,"TR.TtlDebtToTtlEquityPct")) -> Please sign in | L41: =IF($B41="","",_xll.RDP.Data($B41,"TR.LTDebtToTtlCapitalPct")) -> Please sign in | M41: =IF($B41="","",_xll.RDP.Data($B41,"TR.QuickRatio")) -> Please sign in | N41: =IF($B41="","",_xll.RDP.Data($B41,"TR.CurrentRatio")) -> Please sign in | O41: {=IF($B41="","",_xll.RDP.Data($B41,"TR.EBITDA")/_xll.RDP.Data($B41,"TR.InterestExpense"))} -> #VALUE!
A42: =A9 -> Please sign in | B42: =IF(B18="","",B27) -> LHX | C42: {=IF($B42="","",_xll.RDP.Data($B42,"TR.GrossMargin")/100)} -> #VALUE! | D42: {=IF($B42="","",_xll.RDP.Data($B42,"TR.OperatingMarginPercent")/100)} -> #VALUE! | E42: {=IF($B42="","",_xll.RDP.Data($B42,"TR.NetProfitMargin")/100)} -> #VALUE! | F42: {=IF($B42="","",_xll.RDP.Data($B42,"TR.ROAActValue")/100)} -> #VALUE! | G42: {=IF($B42="","",_xll.RDP.Data($B42,"TR.ROEActValue")/100)} -> #VALUE! | H42: =IF($B42="","",_xll.RDP.Data($B42,"TR.AssetTurnover")) -> Please sign in | I42: =IF($B42="","",_xll.RDP.Data($B42,"TR.InventoryTurnover")) -> Please sign in | J42: {=IF($B42="","",_xll.RDP.Data($B42,"TR.Revenue")/_xll.RDP.Data($B42,"TR.TotalReceivablesNet"))} -> #VALUE! | K42: =IF($B42="","",_xll.RDP.Data($B42,"TR.TtlDebtToTtlEquityPct")) -> Please sign in | L42: =IF($B42="","",_xll.RDP.Data($B42,"TR.LTDebtToTtlCapitalPct")) -> Please sign in | M42: =IF($B42="","",_xll.RDP.Data($B42,"TR.QuickRatio")) -> Please sign in | N42: =IF($B42="","",_xll.RDP.Data($B42,"TR.CurrentRatio")) -> Please sign in | O42: {=IF($B42="","",_xll.RDP.Data($B42,"TR.EBITDA")/_xll.RDP.Data($B42,"TR.InterestExpense"))} -> #VALUE!
A43: =A10 -> Please sign in | B43: =IF(B19="","",B28) -> GD | C43: {=IF($B43="","",_xll.RDP.Data($B43,"TR.GrossMargin")/100)} -> #VALUE! | D43: {=IF($B43="","",_xll.RDP.Data($B43,"TR.OperatingMarginPercent")/100)} -> #VALUE! | E43: {=IF($B43="","",_xll.RDP.Data($B43,"TR.NetProfitMargin")/100)} -> #VALUE! | F43: {=IF($B43="","",_xll.RDP.Data($B43,"TR.ROAActValue")/100)} -> #VALUE! | G43: {=IF($B43="","",_xll.RDP.Data($B43,"TR.ROEActValue")/100)} -> #VALUE! | H43: =IF($B43="","",_xll.RDP.Data($B43,"TR.AssetTurnover")) -> Please sign in | I43: =IF($B43="","",_xll.RDP.Data($B43,"TR.InventoryTurnover")) -> Please sign in | J43: {=IF($B43="","",_xll.RDP.Data($B43,"TR.Revenue")/_xll.RDP.Data($B43,"TR.TotalReceivablesNet"))} -> #VALUE! | K43: =IF($B43="","",_xll.RDP.Data($B43,"TR.TtlDebtToTtlEquityPct")) -> Please sign in | L43: =IF($B43="","",_xll.RDP.Data($B43,"TR.LTDebtToTtlCapitalPct")) -> Please sign in | M43: =IF($B43="","",_xll.RDP.Data($B43,"TR.QuickRatio")) -> Please sign in | N43: =IF($B43="","",_xll.RDP.Data($B43,"TR.CurrentRatio")) -> Please sign in | O43: {=IF($B43="","",_xll.RDP.Data($B43,"TR.EBITDA")/_xll.RDP.Data($B43,"TR.InterestExpense"))} -> #VALUE!

Sheet Comps no formuals
C1: USD
A2: COMPARABLE COMPANY ANALYSIS
A3: COMPANY DATA
A4: (in millions) | C4: Recent | D4: 52 week | E4: Shares | F4: Market | G4: Total | I4: Enterprise | J4: Book | L4: WS 12-mo
A5: Company Name | B5: Ticker | C5: Price | D5: High | E5: Out | F5: Cap | G5: Debt | H5: Cash | I5: Value | J5: Value | K5: Beta | L5: Price Target
A6: Lockheed Martin Corp | B6: LMT | C6: 637.51 | D6: 692 | E6: 230.08024 | F6: 146678.45 | G6: 21700 | H6: 4121 | I6: 164257.45 | J6: 6721 | K6: 0.21173258 | L6: 663.69111
A7: RTX Corp | B7: RTX | C7: 200.73 | D7: 214.5 | E7: 1345.9742 | F7: 270177.41 | G7: 37904 | H7: 7435 | I7: 300646.41 | J7: 65245 | K7: 0.40948776 | L7: 208.60238
A8: Northrop Grumman Corp | B8: NOC | C8: 714.15 | D8: 774 | E8: 141.92162 | F8: 101353.33 | G8: 15696 | H8: 4403 | I8: 112646.33 | J8: 16674 | K8: 0.02049081 | L8: 729.99421
A9: L3Harris Technologies Inc | B9: LHX | C9: 363.7 | D9: 379.23 | E9: 186.77626 | F9: 67930.527 | G9: 11116 | H9: 0 | I9: 79046.527 | J9: 19635 | K9: 0.59925533 | L9: 386.20875
A10: General Dynamics Corp | B10: GD | C10: 349.63 | D10: 369.7 | E10: 270.38976 | F10: 94536.371 | G10: 8405 | H10: 2333 | I10: 100608.37 | J10: 25622 | K10: 0.37863835 | L10: 392.40947
A12: I/B/E/S ESTIMATES
C13: SALES | G13: EPS | K13: EBIT | N13: EBITDA | Q13: EPS 5-yr
A14: Company Name | B14: Ticker | C14: Last FY | D14: FYR1 | E14: FYR2 | F14: FYR3 | G14: Last FY | H14: FYR1 | I14: FYR2 | J14: FYR3 | K14: Last FY | L14: FYR1 | M14: FYR2 | N14: Last FY | O14: FYR1 | P14: FYR2 | Q14: Growth %
A15: Lockheed Martin Corp | B15: LMT | C15: 75048 | D15: 79124.195 | E15: 82983.752 | F15: 86526.353 | G15: 21.57996 | H15: 29.91248 | I15: 31.95077 | J15: 33.89786 | K15: 7634.843 | L15: 9595.1872 | M15: 10021.28 | N15: 9249.1691 | O15: 11291.974 | P15: 11741.164 | Q15: 0.1626
A16: RTX Corp | B16: RTX | C16: 88603 | D16: 93351.339 | E16: 99562.492 | F16: 105811.32 | G16: 6.20296 | H16: 6.83081 | I16: 7.5103 | J16: 8.21236 | K16: 11066.934 | L16: 12062.318 | M16: 13313.65 | N16: 14385.988 | O16: 15787.91 | P16: 17174.389 | Q16: 0.1013
A17: Northrop Grumman Corp | B17: NOC | C17: 41954 | D17: 43865.942 | E17: 46517.821 | F17: 48975.006 | G17: 26.06478 | H17: 27.98568 | I17: 29.93867 | J17: 32.34214 | K17: 4483.0079 | L17: 4650.692 | M17: 5025.0594 | N17: 5942.67 | O17: 6229.2801 | P17: 6654.571 | Q17: 0.072 | R17: Not available
A18: L3Harris Technologies Inc | B18: LHX | C18: 21865 | D18: 23415.826 | E18: 25159.732 | F18: 27018.979 | G18: 10.64989 | H18: 11.59672 | I18: 13.45239 | J18: 15.48385 | K18: 3446.7564 | L18: 3687.5607 | M18: 4002.9721 | N18: 3880.1633 | O18: 4375.2343 | P18: 4705.4173 | Q18: 0.143 | R18: Not available
A19: General Dynamics Corp | B19: GD | C19: 52550 | D19: 54686.56 | E19: 57124.894 | F19: 59502.514 | G19: 15.39182 | H19: 16.30981 | I19: 18.01535 | J19: 19.5195 | K19: 5339.416 | L19: 5674.4095 | M19: 6190.125 | N19: 6267.7472 | O19: 6656.0717 | P19: 7224.9028 | Q19: 0.105
A21: VALUATION MULTIPLES
C22: Recent | D22: Price / | E22: Price/Sales | H22: P/E | K22: PEG | N22: EV/EBITDA
A23: Company Name | B23: Ticker | C23: Price | D23: Book | E23: FYR1 | F23: FYR2 | G23: FYR3 | H23: FYR1 | I23: FYR2 | J23: FYR3 | K23: FYR1 | L23: FYR2 | M23: FYR3 | N23: Last FY | O23: FYR1 | P23: FYR2
A24: Lockheed Martin Corp | B24: LMT | C24: 637.51 | D24: 21.823903 | E24: 1.853775 | F24: 1.7675563 | G24: 1.6951882 | H24: 21.312509 | I24: 19.952884 | J24: 18.806792 | K24: 1.3107324 | L24: 1.2271146 | M24: 1.1566293 | N24: 17.759158 | O24: 14.546389 | P24: 13.989878
A25: RTX Corp | B25: RTX | C25: 200.73 | D25: 4.1409672 | E25: 2.8941996 | F25: 2.7136465 | G25: 2.5533884 | H25: 29.385973 | I25: 26.727295 | J25: 24.442426 | K25: 2.9008858 | L25: 2.6384299 | M25: 2.4128752 | N25: 20.898559 | O25: 19.042825 | P25: 17.505508
A26: Northrop Grumman Corp | B26: NOC | C26: 714.15 | D26: 6.078525 | E26: 2.3105243 | F26: 2.1788064 | G26: 2.0694908 | H26: 25.518408 | I26: 23.853765 | J26: 22.081099 | K26: 3.5442233 | L26: 3.3130229 | M26: 3.0668193 | N26: 18.955507 | O26: 18.083362 | P26: 16.927661
A27: L3Harris Technologies Inc | B27: LHX | C27: 363.7 | D27: 3.4596652 | E27: 2.9010519 | F27: 2.6999702 | G27: 2.5141782 | H27: 31.362316 | I27: 27.036088 | J27: 23.48899 | K27: 2.193169 | L27: 1.8906355 | M27: 1.6425867 | N27: 20.371959 | O27: 18.06681 | P27: 16.799047
A28: General Dynamics Corp | B28: GD | C28: 349.63 | D28: 3.6896562 | E28: 1.7286948 | F28: 1.6549067 | G28: 1.5887795 | H28: 21.436792 | I28: 19.407339 | J28: 17.911832 | K28: 2.0415992 | L28: 1.848318 | M28: 1.7058887 | N28: 16.05176 | O28: 15.115278 | P28: 13.925221
C30: Average | D30: 8.8757652 | E30: 2.4898877 | F30: 2.3399948 | G30: 2.2080614 | H30: 26.894802 | I30: 24.392508 | J30: 22.204827 | K30: 2.4274779 | L30: 2.2700688 | M30: 2.1117243 | N30: 19.496296 | O30: 17.434847 | P30: 16.305523
C31: Median | D31: 5.1097461 | E31: 2.6023619 | F31: 2.4393883 | G31: 2.2918345 | H31: 27.452191 | I31: 25.29053 | J31: 22.785045 | K31: 2.4274779 | L31: 2.2700688 | M31: 2.1117243 | N31: 19.663733 | O31: 18.075086 | P31: 16.863354
C33: Average | D33: 841.06312 | E33: 503.58192 | F33: 494.36768 | G33: 485.91043 | H33: 438.6491 | I33: 439.43957 | J33: 433.42712 | K33: 415.71288 | L33: 429.40888 | M33: 432.80793 | N33: 429.47578 | O33: 406.72986 | P33: 413.23245
C34: Median | D34: 484.19702 | E34: 526.32993 | F34: 515.3664 | G34: 504.34571 | H34: 447.74001 | I34: 455.61775 | J34: 444.75268 | K34: 415.71288 | L34: 429.40888 | M34: 432.80793 | N34: 433.35705 | O34: 422.49036 | P34: 428.13787
D35: ws.OperatingProfitMargin[ws.cpa] | H35: ws.AssetTurnover[ws.cpa] | I35: ws.InventoryTurnover[ws.cpa] | J35: ws.ReceivablesTurnover[ws.cpa] | K35: ws.TotalDebtPctCommonEquity[ws.cpa] | L35: ws.LTDebtPctCommonEquity[ws.cpa] | M35: ws.LTDebtPctTotalCapital[ws.cpa] | N35: ws.QuickRatio[ws.cpa] | O35: ws.CurrentRatio[ws.cpa]
A36: RATIO ANALYSIS
C37: Gross | D37: Operating | E37: Net | H37: Asset | I37: Inventory | J37: Receivables | M37: Quick | N37: Current | O37: Interest
A38: Company Name | B38: Ticker | C38: Margin | D38: Margin | E38: Margin | F38: ROA | G38: ROE | H38: Turnvover | I38: Turnvover | J38: Turnvover | K38: Debt/E | L38: LTD/TC | M38: Ratio | N38: Ratio | O38: Coverage
A39: Lockheed Martin Corp | B39: LMT | C39: 0.1024011 | D39: 0.1030141 | E39: 0.0668505 | F39: 0.09339 | G39: 0.8264 | H39: 1.3000165 | I39: 19.252072 | J39: 4.4401846 | K39: 322.86862 | L39: 72.242356 | M39: 0.93585 | N39: 1.08687 | O39: 10.224508
A40: RTX Corp | B40: RTX | C40: 0.200772 | D40: 0.1049626 | E40: 0.0759794 | F40: 0.0511 | G40: 0.13609 | H40: 0.53065221 | I40: 5.4197153 | J40: 2.7868713 | K40: 58.094873 | L40: 32.642181 | M40: 0.79899 | N40: 1.02633 | O40: 8.546594
A41: Northrop Grumman Corp | B41: NOC | C41: 0.1981456 | D41: 0.1075225 | E41: 0.0996806 | F41: 0.07519 | G41: 0.23699 | H41: 0.83294949 | I41: 24.342258 | J41: 4.7443175 | K41: 94.134581 | L41: 46.839666 | M41: 1.00692 | N41: 1.10121 | O41: 9.3669173
A42: L3Harris Technologies Inc | B42: LHX | C42: 0.2572605 | D42: 0.0965013 | E42: 0.0734507 | F42: 0.0486 | G42: 0.1031 | H42: 0.52562623 | I42: 12.742252 | J42: 4.3817635 | K42: 56.613191 | L42: 33.959871 | M42: 1.02048 | N42: 1.18918 | O42: 7.1155779
A43: General Dynamics Corp | B43: GD | C43: 0.1513035 | D43: 0.101922 | E43: 0.0801142 | F43: 0.0744 | G43: 0.1766 | H43: 0.92902792 | I43: 4.7055286 | J43: 4.8720564 | K43: 32.80384 | L43: 21.629882 | M43: 0.89402 | N43: 1.44368 | O43: 15.621891
