Workbook

Sheet Cover
E5: NEWMONT Corporation
D11: Valuation Date: | E11: =TODAY() -> 46133 | H11: Scenario Switchboard
D12: Company Name: | E12: Newmont corporation
D13: Sector: | E13: Materials | H13: Revenue & Operating Expenses
D14: Industry: | E14: Metals and mining | H14: Gold Price | I14: 2
D15: Rating: | E15: =IF(E23>=Ke!D32,"BUY","SELL") -> BUY | H15: Cost of Sales | I15: 2
D17: Current Price | E17: =Ke!D17 -> 101
D18: Valuation Price | E18: =DCF!B8 -> 108.41662
D19: 12-month Valuation Price | E19: =DCF!B9 -> 114.20683
D20: Valuation Appreciation | E20: =E18/E17-1 -> 0.07343193
D21: 12-mo Valuation Appreciation | E21: =E19/E17-1 -> 0.13076071 | H21: Scenario Key
D22: Dividend Yield | E22: 0.01 | H22: Bull | I22: 1
D23: Total Valuation Appreciation | E23: =E21+E22 -> 0.14076071 | H23: Base | I23: 2
H24: Bear | I24: 3

Sheet DCF
A1: #VALUE!
G2: Share count in Millions
A3: Cost of Equity | B3: =Ke!D32 -> 0.093134239 | G3: =TODAY() -> 46133 | H3: Today | I3: =1087874212/1000000 -> 1087.8742
A4: Number of Shares in thousands: | G4: =G3+365 -> 46498 | H4: One year | I4: ='Changes in Equity'!H7 -> 1072.0088
G5: =G4+366 -> 46864 | H5: Two year | I5: ='Changes in Equity'!I7 -> 1053.8666
A6: Actual Price: | B6: =Ke!D17 -> 101 | C6: At close oct 22, 2025
G7: Price Appreciation
A8: Model Valuation: | B8: =B24 -> 108.41662 | G8: Price Appreciation | I8: =(B8-$B$6)/$B$6 -> 0.07343193
A9: Model 12 Month Price Target: | B9: =B46 -> 114.20683 | G9: Price Appreciation (12 month) | I9: =(B9-$B$6)/$B$6 -> 0.13076071
A12: Model Current Valuation with Sensitivity of Ke
D14: 46387 | E14: 46752 | F14: 47118 | G14: 47483 | H14: 47848
A15: Time period (years) | D15: =MAX((D14-$G$3)/365,0) -> 0.69589041 | E15: =MAX((E14-$G$3)/365,0) -> 1.6958904 | F15: =MAX((F14-$G$3)/365,0) -> 2.6986301 | G15: =MAX((G14-$G$3)/365,0) -> 3.6986301 | H15: =MAX((H14-$G$3)/365,0) -> 4.6986301
A16: Nominal FCFE: | D16: ='Cash flow'!C61 -> 5326.1378 | E16: ='Cash flow'!D61 -> 9408.753 | F16: ='Cash flow'!E61 -> 9139.8971 | G16: ='Cash flow'!F61 -> 9344.659 | H16: ='Cash flow'!G61 -> 9399.7044
A17: PV FCFE: | D17: =D16*D15/((1+$B$3)^D15) -> 3483.6999 | E17: =E16/((1+$B$3)^E15) -> 8089.954 | F17: =F16/((1+$B$3)^F15) -> 7187.4667 | G17: =G16/((1+$B$3)^G15) -> 6722.4023 | H17: =H16/((1+$B$3)^H15) -> 6185.8835
A19: Terminal Growth Rate | B19: 0.02
A21: Terminal Value in 2030 | B21: =H16*(1+B19)/(B3-B19) -> 131097.26 | D21: <== Implied terminal value / net income (or P/E) multiple for terminal value
A22: PV of Terminal Value | B22: =B21/(1+B3)^(H15) -> 86274.244
A23: Total PV: | B23: =SUM(D17:H17)+B22 -> 117943.65
A24: Valuation per Share ($): | B24: =B23/I3 -> 108.41662
C25: Terminal Growth Rate
B26: =B24 -> 108.41662 | C26: =D26-L27 -> 0.005 | D26: =E26-L27 -> 0.01 | E26: =F26-L27 -> 0.015 | F26: 0.02 | G26: =F26+L27 -> 0.025 | H26: =G26+L27 -> 0.03 | I26: =H26+L27 -> 0.035 | L26: 0.005
B27: =B28+L27 -> 0.10813424 | C27: 79.988827 | D27: 82.908615 | E27: 86.141907 | F27: 89.742059 | G27: 93.775263 | H27: 98.324657 | I27: 103.49611 | L27: 0.005
B28: =B29+L27 -> 0.10313424 | C28: 84.167688 | D28: 87.455515 | E28: 91.116391 | F28: 95.217623 | G28: 99.843751 | H28: 105.10243 | I28: 111.13293
B29: =B30+L27 -> 0.098134239 | C29: 88.796384 | D29: 92.51929 | E29: 96.690015 | F29: 101.39453 | G29: 106.74231 | H29: 112.87499 | I29: 119.97904
A30: Cost Of Equity Ke | B30: =Ke!D32 -> 0.093134239 | C30: 93.951493 | D30: 98.193212 | E30: 102.97781 | F30: 108.41662 | G30: 114.65369 | H30: 121.87866 | I30: 130.34645
B31: =B30-L27 -> 0.088134239 | C31: 99.728013 | D31: 104.59443 | E31: 110.12626 | F31: 116.46998 | G31: 123.81851 | H31: 132.4311 | I31: 142.6646
B32: =B31-L27 -> 0.083134239 | C32: 106.24526 | D32: 111.87213 | E32: 118.32484 | F32: 125.79962 | G32: 134.56017 | H32: 144.96949 | I32: 157.54136
B33: =B32-L27 -> 0.078134239 | C33: 113.65519 | D33: 120.21928 | E33: 127.82308 | F33: 136.73484 | G33: 147.32383 | H33: 160.1127 | I33: 175.86647
A36: Model 12 Month Price Target with Sensitivity of Ke
D38: =D14 -> 46387 | E38: =E14 -> 46752 | F38: =F14 -> 47118 | G38: =G14 -> 47483 | H38: =H14 -> 47848
A39: Time period | D39: =MAX((D38-$G$4)/365,0) -> 0 | E39: =MAX((E38-$G$4)/365,0) -> 0.69589041 | F39: =MAX((F38-$G$4)/365,0) -> 1.6986301 | G39: =MAX((G38-$G$4)/365,0) -> 2.6986301 | H39: =MAX((H38-$G$4)/365,0) -> 3.6986301
A40: Nominal FCFE: | D40: =D16*D39 -> 0 | E40: =E16 -> 9408.753 | F40: =F16 -> 9139.8971 | G40: =G16 -> 9344.659 | H40: =H16 -> 9399.7044
A41: PV FCFE: | D41: =D40/((1+$B$3)^D39) -> 0 | E41: =E40*E39/((1+$B$3)^E39) -> 6154.0412 | F41: =F40/((1+$B$3)^F39) -> 7856.8659 | G41: =G40/((1+$B$3)^G39) -> 7348.4881 | H41: =H40/((1+$B$3)^H39) -> 6762.001
A43: Terminal Value in 2030 | B43: =H40*(1+B19)/(B3-B19) -> 131097.26
A44: PV of Terminal Value | B44: =B43/(1+B3)^H39 -> 94309.33
A45: Total PV: | B45: =SUM(D41:H41)+B44 -> 122430.73
A46: Valuation per Share ($): | B46: =B45/I4 -> 114.20683
C47: Terminal Growth Rate
B48: =B46 -> 114.20683 | C48: =D48-$L$26 -> 0.005 | D48: =E48-$L$26 -> 0.01 | E48: =F48-$L$26 -> 0.015 | F48: 0.02 | G48: =F48+$L$26 -> 0.025 | H48: =G48+$L$26 -> 0.03 | I48: =H48+$L$26 -> 0.035
B49: =B50+$L$27 -> 0.10813424 | C49: 83.898041 | D49: 87.181443 | E49: 90.817391 | F49: 94.865885 | G49: 99.401362 | H49: 104.51731 | I49: 110.33279
B50: =B51+$L$27 -> 0.10313424 | C50: 88.167317 | D50: 91.847909 | E50: 95.946114 | F50: 100.53728 | G50: 105.71605 | H50: 111.60293 | I50: 118.35383
B51: =B52+$L$27 -> 0.098134239 | C51: 92.89543 | D51: 97.044186 | E51: 101.69198 | F51: 106.93463 | G51: 112.89413 | H51: 119.7283 | I51: 127.64495
A52: Cost Of Equity Ke | B52: =Ke!D32 -> 0.093134239 | C52: 98.160482 | D52: 102.86587 | E52: 108.17349 | F52: 114.20683 | G52: 121.12569 | H52: 129.14044 | I52: 138.53385
B53: =B52-$L$27 -> 0.088134239 | C53: 104.05936 | D53: 109.43304 | E53: 115.5415 | F53: 122.54648 | G53: 130.66101 | H53: 140.17136 | I53: 151.47158
B54: =B53-$L$27 -> 0.083134239 | C54: 110.71376 | D54: 116.8986 | E54: 123.9912 | F54: 132.20721 | G54: 141.8365 | H54: 153.27804 | I54: 167.0966
B55: =B54-$L$27 -> 0.078134239 | C55: 118.27864 | D55: 125.46034 | E55: 133.77958 | F55: 143.52986 | G55: 155.11517 | H55: 169.10735 | I55: 186.3434

Sheet Ke
B2: Company name | D2: Company ticker
B3: Newmont Corporation | D3: NEM
B4: Cost of Equity
B5: (Blue = input, Black = calculation)
B7: S&P 500 data | F7: Source
C8: S&P500 Forward P/E | D8: 20.57 | F8: WSJ
C9: Projected EPS growth rate (g S&P) | D9: 0.122 | E9: Yahoo Finance | F9: CapIQ / Bloomberg | G9: (5 years)
C10: Risk-free rate (Rf) | D10: 0.043 | F10: Market quote
C11: Implied required return on equity (Rs&p500) | D11: =((1+D9)/D8)+D9 -> 0.17654545
C12: Implied equity risk premium (Rm) | D12: =+D11-D10 -> 0.13354545
B15: Beta
B16: Newmont Corporation
C17: Current Price (P) | D17: 101 | F17: Yahoo!Finance | K17: Book
C18: Forward EPS (E) | D18: 8.92 | F18: Yahoo!Finance | J18: Company | K18: D/E Ratio | L18: Tax Rate | M18: Beta | N18: bU = bL / (1+ ((1-t)D/E)) | O18: bL = bu (1+ ((1-t)D/E))
C19: P/E ratio | D19: =D17/D18 -> 11.32287 | J19: RGLD.OQ | K19: 0.25 | L19: 0.22 | M19: 0.5 | N19: =M19/(1+((1-L19)*K19)) -> 0.41841004 | O19: =N19*(1+((1-$L$26)*$K$26)) -> 0.50558635
C20: Projected EPS growth rate (g) | D20: 0.585 | F20: LSEG>Estmates>Recommendations & Target Price | G20: (5 years) | J20: GFIJ.J | K20: ='Comps no formula'!K40/100 -> 0.56634752 | L20: 0.342 | M20: 1.72 | N20: =M20/(1+((1-L20)*K20)) -> 1.2530446 | O20: =N20*(1+((1-$L$26)*$K$26)) -> 1.5141181
C21: Implied required return on equity (Re) | D21: =+((1+D20)/D19)+D20 -> 0.72498218 | J21: AEM.N | K21: ='Comps no formula'!K41/100 -> 0.061546016 | L21: 0.328 | M21: 1.18 | N21: =M21/(1+((1-L21)*K21)) -> 1.1331348 | O21: =N21*(1+((1-$L$26)*$K$26)) -> 1.369225
C22: Forward (Bf) | D22: =(D21-D10)/D12 -> 5.106742 | J22: ABX.TO | K22: ='Comps no formula'!K42/100 -> 0.19621945 | L22: 0.188 | M22: 0.98 | N22: =M22/(1+((1-L22)*K22)) -> 0.84531569 | O22: =N22*(1+((1-$L$26)*$K$26)) -> 1.0214384
C23: Historical (Bh) | D23: 0.44 | F23: Yahoo!Finance | O23: =+AVERAGE(O19:O22) -> 1.102592
C24: Average Beta | D24: =+(D22+D23)/2 -> 2.773371
C25: Comperable Beta | D25: =+O23 -> 1.102592 | F25: Calculation | K25: D/E Ratio | L25: Tax Rate | O25: Relevered
J26: NEM | K26: ='Comps no formula'!K43/100 -> 0.29978615 | L26: 0.305 | M26: 0.43 | N26: =M26/(1+((1-L26)*K26)) -> 0.35585676 | O26: =N26*(1+((1-L26)*K26)) -> 0.43
B27: Cost of Equity:
C28: Historic equity risk premium | D28: 0.065
C29: Using Forward Beta | D29: =+$D$10+D22*($D$28) -> 0.37493823 | E29: 0
C30: Using Historic Beta | D30: =+$D$10+D23*($D$28) -> 0.0716 | E30: 0.5
C31: Comperable Beta | D31: =+$D$10+D25*($D$28) -> 0.11466848 | E31: 0.5
C32: Weighted COE | D32: =+SUMPRODUCT(D29:D31,E29:E31) -> 0.093134239
C34: Market COE (beta = 1) | D34: =+D10+1*D28 -> 0.108

Sheet Revenue
A2: Millions | D2: Revenue Generated(volume sold*metal price)
A3: Revenue | B3: 2020 | C3: 2021 | D3: 2022 | E3: 2023 | F3: 2024 | G3: 2025A | H3: 2026E | I3: 2027E | J3: 2028E | K3: 2029E | L3: 2030E
A4: Gold | B4: 10350 | C4: 10543 | D4: 10416 | E4: 10593 | F4: 15746 | G4: 19304 | H4: =H24*(H15/1000) -> 23141.775 | I4: =I24*(I15/1000) -> 26579.622 | J4: =J24*(J15/1000) -> 27584.6 | K4: =K24*(K15/1000) -> 28482.752 | L4: =L24*(L15/1000) -> 29245.009
A5: Silver | B5: 510 | C5: 651 | D5: 549 | E5: 335 | F5: 792 | G5: 1080 | H5: =+H25*H16 -> 2464 | I5: =+I25*I16 -> 2100 | J5: =+J25*J16 -> 2129.68 | K5: =+K25*K16 -> 2213.372 | L5: =+L25*L16 -> 2233.84
A6: Copper | B6: 155 | C6: 295 | D6: 316 | E6: 575 | F6: 1327 | G6: 1438 | H6: =+H26*H17 -> 1255.5 | I6: =+I26*I17 -> 1894.088 | J6: =+J26*J17 -> 1964.3067 | K6: =+K26*K17 -> 2137.5833 | L6: =+L26*L17 -> 2194.0307
A7: Zinc | B7: 348 | C7: 561 | D7: 501 | E7: 213 | F7: 622 | G7: 664 | H7: =+H27*H18 -> 544.17 | I7: =+I27*I18 -> 769.62667 | J7: =+J27*J18 -> 781.2 | K7: =+K27*K18 -> 792.77333 | L7: =+L27*L18 -> 804.34667
A8: Lead | B8: 134 | C8: 172 | D8: 133 | E8: 96 | F8: 195 | G8: 183 | H8: =+H19*H28 -> 205.326 | I8: =+I19*I28 -> 257.48 | J8: =+J19*J28 -> 260.62 | K8: =+K19*K28 -> 262.71333 | L8: =+L19*L28 -> 264.80667
A9: Total | B9: =+SUM(B4:B8) -> 11497 | C9: =+SUM(C4:C8) -> 12222 | D9: =+SUM(D4:D8) -> 11915 | E9: =+SUM(E4:E8) -> 11812 | F9: =+SUM(F4:F8) -> 18682 | G9: =+SUM(G4:G8) -> 22669 | H9: =+SUM(H4:H8) -> 27610.771 | I9: =+SUM(I4:I8) -> 31600.817 | ... L9: =+SUM(L4:L8) -> 34742.033
A13: Thousands | E13: Volume of metals sold
A14: Volume | B14: 2020 | C14: 2021 | D14: 2022 | E14: 2023 | F14: 2024 | G14: 2025A | H14: 2026E | I14: 2027E | J14: 2028E | K14: 2029E | L14: 2030E
A15: Gold | B15: 5831 | C15: 5897 | D15: 5812 | E15: 5420 | F15: 6540 | G15: 5519 | H15: ='Cost of sales'!H44 -> 4850 | I15: ='Cost of sales'!I44 -> 5392.7167 | J15: ='Cost of sales'!J44 -> 5375.5432 | K15: ='Cost of sales'!K44 -> 5360.1475 | L15: ='Cost of sales'!L44 -> 5346.5345 | M15: Kept sold quantity constant as production is constant as historicals.
A16: Silver | B16: =28596/1000 -> 28.596 | C16: =32237/1000 -> 32.237 | D16: =29743/1000 -> 29.743 | E16: =+E47 -> 17 | F16: =+F47 -> 33 | G16: 28 | H16: =+H47 -> 32 | I16: =+I47 -> 28 | J16: =+J47 -> 28 | K16: =+K47 -> 28 | L16: =+L47 -> 28 | M16: See Table below
A17: Copper | B17: =+B56 -> 56 | C17: =+C56 -> 69 | D17: =+D56 -> 85 | E17: =+E56 -> 155 | F17: =+F56 -> 332 | G17: 294 | H17: =+H56 -> 225 | I17: =+I56 -> 302.66667 | J17: =+J56 -> 302.66667 | K17: =+K56 -> 302.66667 | L17: =+L56 -> 302.66667 | M17: See Table below
A18: Zinc | B18: =+B61 -> 407 | C18: =+C61 -> 433 | D18: =+D61 -> 373 | E18: =+E61 -> 222 | F18: =+F61 -> 545 | G18: 542 | H18: =+H61 -> 485 | I18: =+I61 -> 578.66667 | J18: =+J61 -> 578.66667 | K18: =+K61 -> 578.66667 | L18: =+L61 -> 578.66667 | M18: See Table below
A19: Lead | B19: =+B65 -> 185 | C19: =+C65 -> 173 | D19: =+D65 -> 147 | E19: =+E65 -> 107 | F19: =+F65 -> 213 | G19: 216 | H19: =+H65 -> 198 | I19: =+I65 -> 209.33333 | J19: =+J65 -> 209.33333 | K19: =+K65 -> 209.33333 | L19: =+L65 -> 209.33333 | M19: See Table below
E22: Price of metals
A23: Price | B23: 2020 | C23: 2021 | D23: 2022 | E23: 2023 | F23: 2024 | G23: 2025A | H23: 2026E | I23: 2027E | J23: 2028E | K23: 2029E | L23: 2030E
A24: Gold ($/oz) | B24: =+(B4*1000)/(B15) -> 1774.9957 | C24: =+(C4*1000)/(C15) -> 1787.8582 | D24: =+(D4*1000)/(D15) -> 1792.1542 | E24: =+(E4*1000)/(E15) -> 1954.428 | F24: =+(F4*1000)/(F15) -> 2407.6453 | G24: =+(G4*1000)/(G15) -> 3497.7351 | H24: =CHOOSE(Cover!$I$14,Revenue!H30,Revenue!H31,Revenue!H32) -> 4771.5 | I24: =CHOOSE(Cover!$I$14,Revenue!I30,Revenue!I31,Revenue!I32) -> 4928.8 | J24: =CHOOSE(Cover!$I$14,Revenue!J30,Revenue!J31,Revenue!J32) -> 5131.5 | K24: =CHOOSE(Cover!$I$14,Revenue!K30,Revenue!K31,Revenue!K32) -> 5313.8 | L24: =CHOOSE(Cover!$I$14,Revenue!L30,Revenue!L31,Revenue!L32) -> 5469.9 | M24: all Prices from following table consisting multiple reports and projections
A25: Silver ($/oz) | B25: =+(B5)/(B16) -> 17.834662 | C25: =+(C5)/(C16) -> 20.194187 | D25: =+(D5)/(D16) -> 18.458125 | E25: =+(E5)/(E16) -> 19.705882 | F25: =+(F5)/(F16) -> 24 | G25: =+(G5)/(G16) -> 38.571429 | H25: =+(79+H37)/2 -> 77 | I25: 75 | J25: 76.06 | K25: 79.049 | L25: 79.78
A26: Copper ($/lb) | B26: =+(B6)/(B17) -> 2.7678571 | C26: =+(C6)/(C17) -> 4.2753623 | D26: =+(D6)/(D17) -> 3.7176471 | E26: =+(E6)/(E17) -> 3.7096774 | F26: =+(F6)/(F17) -> 3.996988 | G26: =+(G6)/(G17) -> 4.8911565 | H26: =+(5.72+H38)/2 -> 5.58 | I26: 6.258 | J26: 6.49 | K26: 7.0625 | L26: 7.249
A27: Zinc ($/lb) | B27: =+(B7)/(B18) -> 0.85503686 | C27: =+(C7)/(C18) -> 1.295612 | D27: =+(D7)/(D18) -> 1.3431635 | E27: =+(E7)/(E18) -> 0.95945946 | F27: =+(F7)/(F18) -> 1.1412844 | G27: =+(G7)/(G18) -> 1.2250923 | H27: =+H40*85% -> 1.122 | I27: =+(I40+H40)/2 -> 1.33 | J27: =+(J40+I40)/2 -> 1.35 | K27: =+(K40+J40)/2 -> 1.37 | L27: =+(L40+K40)/2 -> 1.39
A28: Lead ($/lb) | B28: =B8/B19 -> 0.72432432 | C28: =C8/C19 -> 0.99421965 | D28: =D8/D19 -> 0.9047619 | E28: =E8/E19 -> 0.89719626 | F28: =F8/F19 -> 0.91549296 | G28: =G8/G19 -> 0.84722222 | H28: =+H39*85% -> 1.037 | I28: =+(I39+H39)/2 -> 1.23 | J28: =+(J39+I39)/2 -> 1.245 | K28: =+(K39+J39)/2 -> 1.255 | L28: =+(L39+K39)/2 -> 1.265
H30: =H31+200 -> 4971.5 | I30: =I31+200 -> 5128.8 | J30: =J31+200 -> 5331.5 | K30: =K31+200 -> 5513.8 | L30: =L31+200 -> 5669.9 | M30: bull
H31: 4771.5 | I31: 4928.8 | J31: 5131.5 | K31: 5313.8 | L31: 5469.9 | M31: base | N31: https://www.wsj.com/market-data/quotes/futures/GC00/contracts
H32: =H31-200 -> 4571.5 | I32: =I31-200 -> 4728.8 | J32: =J31-200 -> 4931.5 | K32: =K31-200 -> 5113.8 | L32: =L31-200 -> 5269.9 | M32: bear
A33: Avg Prices
A34: The below table is for referal only
A35: Metal (Unit) | B35: 2020 | C35: 2021 | D35: 2022 | E35: 2023 | F35: 2024 | G35: 2025A | H35: 2026E | I35: 2027E | J35: 2028E | K35: 2029E | L35: 2030E
A36: Gold ($/oz) | B36: 1770 | C36: 1799 | D36: 1800 | E36: 1941 | F36: 2386 | G36: 4400 | H36: 6300 | I36: 6000 | J36: 5750 | K36: 5500 | L36: 5350 | M36: https://www.thestreet.com/investing/j-p-morgan-revises-gold-price-target-for-2026?utm_source=chatgpt.com
A37: Silver ($/oz) | B37: 20.58 | C37: 25.23 | D37: 21.88 | E37: 23.54 | F37: 27.7 | G37: 65 | H37: 75 | I37: 70 | J37: 68 | K37: 66 | L37: 65 | M37: https://www.reuters.com/world/africa/jp-morgan-sees-gold-6300-an-ounce-by-year-end-robust-centralbank-investor-demand-2026-02-02/?utm_source=chatgpt.com
A38: Copper ($/lb) | B38: 2.8 | C38: 4.24 | D38: 4.01 | E38: 3.86 | F38: 4.2 | G38: 4.5 | H38: 5.44 | I38: 5.44 | J38: 5 | K38: 4.9 | L38: 5 | M38: https://www.jpmorgan.com/insights/global-research/commodities/copper-outlook
A39: Lead ($/lb) | B39: 0.91 | C39: 1.13 | D39: 1.17 | E39: 1.14 | F39: 1.1 | G39: 1.2 | H39: 1.22 | I39: 1.24 | J39: 1.25 | K39: 1.26 | L39: 1.27 | M39: More stable, industrial metals with less speculative demand than precious metals — modest annual increases are assumed.
A40: Zinc ($/lb) | B40: 1.03 | C40: 1.36 | D40: 1.58 | E40: 1.2 | F40: 1.26 | G40: 1.3 | H40: 1.32 | I40: 1.34 | J40: 1.36 | K40: 1.38 | L40: 1.4 | M40: More stable, industrial metals with less speculative demand than precious metals — modest annual increases are assumed.
C44: millions
A45: Silver | B45: penasquito
A46: Ounces Sold | B46: 2020 | C46: 2021 | D46: 2022 | E46: 2023 | F46: 2024 | G46: 2025A | H46: 2026E | I46: 2027E | J46: 2028E | K46: 2029E | L46: 2030E
B47: 28 | C47: 32 | D47: 30 | E47: 17 | F47: 33 | G47: 28 | H47: 32 | I47: 28 | J47: 28 | K47: 28 | L47: 28
A50: Copper | C50: millions
A51: Ounces Sold | B51: 2020 | C51: 2021 | D51: 2022 | E51: 2023 | F51: 2024 | G51: 2025E | H51: 2026E | I51: 2027E | J51: 2028E | K51: 2029E | L51: 2030E
A52: Red Chris | E52: 7 | F52: 57
A53: Boddington | E53: 98 | F53: 83
A54: Cadia | E54: 45 | F54: 186
A55: Tefler | E55: 5 | F55: 6
A56: Total | B56: 56 | C56: 69 | D56: 85 | E56: =+SUM(E52:E55) -> 155 | F56: =+SUM(F52:F55) -> 332 | G56: 303 | H56: 225 | I56: 302.66667 | J56: 302.66667 | K56: 302.66667 | L56: 302.66667
A59: Zinc | B59: penasquito
A60: Ounces Sold | B60: 2020 | C60: 2021 | D60: 2022 | E60: 2023 | F60: 2024 | G60: 2025E | H60: 2026E | I60: 2027E | J60: 2028E | K60: 2029E | L60: 2030E
B61: 407 | C61: 433 | D61: 373 | E61: 222 | F61: 545 | G61: 579 | H61: 485 | I61: 578.66667 | J61: 578.66667 | K61: 578.66667 | L61: 578.66667
A63: Lead | B63: penasquito
A64: Ounces Sold | B64: 2020 | C64: 2021 | D64: 2022 | E64: 2023 | F64: 2024 | G64: 2025E | H64: 2026E | I64: 2027E | J64: 2028E | K64: 2029E | L64: 2030E
B65: 185 | C65: 173 | D65: 147 | E65: 107 | F65: 213 | G65: 209 | H65: 198 | I65: 209.33333 | J65: 209.33333 | K65: 209.33333 | L65: 209.33333

Sheet Cost of sales
A1: Millions
A2: Cost of production | B2: 2020 | C2: 2021 | D2: 2022 | E2: 2023 | F2: 2024 | G2: 2025A | H2: 2026E | I2: 2027E | J2: 2028E | K2: 2029E | L2: 2030E
A3: Gold | B3: 4408 | C3: 4628 | D3: 5423 | E3: 5689 | F3: 7364 | G3: 6615 | H3: =H12*H44/1000 -> 6396.665 | I3: =I12*I44/1000 -> 7539.2013 | J3: =J12*J44/1000 -> 7890.9517 | K3: =K12*K44/1000 -> 8261.7695 | L3: =L12*L44/1000 -> 8652.8267
A4: Silver | B4: 201 | C4: 201 | D4: 454 | E4: 300 | F4: 360 | G4: 334 | H4: =H17*H48 -> 314.62731 | I4: =I17*I48 -> 314.62731 | J4: =J17*J48 -> 314.62731 | K4: =K17*K48 -> 314.62731 | L4: =L17*L48 -> 314.62731
A5: Copper | B5: 107 | C5: 107 | D5: 181 | E5: 359 | F5: 696 | G5: 597 | H5: =H18*H53 -> 596.86636 | I5: =I18*I53 -> 596.86636 | J5: =J18*J53 -> 596.86636 | K5: =K18*K53 -> 596.86636 | L5: =L18*L53 -> 596.86636
A6: Zinc | B6: 221 | C6: 256 | D6: 316 | E6: 253 | F6: 427 | G6: 423 | H6: =H20*H58 -> 392.66234 | I6: =I20*I58 -> 392.66234 | J6: =J20*J58 -> 392.66234 | K6: =K20*K58 -> 392.66234 | L6: =L20*L58 -> 392.66234
A7: Lead | B7: 77 | C7: 76 | D7: 94 | E7: 98 | F7: 116 | G7: 116 | H7: =H19*H62 -> 125.48931 | I7: =I19*I62 -> 125.48931 | J7: =J19*J62 -> 125.48931 | K7: =K19*K62 -> 125.48931 | L7: =L19*L62 -> 125.48931
A8: Total | B8: =SUM(B3:B7) -> 5014 | C8: =SUM(C3:C7) -> 5268 | D8: =SUM(D3:D7) -> 6468 | E8: =SUM(E3:E7) -> 6699 | F8: =SUM(F3:F7) -> 8963 | G8: =SUM(G3:G7) -> 8085 | H8: =SUM(H3:H7) -> 7826.3103 | I8: =SUM(I3:I7) -> 8968.8466 | ... L8: =SUM(L3:L7) -> 10082.472
E10: cost of sale/unit | I10: 0.0885
A11: Cost/Unit | B11: 2020 | C11: 2021 | D11: 2022 | E11: 2023 | F11: 2024 | G11: 2025A | H11: 2026E | I11: 2027E | J11: 2028E | K11: 2029E | L11: 2030E
A12: Gold ($/oz) | B12: =B3*1000/B44 -> 756.86813 | C12: =C3*1000/C44 -> 786.53977 | D12: =D3*1000/D44 -> 937.26236 | E12: =E3*1000/E44 -> 1053.3235 | F12: =F3*1000/F44 -> 1125.1337 | G12: 1199 | H12: =G12*(1+H13) -> 1318.9 | I12: =H12*(1+I13) -> 1398.034 | J12: =I12*(1+J13) -> 1467.9357 | K12: =J12*(1+K13) -> 1541.3325 | L12: =K12*(1+L13) -> 1618.3991
C13: =(C12-B12)/B12 -> 0.039203179 | D13: =(D12-C12)/C12 -> 0.19162742 | E13: =(E12-D12)/D12 -> 0.1238299 | F13: =(F12-E12)/E12 -> 0.068174909 | G13: =(G12-F12)/F12 -> 0.065651141 | H13: =CHOOSE(Cover!$I$15,'Cost of sales'!H14,'Cost of sales'!H15,'Cost of sales'!H16) -> 0.1 | I13: =CHOOSE(Cover!$I$15,'Cost of sales'!I14,'Cost of sales'!I15,'Cost of sales'!I16) -> 0.06 | J13: =CHOOSE(Cover!$I$15,'Cost of sales'!J14,'Cost of sales'!J15,'Cost of sales'!J16) -> 0.05 | K13: =CHOOSE(Cover!$I$15,'Cost of sales'!K14,'Cost of sales'!K15,'Cost of sales'!K16) -> 0.05 | L13: =CHOOSE(Cover!$I$15,'Cost of sales'!L14,'Cost of sales'!L15,'Cost of sales'!L16) -> 0.05
H14: =H15-0.01 -> 0.09 | I14: =I15-0.01 -> 0.05 | J14: =J15-0.01 -> 0.04 | K14: =K15-0.01 -> 0.04 | L14: =L15-0.01 -> 0.04 | M14: bull
H15: 0.1 | I15: 0.06 | J15: 0.05 | K15: 0.05 | L15: 0.05 | M15: base
H16: =H15+0.01 -> 0.11 | I16: =I15+0.01 -> 0.07 | J16: =J15+0.01 -> 0.06 | K16: =K15+0.01 -> 0.06 | L16: =L15+0.01 -> 0.06 | M16: bear
A17: Silver ($/oz) | B17: =B4/B48 -> 7.0526316 | C17: =C4/C48 -> 6.4217252 | D17: =D4/D48 -> 15.133333 | E17: =E4/E48 -> 16.666667 | F17: =F4/F48 -> 10.909091 | G17: =AVERAGE(B17:F17) -> 11.23669 | H17: =G17 -> 11.23669 | I17: =H17 -> 11.23669 | J17: =I17 -> 11.23669 | K17: =J17 -> 11.23669 | L17: =K17 -> 11.23669
A18: Copper ($/lb) | B18: =B5/B53 -> 1.9107143 | C18: =C5/C53 -> 1.5070423 | D18: =D5/D53 -> 2.1294118 | E18: =E5/E53 -> 2.4758621 | F18: =F5/F53 -> 2.0591716 | G18: =AVERAGE(B18:F18) -> 2.0164404 | H18: =G18 -> 2.0164404 | I18: =H18 -> 2.0164404 | J18: =I18 -> 2.0164404 | K18: =J18 -> 2.0164404 | L18: =K18 -> 2.0164404
A19: Lead ($/lb) | B19: =B7/B62 -> 0.4301676 | C19: =C7/C62 -> 0.42937853 | D19: =D7/D62 -> 0.63087248 | E19: =E7/E62 -> 0.86725664 | F19: =F7/F62 -> 0.54716981 | G19: =AVERAGE(B19:F19) -> 0.58096901 | H19: =G19 -> 0.58096901 | I19: =H19 -> 0.58096901 | J19: =I19 -> 0.58096901 | K19: =J19 -> 0.58096901 | L19: =K19 -> 0.58096901
A20: Zinc ($/lb) | B20: =B6/B58 -> 0.58005249 | C20: =C6/C58 -> 0.58850575 | D20: =D6/D58 -> 0.83819629 | E20: =E6/E58 -> 1.1 | F20: =F6/F58 -> 0.75043937 | G20: =AVERAGE(B20:F20) -> 0.77143878 | H20: =G20 -> 0.77143878 | I20: =H20 -> 0.77143878 | J20: =I20 -> 0.77143878 | K20: =J20 -> 0.77143878 | L20: =K20 -> 0.77143878
A23: Gold | F23: Production volume
A24: million 'Ounces Produced | B24: 2020 | C24: 2021 | D24: 2022 | E24: 2023 | F24: 2024 | G24: 2025A | H24: 2026E | I24: 2027E | J24: 2028E | K24: 2029E | L24: 2030E | M24: projection explanation | N24: Management commentary
A25: Brucejack | D25: 0 | E25: 29 | F25: 258 | G25: 231 | H25: 260 | I25: 226.66667 | J25: 226.66667 | K25: 226.66667 | L25: 226.66667 | N25: A high-grade underground asset contributing stable production following integration from Newcrest.
A26: Red Chris | D26: 0 | E26: 5 | F26: 40 | G26: 62 | H26: 35 | I26: =H26*1.05 -> 36.75 | J26: =I26*1.05 -> 38.5875 | K26: =J26*1.05 -> 40.516875 | L26: =K26*1.05 -> 42.542719 | N26: A long-life copper-gold asset with block cave growth potential.
A27: Penasquito | D27: 566 | E27: 143 | F27: 299 | G27: 415 | H27: 185 | I27: 500 | J27: 500 | K27: 500 | L27: 500 | N27: A large-scale polymetallic asset delivering strong gold and co-product exposure
A28: Merian | D28: 403 | E28: 322 | F28: 274 | G28: 237 | H28: 225 | I28: =H28*0.98 -> 220.5 | J28: =I28*0.98 -> 216.09 | K28: =J28*0.98 -> 211.7682 | L28: =K28*0.98 -> 207.53284 | N28: A mature Suriname operation generating consistent free cash flow.
A29: Cerro Negro | D29: 278 | E29: 269 | F29: 238 | G29: 202 | H29: 220 | I29: =H29*0.95 -> 209 | J29: =I29*0.95 -> 198.55 | K29: =J29*0.95 -> 188.6225 | L29: =K29*0.95 -> 179.19137 | N29: An established underground operation in Argentina
A30: Yanacocha | D30: 244 | E30: 276 | F30: 354 | G30: 515 | H30: 460 | I30: 517.33333 | J30: 517.33333 | K30: 517.33333 | L30: 517.33333 | N30: Transitioning through mine sequencing as oxide production evolves.
A31: Boddington | D31: 798 | E31: 745 | F31: 590 | G31: 565 | H31: 580 | I31: 558.66667 | J31: 558.66667 | K31: 558.66667 | L31: 558.66667 | N31: A cornerstone Australian asset with integrated gold and copper production
A32: Tanami | D32: 484 | E32: 448 | F32: 408 | G32: 391 | H32: 365 | I32: =H32+200 -> 565 | J32: =I32 -> 565 | K32: =J32 -> 565 | L32: =K32 -> 565 | N32: Tanami Expansion 2 secures Tanami’s future as a long-life, low-cost producer.
A33: Cadia | D33: 0 | E33: 97 | F33: 464 | G33: 385 | H33: 270 | I33: =H33*1.05 -> 283.5 | J33: =I33*1.05 -> 297.675 | K33: =J33*1.05 -> 312.55875 | L33: =K33*1.05 -> 328.18669 | N33: A world-class, long-life copper-gold system anchored by panel cave development.
A34: Lihir | D34: 0 | E34: 134 | F34: 614 | G34: 585 | H34: 560 | I34: 604 | J34: 604 | K34: 604 | L34: 604 | N34: A long-life asset with significant resource base and optimization potential.
A35: Ahafo | D35: 574 | E35: 581 | F35: 798 | G35: =664+70 -> 734 | H35: 755 | I35: =H35 -> 755 | J35: =I35 -> 755 | K35: =J35 -> 755 | L35: =K35 -> 755 | N35: Ahafo North will deliver 275,000–325,000 ounces annually in its first five full years.
A36: NGM | D36: 1169 | E36: 1170 | F36: 1039 | G36: 999 | H36: 935 | I36: =H36*0.98 -> 916.3 | J36: =I36*0.98 -> 897.974 | K36: =J36*0.98 -> 880.01452 | L36: =K36*0.98 -> 862.41423 | N36: A cornerstone joint venture with long reserve life and strong margins.
A37: CC&V | D37: 182 | E37: 172 | F37: 146 | G37: 0 | H37: 0 | I37: 0 | J37: 0 | K37: 0 | L37: 0 | N37: Non-core asset identified under portfolio optimization program
A38: Musslewhite | D38: 173 | E38: 180 | F38: 212 | G38: 0 | H38: 0 | I38: 0 | J38: 0 | K38: 0 | L38: 0 | N38: Non-core asset identified under portfolio optimization program
A39: Porcupine | D39: 280 | E39: 260 | F39: 284 | G39: 0 | H39: 0 | I39: 0 | J39: 0 | K39: 0 | L39: 0 | N39: Non-core asset identified under portfolio optimization program
A40: Eleonore | D40: 215 | E40: 232 | F40: 240 | G40: 0 | H40: 0 | I40: 0 | J40: 0 | K40: 0 | L40: 0 | N40: Non-core asset identified under portfolio optimization program
A41: Akyem | D41: 420 | E41: 295 | F41: 204 | G41: 0 | H41: 0 | I41: 0 | J41: 0 | K41: 0 | L41: 0 | N41: Non-core asset identified under portfolio optimization program
A42: Divested | G42: 209 | H42: 0 | I42: 0 | J42: 0 | K42: 0 | L42: 0 | N42: sold in mid 2025 , so pre-sold production.
A43: Telfer | D43: 0 | E43: 43 | F43: 83 | N43: Newmont is prioritizing margin resilience and long-life Tier-1 assets over volume growth.
A44: Total Gold | B44: 5824 | C44: 5884 | D44: =+SUM(D25:D43) -> 5786 | E44: =+SUM(E25:E43) -> 5401 | F44: =+SUM(F25:F43) -> 6545 | G44: =+SUM(G25:G43) -> 5530 | H44: =+SUM(H25:H43) -> 4850 | I44: =+SUM(I25:I43) -> 5392.7167 | J44: =+SUM(J25:J43) -> 5375.5432 | K44: =+SUM(K25:K43) -> 5360.1475 | L44: =+SUM(L25:L43) -> 5346.5345 | N44: 2025 reset → 2026–2028 rebuild → steady 6Moz+ long-term plateau.
A46: Silver
A47: Ounces produced | B47: 2020 | C47: 2021 | D47: 2022 | E47: 2023 | F47: 2024 | G47: 2025A | H47: 2026E | I47: 2027E | J47: 2028E | K47: 2029E | L47: 2030E
B48: 28.5 | C48: 31.3 | D48: 30 | E48: 18 | F48: 33 | G48: 28 | H48: =G48 -> 28 | I48: =H48 -> 28 | J48: =I48 -> 28 | K48: =J48 -> 28 | L48: =K48 -> 28
A51: Copper
A52: Ounces produced | B52: 2020 | C52: 2021 | D52: 2022 | E52: 2023 | F52: 2024 | G52: 2025A | H52: 2026E | I52: 2027E | J52: 2028E | K52: 2029E | L52: 2030E
A53: Total | B53: 56 | C53: 71 | D53: 85 | E53: 145 | F53: 338 | G53: 296 | H53: 296 | I53: 296 | J53: 296 | K53: 296 | L53: 296
A56: Zinc
A57: Ounces produced | B57: 2020 | C57: 2021 | D57: 2022 | E57: 2023 | F57: 2024 | G57: 2025A | H57: 2026E | I57: 2027E | J57: 2028E | K57: 2029E | L57: 2030E
B58: 381 | C58: 435 | D58: 377 | E58: 230 | F58: 569 | G58: 509 | H58: 509 | I58: 509 | J58: 509 | K58: 509 | L58: 509
A60: Lead
A61: Ounces produced | B61: 2020 | C61: 2021 | D61: 2022 | E61: 2023 | F61: 2024 | G61: 2025A | H61: 2026E | I61: 2027E | J61: 2028E | K61: 2029E | L61: 2030E
B62: 179 | C62: 177 | D62: 149 | E62: 113 | F62: 212 | G62: 216 | H62: 216 | I62: 216 | J62: 216 | K62: 216 | L62: 216
A66: Total production | B66: =SUM(B44,B48,B53,B58,B62) -> 6468.5 | C66: =SUM(C44,C48,C53,C58,C62) -> 6598.3 | D66: =SUM(D44,D48,D53,D58,D62) -> 6427 | E66: =SUM(E44,E48,E53,E58,E62) -> 5907 | F66: =SUM(F44,F48,F53,F58,F62) -> 7697 | G66: =SUM(G44,G48,G53,G58,G62) -> 6579 | H66: =SUM(H44,H48,H53,H58,H62) -> 5899 | I66: =SUM(I44,I48,I53,I58,I62) -> 6441.7167 | ... L66: =SUM(L44,L48,L53,L58,L62) -> 6395.5345

Sheet Income statement
A2: Particulars | B2: 2020 | C2: 2021 | D2: 2022 | E2: 2023 | F2: 2024 | G2: 2025A | H2: 2026E | I2: 2027E | J2: 2028E | K2: 2029E | L2: 2030E
A3: Sales | B3: 11497 | C3: 12222 | D3: 11915 | E3: 11812 | F3: 18682 | G3: 22669 | H3: =Revenue!H9 -> 27610.771 | I3: =Revenue!I9 -> 31600.817 | J3: =Revenue!J9 -> 32720.406 | K3: =Revenue!K9 -> 33889.194 | L3: =Revenue!L9 -> 34742.033
A4: Costs applicable to sales | B4: 5014 | C4: 5435 | D4: 6468 | E4: 6699 | F4: 8963 | G4: 8085 | H4: ='Cost of sales'!H8 -> 7826.3103 | I4: ='Cost of sales'!I8 -> 8968.8466 | J4: ='Cost of sales'!J8 -> 9320.597 | K4: ='Cost of sales'!K8 -> 9691.4148 | L4: ='Cost of sales'!L8 -> 10082.472
A5: Depreciation and amortization | B5: 2300 | C5: 2323 | D5: 2185 | E5: 2108 | F5: 2576 | G5: 2521 | H5: =H31*'Balance sheet'!H13 -> 2795.8649 | I5: =I31*'Balance sheet'!I13 -> 2977.0419 | J5: =J31*'Balance sheet'!J13 -> 3165.3245 | K5: =K31*'Balance sheet'!K13 -> 3361.0979 | L5: =L31*'Balance sheet'!L13 -> 3564.7709
A6: Reclamation and remediation | B6: 366 | C6: 1846 | D6: 921 | E6: 1533 | F6: 328 | G6: 249 | H6: =H32*'Balance sheet'!H32 -> 344.98376 | I6: =I32*'Balance sheet'!I32 -> 339.53412 | J6: =J32*'Balance sheet'!J32 -> 381.85114 | K6: =K32*'Balance sheet'!K32 -> 381.96571 | L6: =L32*'Balance sheet'!L32 -> 405.2212
A7: Exploration | B7: 187 | C7: 209 | D7: 231 | E7: 265 | F7: 266 | G7: 243 | H7: =H33*H3 -> 254.01909 | I7: =I33*I3 -> 290.72751 | J7: =J33*J3 -> 301.02774 | K7: =K33*K3 -> 311.78058 | L7: =L33*L3 -> 319.6267
A8: Advanced projects, research and development | B8: 122 | C8: 154 | D8: 229 | E8: 200 | F8: 197 | G8: 166 | H8: 285 | I8: 150 | J8: 150 | K8: 150 | L8: 150 | N8: caterpillar project
A9: General and administrative | B9: 269 | C9: 259 | D9: 276 | E9: 299 | F9: 442 | G9: 382 | H9: =H35*H4 -> 335.74871 | I9: =I35*I4 -> 384.76352 | J9: =J35*J4 -> 399.85361 | K9: =K35*K4 -> 415.76169 | L9: =L35*L4 -> 432.53805
A10: Impairment charges | B10: 49 | C10: 25 | D10: 1320 | E10: 1891 | F10: 78 | G10: 842 | H10: 0 | I10: 0 | J10: 0 | K10: 0 | L10: 0
A11: Loss on assets held for sale | B11: 0 | C11: 571 | D11: 0 | E11: 0 | F11: 1114 | G11: -1066 | H11: 0 | I11: 0 | J11: 0 | K11: 0 | L11: 0
A12: Other expense, net | B12: 384 | C12: 143 | D12: 82 | E12: 517 | F12: 191 | G12: 286 | H12: =G12 -> 286 | I12: =H12 -> 286 | J12: =I12 -> 286 | K12: =J12 -> 286 | L12: =K12 -> 286
A13: Total costs and expenses | B13: =SUM(B4:B12) -> 8691 | C13: =SUM(C4:C12) -> 10965 | D13: =SUM(D4:D12) -> 11712 | E13: =SUM(E4:E12) -> 13512 | F13: =SUM(F4:F12) -> 14155 | G13: =SUM(G4:G12) -> 11708 | H13: =SUM(H4:H12) -> 12127.927 | I13: =SUM(I4:I12) -> 13396.914 | ... L13: =SUM(L4:L12) -> 15240.629
A14: Other income (loss), net | B14: -32 | C14: -87 | D14: -27 | E14: -88 | F14: 425 | G14: 6 | H14: 0 | I14: 0 | J14: 0 | K14: 0 | L14: 0 | N14: note 8
A15: Gain on asset and investment sales, net | B15: 677 | C15: 212 | D15: 35 | G15: 604 | H15: 0 | I15: 0 | J15: 0 | K15: 0 | L15: 0
A16: Interest expense, net | B16: -308 | C16: -274 | D16: -227 | E16: -243 | F16: -375 | G16: -229 | H16: =H42*('Balance sheet'!H30+'Balance sheet'!H26) -> -173.6527 | I16: =I42*('Balance sheet'!I30+'Balance sheet'!I26) -> -204.66867 | J16: =J42*('Balance sheet'!J30+'Balance sheet'!J26) -> -234.68612 | K16: =K42*('Balance sheet'!K30+'Balance sheet'!K26) -> -263.8924 | L16: =L42*('Balance sheet'!L30+'Balance sheet'!L26) -> -291.15132
A17: Income (loss) before income and mining tax and other items | B17: =B3-B13+B14+B15+B16 -> 3143 | C17: =C3-C13+C14+C15+C16 -> 1108 | D17: =D3-D13+D14+D15+D16 -> -16 | E17: =E3-E13+E14+E15+E16 -> -2031 | F17: =F3-F13+F14+F15+F16 -> 4577 | G17: =G3-G13+G14+G15+G16 -> 11342 | H17: =H3-H13+H14+H15+H16 -> 15309.191 | I17: =I3-I13+I14+I15+I16 -> 17999.234 | ... L17: =L3-L13+L14+L15+L16 -> 19210.253
A18: Income and mining tax benefit (expense) | B18: -704 | C18: -1098 | D18: -455 | E18: -526 | F18: -1397 | G18: -4596 | H18: =H17*H44 -> -5052.0332 | I18: =I17*I44 -> -5939.7473 | J18: =J17*J44 -> -6098.7519 | K18: =K17*K44 -> -6279.0027 | L18: =L17*L44 -> -6339.3835
A19: Equity income (loss) of affiliates | B19: 189 | C19: 166 | D19: 107 | E19: 63 | F19: 133 | G19: 421 | H19: =AVERAGE(B19:G19) -> 179.83333 | I19: =H19 -> 179.83333 | J19: =I19 -> 179.83333 | K19: =J19 -> 179.83333 | L19: =K19 -> 179.83333
A20: Net income (loss) from continuing operations | B20: =SUM(B17:B19) -> 2628 | C20: =SUM(C17:C19) -> 176 | D20: =SUM(D17:D19) -> -364 | E20: =SUM(E17:E19) -> -2494 | F20: =SUM(F17:F19) -> 3313 | G20: =SUM(G17:G19) -> 7167 | H20: =SUM(H17:H19) -> 10436.992 | I20: =SUM(I17:I19) -> 12239.32 | ... L20: =SUM(L17:L19) -> 13050.703
A21: Net income (loss) from discontinued operations | B21: 163 | C21: 57 | D21: 30 | E21: 27 | F21: 68 | G21: 0 | H21: 0 | I21: 0 | J21: 0 | K21: 0 | L21: 0
A22: Net income (loss) | B22: =B20+B21 -> 2791 | C22: =C20+C21 -> 233 | D22: =D20+D21 -> -334 | E22: =E20+E21 -> -2467 | F22: =F20+F21 -> 3381 | G22: =G20+G21 -> 7167 | H22: =H20+H21 -> 10436.992 | I22: =I20+I21 -> 12239.32 | ... L22: =L20+L21 -> 13050.703
A23: Net loss (income) attributable to noncontrolling interests | B23: 38 | C23: 933 | D23: -60 | E23: -27 | F23: -33 | G23: -82 | H23: =H49*H17 -> -5.8470112 | I23: =I49*I17 -> -6.8744143 | J23: =J49*J17 -> -7.0584395 | K23: =K49*K17 -> -7.2670542 | L23: =L49*L17 -> -7.3369365
A24: Net income (loss) attributable to stockholders | B24: 2829 | C24: 1166 | D24: -429 | E24: -2494 | F24: 3348 | G24: =G20+G21+G23 -> 7085 | H24: =H20+H21+H23 -> 10431.145 | I24: =I20+I21+I23 -> 12232.446 | J24: =J20+J21+J23 -> 12555.089 | K24: =K20+K21+K23 -> 12920.844 | L24: =L20+L21+L23 -> 13043.366
A26: Assumptions
A28: Particulars | B28: 2020 | C28: 2021 | D28: 2022 | E28: 2023 | F28: 2024 | G28: 2025 | H28: 2026E | I28: 2027E | J28: 2028E | K28: 2029E | L28: 2030E
A29: Sales | N29: Revenue sheet
A30: Costs applicable to sales | N30: Cost of sales sheet
A31: Depreciation and amortization | B31: =B5/'Balance sheet'!B13 -> 0.09472427 | C31: =C5/'Balance sheet'!C13 -> 0.096294147 | D31: =D5/'Balance sheet'!D13 -> 0.090765588 | E31: =E5/'Balance sheet'!E13 -> 0.056119053 | F31: =F5/'Balance sheet'!F13 -> 0.07678779 | G31: =G5/'Balance sheet'!G13 -> 0.075682978 | H31: 0.0758 | I31: =H31 -> 0.0758 | J31: =I31 -> 0.0758 | K31: =J31 -> 0.0758 | L31: =K31 -> 0.0758 | N31: Held at a stable percentage of sales reflecting a steady-state asset base post-divestitures.
A32: Reclamation and remediation | B32: =B6/'Balance sheet'!B32 -> 0.095861708 | C32: =C6/'Balance sheet'!C32 -> 0.31615003 | D32: =D6/'Balance sheet'!D32 -> 0.14001216 | E32: =E6/'Balance sheet'!E32 -> 0.18770662 | F32: =F6/'Balance sheet'!F32 -> 0.051298092 | G32: =G6/'Balance sheet'!G32 -> 0.039542639 | H32: 0.0551 | I32: =AVERAGE(H32,G32) -> 0.04732132 | J32: =AVERAGE(I32,H32) -> 0.05121066 | K32: =AVERAGE(J32,I32) -> 0.04926599 | L32: =AVERAGE(K32,J32) -> 0.050238325 | N32: % of rand r liabilities
A33: Exploration | B33: =B7/B3 -> 0.016265113 | C33: =C7/C3 -> 0.017100311 | D33: =D7/D3 -> 0.019387327 | E33: =E7/E3 -> 0.022434812 | F33: =F7/F3 -> 0.014238304 | G33: =G7/G3 -> 0.010719485 | H33: 0.0092 | I33: =H33 -> 0.0092 | J33: =I33 -> 0.0092 | K33: =J33 -> 0.0092 | L33: =K33 -> 0.0092 | N33: percentage of sales
A34: Advanced projects, research and development | N34: Step-down after 2025 as major development projects move into construction or production phases.
A35: General and administrative | B35: =B9/B4 -> 0.053649781 | C35: =C9/C4 -> 0.047654094 | D35: =D9/D4 -> 0.042671614 | E35: =E9/E4 -> 0.044633527 | F35: =F9/F4 -> 0.049313846 | G35: =G9/G4 -> 0.04724799 | H35: 0.0429 | I35: 0.0429 | J35: 0.0429 | K35: 0.0429 | L35: 0.0429 | N35: % of cost of sales
A36: Impairment charges | N36: Assumed zero beyond near term as impairments are non-recurring and not part of base-case earnings.
A37: Loss on assets held for sale | N37: Modeled only in transition years and eliminated thereafter as divestiture program concludes.
A38: Other expense, net | N38: Held constant to reflect recurring miscellaneous costs without forecasting episodic volatility.
A39: Total costs and expenses
A40: Other income (loss), net | N40: Normalized to zero long term given its volatile and non-core nature.
A41: Gain on asset and investment sales, net | N41: Included only where divestitures are explicitly assumed and set to zero thereafter.
A42: Interest expense, net | B42: =B16/('Balance sheet'!B30+'Balance sheet'!B26) -> -0.051069474 | C42: =C16/('Balance sheet'!C30+'Balance sheet'!C26) -> -0.048478415 | D42: =D16/('Balance sheet'!D30+'Balance sheet'!D26) -> -0.040746724 | E42: =E16/('Balance sheet'!E30+'Balance sheet'!E26) -> -0.027383367 | F42: =F16/('Balance sheet'!F30+'Balance sheet'!F26) -> -0.044242567 | G42: =G16/('Balance sheet'!G30+'Balance sheet'!G26) -> -0.044770283 | H42: -0.029 | I42: -0.029 | J42: -0.029 | K42: -0.029 | L42: -0.029 | N42: % of total debt (net rate ~2.9%), aligned with 2026 guidance of $175M interest expense (net of $175M capitalized interest).
A43: Income (loss) before income and mining tax and other items
A44: Income and mining tax benefit (expense) | B44: =B18/B17 -> -0.22398982 | C44: =C18/C17 -> -0.99097473 | D44: =D18/D17 -> 28.4375 | E44: =E18/E17 -> 0.25898572 | F44: =F18/F17 -> -0.30522176 | G44: =G18/G17 -> -0.40521954 | H44: -0.33 | I44: -0.33 | J44: -0.33 | K44: -0.33 | L44: -0.33 | N44: Applied a normalized effective tax rate reflecting steady-state jurisdictional mix.
A45: Equity income (loss) of affiliates | N45: Modeled as a stable contribution reflecting mature joint-venture operations.
A46: Net income (loss) from continuing operations
A47: Net income (loss) from discontinued operations | N47: Assumed zero as discontinued assets have been divested.
A48: Net income (loss)
A49: Net loss (income) attributable to noncontrolling interests | B49: =B23/B17 -> 0.01209036 | C49: =C23/C17 -> 0.84205776 | D49: =D23/D17 -> 3.75 | E49: =E23/E17 -> 0.013293944 | F49: =F23/F17 -> -0.0072099629 | G49: =G23/G17 -> -0.0072297655 | H49: =AVERAGE(E49:G49) -> -0.00038192815 | I49: =H49 -> -0.00038192815 | J49: =I49 -> -0.00038192815 | K49: =J49 -> -0.00038192815 | L49: =K49 -> -0.00038192815 | N49: Estimated as a small percentage of consolidated earnings based on historical ownership structures.
A50: Net income (loss) attributable to stockholders

Sheet Balance sheet
A2: what
A3: Particulars | B3: 2020 | C3: 2021 | D3: 2022 | E3: 2023 | F3: 2024 | G3: 2025 | H3: 2026E | I3: 2027E | J3: 2028E | K3: 2029E | L3: 2030E
A4: Cash and cash equivalents | B4: 5540 | C4: 4992 | D4: 2877 | E4: 3002 | F4: 3619 | G4: 7647 | H4: ='Cash flow'!C59 -> 9858.2487 | I4: ='Cash flow'!D59 -> 15649.903 | J4: ='Cash flow'!E59 -> 20673.133 | K4: ='Cash flow'!F59 -> 25403.827 | L4: ='Cash flow'!G59 -> 29694.201
A5: Trade receivables | B5: 449 | C5: 337 | D5: 366 | E5: 734 | F5: 1056 | G5: 1067 | H5: =H55*'Income statement'!H3 -> 1380.5386 | I5: =I55*'Income statement'!I3 -> 1580.0408 | J5: =J55*'Income statement'!J3 -> 1636.0203 | K5: =K55*'Income statement'!K3 -> 1694.4597 | L5: =L55*'Income statement'!L3 -> 1737.1017 | N5: schedules
A6: Investments (current / time deposits) | B6: 290 | C6: 82 | D6: 880 | E6: 23 | F6: 21 | G6: 594 | H6: 1000 | I6: 1500 | J6: 2000 | K6: 2500 | L6: 3000 | N6: increase reflecting cash buildup.
A7: Inventories | B7: 963 | C7: 930 | D7: 979 | E7: 1663 | F7: 1423 | G7: 1512 | H7: =Schedules!H10 -> 1440.7713 | I7: =Schedules!I10 -> 1620.3455 | J7: =Schedules!J10 -> 1665.5201 | K7: =Schedules!K10 -> 1713.2921 | L7: =Schedules!L10 -> 1763.8155 | N7: schedules
A8: Stockpiles and ore on leach pads (current) | B8: 827 | C8: 857 | D8: 774 | E8: 979 | F8: 761 | G8: 1177 | H8: =Schedules!H18 -> 971.03009 | I8: =Schedules!I18 -> 1112.7874 | J8: =Schedules!J18 -> 1156.43 | K8: =Schedules!K18 -> 1202.4383 | L8: =Schedules!L18 -> 1250.9578 | N8: schedules(% of cost of sales)
A9: Derivative assets (current) | B9: 0 | C9: 0 | D9: 0 | E9: 198 | F9: 0 | G9: 0 | H9: 0 | I9: 0 | J9: 0 | K9: 0 | L9: 0
A10: Other current assets | B10: 436 | C10: 498 | D10: 639 | E10: 913 | F10: 786 | G10: 1069 | H10: =H60*'Income statement'!H3 -> 1380.5386 | I10: =I60*'Income statement'!I3 -> 1580.0408 | J10: =J60*'Income statement'!J3 -> 1636.0203 | K10: =K60*'Income statement'!K3 -> 1694.4597 | L10: =L60*'Income statement'!L3 -> 1737.1017 | N10: % of sales
A11: Assets held for sale (current) | B11: 0 | C11: 0 | D11: 0 | E11: 0 | F11: 4609 | G11: 0 | H11: 0 | I11: 0 | J11: 0 | K11: 0 | L11: 0
A12: Current assets | B12: =SUM(B4:B11) -> 8505 | C12: =SUM(C4:C11) -> 7696 | D12: =SUM(D4:D11) -> 6515 | E12: =SUM(E4:E11) -> 7512 | F12: =SUM(F4:F11) -> 12275 | G12: =SUM(G4:G11) -> 13066 | H12: =SUM(H4:H11) -> 16031.127 | I12: =SUM(I4:I11) -> 23043.118 | ... L12: =SUM(L4:L11) -> 39183.178
A13: Property, plant and mine development, net | B13: 24281 | C13: 24124 | D13: 24073 | E13: 37563 | F13: 33547 | G13: 33310 | H13: =Schedules!H44 -> 36884.762 | I13: =Schedules!I44 -> 39274.959 | J13: =Schedules!J44 -> 41758.898 | K13: =Schedules!K44 -> 44341.66 | L13: =Schedules!L44 -> 47028.639 | N13: schedules
A14: Investments (non-current) | B14: 3197 | C14: 3243 | D14: 3278 | E14: 4143 | F14: 4471 | G14: 4186 | H14: =Schedules!H46 -> 3208.7872 | I14: =Schedules!I46 -> 3677.2271 | J14: =Schedules!J46 -> 3821.4448 | K14: =Schedules!K46 -> 3973.4801 | L14: =Schedules!L46 -> 4133.8135 | N14: schedules
A15: Stockpiles and ore on leach pads (non-current) | B15: 1705 | C15: 1775 | D15: 1716 | E15: 1935 | F15: 2266 | G15: 2410 | H15: =Schedules!H23 -> 1851.2441 | I15: =Schedules!I23 -> 2021.5613 | J15: =Schedules!J23 -> 2016.1719 | K15: =Schedules!K23 -> 2011.3404 | L15: =Schedules!L23 -> 2007.0683 | N15: schedules
A16: Deferred income tax assets | B16: 337 | C16: 269 | D16: 173 | E16: 268 | F16: 124 | G16: 45 | H16: =G16 -> 45 | I16: =H16 -> 45 | J16: =I16 -> 45 | K16: =J16 -> 45 | L16: =K16 -> 45 | N16: kept constant at 2024 as past trend is similar
A17: Goodwill | B17: 2771 | C17: 2771 | D17: 1971 | E17: 3001 | F17: 2658 | G17: 2658 | H17: =G17 -> 2658 | I17: =H17 -> 2658 | J17: =I17 -> 2658 | K17: =J17 -> 2658 | L17: =K17 -> 2658
A18: Derivative assets (non-current) | B18: 0 | C18: 0 | D18: 0 | E18: 444 | F18: 142 | H18: 0 | I18: =H18 -> 0 | J18: =I18 -> 0 | K18: =J18 -> 0 | L18: =K18 -> 0
A19: Other non-current assets | B19: 573 | C19: 686 | D19: 756 | E19: 640 | F19: 866 | G19: 1446 | H19: =H69*H32 -> 1437.7443 | I19: =I69*I32 -> 1647.6357 | J19: =J69*J32 -> 1712.2545 | K19: =K69*K32 -> 1780.3762 | L19: =L69*L32 -> 1852.2159
A20: Total assets | B20: =SUM(B12:B19) -> 41369 | C20: =SUM(C12:C19) -> 40564 | D20: =SUM(D12:D19) -> 38482 | E20: =SUM(E12:E19) -> 55506 | F20: =SUM(F12:F19) -> 56349 | G20: =SUM(G12:G19) -> 57121 | H20: =SUM(H12:H19) -> 62116.665 | I20: =SUM(I12:I19) -> 72367.501 | ... L20: =SUM(L12:L19) -> 96907.915
A22: Accounts payable | B22: 493 | C22: 518 | D22: 633 | E22: 960 | F22: 843 | G22: 816 | H22: =H72*'Income statement'!H3 -> 993.88544 | I22: =I72*'Income statement'!I3 -> 1137.5123 | J22: =J72*'Income statement'!J3 -> 1177.8134 | K22: =K72*'Income statement'!K3 -> 1219.8854 | L22: =L72*'Income statement'!L3 -> 1250.5845 | N22: Projected as a percentage of cost of sales, reflecting supplier payment cycles.
A23: Employee-related benefits (current) | B23: 380 | C23: 386 | D23: 399 | E23: 551 | F23: 630 | G23: 898 | H23: =H73*'Income statement'!H9 -> 789.27315 | I23: =I73*'Income statement'!I9 -> 904.49644 | J23: =J73*'Income statement'!J9 -> 939.97001 | K23: =K73*'Income statement'!K9 -> 977.3665 | L23: =L73*'Income statement'!L9 -> 1016.8041
A24: Income and mining taxes payable | B24: 657 | C24: 384 | D24: 199 | E24: 88 | F24: 381 | G24: 1188 | H24: =H74*'Income statement'!H18 -> 1176.3041 | I24: =I74*'Income statement'!I18 -> 1382.9975 | J24: =J74*'Income statement'!J18 -> 1420.0198 | K24: =K74*'Income statement'!K18 -> 1461.9889 | L24: =L74*'Income statement'!L18 -> 1476.0479
A25: Lease and other financing obligations (current) | B25: 106 | C25: 106 | D25: 96 | E25: 114 | F25: 107 | G25: 118 | H25: 96 | I25: 77 | J25: 71 | K25: 46 | L25: 252 | N25: Projected using contractual amortization schedules.
A26: Debt (current) | B26: 551 | C26: 87 | D26: 0 | E26: 1923 | F26: 924 | G26: 0 | H26: 0 | I26: 0 | J26: 0 | K26: 0 | L26: 0 | N26: Reflects scheduled maturities and refinancing assumptions.
A27: Other current liabilities | B27: 1182 | C27: 1173 | D27: 1599 | E27: 2362 | F27: 2481 | G27: 2692 | H27: =H77*'Income statement'!H4 -> 2510.5678 | I27: =I77*'Income statement'!I4 -> 2877.077 | J27: =J77*'Income statement'!J4 -> 2989.9135 | K27: =K77*'Income statement'!K4 -> 3108.8665 | L27: =L77*'Income statement'!L4 -> 3234.312 | N27: Projected as a percentage of cost of sales, based on historical averages.
A28: Liabilities held for sale (current) | B28: 0 | C28: 0 | D28: 0 | E28: 0 | F28: 2177 | G28: 0 | H28: 0 | I28: 0 | J28: 0 | K28: 0 | L28: 0
A29: Current liabilities | B29: =SUM(B22:B28) -> 3369 | C29: =SUM(C22:C28) -> 2654 | D29: =SUM(D22:D28) -> 2926 | E29: =SUM(E22:E28) -> 5998 | F29: =SUM(F22:F28) -> 7543 | G29: =SUM(G22:G28) -> 5712 | H29: =SUM(H22:H28) -> 5566.0305 | I29: =SUM(I22:I28) -> 6379.0832 | ... L29: =SUM(L22:L28) -> 7229.7485
A30: Debt (non-current) | B30: 5480 | C30: 5565 | D30: 5571 | E30: 6951 | F30: 7552 | G30: 5115 | H30: =H80*H44 -> 5988.024 | I30: =I80*I44 -> 7057.5403 | J30: =J80*J44 -> 8092.6248 | K30: =K80*K44 -> 9099.7379 | L30: =L80*L44 -> 10039.701 | N30: Projected as 15% of stockholders' equity (D/E ratio), consistent with 2025 post-deleveraging level.
A31: Lease and other financing obligations (non-current) | B31: 565 | C31: 544 | D31: 465 | E31: 448 | F31: 389 | G31: 356 | H31: =G31-H25 -> 260 | I31: =H31-I25 -> 183 | J31: =I31-J25 -> 112 | K31: =J31-K25 -> 66 | L31: 0
A32: Reclamation and remediation liabilities | B32: 3818 | C32: 5839 | D32: 6578 | E32: 8167 | F32: 6394 | G32: 6297 | H32: =Schedules!H35 -> 6261.0482 | I32: =Schedules!I35 -> 7175.0772 | J32: =Schedules!J35 -> 7456.4776 | K32: =Schedules!K35 -> 7753.1318 | L32: =Schedules!L35 -> 8065.9776 | N32: Projected to grow annually reflecting inflation, mine expansion, and updated closure cost estimates.
A33: Deferred income tax liabilities | B33: 2073 | C33: 2144 | D33: 1809 | E33: 2987 | F33: 2820 | G33: 4045 | H33: =H83*'Income statement'!H3 -> 2484.9694 | I33: =I83*'Income statement'!I3 -> 2844.0735 | J33: =J83*'Income statement'!J3 -> 2944.8366 | K33: =K83*'Income statement'!K3 -> 3050.0274 | L33: =L83*'Income statement'!L3 -> 3126.783 | N33: Modeled as a percentage of sales and accelerated tax depreciation.
A34: Employee-related benefits (non-current) | B34: 493 | C34: 439 | D34: 342 | E34: 655 | F34: 555 | G34: 634 | H34: =H84*'Income statement'!H9 -> 557.23739 | I34: =I84*'Income statement'!I9 -> 638.58657 | J34: =J84*'Income statement'!J9 -> 663.63139 | K34: =K84*'Income statement'!K9 -> 690.03381 | L34: =L84*'Income statement'!L9 -> 717.87729
A35: Silver streaming agreement | B35: 993 | C35: 910 | D35: 828 | E35: 779 | F35: 699 | G35: 598 | H35: =G35-96 -> 502 | I35: =H35-96 -> 406 | J35: =I35-96 -> 310 | K35: =J35-96 -> 214 | L35: =K35-96 -> 118 | N35: Amortized over the remaining life of the streaming contracts.
A36: Other non-current liabilities | B36: 699 | C36: 608 | D36: 430 | E36: 316 | F36: 288 | G36: 322 | H36: =H86*'Income statement'!H3 -> 392.19499 | I36: =I86*'Income statement'!I3 -> 448.87128 | J36: =J86*'Income statement'!J3 -> 464.7744 | K36: =K86*'Income statement'!K3 -> 481.37635 | L36: =L86*'Income statement'!L3 -> 493.49043 | N36: Projected as a percentage of revenue, consistent with historical behavior.
A37: Total liabilities | B37: =SUM(B29:B36) -> 17490 | C37: =SUM(C29:C36) -> 18703 | D37: =SUM(D29:D36) -> 18949 | E37: =SUM(E29:E36) -> 26301 | F37: =SUM(F29:F36) -> 26240 | G37: =SUM(G29:G36) -> 23079 | H37: =SUM(H29:H36) -> 22011.505 | I37: =SUM(I29:I36) -> 25132.232 | ... L37: =SUM(L29:L36) -> 29791.577
A39: Common stock | B39: 1287 | C39: 1276 | D39: 1279 | E39: 1854 | F39: 1813 | G39: 1753 | H39: 1760 | I39: 1760 | J39: 1760 | K39: 1760 | L39: 1760 | N39: Held constant, assuming no issuance of new shares.
A40: Treasury stock | B40: -168 | C40: -200 | D40: -239 | E40: -264 | F40: -278 | G40: -301 | H40: =+-'Changes in Equity'!H28 -> -328.61077 | I40: =+-'Changes in Equity'!I28 -> -391.8124 | J40: =+-'Changes in Equity'!J28 -> -457.25322 | K40: =+-'Changes in Equity'!K28 -> -525.0316 | L40: =+-'Changes in Equity'!L28 -> -629.2577 | N40: Increased gradually, reflecting ongoing share repurchase activity.
A41: Additional paid-in capital | B41: 18103 | C41: 17981 | D41: 17369 | E41: 30419 | F41: 29808 | G41: 28847 | H41: =+'Changes in Equity'!H37 -> 27604.515 | I41: =+'Changes in Equity'!I37 -> 26182.479 | J41: =+'Changes in Equity'!J37 -> 24710.06 | K41: =+'Changes in Equity'!K37 -> 23185.047 | L41: =+'Changes in Equity'!L37 -> 21621.655 | N41: Adjusted for share repurchases and equity compensation.
A42: Accumulated other comprehensive income (loss) | B42: -216 | C42: -133 | D42: 29 | E42: 14 | F42: -95 | G42: 137 | H42: =G42 -> 137 | I42: =+H42 -> 137 | J42: =+I42 -> 137 | K42: =+J42 -> 137 | L42: =+K42 -> 137 | N42: Held constant, assuming stable FX and pension assumptions.
A43: Retained earnings (accumulated deficit) | B43: 4002 | C43: 3098 | D43: 916 | E43: -2996 | F43: -1320 | G43: 3431 | H43: =+'Changes in Equity'!H21 -> 10747.255 | I43: =+'Changes in Equity'!I21 -> 19362.603 | J43: =+'Changes in Equity'!J21 -> 27801.025 | K43: =+'Changes in Equity'!K21 -> 36107.904 | L43: =+'Changes in Equity'!L21 -> 44041.94 | N43: Rolled forward based on projected net income less dividends.
A44: Newmont stockholders’ equity | B44: =+B39+B40+B41+B42+B43 -> 23008 | C44: =+C39+C40+C41+C42+C43 -> 22022 | D44: =+D39+D40+D41+D42+D43 -> 19354 | E44: =+E39+E40+E41+E42+E43 -> 29027 | F44: =+F39+F40+F41+F42+F43 -> 29928 | G44: =+G39+G40+G41+G42+G43 -> 33867 | H44: =+H39+H40+H41+H42+H43 -> 39920.16 | I44: =+I39+I40+I41+I42+I43 -> 47050.269 | ... L44: =+L39+L40+L41+L42+L43 -> 66931.338
A45: Contingently Redeemable Noncontrolling Interest | B45: 34 | C45: 48 | D45: 0 | E45: 0 | F45: 0 | G45: 0 | H45: 0 | I45: 0 | J45: 0 | K45: 0 | L45: 0
A46: Noncontrolling interests | B46: 837 | C46: -209 | D46: 179 | E46: 178 | F46: 181 | G46: 175 | H46: 185 | I46: 185 | J46: 185 | K46: 185 | L46: 185 | N46: Held Constant
A47: Total equity | B47: =+B44+B45+B46 -> 23879 | C47: =+C44+C45+C46 -> 21861 | D47: =+D44+D45+D46 -> 19533 | E47: =+E44+E45+E46 -> 29205 | F47: =+F44+F45+F46 -> 30109 | G47: =+G44+G45+G46 -> 34042 | H47: =+H44+H45+H46 -> 40105.16 | I47: =+I44+I45+I46 -> 47235.269 | ... L47: =+L44+L45+L46 -> 67116.338
A48: Total liabilities and equity | B48: =+B37+B47 -> 41369 | C48: =+C37+C47 -> 40564 | D48: =+D37+D47 -> 38482 | E48: =+E37+E47 -> 55506 | F48: =+F37+F47 -> 56349 | G48: =+G37+G47 -> 57121 | H48: =+H37+H47 -> 62116.665 | I48: =+I37+I47 -> 72367.501 | ... L48: =+L37+L47 -> 96907.915
A51: ASSUMPTIONS
A53: Particulars | B53: 2020 | C53: 2021 | D53: 2022 | E53: 2023 | F53: 2024 | G53: 2025 | H53: 2026E | I53: 2027E | J53: 2028E | K53: 2029E | L53: 2030E
A54: Cash and cash equivalents
A55: Trade receivables | B55: =B5/'Income statement'!B3 -> 0.039053666 | C55: =C5/'Income statement'!C3 -> 0.027573229 | D55: =D5/'Income statement'!D3 -> 0.030717583 | E55: =E5/'Income statement'!E3 -> 0.062140196 | F55: =F5/'Income statement'!F3 -> 0.056524997 | G55: =G5/'Income statement'!G3 -> 0.047068684 | H55: 0.05 | I55: 0.05 | J55: 0.05 | K55: 0.05 | L55: 0.05
A56: Investments (current / time deposits)
A57: Inventories
A58: Stockpiles and ore on leach pads (current)
A59: Derivative assets (current)
A60: Other current assets | B60: =B10/'Income statement'!B3 -> 0.037922936 | C60: =C10/'Income statement'!C3 -> 0.040746195 | D60: =D10/'Income statement'!D3 -> 0.053629878 | E60: =E10/'Income statement'!E3 -> 0.077294277 | F60: =F10/'Income statement'!F3 -> 0.042072583 | G60: =G10/'Income statement'!G3 -> 0.04715691 | H60: 0.05 | I60: 0.05 | J60: 0.05 | K60: 0.05 | L60: 0.05
A61: Assets held for sale (current)
A62: Current assets
A63: Property, plant and mine development, net
A64: Investments (non-current)
A65: Stockpiles and ore on leach pads (non-current)
A66: Deferred income tax assets
A67: Goodwill
A68: Derivative assets (non-current)
A69: Other non-current assets | B69: =B19/B32 -> 0.15007858 | C69: =C19/C32 -> 0.11748587 | D69: =D19/D32 -> 0.11492855 | E69: =E19/E32 -> 0.078364148 | F69: =F19/F32 -> 0.13543947 | G69: =G19/G32 -> 0.22963316 | H69: =G69 -> 0.22963316 | I69: =H69 -> 0.22963316 | J69: =I69 -> 0.22963316 | K69: =J69 -> 0.22963316 | L69: =K69 -> 0.22963316
A70: Total assets
A72: Accounts payable | B72: =B22/'Income statement'!B3 -> 0.042880752 | C72: =C22/'Income statement'!C3 -> 0.042382589 | D72: =D22/'Income statement'!D3 -> 0.053126311 | E72: =E22/'Income statement'!E3 -> 0.081273281 | F72: =F22/'Income statement'!F3 -> 0.045123648 | G72: =G22/'Income statement'!G3 -> 0.035996294 | H72: =G72 -> 0.035996294 | I72: =H72 -> 0.035996294 | J72: =I72 -> 0.035996294 | K72: =J72 -> 0.035996294 | L72: =K72 -> 0.035996294
A73: Employee-related benefits (current) | B73: =B23/'Income statement'!B9 -> 1.4126394 | C73: =C23/'Income statement'!C9 -> 1.4903475 | D73: =D23/'Income statement'!D9 -> 1.4456522 | E73: =E23/'Income statement'!E9 -> 1.8428094 | F73: =F23/'Income statement'!F9 -> 1.4253394 | G73: =G23/'Income statement'!G9 -> 2.3507853 | H73: =G73 -> 2.3507853 | I73: =H73 -> 2.3507853 | J73: =I73 -> 2.3507853 | K73: =J73 -> 2.3507853 | L73: =K73 -> 2.3507853
A74: Income and mining taxes payable | B74: =B24/'Income statement'!B18 -> -0.93323864 | C74: =C24/'Income statement'!C18 -> -0.34972678 | D74: =D24/'Income statement'!D18 -> -0.43736264 | E74: =E24/'Income statement'!E18 -> -0.16730038 | F74: =F24/'Income statement'!F18 -> -0.27272727 | G74: =G24/'Income statement'!G18 -> -0.25848564 | H74: =AVERAGE(E74:G74) -> -0.23283776 | I74: =H74 -> -0.23283776 | J74: =I74 -> -0.23283776 | K74: =J74 -> -0.23283776 | L74: =K74 -> -0.23283776
A75: Lease and other financing obligations (current)
A76: Debt (current)
A77: Other current liabilities | B77: =B27/'Income statement'!B4 -> 0.23573993 | C77: =C27/'Income statement'!C4 -> 0.21582337 | D77: =D27/'Income statement'!D4 -> 0.24721707 | E77: =E27/'Income statement'!E4 -> 0.35258994 | F77: =F27/'Income statement'!F4 -> 0.27680464 | G77: =G27/'Income statement'!G4 -> 0.33296228 | H77: =AVERAGE(E77:G77) -> 0.32078562 | I77: =H77 -> 0.32078562 | J77: =I77 -> 0.32078562 | K77: =J77 -> 0.32078562 | L77: =K77 -> 0.32078562
A78: Liabilities held for sale (current)
A79: Current liabilities
A80: Debt (non-current) | B80: =B30/B13 -> 0.22569087 | C80: =C30/C13 -> 0.23068314 | D80: =D30/D13 -> 0.23142109 | E80: =E30/E13 -> 0.18504912 | F80: =F30/F13 -> 0.225117 | G80: =G30/G13 -> 0.15355749 | H80: 0.15 | I80: 0.15 | J80: 0.15 | K80: 0.15 | L80: 0.15
A81: Lease and other financing obligations (non-current)
A82: Reclamation and remediation liabilities
A83: Deferred income tax liabilities | B83: =B33/'Income statement'!B3 -> 0.18030791 | C83: =C33/'Income statement'!C3 -> 0.17542137 | D83: =D33/'Income statement'!D3 -> 0.15182543 | E83: =E33/'Income statement'!E3 -> 0.25287843 | F83: =F33/'Income statement'!F3 -> 0.15094744 | G83: =G33/'Income statement'!G3 -> 0.17843751 | H83: 0.09 | I83: 0.09 | J83: 0.09 | K83: 0.09 | L83: 0.09
A84: Employee-related benefits (non-current) | B84: =B34/'Income statement'!B9 -> 1.8327138 | C84: =C34/'Income statement'!C9 -> 1.6949807 | D84: =D34/'Income statement'!D9 -> 1.2391304 | E84: =E34/'Income statement'!E9 -> 2.1906355 | F84: =F34/'Income statement'!F9 -> 1.2556561 | G84: =G34/'Income statement'!G9 -> 1.6596859 | H84: =G84 -> 1.6596859 | I84: =H84 -> 1.6596859 | J84: =I84 -> 1.6596859 | K84: =J84 -> 1.6596859 | L84: =K84 -> 1.6596859
A85: Silver streaming agreement
A86: Other non-current liabilities | B86: =B36/'Income statement'!B3 -> 0.060798469 | C86: =C36/'Income statement'!C3 -> 0.049746359 | D86: =D36/'Income statement'!D3 -> 0.036088963 | E86: =E36/'Income statement'!E3 -> 0.026752455 | F86: =F36/'Income statement'!F3 -> 0.015415908 | G86: =G36/'Income statement'!G3 -> 0.01420442 | H86: =G86 -> 0.01420442 | I86: =H86 -> 0.01420442 | J86: =I86 -> 0.01420442 | K86: =J86 -> 0.01420442 | L86: =K86 -> 0.01420442
A87: Total liabilities
A89: Common stock
A90: Treasury stock
A91: Additional paid-in capital
A92: Accumulated other comprehensive income (loss)
A93: Retained earnings (accumulated deficit)
A94: Newmont stockholders’ equity
A95: Noncontrolling interests
A96: Total equity
A97: Total liabilities and equity

Sheet Cash flow
A2: NET INCOME | B2: =+'Income statement'!G24 -> 7085 | C2: =+'Income statement'!H24 -> 10431.145 | D2: =+'Income statement'!I24 -> 12232.446 | E2: =+'Income statement'!J24 -> 12555.089 | F2: =+'Income statement'!K24 -> 12920.844 | G2: =+'Income statement'!L24 -> 13043.366
A4: Particulars | B4: 2025A | C4: 2026E | D4: 2027E | E4: 2028E | F4: 2029E | G4: 2030E
A5: Cash and cash equivalents
A6: Trade receivables | B6: =+'Balance sheet'!F5-'Balance sheet'!G5 -> -11 | C6: =+'Balance sheet'!G5-'Balance sheet'!H5 -> -313.53855 | D6: =+'Balance sheet'!H5-'Balance sheet'!I5 -> -199.50228 | E6: =+'Balance sheet'!I5-'Balance sheet'!J5 -> -55.979493 | F6: =+'Balance sheet'!J5-'Balance sheet'!K5 -> -58.439371 | G6: =+'Balance sheet'!K5-'Balance sheet'!L5 -> -42.641964
A7: Investments (current / time deposits) | B7: =+'Balance sheet'!F6-'Balance sheet'!G6 -> -573 | C7: =+'Balance sheet'!G6-'Balance sheet'!H6 -> -406 | D7: =+'Balance sheet'!H6-'Balance sheet'!I6 -> -500 | E7: =+'Balance sheet'!I6-'Balance sheet'!J6 -> -500 | F7: =+'Balance sheet'!J6-'Balance sheet'!K6 -> -500 | G7: =+'Balance sheet'!K6-'Balance sheet'!L6 -> -500
A8: Inventories | B8: =+'Balance sheet'!F7-'Balance sheet'!G7 -> -89 | C8: =+'Balance sheet'!G7-'Balance sheet'!H7 -> 71.228688 | D8: =+'Balance sheet'!H7-'Balance sheet'!I7 -> -179.5742 | E8: =+'Balance sheet'!I7-'Balance sheet'!J7 -> -45.174608 | F8: =+'Balance sheet'!J7-'Balance sheet'!K7 -> -47.772016 | G8: =+'Balance sheet'!K7-'Balance sheet'!L7 -> -50.523367
A9: Stockpiles and ore on leach pads (current) | B9: =+'Balance sheet'!F8-'Balance sheet'!G8 -> -416 | C9: =+'Balance sheet'!G8-'Balance sheet'!H8 -> 205.96991 | D9: =+'Balance sheet'!H8-'Balance sheet'!I8 -> -141.75736 | E9: =+'Balance sheet'!I8-'Balance sheet'!J8 -> -43.642569 | F9: =+'Balance sheet'!J8-'Balance sheet'!K8 -> -46.008296 | G9: =+'Balance sheet'!K8-'Balance sheet'!L8 -> -48.519456
A10: Derivative assets (current) | B10: =+'Balance sheet'!F9-'Balance sheet'!G9 -> 0 | C10: =+'Balance sheet'!G9-'Balance sheet'!H9 -> 0 | D10: =+'Balance sheet'!H9-'Balance sheet'!I9 -> 0 | E10: =+'Balance sheet'!I9-'Balance sheet'!J9 -> 0 | F10: =+'Balance sheet'!J9-'Balance sheet'!K9 -> 0 | G10: =+'Balance sheet'!K9-'Balance sheet'!L9 -> 0
A11: Other current assets | B11: =+'Balance sheet'!F10-'Balance sheet'!G10 -> -283 | C11: =+'Balance sheet'!G10-'Balance sheet'!H10 -> -311.53855 | D11: =+'Balance sheet'!H10-'Balance sheet'!I10 -> -199.50228 | E11: =+'Balance sheet'!I10-'Balance sheet'!J10 -> -55.979493 | F11: =+'Balance sheet'!J10-'Balance sheet'!K10 -> -58.439371 | G11: =+'Balance sheet'!K10-'Balance sheet'!L10 -> -42.641964
A12: Assets held for sale (current) | B12: =+'Balance sheet'!F11-'Balance sheet'!G11 -> 4609 | C12: =+'Balance sheet'!G11-'Balance sheet'!H11 -> 0 | D12: =+'Balance sheet'!H11-'Balance sheet'!I11 -> 0 | E12: =+'Balance sheet'!I11-'Balance sheet'!J11 -> 0 | F12: =+'Balance sheet'!J11-'Balance sheet'!K11 -> 0 | G12: =+'Balance sheet'!K11-'Balance sheet'!L11 -> 0
A13: Current assets
A14: Property, plant and mine development, net | B14: =+'Balance sheet'!F13-'Balance sheet'!G13 -> 237 | C14: =+'Balance sheet'!G13-'Balance sheet'!H13 -> -3574.7617 | D14: =+'Balance sheet'!H13-'Balance sheet'!I13 -> -2390.1976 | E14: =+'Balance sheet'!I13-'Balance sheet'!J13 -> -2483.9391 | F14: =+'Balance sheet'!J13-'Balance sheet'!K13 -> -2582.762 | G14: =+'Balance sheet'!K13-'Balance sheet'!L13 -> -2686.9788
A15: Investments (non-current) | B15: =+'Balance sheet'!F14-'Balance sheet'!G14 -> 285 | C15: =+'Balance sheet'!G14-'Balance sheet'!H14 -> 977.21277 | D15: =+'Balance sheet'!H14-'Balance sheet'!I14 -> -468.43986 | E15: =+'Balance sheet'!I14-'Balance sheet'!J14 -> -144.21769 | F15: =+'Balance sheet'!J14-'Balance sheet'!K14 -> -152.03528 | G15: =+'Balance sheet'!K14-'Balance sheet'!L14 -> -160.33346
A16: Stockpiles and ore on leach pads (non-current) | B16: =+'Balance sheet'!F15-'Balance sheet'!G15 -> -144 | C16: =+'Balance sheet'!G15-'Balance sheet'!H15 -> 558.75586 | D16: =+'Balance sheet'!H15-'Balance sheet'!I15 -> -170.31718 | E16: =+'Balance sheet'!I15-'Balance sheet'!J15 -> 5.3894459 | F16: =+'Balance sheet'!J15-'Balance sheet'!K15 -> 4.8315165 | G16: =+'Balance sheet'!K15-'Balance sheet'!L15 -> 4.2720771
A17: Deferred income tax assets | B17: =+'Balance sheet'!F16-'Balance sheet'!G16 -> 79 | C17: =+'Balance sheet'!G16-'Balance sheet'!H16 -> 0 | D17: =+'Balance sheet'!H16-'Balance sheet'!I16 -> 0 | E17: =+'Balance sheet'!I16-'Balance sheet'!J16 -> 0 | F17: =+'Balance sheet'!J16-'Balance sheet'!K16 -> 0 | G17: =+'Balance sheet'!K16-'Balance sheet'!L16 -> 0
A18: Goodwill | B18: =+'Balance sheet'!F17-'Balance sheet'!G17 -> 0 | C18: =+'Balance sheet'!G17-'Balance sheet'!H17 -> 0 | D18: =+'Balance sheet'!H17-'Balance sheet'!I17 -> 0 | E18: =+'Balance sheet'!I17-'Balance sheet'!J17 -> 0 | F18: =+'Balance sheet'!J17-'Balance sheet'!K17 -> 0 | G18: =+'Balance sheet'!K17-'Balance sheet'!L17 -> 0
A19: Derivative assets (non-current) | B19: =+'Balance sheet'!F18-'Balance sheet'!G18 -> 142 | C19: =+'Balance sheet'!G18-'Balance sheet'!H18 -> 0 | D19: =+'Balance sheet'!H18-'Balance sheet'!I18 -> 0 | E19: =+'Balance sheet'!I18-'Balance sheet'!J18 -> 0 | F19: =+'Balance sheet'!J18-'Balance sheet'!K18 -> 0 | G19: =+'Balance sheet'!K18-'Balance sheet'!L18 -> 0
A20: Other non-current assets | B20: =+'Balance sheet'!F19-'Balance sheet'!G19 -> -580 | C20: =+'Balance sheet'!G19-'Balance sheet'!H19 -> 8.2557146 | D20: =+'Balance sheet'!H19-'Balance sheet'!I19 -> -209.89137 | E20: =+'Balance sheet'!I19-'Balance sheet'!J19 -> -64.618857 | F20: =+'Balance sheet'!J19-'Balance sheet'!K19 -> -68.121643 | G20: =+'Balance sheet'!K19-'Balance sheet'!L19 -> -71.839762
A21: Total assets
A23: Accounts payable | B23: =+'Balance sheet'!G22-'Balance sheet'!F22 -> -27 | C23: =+'Balance sheet'!H22-'Balance sheet'!G22 -> 177.88544 | D23: =+'Balance sheet'!I22-'Balance sheet'!H22 -> 143.62686 | E23: =+'Balance sheet'!J22-'Balance sheet'!I22 -> 40.301086 | F23: =+'Balance sheet'!K22-'Balance sheet'!J22 -> 42.072016 | G23: =+'Balance sheet'!L22-'Balance sheet'!K22 -> 30.699054
A24: Employee-related benefits (current) | B24: =+'Balance sheet'!G23-'Balance sheet'!F23 -> 268 | C24: =+'Balance sheet'!H23-'Balance sheet'!G23 -> -108.72685 | D24: =+'Balance sheet'!I23-'Balance sheet'!H23 -> 115.22329 | E24: =+'Balance sheet'!J23-'Balance sheet'!I23 -> 35.473574 | F24: =+'Balance sheet'!K23-'Balance sheet'!J23 -> 37.396486 | G24: =+'Balance sheet'!L23-'Balance sheet'!K23 -> 39.437608
A25: Income and mining taxes payable | B25: =+'Balance sheet'!G24-'Balance sheet'!F24 -> 807 | C25: =+'Balance sheet'!H24-'Balance sheet'!G24 -> -11.695887 | D25: =+'Balance sheet'!I24-'Balance sheet'!H24 -> 206.69337 | E25: =+'Balance sheet'!J24-'Balance sheet'!I24 -> 37.022267 | F25: =+'Balance sheet'!K24-'Balance sheet'!J24 -> 41.969191 | G25: =+'Balance sheet'!L24-'Balance sheet'!K24 -> 14.058937
A26: Lease and other financing obligations (current) | B26: =+'Balance sheet'!G25-'Balance sheet'!F25 -> 11 | C26: =+'Balance sheet'!H25-'Balance sheet'!G25 -> -22 | D26: =+'Balance sheet'!I25-'Balance sheet'!H25 -> -19 | E26: =+'Balance sheet'!J25-'Balance sheet'!I25 -> -6 | F26: =+'Balance sheet'!K25-'Balance sheet'!J25 -> -25 | G26: =+'Balance sheet'!L25-'Balance sheet'!K25 -> 206
A27: Debt (current) | B27: =+'Balance sheet'!G26-'Balance sheet'!F26 -> -924 | C27: =+'Balance sheet'!H26-'Balance sheet'!G26 -> 0 | D27: =+'Balance sheet'!I26-'Balance sheet'!H26 -> 0 | E27: =+'Balance sheet'!J26-'Balance sheet'!I26 -> 0 | F27: =+'Balance sheet'!K26-'Balance sheet'!J26 -> 0 | G27: =+'Balance sheet'!L26-'Balance sheet'!K26 -> 0
A28: Other current liabilities | B28: =+'Balance sheet'!G27-'Balance sheet'!F27 -> 211 | C28: =+'Balance sheet'!H27-'Balance sheet'!G27 -> -181.43221 | D28: =+'Balance sheet'!I27-'Balance sheet'!H27 -> 366.5092 | E28: =+'Balance sheet'!J27-'Balance sheet'!I27 -> 112.83649 | F28: =+'Balance sheet'!K27-'Balance sheet'!J27 -> 118.95301 | G28: =+'Balance sheet'!L27-'Balance sheet'!K27 -> 125.44553
A29: Liabilities held for sale (current) | B29: =+'Balance sheet'!G28-'Balance sheet'!F28 -> -2177 | C29: =+'Balance sheet'!H28-'Balance sheet'!G28 -> 0 | D29: =+'Balance sheet'!I28-'Balance sheet'!H28 -> 0 | E29: =+'Balance sheet'!J28-'Balance sheet'!I28 -> 0 | F29: =+'Balance sheet'!K28-'Balance sheet'!J28 -> 0 | G29: =+'Balance sheet'!L28-'Balance sheet'!K28 -> 0
A30: Current liabilities
A31: Debt (non-current) | B31: =+'Balance sheet'!G30-'Balance sheet'!F30 -> -2437 | C31: =+'Balance sheet'!H30-'Balance sheet'!G30 -> 873.024 | D31: =+'Balance sheet'!I30-'Balance sheet'!H30 -> 1069.5163 | E31: =+'Balance sheet'!J30-'Balance sheet'!I30 -> 1035.0845 | F31: =+'Balance sheet'!K30-'Balance sheet'!J30 -> 1007.1131 | G31: =+'Balance sheet'!L30-'Balance sheet'!K30 -> 939.96274
A32: Lease and other financing obligations (non-current) | B32: =+'Balance sheet'!G31-'Balance sheet'!F31 -> -33 | C32: =+'Balance sheet'!H31-'Balance sheet'!G31 -> -96 | D32: =+'Balance sheet'!I31-'Balance sheet'!H31 -> -77 | E32: =+'Balance sheet'!J31-'Balance sheet'!I31 -> -71 | F32: =+'Balance sheet'!K31-'Balance sheet'!J31 -> -46 | G32: =+'Balance sheet'!L31-'Balance sheet'!K31 -> -66
A33: Reclamation and remediation liabilities | B33: =+'Balance sheet'!G32-'Balance sheet'!F32 -> -97 | C33: =+'Balance sheet'!H32-'Balance sheet'!G32 -> -35.951753 | D33: =+'Balance sheet'!I32-'Balance sheet'!H32 -> 914.029 | E33: =+'Balance sheet'!J32-'Balance sheet'!I32 -> 281.40038 | F33: =+'Balance sheet'!K32-'Balance sheet'!J32 -> 296.65421 | G33: =+'Balance sheet'!L32-'Balance sheet'!K32 -> 312.84577
A34: Deferred income tax liabilities | B34: =+'Balance sheet'!G33-'Balance sheet'!F33 -> 1225 | C34: =+'Balance sheet'!H33-'Balance sheet'!G33 -> -1560.0306 | D34: =+'Balance sheet'!I33-'Balance sheet'!H33 -> 359.1041 | E34: =+'Balance sheet'!J33-'Balance sheet'!I33 -> 100.76309 | F34: =+'Balance sheet'!K33-'Balance sheet'!J33 -> 105.19087 | G34: =+'Balance sheet'!L33-'Balance sheet'!K33 -> 76.755536
A35: Employee-related benefits (non-current) | B35: =+'Balance sheet'!G34-'Balance sheet'!F34 -> 79 | C35: =+'Balance sheet'!H34-'Balance sheet'!G34 -> -76.762608 | D35: =+'Balance sheet'!I34-'Balance sheet'!H34 -> 81.349179 | E35: =+'Balance sheet'!J34-'Balance sheet'!I34 -> 25.044818 | F35: =+'Balance sheet'!K34-'Balance sheet'!J34 -> 26.402419 | G35: =+'Balance sheet'!L34-'Balance sheet'!K34 -> 27.843478
A36: Silver streaming agreement | B36: =+'Balance sheet'!G35-'Balance sheet'!F35 -> -101 | C36: =+'Balance sheet'!H35-'Balance sheet'!G35 -> -96 | D36: =+'Balance sheet'!I35-'Balance sheet'!H35 -> -96 | E36: =+'Balance sheet'!J35-'Balance sheet'!I35 -> -96 | F36: =+'Balance sheet'!K35-'Balance sheet'!J35 -> -96 | G36: =+'Balance sheet'!L35-'Balance sheet'!K35 -> -96
A37: Other non-current liabilities | B37: =+'Balance sheet'!G36-'Balance sheet'!F36 -> 34 | C37: =+'Balance sheet'!H36-'Balance sheet'!G36 -> 70.194991 | D37: =+'Balance sheet'!I36-'Balance sheet'!H36 -> 56.676284 | E37: =+'Balance sheet'!J36-'Balance sheet'!I36 -> 15.903125 | F37: =+'Balance sheet'!K36-'Balance sheet'!J36 -> 16.601948 | G37: =+'Balance sheet'!L36-'Balance sheet'!K36 -> 12.114088
A38: Total liabilities
A40: Common stock | B40: =+'Balance sheet'!G39-'Balance sheet'!F39 -> -60 | C40: =+'Balance sheet'!H39-'Balance sheet'!G39 -> 7 | D40: =+'Balance sheet'!I39-'Balance sheet'!H39 -> 0 | E40: =+'Balance sheet'!J39-'Balance sheet'!I39 -> 0 | F40: =+'Balance sheet'!K39-'Balance sheet'!J39 -> 0 | G40: =+'Balance sheet'!L39-'Balance sheet'!K39 -> 0
A41: Treasury stock | B41: =+'Balance sheet'!G40-'Balance sheet'!F40 -> -23 | C41: =+'Balance sheet'!H40-'Balance sheet'!G40 -> -27.610771 | D41: =+'Balance sheet'!I40-'Balance sheet'!H40 -> -63.201633 | E41: =+'Balance sheet'!J40-'Balance sheet'!I40 -> -65.440813 | F41: =+'Balance sheet'!K40-'Balance sheet'!J40 -> -67.778388 | G41: =+'Balance sheet'!L40-'Balance sheet'!K40 -> -104.2261
A42: Additional paid-in capital | B42: =+'Balance sheet'!G41-'Balance sheet'!F41 -> -961 | C42: =+'Balance sheet'!H41-'Balance sheet'!G41 -> -1242.4847 | D42: =+'Balance sheet'!I41-'Balance sheet'!H41 -> -1422.0367 | E42: =+'Balance sheet'!J41-'Balance sheet'!I41 -> -1472.4183 | F42: =+'Balance sheet'!K41-'Balance sheet'!J41 -> -1525.0137 | G42: =+'Balance sheet'!L41-'Balance sheet'!K41 -> -1563.3915
A43: Accumulated other comprehensive income (loss) | B43: =+'Balance sheet'!G42-'Balance sheet'!F42 -> 232 | C43: =+'Balance sheet'!H42-'Balance sheet'!G42 -> 0 | D43: =+'Balance sheet'!I42-'Balance sheet'!H42 -> 0 | E43: =+'Balance sheet'!J42-'Balance sheet'!I42 -> 0 | F43: =+'Balance sheet'!K42-'Balance sheet'!J42 -> 0 | G43: =+'Balance sheet'!L42-'Balance sheet'!K42 -> 0
A44: Retained earnings (accumulated deficit)
A45: Newmont stockholders’ equity
A46: Contingently Redeemable Noncontrolling Interest | B46: =+'Balance sheet'!G45-'Balance sheet'!F45 -> 0 | C46: =+'Balance sheet'!H45-'Balance sheet'!G45 -> 0 | D46: =+'Balance sheet'!I45-'Balance sheet'!H45 -> 0 | E46: =+'Balance sheet'!J45-'Balance sheet'!I45 -> 0 | F46: =+'Balance sheet'!K45-'Balance sheet'!J45 -> 0 | G46: =+'Balance sheet'!L45-'Balance sheet'!K45 -> 0
A47: Noncontrolling interests | B47: =+'Balance sheet'!G46-'Balance sheet'!F46 -> -6 | C47: =+'Balance sheet'!H46-'Balance sheet'!G46 -> 10 | D47: =+'Balance sheet'!I46-'Balance sheet'!H46 -> 0 | E47: =+'Balance sheet'!J46-'Balance sheet'!I46 -> 0 | F47: =+'Balance sheet'!K46-'Balance sheet'!J46 -> 0 | G47: =+'Balance sheet'!L46-'Balance sheet'!K46 -> 0
A48: Total equity
A49: Total liabilities and equity
A51: Net | B51: =+SUM(B6:B47)+B2 -> 6362 | C51: =+SUM(C6:C47)+C2 -> 5326.1378 | D51: =+SUM(D6:D47)+D2 -> 9408.753 | E51: =+SUM(E6:E47)+E2 -> 9139.8971 | F51: =+SUM(F6:F47)+F2 -> 9344.659 | G51: =+SUM(G6:G47)+G2 -> 9399.7044
A53: Dividends | B53: =+'Changes in Equity'!G12 -> 1108 | C53: =+'Changes in Equity'!H12 -> 1114.8891 | D53: =+'Changes in Equity'!I12 -> 1117.0986 | E53: =+'Changes in Equity'!J12 -> 1116.667 | F53: =+'Changes in Equity'!K12 -> 1113.9651 | G53: =+'Changes in Equity'!L12 -> 1109.3301
A54: Repurchases | B54: =+'Changes in Equity'!G4 -> 1226 | C54: =+'Changes in Equity'!H4 -> 2000 | D54: =+'Changes in Equity'!I4 -> 2500 | E54: =+'Changes in Equity'!J4 -> 3000 | F54: =+'Changes in Equity'!K4 -> 3500 | G54: =+'Changes in Equity'!L4 -> 4000
A56: Cash Generated | B56: =+B51-B53-B54 -> 4028 | C56: =+C51-C53-C54 -> 2211.2487 | D56: =+D51-D53-D54 -> 5791.6543 | E56: =+E51-E53-E54 -> 5023.2301 | F56: =+F51-F53-F54 -> 4730.694 | G56: =+G51-G53-G54 -> 4290.3743
A58: Opening Cash | B58: =+'Balance sheet'!F4 -> 3619 | C58: =B59 -> 7647 | D58: =+C59 -> 9858.2487 | E58: =+D59 -> 15649.903 | F58: =+E59 -> 20673.133 | G58: =+F59 -> 25403.827
A59: Closing Cash | B59: =+B58+B56 -> 7647 | C59: =+C58+C56 -> 9858.2487 | D59: =+D58+D56 -> 15649.903 | E59: =+E58+E56 -> 20673.133 | F59: =+F58+F56 -> 25403.827 | G59: =+G58+G56 -> 29694.201
A61: FCFE | B61: =+B56+B53+B54 -> 6362 | C61: =+C56+C53+C54 -> 5326.1378 | D61: =+D56+D53+D54 -> 9408.753 | E61: =+E56+E53+E54 -> 9139.8971 | F61: =+F56+F53+F54 -> 9344.659 | G61: =+G56+G53+G54 -> 9399.7044
A65: Check | B65: =+'Balance sheet'!G20-'Balance sheet'!G48 -> 0 | C65: =+'Balance sheet'!H20-'Balance sheet'!H48 -> 0 | D65: =+'Balance sheet'!I20-'Balance sheet'!I48 -> 0 | E65: =+'Balance sheet'!J20-'Balance sheet'!J48 -> 0 | F65: =+'Balance sheet'!K20-'Balance sheet'!K48 -> 0 | G65: =+'Balance sheet'!L20-'Balance sheet'!L48 -> 0

Sheet Changes in Equity
A2: Repurchase | B2: 2020 | C2: 2021 | D2: 2022 | E2: 2023 | F2: 2024 | G2: 2025 | H2: 2026 | I2: 2027E | J2: 2028E | K2: 2029E | L2: 2030E
A4: Repurchase Value | B4: 274 | C4: 306 | D4: 0 | E4: 0 | F4: 524 | G4: 1226 | H4: 2000 | I4: 2500 | J4: 3000 | K4: 3500 | L4: 4000
A5: Share price | B5: 60 | C5: 60 | F5: 40 | G5: 115.32 | H5: =+G5*(1+Ke!$D$32) -> 126.06024 | I5: =+H5*(1+Ke!$D$32) -> 137.80076 | J5: =+I5*(1+Ke!$D$32) -> 150.63473 | K5: =+J5*(1+Ke!$D$32) -> 164.66399 | L5: =+K5*(1+Ke!$D$32) -> 179.99984 | M5: Grew with Ke
A6: Shares Repurchased | G6: =+G4/G5 -> 10.631287 | H6: =+H4/H5 -> 15.865431 | I6: =+I4/I5 -> 18.142134 | J6: =+J4/J5 -> 19.915725 | K6: =+K4/K5 -> 21.255407 | L6: =+L4/L5 -> 22.222242
A7: Total Shares | G7: =+DCF!I3 -> 1087.8742 | H7: =+G7-H6 -> 1072.0088 | I7: =+H7-I6 -> 1053.8666 | J7: =+I7-J6 -> 1033.9509 | K7: =+J7-K6 -> 1012.6955 | L7: =+K7-L6 -> 990.47327
A8: Dividend | B8: 2020 | C8: 2021 | D8: 2022 | E8: 2023 | F8: 2024 | G8: 2025 | H8: 2026 | I8: 2027E | J8: 2028E | K8: 2029E | L8: 2030E
A10: Dividend per share | B10: 1.04 | C10: 2.2 | D10: 2.2 | E10: 1.6 | F10: 1 | G10: =G12/G11 -> 1.0185001 | H10: 1.04 | I10: 1.06 | J10: 1.08 | K10: 1.1 | L10: 1.12
A11: Total Shares | G11: =+G7 -> 1087.8742 | H11: =+H7 -> 1072.0088 | I11: =+I7 -> 1053.8666 | J11: =+J7 -> 1033.9509 | K11: =+K7 -> 1012.6955 | L11: =+L7 -> 990.47327
A12: Total Dividend | G12: 1108 | H12: =+H10*H11 -> 1114.8891 | I12: =+I10*I11 -> 1117.0986 | J12: =+J10*J11 -> 1116.667 | K12: =+K10*K11 -> 1113.9651 | L12: =+L10*L11 -> 1109.3301
A13: Growth
A16: Retained Earnings | B16: 2020 | C16: 2021 | D16: 2022 | E16: 2023 | F16: 2024 | G16: 2025 | H16: 2026 | I16: 2027E | J16: 2028E | K16: 2029E | L16: 2030E
A17: Opening | F17: -2996 | G17: =+'Balance sheet'!F43 -> -1320 | H17: =+G21 -> 3431 | I17: =+H21 -> 10747.255 | J17: =+I21 -> 19362.603 | K17: =+J21 -> 27801.025 | L17: =+K21 -> 36107.904
A18: Net Income | B18: ='Income statement'!B24 -> 2829 | C18: ='Income statement'!C24 -> 1166 | D18: ='Income statement'!D24 -> -429 | E18: ='Income statement'!E24 -> -2494 | F18: ='Income statement'!F24 -> 3348 | G18: ='Income statement'!G24 -> 7085 | H18: ='Income statement'!H24 -> 10431.145 | I18: ='Income statement'!I24 -> 12232.446 | ... L18: ='Income statement'!L24 -> 13043.366
A19: Dividends | D19: 1753 | E19: 1418 | F19: 1148 | G19: 1108 | H19: =+H12 -> 1114.8891 | I19: =+I12 -> 1117.0986 | J19: =+J12 -> 1116.667 | K19: =+K12 -> 1113.9651 | L19: =+L12 -> 1109.3301
A20: Repurchases | F20: =F4 -> 524 | G20: 1226 | H20: =+H4 -> 2000 | I20: =+I4 -> 2500 | J20: =+J4 -> 3000 | K20: =+K4 -> 3500 | L20: =+L4 -> 4000
A21: Closing | F21: =F17+F18-F19-F20 -> -1320 | G21: =+G17+G18-G19-G20 -> 3431 | H21: =+H17+H18-H19-H20 -> 10747.255 | I21: =+I17+I18-I19-I20 -> 19362.603 | J21: =+J17+J18-J19-J20 -> 27801.025 | K21: =+K17+K18-K19-K20 -> 36107.904 | L21: =+L17+L18-L19-L20 -> 44041.94
A25: Treasury Stock | B25: 2020 | C25: 2021 | D25: 2022 | E25: 2023 | F25: 2024 | G25: 2025 | H25: 2026 | I25: 2027E | J25: 2028E | K25: 2029E | L25: 2030E
A27: Stock Based Comp | B27: 48 | C27: 32 | D27: 39 | E27: 25 | F27: 14 | G27: 23 | H27: =+H29*'Income statement'!H3 -> 27.610771 | I27: =+I29*'Income statement'!I3 -> 63.201633 | J27: =+J29*'Income statement'!J3 -> 65.440813 | K27: =+K29*'Income statement'!K3 -> 67.778388 | L27: =+L29*'Income statement'!L3 -> 104.2261
A28: Treasury Stock | B28: 168 | C28: =B28+C27 -> 200 | D28: =C28+D27 -> 239 | E28: =D28+E27 -> 264 | F28: =E28+F27 -> 278 | G28: =+F28+G27 -> 301 | H28: =+G28+H27 -> 328.61077 | I28: =+H28+I27 -> 391.8124 | J28: =+I28+J27 -> 457.25322 | K28: =+J28+K27 -> 525.0316 | L28: =+K28+L27 -> 629.2577
A29: Stock Base comp as % of Revenue | B29: =+B27/'Income statement'!B3 -> 0.0041750022 | C29: =+C27/'Income statement'!C3 -> 0.0026182294 | D29: =+D27/'Income statement'!D3 -> 0.0032731851 | E29: =+E27/'Income statement'!E3 -> 0.0021164917 | F29: =+F27/'Income statement'!F3 -> 0.00074938443 | G29: 0.0005 | H29: 0.001 | I29: 0.002 | J29: 0.002 | K29: 0.002 | L29: 0.003
A31: Additional Paid in Capital | B31: 2020 | C31: 2021 | D31: 2022 | E31: 2023 | F31: 2024 | G31: 2025 | H31: 2026 | I31: 2027E | J31: 2028E | K31: 2029E | L31: 2030E
A32: Open
A33: Retirement of Common Stock | B33: 500 | C33: 500 | D33: 500 | E33: 500 | F33: 500 | G33: 1037
A34: Stock Based other aswards | B34: =49+68 -> 117 | C34: =17+68 -> 85 | D34: =14+73 -> 87 | E34: 73 | F34: 82 | G34: 76
A35: Retiremnet and awards | B35: =+B33+B34 -> 617 | C35: =+C33+C34 -> 585 | D35: =+D33+D34 -> 587 | E35: =+E33+E34 -> 573 | F35: =+F33+F34 -> 582 | G35: =+G33+G34 -> 1113 | H35: =+H39*'Income statement'!H3 -> 1242.4847 | I35: =+I39*'Income statement'!I3 -> 1422.0367 | J35: =+J39*'Income statement'!J3 -> 1472.4183 | K35: =+K39*'Income statement'!K3 -> 1525.0137 | L35: =+L39*'Income statement'!L3 -> 1563.3915
A36: Shares issued for Newcast Transaction | E36: 12977
A37: Closing | B37: =+'Balance sheet'!B41 -> 18103 | C37: =+'Balance sheet'!C41 -> 17981 | D37: =+'Balance sheet'!D41 -> 17369 | E37: =+'Balance sheet'!E41 -> 30419 | F37: =+'Balance sheet'!F41 -> 29808 | G37: =+'Balance sheet'!G41 -> 28847 | H37: =+G37-H35 -> 27604.515 | I37: =+H37-I35 -> 26182.479 | J37: =+I37-J35 -> 24710.06 | K37: =+J37-K35 -> 23185.047 | L37: =+K37-L35 -> 21621.655
A39: % of revenue | B39: =+(B33+B34)/'Income statement'!B3 -> 0.053666174 | C39: =+(C33+C34)/'Income statement'!C3 -> 0.047864507 | D39: =+(D33+D34)/'Income statement'!D3 -> 0.049265632 | E39: =+(E33+E34)/'Income statement'!E3 -> 0.04850999 | F39: =+(F33+F34)/'Income statement'!F3 -> 0.031152981 | G39: 0.045 | H39: 0.045 | I39: 0.045 | J39: 0.045 | K39: 0.045 | L39: 0.045

Sheet Schedules
A1: Inventories
B2: 2020 | C2: 2021 | D2: 2022 | E2: 2023 | F2: 2024 | G2: 2025 | H2: 2026 | I2: 2027 | J2: 2028 | K2: 2029 | L2: 2030
A3: Materials and supplies | B3: 673 | C3: 669 | D3: 750 | E3: 1247 | F3: 1081 | G3: 1060 | H3: =H4*'Income statement'!H4 -> 1026.084 | I3: =I4*'Income statement'!I4 -> 1175.8785 | J3: =J4*'Income statement'!J4 -> 1221.9954 | K3: =K4*'Income statement'!K4 -> 1270.6122 | L3: =L4*'Income statement'!L4 -> 1321.8825
B4: =B3/'Income statement'!B4 -> 0.13422417 | C4: =C3/'Income statement'!C4 -> 0.12309108 | D4: =D3/'Income statement'!D4 -> 0.11595547 | E4: =E3/'Income statement'!E4 -> 0.18614719 | F4: =F3/'Income statement'!F4 -> 0.12060694 | G4: =G3/'Income statement'!G4 -> 0.13110699 | H4: =G4 -> 0.13110699 | I4: =H4 -> 0.13110699 | J4: =I4 -> 0.13110699 | K4: =J4 -> 0.13110699 | L4: =K4 -> 0.13110699
A5: In-process | B5: 148 | C5: 132 | D5: 123 | E5: 160 | F5: 118 | G5: 199 | H5: =H6*'Cost of sales'!H66 -> 178.43152 | I5: =I6*'Cost of sales'!I66 -> 194.84749 | J5: =J6*'Cost of sales'!J66 -> 194.32803 | K5: =K6*'Cost of sales'!K66 -> 193.86234 | L5: =L6*'Cost of sales'!L66 -> 193.45058
B6: =B5/'Cost of sales'!B66 -> 0.022880111 | C6: =C5/'Cost of sales'!C66 -> 0.020005153 | D6: =D5/'Cost of sales'!D66 -> 0.019138012 | E6: =E5/'Cost of sales'!E66 -> 0.027086508 | F6: =F5/'Cost of sales'!F66 -> 0.015330648 | G6: =G5/'Cost of sales'!G66 -> 0.030247758 | H6: =G6 -> 0.030247758 | I6: =H6 -> 0.030247758 | J6: =I6 -> 0.030247758 | K6: =J6 -> 0.030247758 | L6: =K6 -> 0.030247758
A7: Concentrate | B7: 39 | C7: 58 | D7: 47 | E7: 134 | F7: 148 | G7: 162 | H7: =H8*'Cost of sales'!H66 -> 145.25581 | I7: =I8*'Cost of sales'!I66 -> 158.61956 | J7: =J8*'Cost of sales'!J66 -> 158.19669 | K7: =K8*'Cost of sales'!K66 -> 157.81759 | L7: =L8*'Cost of sales'!L66 -> 157.48238
B8: =B7/'Cost of sales'!B66 -> 0.0060292185 | C8: =C7/'Cost of sales'!C66 -> 0.0087901429 | D8: =D7/'Cost of sales'!D66 -> 0.0073128987 | E8: =E7/'Cost of sales'!E66 -> 0.02268495 | F8: =F7/'Cost of sales'!F66 -> 0.019228271 | G8: =G7/'Cost of sales'!G66 -> 0.024623803 | H8: =G8 -> 0.024623803 | I8: =H8 -> 0.024623803 | J8: =I8 -> 0.024623803 | K8: =J8 -> 0.024623803 | L8: =K8 -> 0.024623803
A9: Precious metals | B9: 103 | C9: 71 | D9: 59 | E9: 122 | F9: 76 | G9: 91 | H9: =G9 -> 91 | I9: =H9 -> 91 | J9: =I9 -> 91 | K9: =J9 -> 91 | L9: =K9 -> 91
A10: Total Inventories | B10: 963 | C10: 930 | D10: 979 | E10: 1663 | F10: 1423 | G10: =G3+G5+G7+G9 -> 1512 | H10: =H3+H5+H7+H9 -> 1440.7713 | I10: =I3+I5+I7+I9 -> 1620.3455 | J10: =J3+J5+J7+J9 -> 1665.5201 | K10: =K3+K5+K7+K9 -> 1713.2921 | L10: =L3+L5+L7+L9 -> 1763.8155
A13: Stockpiles and ore on leach pads (current)
A14: Category / Line Item | B14: 2020 | C14: 2021 | D14: 2022 | E14: 2023 | F14: 2024 | G14: 2025 | H14: 2026 | I14: 2027 | J14: 2028 | K14: 2029 | L14: 2030
A15: CURRENT
A16: Stockpiles | B16: 514 | C16: 491 | D16: 480 | E16: 746 | F16: 624
A17: Ore on leach pads | B17: 313 | C17: 366 | D17: 294 | E17: 233 | F17: 137
A18: Total Current | B18: 827 | C18: 857 | D18: 774 | E18: 979 | F18: 761 | G18: 1177 | H18: =H19*'Income statement'!H4 -> 971.03009 | I18: =I19*'Income statement'!I4 -> 1112.7874 | J18: =J19*'Income statement'!J4 -> 1156.43 | K18: =K19*'Income statement'!K4 -> 1202.4383 | L18: =L19*'Income statement'!L4 -> 1250.9578
B19: =B18/'Income statement'!B4 -> 0.16493817 | C19: =C18/'Income statement'!C4 -> 0.15768169 | D19: =D18/'Income statement'!D4 -> 0.11966605 | E19: =E18/'Income statement'!E4 -> 0.14614122 | F19: =F18/'Income statement'!F4 -> 0.084904608 | G19: =G18/'Income statement'!G4 -> 0.14557823 | H19: =AVERAGE(D19:G19) -> 0.12407253 | I19: =H19 -> 0.12407253 | J19: =I19 -> 0.12407253 | K19: =J19 -> 0.12407253 | L19: =K19 -> 0.12407253
A20: NON-CURRENT
A21: Stockpiles | B21: 1446 | C21: 1442 | D21: 1391 | E21: 1532 | F21: 2072
A22: Ore on leach pads | B22: 259 | C22: 333 | D22: 325 | E22: 403 | F22: 194
A23: Total Non-Current | B23: 1705 | C23: 1775 | D23: 1716 | E23: 1935 | F23: 2266 | G23: 2410 | H23: =H24*'Cost of sales'!H66 -> 1851.2441 | I23: =I24*'Cost of sales'!I66 -> 2021.5613 | J23: =J24*'Cost of sales'!J66 -> 2016.1719 | K23: =K24*'Cost of sales'!K66 -> 2011.3404 | L23: =L24*'Cost of sales'!L66 -> 2007.0683
B24: =B23/'Cost of sales'!B66 -> 0.26358507 | C24: =C23/'Cost of sales'!C66 -> 0.26900868 | D24: =D23/'Cost of sales'!D66 -> 0.2669986 | E24: =E23/'Cost of sales'!E66 -> 0.32757745 | F24: =F23/'Cost of sales'!F66 -> 0.29440042 | G24: =G23/'Cost of sales'!G66 -> 0.36631707 | H24: =AVERAGE(D24:G24) -> 0.31382338 | I24: =H24 -> 0.31382338 | J24: =I24 -> 0.31382338 | K24: =J24 -> 0.31382338 | L24: =K24 -> 0.31382338
A25: COMBINED TOTALS
A26: Total Stockpiles | B26: 1960 | C26: 1933 | D26: 1871 | E26: 2278 | F26: 2696
A27: Total Ore on leach pads | B27: 572 | C27: 699 | D27: 619 | E27: 636 | F27: 331
A28: Grand Total | B28: 2532 | C28: 2632 | D28: 2490 | E28: 2914 | F28: 3027 | G28: =G18+G23 -> 3587 | H28: =H18+H23 -> 2822.2742 | I28: =I18+I23 -> 3134.3488 | J28: =J18+J23 -> 3172.6019 | K28: =K18+K23 -> 3213.7787 | L28: =L18+L23 -> 3258.026
A31: Reclamation and remediation
A32: Category / Line Item | B32: 2020 | C32: 2021 | D32: 2022 | E32: 2023 | F32: 2024 | G32: 2025 | H32: 2026 | I32: 2027 | J32: 2028 | K32: 2029 | L32: 2030
A35: ending | B35: ='Balance sheet'!B32 -> 3818 | C35: ='Balance sheet'!C32 -> 5839 | D35: ='Balance sheet'!D32 -> 6578 | E35: ='Balance sheet'!E32 -> 8167 | F35: ='Balance sheet'!F32 -> 6394 | G35: 6297 | H35: =H36*'Income statement'!H4 -> 6261.0482 | I35: =I36*'Income statement'!I4 -> 7175.0772 | J35: =J36*'Income statement'!J4 -> 7456.4776 | K35: =K36*'Income statement'!K4 -> 7753.1318 | L35: =L36*'Income statement'!L4 -> 8065.9776
B36: =B35/'Income statement'!B4 -> 0.76146789 | C36: =C35/'Income statement'!C4 -> 1.074333 | D36: =D35/'Income statement'!D4 -> 1.0170068 | E36: =E35/'Income statement'!E4 -> 1.2191372 | F36: =F35/'Income statement'!F4 -> 0.71337722 | G36: 0.8 | H36: 0.8 | I36: 0.8 | J36: 0.8 | K36: 0.8 | L36: 0.8
A38: PPE
B39: 2020 | C39: 2021 | D39: 2022 | E39: 2023 | F39: 2024 | G39: 2025 | H39: 2026 | I39: 2027 | J39: 2028 | K39: 2029 | L39: 2030
A42: Gross | B42: 38181 | C42: 40113 | D42: 42225 | E42: 57623 | F42: 52410 | G42: 53537 | H42: =+G42+H46 -> 56745.787 | I42: =+H42+I46 -> 60423.014 | J42: =+I42+J46 -> 64244.459 | K42: =+J42+K46 -> 68217.939 | L42: =+K42+L46 -> 72351.753
A43: DEPRECIATION | B43: 13900 | C43: 15989 | D43: 18152 | E43: 20060 | F43: 18863 | G43: 20227 | H43: =+H42*H45 -> 19861.026 | I43: =+I42*I45 -> 21148.055 | J43: =+J42*J45 -> 22485.561 | K43: =+K42*K45 -> 23876.279 | L43: =+L42*L45 -> 25323.113
A44: Net | B44: =+B42-B43 -> 24281 | C44: =+C42-C43 -> 24124 | D44: =+D42-D43 -> 24073 | E44: =+E42-E43 -> 37563 | F44: =+F42-F43 -> 33547 | G44: =+G42-G43 -> 33310 | H44: =+H42-H43 -> 36884.762 | I44: =+I42-I43 -> 39274.959 | ... L44: =+L42-L43 -> 47028.639
A45: Depre ratio of gross | B45: =+B43/B42 -> 0.36405542 | C45: =+C43/C42 -> 0.39859896 | D45: =+D43/D42 -> 0.42988751 | E45: =+E43/E42 -> 0.34812488 | F45: =+F43/F42 -> 0.35991223 | G45: 0.35 | H45: 0.35 | I45: 0.35 | J45: 0.35 | K45: 0.35 | L45: 0.35
A46: Investments/Capex | B46: ='Balance sheet'!B14 -> 3197 | C46: ='Balance sheet'!C14 -> 3243 | D46: ='Balance sheet'!D14 -> 3278 | E46: ='Balance sheet'!E14 -> 4143 | F46: ='Balance sheet'!F14 -> 4471 | G46: ='Balance sheet'!G14 -> 4186 | H46: =H48*'Income statement'!H4 -> 3208.7872 | I46: =I48*'Income statement'!I4 -> 3677.2271 | J46: =J48*'Income statement'!J4 -> 3821.4448 | K46: =K48*'Income statement'!K4 -> 3973.4801 | L46: =L48*'Income statement'!L4 -> 4133.8135
A48: Capex/Cost of Sales | B48: =B46/'Income statement'!B4 -> 0.63761468 | C48: =C46/'Income statement'!C4 -> 0.59668813 | D48: =D46/'Income statement'!D4 -> 0.50680272 | E48: =E46/'Income statement'!E4 -> 0.61845052 | F48: =F46/'Income statement'!F4 -> 0.49882852 | G48: =G46/'Income statement'!G4 -> 0.51774892 | H48: 0.41 | I48: 0.41 | J48: 0.41 | K48: 0.41 | L48: 0.41

Sheet Comps
C1: USD
A2: COMPARABLE COMPANY ANALYSIS
A3: COMPANY DATA
A4: (in millions) | C4: Recent | D4: 52 week | E4: Shares | F4: Market | G4: Total | I4: Enterprise | J4: Book | L4: WS 12-mo
A5: Company Name | B5: Ticker | C5: Price | D5: High | E5: Out | F5: Cap | G5: Debt | H5: Cash | I5: Value | J5: Value | K5: Beta | L5: Price Target
A6: {=IF($B6="","",_xll.RDP.Data($B6,"TR.CompanyName"))} -> Please sign in | B6: RGLD.OQ | C6: =IF(B6="","",_xll.RDP.Data($B6,"TR.PriceClose","Curn=#1",,$C$1)) -> Please sign in | D6: =IF($B6="","",_xll.RDP.Data($B6,"MAX(TR.PriceHigh(SDate=0D,EDate=0D-364C))/*52 Week High*/","Curn=#1",,$C$1)) -> Please sign in | E6: =IF(B6="","",_xll.RDP.Data($B6,"TR.CompanySharesOutstanding(SDate=0)/*# Shares Outstanding*/")/1000000) -> #VALUE! | F6: =IF(B6="","",C6*E6) -> #VALUE! | G6: {=IF($B6="","",_xll.RDP.Data($B6,"TR.TotalDebtOutstanding","Curn=#1",,$C$1)/1000000)} -> #VALUE! | H6: =IF($B6="","",_xll.RDP.Data($B6,"TR.CashandEquivalents","Curn=#1",,$C$1)/1000000) -> #VALUE! | I6: =IF(B6="","",F6+G6-H6) -> #VALUE! | J6: {=IF($B6="","",_xll.RDP.Data($B6,"TR.TotalEquity","Curn=#1",,$C$1)/1000000)} -> #VALUE! | K6: =IF($B6="","",_xll.RDP.Data($B6,"TR.BetaFiveYear/*Beta 5 Year Monthly*//*Beta 5 Year Monthly*/")) -> Please sign in | L6: =IF(B6="","",_xll.RDP.Data($B6,"TR.PriceTargetMean","Curn=#1",,$C$1)) -> Please sign in
A7: {=IF($B7="","",_xll.RDP.Data($B7,"TR.CompanyName"))} -> Please sign in | B7: GFIJ.J | C7: =IF(B7="","",_xll.RDP.Data($B7,"TR.PriceClose","Curn=#1",,$C$1)) -> Please sign in | D7: =IF($B7="","",_xll.RDP.Data($B7,"MAX(TR.PriceHigh(SDate=0D,EDate=0D-364C))/*52 Week High*/","Curn=#1",,$C$1)) -> Please sign in | E7: =IF(B7="","",_xll.RDP.Data($B7,"TR.CompanySharesOutstanding(SDate=0)/*# Shares Outstanding*/")/1000000) -> #VALUE! | F7: =IF(B7="","",C7*E7) -> #VALUE! | G7: {=IF($B7="","",_xll.RDP.Data($B7,"TR.TotalDebtOutstanding","Curn=#1",,$C$1)/1000000)} -> #VALUE! | H7: =IF($B7="","",_xll.RDP.Data($B7,"TR.CashandEquivalents","Curn=#1",,$C$1)/1000000) -> #VALUE! | I7: =IF(B7="","",F7+G7-H7) -> #VALUE! | J7: {=IF($B7="","",_xll.RDP.Data($B7,"TR.TotalEquity","Curn=#1",,$C$1)/1000000)} -> #VALUE! | K7: =IF($B7="","",_xll.RDP.Data($B7,"TR.BetaFiveYear/*Beta 5 Year Monthly*//*Beta 5 Year Monthly*/")) -> Please sign in | L7: =IF(B7="","",_xll.RDP.Data($B7,"TR.PriceTargetMean","Curn=#1",,$C$1)) -> Please sign in
A8: {=IF($B8="","",_xll.RDP.Data($B8,"TR.CompanyName"))} -> Please sign in | B8: AEM.N | C8: =IF(B8="","",_xll.RDP.Data($B8,"TR.PriceClose","Curn=#1",,$C$1)) -> Please sign in | D8: =IF($B8="","",_xll.RDP.Data($B8,"MAX(TR.PriceHigh(SDate=0D,EDate=0D-364C))/*52 Week High*/","Curn=#1",,$C$1)) -> Please sign in | E8: =IF(B8="","",_xll.RDP.Data($B8,"TR.CompanySharesOutstanding(SDate=0)/*# Shares Outstanding*/")/1000000) -> #VALUE! | F8: =IF(B8="","",C8*E8) -> #VALUE! | G8: {=IF($B8="","",_xll.RDP.Data($B8,"TR.TotalDebtOutstanding","Curn=#1",,$C$1)/1000000)} -> #VALUE! | H8: =IF($B8="","",_xll.RDP.Data($B8,"TR.CashandEquivalents","Curn=#1",,$C$1)/1000000) -> #VALUE! | I8: =IF(B8="","",F8+G8-H8) -> #VALUE! | J8: {=IF($B8="","",_xll.RDP.Data($B8,"TR.TotalEquity","Curn=#1",,$C$1)/1000000)} -> #VALUE! | K8: =IF($B8="","",_xll.RDP.Data($B8,"TR.BetaFiveYear/*Beta 5 Year Monthly*//*Beta 5 Year Monthly*/")) -> Please sign in | L8: =IF(B8="","",_xll.RDP.Data($B8,"TR.PriceTargetMean","Curn=#1",,$C$1)) -> Please sign in
A9: {=IF($B9="","",_xll.RDP.Data($B9,"TR.CompanyName"))} -> Please sign in | B9: ABX.TO | C9: =IF(B9="","",_xll.RDP.Data($B9,"TR.PriceClose","Curn=#1",,$C$1)) -> Please sign in | D9: =IF($B9="","",_xll.RDP.Data($B9,"MAX(TR.PriceHigh(SDate=0D,EDate=0D-364C))/*52 Week High*/","Curn=#1",,$C$1)) -> Please sign in | E9: =IF(B9="","",_xll.RDP.Data($B9,"TR.CompanySharesOutstanding(SDate=0)/*# Shares Outstanding*/")/1000000) -> #VALUE! | F9: =IF(B9="","",C9*E9) -> #VALUE! | G9: {=IF($B9="","",_xll.RDP.Data($B9,"TR.TotalDebtOutstanding","Curn=#1",,$C$1)/1000000)} -> #VALUE! | H9: 0 | I9: =IF(B9="","",F9+G9-H9) -> #VALUE! | J9: {=IF($B9="","",_xll.RDP.Data($B9,"TR.TotalEquity","Curn=#1",,$C$1)/1000000)} -> #VALUE! | K9: =IF($B9="","",_xll.RDP.Data($B9,"TR.BetaFiveYear/*Beta 5 Year Monthly*//*Beta 5 Year Monthly*/")) -> Please sign in | L9: =IF(B9="","",_xll.RDP.Data($B9,"TR.PriceTargetMean","Curn=#1",,$C$1)) -> Please sign in
A10: {=IF($B10="","",_xll.RDP.Data($B10,"TR.CompanyName"))} -> Please sign in | B10: NEM | C10: =IF(B10="","",_xll.RDP.Data($B10,"TR.PriceClose","Curn=#1",,$C$1)) -> Please sign in | D10: =IF($B10="","",_xll.RDP.Data($B10,"MAX(TR.PriceHigh(SDate=0D,EDate=0D-364C))/*52 Week High*/","Curn=#1",,$C$1)) -> Please sign in | E10: =IF(B10="","",_xll.RDP.Data($B10,"TR.CompanySharesOutstanding(SDate=0)/*# Shares Outstanding*/")/1000000) -> #VALUE! | F10: =IF(B10="","",C10*E10) -> #VALUE! | G10: {=IF($B10="","",_xll.RDP.Data($B10,"TR.TotalDebtOutstanding","Curn=#1",,$C$1)/1000000)} -> #VALUE! | H10: =IF($B10="","",_xll.RDP.Data($B10,"TR.CashandEquivalents","Curn=#1",,$C$1)/1000000) -> #VALUE! | I10: =IF(B10="","",F10+G10-H10) -> #VALUE! | J10: {=IF($B10="","",_xll.RDP.Data($B10,"TR.TotalEquity","Curn=#1",,$C$1)/1000000)} -> #VALUE! | K10: =IF($B10="","",_xll.RDP.Data($B10,"TR.BetaFiveYear/*Beta 5 Year Monthly*//*Beta 5 Year Monthly*/")) -> Please sign in | L10: =IF(B10="","",_xll.RDP.Data($B10,"TR.PriceTargetMean","Curn=#1",,$C$1)) -> Please sign in
A12: I/B/E/S ESTIMATES
C13: SALES | G13: EPS | K13: EBIT | N13: EBITDA | Q13: EPS 5-yr
A14: Company Name | B14: Ticker | C14: Last FY | D14: FYR1 | E14: FYR2 | F14: FYR3 | G14: Last FY | H14: FYR1 | I14: FYR2 | J14: FYR3 | K14: Last FY | L14: FYR1 | M14: FYR2 | N14: Last FY | O14: FYR1 | P14: FYR2 | Q14: Growth %
A15: =A6 -> Please sign in | B15: =IF(B6="","",B6) -> RGLD.OQ | C15: {=IF($B15="","",_xll.RDP.Data($B15,"TR.Revenue","Curn=#1",,$C$1)/1000000)} -> #VALUE! | D15: {=IF($B15="","",_xll.RDP.Data($B15,"TR.RevenueMean","Period=FY1 Frq=D SDate=1D Curn=#1",,$C$1)/1000000)} -> #VALUE! | E15: {=IF($B15="","",_xll.RDP.Data($B15,"TR.RevenueMean","Period=FY2 Frq=D SDate=1D Curn=#1",,$C$1)/1000000)} -> #VALUE! | F15: {=IF($B15="","",_xll.RDP.Data($B15,"TR.RevenueMean","Period=FY3 Frq=D SDate=1D Curn=#1",,$C$1)/1000000)} -> #VALUE! | G15: =IF($B15="","",_xll.RDP.Data($B15,"TR.EPSMean","Period=FY0 Frq=D SDate=1D Curn=#1",,$C$1)) -> Please sign in | H15: =IF($B15="","",_xll.RDP.Data($B15,"TR.EPSMean","Period=FY1 Frq=D SDate=1D Curn=#1",,$C$1)) -> Please sign in | I15: =IF($B15="","",_xll.RDP.Data($B15,"TR.EPSMean","Period=FY2 Frq=D SDate=1D Curn=#1",,$C$1)) -> Please sign in | J15: =IF($B15="","",_xll.RDP.Data($B15,"TR.EPSMean","Period=FY3 Frq=D SDate=1D Curn=#1",,$C$1)) -> Please sign in | K15: {=IF($B15="","",_xll.RDP.Data($B15,"TR.EBITMean","Period=FY0 Frq=D SDate=1D Curn=#1",,$C$1)/1000000)} -> #VALUE! | L15: {=IF($B15="","",_xll.RDP.Data($B15,"TR.EBITMean","Period=FY1 Frq=D SDate=1D Curn=#1",,$C$1)/1000000)} -> #VALUE! | M15: {=IF($B15="","",_xll.RDP.Data($B15,"TR.EBITMean","Period=FY2 Frq=D SDate=1D Curn=#1",,$C$1)/1000000)} -> #VALUE! | N15: {=IF($B15="","",_xll.RDP.Data($B15,"TR.EBITDAMean","Period=FY0 Frq=D SDate=1D Curn=#1",,$C$1)/1000000)} -> #VALUE! | O15: {=IF($B15="","",_xll.RDP.Data($B15,"TR.EBITDAMean","Period=FY1 Frq=D SDate=1D Curn=#1",,$C$1)/1000000)} -> #VALUE! | P15: {=IF($B15="","",_xll.RDP.Data($B15,"TR.EBITDAMean","Period=FY2 Frq=D SDate=1D Curn=#1",,$C$1)/1000000)} -> #VALUE! | Q15: {=IF($B15="","",_xll.RDP.Data($B15,"TR.LTGMean",,)/100)} -> #VALUE!
A16: =A7 -> Please sign in | B16: =IF(B7="","",B7) -> GFIJ.J | C16: {=IF($B16="","",_xll.RDP.Data($B16,"TR.Revenue","Curn=#1",,$C$1)/1000000)} -> #VALUE! | D16: {=IF($B16="","",_xll.RDP.Data($B16,"TR.RevenueMean","Period=FY1 Frq=D SDate=1D Curn=#1",,$C$1)/1000000)} -> #VALUE! | E16: {=IF($B16="","",_xll.RDP.Data($B16,"TR.RevenueMean","Period=FY2 Frq=D SDate=1D Curn=#1",,$C$1)/1000000)} -> #VALUE! | F16: {=IF($B16="","",_xll.RDP.Data($B16,"TR.RevenueMean","Period=FY3 Frq=D SDate=1D Curn=#1",,$C$1)/1000000)} -> #VALUE! | G16: =IF($B16="","",_xll.RDP.Data($B16,"TR.EPSMean","Period=FY0 Frq=D SDate=1D Curn=#1",,$C$1)) -> Please sign in | H16: =IF($B16="","",_xll.RDP.Data($B16,"TR.EPSMean","Period=FY1 Frq=D SDate=1D Curn=#1",,$C$1)) -> Please sign in | I16: =IF($B16="","",_xll.RDP.Data($B16,"TR.EPSMean","Period=FY2 Frq=D SDate=1D Curn=#1",,$C$1)) -> Please sign in | J16: =IF($B16="","",_xll.RDP.Data($B16,"TR.EPSMean","Period=FY3 Frq=D SDate=1D Curn=#1",,$C$1)) -> Please sign in | K16: {=IF($B16="","",_xll.RDP.Data($B16,"TR.EBITMean","Period=FY0 Frq=D SDate=1D Curn=#1",,$C$1)/1000000)} -> #VALUE! | L16: {=IF($B16="","",_xll.RDP.Data($B16,"TR.EBITMean","Period=FY1 Frq=D SDate=1D Curn=#1",,$C$1)/1000000)} -> #VALUE! | M16: {=IF($B16="","",_xll.RDP.Data($B16,"TR.EBITMean","Period=FY2 Frq=D SDate=1D Curn=#1",,$C$1)/1000000)} -> #VALUE! | N16: {=IF($B16="","",_xll.RDP.Data($B16,"TR.EBITDAMean","Period=FY0 Frq=D SDate=1D Curn=#1",,$C$1)/1000000)} -> #VALUE! | O16: {=IF($B16="","",_xll.RDP.Data($B16,"TR.EBITDAMean","Period=FY1 Frq=D SDate=1D Curn=#1",,$C$1)/1000000)} -> #VALUE! | P16: {=IF($B16="","",_xll.RDP.Data($B16,"TR.EBITDAMean","Period=FY2 Frq=D SDate=1D Curn=#1",,$C$1)/1000000)} -> #VALUE! | Q16: {=IF($B16="","",_xll.RDP.Data($B16,"TR.LTGMean",,)/100)} -> #VALUE!
A17: =A8 -> Please sign in | B17: =IF(B8="","",B8) -> AEM.N | C17: {=IF($B17="","",_xll.RDP.Data($B17,"TR.Revenue","Curn=#1",,$C$1)/1000000)} -> #VALUE! | D17: {=IF($B17="","",_xll.RDP.Data($B17,"TR.RevenueMean","Period=FY1 Frq=D SDate=1D Curn=#1",,$C$1)/1000000)} -> #VALUE! | E17: {=IF($B17="","",_xll.RDP.Data($B17,"TR.RevenueMean","Period=FY2 Frq=D SDate=1D Curn=#1",,$C$1)/1000000)} -> #VALUE! | F17: {=IF($B17="","",_xll.RDP.Data($B17,"TR.RevenueMean","Period=FY3 Frq=D SDate=1D Curn=#1",,$C$1)/1000000)} -> #VALUE! | G17: =IF($B17="","",_xll.RDP.Data($B17,"TR.EPSMean","Period=FY0 Frq=D SDate=1D Curn=#1",,$C$1)) -> Please sign in | H17: =IF($B17="","",_xll.RDP.Data($B17,"TR.EPSMean","Period=FY1 Frq=D SDate=1D Curn=#1",,$C$1)) -> Please sign in | I17: =IF($B17="","",_xll.RDP.Data($B17,"TR.EPSMean","Period=FY2 Frq=D SDate=1D Curn=#1",,$C$1)) -> Please sign in | J17: =IF($B17="","",_xll.RDP.Data($B17,"TR.EPSMean","Period=FY3 Frq=D SDate=1D Curn=#1",,$C$1)) -> Please sign in | K17: {=IF($B17="","",_xll.RDP.Data($B17,"TR.EBITMean","Period=FY0 Frq=D SDate=1D Curn=#1",,$C$1)/1000000)} -> #VALUE! | L17: {=IF($B17="","",_xll.RDP.Data($B17,"TR.EBITMean","Period=FY1 Frq=D SDate=1D Curn=#1",,$C$1)/1000000)} -> #VALUE! | M17: {=IF($B17="","",_xll.RDP.Data($B17,"TR.EBITMean","Period=FY2 Frq=D SDate=1D Curn=#1",,$C$1)/1000000)} -> #VALUE! | N17: {=IF($B17="","",_xll.RDP.Data($B17,"TR.EBITDAMean","Period=FY0 Frq=D SDate=1D Curn=#1",,$C$1)/1000000)} -> #VALUE! | O17: {=IF($B17="","",_xll.RDP.Data($B17,"TR.EBITDAMean","Period=FY1 Frq=D SDate=1D Curn=#1",,$C$1)/1000000)} -> #VALUE! | P17: {=IF($B17="","",_xll.RDP.Data($B17,"TR.EBITDAMean","Period=FY2 Frq=D SDate=1D Curn=#1",,$C$1)/1000000)} -> #VALUE! | Q17: {=IF($B17="","",_xll.RDP.Data($B17,"TR.LTGMean",,)/100)} -> #VALUE! | R17: Not available
A18: =A9 -> Please sign in | B18: =IF(B9="","",B9) -> ABX.TO | C18: {=IF($B18="","",_xll.RDP.Data($B18,"TR.Revenue","Curn=#1",,$C$1)/1000000)} -> #VALUE! | D18: {=IF($B18="","",_xll.RDP.Data($B18,"TR.RevenueMean","Period=FY1 Frq=D SDate=1D Curn=#1",,$C$1)/1000000)} -> #VALUE! | E18: {=IF($B18="","",_xll.RDP.Data($B18,"TR.RevenueMean","Period=FY2 Frq=D SDate=1D Curn=#1",,$C$1)/1000000)} -> #VALUE! | F18: {=IF($B18="","",_xll.RDP.Data($B18,"TR.RevenueMean","Period=FY3 Frq=D SDate=1D Curn=#1",,$C$1)/1000000)} -> #VALUE! | G18: =IF($B18="","",_xll.RDP.Data($B18,"TR.EPSMean","Period=FY0 Frq=D SDate=1D Curn=#1",,$C$1)) -> Please sign in | H18: =IF($B18="","",_xll.RDP.Data($B18,"TR.EPSMean","Period=FY1 Frq=D SDate=1D Curn=#1",,$C$1)) -> Please sign in | I18: =IF($B18="","",_xll.RDP.Data($B18,"TR.EPSMean","Period=FY2 Frq=D SDate=1D Curn=#1",,$C$1)) -> Please sign in | J18: =IF($B18="","",_xll.RDP.Data($B18,"TR.EPSMean","Period=FY3 Frq=D SDate=1D Curn=#1",,$C$1)) -> Please sign in | K18: {=IF($B18="","",_xll.RDP.Data($B18,"TR.EBITMean","Period=FY0 Frq=D SDate=1D Curn=#1",,$C$1)/1000000)} -> #VALUE! | L18: {=IF($B18="","",_xll.RDP.Data($B18,"TR.EBITMean","Period=FY1 Frq=D SDate=1D Curn=#1",,$C$1)/1000000)} -> #VALUE! | M18: {=IF($B18="","",_xll.RDP.Data($B18,"TR.EBITMean","Period=FY2 Frq=D SDate=1D Curn=#1",,$C$1)/1000000)} -> #VALUE! | N18: {=IF($B18="","",_xll.RDP.Data($B18,"TR.EBITDAMean","Period=FY0 Frq=D SDate=1D Curn=#1",,$C$1)/1000000)} -> #VALUE! | O18: {=IF($B18="","",_xll.RDP.Data($B18,"TR.EBITDAMean","Period=FY1 Frq=D SDate=1D Curn=#1",,$C$1)/1000000)} -> #VALUE! | P18: {=IF($B18="","",_xll.RDP.Data($B18,"TR.EBITDAMean","Period=FY2 Frq=D SDate=1D Curn=#1",,$C$1)/1000000)} -> #VALUE! | Q18: {=IF($B18="","",_xll.RDP.Data($B18,"TR.LTGMean",,)/100)} -> #VALUE! | R18: Not available
A19: =A10 -> Please sign in | B19: =IF(B10="","",B10) -> NEM | C19: {=IF($B19="","",_xll.RDP.Data($B19,"TR.Revenue","Curn=#1",,$C$1)/1000000)} -> #VALUE! | D19: {=IF($B19="","",_xll.RDP.Data($B19,"TR.RevenueMean","Period=FY1 Frq=D SDate=1D Curn=#1",,$C$1)/1000000)} -> #VALUE! | E19: {=IF($B19="","",_xll.RDP.Data($B19,"TR.RevenueMean","Period=FY2 Frq=D SDate=1D Curn=#1",,$C$1)/1000000)} -> #VALUE! | F19: {=IF($B19="","",_xll.RDP.Data($B19,"TR.RevenueMean","Period=FY3 Frq=D SDate=1D Curn=#1",,$C$1)/1000000)} -> #VALUE! | G19: =IF($B19="","",_xll.RDP.Data($B19,"TR.EPSMean","Period=FY0 Frq=D SDate=1D Curn=#1",,$C$1)) -> Please sign in | H19: =IF($B19="","",_xll.RDP.Data($B19,"TR.EPSMean","Period=FY1 Frq=D SDate=1D Curn=#1",,$C$1)) -> Please sign in | I19: =IF($B19="","",_xll.RDP.Data($B19,"TR.EPSMean","Period=FY2 Frq=D SDate=1D Curn=#1",,$C$1)) -> Please sign in | J19: =IF($B19="","",_xll.RDP.Data($B19,"TR.EPSMean","Period=FY3 Frq=D SDate=1D Curn=#1",,$C$1)) -> Please sign in | K19: {=IF($B19="","",_xll.RDP.Data($B19,"TR.EBITMean","Period=FY0 Frq=D SDate=1D Curn=#1",,$C$1)/1000000)} -> #VALUE! | L19: {=IF($B19="","",_xll.RDP.Data($B19,"TR.EBITMean","Period=FY1 Frq=D SDate=1D Curn=#1",,$C$1)/1000000)} -> #VALUE! | M19: {=IF($B19="","",_xll.RDP.Data($B19,"TR.EBITMean","Period=FY2 Frq=D SDate=1D Curn=#1",,$C$1)/1000000)} -> #VALUE! | N19: {=IF($B19="","",_xll.RDP.Data($B19,"TR.EBITDAMean","Period=FY0 Frq=D SDate=1D Curn=#1",,$C$1)/1000000)} -> #VALUE! | O19: {=IF($B19="","",_xll.RDP.Data($B19,"TR.EBITDAMean","Period=FY1 Frq=D SDate=1D Curn=#1",,$C$1)/1000000)} -> #VALUE! | P19: {=IF($B19="","",_xll.RDP.Data($B19,"TR.EBITDAMean","Period=FY2 Frq=D SDate=1D Curn=#1",,$C$1)/1000000)} -> #VALUE! | Q19: {=IF($B19="","",_xll.RDP.Data($B19,"TR.LTGMean",,)/100)} -> #VALUE!
A21: VALUATION MULTIPLES
C22: Recent | D22: Price / | E22: Price/Sales | H22: P/E | K22: PEG | N22: EV/EBITDA
A23: Company Name | B23: Ticker | C23: Price | D23: Book | E23: FYR1 | F23: FYR2 | G23: FYR3 | H23: FYR1 | I23: FYR2 | J23: FYR3 | K23: FYR1 | L23: FYR2 | M23: FYR3 | N23: Last FY | O23: FYR1 | P23: FYR2
A24: =A6 -> Please sign in | B24: =IF(B6="","",B6) -> RGLD.OQ | C24: =IF(C6="","",C6) -> Please sign in | D24: =IF(OR(B24="",ISNUMBER(F6)=FALSE,ISNUMBER(J6)=FALSE),"",F6/J6) | E24: =IF(OR($B24="",ISNUMBER($F6)=FALSE,ISNUMBER(D15)=FALSE),"",$F6/D15) | F24: =IF(OR($B24="",ISNUMBER($F6)=FALSE,ISNUMBER(E15)=FALSE),"",$F6/E15) | G24: =IF(OR($B24="",ISNUMBER($F6)=FALSE,ISNUMBER(F15)=FALSE),"",$F6/F15) | H24: =IF(OR($B24="",ISNA(H15)=TRUE),"",$C6/H15) -> #VALUE! | I24: =IF(OR($B24="",ISNA(I15)=TRUE),"",$C6/I15) -> #VALUE! | J24: =IF(OR($B24="",ISNA(J15)=TRUE),"",$C6/J15) -> #VALUE! | K24: =IF(OR($B24="",H24="",ISNA($Q15)=TRUE),"",H24/$Q15/100) -> #VALUE! | L24: =IF(OR($B24="",I24="",ISNA($Q15)=TRUE),"",I24/$Q15/100) -> #VALUE! | M24: =IF(OR($B24="",J24="",ISNA($Q15)=TRUE),"",J24/$Q15/100) -> #VALUE! | N24: =IF(OR($B24="",ISNA($I6)=TRUE,ISNA(N15)=TRUE),"",$I6/N15) -> #VALUE! | O24: =IF(OR($B24="",ISNA($I6)=TRUE,ISNA(O15)=TRUE),"",$I6/O15) -> #VALUE! | P24: =IF(OR($B24="",ISNA($I6)=TRUE,ISNA(P15)=TRUE),"",$I6/P15) -> #VALUE!
A25: =A7 -> Please sign in | B25: =IF(B7="","",B7) -> GFIJ.J | C25: =IF(C7="","",C7) -> Please sign in | D25: =IF(OR(B25="",ISNUMBER(F7)=FALSE,ISNUMBER(J7)=FALSE),"",F7/J7) | E25: =IF(OR($B25="",ISNUMBER($F7)=FALSE,ISNUMBER(D16)=FALSE),"",$F7/D16) | F25: =IF(OR($B25="",ISNUMBER($F7)=FALSE,ISNUMBER(E16)=FALSE),"",$F7/E16) | G25: =IF(OR($B25="",ISNUMBER($F7)=FALSE,ISNUMBER(F16)=FALSE),"",$F7/F16) | H25: =IF(OR($B25="",ISNA(H16)=TRUE),"",$C7/H16) -> #VALUE! | I25: =IF(OR($B25="",ISNA(I16)=TRUE),"",$C7/I16) -> #VALUE! | J25: =IF(OR($B25="",ISNA(J16)=TRUE),"",$C7/J16) -> #VALUE! | K25: =IF(OR($B25="",H25="",ISNA($Q16)=TRUE),"",H25/$Q16/100) -> #VALUE! | L25: =IF(OR($B25="",I25="",ISNA($Q16)=TRUE),"",I25/$Q16/100) -> #VALUE! | M25: =IF(OR($B25="",J25="",ISNA($Q16)=TRUE),"",J25/$Q16/100) -> #VALUE! | N25: =IF(OR($B25="",ISNA($I7)=TRUE,ISNA(N16)=TRUE),"",$I7/N16) -> #VALUE! | O25: =IF(OR($B25="",ISNA($I7)=TRUE,ISNA(O16)=TRUE),"",$I7/O16) -> #VALUE! | P25: =IF(OR($B25="",ISNA($I7)=TRUE,ISNA(P16)=TRUE),"",$I7/P16) -> #VALUE!
A26: =A8 -> Please sign in | B26: =IF(B8="","",B8) -> AEM.N | C26: =IF(C8="","",C8) -> Please sign in | D26: =IF(OR(B26="",ISNUMBER(F8)=FALSE,ISNUMBER(J8)=FALSE),"",F8/J8) | E26: =IF(OR($B26="",ISNUMBER($F8)=FALSE,ISNUMBER(D17)=FALSE),"",$F8/D17) | F26: =IF(OR($B26="",ISNUMBER($F8)=FALSE,ISNUMBER(E17)=FALSE),"",$F8/E17) | G26: =IF(OR($B26="",ISNUMBER($F8)=FALSE,ISNUMBER(F17)=FALSE),"",$F8/F17) | H26: =IF(OR($B26="",ISNA(H17)=TRUE),"",$C8/H17) -> #VALUE! | I26: =IF(OR($B26="",ISNA(I17)=TRUE),"",$C8/I17) -> #VALUE! | J26: =IF(OR($B26="",ISNA(J17)=TRUE),"",$C8/J17) -> #VALUE! | K26: =IF(OR($B26="",H26="",ISNA($Q17)=TRUE),"",H26/$Q17/100) -> #VALUE! | L26: =IF(OR($B26="",I26="",ISNA($Q17)=TRUE),"",I26/$Q17/100) -> #VALUE! | M26: =IF(OR($B26="",J26="",ISNA($Q17)=TRUE),"",J26/$Q17/100) -> #VALUE! | N26: =IF(OR($B26="",ISNA($I8)=TRUE,ISNA(N17)=TRUE),"",$I8/N17) -> #VALUE! | O26: =IF(OR($B26="",ISNA($I8)=TRUE,ISNA(O17)=TRUE),"",$I8/O17) -> #VALUE! | P26: =IF(OR($B26="",ISNA($I8)=TRUE,ISNA(P17)=TRUE),"",$I8/P17) -> #VALUE!
A27: =A9 -> Please sign in | B27: =IF(B9="","",B9) -> ABX.TO | C27: =IF(C9="","",C9) -> Please sign in | D27: =IF(OR(B27="",ISNUMBER(F9)=FALSE,ISNUMBER(J9)=FALSE),"",F9/J9) | E27: =IF(OR($B27="",ISNUMBER($F9)=FALSE,ISNUMBER(D18)=FALSE),"",$F9/D18) | F27: =IF(OR($B27="",ISNUMBER($F9)=FALSE,ISNUMBER(E18)=FALSE),"",$F9/E18) | G27: =IF(OR($B27="",ISNUMBER($F9)=FALSE,ISNUMBER(F18)=FALSE),"",$F9/F18) | H27: =IF(OR($B27="",ISNA(H18)=TRUE),"",$C9/H18) -> #VALUE! | I27: =IF(OR($B27="",ISNA(I18)=TRUE),"",$C9/I18) -> #VALUE! | J27: =IF(OR($B27="",ISNA(J18)=TRUE),"",$C9/J18) -> #VALUE! | K27: =IF(OR($B27="",H27="",ISNA($Q18)=TRUE),"",H27/$Q18/100) -> #VALUE! | L27: =IF(OR($B27="",I27="",ISNA($Q18)=TRUE),"",I27/$Q18/100) -> #VALUE! | M27: =IF(OR($B27="",J27="",ISNA($Q18)=TRUE),"",J27/$Q18/100) -> #VALUE! | N27: =IF(OR($B27="",ISNA($I9)=TRUE,ISNA(N18)=TRUE),"",$I9/N18) -> #VALUE! | O27: =IF(OR($B27="",ISNA($I9)=TRUE,ISNA(O18)=TRUE),"",$I9/O18) -> #VALUE! | P27: =IF(OR($B27="",ISNA($I9)=TRUE,ISNA(P18)=TRUE),"",$I9/P18) -> #VALUE!
A28: =A10 -> Please sign in | B28: =IF(B10="","",B10) -> NEM | C28: =IF(C10="","",C10) -> Please sign in | D28: =IF(OR(B28="",ISNUMBER(F10)=FALSE,ISNUMBER(J10)=FALSE),"",F10/J10) | E28: =IF(OR($B28="",ISNUMBER($F10)=FALSE,ISNUMBER(D19)=FALSE),"",$F10/D19) | F28: =IF(OR($B28="",ISNUMBER($F10)=FALSE,ISNUMBER(E19)=FALSE),"",$F10/E19) | G28: =IF(OR($B28="",ISNUMBER($F10)=FALSE,ISNUMBER(F19)=FALSE),"",$F10/F19) | H28: =IF(OR($B28="",ISNA(H19)=TRUE),"",$C10/H19) -> #VALUE! | I28: =IF(OR($B28="",ISNA(I19)=TRUE),"",$C10/I19) -> #VALUE! | J28: =IF(OR($B28="",ISNA(J19)=TRUE),"",$C10/J19) -> #VALUE! | K28: =IF(OR($B28="",H28="",ISNA($Q19)=TRUE),"",H28/$Q19/100) -> #VALUE! | L28: =IF(OR($B28="",I28="",ISNA($Q19)=TRUE),"",I28/$Q19/100) -> #VALUE! | M28: =IF(OR($B28="",J28="",ISNA($Q19)=TRUE),"",J28/$Q19/100) -> #VALUE! | N28: =IF(OR($B28="",ISNA($I10)=TRUE,ISNA(N19)=TRUE),"",$I10/N19) -> #VALUE! | O28: =IF(OR($B28="",ISNA($I10)=TRUE,ISNA(O19)=TRUE),"",$I10/O19) -> #VALUE! | P28: =IF(OR($B28="",ISNA($I10)=TRUE,ISNA(P19)=TRUE),"",$I10/P19) -> #VALUE!
C30: Average | D30: =AVERAGE(D24:D27) -> #DIV/0! | E30: =AVERAGE(E24:E27) -> #DIV/0! | F30: =AVERAGE(F24:F27) -> #DIV/0! | G30: =AVERAGE(G24:G27) -> #DIV/0! | H30: =AVERAGE(H24:H27) -> #VALUE! | I30: =AVERAGE(I24:I27) -> #VALUE! | J30: =AVERAGE(J24:J27) -> #VALUE! | K30: =AVERAGE(K24,K26:K26) -> #VALUE! | L30: =AVERAGE(L24,L26:L26) -> #VALUE! | M30: =AVERAGE(M24,M26:M26) -> #VALUE! | N30: =AVERAGE(N24:N27) -> #VALUE! | O30: =AVERAGE(O24:O27) -> #VALUE! | P30: =AVERAGE(P24:P27) -> #VALUE!
C31: Median | D31: =MEDIAN(D24:D27) -> #NUM! | E31: =MEDIAN(E24:E27) -> #NUM! | F31: =MEDIAN(F24:F27) -> #NUM! | G31: =MEDIAN(G24:G27) -> #NUM! | H31: =MEDIAN(H24:H27) -> #VALUE! | I31: =MEDIAN(I24:I27) -> #VALUE! | J31: =MEDIAN(J24:J27) -> #VALUE! | K31: =MEDIAN(K24,K26:K26) -> #VALUE! | L31: =MEDIAN(L24,L26:L26) -> #VALUE! | M31: =MEDIAN(M24,M26:M26) -> #VALUE! | N31: =MEDIAN(N24:N27) -> #VALUE! | O31: =MEDIAN(O24:O27) -> #VALUE! | P31: =MEDIAN(P24:P27) -> #VALUE!
C33: Average | D33: =D30*$J$10/$E$10 -> #DIV/0! | E33: =(E30*D$19)/$E$10 -> #DIV/0! | F33: =(F30*E$19)/$E$10 -> #DIV/0! | G33: =(G30*F$19)/$E$10 -> #DIV/0! | H33: =H30*H$19 -> #VALUE! | I33: =I30*I$19 -> #VALUE! | J33: =J30*J$19 -> #VALUE! | K33: =K30*H$19*$Q$19*100 -> #VALUE! | L33: =L30*I$19*$Q$19*100 -> #VALUE! | M33: =M30*J$19*$Q$19*100 -> #VALUE! | N33: =(N30*N$19-($G$10-$H$10))/$E$10 -> #VALUE! | O33: =(O30*O$19-($G$10-$H$10))/$E$10 -> #VALUE! | P33: =(P30*P$19-($G$10-$H$10))/$E$10 -> #VALUE!
C34: Median | D34: =D31*$J$10/$E$10 -> #NUM! | E34: =(E31*D$19)/$E$10 -> #NUM! | F34: =(F31*E$19)/$E$10 -> #NUM! | G34: =(G31*F$19)/$E$10 -> #NUM! | H34: =H31*H$19 -> #VALUE! | I34: =I31*I$19 -> #VALUE! | J34: =J31*J$19 -> #VALUE! | K34: =K31*H$19*$Q$19*100 -> #VALUE! | L34: =L31*I$19*$Q$19*100 -> #VALUE! | M34: =M31*J$19*$Q$19*100 -> #VALUE! | N34: =(N31*N$19-($G$10-$H$10))/$E$10 -> #VALUE! | O34: =(O31*O$19-($G$10-$H$10))/$E$10 -> #VALUE! | P34: =(P31*P$19-($G$10-$H$10))/$E$10 -> #VALUE!
D35: ws.OperatingProfitMargin[ws.cpa] | H35: ws.AssetTurnover[ws.cpa] | I35: ws.InventoryTurnover[ws.cpa] | J35: ws.ReceivablesTurnover[ws.cpa] | K35: ws.TotalDebtPctCommonEquity[ws.cpa] | L35: ws.LTDebtPctCommonEquity[ws.cpa] | M35: ws.LTDebtPctTotalCapital[ws.cpa] | N35: ws.QuickRatio[ws.cpa] | O35: ws.CurrentRatio[ws.cpa]
A36: RATIO ANALYSIS
C37: Gross | D37: Operating | E37: Net | H37: Asset | I37: Inventory | J37: Receivables | M37: Quick | N37: Current | O37: Interest
A38: Company Name | B38: Ticker | C38: Margin | D38: Margin | E38: Margin | F38: ROA | G38: ROE | H38: Turnvover | I38: Turnvover | J38: Turnvover | K38: Debt/E | L38: LTD/TC | M38: Ratio | N38: Ratio | O38: Coverage
A39: =A6 -> Please sign in | B39: =IF(B15="","",B24) -> RGLD.OQ | C39: {=IF($B39="","",_xll.RDP.Data($B39,"TR.GrossMargin")/100)} -> #VALUE! | D39: {=IF($B39="","",_xll.RDP.Data($B39,"TR.OperatingMarginPercent")/100)} -> #VALUE! | E39: {=IF($B39="","",_xll.RDP.Data($B39,"TR.NetProfitMargin")/100)} -> #VALUE! | F39: {=IF($B39="","",_xll.RDP.Data($B39,"TR.ROAActValue")/100)} -> #VALUE! | G39: {=IF($B39="","",_xll.RDP.Data($B39,"TR.ROEActValue")/100)} -> #VALUE! | H39: =IF($B39="","",_xll.RDP.Data($B39,"TR.AssetTurnover")) -> Please sign in | I39: =IF($B39="","",_xll.RDP.Data($B39,"TR.InventoryTurnover")) -> Please sign in | J39: {=IF($B39="","",_xll.RDP.Data($B39,"TR.Revenue")/_xll.RDP.Data($B39,"TR.TotalReceivablesNet"))} -> #VALUE! | K39: =IF($B39="","",_xll.RDP.Data($B39,"TR.TtlDebtToTtlEquityPct")) -> Please sign in | L39: =IF($B39="","",_xll.RDP.Data($B39,"TR.LTDebtToTtlCapitalPct")) -> Please sign in | M39: =IF($B39="","",_xll.RDP.Data($B39,"TR.QuickRatio")) -> Please sign in | N39: =IF($B39="","",_xll.RDP.Data($B39,"TR.CurrentRatio")) -> Please sign in | O39: {=IF($B39="","",_xll.RDP.Data($B39,"TR.EBITDA")/_xll.RDP.Data($B39,"TR.InterestExpense"))} -> #VALUE!
A40: =A7 -> Please sign in | B40: =IF(B16="","",B25) -> GFIJ.J | C40: {=IF($B40="","",_xll.RDP.Data($B40,"TR.GrossMargin")/100)} -> #VALUE! | D40: {=IF($B40="","",_xll.RDP.Data($B40,"TR.OperatingMarginPercent")/100)} -> #VALUE! | E40: {=IF($B40="","",_xll.RDP.Data($B40,"TR.NetProfitMargin")/100)} -> #VALUE! | F40: {=IF($B40="","",_xll.RDP.Data($B40,"TR.ROAActValue")/100)} -> #VALUE! | G40: {=IF($B40="","",_xll.RDP.Data($B40,"TR.ROEActValue")/100)} -> #VALUE! | H40: =IF($B40="","",_xll.RDP.Data($B40,"TR.AssetTurnover")) -> Please sign in | I40: =IF($B40="","",_xll.RDP.Data($B40,"TR.InventoryTurnover")) -> Please sign in | J40: {=IF($B40="","",_xll.RDP.Data($B40,"TR.Revenue")/_xll.RDP.Data($B40,"TR.TotalReceivablesNet"))} -> #VALUE! | K40: =IF($B40="","",_xll.RDP.Data($B40,"TR.TtlDebtToTtlEquityPct")) -> Please sign in | L40: =IF($B40="","",_xll.RDP.Data($B40,"TR.LTDebtToTtlCapitalPct")) -> Please sign in | M40: =IF($B40="","",_xll.RDP.Data($B40,"TR.QuickRatio")) -> Please sign in | N40: =IF($B40="","",_xll.RDP.Data($B40,"TR.CurrentRatio")) -> Please sign in | O40: {=IF($B40="","",_xll.RDP.Data($B40,"TR.EBITDA")/_xll.RDP.Data($B40,"TR.InterestExpense"))} -> #VALUE!
A41: =A8 -> Please sign in | B41: =IF(B17="","",B26) -> AEM.N | C41: {=IF($B41="","",_xll.RDP.Data($B41,"TR.GrossMargin")/100)} -> #VALUE! | D41: {=IF($B41="","",_xll.RDP.Data($B41,"TR.OperatingMarginPercent")/100)} -> #VALUE! | E41: {=IF($B41="","",_xll.RDP.Data($B41,"TR.NetProfitMargin")/100)} -> #VALUE! | F41: {=IF($B41="","",_xll.RDP.Data($B41,"TR.ROAActValue")/100)} -> #VALUE! | G41: {=IF($B41="","",_xll.RDP.Data($B41,"TR.ROEActValue")/100)} -> #VALUE! | H41: =IF($B41="","",_xll.RDP.Data($B41,"TR.AssetTurnover")) -> Please sign in | I41: =IF($B41="","",_xll.RDP.Data($B41,"TR.InventoryTurnover")) -> Please sign in | J41: {=IF($B41="","",_xll.RDP.Data($B41,"TR.Revenue")/_xll.RDP.Data($B41,"TR.TotalReceivablesNet"))} -> #VALUE! | K41: =IF($B41="","",_xll.RDP.Data($B41,"TR.TtlDebtToTtlEquityPct")) -> Please sign in | L41: =IF($B41="","",_xll.RDP.Data($B41,"TR.LTDebtToTtlCapitalPct")) -> Please sign in | M41: =IF($B41="","",_xll.RDP.Data($B41,"TR.QuickRatio")) -> Please sign in | N41: =IF($B41="","",_xll.RDP.Data($B41,"TR.CurrentRatio")) -> Please sign in | O41: {=IF($B41="","",_xll.RDP.Data($B41,"TR.EBITDA")/_xll.RDP.Data($B41,"TR.InterestExpense"))} -> #VALUE!
A42: =A9 -> Please sign in | B42: =IF(B18="","",B27) -> ABX.TO | C42: {=IF($B42="","",_xll.RDP.Data($B42,"TR.GrossMargin")/100)} -> #VALUE! | D42: {=IF($B42="","",_xll.RDP.Data($B42,"TR.OperatingMarginPercent")/100)} -> #VALUE! | E42: {=IF($B42="","",_xll.RDP.Data($B42,"TR.NetProfitMargin")/100)} -> #VALUE! | F42: {=IF($B42="","",_xll.RDP.Data($B42,"TR.ROAActValue")/100)} -> #VALUE! | G42: {=IF($B42="","",_xll.RDP.Data($B42,"TR.ROEActValue")/100)} -> #VALUE! | H42: =IF($B42="","",_xll.RDP.Data($B42,"TR.AssetTurnover")) -> Please sign in | I42: =IF($B42="","",_xll.RDP.Data($B42,"TR.InventoryTurnover")) -> Please sign in | J42: {=IF($B42="","",_xll.RDP.Data($B42,"TR.Revenue")/_xll.RDP.Data($B42,"TR.TotalReceivablesNet"))} -> #VALUE! | K42: =IF($B42="","",_xll.RDP.Data($B42,"TR.TtlDebtToTtlEquityPct")) -> Please sign in | L42: =IF($B42="","",_xll.RDP.Data($B42,"TR.LTDebtToTtlCapitalPct")) -> Please sign in | M42: =IF($B42="","",_xll.RDP.Data($B42,"TR.QuickRatio")) -> Please sign in | N42: =IF($B42="","",_xll.RDP.Data($B42,"TR.CurrentRatio")) -> Please sign in | O42: {=IF($B42="","",_xll.RDP.Data($B42,"TR.EBITDA")/_xll.RDP.Data($B42,"TR.InterestExpense"))} -> #VALUE!
A43: =A10 -> Please sign in | B43: =IF(B19="","",B28) -> NEM | C43: {=IF($B43="","",_xll.RDP.Data($B43,"TR.GrossMargin")/100)} -> #VALUE! | D43: {=IF($B43="","",_xll.RDP.Data($B43,"TR.OperatingMarginPercent")/100)} -> #VALUE! | E43: {=IF($B43="","",_xll.RDP.Data($B43,"TR.NetProfitMargin")/100)} -> #VALUE! | F43: {=IF($B43="","",_xll.RDP.Data($B43,"TR.ROAActValue")/100)} -> #VALUE! | G43: {=IF($B43="","",_xll.RDP.Data($B43,"TR.ROEActValue")/100)} -> #VALUE! | H43: =IF($B43="","",_xll.RDP.Data($B43,"TR.AssetTurnover")) -> Please sign in | I43: =IF($B43="","",_xll.RDP.Data($B43,"TR.InventoryTurnover")) -> Please sign in | J43: {=IF($B43="","",_xll.RDP.Data($B43,"TR.Revenue")/_xll.RDP.Data($B43,"TR.TotalReceivablesNet"))} -> #VALUE! | K43: =IF($B43="","",_xll.RDP.Data($B43,"TR.TtlDebtToTtlEquityPct")) -> Please sign in | L43: =IF($B43="","",_xll.RDP.Data($B43,"TR.LTDebtToTtlCapitalPct")) -> Please sign in | M43: =IF($B43="","",_xll.RDP.Data($B43,"TR.QuickRatio")) -> Please sign in | N43: =IF($B43="","",_xll.RDP.Data($B43,"TR.CurrentRatio")) -> Please sign in | O43: {=IF($B43="","",_xll.RDP.Data($B43,"TR.EBITDA")/_xll.RDP.Data($B43,"TR.InterestExpense"))} -> #VALUE!

Sheet Comps no formula
C1: USD
A2: COMPARABLE COMPANY ANALYSIS
A3: COMPANY DATA
A4: (in millions) | C4: Recent | D4: 52 week | E4: Shares | F4: Market | G4: Total | I4: Enterprise | J4: Book | L4: WS 12-mo
A5: Company Name | B5: Ticker | C5: Price | D5: High | E5: Out | F5: Cap | G5: Debt | H5: Cash | I5: Value | J5: Value | K5: Beta | L5: Price Target
A6: Royal Gold Inc | B6: RGLD.OQ | C6: 265.77 | D6: 305.28 | E6: 84.398063 | F6: 22430.473 | G6: 0 | H6: 195.498 | I6: 22234.975 | J6: 3118.957 | K6: 0.50158646 | L6: 293.18182
A7: Gold Fields Ltd | B7: GFIJ.J | C7: 53.995721 | D7: 63.020118 | E7: 895.02425 | F7: 48327.479 | G7: 2945.8 | H7: 860.2 | I7: 50413.079 | J7: 5201.4 | K7: 1.716962 | L7: 54.548737
A8: Agnico Eagle Mines Ltd | B8: AEM.N | C8: 196.6 | D8: 225 | E8: 501.63359 | F8: 98621.163 | G8: 1282.182 | H8: 926.431 | I8: 98976.914 | J8: 20832.9 | K8: 0.64890628 | L8: 231.86952
A9: Barrick Mining Corp | B9: ABX.TO | C9: 45.142189 | D9: 54.859515 | E9: 1687.4339 | F9: 76174.461 | G9: 5211 | H9: 0 | I9: 81385.461 | J9: 26557 | K9: 0.98435743 | L9: 56.528211
A10: Newmont Corporation | B10: NEM | C10: 115.32 | D10: 134.88 | E10: 1091.263 | F10: 125844.45 | G10: 8972 | H10: 3619 | I10: 131197.45 | J10: 29928 | K10: 0.43578128 | L10: 126.91909
A12: I/B/E/S ESTIMATES
C13: SALES | G13: EPS | K13: EBIT | N13: EBITDA | Q13: EPS 5-yr
A14: Company Name | B14: Ticker | C14: Last FY | D14: FYR1 | E14: FYR2 | F14: FYR3 | G14: Last FY | H14: FYR1 | I14: FYR2 | J14: FYR3 | K14: Last FY | L14: FYR1 | M14: FYR2 | N14: Last FY | O14: FYR1 | P14: FYR2 | Q14: Growth %
A15: Royal Gold Inc | B15: RGLD.OQ | C15: 719.395 | D15: 892.49833 | E15: 1526.0543 | F15: 1814.99 | G15: 5.10244 | H15: 7.9547 | I15: 11.5363 | J15: 11.96157 | K15: 416.114 | L15: 669.192 | M15: 1170.736 | N15: 569.54425 | O15: 845.28056 | P15: 1523.7198 | Q15: #VALUE!
A16: Gold Fields Ltd | B16: GFIJ.J | C16: 5201.6 | D16: 8578.2099 | E16: 11599.858 | F16: 11262.915 | G16: 1.2645 | H16: 3.322 | I16: 5.42478 | J16: 5.55513 | K16: 2041.8324 | L16: 4926.1708 | M16: 7401.0891 | N16: 2700.2439 | O16: 5723.4677 | P16: 8212.7808 | Q16: 0.514
A17: Agnico Eagle Mines Ltd | B17: AEM.N | C17: 8285.753 | D17: 11771.385 | E17: 15206.229 | F17: 15048.142 | G17: 4.13421 | H17: 8.15713 | I17: 11.59882 | J17: 11.84029 | K17: 3128.0353 | L17: 6446.1028 | M17: 9536.0613 | N17: 4712.7132 | O17: 7988.2078 | P17: 10997.369 | Q17: #VALUE! | R17: Not available
A18: Barrick Mining Corp | B18: ABX.TO | C18: 16956 | D18: 20670.977 | E18: 22372.735 | F18: 24319.286 | G18: 2.28444 | H18: 3.49338 | I18: 3.99392 | J18: 4.12463 | K18: 8151.375 | L18: 12639.7 | M18: 13849.222 | N18: 9054.4017 | O18: 13100.545 | P18: 14757.348 | Q18: #VALUE! | R18: Not available
A19: Newmont Corporation | B19: NEM | C19: 18682 | D19: 22004.587 | E19: 25480.727 | F19: 26779.156 | G19: 3.14588 | H19: 6.41977 | I19: 8.721 | J19: 9.55527 | K19: 5430.4686 | L19: 10571.938 | M19: 13866.162 | N19: 8151.4989 | O19: 13084.464 | P19: 16813.511 | Q19: 0.3775
A21: VALUATION MULTIPLES
C22: Recent | D22: Price / | E22: Price/Sales | H22: P/E | K22: PEG | N22: EV/EBITDA
A23: Company Name | B23: Ticker | C23: Price | D23: Book | E23: FYR1 | F23: FYR2 | G23: FYR3 | H23: FYR1 | I23: FYR2 | J23: FYR3 | K23: FYR1 | L23: FYR2 | M23: FYR3 | N23: Last FY | O23: FYR1 | P23: FYR2
A24: Royal Gold Inc | B24: RGLD.OQ | C24: 265.77 | D24: 7.1916584 | E24: 25.13223 | F24: 14.698345 | G24: 12.358456 | H24: 33.410437 | I24: 23.037716 | J24: 22.218655 | K24: #VALUE! | L24: #VALUE! | M24: #VALUE! | N24: 39.039943 | O24: 26.304846 | P24: 14.592562
A25: Gold Fields Ltd | B25: GFIJ.J | C25: 53.995721 | D25: 9.2912445 | E25: 5.6337488 | F25: 4.1662132 | G25: 4.29085 | H25: 16.25398 | I25: 9.9535319 | J25: 9.7199743 | K25: 0.31622529 | L25: 0.19364848 | M25: 0.18910456 | N25: 18.669824 | O25: 8.8081356 | P25: 6.138369
A26: Agnico Eagle Mines Ltd | B26: AEM.N | C26: 196.6 | D26: 4.7339143 | E26: 8.3780422 | F26: 6.4855765 | G26: 6.5537105 | H26: 24.101614 | I26: 16.95 | J26: 16.604323 | K26: #VALUE! | L26: #VALUE! | M26: #VALUE! | N26: 21.002108 | O26: 12.390378 | P26: 9.0000543
A27: Barrick Mining Corp | B27: ABX.TO | C27: 45.142189 | D27: 2.8683383 | E27: 3.6850925 | F27: 3.4047898 | G27: 3.1322656 | H27: 12.92221 | I27: 11.302727 | J27: 10.944543 | K27: #VALUE! | L27: #VALUE! | M27: #VALUE! | N27: 8.9884968 | O27: 6.212372 | P27: 5.5149109
A28: Newmont Corporation | B28: NEM | C28: 115.32 | D28: 4.2049067 | E28: 5.7190097 | F28: 4.9388092 | G28: 4.6993433 | H28: 17.96326 | I28: 13.223254 | J28: 12.068733 | K28: 0.47584796 | L28: 0.35028488 | M28: 0.31970153 | N28: 16.094886 | O28: 10.026964 | P28: 7.8030962
C30: Average | D30: 6.0212889 | E30: 10.707278 | F30: 7.1887312 | G30: 6.5838204 | H30: 21.67206 | I30: 15.310994 | J30: 14.871874 | K30: #VALUE! | L30: #VALUE! | M30: #VALUE! | N30: 21.925093 | O30: 13.428933 | P30: 8.811474
C31: Median | D31: 5.9627863 | E31: 7.0058955 | F31: 5.3258948 | G31: 5.4222802 | H31: 20.177797 | I31: 14.126364 | J31: 13.774433 | K31: #VALUE! | L31: #VALUE! | M31: #VALUE! | N31: 19.835966 | O31: 10.599257 | P31: 7.5692117
C33: Average | D33: 165.13447 | E33: 215.90509 | F33: 167.85514 | G33: 161.56431 | H33: 139.12964 | I33: 133.52718 | J33: 142.10477 | K33: #VALUE! | L33: #VALUE! | M33: #VALUE! | N33: 158.87039 | O33: 156.1103 | P33: 130.85647
C34: Median | D34: 163.53003 | E34: 141.26919 | F34: 124.35836 | G34: 133.06058 | H34: 129.53682 | I34: 123.19602 | J34: 131.61842 | K34: #VALUE! | L34: #VALUE! | M34: #VALUE! | N34: 143.26506 | O34: 122.18191 | P34: 111.71645
D35: ws.OperatingProfitMargin[ws.cpa] | H35: ws.AssetTurnover[ws.cpa] | I35: ws.InventoryTurnover[ws.cpa] | J35: ws.ReceivablesTurnover[ws.cpa] | K35: ws.TotalDebtPctCommonEquity[ws.cpa] | L35: ws.LTDebtPctCommonEquity[ws.cpa] | M35: ws.LTDebtPctTotalCapital[ws.cpa] | N35: ws.QuickRatio[ws.cpa] | O35: ws.CurrentRatio[ws.cpa]
A36: RATIO ANALYSIS
C37: Gross | D37: Operating | E37: Net | H37: Asset | I37: Inventory | J37: Receivables | M37: Quick | N37: Current | O37: Interest
A38: Company Name | B38: Ticker | C38: Margin | D38: Margin | E38: Margin | F38: ROA | G38: ROE | H38: Turnvover | I38: Turnvover | J38: Turnvover | K38: Debt/E | L38: LTD/TC | M38: Ratio | N38: Ratio | O38: Coverage
A39: Royal Gold Inc | B39: RGLD.OQ | C39: 0.855245 | D39: 0.5975841 | E39: 0.4615309 | F39: 0.10259 | G39: 0.11529 | H39: 0.21305348 | I39: 9.1503888 | J39: 11.136318 | K39: 0 | L39: 0 | M39: 3.08057 | N39: 3.23293 | O39: 58.91117
A40: Gold Fields Ltd | B40: GFIJ.J | C40: 0.4533028 | D40: 0.4514188 | E40: 0.2393494 | F40: 0.1282 | G40: 0.2398 | H40: 0.56633931 | I40: 3.7240702 | J40: 16.439949 | K40: 56.634752 | L40: 25.741336 | M40: 0.71761 | N40: 1.12646 | O40: 119.412
A41: Agnico Eagle Mines Ltd | B41: AEM.N | C41: 0.6279904 | D41: 0.3801017 | E41: 0.2287759 | F41: 0.0722 | G41: 0.1052 | H41: 0.28244333 | I41: 2.10426 | J41: 43.695237 | K41: 6.1546016 | L41: 5.2085586 | M41: 0.85621 | N41: 1.85539 | O41: 51.672959
A42: Barrick Mining Corp | B42: ABX.TO | C42: 0.5125619 | D42: 0.5326728 | E42: 0.294468 | F42: #VALUE! | G42: #VALUE! | H42: 0.3418445 | I42: 4.1221945 | J42: 15.098842 | K42: 19.621945 | L42: 12.407907 | M42: 2.33028 | N42: 2.92165 | O42: 28.534819
A43: Newmont Corporation | B43: NEM | C43: 0.5202334 | D43: 0.244674 | E43: 0.1755701 | F43: 0.07129 | G43: 0.13529 | H43: 0.3340396 | I43: 3.7144633 | J43: 17.691288 | K43: 29.978615 | L43: 20.319337 | M43: 1.3378 | N43: 1.62734 | O43: 22.512
